Workbook

Sheet 1_README
A1: FOMA CER-COD (Paris) -- T1 Results Workbook: Block A (A1-A8)
A2: Per-run results workbook per Setup par.5/par.7 (SOMA template) -- frontmatter + analysis tabs + Manuscript Inputs
A3: Canonical run 2026-07-13 20:39 CEST | verifier R/01_verify_outputs.R: 21/21 PASS | seed 20260710
A5: Item | B5: Value
A6: Version | B6: v1 (T1 canonical run, 2026-07-13)
A7: Method | B7: Three-level meta-analysis with robust variance estimation (3LMA-RVE) on Fisher-z PCC; CR2/Satterthwaite on cluster_id; see 2_Methodology
A8: Repo | B8: github.com/rwitte-wu-research/FOMA-CER-COD-Paris (main); local C:\R_Projects\FOMA-CER-COD-Paris
A9: Computational stack | B9: R 4.6.1 (ucrt, Win 11) | metafor 5.0-1 | clubSandwich 0.7.0 | ggplot2 4.0.3 | renv consistent
A10: Scripts | B10: R/01_core.R + paired verifier R/01_verify_outputs.R; prompt docs/cc_prompt_T1.md
A11: Decision basis | B11: [DEC-031/031a] battery Block A | [DEC-042/042a] v12 + estimation set | [DEC-042b] period-NA rule | [DEC-012/012a] economic translation | F53-F57 rulings
A13: TAB-INDEX
A14: Tab | B14: Content
A15: 1_README | B15: this tab
A16: 2_Methodology | B16: Quantity | Formula | Reference
A17: 3_Interpretation_Guide | B17: Quantity | Meaning | Decision rule
A18: 4_Formula_Reference | B18: Quantity | R call | Reference
A19: 5_Data_Provenance | B19: Item | Value | Source
A20: 6_A1_Main_Results | B20: headline pooled effect, both scales, interpretation, reviewer Q&A
A21: 7_A2_Heterogeneity | B21: variance decomposition + prediction interval
A22: 8_A3_Periods_PI | B22: pre/post-Paris subsets, PIs (descriptive; test = B1)
A23: 9_A4_A5_Sensitivity | B23: rho grid + estimator robustness vs headline (Delta, %Delta, CI overlap) + verdict
A24: 10_A6_Economic_Translation | B24: bp translation (PENDING DEC-012a) + Doucouliagos ratio
A25: 11_Results_Long | B25: verbatim transport of output/T1_results.csv (15 x 35, full precision)
... A27: 13_Manuscript_Text_Blocks | B27: copy-paste-ready English prose blocks (READY / BLOCKED / DRAFT status; framing-neutral until Ablauf 3b)

Sheet 2_Methodology
A1: Methodology -- estimators and constructions used in Block A
A2: All conventions fixed a priori; source pointers per project notation
A5: Quantity | B5: Formula / Construction | C5: Reference
A6: Effect size | B6: z = atanh(r_p); v = 1/(n_eff - 3); n_eff = column-E basis (n_obs, else n_firms x window years) | C6: van Aert (2023); [DEC-042a D31.6]
A7: Headline model | B7: rma.mv(z, V, random = ~1|cluster_id/study/esid, REML) | C7: Pustejovsky & Tipton (2022); van den Noortgate et al. (2013, 2015); [DEC-031 D31.1]
A8: Working covariance V | B8: CHE blocks: impute_covariance_matrix(v, cluster = cluster_id, r = 0.6); grid rho in {0.4, 0.8} | C8: [DEC-017; E1; F56: sample-overlap cluster]
A9: Robust inference | B9: CR2 with Satterthwaite df, clustered on cluster_id (coef_test / conf_int) | C9: Tipton & Pustejovsky (2015); [plan par.5]
A10: Prediction interval | B10: b +/- t(df_Satt) * sqrt(SE_CR2^2 + sigma2_cluster + sigma2_study + omega2_esid) -- ALL three components | C10: [F55; plan Addendum A.8]
A11: Variance shares | B11: pct_i = sigma2_i / (sum sigma2 + v_typ); v_typ = Higgins-Thompson typical sampling variance | C11: Borenstein et al. (2017) I2 machinery
A12: One-effect-per-cluster | B12: aggregate.escalc (CS, rho = 0.6) within cluster_id -> rma REML + Knapp-Hartung, k = 114 | C12: Borenstein et al. (2009); [DEC-031a.4]
A13: UWLS+3 | B13: rp3 = t/sqrt(t^2 + df + 3); var3 = 1/(t^2 + df + 3); df ~= n_eff; WLS; CR2 on cluster_id | C13: Stanley et al. (2024) Eq 2/4/9; [F21; F54]
A14: HS bare-bones | B14: r_bar = sum(n r)/sum(n); SE = SD_w/sqrt(k), k = 2,713 ES (anti-conservative, disclosed) | C14: Stanley et al. (2025) Eq 9-11; Hunter & Schmidt (2004); [F54]
A15: WAAP | B15: adequately powered iff SE_i <= |UWLS+3|/2.8; UWLS on powered subset; <2 powered -> UWLS fallback | C15: Stanley, Doucouliagos & Ioannidis (2017)
A16: Economic translation | B16: Delta COD (bp) per 1-SD CER = tanh(z_pooled) x SD_COD_bp; constants = instrument-level medians (loan/bond/CDS) | C16: [DEC-012; DEC-012a -- constants PENDING]
A17: Period cells | B17: pp_mid_lag0 (mid >= 2015.5); 8 ES / 2 studies window-undefined drop listwise from period cells only | C17: [Addendum A.3; DEC-042b]

Sheet 3_Interpretation_Guide
A1: Interpretation guide -- how to read each quantity
A5: Quantity | B5: Meaning | C5: Decision rule
A6: est_r | B6: Pooled partial correlation CER -> COD (negative = CER associated with lower COD) | C6: |r| < 0.07 = below the field's 'small' benchmark (Doucouliagos 2011)
A7: 95% CI | B7: Precision of the MEAN effect | C7: Excludes 0 -> nonzero average association
A8: 95% PI | B8: Plausible range of a SINGLE new effect (all heterogeneity levels) | C8: Sign-inclusive -> heterogeneity dominates; report PI alongside mean (N4)
A9: df (Satterthwaite) | B9: Effective number of independent clusters behind the estimate | C9: df < 4 -> CI unreliable (Tipton); F57: disclose, rely on point estimate
A10: Variance shares | B10: Where heterogeneity lives (cluster / study / ES / sampling) | C10: Large ES-level share -> within-study moderators matter (Blocks C/E)
A11: Delta / %Delta vs headline | B11: Estimator sensitivity of the pooled mean | C11: Same sign + CI overlap -> robust; magnitude shifts -> explain mechanism
A12: CI overlap | B12: Spec CI intersects headline CI (z scale) | C12: 'yes' across all specs -> no estimator drives the conclusion
A13: PENDING DEC-012a | B13: bp values rest on placeholder SD constants | C13: Do NOT quote bp in the manuscript until DEC-012a constants land

Sheet 4_Formula_Reference
A1: Formula reference -- exact R calls (see R/01_core.R)
A5: Quantity | B5: R call | C5: Reference / section
A6: Headline fit | B6: metafor::rma.mv(yi, V, random = ~1|cluster/study/esid, sparse = TRUE, method = 'REML') | C6: R/01_core.R par.4 (fit_3lma)
A7: V blocks | B7: clubSandwich::impute_covariance_matrix(vi, cluster = cluster_id, r = rho) | C7: R/01_core.R (fit_3lma); F56 comment
A8: CR2 inference | B8: clubSandwich::coef_test(m, vcov='CR2', cluster, test='Satterthwaite'); conf_int(...) | C8: R/01_core.R (rob_stats)
A9: Prediction interval | B9: qt(.975, df_Satt) * sqrt(SE_CR2^2 + sum(sigma2)) | C9: R/01_core.R (pi_bounds); F55
A10: Typical v | B10: (k-1) * sum(w) / (sum(w)^2 - sum(w^2)), w = 1/vi | C10: R/01_core.R (typical_v)
A11: Cluster aggregation | B11: metafor::escalc(measure='GEN') -> aggregate(esc, cluster, rho = 0.6) | C11: R/01_core.R (agg_rho)
A12: One-per-cluster RE | B12: metafor::rma(yi, vi, method='REML', test='knha') | C12: R/01_core.R par.8a
A13: UWLS+3 | B13: lm(rp3 ~ 1, weights = 1/var3); clubSandwich::coef_test(fit, 'CR2', cluster) | C13: R/01_core.R par.8b; Stanley et al. 2024
A14: HS | B14: sum(n*r)/sum(n); sqrt(sum(n*(r-rbar)^2)/sum(n)/k) | C14: R/01_core.R par.8c
A15: WAAP subset | B15: powered <- sqrt(var3) <= abs(uwls3)/2.8; lm on subset + CR2 | C15: R/01_core.R par.8d
A16: bp translation | B16: tanh(z_pooled) * SD_COD_bp (grid; PENDING DEC-012a) | C16: R/01_core.R par.9

Sheet 5_Data_Provenance
A1: Data provenance -- run and input identity
A5: Item | B5: Value | C5: Source
A6: Raw data | B6: data/CER-COD_data_v12.xlsx (canonical, frozen) | C6: [DEC-042; commit 63356a7]
A7: Estimation set | B7: 2,713 ES / 115 studies / 114 clusters | C7: [DEC-042a]
A8: Prep object | B8: output/dat_prep.rds -- list(pr$dat, pr$n = 2713, pr$seed = 20260710) | C8: R/00_prep.R; md5 6702ef3dc45fe0b693b13f50ebd1576b
A9: Period NA | B9: 8 ES / 2 studies (Bhattacharya & Sharma 2019; Ng & Rezaee 2012) -- design fact, listwise out of period cells only | C9: [DEC-042b]
A10: Run | B10: 2026-07-13 20:39:15 CEST, Claude Code canonical (docs/cc_prompt_T1.md) | C10: output/T1_run_meta.txt
A11: Verifier | B11: R/01_verify_outputs.R -- 21/21 PASS; O18: min 3LMA df 27.52; appendix df 2.28 / 2.22 (F57) | C11: CC run report
A12: Results | B12: output/T1_results.csv (15 rows x 35 cols) -- verbatim in 11_Results_Long | C12: this workbook
A13: Figures | B13: output/figures/T1_A7_caterpillar_cluster.pdf/.png; T1_A8_forest_study.pdf | C13: R/01_core.R par.10-11
A14: SD_COD grid | B14: 100 / 150 / 200 bp -- PLACEHOLDER, PENDING DEC-012a (Volker instrument-median extraction) | C14: [DEC-012a]
A15: Known warning | B15: impute_covariance_matrix() deprecation (clubSandwich >= 0.5.11) -- frozen by design; maintenance DEC later | C15: CC session notes

Sheet 6_A1_Main_Results
A1: A1 -- Headline pooled effect (3LMA-RVE, rho = 0.6, CR2/Satterthwaite on cluster_id)
A2: k = 2,713 ES / 115 studies / 114 clusters [DEC-042a] | spec label: headline
A3: Run 2026-07-13 | verifier 21/21 PASS
A5: Quantity | B5: Fisher z | C5: r (reporting scale)
A6: Estimate | B6: ='11_Results_Long'!J2 -> -0.058646737 | C6: ='11_Results_Long'!S2 -> -0.058579592
A7: SE | B7: ='11_Results_Long'!K2 -> 0.01385655
A8: t | B8: ='11_Results_Long'!L2 -> -4.2324199
A9: df (Satterthwaite) | B9: ='11_Results_Long'!M2 -> 111.6718
A10: p | B10: ='11_Results_Long'!N2 -> 4.7619835e-05
A11: 95% CI lower | B11: ='11_Results_Long'!O2 -> -0.086102595 | C11: ='11_Results_Long'!T2 -> -0.085890445
A12: 95% CI upper | B12: ='11_Results_Long'!P2 -> -0.031190879 | C12: ='11_Results_Long'!U2 -> -0.031180768
A13: 95% PI lower | B13: ='11_Results_Long'!Q2 -> -0.41210245 | C13: ='11_Results_Long'!V2 -> -0.39025639
A14: 95% PI upper | B14: ='11_Results_Long'!R2 -> 0.29480898 | C14: ='11_Results_Long'!W2 -> 0.28655497
A16: Interpretation
A17: Small, precisely estimated negative pooled association: r = -0.059 [-0.086; -0.031], p < 0.0001.
A18: Magnitude sits at 0.84x the Doucouliagos (2011) 'small' benchmark (0.07) -- economically modest by the field's own yardstick.
A19: The mean is not the story: see 7_A2 -- the 95% PI is sign-inclusive; heterogeneity carries the substantive message.
A21: Reviewer Q&A
A22: Question | B22: Answer
A23: Why Fisher-z PCC rather than raw correlations? | B23: 97% of the corpus are partial correlations from regressions; Fisher-z stabilizes variances (van Aert 2023); back-transform is for reporting only.
A24: A p < 0.0001 headline -- does that not contradict the paper's null thesis? | B24: No. The null thesis concerns the PARIS moderation, not the level. The level is small-negative and precise; the Paris contrast is B1's test.
A25: Why CR2 on cluster_id rather than study? | B25: The one multi-study cluster exists because of sample overlap (F56) -- sampling errors correlate at cluster level; CR2 on the coarser unit is the conservative, substantively correct choice.
A27: Verdict: The headline association is real but small; its economic reading (A6) and its heterogeneity envelope (A2/A3), not its p-value, drive the manuscript.

Sheet 7_A2_Heterogeneity
A1: A2 -- Variance decomposition + A3 overall prediction interval
A2: 3LMA-RVE variance components; shares vs Higgins-Thompson typical sampling variance
A3: Run 2026-07-13 | verifier O8 PASS (shares sum to 1)
A5: Component | B5: Value (z^2 scale) | C5: Share | D5: Interpretation
A6: sigma2 cluster (between clusters) | B6: ='11_Results_Long'!X3 -> 0.019745549 | C6: ='11_Results_Long'!AA3 -> 0.62343415 | D6: Dominant layer: population/design differences between author-clusters
A7: sigma2 study (within cluster) | B7: ='11_Results_Long'!Y3 -> 1.0209213e-09 | C7: ='11_Results_Long'!AB3 -> 3.2233959e-08 | D7: At boundary (~0): only ONE multi-study cluster exists -- weakly identified by design [DEC-042a]; battery wording '+where estimable' anticipated this
A8: omega2 ES (within study) | B8: ='11_Results_Long'!Z3 -> 0.011883179 | C8: ='11_Results_Long'!AC3 -> 0.3751924 | D8: Substantial within-study spread -> specification choices inside papers matter (Blocks C/E)
A9: Typical sampling variance | B9: ='11_Results_Long'!AE3 -> 4.3499164e-05 | C9: ='11_Results_Long'!AD3 -> 0.0013734166 | D9: Negligible: differences are real heterogeneity, not noise
A11: 95% prediction interval (r scale)
A12: PI lower | B12: ='11_Results_Long'!V2 -> -0.39025639
A13: PI upper | B13: ='11_Results_Long'!W2 -> 0.28655497
A15: Interpretation
A16: The PI [-0.390; +0.287] is sign-inclusive: a single new study can plausibly find either direction.
A17: This is the N4 statement: report the PI alongside the mean; the pooled average alone would overstate consensus.
A18: 62% of variance lies between clusters, 38% within studies, <1% study-within-cluster (boundary) and sampling.
A20: Reviewer Q&A
A21: Question | B21: Answer
A22: Is a pooled mean meaningful under a sign-inclusive PI? | B22: Yes, as the average association -- but the manuscript reports PI and mean together (N4) and builds the contribution on heterogeneity, not on a universal effect.
A23: Why is the study level ~0? | B23: 113 of 114 clusters contain exactly one study; the cluster/study split is identified by a single cluster (Sandra/Ofogbe). The component collapses to the boundary as anticipated [DEC-042a].
A25: Verdict: Heterogeneity, not the mean, is the dominant feature of this evidence base -- the PI carries the substantive story.

Sheet 8_A3_Periods_PI
A1: A3 -- Pre/Post-Paris subsets (pp_mid_lag0), descriptive; the formal moderation test is B1 [DEC-031a.6]
A2: 8 ES / 2 studies with undefined windows excluded listwise [DEC-042b]; straddling studies appear in both cells
A3: Run 2026-07-13
A5: Subset | B5: k ES | C5: k studies | D5: k clusters | E5: r | F5: 95% CI lb | G5: 95% CI ub | H5: 95% PI lb | I5: 95% PI ub | J5: df | K5: p
A6: Overall | B6: ='11_Results_Long'!G4 -> 2713 | C6: ='11_Results_Long'!H4 -> 115 | D6: ='11_Results_Long'!I4 -> 114 | E6: ='11_Results_Long'!S4 -> -0.058579592 | F6: ='11_Results_Long'!T4 -> -0.085890445 | G6: ='11_Results_Long'!U4 -> -0.031180768 | H6: ='11_Results_Long'!V4 -> -0.39025639 | I6: ='11_Results_Long'!W4 -> 0.28655497 | J6: =ROUND('11_Results_Long'!M4,1) -> 111.7 | K6: =IF('11_Results_Long'!N4="","",IF('11_Results_Long'!N4<0.0001,"< 0.0001",TEXT('11_Results_Long'!N4,"0.0000")))
A7: Pre-Paris | B7: ='11_Results_Long'!G5 -> 1994 | C7: ='11_Results_Long'!H5 -> 83 | D7: ='11_Results_Long'!I5 -> 82 | E7: ='11_Results_Long'!S5 -> -0.060209887 | F7: ='11_Results_Long'!T5 -> -0.098458627 | G7: ='11_Results_Long'!U5 -> -0.021783516 | H7: ='11_Results_Long'!V5 -> -0.43972763 | I7: ='11_Results_Long'!W5 -> 0.3375523 | J7: =ROUND('11_Results_Long'!M5,1) -> 80.3 | K7: =IF('11_Results_Long'!N5="","",IF('11_Results_Long'!N5<0.0001,"< 0.0001",TEXT('11_Results_Long'!N5,"0.0000"))) -> #VALUE!
A8: Post-Paris | B8: ='11_Results_Long'!G6 -> 711 | C8: ='11_Results_Long'!H6 -> 31 | D8: ='11_Results_Long'!I6 -> 31 | E8: ='11_Results_Long'!S6 -> -0.048667159 | F8: ='11_Results_Long'!T6 -> -0.066109574 | G8: ='11_Results_Long'!U6 -> -0.03119501 | H8: ='11_Results_Long'!V6 -> -0.20794704 | I8: ='11_Results_Long'!W6 -> 0.11312704 | J8: =ROUND('11_Results_Long'!M6,1) -> 27.5 | K8: =IF('11_Results_Long'!N6="","",IF('11_Results_Long'!N6<0.0001,"< 0.0001",TEXT('11_Results_Long'!N6,"0.0000"))) -> < 0.0001
A10: Interpretation
A11: Point contrast: post -0.049 vs pre -0.060 -- a small shift toward zero after Paris (+0.011), descriptive only.
A12: Post-cell PI [-0.208; +0.113] is narrower than pre -- fewer, more recent, somewhat more homogeneous studies (31).
A13: Consistent with the expected approximately-null Paris result; inference belongs to B1 (CR2 moderator test).
A15: Reviewer Q&A
A16: Question | B16: Answer
A17: Why no significance test of the pre/post difference here? | B17: Pre-registered separation: A3 delivers descriptive per-period PIs; the moderation test with CR2 inference is B1 [DEC-031a.6]. Reporting both here would invite double testing.
A18: Could cell assignment drive the contrast? | B18: Cells are window-based (majority-of-window, ties -> Post [DEC-024]); straddlers enter both cells; 8 window-undefined ES are excluded and disclosed [DEC-042b]. Coding sensitivity runs in Block B.
A20: Verdict: Descriptively, the association is slightly weaker post-Paris -- small enough to preview the null moderation story; B1 decides.

Sheet 9_A4_A5_Sensitivity
A1: A4 + A5 -- Working-correlation grid and estimator robustness vs headline
A2: Delta/%Delta on the z scale vs headline; CI overlap = spec CI intersects headline CI (z scale)
A3: F57: UWLS+3/WAAP CIs unreliable below df 4 (weight concentration disclosed in 11_Results_Long notes)
A5: Spec | B5: k ES | C5: k clusters | D5: est z | E5: 95% CI z lb | F5: 95% CI z ub | G5: Delta z | H5: %Delta | I5: est r | J5: 95% CI r lb | K5: 95% CI r ub | L5: df | M5: CI overlap
A6: headline (reference) | B6: ='11_Results_Long'!G2 -> 2713 | C6: ='11_Results_Long'!I2 -> 114 | D6: ='11_Results_Long'!J2 -> -0.058646737 | E6: ='11_Results_Long'!O2 -> -0.086102595 | F6: ='11_Results_Long'!P2 -> -0.031190879 | G6: ='11_Results_Long'!J2-'11_Results_Long'!$J$2 -> 0 | H6: =('11_Results_Long'!J2-'11_Results_Long'!$J$2)/ABS('11_Results_Long'!$J$2) -> 0 | I6: ='11_Results_Long'!S2 -> -0.058579592 | J6: ='11_Results_Long'!T2 -> -0.085890445 | K6: ='11_Results_Long'!U2 -> -0.031180768 | L6: =IF('11_Results_Long'!M2="","",ROUND('11_Results_Long'!M2,1)) -> 111.7 | M6: =IF(AND('11_Results_Long'!O2<='11_Results_Long'!$P$2,'11_Results_Long'!P2>='11_Results_Long'!$O$2),"yes","no") -> yes
A7: rho_0.4 | B7: ='11_Results_Long'!G7 -> 2713 | C7: ='11_Results_Long'!I7 -> 114 | D7: ='11_Results_Long'!J7 -> -0.059331662 | E7: ='11_Results_Long'!O7 -> -0.086819506 | F7: ='11_Results_Long'!P7 -> -0.031843817 | G7: ='11_Results_Long'!J7-'11_Results_Long'!$J$2 -> -0.00068492495 | H7: =('11_Results_Long'!J7-'11_Results_Long'!$J$2)/ABS('11_Results_Long'!$J$2) -> -0.011678825 | I7: ='11_Results_Long'!S7 -> -0.059262139 | J7: ='11_Results_Long'!T7 -> -0.086602024 | K7: ='11_Results_Long'!U7 -> -0.031833058 | L7: =IF('11_Results_Long'!M7="","",ROUND('11_Results_Long'!M7,1)) -> 111.8 | M7: =IF(AND('11_Results_Long'!O7<='11_Results_Long'!$P$2,'11_Results_Long'!P7>='11_Results_Long'!$O$2),"yes","no") -> yes
A8: rho_0.8 | B8: ='11_Results_Long'!G8 -> 2713 | C8: ='11_Results_Long'!I8 -> 114 | D8: ='11_Results_Long'!J8 -> -0.058036025 | E8: ='11_Results_Long'!O8 -> -0.085430225 | F8: ='11_Results_Long'!P8 -> -0.030641825 | G8: ='11_Results_Long'!J8-'11_Results_Long'!$J$2 -> 0.00061071147 | H8: =('11_Results_Long'!J8-'11_Results_Long'!$J$2)/ABS('11_Results_Long'!$J$2) -> 0.010413392 | I8: ='11_Results_Long'!S8 -> -0.057970954 | J8: ='11_Results_Long'!T8 -> -0.085222997 | K8: ='11_Results_Long'!U8 -> -0.030632239 | L8: =IF('11_Results_Long'!M8="","",ROUND('11_Results_Long'!M8,1)) -> 111.5 | M8: =IF(AND('11_Results_Long'!O8<='11_Results_Long'!$P$2,'11_Results_Long'!P8>='11_Results_Long'!$O$2),"yes","no") -> yes
A9: one_effect_per_cluster | B9: ='11_Results_Long'!G9 -> 114 | C9: ='11_Results_Long'!I9 -> 114 | D9: ='11_Results_Long'!J9 -> -0.061660839 | E9: ='11_Results_Long'!O9 -> -0.10986426 | F9: ='11_Results_Long'!P9 -> -0.013457412 | G9: ='11_Results_Long'!J9-'11_Results_Long'!$J$2 -> -0.003014102 | H9: =('11_Results_Long'!J9-'11_Results_Long'!$J$2)/ABS('11_Results_Long'!$J$2) -> -0.051394199 | I9: ='11_Results_Long'!S9 -> -0.061582811 | J9: ='11_Results_Long'!T9 -> -0.10942436 | K9: ='11_Results_Long'!U9 -> -0.0134566 | L9: =IF('11_Results_Long'!M9="","",ROUND('11_Results_Long'!M9,1)) -> 113 | M9: =IF(AND('11_Results_Long'!O9<='11_Results_Long'!$P$2,'11_Results_Long'!P9>='11_Results_Long'!$O$2),"yes","no") -> yes
A10: uwls3 | B10: ='11_Results_Long'!G10 -> 2713 | C10: ='11_Results_Long'!I10 -> 114 | D10: ='11_Results_Long'!J10 -> -0.030667422 | E10: ='11_Results_Long'!O10 -> -0.086946258 | F10: ='11_Results_Long'!P10 -> 0.025417673 | G10: ='11_Results_Long'!J10-'11_Results_Long'!$J$2 -> 0.027979315 | H10: =('11_Results_Long'!J10-'11_Results_Long'!$J$2)/ABS('11_Results_Long'!$J$2) -> 0.47708221 | I10: ='11_Results_Long'!S10 -> -0.030657811 | J10: ='11_Results_Long'!T10 -> -0.086727824 | K10: ='11_Results_Long'!U10 -> 0.025412201 | L10: =IF('11_Results_Long'!M10="","",ROUND('11_Results_Long'!M10,1)) -> 2.3 | M10: =IF(AND('11_Results_Long'!O10<='11_Results_Long'!$P$2,'11_Results_Long'!P10>='11_Results_Long'!$O$2),"yes","no") -> yes
A11: hs_es_level | B11: ='11_Results_Long'!G11 -> 2713 | C11: ='11_Results_Long'!I11 -> 114 | D11: ='11_Results_Long'!J11 -> -0.021773098 | E11: ='11_Results_Long'!O11 -> -0.02448315 | F11: ='11_Results_Long'!P11 -> -0.019063366 | G11: ='11_Results_Long'!J11-'11_Results_Long'!$J$2 -> 0.036873638 | H11: =('11_Results_Long'!J11-'11_Results_Long'!$J$2)/ABS('11_Results_Long'!$J$2) -> 0.62874152 | I11: ='11_Results_Long'!S11 -> -0.021769658 | J11: ='11_Results_Long'!T11 -> -0.02447826 | K11: ='11_Results_Long'!U11 -> -0.019061057 | L11: =IF('11_Results_Long'!M11="","",ROUND('11_Results_Long'!M11,1)) | M11: =IF(AND('11_Results_Long'!O11<='11_Results_Long'!$P$2,'11_Results_Long'!P11>='11_Results_Long'!$O$2),"yes","no") -> no
A12: waap_uwls | B12: ='11_Results_Long'!G12 -> 704 | C12: ='11_Results_Long'!I12 -> 49 | D12: ='11_Results_Long'!J12 -> -0.030912018 | E12: ='11_Results_Long'!O12 -> -0.092903674 | F12: ='11_Results_Long'!P12 -> 0.030842731 | G12: ='11_Results_Long'!J12-'11_Results_Long'!$J$2 -> 0.027734718 | H12: =('11_Results_Long'!J12-'11_Results_Long'!$J$2)/ABS('11_Results_Long'!$J$2) -> 0.47291154 | I12: ='11_Results_Long'!S12 -> -0.030902176 | J12: ='11_Results_Long'!T12 -> -0.092637307 | K12: ='11_Results_Long'!U12 -> 0.030832954 | L12: =IF('11_Results_Long'!M12="","",ROUND('11_Results_Long'!M12,1)) -> 2.2 | M12: =IF(AND('11_Results_Long'!O12<='11_Results_Long'!$P$2,'11_Results_Long'!P12>='11_Results_Long'!$O$2),"yes","no") -> yes
A14: Interpretation
A15: rho 0.4/0.8: estimate moves by <2% -- the working-correlation assumption is immaterial.
A16: One-effect-per-cluster (-0.062, KnHa df 113) brackets the headline from below -- aggregation does not create the effect.
A17: UWLS+3 (-0.031) and WAAP (-0.031) halve the estimate: FE-type precision weights concentrate on mega-samples (top cluster 37.9% / 41.1% of weight) -- the documented rationale for the hierarchical headline. Point estimates keep sign and order of magnitude.
A18: HS (-0.022) is the n-weighted floor; its SE is anti-conservative under dependence (disclosed) -- the 'no' in the CI-overlap column is an artifact of that too-narrow interval, not a point-estimate divergence.
A19: WAAP power finding: only 704 of 2,713 ES (26%) are adequately powered against the pooled effect (Ioannidis et al. 2017 narrative).
A21: Reviewer Q&A
A22: Question | B22: Answer
A23: Are the UWLS+3/WAAP confidence intervals valid at df ~ 2.2? | B23: No -- flagged unreliable below df 4 (Tipton); the robustness claim rests on point-estimate agreement. Inference burden per F54: one_effect_per_cluster + the 3LMA family [F57].
A24: Why does the FE-type estimator shrink the effect? | B24: Two mega-sample clusters dominate the precision weights (top-2 = 52.6%); their effects are closer to zero. That precision-weighted view is reported, disclosed -- and is exactly why the headline uses hierarchical weighting.
A25: Is one robustness row enough per estimator family? | B25: Block G runs the full pre-registered catalogue (LOSO, outliers, winsorizing, r-type, k10/k20 df sensitivity etc.); A5 anchors the estimator families [DEC-031a.4].
A27: Verdict: The pooled association is robust in sign and order of magnitude across rho and estimator families; magnitude differences are explained, disclosed weight-concentration effects -- no estimator overturns the headline reading.

Sheet 10_A6_Economic_Translation
A1: A6 -- Economic translation [DEC-012/DEC-012a]
A2: Delta COD (bp) per 1-SD CER improvement = tanh(z_pooled) x SD_COD_bp -- constants PENDING DEC-012a (Volker instrument-median extraction)
A3: Manuscript economic-significance line stays BLOCKED until instrument medians (loan/bond/CDS) land
A5: Spec | B5: SD_COD (bp) | C5: Delta COD (bp) | D5: Status
A6: bp_per_1sd_sd100 | B6: 100 | C6: ='11_Results_Long'!AF13 -> -5.8579592 | D6: PLACEHOLDER -- PENDING DEC-012a
A7: bp_per_1sd_sd150 | B7: 150 | C7: ='11_Results_Long'!AF14 -> -8.7869388 | D7: PLACEHOLDER -- PENDING DEC-012a
A8: bp_per_1sd_sd200 | B8: 200 | C8: ='11_Results_Long'!AF15 -> -11.715918 | D8: PLACEHOLDER -- PENDING DEC-012a
A9: small_benchmark_ratio | B9: - | C9: ='11_Results_Long'!AF16 -> -0.83685131 | D9: constant-free: pooled r / 0.07 (Doucouliagos 2011)
A11: Interpretation
A12: Under plausible SD anchors, a 1-SD CER improvement maps to single-digit bp reductions in COD (-5.9 to -11.7 bp).
A13: Constant-free anchor: |r| = 0.84x the field's own 'small' benchmark -- quotable now.
A14: Final manuscript numbers re-key to bp_per_1sd_{loan,bond,cds} once DEC-012a medians land (deterministic constants-patch re-run).
A16: Reviewer Q&A
A17: Question | B17: Answer
A18: Where do the SD benchmarks come from? | B18: Pre-fixed extraction rule [DEC-012a]: median reported SD(COD) per instrument class (loan/bond/CDS) across all corpus studies reporting it -- rule fixed before any constant was seen.
A19: Is r x SD a valid economic mapping? | B19: It is the transparent first-order approximation, labelled as such -- not a structural elasticity. Zarea et al. do not quantify at all; doing it per instrument is the differentiator [DEC-012].
A21: Verdict: Economically modest under any plausible scale anchor -- exactly the honest-magnitude statement DEC-012 requires; final bp values await DEC-012a.

Sheet 11_Results_Long
A1: analysis_id | B1: spec | C1: subset | D1: metric | E1: estimator | F1: rho | G1: k_es | H1: k_study | I1: k_cluster | J1: est_z | K1: se_z | L1: t_stat | M1: df | N1: p | O1: ci_lb_z | P1: ci_ub_z | Q1: pi_lb_z | R1: pi_ub_z | S1: est_r | T1: ci_lb_r | U1: ci_ub_r | V1: pi_lb_r | W1: pi_ub_r | X1: sigma2_cluster | Y1: sigma2_study | Z1: sigma2_esid | AA1: pct_cluster | AB1: pct_study | AC1: pct_esid | AD1: pct_sampling | AE1: typical_v | AF1: value | AG1: ms_input | AH1: ms_label | AI1: note
A2: A1 | B2: headline | C2: all | D2: Fisher_z | E2: 3LMA-RVE_CR2 | F2: 0.6 | G2: 2713 | H2: 115 | I2: 114 | J2: -0.058646737 | K2: 0.01385655 | L2: -4.2324199 | M2: 111.6718 | N2: 4.7619835e-05 | O2: -0.086102595 | P2: -0.031190879 | Q2: -0.41210245 | R2: 0.29480898 | S2: -0.058579592 | T2: -0.085890445 | U2: -0.031180768 | V2: -0.39025639 | W2: 0.28655497 | X2: 0.019745549 | Y2: 1.0209213e-09 | Z2: 0.011883179 | AG2: TRUE | AH2: headline_pooled | AI2: rma.mv ~1|cluster_id/study/esid; V blocks within cluster_id, rho=0.6 [D31.1/F56: sample-overlap cluster]; CR2/Satterthwaite on cluster_id
A3: A2 | B3: var_decomposition | C3: all | D3: Fisher_z | E3: 3LMA-RVE_REML | F3: 0.6 | G3: 2713 | H3: 115 | I3: 114 | X3: 0.019745549 | Y3: 1.0209213e-09 | Z3: 0.011883179 | AA3: 0.62343415 | AB3: 3.2233959e-08 | AC3: 0.3751924 | AD3: 0.0013734166 | AE3: 4.3499164e-05 | AG3: TRUE | AH3: variance_decomposition | AI3: Cluster/study split weakly identified by design (1 multi-study cluster, DEC-042a); battery A2: '+Cluster-Ebene wo schaetzbar'. Sampling share via Higgins-Thompson typical v.
A4: A3 | B4: pi_overall | C4: all | D4: Fisher_z | E4: 3LMA-RVE_CR2 | F4: 0.6 | G4: 2713 | H4: 115 | I4: 114 | J4: -0.058646737 | K4: 0.01385655 | M4: 111.6718 | O4: -0.086102595 | P4: -0.031190879 | Q4: -0.41210245 | R4: 0.29480898 | S4: -0.058579592 | T4: -0.085890445 | U4: -0.031180768 | V4: -0.39025639 | W4: 0.28655497 | AG4: TRUE | AH4: pi_overall | AI4: Identical fit to A1 (verifier identity O20). PI = est +/- t_dfSatt*sqrt(SE_CR2^2+sum(sigma2)) [F55].
A5: A3 | B5: pi_pre | C5: pre | D5: Fisher_z | E5: 3LMA-RVE_CR2 | F5: 0.6 | G5: 1994 | H5: 83 | I5: 82 | J5: -0.060282804 | K5: 0.019345037 | L5: -3.1161896 | M5: 80.272947 | N5: 0.0025416564 | O5: -0.098778646 | P5: -0.021786962 | Q5: -0.47189309 | R5: 0.35132748 | S5: -0.060209887 | T5: -0.098458627 | U5: -0.021783516 | V5: -0.43972763 | W5: 0.3375523 | X5: 0.028149686 | Y5: 1.9888003e-09 | Z5: 0.014260334 | AG5: TRUE | AH5: pi_pre | AI5: Descriptive per-period fit on pp_mid_lag0 subset; straddling studies appear in both cells (design fact); 8 ES / 2 studies with undefined windows excluded listwise [DEC-042b]; NO between-group test here (that is B1) [DEC-031a.6].
A6: A3 | B6: pi_post | C6: post | D6: Fisher_z | E6: 3LMA-RVE_CR2 | F6: 0.6 | G6: 711 | H6: 31 | I6: 31 | J6: -0.048705636 | K6: 0.0085367029 | L6: -5.7054389 | M6: 27.516321 | N6: 4.3127478e-06 | O6: -0.066206138 | P6: -0.031205135 | Q6: -0.21102464 | R6: 0.11361336 | S6: -0.048667159 | T6: -0.066109574 | U6: -0.03119501 | V6: -0.20794704 | W6: 0.11312704 | X6: 0.00073681522 | Y6: 0.00073681522 | Z6: 0.00472278 | AG6: TRUE | AH6: pi_post | AI6: Descriptive per-period fit on pp_mid_lag0 subset; straddling studies appear in both cells (design fact); 8 ES / 2 studies with undefined windows excluded listwise [DEC-042b]; NO between-group test here (that is B1) [DEC-031a.6].
A7: A4 | B7: rho_0.4 | C7: all | D7: Fisher_z | E7: 3LMA-RVE_CR2 | F7: 0.4 | G7: 2713 | H7: 115 | I7: 114 | J7: -0.059331662 | K7: 0.013872878 | L7: -4.2768098 | M7: 111.80835 | N7: 4.011838e-05 | O7: -0.086819506 | P7: -0.031843817 | Q7: -0.41232126 | R7: 0.29365794 | S7: -0.059262139 | T7: -0.086602024 | U7: -0.031833058 | V7: -0.39044186 | W7: 0.28549809 | X7: 0.019970875 | Y7: 2.0563758e-09 | Z7: 0.011574377 | AG7: FALSE | AI7: Spec-label compatible with catalogue G long table [battery A4 remark].
A8: A4 | B8: rho_0.8 | C8: all | D8: Fisher_z | E8: 3LMA-RVE_CR2 | F8: 0.8 | G8: 2713 | H8: 115 | I8: 114 | J8: -0.058036025 | K8: 0.013825217 | L8: -4.1978381 | M8: 111.51402 | N8: 5.4394338e-05 | O8: -0.085430225 | P8: -0.030641825 | Q8: -0.41211656 | R8: 0.29604451 | S8: -0.057970954 | T8: -0.085222997 | U8: -0.030632239 | V8: -0.39026835 | W8: 0.28768864 | X8: 0.019478876 | Y8: 2.8549316e-09 | Z8: 0.012262329 | AG8: FALSE | AI8: Spec-label compatible with catalogue G long table [battery A4 remark].
A9: A5 | B9: one_effect_per_cluster | C9: all | D9: Fisher_z | E9: RE_REML_KnHa | F9: 0.6 | G9: 114 | I9: 114 | J9: -0.061660839 | K9: 0.02433066 | L9: -2.5342855 | M9: 113 | N9: 0.012636764 | O9: -0.10986426 | P9: -0.013457412 | S9: -0.061582811 | T9: -0.10942436 | U9: -0.0134566 | AG9: FALSE | AI9: aggregate.escalc CS rho=0.6 within cluster_id; RE REML + Knapp-Hartung on k=114 aggregates.
A10: A5 | B10: uwls3 | C10: all | D10: PCC_r | E10: UWLS+3_CR2 | G10: 2713 | H10: 115 | I10: 114 | J10: -0.030667422 | L10: -2.0951956 | M10: 2.2814986 | N10: 0.15520197 | O10: -0.086946258 | P10: 0.025417673 | S10: -0.030657811 | T10: -0.086727824 | U10: 0.025412201 | AG10: FALSE | AI10: rp3=t/sqrt(t^2+n_eff+3), var3=1/(t^2+n_eff+3) [Stanley et al. 2024 Eq 2/4/9; df~=n_eff per F21]; CR2 on cluster_id [plan par.5]; conventional UWLS SE = 0.002270. F57 disclosure (unconditional): CR2 df_Satt = 2.28; top-cluster weight share = 37.9%; top-2 = 52.6%. CI below df 4 unreliable (Tipton); inference burden per F54 on one_effect_per_cluster + 3LMA family.
A11: A5 | B11: hs_es_level | C11: all | D11: PCC_r | E11: HS_bare_bones | G11: 2713 | H11: 115 | I11: 114 | J11: -0.021773098 | O11: -0.02448315 | P11: -0.019063366 | S11: -0.021769658 | T11: -0.02447826 | U11: -0.019061057 | AG11: FALSE | AI11: n-weighted mean r; SE = SD_w/sqrt(k), k = 2713 ES -- anti-conservative under dependence; descriptive appendix benchmark [F54]. SE_HS = 0.001382.
A12: A5 | B12: waap_uwls | C12: powered | D12: PCC_r | E12: WAAP_CR2 | G12: 704 | I12: 49 | J12: -0.030912018 | L12: -1.9648331 | M12: 2.215631 | N12: 0.17582816 | O12: -0.092903674 | P12: 0.030842731 | S12: -0.030902176 | T12: -0.092637307 | U12: 0.030832954 | AG12: FALSE | AI12: Adequately powered: SE_i <= |UWLS+3|/2.8; k_powered = 704 of 2713 ES. F57 disclosure (unconditional): CR2 df_Satt = 2.22; top-cluster weight share = 41.1%; top-2 = 56.9% (powered subset).
A13: A6 | B13: bp_per_1sd_sd100 | C13: all | D13: bp_COD | E13: translation | G13: 2713 | H13: 115 | I13: 114 | S13: -0.058579592 | T13: -0.085890445 | U13: -0.031180768 | AF13: -5.8579592 | AG13: TRUE | AH13: bp_translation_sd100 | AI13: Delta COD (bp) per 1-SD CER = tanh(z_pooled) * SD_COD_bp; SD_COD_bp = 100 <<< PLACEHOLDER -- PENDING DEC-012a (instrument medians via Volker task) >>>. CI endpoints scale identically (value column = point).
A14: A6 | B14: bp_per_1sd_sd150 | C14: all | D14: bp_COD | E14: translation | G14: 2713 | H14: 115 | I14: 114 | S14: -0.058579592 | T14: -0.085890445 | U14: -0.031180768 | AF14: -8.7869388 | AG14: TRUE | AH14: bp_translation_sd150 | AI14: Delta COD (bp) per 1-SD CER = tanh(z_pooled) * SD_COD_bp; SD_COD_bp = 150 <<< PLACEHOLDER -- PENDING DEC-012a (instrument medians via Volker task) >>>. CI endpoints scale identically (value column = point).
A15: A6 | B15: bp_per_1sd_sd200 | C15: all | D15: bp_COD | E15: translation | G15: 2713 | H15: 115 | I15: 114 | S15: -0.058579592 | T15: -0.085890445 | U15: -0.031180768 | AF15: -11.715918 | AG15: TRUE | AH15: bp_translation_sd200 | AI15: Delta COD (bp) per 1-SD CER = tanh(z_pooled) * SD_COD_bp; SD_COD_bp = 200 <<< PLACEHOLDER -- PENDING DEC-012a (instrument medians via Volker task) >>>. CI endpoints scale identically (value column = point).
A16: A6 | B16: small_benchmark_ratio | C16: all | D16: ratio | E16: translation | S16: -0.058579592 | AF16: -0.83685131 | AG16: TRUE | AH16: doucouliagos_small_ratio | AI16: Pooled r over Doucouliagos (2011) 'small' benchmark 0.07 [DEC-012 rationale]; constant-free.

Sheet 12_Manuscript_Inputs
A1: Manuscript Inputs -- copy-paste-ready values (SOMA's most valuable sheet)
A2: All cells derive by formula from 11_Results_Long; ms_input = TRUE rows only
A3: bp rows: PENDING DEC-012a -- do not quote in the manuscript yet
A5: ms_label | B5: analysis | C5: quantity | D5: value | E5: 95% CI | F5: PI (95%) | G5: df | H5: p | I5: k (ES/studies/clusters) | J5: status / note
A6: headline_pooled | B6: A1 | C6: Pooled partial correlation (3LMA-RVE, rho=0.6, CR2) | D6: =TEXT('11_Results_Long'!S2,"0.000") -> #VALUE! | E6: ="["&TEXT('11_Results_Long'!T2,"0.000")&"; "&TEXT('11_Results_Long'!U2,"0.000")&"]" -> #VALUE! | F6: ="["&TEXT('11_Results_Long'!V2,"0.000")&"; "&TEXT('11_Results_Long'!W2,"0.000")&"]" -> #VALUE! | G6: =ROUND('11_Results_Long'!M2,1) -> 111.7 | H6: =IF('11_Results_Long'!N2<0.0001,"< 0.0001",TEXT('11_Results_Long'!N2,"0.0000")) -> < 0.0001 | I6: ='11_Results_Long'!G2&" / "&'11_Results_Long'!H2&" / "&'11_Results_Long'!I2 -> 2713 / 115 / 114 | J6: headline
A7: variance_decomposition | B7: A2 | C7: Variance shares cluster / study / ES / sampling | D7: =TEXT('11_Results_Long'!AA3,"0.0%")&" / "&TEXT('11_Results_Long'!AB3,"0.0%")&" / "&TEXT('11_Results_Long'!AC3,"0.0%")&" / "&TEXT('11_Results_Long'!AD3,"0.0%") -> #VALUE! | I7: ='11_Results_Long'!G3&" / "&'11_Results_Long'!H3&" / "&'11_Results_Long'!I3 -> 2713 / 115 / 114 | J7: study level at boundary (1 multi-study cluster)
A8: pi_overall | B8: A3 | C8: Prediction interval, full set | D8: =TEXT('11_Results_Long'!S4,"0.000") -> #VALUE! | E8: ="["&TEXT('11_Results_Long'!T4,"0.000")&"; "&TEXT('11_Results_Long'!U4,"0.000")&"]" -> #VALUE! | F8: ="["&TEXT('11_Results_Long'!V4,"0.000")&"; "&TEXT('11_Results_Long'!W4,"0.000")&"]" -> #VALUE! | G8: =ROUND('11_Results_Long'!M4,1) -> 111.7 | I8: ='11_Results_Long'!G4&" / "&'11_Results_Long'!H4&" / "&'11_Results_Long'!I4 -> 2713 / 115 / 114 | J8: F55 construction
A9: pi_pre | B9: A3 | C9: Pre-Paris subset | D9: =TEXT('11_Results_Long'!S5,"0.000") -> #VALUE! | E9: ="["&TEXT('11_Results_Long'!T5,"0.000")&"; "&TEXT('11_Results_Long'!U5,"0.000")&"]" -> #VALUE! | F9: ="["&TEXT('11_Results_Long'!V5,"0.000")&"; "&TEXT('11_Results_Long'!W5,"0.000")&"]" -> #VALUE! | G9: =ROUND('11_Results_Long'!M5,1) -> 80.3 | H9: =IF('11_Results_Long'!N5<0.0001,"< 0.0001",TEXT('11_Results_Long'!N5,"0.0000")) -> #VALUE! | I9: ='11_Results_Long'!G5&" / "&'11_Results_Long'!H5&" / "&'11_Results_Long'!I5 -> 1994 / 83 / 82 | J9: descriptive; test in B1; 8 ES excluded [DEC-042b]
A10: pi_post | B10: A3 | C10: Post-Paris subset | D10: =TEXT('11_Results_Long'!S6,"0.000") -> #VALUE! | E10: ="["&TEXT('11_Results_Long'!T6,"0.000")&"; "&TEXT('11_Results_Long'!U6,"0.000")&"]" -> #VALUE! | F10: ="["&TEXT('11_Results_Long'!V6,"0.000")&"; "&TEXT('11_Results_Long'!W6,"0.000")&"]" -> #VALUE! | G10: =ROUND('11_Results_Long'!M6,1) -> 27.5 | H10: =IF('11_Results_Long'!N6<0.0001,"< 0.0001",TEXT('11_Results_Long'!N6,"0.0000")) -> < 0.0001 | I10: ='11_Results_Long'!G6&" / "&'11_Results_Long'!H6&" / "&'11_Results_Long'!I6 -> 711 / 31 / 31 | J10: descriptive; test in B1; 8 ES excluded [DEC-042b]
A11: bp_translation_sd100 | B11: A6 | C11: Delta COD per 1-SD CER, SD_COD = 100 bp | D11: =TEXT('11_Results_Long'!AF13,"0.0")&" bp" -> #VALUE! | I11: ='11_Results_Long'!G13&" / "&'11_Results_Long'!H13&" / "&'11_Results_Long'!I13 -> 2713 / 115 / 114 | J11: PENDING DEC-012a
A12: bp_translation_sd150 | B12: A6 | C12: Delta COD per 1-SD CER, SD_COD = 150 bp | D12: =TEXT('11_Results_Long'!AF14,"0.0")&" bp" -> #VALUE! | I12: ='11_Results_Long'!G14&" / "&'11_Results_Long'!H14&" / "&'11_Results_Long'!I14 -> 2713 / 115 / 114 | J12: PENDING DEC-012a
A13: bp_translation_sd200 | B13: A6 | C13: Delta COD per 1-SD CER, SD_COD = 200 bp | D13: =TEXT('11_Results_Long'!AF15,"0.0")&" bp" -> #VALUE! | I13: ='11_Results_Long'!G15&" / "&'11_Results_Long'!H15&" / "&'11_Results_Long'!I15 -> 2713 / 115 / 114 | J13: PENDING DEC-012a
A14: doucouliagos_small_ratio | B14: A6 | C14: Pooled r / 0.07 (Doucouliagos 'small') | D14: =TEXT('11_Results_Long'!AF16,"0.00")&" x" -> #VALUE! | J14: constant-free [DEC-012]

Sheet 13_Manuscript_Text_Blocks
A1: Manuscript text blocks -- Block A (copy-paste-ready English prose)
A2: Framing-neutral report-level prose; the A-vs-C positioning (Ablauf 3b, after T8) may adjust emphasis, not numbers.
A3: Numbers are hardcoded from 11_Results_Long (run 2026-07-13, verifier 21/21) -- regenerate this tab on any re-run. Cross-references [in brackets] to be resolved at write-up.
A5: ID | B5: Target | C5: Status | D5: Text (EN) | E5: Source pointers | F5: Note
A6: TB-01 | B6: Methods 3.x (model) | C6: READY | D6: We estimate a three-level random-effects model on Fisher-z transformed partial correlations, with effect sizes nested in studies nested in author clusters. The working covariance follows the correlated-and-hierarchical-effects structure with an assumed within-cluster sampling correlation of rho = 0.6, and all inference uses CR2 small-sample robust standard errors with Satterthwaite degrees of freedom, clustered at the author-cluster level (Hedges, Tipton, & Johnson, 2010; Tipton & Pustejovsky, 2015; Pustejovsky & Tipton, 2022). Partial correlations are transformed per van Aert (2023), with sampling variance 1/(n - 3); results are back-transformed to r for reporting. | E6: [R/01]; [DEC-017]; [DEC-031 D31.1]; [plan par.3/par.5] | F6: rho grid {0.4, 0.8} sensitivity -> TB-09
A7: TB-02 | B7: Methods 3.x (PI) | C7: READY | D7: Prediction intervals are constructed as b +/- t(df) * sqrt(SE^2 + sigma2_cluster + sigma2_study + omega2), i.e., including all estimated variance components, so that they describe the plausible range of a single new effect. | E7: [F55]; [plan Addendum A.8]; [R/01] | F7: one sentence; place after model paragraph
A8: TB-03 | B8: Methods 3.x (sample) | C8: READY | D8: The estimation set comprises 2,713 effect sizes from 115 studies forming 114 independent author clusters. Eight effect sizes from two studies (Bhattacharya & Sharma, 2019; Ng & Rezaee, 2012) do not report recoverable sample windows; they remain in the estimation set but are excluded listwise from all period-based cells. | E8: [DEC-042a]; [DEC-042b] | F8: second sentence doubles as the DEC-042b disclosure
A9: TB-04 | B9: Results 4.1 (headline) | C9: READY | D9: Across 2,713 effect sizes from 115 studies, the pooled partial correlation between corporate environmental responsibility and the cost of debt is r = -0.059 (95% CI [-0.086; -0.031], df = 111.7, p < 0.001). | E9: [11_Results_Long row 2]; [DEC-042a] | F9: headline sentence
A10: TB-05 | B10: Results 4.1 (magnitude) | C10: READY | D10: At |r| = 0.059, the pooled association falls below the 'small' partial-correlation benchmark of 0.07 (Doucouliagos, 2011), at 0.84 times that threshold. | E10: [11_Results_Long row 16]; [DEC-012] | F10: constant-free; quotable now
A11: TB-06 | B11: Results 4.1 (heterogeneity) | C11: READY | D11: Heterogeneity, not the mean, is the dominant feature of the evidence base: the 95% prediction interval spans [-0.390; 0.287], so a single new study can plausibly report either sign. Of total variance, 62.3% lies between author clusters and 37.5% within studies; sampling error accounts for less than 1%. The study-within-cluster component is empirically indistinguishable from zero, as only one cluster contains more than one study. | E11: [11_Results_Long rows 2-3]; [N4]; [DEC-042a] | F11: PI sentence = N4 commitment
A12: TB-07 | B12: Results 4.x (pre/post descriptive) | C12: READY | D12: Descriptively, the association is marginally weaker in study windows lying predominantly after the Paris Agreement (r = -0.049, 95% CI [-0.066; -0.031], 711 effect sizes from 31 studies) than before (r = -0.060, 95% CI [-0.098; -0.022], 1,994 effect sizes from 83 studies); the corresponding prediction intervals are [-0.208; 0.113] and [-0.440; 0.338]. The formal moderation test follows in Section [B1]. | E12: [11_Results_Long rows 5-6]; [DEC-031a.6] | F12: cross-ref [B1] to resolve; no test language here
A13: TB-08 | B13: Results 4.x (economic translation) | C13: BLOCKED -- DEC-012a | D13: Translated into economic terms, a one-standard-deviation improvement in CER corresponds to a reduction in borrowing costs of approximately [X] basis points for loans, [Y] basis points for bonds, and [Z] basis points for CDS spreads, based on instrument-level median standard deviations of the cost-of-debt measures reported in the primary studies. | E13: [DEC-012a]; [11_Results_Long rows 13-15] | F13: DO NOT fill [X/Y/Z] from the placeholder grid (-5.9/-8.8/-11.7 rest on illustrative SDs); wait for Volker extraction
A14: TB-09 | B14: Results 4.x / Robustness | C14: READY | D14: The pooled estimate is insensitive to the working-correlation assumption (rho = 0.4/0.8: r = -0.059/-0.058) and to aggregation to one effect per cluster (r = -0.062, 95% CI [-0.109; -0.013], Knapp-Hartung, k = 114). Precision-weighted estimators are smaller (UWLS+3: -0.031; WAAP: -0.031; Hunter-Schmidt: -0.022), reflecting the dominance of two very large samples in the precision weights (top cluster: 37.9% of total UWLS+3 weight; top two: 52.6%); we therefore retain the hierarchical model as the headline and report the precision-weighted family in Appendix [X]. | E14: [11_Results_Long rows 7-12]; [F54]; [F57] | F14: appendix cross-ref to resolve
A15: TB-10 | B15: Appendix (df footnote) | C15: READY | D15: CR2 Satterthwaite degrees of freedom for the UWLS+3 and WAAP estimators are 2.3 and 2.2, respectively -- below the df >= 4 threshold at which the t-approximation is reliable (Tipton & Pustejovsky, 2015); their confidence intervals should therefore not be used for inference. The small degrees of freedom reflect weight concentration rather than an estimation defect. | E15: [F57]; [11_Results_Long rows 10, 12] | F15: footnote to the appendix estimator table
A16: TB-11 | B16: Appendix / Discussion (power) | C16: READY | D16: Only 704 of 2,713 effect sizes (26%, from 49 clusters) are adequately powered against the pooled effect (Stanley, Doucouliagos, & Ioannidis, 2017), echoing the low statistical power documented for empirical economics more broadly (Ioannidis, Stanley, & Doucouliagos, 2017). | E16: [11_Results_Long row 12] | F16: feeds the null-security narrative; placement decided at 3b
A17: TB-12 | B17: Abstract | C17: READY | D17: Whether the Paris Agreement repriced corporate environmental responsibility (CER) in credit markets is a central expectation of sustainable finance that no synthesis has tested. We meta-analyze the CER–cost of debt relationship, pooling 2,713 effect sizes from 115 studies forming 114 independent author clusters, with three-level cluster-robust models and pre-specified equivalence tests. The pooled association is statistically detectable but economically negligible — r = −0.059 (95% CI [−0.086; −0.031]), 0.84 times the conventional small-effect benchmark for partial correlations — and explicitly not a null effect. Centrally, the post-minus-pre Paris contrast is statistically equivalent to zero within the pre-specified smallest-effect-size-of-interest band: no detectable Paris-Agreement moderation. No coded measurement, instrument, industry, regulatory, or country context detectably shifts the association, and publication-selection corrections mark the pooled magnitude as an upper bound. We convert a scattered literature into a calibrated quantity and give the Paris-repricing thesis its first meta-analytic test in credit-market pricing. | E17: [Ablauf #11] | F17: Finalized at M6 (DEC-058); supersedes the Block-A fragment at use — deltas: PI clause dropped (single home ch4 §4.1.1/A.8); benchmark wording → 0.84-ratio Tier-2 form; Paris, moderation/selection, and contribution elements added. BSE cap author-verified (≤ 150 words, citation-free, ≤ 6 keywords).
