Workbook

Sheet 1_README
A1: FOMA CER–COD–Paris — T7 / Block C results workbook (narrative moderators C0–C9)
A2: Template: docs/results_workbook_template.md (binding) · one workbook per run
A3: Run 7 · 2026-07-29 09:30:52 · HEAD 6e7ce03 · verifier R/10_verify_outputs.R: 27/27 PASS, exit 0
A5: Item | B5: Value
A6: Data version | B6: CERCOD v12 — estimation set 2,713 ES / 115 studies / 114 clusters
A7: Method (one line) | B7: random ~1|cluster_id/study/esid; V blocks within cluster_id, rho=0.6; CR2/Satterthwaite on cluster_id [D31.1/A.2]
A8: Scope | B8: Block C: eight univariate moderator panels (M_A/M_B), M-pre guards, any-with sensitivity, unified models V1/V2, C0 background (separate file)
A9: Repository | B9: github.com/rwitte-wu-research/FOMA-CER-COD-Paris (public, main)
A10: Computational stack | B10: R 4.6.1 · metafor 5.0-1 · clubSandwich 0.7.0 · seed 20260710
A11: Scripts | B11: R/10_moderators.R + R/10_verify_outputs.R @ 6e7ce03
A12: Decision basis | B12: DEC-043 · DEC-048 · DEC-049 · DEC-049a · analysis_plan A.14; language regime per DEC-044/DEC-047
A14: TAB-INDEX
A15: 1_README
A16: 2_Methodology
A17: 3_Interpretation_Guide
A18: 4_Formula_Reference
A19: 5_Data_Provenance
A20: 6_Moderation_Overview
A21: 7_Featured_Panels
A22: 8_Other_Panels
A23: 9_C9_Unified
A24: 10_Guards_Sensitivity
A25: Results_Long
... A27: Manuscript_Text_Blocks

Sheet 2_Methodology
A1: Methodology — constructions as implemented
A2: All quantities computed by R/10_moderators.R @ 6e7ce03
A3: Source pointers in project notation
A5: Quantity | B5: Formula / Construction | C5: Reference
A6: M_A level means | B6: rma.mv: zi ~ 0 + moderator (cell means, NCE excluded); CR2/Satterthwaite per level | C6: [DEC-048; DEC-031e]
A7: M_B period cells | B7: zi ~ 0 + cell(moderator × pp_mid_lag0), nonempty cells; domain = period ∩ classified | C7: [DEC-048; K1]
A8: Prediction interval (levels) | B8: b ± t(df_Satt)·sqrt(SE_CR2² + σ²_cluster + σ²_study + ω²_esid) | C8: [A.8 extension, DEC-048]
A9: Pairwise level contrasts | B9: c'b with CR2 var; t = sign·sqrt(F_HTZ), df = Satterthwaite denominator | C9: [DEC-048]
A10: Moderation test (per panel) | B10: HTZ Wald on the difference-in-differences block across levels with both period cells | C10: [D31.5; DEC-048]
A11: Multiplicity | B11: Unadjusted primary + one Holm line over the eight interaction-HTZ p-values | C11: [DEC-048 R7]
A12: M-pre guards (C3/C4) | B12: zi ~ 0 + exposure + exposure:ts_knot, ts_knot = sample_mid − 2015.5, pre domain; HTZ on slope block | C12: [DEC-031c]
A13: regulation3 | B13: end-anchored: = regulation_sample_end; run-time gate post clusters 14/6/11 | C13: [DEC-048 Q11a]
A14: Any-with sensitivity | B14: single C4-M_B refit under ever-treated coding; appendix, descriptive | C14: [DEC-048 Q11b]
A15: Unified V1/V2 | B15: reference coding (refs per DEC-043); interaction blocks admitted by mechanical rule | C15: [DEC-043]
A16: Design-df rule | B16: synthetic-outcome FE fit (sin index; df outcome-invariant under FE/V weights); block df_denom ≥ 5 AND ≥2 post-supported levels | C16: [DEC-043; DEC-049a]
... A19: Identity gates | B19: F65: A5 row by value (1e-9) + pinned aggregate refit (1e-6, df 113); verifier: 3L headline refit vs T1_results (1e-6) | C19: [DEC-031g; DEC-048]

Sheet 3_Interpretation_Guide
A1: Interpretation guide
A2: How to read the reported quantities
A3: Thresholds with citations
A5: Quantity | B5: Meaning | C5: Decision rule
A6: Interaction HTZ p | B6: Does the Paris-period contrast differ across moderator levels? | C6: α = 0.05 unadjusted primary; Holm line disclosed [DEC-048]
A7: descriptive flag | B7: Estimate + CI + df shown; p and t suppressed | C7: cell < 3 clusters [Battery C] or df_Satt < 5 [DEC-024 echo; cf. Tipton & Pustejovsky df guidance]
A8: not_estimable (n.e.) | B8: Planned quantity without support; triggering condition in the note | C8: [P-T5-4; DEC-049]
A9: PI per level | B9: Range for a single new study-level true effect at that level | C9: wider than CI by construction [A.8]
A10: q_planned / q_eff | B10: Interaction columns planned vs. carried by the fit on the CC domain | C10: drops disclosed per block [DEC-043/#27]
A11: Verdict lines | B11: Mechanical outcome only | C11: wording per the resolved gate [DEC-044/DEC-047]

Sheet 4_Formula_Reference
A1: Formula reference — exact calls
A2: As implemented in R/10_moderators.R @ 6e7ce03
A3: Documented template deviation listed below
A5: Quantity | B5: R call / construction | C5: Reference
A6: 3L fit | B6: rma.mv(yi=zi, V=build_V, mods=X, intercept=FALSE, random=~1|cluster_id/study/esid, method="REML", sparse=TRUE, control=ladder) | C6: S6; DEC-031f/A.11
A7: CR2 vcov | B7: vcovCR(fit, cluster=cluster_id, type="CR2") | C7: clubSandwich 0.7.0
A8: Per-coef inference | B8: coef_test(fit, vcov=Vc, test="Satterthwaite") — fields beta/SE/df_Satt/p_Satt | C8: run_meta accessor echo
A9: Block tests | B9: Wald_test(fit, constraints=C, vcov=Vc, test="HTZ") — Fstat/df_num/df_denom/p_val | C9: safe_wald wrapper [DEC-049]
A10: F65 aggregate | B10: aggregate(escalc(...), cluster=cluster_id, struct="CS", rho=0.6) → rma.uni(method="REML", test="knha") | C10: [DEC-031g]
A11: Holm | B11: p.adjust(p_HTZ, "holm") over the finite family | C11: [DEC-048 R7]
A12: Design-df probe | B12: FE fit with yi = sin(1:n); df_denom harvested, F/p never read | C12: [DEC-049a]
A13: TEMPLATE DEVIATION (documented) | B13: Manuscript_Inputs strings are built locale-neutrally via sign/INT/frac/REPT arithmetic instead of TEXT() — robust under LC-independent recalc | C13: C-session pin [§4]

Sheet 5_Data_Provenance
A1: Data provenance & run record
A2: Run 7 (canonical) — seven runs total, six pre-canonical stops, all gate-caught
A3: ERROR_LOG #23–#28; nothing entered committed bytes
A5: Item | B5: Value | C5: Source
A6: Estimation set | B6: 2,713 ES / 115 studies / 114 clusters; period 2,705/113/112; post 711/31/31 | C6: dat_prep.rds; gates
A7: dat_prep md5 | B7: 6702ef3dc45fe0b693b13f50ebd1576b | C7: run_meta
A8: Seed / rho | B8: 20260710 / 0.6 | C8: FROZEN ZONE
A9: Run stamp | B9: 2026-07-29 09:30:52 · elapsed 7.9 min · 24 convergence certificates (all nlminb rung 1) | C9: T7_run_meta.txt
A10: Verifier | B10: V01–V27 all PASS (schema parity to T8, budget 200, 4-key unique, domain pins, F65, 3L identity, single-home, C0 separation) | C10: R/10_verify_outputs.R
A11: Known warnings | B11: three "Redundant predictors dropped" = the exact identity pp = pp:Europe + pp:AsiaPac on the US-free V1 CC post cell (fit, hardening, design probe); mapped, disclosed | C11: [#27/#28]
A12: Hardening refits | B12: V1 max|Δβ| = 3.3e-08 · V2 = 5.1e-07 (< 1e-5) | C12: [A.11]
A13: C0 background | B13: output/T7_background_C0.csv — 56 rows, background-only, absent from results (verifier check) | C13: [r15; K5]
A14: Canonical HEAD | B14: 6e7ce03 (fix 6); canonical bytes = author machine output/ | C14: CC report run 7

Sheet 6_Moderation_Overview
A1: Moderation overview — the eight pre-registered interaction tests
A2: HTZ Wald on the difference-in-differences block per panel [DEC-048]
A3: Unadjusted primary + Holm family line; flags per the small-cell double rule
A5: Panel | B5: F (HTZ) | C5: df | D5: p | E5: Flag | F5: Moderator
A6: C1 | B6: =IF(ISBLANK(INDEX(Results_Long!$M$2:$M$201,MATCH("C1|paris_mid|defined_classified|interaction_HTZ",Results_Long!$AK$2:$AK$201,0))),"n.e.",INDEX(Results_Long!$M$2:$M$201,MATCH("C1|paris_mid|defined_classified|interaction_HTZ",Results_Long!$AK$2:$AK$201,0))) -> 4.5435597 | C6: =IF(ISBLANK(INDEX(Results_Long!$N$2:$N$201,MATCH("C1|paris_mid|defined_classified|interaction_HTZ",Results_Long!$AK$2:$AK$201,0))),"n.e.",INDEX(Results_Long!$N$2:$N$201,MATCH("C1|paris_mid|defined_classified|interaction_HTZ",Results_Long!$AK$2:$AK$201,0))) -> 6.0016344 | D6: =IF(ISBLANK(INDEX(Results_Long!$O$2:$O$201,MATCH("C1|paris_mid|defined_classified|interaction_HTZ",Results_Long!$AK$2:$AK$201,0))),"—",INDEX(Results_Long!$O$2:$O$201,MATCH("C1|paris_mid|defined_classified|interaction_HTZ",Results_Long!$AK$2:$AK$201,0))) -> 0.07703039 | E6: =IF(ISNUMBER(SEARCH("<3-cluster",INDEX(Results_Long!$AJ$2:$AJ$201,MATCH("C1|paris_mid|defined_classified|interaction_HTZ",Results_Long!$AK$2:$AK$201,0)))),"touches <3-cluster cell","") | F6: CER_measure
A7: C2 | B7: =IF(ISBLANK(INDEX(Results_Long!$M$2:$M$201,MATCH("C2|paris_mid|defined_classified|interaction_HTZ",Results_Long!$AK$2:$AK$201,0))),"n.e.",INDEX(Results_Long!$M$2:$M$201,MATCH("C2|paris_mid|defined_classified|interaction_HTZ",Results_Long!$AK$2:$AK$201,0))) -> 0.38881646 | C7: =IF(ISBLANK(INDEX(Results_Long!$N$2:$N$201,MATCH("C2|paris_mid|defined_classified|interaction_HTZ",Results_Long!$AK$2:$AK$201,0))),"n.e.",INDEX(Results_Long!$N$2:$N$201,MATCH("C2|paris_mid|defined_classified|interaction_HTZ",Results_Long!$AK$2:$AK$201,0))) -> 3.0916267 | D7: =IF(ISBLANK(INDEX(Results_Long!$O$2:$O$201,MATCH("C2|paris_mid|defined_classified|interaction_HTZ",Results_Long!$AK$2:$AK$201,0))),"—",INDEX(Results_Long!$O$2:$O$201,MATCH("C2|paris_mid|defined_classified|interaction_HTZ",Results_Long!$AK$2:$AK$201,0))) -> 0.70692718 | E7: =IF(ISNUMBER(SEARCH("<3-cluster",INDEX(Results_Long!$AJ$2:$AJ$201,MATCH("C2|paris_mid|defined_classified|interaction_HTZ",Results_Long!$AK$2:$AK$201,0)))),"touches <3-cluster cell","") | F7: COD_instrument
A8: C3 | B8: =IF(ISBLANK(INDEX(Results_Long!$M$2:$M$201,MATCH("C3|paris_mid|defined_classified|interaction_HTZ",Results_Long!$AK$2:$AK$201,0))),"n.e.",INDEX(Results_Long!$M$2:$M$201,MATCH("C3|paris_mid|defined_classified|interaction_HTZ",Results_Long!$AK$2:$AK$201,0))) -> 0.15811514 | C8: =IF(ISBLANK(INDEX(Results_Long!$N$2:$N$201,MATCH("C3|paris_mid|defined_classified|interaction_HTZ",Results_Long!$AK$2:$AK$201,0))),"n.e.",INDEX(Results_Long!$N$2:$N$201,MATCH("C3|paris_mid|defined_classified|interaction_HTZ",Results_Long!$AK$2:$AK$201,0))) -> 8.7855308 | D8: =IF(ISBLANK(INDEX(Results_Long!$O$2:$O$201,MATCH("C3|paris_mid|defined_classified|interaction_HTZ",Results_Long!$AK$2:$AK$201,0))),"—",INDEX(Results_Long!$O$2:$O$201,MATCH("C3|paris_mid|defined_classified|interaction_HTZ",Results_Long!$AK$2:$AK$201,0))) -> 0.70038592 | E8: =IF(ISNUMBER(SEARCH("<3-cluster",INDEX(Results_Long!$AJ$2:$AJ$201,MATCH("C3|paris_mid|defined_classified|interaction_HTZ",Results_Long!$AK$2:$AK$201,0)))),"touches <3-cluster cell","") | F8: industry
A9: C4 | B9: =IF(ISBLANK(INDEX(Results_Long!$M$2:$M$201,MATCH("C4|paris_mid|defined_classified|interaction_HTZ",Results_Long!$AK$2:$AK$201,0))),"n.e.",INDEX(Results_Long!$M$2:$M$201,MATCH("C4|paris_mid|defined_classified|interaction_HTZ",Results_Long!$AK$2:$AK$201,0))) -> 0.83663292 | C9: =IF(ISBLANK(INDEX(Results_Long!$N$2:$N$201,MATCH("C4|paris_mid|defined_classified|interaction_HTZ",Results_Long!$AK$2:$AK$201,0))),"n.e.",INDEX(Results_Long!$N$2:$N$201,MATCH("C4|paris_mid|defined_classified|interaction_HTZ",Results_Long!$AK$2:$AK$201,0))) -> 9.4938297 | D9: =IF(ISBLANK(INDEX(Results_Long!$O$2:$O$201,MATCH("C4|paris_mid|defined_classified|interaction_HTZ",Results_Long!$AK$2:$AK$201,0))),"—",INDEX(Results_Long!$O$2:$O$201,MATCH("C4|paris_mid|defined_classified|interaction_HTZ",Results_Long!$AK$2:$AK$201,0))) -> 0.38300481 | E9: =IF(ISNUMBER(SEARCH("<3-cluster",INDEX(Results_Long!$AJ$2:$AJ$201,MATCH("C4|paris_mid|defined_classified|interaction_HTZ",Results_Long!$AK$2:$AK$201,0)))),"touches <3-cluster cell","") | F9: regulation3
A10: C5 | B10: =IF(ISBLANK(INDEX(Results_Long!$M$2:$M$201,MATCH("C5|paris_mid|defined_classified|interaction_HTZ",Results_Long!$AK$2:$AK$201,0))),"n.e.",INDEX(Results_Long!$M$2:$M$201,MATCH("C5|paris_mid|defined_classified|interaction_HTZ",Results_Long!$AK$2:$AK$201,0))) -> 0.46062069 | C10: =IF(ISBLANK(INDEX(Results_Long!$N$2:$N$201,MATCH("C5|paris_mid|defined_classified|interaction_HTZ",Results_Long!$AK$2:$AK$201,0))),"n.e.",INDEX(Results_Long!$N$2:$N$201,MATCH("C5|paris_mid|defined_classified|interaction_HTZ",Results_Long!$AK$2:$AK$201,0))) -> 3.3629019 | D10: =IF(ISBLANK(INDEX(Results_Long!$O$2:$O$201,MATCH("C5|paris_mid|defined_classified|interaction_HTZ",Results_Long!$AK$2:$AK$201,0))),"—",INDEX(Results_Long!$O$2:$O$201,MATCH("C5|paris_mid|defined_classified|interaction_HTZ",Results_Long!$AK$2:$AK$201,0))) -> 0.66557314 | E10: =IF(ISNUMBER(SEARCH("<3-cluster",INDEX(Results_Long!$AJ$2:$AJ$201,MATCH("C5|paris_mid|defined_classified|interaction_HTZ",Results_Long!$AK$2:$AK$201,0)))),"touches <3-cluster cell","") -> touches <3-cluster cell | F10: country_region
A11: C6 | B11: =IF(ISBLANK(INDEX(Results_Long!$M$2:$M$201,MATCH("C6|paris_mid|defined_classified|interaction_HTZ",Results_Long!$AK$2:$AK$201,0))),"n.e.",INDEX(Results_Long!$M$2:$M$201,MATCH("C6|paris_mid|defined_classified|interaction_HTZ",Results_Long!$AK$2:$AK$201,0))) -> 3.4928388 | C11: =IF(ISBLANK(INDEX(Results_Long!$N$2:$N$201,MATCH("C6|paris_mid|defined_classified|interaction_HTZ",Results_Long!$AK$2:$AK$201,0))),"n.e.",INDEX(Results_Long!$N$2:$N$201,MATCH("C6|paris_mid|defined_classified|interaction_HTZ",Results_Long!$AK$2:$AK$201,0))) -> 2.2032508 | D11: =IF(ISBLANK(INDEX(Results_Long!$O$2:$O$201,MATCH("C6|paris_mid|defined_classified|interaction_HTZ",Results_Long!$AK$2:$AK$201,0))),"—",INDEX(Results_Long!$O$2:$O$201,MATCH("C6|paris_mid|defined_classified|interaction_HTZ",Results_Long!$AK$2:$AK$201,0))) -> 0.19073471 | E11: =IF(ISNUMBER(SEARCH("<3-cluster",INDEX(Results_Long!$AJ$2:$AJ$201,MATCH("C6|paris_mid|defined_classified|interaction_HTZ",Results_Long!$AK$2:$AK$201,0)))),"touches <3-cluster cell","") | F11: country_econ
A12: C7 | B12: =IF(ISBLANK(INDEX(Results_Long!$M$2:$M$201,MATCH("C7|paris_mid|defined_classified|interaction_HTZ",Results_Long!$AK$2:$AK$201,0))),"n.e.",INDEX(Results_Long!$M$2:$M$201,MATCH("C7|paris_mid|defined_classified|interaction_HTZ",Results_Long!$AK$2:$AK$201,0))) -> 0.067668187 | C12: =IF(ISBLANK(INDEX(Results_Long!$N$2:$N$201,MATCH("C7|paris_mid|defined_classified|interaction_HTZ",Results_Long!$AK$2:$AK$201,0))),"n.e.",INDEX(Results_Long!$N$2:$N$201,MATCH("C7|paris_mid|defined_classified|interaction_HTZ",Results_Long!$AK$2:$AK$201,0))) -> 13.146308 | D12: =IF(ISBLANK(INDEX(Results_Long!$O$2:$O$201,MATCH("C7|paris_mid|defined_classified|interaction_HTZ",Results_Long!$AK$2:$AK$201,0))),"—",INDEX(Results_Long!$O$2:$O$201,MATCH("C7|paris_mid|defined_classified|interaction_HTZ",Results_Long!$AK$2:$AK$201,0))) -> 0.79879242 | E12: =IF(ISNUMBER(SEARCH("<3-cluster",INDEX(Results_Long!$AJ$2:$AJ$201,MATCH("C7|paris_mid|defined_classified|interaction_HTZ",Results_Long!$AK$2:$AK$201,0)))),"touches <3-cluster cell","") | F12: country_culture
A13: C8 | B13: =IF(ISBLANK(INDEX(Results_Long!$M$2:$M$201,MATCH("C8|paris_mid|defined_classified|interaction_HTZ",Results_Long!$AK$2:$AK$201,0))),"n.e.",INDEX(Results_Long!$M$2:$M$201,MATCH("C8|paris_mid|defined_classified|interaction_HTZ",Results_Long!$AK$2:$AK$201,0))) -> 0.44248965 | C13: =IF(ISBLANK(INDEX(Results_Long!$N$2:$N$201,MATCH("C8|paris_mid|defined_classified|interaction_HTZ",Results_Long!$AK$2:$AK$201,0))),"n.e.",INDEX(Results_Long!$N$2:$N$201,MATCH("C8|paris_mid|defined_classified|interaction_HTZ",Results_Long!$AK$2:$AK$201,0))) -> 1.214221 | D13: =IF(ISBLANK(INDEX(Results_Long!$O$2:$O$201,MATCH("C8|paris_mid|defined_classified|interaction_HTZ",Results_Long!$AK$2:$AK$201,0))),"—",INDEX(Results_Long!$O$2:$O$201,MATCH("C8|paris_mid|defined_classified|interaction_HTZ",Results_Long!$AK$2:$AK$201,0))) -> 0.60963825 | E13: =IF(ISNUMBER(SEARCH("<3-cluster",INDEX(Results_Long!$AJ$2:$AJ$201,MATCH("C8|paris_mid|defined_classified|interaction_HTZ",Results_Long!$AK$2:$AK$201,0)))),"touches <3-cluster cell","") -> touches <3-cluster cell | F13: country_legal
A15: Holm (family of 8) | D15: =IF(ISBLANK(INDEX(Results_Long!$AG$2:$AG$201,MATCH("C_family|multiplicity|defined_classified|interaction_HTZ_holm",Results_Long!$AK$2:$AK$201,0))),"n.e.",INDEX(Results_Long!$AG$2:$AG$201,MATCH("C_family|multiplicity|defined_classified|interaction_HTZ_holm",Results_Long!$AK$2:$AK$201,0))) -> 0.61624312 | E15: minimum Holm-adjusted p; per-panel adjusted values in the Results_Long note
A17: Interpretation
A18: No panel reaches the 0.05 level, unadjusted or Holm-adjusted; the closest value is the CER-measurement panel (see 7_Featured_Panels).
A19: Two tests carry the disclosed small-cell flag (C5, C8); both are reported with their own Satterthwaite df.
A20: Under the null-claim framing, unadjusted testing maximises the claim exposure; the Holm line is the pre-registered safeguard [DEC-048].
A22: Question | B22: Answer
A23: Why report unadjusted p-values as primary? | B23: Any chance rejection works against the null claim; unadjusted testing is therefore the stricter presentation, with the Holm family line disclosed alongside [DEC-048 R7].
A24: Why are two tests flagged? | B24: Their difference-in-differences blocks touch a period cell with fewer than three clusters (US x post; common-law x post); HTZ tests are always reported with the flag naming the cell [R6].
A25: Where are the underlying cells? | B25: Per-panel tables in 7_Featured_Panels / 8_Other_Panels; every quantity is formula-linked to Results_Long.
A27: Mechanical outcome: none of the eight pre-registered panel interaction tests is significant at the 0.05 level, unadjusted or Holm-adjusted; wording per the resolved gate [DEC-044/DEC-047].

Sheet 7_Featured_Panels
A1: Featured panels — CER measure, debt instrument, carbon regulation, region
A2: Featured set == V1 moderator set [DEC-043; R1]
A3: All cells formula-linked to Results_Long
A5: C1 — CER_measure
A6: Level (M_A) | B6: r | C6: CI_r low | D6: CI_r high | E6: PI_r low | F6: PI_r high | G6: df
A7: performance | B7: =IF(ISBLANK(INDEX(Results_Long!$T$2:$T$201,MATCH("C1|levels|classified|lvl::performance",Results_Long!$AK$2:$AK$201,0))),"n.e.",INDEX(Results_Long!$T$2:$T$201,MATCH("C1|levels|classified|lvl::performance",Results_Long!$AK$2:$AK$201,0))) -> -0.055821677 | C7: =IF(ISBLANK(INDEX(Results_Long!$U$2:$U$201,MATCH("C1|levels|classified|lvl::performance",Results_Long!$AK$2:$AK$201,0))),"n.e.",INDEX(Results_Long!$U$2:$U$201,MATCH("C1|levels|classified|lvl::performance",Results_Long!$AK$2:$AK$201,0))) -> -0.084626723 | D7: =IF(ISBLANK(INDEX(Results_Long!$V$2:$V$201,MATCH("C1|levels|classified|lvl::performance",Results_Long!$AK$2:$AK$201,0))),"n.e.",INDEX(Results_Long!$V$2:$V$201,MATCH("C1|levels|classified|lvl::performance",Results_Long!$AK$2:$AK$201,0))) -> -0.026923406 | E7: =IF(ISBLANK(INDEX(Results_Long!$W$2:$W$201,MATCH("C1|levels|classified|lvl::performance",Results_Long!$AK$2:$AK$201,0))),"n.e.",INDEX(Results_Long!$W$2:$W$201,MATCH("C1|levels|classified|lvl::performance",Results_Long!$AK$2:$AK$201,0))) -> -0.38826484 | F7: =IF(ISBLANK(INDEX(Results_Long!$X$2:$X$201,MATCH("C1|levels|classified|lvl::performance",Results_Long!$AK$2:$AK$201,0))),"n.e.",INDEX(Results_Long!$X$2:$X$201,MATCH("C1|levels|classified|lvl::performance",Results_Long!$AK$2:$AK$201,0))) -> 0.28947734 | G7: =IF(ISBLANK(INDEX(Results_Long!$N$2:$N$201,MATCH("C1|levels|classified|lvl::performance",Results_Long!$AK$2:$AK$201,0))),"n.e.",INDEX(Results_Long!$N$2:$N$201,MATCH("C1|levels|classified|lvl::performance",Results_Long!$AK$2:$AK$201,0))) -> 109.55901
A8: disclosure | B8: =IF(ISBLANK(INDEX(Results_Long!$T$2:$T$201,MATCH("C1|levels|classified|lvl::disclosure",Results_Long!$AK$2:$AK$201,0))),"n.e.",INDEX(Results_Long!$T$2:$T$201,MATCH("C1|levels|classified|lvl::disclosure",Results_Long!$AK$2:$AK$201,0))) -> -0.068460526 | C8: =IF(ISBLANK(INDEX(Results_Long!$U$2:$U$201,MATCH("C1|levels|classified|lvl::disclosure",Results_Long!$AK$2:$AK$201,0))),"n.e.",INDEX(Results_Long!$U$2:$U$201,MATCH("C1|levels|classified|lvl::disclosure",Results_Long!$AK$2:$AK$201,0))) -> -0.10283801 | D8: =IF(ISBLANK(INDEX(Results_Long!$V$2:$V$201,MATCH("C1|levels|classified|lvl::disclosure",Results_Long!$AK$2:$AK$201,0))),"n.e.",INDEX(Results_Long!$V$2:$V$201,MATCH("C1|levels|classified|lvl::disclosure",Results_Long!$AK$2:$AK$201,0))) -> -0.033919694 | E8: =IF(ISBLANK(INDEX(Results_Long!$W$2:$W$201,MATCH("C1|levels|classified|lvl::disclosure",Results_Long!$AK$2:$AK$201,0))),"n.e.",INDEX(Results_Long!$W$2:$W$201,MATCH("C1|levels|classified|lvl::disclosure",Results_Long!$AK$2:$AK$201,0))) -> -0.40271441 | F8: =IF(ISBLANK(INDEX(Results_Long!$X$2:$X$201,MATCH("C1|levels|classified|lvl::disclosure",Results_Long!$AK$2:$AK$201,0))),"n.e.",INDEX(Results_Long!$X$2:$X$201,MATCH("C1|levels|classified|lvl::disclosure",Results_Long!$AK$2:$AK$201,0))) -> 0.28190377 | G8: =IF(ISBLANK(INDEX(Results_Long!$N$2:$N$201,MATCH("C1|levels|classified|lvl::disclosure",Results_Long!$AK$2:$AK$201,0))),"n.e.",INDEX(Results_Long!$N$2:$N$201,MATCH("C1|levels|classified|lvl::disclosure",Results_Long!$AK$2:$AK$201,0))) -> 54.996246
A10: Paris shift (M_B) | B10: dz (post-pre) | C10: CI_z low | D10: CI_z high | E10: df | F10: p | G10: status
A11: performance | B11: =IF(ISBLANK(INDEX(Results_Long!$K$2:$K$201,MATCH("C1|paris_mid|defined_classified|diff::performance",Results_Long!$AK$2:$AK$201,0))),"n.e.",INDEX(Results_Long!$K$2:$K$201,MATCH("C1|paris_mid|defined_classified|diff::performance",Results_Long!$AK$2:$AK$201,0))) -> 0.021593762 | C11: =IF(ISBLANK(INDEX(Results_Long!$P$2:$P$201,MATCH("C1|paris_mid|defined_classified|diff::performance",Results_Long!$AK$2:$AK$201,0))),"n.e.",INDEX(Results_Long!$P$2:$P$201,MATCH("C1|paris_mid|defined_classified|diff::performance",Results_Long!$AK$2:$AK$201,0))) -> -0.016820001 | D11: =IF(ISBLANK(INDEX(Results_Long!$Q$2:$Q$201,MATCH("C1|paris_mid|defined_classified|diff::performance",Results_Long!$AK$2:$AK$201,0))),"n.e.",INDEX(Results_Long!$Q$2:$Q$201,MATCH("C1|paris_mid|defined_classified|diff::performance",Results_Long!$AK$2:$AK$201,0))) -> 0.060007525 | E11: =IF(ISBLANK(INDEX(Results_Long!$N$2:$N$201,MATCH("C1|paris_mid|defined_classified|diff::performance",Results_Long!$AK$2:$AK$201,0))),"n.e.",INDEX(Results_Long!$N$2:$N$201,MATCH("C1|paris_mid|defined_classified|diff::performance",Results_Long!$AK$2:$AK$201,0))) -> 14.348492 | F11: =IF(ISBLANK(INDEX(Results_Long!$O$2:$O$201,MATCH("C1|paris_mid|defined_classified|diff::performance",Results_Long!$AK$2:$AK$201,0))),"—",INDEX(Results_Long!$O$2:$O$201,MATCH("C1|paris_mid|defined_classified|diff::performance",Results_Long!$AK$2:$AK$201,0))) -> 0.2484811 | G11: =INDEX(Results_Long!$F$2:$F$201,MATCH("C1|paris_mid|defined_classified|diff::performance",Results_Long!$AK$2:$AK$201,0)) -> 3LMA-RVE_CR2
A12: disclosure | B12: =IF(ISBLANK(INDEX(Results_Long!$K$2:$K$201,MATCH("C1|paris_mid|defined_classified|diff::disclosure",Results_Long!$AK$2:$AK$201,0))),"n.e.",INDEX(Results_Long!$K$2:$K$201,MATCH("C1|paris_mid|defined_classified|diff::disclosure",Results_Long!$AK$2:$AK$201,0))) -> -0.036452479 | C12: =IF(ISBLANK(INDEX(Results_Long!$P$2:$P$201,MATCH("C1|paris_mid|defined_classified|diff::disclosure",Results_Long!$AK$2:$AK$201,0))),"n.e.",INDEX(Results_Long!$P$2:$P$201,MATCH("C1|paris_mid|defined_classified|diff::disclosure",Results_Long!$AK$2:$AK$201,0))) -> -0.094282611 | D12: =IF(ISBLANK(INDEX(Results_Long!$Q$2:$Q$201,MATCH("C1|paris_mid|defined_classified|diff::disclosure",Results_Long!$AK$2:$AK$201,0))),"n.e.",INDEX(Results_Long!$Q$2:$Q$201,MATCH("C1|paris_mid|defined_classified|diff::disclosure",Results_Long!$AK$2:$AK$201,0))) -> 0.021377654 | E12: =IF(ISBLANK(INDEX(Results_Long!$N$2:$N$201,MATCH("C1|paris_mid|defined_classified|diff::disclosure",Results_Long!$AK$2:$AK$201,0))),"n.e.",INDEX(Results_Long!$N$2:$N$201,MATCH("C1|paris_mid|defined_classified|diff::disclosure",Results_Long!$AK$2:$AK$201,0))) -> 22.075179 | F12: =IF(ISBLANK(INDEX(Results_Long!$O$2:$O$201,MATCH("C1|paris_mid|defined_classified|diff::disclosure",Results_Long!$AK$2:$AK$201,0))),"—",INDEX(Results_Long!$O$2:$O$201,MATCH("C1|paris_mid|defined_classified|diff::disclosure",Results_Long!$AK$2:$AK$201,0))) -> 0.20467077 | G12: =INDEX(Results_Long!$F$2:$F$201,MATCH("C1|paris_mid|defined_classified|diff::disclosure",Results_Long!$AK$2:$AK$201,0)) -> 3LMA-RVE_CR2
A14: Level contrasts (M_A) | B14: dz | C14: df | D14: p
A15: performance vs disclosure | B15: =IF(ISBLANK(INDEX(Results_Long!$K$2:$K$201,MATCH("C1|levels|classified|pair::performance - disclosure",Results_Long!$AK$2:$AK$201,0))),"n.e.",INDEX(Results_Long!$K$2:$K$201,MATCH("C1|levels|classified|pair::performance - disclosure",Results_Long!$AK$2:$AK$201,0))) -> 0.012688016 | C15: =IF(ISBLANK(INDEX(Results_Long!$N$2:$N$201,MATCH("C1|levels|classified|pair::performance - disclosure",Results_Long!$AK$2:$AK$201,0))),"n.e.",INDEX(Results_Long!$N$2:$N$201,MATCH("C1|levels|classified|pair::performance - disclosure",Results_Long!$AK$2:$AK$201,0))) -> 8.7257163 | D15: =IF(ISBLANK(INDEX(Results_Long!$O$2:$O$201,MATCH("C1|levels|classified|pair::performance - disclosure",Results_Long!$AK$2:$AK$201,0))),"—",INDEX(Results_Long!$O$2:$O$201,MATCH("C1|levels|classified|pair::performance - disclosure",Results_Long!$AK$2:$AK$201,0))) -> 0.42751159
A17: Levels equal (HTZ) | B17: =IF(ISBLANK(INDEX(Results_Long!$M$2:$M$201,MATCH("C1|levels|classified|levels_HTZ",Results_Long!$AK$2:$AK$201,0))),"n.e.",INDEX(Results_Long!$M$2:$M$201,MATCH("C1|levels|classified|levels_HTZ",Results_Long!$AK$2:$AK$201,0))) -> 0.69247038 | C17: =IF(ISBLANK(INDEX(Results_Long!$N$2:$N$201,MATCH("C1|levels|classified|levels_HTZ",Results_Long!$AK$2:$AK$201,0))),"n.e.",INDEX(Results_Long!$N$2:$N$201,MATCH("C1|levels|classified|levels_HTZ",Results_Long!$AK$2:$AK$201,0))) -> 8.7257163 | D17: =IF(ISBLANK(INDEX(Results_Long!$O$2:$O$201,MATCH("C1|levels|classified|levels_HTZ",Results_Long!$AK$2:$AK$201,0))),"—",INDEX(Results_Long!$O$2:$O$201,MATCH("C1|levels|classified|levels_HTZ",Results_Long!$AK$2:$AK$201,0))) -> 0.42751159 | E17: =IF(ISNUMBER(SEARCH("<3-cluster",INDEX(Results_Long!$AJ$2:$AJ$201,MATCH("C1|levels|classified|levels_HTZ",Results_Long!$AK$2:$AK$201,0)))),"touches <3-cluster cell","")
A18: Moderation test (interaction HTZ) | B18: =IF(ISBLANK(INDEX(Results_Long!$M$2:$M$201,MATCH("C1|paris_mid|defined_classified|interaction_HTZ",Results_Long!$AK$2:$AK$201,0))),"n.e.",INDEX(Results_Long!$M$2:$M$201,MATCH("C1|paris_mid|defined_classified|interaction_HTZ",Results_Long!$AK$2:$AK$201,0))) -> 4.5435597 | C18: =IF(ISBLANK(INDEX(Results_Long!$N$2:$N$201,MATCH("C1|paris_mid|defined_classified|interaction_HTZ",Results_Long!$AK$2:$AK$201,0))),"n.e.",INDEX(Results_Long!$N$2:$N$201,MATCH("C1|paris_mid|defined_classified|interaction_HTZ",Results_Long!$AK$2:$AK$201,0))) -> 6.0016344 | D18: =IF(ISBLANK(INDEX(Results_Long!$O$2:$O$201,MATCH("C1|paris_mid|defined_classified|interaction_HTZ",Results_Long!$AK$2:$AK$201,0))),"—",INDEX(Results_Long!$O$2:$O$201,MATCH("C1|paris_mid|defined_classified|interaction_HTZ",Results_Long!$AK$2:$AK$201,0))) -> 0.07703039 | E18: =IF(ISNUMBER(SEARCH("<3-cluster",INDEX(Results_Long!$AJ$2:$AJ$201,MATCH("C1|paris_mid|defined_classified|interaction_HTZ",Results_Long!$AK$2:$AK$201,0)))),"touches <3-cluster cell","")
A21: C2 — COD_instrument
A22: Level (M_A) | B22: r | C22: CI_r low | D22: CI_r high | E22: PI_r low | F22: PI_r high | G22: df
A23: loan (interest rate) | B23: =IF(ISBLANK(INDEX(Results_Long!$T$2:$T$201,MATCH("C2|levels|classified|lvl::loan (interest rate)",Results_Long!$AK$2:$AK$201,0))),"n.e.",INDEX(Results_Long!$T$2:$T$201,MATCH("C2|levels|classified|lvl::loan (interest rate)",Results_Long!$AK$2:$AK$201,0))) -> -0.038311071 | C23: =IF(ISBLANK(INDEX(Results_Long!$U$2:$U$201,MATCH("C2|levels|classified|lvl::loan (interest rate)",Results_Long!$AK$2:$AK$201,0))),"n.e.",INDEX(Results_Long!$U$2:$U$201,MATCH("C2|levels|classified|lvl::loan (interest rate)",Results_Long!$AK$2:$AK$201,0))) -> -0.05728833 | D23: =IF(ISBLANK(INDEX(Results_Long!$V$2:$V$201,MATCH("C2|levels|classified|lvl::loan (interest rate)",Results_Long!$AK$2:$AK$201,0))),"n.e.",INDEX(Results_Long!$V$2:$V$201,MATCH("C2|levels|classified|lvl::loan (interest rate)",Results_Long!$AK$2:$AK$201,0))) -> -0.019306136 | E23: =IF(ISBLANK(INDEX(Results_Long!$W$2:$W$201,MATCH("C2|levels|classified|lvl::loan (interest rate)",Results_Long!$AK$2:$AK$201,0))),"n.e.",INDEX(Results_Long!$W$2:$W$201,MATCH("C2|levels|classified|lvl::loan (interest rate)",Results_Long!$AK$2:$AK$201,0))) -> -0.37381703 | F23: =IF(ISBLANK(INDEX(Results_Long!$X$2:$X$201,MATCH("C2|levels|classified|lvl::loan (interest rate)",Results_Long!$AK$2:$AK$201,0))),"n.e.",INDEX(Results_Long!$X$2:$X$201,MATCH("C2|levels|classified|lvl::loan (interest rate)",Results_Long!$AK$2:$AK$201,0))) -> 0.30606073 | G23: =IF(ISBLANK(INDEX(Results_Long!$N$2:$N$201,MATCH("C2|levels|classified|lvl::loan (interest rate)",Results_Long!$AK$2:$AK$201,0))),"n.e.",INDEX(Results_Long!$N$2:$N$201,MATCH("C2|levels|classified|lvl::loan (interest rate)",Results_Long!$AK$2:$AK$201,0))) -> 64.656366
A24: bond (yield) | B24: =IF(ISBLANK(INDEX(Results_Long!$T$2:$T$201,MATCH("C2|levels|classified|lvl::bond (yield)",Results_Long!$AK$2:$AK$201,0))),"n.e.",INDEX(Results_Long!$T$2:$T$201,MATCH("C2|levels|classified|lvl::bond (yield)",Results_Long!$AK$2:$AK$201,0))) -> -0.09123577 | C24: =IF(ISBLANK(INDEX(Results_Long!$U$2:$U$201,MATCH("C2|levels|classified|lvl::bond (yield)",Results_Long!$AK$2:$AK$201,0))),"n.e.",INDEX(Results_Long!$U$2:$U$201,MATCH("C2|levels|classified|lvl::bond (yield)",Results_Long!$AK$2:$AK$201,0))) -> -0.12164395 | D24: =IF(ISBLANK(INDEX(Results_Long!$V$2:$V$201,MATCH("C2|levels|classified|lvl::bond (yield)",Results_Long!$AK$2:$AK$201,0))),"n.e.",INDEX(Results_Long!$V$2:$V$201,MATCH("C2|levels|classified|lvl::bond (yield)",Results_Long!$AK$2:$AK$201,0))) -> -0.060656497 | E24: =IF(ISBLANK(INDEX(Results_Long!$W$2:$W$201,MATCH("C2|levels|classified|lvl::bond (yield)",Results_Long!$AK$2:$AK$201,0))),"n.e.",INDEX(Results_Long!$W$2:$W$201,MATCH("C2|levels|classified|lvl::bond (yield)",Results_Long!$AK$2:$AK$201,0))) -> -0.4323466 | F24: =IF(ISBLANK(INDEX(Results_Long!$X$2:$X$201,MATCH("C2|levels|classified|lvl::bond (yield)",Results_Long!$AK$2:$AK$201,0))),"n.e.",INDEX(Results_Long!$X$2:$X$201,MATCH("C2|levels|classified|lvl::bond (yield)",Results_Long!$AK$2:$AK$201,0))) -> 0.27271884 | G24: =IF(ISBLANK(INDEX(Results_Long!$N$2:$N$201,MATCH("C2|levels|classified|lvl::bond (yield)",Results_Long!$AK$2:$AK$201,0))),"n.e.",INDEX(Results_Long!$N$2:$N$201,MATCH("C2|levels|classified|lvl::bond (yield)",Results_Long!$AK$2:$AK$201,0))) -> 19.756484
A25: rating | B25: =IF(ISBLANK(INDEX(Results_Long!$T$2:$T$201,MATCH("C2|levels|classified|lvl::rating",Results_Long!$AK$2:$AK$201,0))),"n.e.",INDEX(Results_Long!$T$2:$T$201,MATCH("C2|levels|classified|lvl::rating",Results_Long!$AK$2:$AK$201,0))) -> -0.058177669 | C25: =IF(ISBLANK(INDEX(Results_Long!$U$2:$U$201,MATCH("C2|levels|classified|lvl::rating",Results_Long!$AK$2:$AK$201,0))),"n.e.",INDEX(Results_Long!$U$2:$U$201,MATCH("C2|levels|classified|lvl::rating",Results_Long!$AK$2:$AK$201,0))) -> -0.092042513 | D25: =IF(ISBLANK(INDEX(Results_Long!$V$2:$V$201,MATCH("C2|levels|classified|lvl::rating",Results_Long!$AK$2:$AK$201,0))),"n.e.",INDEX(Results_Long!$V$2:$V$201,MATCH("C2|levels|classified|lvl::rating",Results_Long!$AK$2:$AK$201,0))) -> -0.0241784 | E25: =IF(ISBLANK(INDEX(Results_Long!$W$2:$W$201,MATCH("C2|levels|classified|lvl::rating",Results_Long!$AK$2:$AK$201,0))),"n.e.",INDEX(Results_Long!$W$2:$W$201,MATCH("C2|levels|classified|lvl::rating",Results_Long!$AK$2:$AK$201,0))) -> -0.40044371 | F25: =IF(ISBLANK(INDEX(Results_Long!$X$2:$X$201,MATCH("C2|levels|classified|lvl::rating",Results_Long!$AK$2:$AK$201,0))),"n.e.",INDEX(Results_Long!$X$2:$X$201,MATCH("C2|levels|classified|lvl::rating",Results_Long!$AK$2:$AK$201,0))) -> 0.29833451 | G25: =IF(ISBLANK(INDEX(Results_Long!$N$2:$N$201,MATCH("C2|levels|classified|lvl::rating",Results_Long!$AK$2:$AK$201,0))),"n.e.",INDEX(Results_Long!$N$2:$N$201,MATCH("C2|levels|classified|lvl::rating",Results_Long!$AK$2:$AK$201,0))) -> 25.971986
A26: derivativ (CDS spread) | B26: =IF(ISBLANK(INDEX(Results_Long!$T$2:$T$201,MATCH("C2|levels|classified|lvl::derivativ (CDS spread)",Results_Long!$AK$2:$AK$201,0))),"n.e.",INDEX(Results_Long!$T$2:$T$201,MATCH("C2|levels|classified|lvl::derivativ (CDS spread)",Results_Long!$AK$2:$AK$201,0))) -> -0.12182373 | C26: =IF(ISBLANK(INDEX(Results_Long!$U$2:$U$201,MATCH("C2|levels|classified|lvl::derivativ (CDS spread)",Results_Long!$AK$2:$AK$201,0))),"n.e.",INDEX(Results_Long!$U$2:$U$201,MATCH("C2|levels|classified|lvl::derivativ (CDS spread)",Results_Long!$AK$2:$AK$201,0))) -> -0.30435397 | D26: =IF(ISBLANK(INDEX(Results_Long!$V$2:$V$201,MATCH("C2|levels|classified|lvl::derivativ (CDS spread)",Results_Long!$AK$2:$AK$201,0))),"n.e.",INDEX(Results_Long!$V$2:$V$201,MATCH("C2|levels|classified|lvl::derivativ (CDS spread)",Results_Long!$AK$2:$AK$201,0))) -> 0.069336026 | E26: =IF(ISBLANK(INDEX(Results_Long!$W$2:$W$201,MATCH("C2|levels|classified|lvl::derivativ (CDS spread)",Results_Long!$AK$2:$AK$201,0))),"n.e.",INDEX(Results_Long!$W$2:$W$201,MATCH("C2|levels|classified|lvl::derivativ (CDS spread)",Results_Long!$AK$2:$AK$201,0))) -> -0.52798216 | F26: =IF(ISBLANK(INDEX(Results_Long!$X$2:$X$201,MATCH("C2|levels|classified|lvl::derivativ (CDS spread)",Results_Long!$AK$2:$AK$201,0))),"n.e.",INDEX(Results_Long!$X$2:$X$201,MATCH("C2|levels|classified|lvl::derivativ (CDS spread)",Results_Long!$AK$2:$AK$201,0))) -> 0.32968929 | G26: =IF(ISBLANK(INDEX(Results_Long!$N$2:$N$201,MATCH("C2|levels|classified|lvl::derivativ (CDS spread)",Results_Long!$AK$2:$AK$201,0))),"n.e.",INDEX(Results_Long!$N$2:$N$201,MATCH("C2|levels|classified|lvl::derivativ (CDS spread)",Results_Long!$AK$2:$AK$201,0))) -> 6.6614305
A28: Paris shift (M_B) | B28: dz (post-pre) | C28: CI_z low | D28: CI_z high | E28: df | F28: p | G28: status
A29: loan (interest rate) | B29: =IF(ISBLANK(INDEX(Results_Long!$K$2:$K$201,MATCH("C2|paris_mid|defined_classified|diff::loan (interest rate)",Results_Long!$AK$2:$AK$201,0))),"n.e.",INDEX(Results_Long!$K$2:$K$201,MATCH("C2|paris_mid|defined_classified|diff::loan (interest rate)",Results_Long!$AK$2:$AK$201,0))) -> 0.016284304 | C29: =IF(ISBLANK(INDEX(Results_Long!$P$2:$P$201,MATCH("C2|paris_mid|defined_classified|diff::loan (interest rate)",Results_Long!$AK$2:$AK$201,0))),"n.e.",INDEX(Results_Long!$P$2:$P$201,MATCH("C2|paris_mid|defined_classified|diff::loan (interest rate)",Results_Long!$AK$2:$AK$201,0))) -> -0.039353919 | D29: =IF(ISBLANK(INDEX(Results_Long!$Q$2:$Q$201,MATCH("C2|paris_mid|defined_classified|diff::loan (interest rate)",Results_Long!$AK$2:$AK$201,0))),"n.e.",INDEX(Results_Long!$Q$2:$Q$201,MATCH("C2|paris_mid|defined_classified|diff::loan (interest rate)",Results_Long!$AK$2:$AK$201,0))) -> 0.071922526 | E29: =IF(ISBLANK(INDEX(Results_Long!$N$2:$N$201,MATCH("C2|paris_mid|defined_classified|diff::loan (interest rate)",Results_Long!$AK$2:$AK$201,0))),"n.e.",INDEX(Results_Long!$N$2:$N$201,MATCH("C2|paris_mid|defined_classified|diff::loan (interest rate)",Results_Long!$AK$2:$AK$201,0))) -> 10.296624 | F29: =IF(ISBLANK(INDEX(Results_Long!$O$2:$O$201,MATCH("C2|paris_mid|defined_classified|diff::loan (interest rate)",Results_Long!$AK$2:$AK$201,0))),"—",INDEX(Results_Long!$O$2:$O$201,MATCH("C2|paris_mid|defined_classified|diff::loan (interest rate)",Results_Long!$AK$2:$AK$201,0))) -> 0.53017574 | G29: =INDEX(Results_Long!$F$2:$F$201,MATCH("C2|paris_mid|defined_classified|diff::loan (interest rate)",Results_Long!$AK$2:$AK$201,0)) -> 3LMA-RVE_CR2
A30: bond (yield) | B30: =IF(ISBLANK(INDEX(Results_Long!$K$2:$K$201,MATCH("C2|paris_mid|defined_classified|diff::bond (yield)",Results_Long!$AK$2:$AK$201,0))),"n.e.",INDEX(Results_Long!$K$2:$K$201,MATCH("C2|paris_mid|defined_classified|diff::bond (yield)",Results_Long!$AK$2:$AK$201,0))) -> -0.050736876 | C30: =IF(ISBLANK(INDEX(Results_Long!$P$2:$P$201,MATCH("C2|paris_mid|defined_classified|diff::bond (yield)",Results_Long!$AK$2:$AK$201,0))),"n.e.",INDEX(Results_Long!$P$2:$P$201,MATCH("C2|paris_mid|defined_classified|diff::bond (yield)",Results_Long!$AK$2:$AK$201,0))) -> -0.20339482 | D30: =IF(ISBLANK(INDEX(Results_Long!$Q$2:$Q$201,MATCH("C2|paris_mid|defined_classified|diff::bond (yield)",Results_Long!$AK$2:$AK$201,0))),"n.e.",INDEX(Results_Long!$Q$2:$Q$201,MATCH("C2|paris_mid|defined_classified|diff::bond (yield)",Results_Long!$AK$2:$AK$201,0))) -> 0.10192107 | E30: =IF(ISBLANK(INDEX(Results_Long!$N$2:$N$201,MATCH("C2|paris_mid|defined_classified|diff::bond (yield)",Results_Long!$AK$2:$AK$201,0))),"n.e.",INDEX(Results_Long!$N$2:$N$201,MATCH("C2|paris_mid|defined_classified|diff::bond (yield)",Results_Long!$AK$2:$AK$201,0))) -> 9.127122 | F30: =IF(ISBLANK(INDEX(Results_Long!$O$2:$O$201,MATCH("C2|paris_mid|defined_classified|diff::bond (yield)",Results_Long!$AK$2:$AK$201,0))),"—",INDEX(Results_Long!$O$2:$O$201,MATCH("C2|paris_mid|defined_classified|diff::bond (yield)",Results_Long!$AK$2:$AK$201,0))) -> 0.47200107 | G30: =INDEX(Results_Long!$F$2:$F$201,MATCH("C2|paris_mid|defined_classified|diff::bond (yield)",Results_Long!$AK$2:$AK$201,0)) -> 3LMA-RVE_CR2
A31: rating | B31: =IF(ISBLANK(INDEX(Results_Long!$K$2:$K$201,MATCH("C2|paris_mid|defined_classified|diff::rating",Results_Long!$AK$2:$AK$201,0))),"n.e.",INDEX(Results_Long!$K$2:$K$201,MATCH("C2|paris_mid|defined_classified|diff::rating",Results_Long!$AK$2:$AK$201,0))) -> 0.052570446 | C31: =IF(ISBLANK(INDEX(Results_Long!$P$2:$P$201,MATCH("C2|paris_mid|defined_classified|diff::rating",Results_Long!$AK$2:$AK$201,0))),"n.e.",INDEX(Results_Long!$P$2:$P$201,MATCH("C2|paris_mid|defined_classified|diff::rating",Results_Long!$AK$2:$AK$201,0))) -> -0.2828952 | D31: =IF(ISBLANK(INDEX(Results_Long!$Q$2:$Q$201,MATCH("C2|paris_mid|defined_classified|diff::rating",Results_Long!$AK$2:$AK$201,0))),"n.e.",INDEX(Results_Long!$Q$2:$Q$201,MATCH("C2|paris_mid|defined_classified|diff::rating",Results_Long!$AK$2:$AK$201,0))) -> 0.38803609 | E31: =IF(ISBLANK(INDEX(Results_Long!$N$2:$N$201,MATCH("C2|paris_mid|defined_classified|diff::rating",Results_Long!$AK$2:$AK$201,0))),"n.e.",INDEX(Results_Long!$N$2:$N$201,MATCH("C2|paris_mid|defined_classified|diff::rating",Results_Long!$AK$2:$AK$201,0))) -> 4.1545139 | F31: =IF(ISBLANK(INDEX(Results_Long!$O$2:$O$201,MATCH("C2|paris_mid|defined_classified|diff::rating",Results_Long!$AK$2:$AK$201,0))),"—",INDEX(Results_Long!$O$2:$O$201,MATCH("C2|paris_mid|defined_classified|diff::rating",Results_Long!$AK$2:$AK$201,0))) -> — | G31: =INDEX(Results_Long!$F$2:$F$201,MATCH("C2|paris_mid|defined_classified|diff::rating",Results_Long!$AK$2:$AK$201,0)) -> 3LMA-RVE_CR2
A32: derivativ (CDS spread) | B32: =IF(ISBLANK(INDEX(Results_Long!$K$2:$K$201,MATCH("C2|paris_mid|defined_classified|diff::derivativ (CDS spread)",Results_Long!$AK$2:$AK$201,0))),"n.e.",INDEX(Results_Long!$K$2:$K$201,MATCH("C2|paris_mid|defined_classified|diff::derivativ (CDS spread)",Results_Long!$AK$2:$AK$201,0))) -> n.e. | C32: =IF(ISBLANK(INDEX(Results_Long!$P$2:$P$201,MATCH("C2|paris_mid|defined_classified|diff::derivativ (CDS spread)",Results_Long!$AK$2:$AK$201,0))),"n.e.",INDEX(Results_Long!$P$2:$P$201,MATCH("C2|paris_mid|defined_classified|diff::derivativ (CDS spread)",Results_Long!$AK$2:$AK$201,0))) -> n.e. | D32: =IF(ISBLANK(INDEX(Results_Long!$Q$2:$Q$201,MATCH("C2|paris_mid|defined_classified|diff::derivativ (CDS spread)",Results_Long!$AK$2:$AK$201,0))),"n.e.",INDEX(Results_Long!$Q$2:$Q$201,MATCH("C2|paris_mid|defined_classified|diff::derivativ (CDS spread)",Results_Long!$AK$2:$AK$201,0))) -> n.e. | E32: =IF(ISBLANK(INDEX(Results_Long!$N$2:$N$201,MATCH("C2|paris_mid|defined_classified|diff::derivativ (CDS spread)",Results_Long!$AK$2:$AK$201,0))),"n.e.",INDEX(Results_Long!$N$2:$N$201,MATCH("C2|paris_mid|defined_classified|diff::derivativ (CDS spread)",Results_Long!$AK$2:$AK$201,0))) -> n.e. | F32: =IF(ISBLANK(INDEX(Results_Long!$O$2:$O$201,MATCH("C2|paris_mid|defined_classified|diff::derivativ (CDS spread)",Results_Long!$AK$2:$AK$201,0))),"—",INDEX(Results_Long!$O$2:$O$201,MATCH("C2|paris_mid|defined_classified|diff::derivativ (CDS spread)",Results_Long!$AK$2:$AK$201,0))) -> — | G32: =INDEX(Results_Long!$F$2:$F$201,MATCH("C2|paris_mid|defined_classified|diff::derivativ (CDS spread)",Results_Long!$AK$2:$AK$201,0)) -> not_estimable
A34: Level contrasts (M_A) | B34: dz | C34: df | D34: p
A35: loan (interest rate) vs bond (yield) | B35: =IF(ISBLANK(INDEX(Results_Long!$K$2:$K$201,MATCH("C2|levels|classified|pair::loan (interest rate) - bond (yield)",Results_Long!$AK$2:$AK$201,0))),"n.e.",INDEX(Results_Long!$K$2:$K$201,MATCH("C2|levels|classified|pair::loan (interest rate) - bond (yield)",Results_Long!$AK$2:$AK$201,0))) -> 0.053160359 | C35: =IF(ISBLANK(INDEX(Results_Long!$N$2:$N$201,MATCH("C2|levels|classified|pair::loan (interest rate) - bond (yield)",Results_Long!$AK$2:$AK$201,0))),"n.e.",INDEX(Results_Long!$N$2:$N$201,MATCH("C2|levels|classified|pair::loan (interest rate) - bond (yield)",Results_Long!$AK$2:$AK$201,0))) -> 7.6978478 | D35: =IF(ISBLANK(INDEX(Results_Long!$O$2:$O$201,MATCH("C2|levels|classified|pair::loan (interest rate) - bond (yield)",Results_Long!$AK$2:$AK$201,0))),"—",INDEX(Results_Long!$O$2:$O$201,MATCH("C2|levels|classified|pair::loan (interest rate) - bond (yield)",Results_Long!$AK$2:$AK$201,0))) -> 0.0090785143
A36: loan (interest rate) vs rating | B36: =IF(ISBLANK(INDEX(Results_Long!$K$2:$K$201,MATCH("C2|levels|classified|pair::loan (interest rate) - rating",Results_Long!$AK$2:$AK$201,0))),"n.e.",INDEX(Results_Long!$K$2:$K$201,MATCH("C2|levels|classified|pair::loan (interest rate) - rating",Results_Long!$AK$2:$AK$201,0))) -> 0.019913609 | C36: =IF(ISBLANK(INDEX(Results_Long!$N$2:$N$201,MATCH("C2|levels|classified|pair::loan (interest rate) - rating",Results_Long!$AK$2:$AK$201,0))),"n.e.",INDEX(Results_Long!$N$2:$N$201,MATCH("C2|levels|classified|pair::loan (interest rate) - rating",Results_Long!$AK$2:$AK$201,0))) -> 6.6077537 | D36: =IF(ISBLANK(INDEX(Results_Long!$O$2:$O$201,MATCH("C2|levels|classified|pair::loan (interest rate) - rating",Results_Long!$AK$2:$AK$201,0))),"—",INDEX(Results_Long!$O$2:$O$201,MATCH("C2|levels|classified|pair::loan (interest rate) - rating",Results_Long!$AK$2:$AK$201,0))) -> 0.25366692
A37: loan (interest rate) vs derivativ (CDS spread) | B37: =IF(ISBLANK(INDEX(Results_Long!$K$2:$K$201,MATCH("C2|levels|classified|pair::loan (interest rate) - derivativ (CDS spread)",Results_Long!$AK$2:$AK$201,0))),"n.e.",INDEX(Results_Long!$K$2:$K$201,MATCH("C2|levels|classified|pair::loan (interest rate) - derivativ (CDS spread)",Results_Long!$AK$2:$AK$201,0))) -> 0.084101991 | C37: =IF(ISBLANK(INDEX(Results_Long!$N$2:$N$201,MATCH("C2|levels|classified|pair::loan (interest rate) - derivativ (CDS spread)",Results_Long!$AK$2:$AK$201,0))),"n.e.",INDEX(Results_Long!$N$2:$N$201,MATCH("C2|levels|classified|pair::loan (interest rate) - derivativ (CDS spread)",Results_Long!$AK$2:$AK$201,0))) -> 6.734945 | D37: =IF(ISBLANK(INDEX(Results_Long!$O$2:$O$201,MATCH("C2|levels|classified|pair::loan (interest rate) - derivativ (CDS spread)",Results_Long!$AK$2:$AK$201,0))),"—",INDEX(Results_Long!$O$2:$O$201,MATCH("C2|levels|classified|pair::loan (interest rate) - derivativ (CDS spread)",Results_Long!$AK$2:$AK$201,0))) -> 0.30907587
A38: bond (yield) vs rating | B38: =IF(ISBLANK(INDEX(Results_Long!$K$2:$K$201,MATCH("C2|levels|classified|pair::bond (yield) - rating",Results_Long!$AK$2:$AK$201,0))),"n.e.",INDEX(Results_Long!$K$2:$K$201,MATCH("C2|levels|classified|pair::bond (yield) - rating",Results_Long!$AK$2:$AK$201,0))) -> -0.03324675 | C38: =IF(ISBLANK(INDEX(Results_Long!$N$2:$N$201,MATCH("C2|levels|classified|pair::bond (yield) - rating",Results_Long!$AK$2:$AK$201,0))),"n.e.",INDEX(Results_Long!$N$2:$N$201,MATCH("C2|levels|classified|pair::bond (yield) - rating",Results_Long!$AK$2:$AK$201,0))) -> 2.1134522 | D38: =IF(ISBLANK(INDEX(Results_Long!$O$2:$O$201,MATCH("C2|levels|classified|pair::bond (yield) - rating",Results_Long!$AK$2:$AK$201,0))),"—",INDEX(Results_Long!$O$2:$O$201,MATCH("C2|levels|classified|pair::bond (yield) - rating",Results_Long!$AK$2:$AK$201,0))) -> —
A39: bond (yield) vs derivativ (CDS spread) | B39: =IF(ISBLANK(INDEX(Results_Long!$K$2:$K$201,MATCH("C2|levels|classified|pair::bond (yield) - derivativ (CDS spread)",Results_Long!$AK$2:$AK$201,0))),"n.e.",INDEX(Results_Long!$K$2:$K$201,MATCH("C2|levels|classified|pair::bond (yield) - derivativ (CDS spread)",Results_Long!$AK$2:$AK$201,0))) -> 0.030941632 | C39: =IF(ISBLANK(INDEX(Results_Long!$N$2:$N$201,MATCH("C2|levels|classified|pair::bond (yield) - derivativ (CDS spread)",Results_Long!$AK$2:$AK$201,0))),"n.e.",INDEX(Results_Long!$N$2:$N$201,MATCH("C2|levels|classified|pair::bond (yield) - derivativ (CDS spread)",Results_Long!$AK$2:$AK$201,0))) -> 5.9932112 | D39: =IF(ISBLANK(INDEX(Results_Long!$O$2:$O$201,MATCH("C2|levels|classified|pair::bond (yield) - derivativ (CDS spread)",Results_Long!$AK$2:$AK$201,0))),"—",INDEX(Results_Long!$O$2:$O$201,MATCH("C2|levels|classified|pair::bond (yield) - derivativ (CDS spread)",Results_Long!$AK$2:$AK$201,0))) -> 0.68748068
A40: rating vs derivativ (CDS spread) | B40: =IF(ISBLANK(INDEX(Results_Long!$K$2:$K$201,MATCH("C2|levels|classified|pair::rating - derivativ (CDS spread)",Results_Long!$AK$2:$AK$201,0))),"n.e.",INDEX(Results_Long!$K$2:$K$201,MATCH("C2|levels|classified|pair::rating - derivativ (CDS spread)",Results_Long!$AK$2:$AK$201,0))) -> 0.064188382 | C40: =IF(ISBLANK(INDEX(Results_Long!$N$2:$N$201,MATCH("C2|levels|classified|pair::rating - derivativ (CDS spread)",Results_Long!$AK$2:$AK$201,0))),"n.e.",INDEX(Results_Long!$N$2:$N$201,MATCH("C2|levels|classified|pair::rating - derivativ (CDS spread)",Results_Long!$AK$2:$AK$201,0))) -> 4.5405051 | D40: =IF(ISBLANK(INDEX(Results_Long!$O$2:$O$201,MATCH("C2|levels|classified|pair::rating - derivativ (CDS spread)",Results_Long!$AK$2:$AK$201,0))),"—",INDEX(Results_Long!$O$2:$O$201,MATCH("C2|levels|classified|pair::rating - derivativ (CDS spread)",Results_Long!$AK$2:$AK$201,0))) -> —
A42: Levels equal (HTZ) | B42: =IF(ISBLANK(INDEX(Results_Long!$M$2:$M$201,MATCH("C2|levels|classified|levels_HTZ",Results_Long!$AK$2:$AK$201,0))),"n.e.",INDEX(Results_Long!$M$2:$M$201,MATCH("C2|levels|classified|levels_HTZ",Results_Long!$AK$2:$AK$201,0))) -> 3.4289985 | C42: =IF(ISBLANK(INDEX(Results_Long!$N$2:$N$201,MATCH("C2|levels|classified|levels_HTZ",Results_Long!$AK$2:$AK$201,0))),"n.e.",INDEX(Results_Long!$N$2:$N$201,MATCH("C2|levels|classified|levels_HTZ",Results_Long!$AK$2:$AK$201,0))) -> 4.7796082 | D42: =IF(ISBLANK(INDEX(Results_Long!$O$2:$O$201,MATCH("C2|levels|classified|levels_HTZ",Results_Long!$AK$2:$AK$201,0))),"—",INDEX(Results_Long!$O$2:$O$201,MATCH("C2|levels|classified|levels_HTZ",Results_Long!$AK$2:$AK$201,0))) -> 0.11339224 | E42: =IF(ISNUMBER(SEARCH("<3-cluster",INDEX(Results_Long!$AJ$2:$AJ$201,MATCH("C2|levels|classified|levels_HTZ",Results_Long!$AK$2:$AK$201,0)))),"touches <3-cluster cell","")
A43: Moderation test (interaction HTZ) | B43: =IF(ISBLANK(INDEX(Results_Long!$M$2:$M$201,MATCH("C2|paris_mid|defined_classified|interaction_HTZ",Results_Long!$AK$2:$AK$201,0))),"n.e.",INDEX(Results_Long!$M$2:$M$201,MATCH("C2|paris_mid|defined_classified|interaction_HTZ",Results_Long!$AK$2:$AK$201,0))) -> 0.38881646 | C43: =IF(ISBLANK(INDEX(Results_Long!$N$2:$N$201,MATCH("C2|paris_mid|defined_classified|interaction_HTZ",Results_Long!$AK$2:$AK$201,0))),"n.e.",INDEX(Results_Long!$N$2:$N$201,MATCH("C2|paris_mid|defined_classified|interaction_HTZ",Results_Long!$AK$2:$AK$201,0))) -> 3.0916267 | D43: =IF(ISBLANK(INDEX(Results_Long!$O$2:$O$201,MATCH("C2|paris_mid|defined_classified|interaction_HTZ",Results_Long!$AK$2:$AK$201,0))),"—",INDEX(Results_Long!$O$2:$O$201,MATCH("C2|paris_mid|defined_classified|interaction_HTZ",Results_Long!$AK$2:$AK$201,0))) -> 0.70692718 | E43: =IF(ISNUMBER(SEARCH("<3-cluster",INDEX(Results_Long!$AJ$2:$AJ$201,MATCH("C2|paris_mid|defined_classified|interaction_HTZ",Results_Long!$AK$2:$AK$201,0)))),"touches <3-cluster cell","")
A46: C4 — regulation3
A47: Level (M_A) | B47: r | C47: CI_r low | D47: CI_r high | E47: PI_r low | F47: PI_r high | G47: df
A48: without ETS/CT | B48: =IF(ISBLANK(INDEX(Results_Long!$T$2:$T$201,MATCH("C4|levels|classified|lvl::without ETS/CT",Results_Long!$AK$2:$AK$201,0))),"n.e.",INDEX(Results_Long!$T$2:$T$201,MATCH("C4|levels|classified|lvl::without ETS/CT",Results_Long!$AK$2:$AK$201,0))) -> -0.063156914 | C48: =IF(ISBLANK(INDEX(Results_Long!$U$2:$U$201,MATCH("C4|levels|classified|lvl::without ETS/CT",Results_Long!$AK$2:$AK$201,0))),"n.e.",INDEX(Results_Long!$U$2:$U$201,MATCH("C4|levels|classified|lvl::without ETS/CT",Results_Long!$AK$2:$AK$201,0))) -> -0.093044155 | D48: =IF(ISBLANK(INDEX(Results_Long!$V$2:$V$201,MATCH("C4|levels|classified|lvl::without ETS/CT",Results_Long!$AK$2:$AK$201,0))),"n.e.",INDEX(Results_Long!$V$2:$V$201,MATCH("C4|levels|classified|lvl::without ETS/CT",Results_Long!$AK$2:$AK$201,0))) -> -0.033155961 | E48: =IF(ISBLANK(INDEX(Results_Long!$W$2:$W$201,MATCH("C4|levels|classified|lvl::without ETS/CT",Results_Long!$AK$2:$AK$201,0))),"n.e.",INDEX(Results_Long!$W$2:$W$201,MATCH("C4|levels|classified|lvl::without ETS/CT",Results_Long!$AK$2:$AK$201,0))) -> -0.43565115 | F48: =IF(ISBLANK(INDEX(Results_Long!$X$2:$X$201,MATCH("C4|levels|classified|lvl::without ETS/CT",Results_Long!$AK$2:$AK$201,0))),"n.e.",INDEX(Results_Long!$X$2:$X$201,MATCH("C4|levels|classified|lvl::without ETS/CT",Results_Long!$AK$2:$AK$201,0))) -> 0.32780626 | G48: =IF(ISBLANK(INDEX(Results_Long!$N$2:$N$201,MATCH("C4|levels|classified|lvl::without ETS/CT",Results_Long!$AK$2:$AK$201,0))),"n.e.",INDEX(Results_Long!$N$2:$N$201,MATCH("C4|levels|classified|lvl::without ETS/CT",Results_Long!$AK$2:$AK$201,0))) -> 48.487822
A49: with ETS/CT | B49: =IF(ISBLANK(INDEX(Results_Long!$T$2:$T$201,MATCH("C4|levels|classified|lvl::with ETS/CT",Results_Long!$AK$2:$AK$201,0))),"n.e.",INDEX(Results_Long!$T$2:$T$201,MATCH("C4|levels|classified|lvl::with ETS/CT",Results_Long!$AK$2:$AK$201,0))) -> -0.068100162 | C49: =IF(ISBLANK(INDEX(Results_Long!$U$2:$U$201,MATCH("C4|levels|classified|lvl::with ETS/CT",Results_Long!$AK$2:$AK$201,0))),"n.e.",INDEX(Results_Long!$U$2:$U$201,MATCH("C4|levels|classified|lvl::with ETS/CT",Results_Long!$AK$2:$AK$201,0))) -> -0.14287093 | D49: =IF(ISBLANK(INDEX(Results_Long!$V$2:$V$201,MATCH("C4|levels|classified|lvl::with ETS/CT",Results_Long!$AK$2:$AK$201,0))),"n.e.",INDEX(Results_Long!$V$2:$V$201,MATCH("C4|levels|classified|lvl::with ETS/CT",Results_Long!$AK$2:$AK$201,0))) -> 0.007443518 | E49: =IF(ISBLANK(INDEX(Results_Long!$W$2:$W$201,MATCH("C4|levels|classified|lvl::with ETS/CT",Results_Long!$AK$2:$AK$201,0))),"n.e.",INDEX(Results_Long!$W$2:$W$201,MATCH("C4|levels|classified|lvl::with ETS/CT",Results_Long!$AK$2:$AK$201,0))) -> -0.46104593 | F49: =IF(ISBLANK(INDEX(Results_Long!$X$2:$X$201,MATCH("C4|levels|classified|lvl::with ETS/CT",Results_Long!$AK$2:$AK$201,0))),"n.e.",INDEX(Results_Long!$X$2:$X$201,MATCH("C4|levels|classified|lvl::with ETS/CT",Results_Long!$AK$2:$AK$201,0))) -> 0.34717438 | G49: =IF(ISBLANK(INDEX(Results_Long!$N$2:$N$201,MATCH("C4|levels|classified|lvl::with ETS/CT",Results_Long!$AK$2:$AK$201,0))),"n.e.",INDEX(Results_Long!$N$2:$N$201,MATCH("C4|levels|classified|lvl::with ETS/CT",Results_Long!$AK$2:$AK$201,0))) -> 16.35057
A51: Paris shift (M_B) | B51: dz (post-pre) | C51: CI_z low | D51: CI_z high | E51: df | F51: p | G51: status
A52: without ETS/CT | B52: =IF(ISBLANK(INDEX(Results_Long!$K$2:$K$201,MATCH("C4|paris_mid|defined_classified|diff::without ETS/CT",Results_Long!$AK$2:$AK$201,0))),"n.e.",INDEX(Results_Long!$K$2:$K$201,MATCH("C4|paris_mid|defined_classified|diff::without ETS/CT",Results_Long!$AK$2:$AK$201,0))) -> -0.013785907 | C52: =IF(ISBLANK(INDEX(Results_Long!$P$2:$P$201,MATCH("C4|paris_mid|defined_classified|diff::without ETS/CT",Results_Long!$AK$2:$AK$201,0))),"n.e.",INDEX(Results_Long!$P$2:$P$201,MATCH("C4|paris_mid|defined_classified|diff::without ETS/CT",Results_Long!$AK$2:$AK$201,0))) -> -0.083456451 | D52: =IF(ISBLANK(INDEX(Results_Long!$Q$2:$Q$201,MATCH("C4|paris_mid|defined_classified|diff::without ETS/CT",Results_Long!$AK$2:$AK$201,0))),"n.e.",INDEX(Results_Long!$Q$2:$Q$201,MATCH("C4|paris_mid|defined_classified|diff::without ETS/CT",Results_Long!$AK$2:$AK$201,0))) -> 0.055884637 | E52: =IF(ISBLANK(INDEX(Results_Long!$N$2:$N$201,MATCH("C4|paris_mid|defined_classified|diff::without ETS/CT",Results_Long!$AK$2:$AK$201,0))),"n.e.",INDEX(Results_Long!$N$2:$N$201,MATCH("C4|paris_mid|defined_classified|diff::without ETS/CT",Results_Long!$AK$2:$AK$201,0))) -> 5.9953518 | F52: =IF(ISBLANK(INDEX(Results_Long!$O$2:$O$201,MATCH("C4|paris_mid|defined_classified|diff::without ETS/CT",Results_Long!$AK$2:$AK$201,0))),"—",INDEX(Results_Long!$O$2:$O$201,MATCH("C4|paris_mid|defined_classified|diff::without ETS/CT",Results_Long!$AK$2:$AK$201,0))) -> 0.64537731 | G52: =INDEX(Results_Long!$F$2:$F$201,MATCH("C4|paris_mid|defined_classified|diff::without ETS/CT",Results_Long!$AK$2:$AK$201,0)) -> 3LMA-RVE_CR2
A53: with ETS/CT | B53: =IF(ISBLANK(INDEX(Results_Long!$K$2:$K$201,MATCH("C4|paris_mid|defined_classified|diff::with ETS/CT",Results_Long!$AK$2:$AK$201,0))),"n.e.",INDEX(Results_Long!$K$2:$K$201,MATCH("C4|paris_mid|defined_classified|diff::with ETS/CT",Results_Long!$AK$2:$AK$201,0))) -> 0.047411264 | C53: =IF(ISBLANK(INDEX(Results_Long!$P$2:$P$201,MATCH("C4|paris_mid|defined_classified|diff::with ETS/CT",Results_Long!$AK$2:$AK$201,0))),"n.e.",INDEX(Results_Long!$P$2:$P$201,MATCH("C4|paris_mid|defined_classified|diff::with ETS/CT",Results_Long!$AK$2:$AK$201,0))) -> -0.1148226 | D53: =IF(ISBLANK(INDEX(Results_Long!$Q$2:$Q$201,MATCH("C4|paris_mid|defined_classified|diff::with ETS/CT",Results_Long!$AK$2:$AK$201,0))),"n.e.",INDEX(Results_Long!$Q$2:$Q$201,MATCH("C4|paris_mid|defined_classified|diff::with ETS/CT",Results_Long!$AK$2:$AK$201,0))) -> 0.20964513 | E53: =IF(ISBLANK(INDEX(Results_Long!$N$2:$N$201,MATCH("C4|paris_mid|defined_classified|diff::with ETS/CT",Results_Long!$AK$2:$AK$201,0))),"n.e.",INDEX(Results_Long!$N$2:$N$201,MATCH("C4|paris_mid|defined_classified|diff::with ETS/CT",Results_Long!$AK$2:$AK$201,0))) -> 5.8548168 | F53: =IF(ISBLANK(INDEX(Results_Long!$O$2:$O$201,MATCH("C4|paris_mid|defined_classified|diff::with ETS/CT",Results_Long!$AK$2:$AK$201,0))),"—",INDEX(Results_Long!$O$2:$O$201,MATCH("C4|paris_mid|defined_classified|diff::with ETS/CT",Results_Long!$AK$2:$AK$201,0))) -> 0.49958477 | G53: =INDEX(Results_Long!$F$2:$F$201,MATCH("C4|paris_mid|defined_classified|diff::with ETS/CT",Results_Long!$AK$2:$AK$201,0)) -> 3LMA-RVE_CR2
A55: Level contrasts (M_A) | B55: dz | C55: df | D55: p
A56: without ETS/CT vs with ETS/CT | B56: =IF(ISBLANK(INDEX(Results_Long!$K$2:$K$201,MATCH("C4|levels|classified|pair::without ETS/CT - with ETS/CT",Results_Long!$AK$2:$AK$201,0))),"n.e.",INDEX(Results_Long!$K$2:$K$201,MATCH("C4|levels|classified|pair::without ETS/CT - with ETS/CT",Results_Long!$AK$2:$AK$201,0))) -> 0.0049646411 | C56: =IF(ISBLANK(INDEX(Results_Long!$N$2:$N$201,MATCH("C4|levels|classified|pair::without ETS/CT - with ETS/CT",Results_Long!$AK$2:$AK$201,0))),"n.e.",INDEX(Results_Long!$N$2:$N$201,MATCH("C4|levels|classified|pair::without ETS/CT - with ETS/CT",Results_Long!$AK$2:$AK$201,0))) -> 3.9178449 | D56: =IF(ISBLANK(INDEX(Results_Long!$O$2:$O$201,MATCH("C4|levels|classified|pair::without ETS/CT - with ETS/CT",Results_Long!$AK$2:$AK$201,0))),"—",INDEX(Results_Long!$O$2:$O$201,MATCH("C4|levels|classified|pair::without ETS/CT - with ETS/CT",Results_Long!$AK$2:$AK$201,0))) -> —
A58: Levels equal (HTZ) | B58: =IF(ISBLANK(INDEX(Results_Long!$M$2:$M$201,MATCH("C4|levels|classified|levels_HTZ",Results_Long!$AK$2:$AK$201,0))),"n.e.",INDEX(Results_Long!$M$2:$M$201,MATCH("C4|levels|classified|levels_HTZ",Results_Long!$AK$2:$AK$201,0))) -> 0.032125917 | C58: =IF(ISBLANK(INDEX(Results_Long!$N$2:$N$201,MATCH("C4|levels|classified|levels_HTZ",Results_Long!$AK$2:$AK$201,0))),"n.e.",INDEX(Results_Long!$N$2:$N$201,MATCH("C4|levels|classified|levels_HTZ",Results_Long!$AK$2:$AK$201,0))) -> 3.9178449 | D58: =IF(ISBLANK(INDEX(Results_Long!$O$2:$O$201,MATCH("C4|levels|classified|levels_HTZ",Results_Long!$AK$2:$AK$201,0))),"—",INDEX(Results_Long!$O$2:$O$201,MATCH("C4|levels|classified|levels_HTZ",Results_Long!$AK$2:$AK$201,0))) -> 0.86663797 | E58: =IF(ISNUMBER(SEARCH("<3-cluster",INDEX(Results_Long!$AJ$2:$AJ$201,MATCH("C4|levels|classified|levels_HTZ",Results_Long!$AK$2:$AK$201,0)))),"touches <3-cluster cell","")
A59: Moderation test (interaction HTZ) | B59: =IF(ISBLANK(INDEX(Results_Long!$M$2:$M$201,MATCH("C4|paris_mid|defined_classified|interaction_HTZ",Results_Long!$AK$2:$AK$201,0))),"n.e.",INDEX(Results_Long!$M$2:$M$201,MATCH("C4|paris_mid|defined_classified|interaction_HTZ",Results_Long!$AK$2:$AK$201,0))) -> 0.83663292 | C59: =IF(ISBLANK(INDEX(Results_Long!$N$2:$N$201,MATCH("C4|paris_mid|defined_classified|interaction_HTZ",Results_Long!$AK$2:$AK$201,0))),"n.e.",INDEX(Results_Long!$N$2:$N$201,MATCH("C4|paris_mid|defined_classified|interaction_HTZ",Results_Long!$AK$2:$AK$201,0))) -> 9.4938297 | D59: =IF(ISBLANK(INDEX(Results_Long!$O$2:$O$201,MATCH("C4|paris_mid|defined_classified|interaction_HTZ",Results_Long!$AK$2:$AK$201,0))),"—",INDEX(Results_Long!$O$2:$O$201,MATCH("C4|paris_mid|defined_classified|interaction_HTZ",Results_Long!$AK$2:$AK$201,0))) -> 0.38300481 | E59: =IF(ISNUMBER(SEARCH("<3-cluster",INDEX(Results_Long!$AJ$2:$AJ$201,MATCH("C4|paris_mid|defined_classified|interaction_HTZ",Results_Long!$AK$2:$AK$201,0)))),"touches <3-cluster cell","")
A62: C5 — country_region
A63: Level (M_A) | B63: r | C63: CI_r low | D63: CI_r high | E63: PI_r low | F63: PI_r high | G63: df
A64: 1_US | B64: =IF(ISBLANK(INDEX(Results_Long!$T$2:$T$201,MATCH("C5|levels|classified|lvl::1_US",Results_Long!$AK$2:$AK$201,0))),"n.e.",INDEX(Results_Long!$T$2:$T$201,MATCH("C5|levels|classified|lvl::1_US",Results_Long!$AK$2:$AK$201,0))) -> -0.051958272 | C64: =IF(ISBLANK(INDEX(Results_Long!$U$2:$U$201,MATCH("C5|levels|classified|lvl::1_US",Results_Long!$AK$2:$AK$201,0))),"n.e.",INDEX(Results_Long!$U$2:$U$201,MATCH("C5|levels|classified|lvl::1_US",Results_Long!$AK$2:$AK$201,0))) -> -0.10124052 | D64: =IF(ISBLANK(INDEX(Results_Long!$V$2:$V$201,MATCH("C5|levels|classified|lvl::1_US",Results_Long!$AK$2:$AK$201,0))),"n.e.",INDEX(Results_Long!$V$2:$V$201,MATCH("C5|levels|classified|lvl::1_US",Results_Long!$AK$2:$AK$201,0))) -> -0.0024216507 | E64: =IF(ISBLANK(INDEX(Results_Long!$W$2:$W$201,MATCH("C5|levels|classified|lvl::1_US",Results_Long!$AK$2:$AK$201,0))),"n.e.",INDEX(Results_Long!$W$2:$W$201,MATCH("C5|levels|classified|lvl::1_US",Results_Long!$AK$2:$AK$201,0))) -> -0.42801245 | F64: =IF(ISBLANK(INDEX(Results_Long!$X$2:$X$201,MATCH("C5|levels|classified|lvl::1_US",Results_Long!$AK$2:$AK$201,0))),"n.e.",INDEX(Results_Long!$X$2:$X$201,MATCH("C5|levels|classified|lvl::1_US",Results_Long!$AK$2:$AK$201,0))) -> 0.33943216 | G64: =IF(ISBLANK(INDEX(Results_Long!$N$2:$N$201,MATCH("C5|levels|classified|lvl::1_US",Results_Long!$AK$2:$AK$201,0))),"n.e.",INDEX(Results_Long!$N$2:$N$201,MATCH("C5|levels|classified|lvl::1_US",Results_Long!$AK$2:$AK$201,0))) -> 22.236172
A65: 2_Europe | B65: =IF(ISBLANK(INDEX(Results_Long!$T$2:$T$201,MATCH("C5|levels|classified|lvl::2_Europe",Results_Long!$AK$2:$AK$201,0))),"n.e.",INDEX(Results_Long!$T$2:$T$201,MATCH("C5|levels|classified|lvl::2_Europe",Results_Long!$AK$2:$AK$201,0))) -> -0.071650806 | C65: =IF(ISBLANK(INDEX(Results_Long!$U$2:$U$201,MATCH("C5|levels|classified|lvl::2_Europe",Results_Long!$AK$2:$AK$201,0))),"n.e.",INDEX(Results_Long!$U$2:$U$201,MATCH("C5|levels|classified|lvl::2_Europe",Results_Long!$AK$2:$AK$201,0))) -> -0.15455228 | D65: =IF(ISBLANK(INDEX(Results_Long!$V$2:$V$201,MATCH("C5|levels|classified|lvl::2_Europe",Results_Long!$AK$2:$AK$201,0))),"n.e.",INDEX(Results_Long!$V$2:$V$201,MATCH("C5|levels|classified|lvl::2_Europe",Results_Long!$AK$2:$AK$201,0))) -> 0.012252573 | E65: =IF(ISBLANK(INDEX(Results_Long!$W$2:$W$201,MATCH("C5|levels|classified|lvl::2_Europe",Results_Long!$AK$2:$AK$201,0))),"n.e.",INDEX(Results_Long!$W$2:$W$201,MATCH("C5|levels|classified|lvl::2_Europe",Results_Long!$AK$2:$AK$201,0))) -> -0.45854838 | F65: =IF(ISBLANK(INDEX(Results_Long!$X$2:$X$201,MATCH("C5|levels|classified|lvl::2_Europe",Results_Long!$AK$2:$AK$201,0))),"n.e.",INDEX(Results_Long!$X$2:$X$201,MATCH("C5|levels|classified|lvl::2_Europe",Results_Long!$AK$2:$AK$201,0))) -> 0.33808076 | G65: =IF(ISBLANK(INDEX(Results_Long!$N$2:$N$201,MATCH("C5|levels|classified|lvl::2_Europe",Results_Long!$AK$2:$AK$201,0))),"n.e.",INDEX(Results_Long!$N$2:$N$201,MATCH("C5|levels|classified|lvl::2_Europe",Results_Long!$AK$2:$AK$201,0))) -> 14.424424
A66: 3_AsiaPac | B66: =IF(ISBLANK(INDEX(Results_Long!$T$2:$T$201,MATCH("C5|levels|classified|lvl::3_AsiaPac",Results_Long!$AK$2:$AK$201,0))),"n.e.",INDEX(Results_Long!$T$2:$T$201,MATCH("C5|levels|classified|lvl::3_AsiaPac",Results_Long!$AK$2:$AK$201,0))) -> -0.073508348 | C66: =IF(ISBLANK(INDEX(Results_Long!$U$2:$U$201,MATCH("C5|levels|classified|lvl::3_AsiaPac",Results_Long!$AK$2:$AK$201,0))),"n.e.",INDEX(Results_Long!$U$2:$U$201,MATCH("C5|levels|classified|lvl::3_AsiaPac",Results_Long!$AK$2:$AK$201,0))) -> -0.1180989 | D66: =IF(ISBLANK(INDEX(Results_Long!$V$2:$V$201,MATCH("C5|levels|classified|lvl::3_AsiaPac",Results_Long!$AK$2:$AK$201,0))),"n.e.",INDEX(Results_Long!$V$2:$V$201,MATCH("C5|levels|classified|lvl::3_AsiaPac",Results_Long!$AK$2:$AK$201,0))) -> -0.028621946 | E66: =IF(ISBLANK(INDEX(Results_Long!$W$2:$W$201,MATCH("C5|levels|classified|lvl::3_AsiaPac",Results_Long!$AK$2:$AK$201,0))),"n.e.",INDEX(Results_Long!$W$2:$W$201,MATCH("C5|levels|classified|lvl::3_AsiaPac",Results_Long!$AK$2:$AK$201,0))) -> -0.44416834 | F66: =IF(ISBLANK(INDEX(Results_Long!$X$2:$X$201,MATCH("C5|levels|classified|lvl::3_AsiaPac",Results_Long!$AK$2:$AK$201,0))),"n.e.",INDEX(Results_Long!$X$2:$X$201,MATCH("C5|levels|classified|lvl::3_AsiaPac",Results_Long!$AK$2:$AK$201,0))) -> 0.31863699 | G66: =IF(ISBLANK(INDEX(Results_Long!$N$2:$N$201,MATCH("C5|levels|classified|lvl::3_AsiaPac",Results_Long!$AK$2:$AK$201,0))),"n.e.",INDEX(Results_Long!$N$2:$N$201,MATCH("C5|levels|classified|lvl::3_AsiaPac",Results_Long!$AK$2:$AK$201,0))) -> 23.41538
A68: Paris shift (M_B) | B68: dz (post-pre) | C68: CI_z low | D68: CI_z high | E68: df | F68: p | G68: status
A69: 1_US | B69: =IF(ISBLANK(INDEX(Results_Long!$K$2:$K$201,MATCH("C5|paris_mid|defined_classified|diff::1_US",Results_Long!$AK$2:$AK$201,0))),"n.e.",INDEX(Results_Long!$K$2:$K$201,MATCH("C5|paris_mid|defined_classified|diff::1_US",Results_Long!$AK$2:$AK$201,0))) -> 0.037225284 | C69: =IF(ISBLANK(INDEX(Results_Long!$P$2:$P$201,MATCH("C5|paris_mid|defined_classified|diff::1_US",Results_Long!$AK$2:$AK$201,0))),"n.e.",INDEX(Results_Long!$P$2:$P$201,MATCH("C5|paris_mid|defined_classified|diff::1_US",Results_Long!$AK$2:$AK$201,0))) -> -0.082672702 | D69: =IF(ISBLANK(INDEX(Results_Long!$Q$2:$Q$201,MATCH("C5|paris_mid|defined_classified|diff::1_US",Results_Long!$AK$2:$AK$201,0))),"n.e.",INDEX(Results_Long!$Q$2:$Q$201,MATCH("C5|paris_mid|defined_classified|diff::1_US",Results_Long!$AK$2:$AK$201,0))) -> 0.15712327 | E69: =IF(ISBLANK(INDEX(Results_Long!$N$2:$N$201,MATCH("C5|paris_mid|defined_classified|diff::1_US",Results_Long!$AK$2:$AK$201,0))),"n.e.",INDEX(Results_Long!$N$2:$N$201,MATCH("C5|paris_mid|defined_classified|diff::1_US",Results_Long!$AK$2:$AK$201,0))) -> 4.0846497 | F69: =IF(ISBLANK(INDEX(Results_Long!$O$2:$O$201,MATCH("C5|paris_mid|defined_classified|diff::1_US",Results_Long!$AK$2:$AK$201,0))),"—",INDEX(Results_Long!$O$2:$O$201,MATCH("C5|paris_mid|defined_classified|diff::1_US",Results_Long!$AK$2:$AK$201,0))) -> — | G69: =INDEX(Results_Long!$F$2:$F$201,MATCH("C5|paris_mid|defined_classified|diff::1_US",Results_Long!$AK$2:$AK$201,0)) -> 3LMA-RVE_CR2
A70: 2_Europe | B70: =IF(ISBLANK(INDEX(Results_Long!$K$2:$K$201,MATCH("C5|paris_mid|defined_classified|diff::2_Europe",Results_Long!$AK$2:$AK$201,0))),"n.e.",INDEX(Results_Long!$K$2:$K$201,MATCH("C5|paris_mid|defined_classified|diff::2_Europe",Results_Long!$AK$2:$AK$201,0))) -> 0.088542298 | C70: =IF(ISBLANK(INDEX(Results_Long!$P$2:$P$201,MATCH("C5|paris_mid|defined_classified|diff::2_Europe",Results_Long!$AK$2:$AK$201,0))),"n.e.",INDEX(Results_Long!$P$2:$P$201,MATCH("C5|paris_mid|defined_classified|diff::2_Europe",Results_Long!$AK$2:$AK$201,0))) -> -0.074109585 | D70: =IF(ISBLANK(INDEX(Results_Long!$Q$2:$Q$201,MATCH("C5|paris_mid|defined_classified|diff::2_Europe",Results_Long!$AK$2:$AK$201,0))),"n.e.",INDEX(Results_Long!$Q$2:$Q$201,MATCH("C5|paris_mid|defined_classified|diff::2_Europe",Results_Long!$AK$2:$AK$201,0))) -> 0.25119418 | E70: =IF(ISBLANK(INDEX(Results_Long!$N$2:$N$201,MATCH("C5|paris_mid|defined_classified|diff::2_Europe",Results_Long!$AK$2:$AK$201,0))),"n.e.",INDEX(Results_Long!$N$2:$N$201,MATCH("C5|paris_mid|defined_classified|diff::2_Europe",Results_Long!$AK$2:$AK$201,0))) -> 12.711284 | F70: =IF(ISBLANK(INDEX(Results_Long!$O$2:$O$201,MATCH("C5|paris_mid|defined_classified|diff::2_Europe",Results_Long!$AK$2:$AK$201,0))),"—",INDEX(Results_Long!$O$2:$O$201,MATCH("C5|paris_mid|defined_classified|diff::2_Europe",Results_Long!$AK$2:$AK$201,0))) -> 0.26009078 | G70: =INDEX(Results_Long!$F$2:$F$201,MATCH("C5|paris_mid|defined_classified|diff::2_Europe",Results_Long!$AK$2:$AK$201,0)) -> 3LMA-RVE_CR2
A71: 3_AsiaPac | B71: =IF(ISBLANK(INDEX(Results_Long!$K$2:$K$201,MATCH("C5|paris_mid|defined_classified|diff::3_AsiaPac",Results_Long!$AK$2:$AK$201,0))),"n.e.",INDEX(Results_Long!$K$2:$K$201,MATCH("C5|paris_mid|defined_classified|diff::3_AsiaPac",Results_Long!$AK$2:$AK$201,0))) -> 0.00092722256 | C71: =IF(ISBLANK(INDEX(Results_Long!$P$2:$P$201,MATCH("C5|paris_mid|defined_classified|diff::3_AsiaPac",Results_Long!$AK$2:$AK$201,0))),"n.e.",INDEX(Results_Long!$P$2:$P$201,MATCH("C5|paris_mid|defined_classified|diff::3_AsiaPac",Results_Long!$AK$2:$AK$201,0))) -> -0.10652122 | D71: =IF(ISBLANK(INDEX(Results_Long!$Q$2:$Q$201,MATCH("C5|paris_mid|defined_classified|diff::3_AsiaPac",Results_Long!$AK$2:$AK$201,0))),"n.e.",INDEX(Results_Long!$Q$2:$Q$201,MATCH("C5|paris_mid|defined_classified|diff::3_AsiaPac",Results_Long!$AK$2:$AK$201,0))) -> 0.10837566 | E71: =IF(ISBLANK(INDEX(Results_Long!$N$2:$N$201,MATCH("C5|paris_mid|defined_classified|diff::3_AsiaPac",Results_Long!$AK$2:$AK$201,0))),"n.e.",INDEX(Results_Long!$N$2:$N$201,MATCH("C5|paris_mid|defined_classified|diff::3_AsiaPac",Results_Long!$AK$2:$AK$201,0))) -> 2.8732971 | F71: =IF(ISBLANK(INDEX(Results_Long!$O$2:$O$201,MATCH("C5|paris_mid|defined_classified|diff::3_AsiaPac",Results_Long!$AK$2:$AK$201,0))),"—",INDEX(Results_Long!$O$2:$O$201,MATCH("C5|paris_mid|defined_classified|diff::3_AsiaPac",Results_Long!$AK$2:$AK$201,0))) -> — | G71: =INDEX(Results_Long!$F$2:$F$201,MATCH("C5|paris_mid|defined_classified|diff::3_AsiaPac",Results_Long!$AK$2:$AK$201,0)) -> 3LMA-RVE_CR2
A73: Level contrasts (M_A) | B73: dz | C73: df | D73: p
A74: 1_US vs 2_Europe | B74: =IF(ISBLANK(INDEX(Results_Long!$K$2:$K$201,MATCH("C5|levels|classified|pair::1_US - 2_Europe",Results_Long!$AK$2:$AK$201,0))),"n.e.",INDEX(Results_Long!$K$2:$K$201,MATCH("C5|levels|classified|pair::1_US - 2_Europe",Results_Long!$AK$2:$AK$201,0))) -> 0.019768695 | C74: =IF(ISBLANK(INDEX(Results_Long!$N$2:$N$201,MATCH("C5|levels|classified|pair::1_US - 2_Europe",Results_Long!$AK$2:$AK$201,0))),"n.e.",INDEX(Results_Long!$N$2:$N$201,MATCH("C5|levels|classified|pair::1_US - 2_Europe",Results_Long!$AK$2:$AK$201,0))) -> 1.8205694 | D74: =IF(ISBLANK(INDEX(Results_Long!$O$2:$O$201,MATCH("C5|levels|classified|pair::1_US - 2_Europe",Results_Long!$AK$2:$AK$201,0))),"—",INDEX(Results_Long!$O$2:$O$201,MATCH("C5|levels|classified|pair::1_US - 2_Europe",Results_Long!$AK$2:$AK$201,0))) -> —
A75: 1_US vs 3_AsiaPac | B75: =IF(ISBLANK(INDEX(Results_Long!$K$2:$K$201,MATCH("C5|levels|classified|pair::1_US - 3_AsiaPac",Results_Long!$AK$2:$AK$201,0))),"n.e.",INDEX(Results_Long!$K$2:$K$201,MATCH("C5|levels|classified|pair::1_US - 3_AsiaPac",Results_Long!$AK$2:$AK$201,0))) -> 0.021636074 | C75: =IF(ISBLANK(INDEX(Results_Long!$N$2:$N$201,MATCH("C5|levels|classified|pair::1_US - 3_AsiaPac",Results_Long!$AK$2:$AK$201,0))),"n.e.",INDEX(Results_Long!$N$2:$N$201,MATCH("C5|levels|classified|pair::1_US - 3_AsiaPac",Results_Long!$AK$2:$AK$201,0))) -> 13.314037 | D75: =IF(ISBLANK(INDEX(Results_Long!$O$2:$O$201,MATCH("C5|levels|classified|pair::1_US - 3_AsiaPac",Results_Long!$AK$2:$AK$201,0))),"—",INDEX(Results_Long!$O$2:$O$201,MATCH("C5|levels|classified|pair::1_US - 3_AsiaPac",Results_Long!$AK$2:$AK$201,0))) -> 0.53113828
A76: 2_Europe vs 3_AsiaPac | B76: =IF(ISBLANK(INDEX(Results_Long!$K$2:$K$201,MATCH("C5|levels|classified|pair::2_Europe - 3_AsiaPac",Results_Long!$AK$2:$AK$201,0))),"n.e.",INDEX(Results_Long!$K$2:$K$201,MATCH("C5|levels|classified|pair::2_Europe - 3_AsiaPac",Results_Long!$AK$2:$AK$201,0))) -> 0.0018673797 | C76: =IF(ISBLANK(INDEX(Results_Long!$N$2:$N$201,MATCH("C5|levels|classified|pair::2_Europe - 3_AsiaPac",Results_Long!$AK$2:$AK$201,0))),"n.e.",INDEX(Results_Long!$N$2:$N$201,MATCH("C5|levels|classified|pair::2_Europe - 3_AsiaPac",Results_Long!$AK$2:$AK$201,0))) -> 6.6421469 | D76: =IF(ISBLANK(INDEX(Results_Long!$O$2:$O$201,MATCH("C5|levels|classified|pair::2_Europe - 3_AsiaPac",Results_Long!$AK$2:$AK$201,0))),"—",INDEX(Results_Long!$O$2:$O$201,MATCH("C5|levels|classified|pair::2_Europe - 3_AsiaPac",Results_Long!$AK$2:$AK$201,0))) -> 0.96863584
A78: Levels equal (HTZ) | B78: =IF(ISBLANK(INDEX(Results_Long!$M$2:$M$201,MATCH("C5|levels|classified|levels_HTZ",Results_Long!$AK$2:$AK$201,0))),"n.e.",INDEX(Results_Long!$M$2:$M$201,MATCH("C5|levels|classified|levels_HTZ",Results_Long!$AK$2:$AK$201,0))) -> 0.74479046 | C78: =IF(ISBLANK(INDEX(Results_Long!$N$2:$N$201,MATCH("C5|levels|classified|levels_HTZ",Results_Long!$AK$2:$AK$201,0))),"n.e.",INDEX(Results_Long!$N$2:$N$201,MATCH("C5|levels|classified|levels_HTZ",Results_Long!$AK$2:$AK$201,0))) -> 3.2985174 | D78: =IF(ISBLANK(INDEX(Results_Long!$O$2:$O$201,MATCH("C5|levels|classified|levels_HTZ",Results_Long!$AK$2:$AK$201,0))),"—",INDEX(Results_Long!$O$2:$O$201,MATCH("C5|levels|classified|levels_HTZ",Results_Long!$AK$2:$AK$201,0))) -> 0.5408501 | E78: =IF(ISNUMBER(SEARCH("<3-cluster",INDEX(Results_Long!$AJ$2:$AJ$201,MATCH("C5|levels|classified|levels_HTZ",Results_Long!$AK$2:$AK$201,0)))),"touches <3-cluster cell","")
A79: Moderation test (interaction HTZ) | B79: =IF(ISBLANK(INDEX(Results_Long!$M$2:$M$201,MATCH("C5|paris_mid|defined_classified|interaction_HTZ",Results_Long!$AK$2:$AK$201,0))),"n.e.",INDEX(Results_Long!$M$2:$M$201,MATCH("C5|paris_mid|defined_classified|interaction_HTZ",Results_Long!$AK$2:$AK$201,0))) -> 0.46062069 | C79: =IF(ISBLANK(INDEX(Results_Long!$N$2:$N$201,MATCH("C5|paris_mid|defined_classified|interaction_HTZ",Results_Long!$AK$2:$AK$201,0))),"n.e.",INDEX(Results_Long!$N$2:$N$201,MATCH("C5|paris_mid|defined_classified|interaction_HTZ",Results_Long!$AK$2:$AK$201,0))) -> 3.3629019 | D79: =IF(ISBLANK(INDEX(Results_Long!$O$2:$O$201,MATCH("C5|paris_mid|defined_classified|interaction_HTZ",Results_Long!$AK$2:$AK$201,0))),"—",INDEX(Results_Long!$O$2:$O$201,MATCH("C5|paris_mid|defined_classified|interaction_HTZ",Results_Long!$AK$2:$AK$201,0))) -> 0.66557314 | E79: =IF(ISNUMBER(SEARCH("<3-cluster",INDEX(Results_Long!$AJ$2:$AJ$201,MATCH("C5|paris_mid|defined_classified|interaction_HTZ",Results_Long!$AK$2:$AK$201,0)))),"touches <3-cluster cell","") -> touches <3-cluster cell
A82: Interpretation
A83: All levels sit in a narrow negative band; no Paris shift within any level is significant, and the CDS x post cell is empty by design (not estimable; coding-robust, see 10_Guards_Sensitivity).
A84: The only significant level contrast is loan vs bond — a difference in overall association, not in the Paris response.
A85: The US Paris shift rests on a single post cluster and is reported descriptively, consistent with the composition disclosure.
A87: Question | B87: Answer
A88: Why is the CDS shift missing? | B88: No CDS study is majority-post (0 of 11 clusters); the planned row is carried as not estimable with the design condition documented, and the absence is coding-robust [DEC-048].
A89: Does the loan-bond contrast qualify the null claim? | B89: No — it is a level difference across instruments in the pooled association; the Paris-period moderation test for the instrument panel is far from significance.
A91: Mechanical outcome: within every featured level the Paris-period contrast is small and non-significant, and the flagged cells are exactly the ex-ante pinned thin cells; wording per the resolved gate [DEC-044/DEC-047].

Sheet 8_Other_Panels
A1: Other panels — industry, economic development, culture, legal origin
A2: Reported in full; main-text prominence per the tiering rule [R1]
A3: All cells formula-linked to Results_Long
A5: C3 — industry
A6: Level (M_A) | B6: r | C6: CI_r low | D6: CI_r high | E6: PI_r low | F6: PI_r high | G6: df
A7: non-sensitive | B7: =IF(ISBLANK(INDEX(Results_Long!$T$2:$T$201,MATCH("C3|levels|classified|lvl::non-sensitive",Results_Long!$AK$2:$AK$201,0))),"n.e.",INDEX(Results_Long!$T$2:$T$201,MATCH("C3|levels|classified|lvl::non-sensitive",Results_Long!$AK$2:$AK$201,0))) -> -0.061609528 | C7: =IF(ISBLANK(INDEX(Results_Long!$U$2:$U$201,MATCH("C3|levels|classified|lvl::non-sensitive",Results_Long!$AK$2:$AK$201,0))),"n.e.",INDEX(Results_Long!$U$2:$U$201,MATCH("C3|levels|classified|lvl::non-sensitive",Results_Long!$AK$2:$AK$201,0))) -> -0.099324122 | D7: =IF(ISBLANK(INDEX(Results_Long!$V$2:$V$201,MATCH("C3|levels|classified|lvl::non-sensitive",Results_Long!$AK$2:$AK$201,0))),"n.e.",INDEX(Results_Long!$V$2:$V$201,MATCH("C3|levels|classified|lvl::non-sensitive",Results_Long!$AK$2:$AK$201,0))) -> -0.023718175 | E7: =IF(ISBLANK(INDEX(Results_Long!$W$2:$W$201,MATCH("C3|levels|classified|lvl::non-sensitive",Results_Long!$AK$2:$AK$201,0))),"n.e.",INDEX(Results_Long!$W$2:$W$201,MATCH("C3|levels|classified|lvl::non-sensitive",Results_Long!$AK$2:$AK$201,0))) -> -0.4234863 | F7: =IF(ISBLANK(INDEX(Results_Long!$X$2:$X$201,MATCH("C3|levels|classified|lvl::non-sensitive",Results_Long!$AK$2:$AK$201,0))),"n.e.",INDEX(Results_Long!$X$2:$X$201,MATCH("C3|levels|classified|lvl::non-sensitive",Results_Long!$AK$2:$AK$201,0))) -> 0.31722383 | G7: =IF(ISBLANK(INDEX(Results_Long!$N$2:$N$201,MATCH("C3|levels|classified|lvl::non-sensitive",Results_Long!$AK$2:$AK$201,0))),"n.e.",INDEX(Results_Long!$N$2:$N$201,MATCH("C3|levels|classified|lvl::non-sensitive",Results_Long!$AK$2:$AK$201,0))) -> 69.595427
A8: sensitive | B8: =IF(ISBLANK(INDEX(Results_Long!$T$2:$T$201,MATCH("C3|levels|classified|lvl::sensitive",Results_Long!$AK$2:$AK$201,0))),"n.e.",INDEX(Results_Long!$T$2:$T$201,MATCH("C3|levels|classified|lvl::sensitive",Results_Long!$AK$2:$AK$201,0))) -> -0.045813193 | C8: =IF(ISBLANK(INDEX(Results_Long!$U$2:$U$201,MATCH("C3|levels|classified|lvl::sensitive",Results_Long!$AK$2:$AK$201,0))),"n.e.",INDEX(Results_Long!$U$2:$U$201,MATCH("C3|levels|classified|lvl::sensitive",Results_Long!$AK$2:$AK$201,0))) -> -0.08067026 | D8: =IF(ISBLANK(INDEX(Results_Long!$V$2:$V$201,MATCH("C3|levels|classified|lvl::sensitive",Results_Long!$AK$2:$AK$201,0))),"n.e.",INDEX(Results_Long!$V$2:$V$201,MATCH("C3|levels|classified|lvl::sensitive",Results_Long!$AK$2:$AK$201,0))) -> -0.010844206 | E8: =IF(ISBLANK(INDEX(Results_Long!$W$2:$W$201,MATCH("C3|levels|classified|lvl::sensitive",Results_Long!$AK$2:$AK$201,0))),"n.e.",INDEX(Results_Long!$W$2:$W$201,MATCH("C3|levels|classified|lvl::sensitive",Results_Long!$AK$2:$AK$201,0))) -> -0.45332966 | F8: =IF(ISBLANK(INDEX(Results_Long!$X$2:$X$201,MATCH("C3|levels|classified|lvl::sensitive",Results_Long!$AK$2:$AK$201,0))),"n.e.",INDEX(Results_Long!$X$2:$X$201,MATCH("C3|levels|classified|lvl::sensitive",Results_Long!$AK$2:$AK$201,0))) -> 0.37754438 | G8: =IF(ISBLANK(INDEX(Results_Long!$N$2:$N$201,MATCH("C3|levels|classified|lvl::sensitive",Results_Long!$AK$2:$AK$201,0))),"n.e.",INDEX(Results_Long!$N$2:$N$201,MATCH("C3|levels|classified|lvl::sensitive",Results_Long!$AK$2:$AK$201,0))) -> 8.8463406
A10: Paris shift (M_B) | B10: dz (post-pre) | C10: CI_z low | D10: CI_z high | E10: df | F10: p | G10: status
A11: non-sensitive | B11: =IF(ISBLANK(INDEX(Results_Long!$K$2:$K$201,MATCH("C3|paris_mid|defined_classified|diff::non-sensitive",Results_Long!$AK$2:$AK$201,0))),"n.e.",INDEX(Results_Long!$K$2:$K$201,MATCH("C3|paris_mid|defined_classified|diff::non-sensitive",Results_Long!$AK$2:$AK$201,0))) -> 0.019059525 | C11: =IF(ISBLANK(INDEX(Results_Long!$P$2:$P$201,MATCH("C3|paris_mid|defined_classified|diff::non-sensitive",Results_Long!$AK$2:$AK$201,0))),"n.e.",INDEX(Results_Long!$P$2:$P$201,MATCH("C3|paris_mid|defined_classified|diff::non-sensitive",Results_Long!$AK$2:$AK$201,0))) -> -0.037560931 | D11: =IF(ISBLANK(INDEX(Results_Long!$Q$2:$Q$201,MATCH("C3|paris_mid|defined_classified|diff::non-sensitive",Results_Long!$AK$2:$AK$201,0))),"n.e.",INDEX(Results_Long!$Q$2:$Q$201,MATCH("C3|paris_mid|defined_classified|diff::non-sensitive",Results_Long!$AK$2:$AK$201,0))) -> 0.075679981 | E11: =IF(ISBLANK(INDEX(Results_Long!$N$2:$N$201,MATCH("C3|paris_mid|defined_classified|diff::non-sensitive",Results_Long!$AK$2:$AK$201,0))),"n.e.",INDEX(Results_Long!$N$2:$N$201,MATCH("C3|paris_mid|defined_classified|diff::non-sensitive",Results_Long!$AK$2:$AK$201,0))) -> 25.771443 | F11: =IF(ISBLANK(INDEX(Results_Long!$O$2:$O$201,MATCH("C3|paris_mid|defined_classified|diff::non-sensitive",Results_Long!$AK$2:$AK$201,0))),"—",INDEX(Results_Long!$O$2:$O$201,MATCH("C3|paris_mid|defined_classified|diff::non-sensitive",Results_Long!$AK$2:$AK$201,0))) -> 0.49498378 | G11: =INDEX(Results_Long!$F$2:$F$201,MATCH("C3|paris_mid|defined_classified|diff::non-sensitive",Results_Long!$AK$2:$AK$201,0)) -> 3LMA-RVE_CR2
A12: sensitive | B12: =IF(ISBLANK(INDEX(Results_Long!$K$2:$K$201,MATCH("C3|paris_mid|defined_classified|diff::sensitive",Results_Long!$AK$2:$AK$201,0))),"n.e.",INDEX(Results_Long!$K$2:$K$201,MATCH("C3|paris_mid|defined_classified|diff::sensitive",Results_Long!$AK$2:$AK$201,0))) -> 0.039265731 | C12: =IF(ISBLANK(INDEX(Results_Long!$P$2:$P$201,MATCH("C3|paris_mid|defined_classified|diff::sensitive",Results_Long!$AK$2:$AK$201,0))),"n.e.",INDEX(Results_Long!$P$2:$P$201,MATCH("C3|paris_mid|defined_classified|diff::sensitive",Results_Long!$AK$2:$AK$201,0))) -> -0.042041651 | D12: =IF(ISBLANK(INDEX(Results_Long!$Q$2:$Q$201,MATCH("C3|paris_mid|defined_classified|diff::sensitive",Results_Long!$AK$2:$AK$201,0))),"n.e.",INDEX(Results_Long!$Q$2:$Q$201,MATCH("C3|paris_mid|defined_classified|diff::sensitive",Results_Long!$AK$2:$AK$201,0))) -> 0.12057311 | E12: =IF(ISBLANK(INDEX(Results_Long!$N$2:$N$201,MATCH("C3|paris_mid|defined_classified|diff::sensitive",Results_Long!$AK$2:$AK$201,0))),"n.e.",INDEX(Results_Long!$N$2:$N$201,MATCH("C3|paris_mid|defined_classified|diff::sensitive",Results_Long!$AK$2:$AK$201,0))) -> 3.8212558 | F12: =IF(ISBLANK(INDEX(Results_Long!$O$2:$O$201,MATCH("C3|paris_mid|defined_classified|diff::sensitive",Results_Long!$AK$2:$AK$201,0))),"—",INDEX(Results_Long!$O$2:$O$201,MATCH("C3|paris_mid|defined_classified|diff::sensitive",Results_Long!$AK$2:$AK$201,0))) -> — | G12: =INDEX(Results_Long!$F$2:$F$201,MATCH("C3|paris_mid|defined_classified|diff::sensitive",Results_Long!$AK$2:$AK$201,0)) -> 3LMA-RVE_CR2
A14: Level contrasts (M_A) | B14: dz | C14: df | D14: p
A15: non-sensitive vs sensitive | B15: =IF(ISBLANK(INDEX(Results_Long!$K$2:$K$201,MATCH("C3|levels|classified|pair::non-sensitive - sensitive",Results_Long!$AK$2:$AK$201,0))),"n.e.",INDEX(Results_Long!$K$2:$K$201,MATCH("C3|levels|classified|pair::non-sensitive - sensitive",Results_Long!$AK$2:$AK$201,0))) -> -0.015842372 | C15: =IF(ISBLANK(INDEX(Results_Long!$N$2:$N$201,MATCH("C3|levels|classified|pair::non-sensitive - sensitive",Results_Long!$AK$2:$AK$201,0))),"n.e.",INDEX(Results_Long!$N$2:$N$201,MATCH("C3|levels|classified|pair::non-sensitive - sensitive",Results_Long!$AK$2:$AK$201,0))) -> 6.7844465 | D15: =IF(ISBLANK(INDEX(Results_Long!$O$2:$O$201,MATCH("C3|levels|classified|pair::non-sensitive - sensitive",Results_Long!$AK$2:$AK$201,0))),"—",INDEX(Results_Long!$O$2:$O$201,MATCH("C3|levels|classified|pair::non-sensitive - sensitive",Results_Long!$AK$2:$AK$201,0))) -> 0.44629706
A17: Levels equal (HTZ) | B17: =IF(ISBLANK(INDEX(Results_Long!$M$2:$M$201,MATCH("C3|levels|classified|levels_HTZ",Results_Long!$AK$2:$AK$201,0))),"n.e.",INDEX(Results_Long!$M$2:$M$201,MATCH("C3|levels|classified|levels_HTZ",Results_Long!$AK$2:$AK$201,0))) -> 0.65344738 | C17: =IF(ISBLANK(INDEX(Results_Long!$N$2:$N$201,MATCH("C3|levels|classified|levels_HTZ",Results_Long!$AK$2:$AK$201,0))),"n.e.",INDEX(Results_Long!$N$2:$N$201,MATCH("C3|levels|classified|levels_HTZ",Results_Long!$AK$2:$AK$201,0))) -> 6.7844465 | D17: =IF(ISBLANK(INDEX(Results_Long!$O$2:$O$201,MATCH("C3|levels|classified|levels_HTZ",Results_Long!$AK$2:$AK$201,0))),"—",INDEX(Results_Long!$O$2:$O$201,MATCH("C3|levels|classified|levels_HTZ",Results_Long!$AK$2:$AK$201,0))) -> 0.44629706 | E17: =IF(ISNUMBER(SEARCH("<3-cluster",INDEX(Results_Long!$AJ$2:$AJ$201,MATCH("C3|levels|classified|levels_HTZ",Results_Long!$AK$2:$AK$201,0)))),"touches <3-cluster cell","")
A18: Moderation test (interaction HTZ) | B18: =IF(ISBLANK(INDEX(Results_Long!$M$2:$M$201,MATCH("C3|paris_mid|defined_classified|interaction_HTZ",Results_Long!$AK$2:$AK$201,0))),"n.e.",INDEX(Results_Long!$M$2:$M$201,MATCH("C3|paris_mid|defined_classified|interaction_HTZ",Results_Long!$AK$2:$AK$201,0))) -> 0.15811514 | C18: =IF(ISBLANK(INDEX(Results_Long!$N$2:$N$201,MATCH("C3|paris_mid|defined_classified|interaction_HTZ",Results_Long!$AK$2:$AK$201,0))),"n.e.",INDEX(Results_Long!$N$2:$N$201,MATCH("C3|paris_mid|defined_classified|interaction_HTZ",Results_Long!$AK$2:$AK$201,0))) -> 8.7855308 | D18: =IF(ISBLANK(INDEX(Results_Long!$O$2:$O$201,MATCH("C3|paris_mid|defined_classified|interaction_HTZ",Results_Long!$AK$2:$AK$201,0))),"—",INDEX(Results_Long!$O$2:$O$201,MATCH("C3|paris_mid|defined_classified|interaction_HTZ",Results_Long!$AK$2:$AK$201,0))) -> 0.70038592 | E18: =IF(ISNUMBER(SEARCH("<3-cluster",INDEX(Results_Long!$AJ$2:$AJ$201,MATCH("C3|paris_mid|defined_classified|interaction_HTZ",Results_Long!$AK$2:$AK$201,0)))),"touches <3-cluster cell","")
A21: C6 — country_econ
A22: Level (M_A) | B22: r | C22: CI_r low | D22: CI_r high | E22: PI_r low | F22: PI_r high | G22: df
A23: 1_developed | B23: =IF(ISBLANK(INDEX(Results_Long!$T$2:$T$201,MATCH("C6|levels|classified|lvl::1_developed",Results_Long!$AK$2:$AK$201,0))),"n.e.",INDEX(Results_Long!$T$2:$T$201,MATCH("C6|levels|classified|lvl::1_developed",Results_Long!$AK$2:$AK$201,0))) -> -0.028924726 | C23: =IF(ISBLANK(INDEX(Results_Long!$U$2:$U$201,MATCH("C6|levels|classified|lvl::1_developed",Results_Long!$AK$2:$AK$201,0))),"n.e.",INDEX(Results_Long!$U$2:$U$201,MATCH("C6|levels|classified|lvl::1_developed",Results_Long!$AK$2:$AK$201,0))) -> -0.043031116 | D23: =IF(ISBLANK(INDEX(Results_Long!$V$2:$V$201,MATCH("C6|levels|classified|lvl::1_developed",Results_Long!$AK$2:$AK$201,0))),"n.e.",INDEX(Results_Long!$V$2:$V$201,MATCH("C6|levels|classified|lvl::1_developed",Results_Long!$AK$2:$AK$201,0))) -> -0.014806804 | E23: =IF(ISBLANK(INDEX(Results_Long!$W$2:$W$201,MATCH("C6|levels|classified|lvl::1_developed",Results_Long!$AK$2:$AK$201,0))),"n.e.",INDEX(Results_Long!$W$2:$W$201,MATCH("C6|levels|classified|lvl::1_developed",Results_Long!$AK$2:$AK$201,0))) -> -0.1838856 | F23: =IF(ISBLANK(INDEX(Results_Long!$X$2:$X$201,MATCH("C6|levels|classified|lvl::1_developed",Results_Long!$AK$2:$AK$201,0))),"n.e.",INDEX(Results_Long!$X$2:$X$201,MATCH("C6|levels|classified|lvl::1_developed",Results_Long!$AK$2:$AK$201,0))) -> 0.12743903 | G23: =IF(ISBLANK(INDEX(Results_Long!$N$2:$N$201,MATCH("C6|levels|classified|lvl::1_developed",Results_Long!$AK$2:$AK$201,0))),"n.e.",INDEX(Results_Long!$N$2:$N$201,MATCH("C6|levels|classified|lvl::1_developed",Results_Long!$AK$2:$AK$201,0))) -> 37.814796
A24: 2_developing | B24: =IF(ISBLANK(INDEX(Results_Long!$T$2:$T$201,MATCH("C6|levels|classified|lvl::2_developing",Results_Long!$AK$2:$AK$201,0))),"n.e.",INDEX(Results_Long!$T$2:$T$201,MATCH("C6|levels|classified|lvl::2_developing",Results_Long!$AK$2:$AK$201,0))) -> -0.05066197 | C24: =IF(ISBLANK(INDEX(Results_Long!$U$2:$U$201,MATCH("C6|levels|classified|lvl::2_developing",Results_Long!$AK$2:$AK$201,0))),"n.e.",INDEX(Results_Long!$U$2:$U$201,MATCH("C6|levels|classified|lvl::2_developing",Results_Long!$AK$2:$AK$201,0))) -> -0.070714944 | D24: =IF(ISBLANK(INDEX(Results_Long!$V$2:$V$201,MATCH("C6|levels|classified|lvl::2_developing",Results_Long!$AK$2:$AK$201,0))),"n.e.",INDEX(Results_Long!$V$2:$V$201,MATCH("C6|levels|classified|lvl::2_developing",Results_Long!$AK$2:$AK$201,0))) -> -0.030568063 | E24: =IF(ISBLANK(INDEX(Results_Long!$W$2:$W$201,MATCH("C6|levels|classified|lvl::2_developing",Results_Long!$AK$2:$AK$201,0))),"n.e.",INDEX(Results_Long!$W$2:$W$201,MATCH("C6|levels|classified|lvl::2_developing",Results_Long!$AK$2:$AK$201,0))) -> -0.20711714 | F24: =IF(ISBLANK(INDEX(Results_Long!$X$2:$X$201,MATCH("C6|levels|classified|lvl::2_developing",Results_Long!$AK$2:$AK$201,0))),"n.e.",INDEX(Results_Long!$X$2:$X$201,MATCH("C6|levels|classified|lvl::2_developing",Results_Long!$AK$2:$AK$201,0))) -> 0.10831997 | G24: =IF(ISBLANK(INDEX(Results_Long!$N$2:$N$201,MATCH("C6|levels|classified|lvl::2_developing",Results_Long!$AK$2:$AK$201,0))),"n.e.",INDEX(Results_Long!$N$2:$N$201,MATCH("C6|levels|classified|lvl::2_developing",Results_Long!$AK$2:$AK$201,0))) -> 28.340856
A26: Paris shift (M_B) | B26: dz (post-pre) | C26: CI_z low | D26: CI_z high | E26: df | F26: p | G26: status
A27: 1_developed | B27: =IF(ISBLANK(INDEX(Results_Long!$K$2:$K$201,MATCH("C6|paris_mid|defined_classified|diff::1_developed",Results_Long!$AK$2:$AK$201,0))),"n.e.",INDEX(Results_Long!$K$2:$K$201,MATCH("C6|paris_mid|defined_classified|diff::1_developed",Results_Long!$AK$2:$AK$201,0))) -> -0.039677855 | C27: =IF(ISBLANK(INDEX(Results_Long!$P$2:$P$201,MATCH("C6|paris_mid|defined_classified|diff::1_developed",Results_Long!$AK$2:$AK$201,0))),"n.e.",INDEX(Results_Long!$P$2:$P$201,MATCH("C6|paris_mid|defined_classified|diff::1_developed",Results_Long!$AK$2:$AK$201,0))) -> -0.11189173 | D27: =IF(ISBLANK(INDEX(Results_Long!$Q$2:$Q$201,MATCH("C6|paris_mid|defined_classified|diff::1_developed",Results_Long!$AK$2:$AK$201,0))),"n.e.",INDEX(Results_Long!$Q$2:$Q$201,MATCH("C6|paris_mid|defined_classified|diff::1_developed",Results_Long!$AK$2:$AK$201,0))) -> 0.03253602 | E27: =IF(ISBLANK(INDEX(Results_Long!$N$2:$N$201,MATCH("C6|paris_mid|defined_classified|diff::1_developed",Results_Long!$AK$2:$AK$201,0))),"n.e.",INDEX(Results_Long!$N$2:$N$201,MATCH("C6|paris_mid|defined_classified|diff::1_developed",Results_Long!$AK$2:$AK$201,0))) -> 1.7895178 | F27: =IF(ISBLANK(INDEX(Results_Long!$O$2:$O$201,MATCH("C6|paris_mid|defined_classified|diff::1_developed",Results_Long!$AK$2:$AK$201,0))),"—",INDEX(Results_Long!$O$2:$O$201,MATCH("C6|paris_mid|defined_classified|diff::1_developed",Results_Long!$AK$2:$AK$201,0))) -> — | G27: =INDEX(Results_Long!$F$2:$F$201,MATCH("C6|paris_mid|defined_classified|diff::1_developed",Results_Long!$AK$2:$AK$201,0)) -> 3LMA-RVE_CR2
A28: 2_developing | B28: =IF(ISBLANK(INDEX(Results_Long!$K$2:$K$201,MATCH("C6|paris_mid|defined_classified|diff::2_developing",Results_Long!$AK$2:$AK$201,0))),"n.e.",INDEX(Results_Long!$K$2:$K$201,MATCH("C6|paris_mid|defined_classified|diff::2_developing",Results_Long!$AK$2:$AK$201,0))) -> -0.00048431195 | C28: =IF(ISBLANK(INDEX(Results_Long!$P$2:$P$201,MATCH("C6|paris_mid|defined_classified|diff::2_developing",Results_Long!$AK$2:$AK$201,0))),"n.e.",INDEX(Results_Long!$P$2:$P$201,MATCH("C6|paris_mid|defined_classified|diff::2_developing",Results_Long!$AK$2:$AK$201,0))) -> -0.038794849 | D28: =IF(ISBLANK(INDEX(Results_Long!$Q$2:$Q$201,MATCH("C6|paris_mid|defined_classified|diff::2_developing",Results_Long!$AK$2:$AK$201,0))),"n.e.",INDEX(Results_Long!$Q$2:$Q$201,MATCH("C6|paris_mid|defined_classified|diff::2_developing",Results_Long!$AK$2:$AK$201,0))) -> 0.037826225 | E28: =IF(ISBLANK(INDEX(Results_Long!$N$2:$N$201,MATCH("C6|paris_mid|defined_classified|diff::2_developing",Results_Long!$AK$2:$AK$201,0))),"n.e.",INDEX(Results_Long!$N$2:$N$201,MATCH("C6|paris_mid|defined_classified|diff::2_developing",Results_Long!$AK$2:$AK$201,0))) -> 14.511869 | F28: =IF(ISBLANK(INDEX(Results_Long!$O$2:$O$201,MATCH("C6|paris_mid|defined_classified|diff::2_developing",Results_Long!$AK$2:$AK$201,0))),"—",INDEX(Results_Long!$O$2:$O$201,MATCH("C6|paris_mid|defined_classified|diff::2_developing",Results_Long!$AK$2:$AK$201,0))) -> 0.9788084 | G28: =INDEX(Results_Long!$F$2:$F$201,MATCH("C6|paris_mid|defined_classified|diff::2_developing",Results_Long!$AK$2:$AK$201,0)) -> 3LMA-RVE_CR2
A30: Level contrasts (M_A) | B30: dz | C30: df | D30: p
A31: 1_developed vs 2_developing | B31: =IF(ISBLANK(INDEX(Results_Long!$K$2:$K$201,MATCH("C6|levels|classified|pair::1_developed - 2_developing",Results_Long!$AK$2:$AK$201,0))),"n.e.",INDEX(Results_Long!$K$2:$K$201,MATCH("C6|levels|classified|pair::1_developed - 2_developing",Results_Long!$AK$2:$AK$201,0))) -> 0.021772584 | C31: =IF(ISBLANK(INDEX(Results_Long!$N$2:$N$201,MATCH("C6|levels|classified|pair::1_developed - 2_developing",Results_Long!$AK$2:$AK$201,0))),"n.e.",INDEX(Results_Long!$N$2:$N$201,MATCH("C6|levels|classified|pair::1_developed - 2_developing",Results_Long!$AK$2:$AK$201,0))) -> 39.270895 | D31: =IF(ISBLANK(INDEX(Results_Long!$O$2:$O$201,MATCH("C6|levels|classified|pair::1_developed - 2_developing",Results_Long!$AK$2:$AK$201,0))),"—",INDEX(Results_Long!$O$2:$O$201,MATCH("C6|levels|classified|pair::1_developed - 2_developing",Results_Long!$AK$2:$AK$201,0))) -> 0.085187647
A33: Levels equal (HTZ) | B33: =IF(ISBLANK(INDEX(Results_Long!$M$2:$M$201,MATCH("C6|levels|classified|levels_HTZ",Results_Long!$AK$2:$AK$201,0))),"n.e.",INDEX(Results_Long!$M$2:$M$201,MATCH("C6|levels|classified|levels_HTZ",Results_Long!$AK$2:$AK$201,0))) -> 3.1183795 | C33: =IF(ISBLANK(INDEX(Results_Long!$N$2:$N$201,MATCH("C6|levels|classified|levels_HTZ",Results_Long!$AK$2:$AK$201,0))),"n.e.",INDEX(Results_Long!$N$2:$N$201,MATCH("C6|levels|classified|levels_HTZ",Results_Long!$AK$2:$AK$201,0))) -> 39.270895 | D33: =IF(ISBLANK(INDEX(Results_Long!$O$2:$O$201,MATCH("C6|levels|classified|levels_HTZ",Results_Long!$AK$2:$AK$201,0))),"—",INDEX(Results_Long!$O$2:$O$201,MATCH("C6|levels|classified|levels_HTZ",Results_Long!$AK$2:$AK$201,0))) -> 0.085187647 | E33: =IF(ISNUMBER(SEARCH("<3-cluster",INDEX(Results_Long!$AJ$2:$AJ$201,MATCH("C6|levels|classified|levels_HTZ",Results_Long!$AK$2:$AK$201,0)))),"touches <3-cluster cell","")
A34: Moderation test (interaction HTZ) | B34: =IF(ISBLANK(INDEX(Results_Long!$M$2:$M$201,MATCH("C6|paris_mid|defined_classified|interaction_HTZ",Results_Long!$AK$2:$AK$201,0))),"n.e.",INDEX(Results_Long!$M$2:$M$201,MATCH("C6|paris_mid|defined_classified|interaction_HTZ",Results_Long!$AK$2:$AK$201,0))) -> 3.4928388 | C34: =IF(ISBLANK(INDEX(Results_Long!$N$2:$N$201,MATCH("C6|paris_mid|defined_classified|interaction_HTZ",Results_Long!$AK$2:$AK$201,0))),"n.e.",INDEX(Results_Long!$N$2:$N$201,MATCH("C6|paris_mid|defined_classified|interaction_HTZ",Results_Long!$AK$2:$AK$201,0))) -> 2.2032508 | D34: =IF(ISBLANK(INDEX(Results_Long!$O$2:$O$201,MATCH("C6|paris_mid|defined_classified|interaction_HTZ",Results_Long!$AK$2:$AK$201,0))),"—",INDEX(Results_Long!$O$2:$O$201,MATCH("C6|paris_mid|defined_classified|interaction_HTZ",Results_Long!$AK$2:$AK$201,0))) -> 0.19073471 | E34: =IF(ISNUMBER(SEARCH("<3-cluster",INDEX(Results_Long!$AJ$2:$AJ$201,MATCH("C6|paris_mid|defined_classified|interaction_HTZ",Results_Long!$AK$2:$AK$201,0)))),"touches <3-cluster cell","")
A37: C7 — country_culture
A38: Level (M_A) | B38: r | C38: CI_r low | D38: CI_r high | E38: PI_r low | F38: PI_r high | G38: df
A39: 1_western | B39: =IF(ISBLANK(INDEX(Results_Long!$T$2:$T$201,MATCH("C7|levels|classified|lvl::1_western",Results_Long!$AK$2:$AK$201,0))),"n.e.",INDEX(Results_Long!$T$2:$T$201,MATCH("C7|levels|classified|lvl::1_western",Results_Long!$AK$2:$AK$201,0))) -> -0.06071469 | C39: =IF(ISBLANK(INDEX(Results_Long!$U$2:$U$201,MATCH("C7|levels|classified|lvl::1_western",Results_Long!$AK$2:$AK$201,0))),"n.e.",INDEX(Results_Long!$U$2:$U$201,MATCH("C7|levels|classified|lvl::1_western",Results_Long!$AK$2:$AK$201,0))) -> -0.11685325 | D39: =IF(ISBLANK(INDEX(Results_Long!$V$2:$V$201,MATCH("C7|levels|classified|lvl::1_western",Results_Long!$AK$2:$AK$201,0))),"n.e.",INDEX(Results_Long!$V$2:$V$201,MATCH("C7|levels|classified|lvl::1_western",Results_Long!$AK$2:$AK$201,0))) -> -0.0041893761 | E39: =IF(ISBLANK(INDEX(Results_Long!$W$2:$W$201,MATCH("C7|levels|classified|lvl::1_western",Results_Long!$AK$2:$AK$201,0))),"n.e.",INDEX(Results_Long!$W$2:$W$201,MATCH("C7|levels|classified|lvl::1_western",Results_Long!$AK$2:$AK$201,0))) -> -0.42289057 | F39: =IF(ISBLANK(INDEX(Results_Long!$X$2:$X$201,MATCH("C7|levels|classified|lvl::1_western",Results_Long!$AK$2:$AK$201,0))),"n.e.",INDEX(Results_Long!$X$2:$X$201,MATCH("C7|levels|classified|lvl::1_western",Results_Long!$AK$2:$AK$201,0))) -> 0.31818646 | G39: =IF(ISBLANK(INDEX(Results_Long!$N$2:$N$201,MATCH("C7|levels|classified|lvl::1_western",Results_Long!$AK$2:$AK$201,0))),"n.e.",INDEX(Results_Long!$N$2:$N$201,MATCH("C7|levels|classified|lvl::1_western",Results_Long!$AK$2:$AK$201,0))) -> 40.156221
A40: 2_non_western | B40: =IF(ISBLANK(INDEX(Results_Long!$T$2:$T$201,MATCH("C7|levels|classified|lvl::2_non_western",Results_Long!$AK$2:$AK$201,0))),"n.e.",INDEX(Results_Long!$T$2:$T$201,MATCH("C7|levels|classified|lvl::2_non_western",Results_Long!$AK$2:$AK$201,0))) -> -0.06596756 | C40: =IF(ISBLANK(INDEX(Results_Long!$U$2:$U$201,MATCH("C7|levels|classified|lvl::2_non_western",Results_Long!$AK$2:$AK$201,0))),"n.e.",INDEX(Results_Long!$U$2:$U$201,MATCH("C7|levels|classified|lvl::2_non_western",Results_Long!$AK$2:$AK$201,0))) -> -0.10404717 | D40: =IF(ISBLANK(INDEX(Results_Long!$V$2:$V$201,MATCH("C7|levels|classified|lvl::2_non_western",Results_Long!$AK$2:$AK$201,0))),"n.e.",INDEX(Results_Long!$V$2:$V$201,MATCH("C7|levels|classified|lvl::2_non_western",Results_Long!$AK$2:$AK$201,0))) -> -0.027694822 | E40: =IF(ISBLANK(INDEX(Results_Long!$W$2:$W$201,MATCH("C7|levels|classified|lvl::2_non_western",Results_Long!$AK$2:$AK$201,0))),"n.e.",INDEX(Results_Long!$W$2:$W$201,MATCH("C7|levels|classified|lvl::2_non_western",Results_Long!$AK$2:$AK$201,0))) -> -0.43472092 | F40: =IF(ISBLANK(INDEX(Results_Long!$X$2:$X$201,MATCH("C7|levels|classified|lvl::2_non_western",Results_Long!$AK$2:$AK$201,0))),"n.e.",INDEX(Results_Long!$X$2:$X$201,MATCH("C7|levels|classified|lvl::2_non_western",Results_Long!$AK$2:$AK$201,0))) -> 0.32173033 | G40: =IF(ISBLANK(INDEX(Results_Long!$N$2:$N$201,MATCH("C7|levels|classified|lvl::2_non_western",Results_Long!$AK$2:$AK$201,0))),"n.e.",INDEX(Results_Long!$N$2:$N$201,MATCH("C7|levels|classified|lvl::2_non_western",Results_Long!$AK$2:$AK$201,0))) -> 20.773209
A42: Paris shift (M_B) | B42: dz (post-pre) | C42: CI_z low | D42: CI_z high | E42: df | F42: p | G42: status
A43: 1_western | B43: =IF(ISBLANK(INDEX(Results_Long!$K$2:$K$201,MATCH("C7|paris_mid|defined_classified|diff::1_western",Results_Long!$AK$2:$AK$201,0))),"n.e.",INDEX(Results_Long!$K$2:$K$201,MATCH("C7|paris_mid|defined_classified|diff::1_western",Results_Long!$AK$2:$AK$201,0))) -> 0.0123765 | C43: =IF(ISBLANK(INDEX(Results_Long!$P$2:$P$201,MATCH("C7|paris_mid|defined_classified|diff::1_western",Results_Long!$AK$2:$AK$201,0))),"n.e.",INDEX(Results_Long!$P$2:$P$201,MATCH("C7|paris_mid|defined_classified|diff::1_western",Results_Long!$AK$2:$AK$201,0))) -> -0.070162284 | D43: =IF(ISBLANK(INDEX(Results_Long!$Q$2:$Q$201,MATCH("C7|paris_mid|defined_classified|diff::1_western",Results_Long!$AK$2:$AK$201,0))),"n.e.",INDEX(Results_Long!$Q$2:$Q$201,MATCH("C7|paris_mid|defined_classified|diff::1_western",Results_Long!$AK$2:$AK$201,0))) -> 0.094915283 | E43: =IF(ISBLANK(INDEX(Results_Long!$N$2:$N$201,MATCH("C7|paris_mid|defined_classified|diff::1_western",Results_Long!$AK$2:$AK$201,0))),"n.e.",INDEX(Results_Long!$N$2:$N$201,MATCH("C7|paris_mid|defined_classified|diff::1_western",Results_Long!$AK$2:$AK$201,0))) -> 10.905747 | F43: =IF(ISBLANK(INDEX(Results_Long!$O$2:$O$201,MATCH("C7|paris_mid|defined_classified|diff::1_western",Results_Long!$AK$2:$AK$201,0))),"—",INDEX(Results_Long!$O$2:$O$201,MATCH("C7|paris_mid|defined_classified|diff::1_western",Results_Long!$AK$2:$AK$201,0))) -> 0.74737192 | G43: =INDEX(Results_Long!$F$2:$F$201,MATCH("C7|paris_mid|defined_classified|diff::1_western",Results_Long!$AK$2:$AK$201,0)) -> 3LMA-RVE_CR2
A44: 2_non_western | B44: =IF(ISBLANK(INDEX(Results_Long!$K$2:$K$201,MATCH("C7|paris_mid|defined_classified|diff::2_non_western",Results_Long!$AK$2:$AK$201,0))),"n.e.",INDEX(Results_Long!$K$2:$K$201,MATCH("C7|paris_mid|defined_classified|diff::2_non_western",Results_Long!$AK$2:$AK$201,0))) -> 0.022955673 | C44: =IF(ISBLANK(INDEX(Results_Long!$P$2:$P$201,MATCH("C7|paris_mid|defined_classified|diff::2_non_western",Results_Long!$AK$2:$AK$201,0))),"n.e.",INDEX(Results_Long!$P$2:$P$201,MATCH("C7|paris_mid|defined_classified|diff::2_non_western",Results_Long!$AK$2:$AK$201,0))) -> -0.036772813 | D44: =IF(ISBLANK(INDEX(Results_Long!$Q$2:$Q$201,MATCH("C7|paris_mid|defined_classified|diff::2_non_western",Results_Long!$AK$2:$AK$201,0))),"n.e.",INDEX(Results_Long!$Q$2:$Q$201,MATCH("C7|paris_mid|defined_classified|diff::2_non_western",Results_Long!$AK$2:$AK$201,0))) -> 0.08268416 | E44: =IF(ISBLANK(INDEX(Results_Long!$N$2:$N$201,MATCH("C7|paris_mid|defined_classified|diff::2_non_western",Results_Long!$AK$2:$AK$201,0))),"n.e.",INDEX(Results_Long!$N$2:$N$201,MATCH("C7|paris_mid|defined_classified|diff::2_non_western",Results_Long!$AK$2:$AK$201,0))) -> 2.7103736 | F44: =IF(ISBLANK(INDEX(Results_Long!$O$2:$O$201,MATCH("C7|paris_mid|defined_classified|diff::2_non_western",Results_Long!$AK$2:$AK$201,0))),"—",INDEX(Results_Long!$O$2:$O$201,MATCH("C7|paris_mid|defined_classified|diff::2_non_western",Results_Long!$AK$2:$AK$201,0))) -> — | G44: =INDEX(Results_Long!$F$2:$F$201,MATCH("C7|paris_mid|defined_classified|diff::2_non_western",Results_Long!$AK$2:$AK$201,0)) -> 3LMA-RVE_CR2
A46: Level contrasts (M_A) | B46: dz | C46: df | D46: p
A47: 1_western vs 2_non_western | B47: =IF(ISBLANK(INDEX(Results_Long!$K$2:$K$201,MATCH("C7|levels|classified|pair::1_western - 2_non_western",Results_Long!$AK$2:$AK$201,0))),"n.e.",INDEX(Results_Long!$K$2:$K$201,MATCH("C7|levels|classified|pair::1_western - 2_non_western",Results_Long!$AK$2:$AK$201,0))) -> 0.0052740422 | C47: =IF(ISBLANK(INDEX(Results_Long!$N$2:$N$201,MATCH("C7|levels|classified|pair::1_western - 2_non_western",Results_Long!$AK$2:$AK$201,0))),"n.e.",INDEX(Results_Long!$N$2:$N$201,MATCH("C7|levels|classified|pair::1_western - 2_non_western",Results_Long!$AK$2:$AK$201,0))) -> 9.2585497 | D47: =IF(ISBLANK(INDEX(Results_Long!$O$2:$O$201,MATCH("C7|levels|classified|pair::1_western - 2_non_western",Results_Long!$AK$2:$AK$201,0))),"—",INDEX(Results_Long!$O$2:$O$201,MATCH("C7|levels|classified|pair::1_western - 2_non_western",Results_Long!$AK$2:$AK$201,0))) -> 0.87988987
A49: Levels equal (HTZ) | B49: =IF(ISBLANK(INDEX(Results_Long!$M$2:$M$201,MATCH("C7|levels|classified|levels_HTZ",Results_Long!$AK$2:$AK$201,0))),"n.e.",INDEX(Results_Long!$M$2:$M$201,MATCH("C7|levels|classified|levels_HTZ",Results_Long!$AK$2:$AK$201,0))) -> 0.024129501 | C49: =IF(ISBLANK(INDEX(Results_Long!$N$2:$N$201,MATCH("C7|levels|classified|levels_HTZ",Results_Long!$AK$2:$AK$201,0))),"n.e.",INDEX(Results_Long!$N$2:$N$201,MATCH("C7|levels|classified|levels_HTZ",Results_Long!$AK$2:$AK$201,0))) -> 9.2585497 | D49: =IF(ISBLANK(INDEX(Results_Long!$O$2:$O$201,MATCH("C7|levels|classified|levels_HTZ",Results_Long!$AK$2:$AK$201,0))),"—",INDEX(Results_Long!$O$2:$O$201,MATCH("C7|levels|classified|levels_HTZ",Results_Long!$AK$2:$AK$201,0))) -> 0.87988987 | E49: =IF(ISNUMBER(SEARCH("<3-cluster",INDEX(Results_Long!$AJ$2:$AJ$201,MATCH("C7|levels|classified|levels_HTZ",Results_Long!$AK$2:$AK$201,0)))),"touches <3-cluster cell","")
A50: Moderation test (interaction HTZ) | B50: =IF(ISBLANK(INDEX(Results_Long!$M$2:$M$201,MATCH("C7|paris_mid|defined_classified|interaction_HTZ",Results_Long!$AK$2:$AK$201,0))),"n.e.",INDEX(Results_Long!$M$2:$M$201,MATCH("C7|paris_mid|defined_classified|interaction_HTZ",Results_Long!$AK$2:$AK$201,0))) -> 0.067668187 | C50: =IF(ISBLANK(INDEX(Results_Long!$N$2:$N$201,MATCH("C7|paris_mid|defined_classified|interaction_HTZ",Results_Long!$AK$2:$AK$201,0))),"n.e.",INDEX(Results_Long!$N$2:$N$201,MATCH("C7|paris_mid|defined_classified|interaction_HTZ",Results_Long!$AK$2:$AK$201,0))) -> 13.146308 | D50: =IF(ISBLANK(INDEX(Results_Long!$O$2:$O$201,MATCH("C7|paris_mid|defined_classified|interaction_HTZ",Results_Long!$AK$2:$AK$201,0))),"—",INDEX(Results_Long!$O$2:$O$201,MATCH("C7|paris_mid|defined_classified|interaction_HTZ",Results_Long!$AK$2:$AK$201,0))) -> 0.79879242 | E50: =IF(ISNUMBER(SEARCH("<3-cluster",INDEX(Results_Long!$AJ$2:$AJ$201,MATCH("C7|paris_mid|defined_classified|interaction_HTZ",Results_Long!$AK$2:$AK$201,0)))),"touches <3-cluster cell","")
A53: C8 — country_legal
A54: Level (M_A) | B54: r | C54: CI_r low | D54: CI_r high | E54: PI_r low | F54: PI_r high | G54: df
A55: 1_common law | B55: =IF(ISBLANK(INDEX(Results_Long!$T$2:$T$201,MATCH("C8|levels|classified|lvl::1_common law",Results_Long!$AK$2:$AK$201,0))),"n.e.",INDEX(Results_Long!$T$2:$T$201,MATCH("C8|levels|classified|lvl::1_common law",Results_Long!$AK$2:$AK$201,0))) -> -0.06371518 | C55: =IF(ISBLANK(INDEX(Results_Long!$U$2:$U$201,MATCH("C8|levels|classified|lvl::1_common law",Results_Long!$AK$2:$AK$201,0))),"n.e.",INDEX(Results_Long!$U$2:$U$201,MATCH("C8|levels|classified|lvl::1_common law",Results_Long!$AK$2:$AK$201,0))) -> -0.13307492 | D55: =IF(ISBLANK(INDEX(Results_Long!$V$2:$V$201,MATCH("C8|levels|classified|lvl::1_common law",Results_Long!$AK$2:$AK$201,0))),"n.e.",INDEX(Results_Long!$V$2:$V$201,MATCH("C8|levels|classified|lvl::1_common law",Results_Long!$AK$2:$AK$201,0))) -> 0.0062656116 | E55: =IF(ISBLANK(INDEX(Results_Long!$W$2:$W$201,MATCH("C8|levels|classified|lvl::1_common law",Results_Long!$AK$2:$AK$201,0))),"n.e.",INDEX(Results_Long!$W$2:$W$201,MATCH("C8|levels|classified|lvl::1_common law",Results_Long!$AK$2:$AK$201,0))) -> -0.45199806 | F55: =IF(ISBLANK(INDEX(Results_Long!$X$2:$X$201,MATCH("C8|levels|classified|lvl::1_common law",Results_Long!$AK$2:$AK$201,0))),"n.e.",INDEX(Results_Long!$X$2:$X$201,MATCH("C8|levels|classified|lvl::1_common law",Results_Long!$AK$2:$AK$201,0))) -> 0.34486632 | G55: =IF(ISBLANK(INDEX(Results_Long!$N$2:$N$201,MATCH("C8|levels|classified|lvl::1_common law",Results_Long!$AK$2:$AK$201,0))),"n.e.",INDEX(Results_Long!$N$2:$N$201,MATCH("C8|levels|classified|lvl::1_common law",Results_Long!$AK$2:$AK$201,0))) -> 30.743132
A56: 2_civil law | B56: =IF(ISBLANK(INDEX(Results_Long!$T$2:$T$201,MATCH("C8|levels|classified|lvl::2_civil law",Results_Long!$AK$2:$AK$201,0))),"n.e.",INDEX(Results_Long!$T$2:$T$201,MATCH("C8|levels|classified|lvl::2_civil law",Results_Long!$AK$2:$AK$201,0))) -> -0.067374676 | C56: =IF(ISBLANK(INDEX(Results_Long!$U$2:$U$201,MATCH("C8|levels|classified|lvl::2_civil law",Results_Long!$AK$2:$AK$201,0))),"n.e.",INDEX(Results_Long!$U$2:$U$201,MATCH("C8|levels|classified|lvl::2_civil law",Results_Long!$AK$2:$AK$201,0))) -> -0.10852106 | D56: =IF(ISBLANK(INDEX(Results_Long!$V$2:$V$201,MATCH("C8|levels|classified|lvl::2_civil law",Results_Long!$AK$2:$AK$201,0))),"n.e.",INDEX(Results_Long!$V$2:$V$201,MATCH("C8|levels|classified|lvl::2_civil law",Results_Long!$AK$2:$AK$201,0))) -> -0.025997837 | E56: =IF(ISBLANK(INDEX(Results_Long!$W$2:$W$201,MATCH("C8|levels|classified|lvl::2_civil law",Results_Long!$AK$2:$AK$201,0))),"n.e.",INDEX(Results_Long!$W$2:$W$201,MATCH("C8|levels|classified|lvl::2_civil law",Results_Long!$AK$2:$AK$201,0))) -> -0.45882283 | F56: =IF(ISBLANK(INDEX(Results_Long!$X$2:$X$201,MATCH("C8|levels|classified|lvl::2_civil law",Results_Long!$AK$2:$AK$201,0))),"n.e.",INDEX(Results_Long!$X$2:$X$201,MATCH("C8|levels|classified|lvl::2_civil law",Results_Long!$AK$2:$AK$201,0))) -> 0.34597607 | G56: =IF(ISBLANK(INDEX(Results_Long!$N$2:$N$201,MATCH("C8|levels|classified|lvl::2_civil law",Results_Long!$AK$2:$AK$201,0))),"n.e.",INDEX(Results_Long!$N$2:$N$201,MATCH("C8|levels|classified|lvl::2_civil law",Results_Long!$AK$2:$AK$201,0))) -> 20.452605
A58: Paris shift (M_B) | B58: dz (post-pre) | C58: CI_z low | D58: CI_z high | E58: df | F58: p | G58: status
A59: 1_common law | B59: =IF(ISBLANK(INDEX(Results_Long!$K$2:$K$201,MATCH("C8|paris_mid|defined_classified|diff::1_common law",Results_Long!$AK$2:$AK$201,0))),"n.e.",INDEX(Results_Long!$K$2:$K$201,MATCH("C8|paris_mid|defined_classified|diff::1_common law",Results_Long!$AK$2:$AK$201,0))) -> -0.021798871 | C59: =IF(ISBLANK(INDEX(Results_Long!$P$2:$P$201,MATCH("C8|paris_mid|defined_classified|diff::1_common law",Results_Long!$AK$2:$AK$201,0))),"n.e.",INDEX(Results_Long!$P$2:$P$201,MATCH("C8|paris_mid|defined_classified|diff::1_common law",Results_Long!$AK$2:$AK$201,0))) -> -0.70348922 | D59: =IF(ISBLANK(INDEX(Results_Long!$Q$2:$Q$201,MATCH("C8|paris_mid|defined_classified|diff::1_common law",Results_Long!$AK$2:$AK$201,0))),"n.e.",INDEX(Results_Long!$Q$2:$Q$201,MATCH("C8|paris_mid|defined_classified|diff::1_common law",Results_Long!$AK$2:$AK$201,0))) -> 0.65989148 | E59: =IF(ISBLANK(INDEX(Results_Long!$N$2:$N$201,MATCH("C8|paris_mid|defined_classified|diff::1_common law",Results_Long!$AK$2:$AK$201,0))),"n.e.",INDEX(Results_Long!$N$2:$N$201,MATCH("C8|paris_mid|defined_classified|diff::1_common law",Results_Long!$AK$2:$AK$201,0))) -> 1.0770482 | F59: =IF(ISBLANK(INDEX(Results_Long!$O$2:$O$201,MATCH("C8|paris_mid|defined_classified|diff::1_common law",Results_Long!$AK$2:$AK$201,0))),"—",INDEX(Results_Long!$O$2:$O$201,MATCH("C8|paris_mid|defined_classified|diff::1_common law",Results_Long!$AK$2:$AK$201,0))) -> — | G59: =INDEX(Results_Long!$F$2:$F$201,MATCH("C8|paris_mid|defined_classified|diff::1_common law",Results_Long!$AK$2:$AK$201,0)) -> 3LMA-RVE_CR2
A60: 2_civil law | B60: =IF(ISBLANK(INDEX(Results_Long!$K$2:$K$201,MATCH("C8|paris_mid|defined_classified|diff::2_civil law",Results_Long!$AK$2:$AK$201,0))),"n.e.",INDEX(Results_Long!$K$2:$K$201,MATCH("C8|paris_mid|defined_classified|diff::2_civil law",Results_Long!$AK$2:$AK$201,0))) -> 0.021836745 | C60: =IF(ISBLANK(INDEX(Results_Long!$P$2:$P$201,MATCH("C8|paris_mid|defined_classified|diff::2_civil law",Results_Long!$AK$2:$AK$201,0))),"n.e.",INDEX(Results_Long!$P$2:$P$201,MATCH("C8|paris_mid|defined_classified|diff::2_civil law",Results_Long!$AK$2:$AK$201,0))) -> -0.044840714 | D60: =IF(ISBLANK(INDEX(Results_Long!$Q$2:$Q$201,MATCH("C8|paris_mid|defined_classified|diff::2_civil law",Results_Long!$AK$2:$AK$201,0))),"n.e.",INDEX(Results_Long!$Q$2:$Q$201,MATCH("C8|paris_mid|defined_classified|diff::2_civil law",Results_Long!$AK$2:$AK$201,0))) -> 0.088514204 | E60: =IF(ISBLANK(INDEX(Results_Long!$N$2:$N$201,MATCH("C8|paris_mid|defined_classified|diff::2_civil law",Results_Long!$AK$2:$AK$201,0))),"n.e.",INDEX(Results_Long!$N$2:$N$201,MATCH("C8|paris_mid|defined_classified|diff::2_civil law",Results_Long!$AK$2:$AK$201,0))) -> 2.5375634 | F60: =IF(ISBLANK(INDEX(Results_Long!$O$2:$O$201,MATCH("C8|paris_mid|defined_classified|diff::2_civil law",Results_Long!$AK$2:$AK$201,0))),"—",INDEX(Results_Long!$O$2:$O$201,MATCH("C8|paris_mid|defined_classified|diff::2_civil law",Results_Long!$AK$2:$AK$201,0))) -> — | G60: =INDEX(Results_Long!$F$2:$F$201,MATCH("C8|paris_mid|defined_classified|diff::2_civil law",Results_Long!$AK$2:$AK$201,0)) -> 3LMA-RVE_CR2
A62: Level contrasts (M_A) | B62: dz | C62: df | D62: p
A63: 1_common law vs 2_civil law | B63: =IF(ISBLANK(INDEX(Results_Long!$K$2:$K$201,MATCH("C8|levels|classified|pair::1_common law - 2_civil law",Results_Long!$AK$2:$AK$201,0))),"n.e.",INDEX(Results_Long!$K$2:$K$201,MATCH("C8|levels|classified|pair::1_common law - 2_civil law",Results_Long!$AK$2:$AK$201,0))) -> 0.0036752896 | C63: =IF(ISBLANK(INDEX(Results_Long!$N$2:$N$201,MATCH("C8|levels|classified|pair::1_common law - 2_civil law",Results_Long!$AK$2:$AK$201,0))),"n.e.",INDEX(Results_Long!$N$2:$N$201,MATCH("C8|levels|classified|pair::1_common law - 2_civil law",Results_Long!$AK$2:$AK$201,0))) -> 7.5169366 | D63: =IF(ISBLANK(INDEX(Results_Long!$O$2:$O$201,MATCH("C8|levels|classified|pair::1_common law - 2_civil law",Results_Long!$AK$2:$AK$201,0))),"—",INDEX(Results_Long!$O$2:$O$201,MATCH("C8|levels|classified|pair::1_common law - 2_civil law",Results_Long!$AK$2:$AK$201,0))) -> 0.9288473
A65: Levels equal (HTZ) | B65: =IF(ISBLANK(INDEX(Results_Long!$M$2:$M$201,MATCH("C8|levels|classified|levels_HTZ",Results_Long!$AK$2:$AK$201,0))),"n.e.",INDEX(Results_Long!$M$2:$M$201,MATCH("C8|levels|classified|levels_HTZ",Results_Long!$AK$2:$AK$201,0))) -> 0.0085251862 | C65: =IF(ISBLANK(INDEX(Results_Long!$N$2:$N$201,MATCH("C8|levels|classified|levels_HTZ",Results_Long!$AK$2:$AK$201,0))),"n.e.",INDEX(Results_Long!$N$2:$N$201,MATCH("C8|levels|classified|levels_HTZ",Results_Long!$AK$2:$AK$201,0))) -> 7.5169366 | D65: =IF(ISBLANK(INDEX(Results_Long!$O$2:$O$201,MATCH("C8|levels|classified|levels_HTZ",Results_Long!$AK$2:$AK$201,0))),"—",INDEX(Results_Long!$O$2:$O$201,MATCH("C8|levels|classified|levels_HTZ",Results_Long!$AK$2:$AK$201,0))) -> 0.9288473 | E65: =IF(ISNUMBER(SEARCH("<3-cluster",INDEX(Results_Long!$AJ$2:$AJ$201,MATCH("C8|levels|classified|levels_HTZ",Results_Long!$AK$2:$AK$201,0)))),"touches <3-cluster cell","")
A66: Moderation test (interaction HTZ) | B66: =IF(ISBLANK(INDEX(Results_Long!$M$2:$M$201,MATCH("C8|paris_mid|defined_classified|interaction_HTZ",Results_Long!$AK$2:$AK$201,0))),"n.e.",INDEX(Results_Long!$M$2:$M$201,MATCH("C8|paris_mid|defined_classified|interaction_HTZ",Results_Long!$AK$2:$AK$201,0))) -> 0.44248965 | C66: =IF(ISBLANK(INDEX(Results_Long!$N$2:$N$201,MATCH("C8|paris_mid|defined_classified|interaction_HTZ",Results_Long!$AK$2:$AK$201,0))),"n.e.",INDEX(Results_Long!$N$2:$N$201,MATCH("C8|paris_mid|defined_classified|interaction_HTZ",Results_Long!$AK$2:$AK$201,0))) -> 1.214221 | D66: =IF(ISBLANK(INDEX(Results_Long!$O$2:$O$201,MATCH("C8|paris_mid|defined_classified|interaction_HTZ",Results_Long!$AK$2:$AK$201,0))),"—",INDEX(Results_Long!$O$2:$O$201,MATCH("C8|paris_mid|defined_classified|interaction_HTZ",Results_Long!$AK$2:$AK$201,0))) -> 0.60963825 | E66: =IF(ISNUMBER(SEARCH("<3-cluster",INDEX(Results_Long!$AJ$2:$AJ$201,MATCH("C8|paris_mid|defined_classified|interaction_HTZ",Results_Long!$AK$2:$AK$201,0)))),"touches <3-cluster cell","") -> touches <3-cluster cell
A69: Interpretation
A70: The pattern replicates: narrow negative level band, small mixed-sign period shifts, no moderation.
A71: Several period contrasts fall to the df < 5 rule despite adequate cluster counts on one side — the Satterthwaite df is governed by the thinner side; all such rows are flagged, none suppressed.
A73: Question | B73: Answer
A74: Why are both C8 shifts descriptive? | B74: The common-law post cell holds two clusters and the resulting Satterthwaite dfs fall below five on both sides; the panel HTZ is reported with the flag [R6].
A76: Mechanical outcome: no moderation and no significant within-level Paris shift in any of the four remaining panels; wording per the resolved gate [DEC-044/DEC-047].

Sheet 9_C9_Unified
A1: Unified models V1 / V2 — conditional Paris contrast
A2: Two-variant ladder with the mechanical design-df + identifiability rule [DEC-043]
A3: Reference coding; refs performance / loan / without ETS-CT / 1_US (+ V2 refs); z scale
A5: Design-rule verdicts (echo rows)
A6: Variant · block | B6: design-df | C6: Verdict
A7: cc_v1 · CER_measure | B7: =IF(ISBLANK(INDEX(Results_Long!$AG$2:$AG$201,MATCH("C9|design_rule|cc_v1|rule::CER_measure",Results_Long!$AK$2:$AK$201,0))),"n.e.",INDEX(Results_Long!$AG$2:$AG$201,MATCH("C9|design_rule|cc_v1|rule::CER_measure",Results_Long!$AK$2:$AK$201,0))) -> 6.9056448 | C7: =IF(ISNUMBER(SEARCH("excluded_structural",INDEX(Results_Long!$AJ$2:$AJ$201,MATCH("C9|design_rule|cc_v1|rule::CER_measure",Results_Long!$AK$2:$AK$201,0)))),"excluded_structural",IF(ISNUMBER(SEARCH("excluded_df",INDEX(Results_Long!$AJ$2:$AJ$201,MATCH("C9|design_rule|cc_v1|rule::CER_measure",Results_Long!$AK$2:$AK$201,0)))),"excluded_df",IF(ISNUMBER(SEARCH("excluded_pd",INDEX(Results_Long!$AJ$2:$AJ$201,MATCH("C9|design_rule|cc_v1|rule::CER_measure",Results_Long!$AK$2:$AK$201,0)))),"excluded_pd","admitted"))) -> admitted
A8: cc_v1 · COD_instrument | B8: =IF(ISBLANK(INDEX(Results_Long!$AG$2:$AG$201,MATCH("C9|design_rule|cc_v1|rule::COD_instrument",Results_Long!$AK$2:$AK$201,0))),"n.e.",INDEX(Results_Long!$AG$2:$AG$201,MATCH("C9|design_rule|cc_v1|rule::COD_instrument",Results_Long!$AK$2:$AK$201,0))) -> 1.3679352 | C8: =IF(ISNUMBER(SEARCH("excluded_structural",INDEX(Results_Long!$AJ$2:$AJ$201,MATCH("C9|design_rule|cc_v1|rule::COD_instrument",Results_Long!$AK$2:$AK$201,0)))),"excluded_structural",IF(ISNUMBER(SEARCH("excluded_df",INDEX(Results_Long!$AJ$2:$AJ$201,MATCH("C9|design_rule|cc_v1|rule::COD_instrument",Results_Long!$AK$2:$AK$201,0)))),"excluded_df",IF(ISNUMBER(SEARCH("excluded_pd",INDEX(Results_Long!$AJ$2:$AJ$201,MATCH("C9|design_rule|cc_v1|rule::COD_instrument",Results_Long!$AK$2:$AK$201,0)))),"excluded_pd","admitted"))) -> excluded_df
A9: cc_v1 · regulation3 | B9: =IF(ISBLANK(INDEX(Results_Long!$AG$2:$AG$201,MATCH("C9|design_rule|cc_v1|rule::regulation3",Results_Long!$AK$2:$AK$201,0))),"n.e.",INDEX(Results_Long!$AG$2:$AG$201,MATCH("C9|design_rule|cc_v1|rule::regulation3",Results_Long!$AK$2:$AK$201,0))) -> 3.0904763 | C9: =IF(ISNUMBER(SEARCH("excluded_structural",INDEX(Results_Long!$AJ$2:$AJ$201,MATCH("C9|design_rule|cc_v1|rule::regulation3",Results_Long!$AK$2:$AK$201,0)))),"excluded_structural",IF(ISNUMBER(SEARCH("excluded_df",INDEX(Results_Long!$AJ$2:$AJ$201,MATCH("C9|design_rule|cc_v1|rule::regulation3",Results_Long!$AK$2:$AK$201,0)))),"excluded_df",IF(ISNUMBER(SEARCH("excluded_pd",INDEX(Results_Long!$AJ$2:$AJ$201,MATCH("C9|design_rule|cc_v1|rule::regulation3",Results_Long!$AK$2:$AK$201,0)))),"excluded_pd","admitted"))) -> excluded_df
A10: cc_v1 · country_region | B10: =IF(ISBLANK(INDEX(Results_Long!$AG$2:$AG$201,MATCH("C9|design_rule|cc_v1|rule::country_region",Results_Long!$AK$2:$AK$201,0))),"n.e.",INDEX(Results_Long!$AG$2:$AG$201,MATCH("C9|design_rule|cc_v1|rule::country_region",Results_Long!$AK$2:$AK$201,0))) -> 9.5760855 | C10: =IF(ISNUMBER(SEARCH("excluded_structural",INDEX(Results_Long!$AJ$2:$AJ$201,MATCH("C9|design_rule|cc_v1|rule::country_region",Results_Long!$AK$2:$AK$201,0)))),"excluded_structural",IF(ISNUMBER(SEARCH("excluded_df",INDEX(Results_Long!$AJ$2:$AJ$201,MATCH("C9|design_rule|cc_v1|rule::country_region",Results_Long!$AK$2:$AK$201,0)))),"excluded_df",IF(ISNUMBER(SEARCH("excluded_pd",INDEX(Results_Long!$AJ$2:$AJ$201,MATCH("C9|design_rule|cc_v1|rule::country_region",Results_Long!$AK$2:$AK$201,0)))),"excluded_pd","admitted"))) -> admitted
A11: cc_v2 · CER_measure | B11: =IF(ISBLANK(INDEX(Results_Long!$AG$2:$AG$201,MATCH("C9|design_rule|cc_v2|rule::CER_measure",Results_Long!$AK$2:$AK$201,0))),"n.e.",INDEX(Results_Long!$AG$2:$AG$201,MATCH("C9|design_rule|cc_v2|rule::CER_measure",Results_Long!$AK$2:$AK$201,0))) -> 3.4105756 | C11: =IF(ISNUMBER(SEARCH("excluded_structural",INDEX(Results_Long!$AJ$2:$AJ$201,MATCH("C9|design_rule|cc_v2|rule::CER_measure",Results_Long!$AK$2:$AK$201,0)))),"excluded_structural",IF(ISNUMBER(SEARCH("excluded_df",INDEX(Results_Long!$AJ$2:$AJ$201,MATCH("C9|design_rule|cc_v2|rule::CER_measure",Results_Long!$AK$2:$AK$201,0)))),"excluded_df",IF(ISNUMBER(SEARCH("excluded_pd",INDEX(Results_Long!$AJ$2:$AJ$201,MATCH("C9|design_rule|cc_v2|rule::CER_measure",Results_Long!$AK$2:$AK$201,0)))),"excluded_pd","admitted"))) -> excluded_df
A12: cc_v2 · COD_instrument | B12: =IF(ISBLANK(INDEX(Results_Long!$AG$2:$AG$201,MATCH("C9|design_rule|cc_v2|rule::COD_instrument",Results_Long!$AK$2:$AK$201,0))),"n.e.",INDEX(Results_Long!$AG$2:$AG$201,MATCH("C9|design_rule|cc_v2|rule::COD_instrument",Results_Long!$AK$2:$AK$201,0))) -> 3.5753431 | C12: =IF(ISNUMBER(SEARCH("excluded_structural",INDEX(Results_Long!$AJ$2:$AJ$201,MATCH("C9|design_rule|cc_v2|rule::COD_instrument",Results_Long!$AK$2:$AK$201,0)))),"excluded_structural",IF(ISNUMBER(SEARCH("excluded_df",INDEX(Results_Long!$AJ$2:$AJ$201,MATCH("C9|design_rule|cc_v2|rule::COD_instrument",Results_Long!$AK$2:$AK$201,0)))),"excluded_df",IF(ISNUMBER(SEARCH("excluded_pd",INDEX(Results_Long!$AJ$2:$AJ$201,MATCH("C9|design_rule|cc_v2|rule::COD_instrument",Results_Long!$AK$2:$AK$201,0)))),"excluded_pd","admitted"))) -> excluded_df
A13: cc_v2 · industry | B13: =IF(ISBLANK(INDEX(Results_Long!$AG$2:$AG$201,MATCH("C9|design_rule|cc_v2|rule::industry",Results_Long!$AK$2:$AK$201,0))),"n.e.",INDEX(Results_Long!$AG$2:$AG$201,MATCH("C9|design_rule|cc_v2|rule::industry",Results_Long!$AK$2:$AK$201,0))) -> 4.2870894 | C13: =IF(ISNUMBER(SEARCH("excluded_structural",INDEX(Results_Long!$AJ$2:$AJ$201,MATCH("C9|design_rule|cc_v2|rule::industry",Results_Long!$AK$2:$AK$201,0)))),"excluded_structural",IF(ISNUMBER(SEARCH("excluded_df",INDEX(Results_Long!$AJ$2:$AJ$201,MATCH("C9|design_rule|cc_v2|rule::industry",Results_Long!$AK$2:$AK$201,0)))),"excluded_df",IF(ISNUMBER(SEARCH("excluded_pd",INDEX(Results_Long!$AJ$2:$AJ$201,MATCH("C9|design_rule|cc_v2|rule::industry",Results_Long!$AK$2:$AK$201,0)))),"excluded_pd","admitted"))) -> excluded_df
A14: cc_v2 · regulation3 | B14: =IF(ISBLANK(INDEX(Results_Long!$AG$2:$AG$201,MATCH("C9|design_rule|cc_v2|rule::regulation3",Results_Long!$AK$2:$AK$201,0))),"n.e.",INDEX(Results_Long!$AG$2:$AG$201,MATCH("C9|design_rule|cc_v2|rule::regulation3",Results_Long!$AK$2:$AK$201,0))) -> 4.0494971 | C14: =IF(ISNUMBER(SEARCH("excluded_structural",INDEX(Results_Long!$AJ$2:$AJ$201,MATCH("C9|design_rule|cc_v2|rule::regulation3",Results_Long!$AK$2:$AK$201,0)))),"excluded_structural",IF(ISNUMBER(SEARCH("excluded_df",INDEX(Results_Long!$AJ$2:$AJ$201,MATCH("C9|design_rule|cc_v2|rule::regulation3",Results_Long!$AK$2:$AK$201,0)))),"excluded_df",IF(ISNUMBER(SEARCH("excluded_pd",INDEX(Results_Long!$AJ$2:$AJ$201,MATCH("C9|design_rule|cc_v2|rule::regulation3",Results_Long!$AK$2:$AK$201,0)))),"excluded_pd","admitted"))) -> excluded_df
A15: cc_v2 · country_region | B15: =IF(ISBLANK(INDEX(Results_Long!$AG$2:$AG$201,MATCH("C9|design_rule|cc_v2|rule::country_region",Results_Long!$AK$2:$AK$201,0))),"n.e.",INDEX(Results_Long!$AG$2:$AG$201,MATCH("C9|design_rule|cc_v2|rule::country_region",Results_Long!$AK$2:$AK$201,0))) -> n.e. | C15: =IF(ISNUMBER(SEARCH("excluded_structural",INDEX(Results_Long!$AJ$2:$AJ$201,MATCH("C9|design_rule|cc_v2|rule::country_region",Results_Long!$AK$2:$AK$201,0)))),"excluded_structural",IF(ISNUMBER(SEARCH("excluded_df",INDEX(Results_Long!$AJ$2:$AJ$201,MATCH("C9|design_rule|cc_v2|rule::country_region",Results_Long!$AK$2:$AK$201,0)))),"excluded_df",IF(ISNUMBER(SEARCH("excluded_pd",INDEX(Results_Long!$AJ$2:$AJ$201,MATCH("C9|design_rule|cc_v2|rule::country_region",Results_Long!$AK$2:$AK$201,0)))),"excluded_pd","admitted"))) -> excluded_structural
A16: cc_v2 · country_econ | B16: =IF(ISBLANK(INDEX(Results_Long!$AG$2:$AG$201,MATCH("C9|design_rule|cc_v2|rule::country_econ",Results_Long!$AK$2:$AK$201,0))),"n.e.",INDEX(Results_Long!$AG$2:$AG$201,MATCH("C9|design_rule|cc_v2|rule::country_econ",Results_Long!$AK$2:$AK$201,0))) -> n.e. | C16: =IF(ISNUMBER(SEARCH("excluded_structural",INDEX(Results_Long!$AJ$2:$AJ$201,MATCH("C9|design_rule|cc_v2|rule::country_econ",Results_Long!$AK$2:$AK$201,0)))),"excluded_structural",IF(ISNUMBER(SEARCH("excluded_df",INDEX(Results_Long!$AJ$2:$AJ$201,MATCH("C9|design_rule|cc_v2|rule::country_econ",Results_Long!$AK$2:$AK$201,0)))),"excluded_df",IF(ISNUMBER(SEARCH("excluded_pd",INDEX(Results_Long!$AJ$2:$AJ$201,MATCH("C9|design_rule|cc_v2|rule::country_econ",Results_Long!$AK$2:$AK$201,0)))),"excluded_pd","admitted"))) -> excluded_structural
A17: cc_v2 · country_culture | B17: =IF(ISBLANK(INDEX(Results_Long!$AG$2:$AG$201,MATCH("C9|design_rule|cc_v2|rule::country_culture",Results_Long!$AK$2:$AK$201,0))),"n.e.",INDEX(Results_Long!$AG$2:$AG$201,MATCH("C9|design_rule|cc_v2|rule::country_culture",Results_Long!$AK$2:$AK$201,0))) -> n.e. | C17: =IF(ISNUMBER(SEARCH("excluded_structural",INDEX(Results_Long!$AJ$2:$AJ$201,MATCH("C9|design_rule|cc_v2|rule::country_culture",Results_Long!$AK$2:$AK$201,0)))),"excluded_structural",IF(ISNUMBER(SEARCH("excluded_df",INDEX(Results_Long!$AJ$2:$AJ$201,MATCH("C9|design_rule|cc_v2|rule::country_culture",Results_Long!$AK$2:$AK$201,0)))),"excluded_df",IF(ISNUMBER(SEARCH("excluded_pd",INDEX(Results_Long!$AJ$2:$AJ$201,MATCH("C9|design_rule|cc_v2|rule::country_culture",Results_Long!$AK$2:$AK$201,0)))),"excluded_pd","admitted"))) -> excluded_structural
A18: cc_v2 · country_legal | B18: =IF(ISBLANK(INDEX(Results_Long!$AG$2:$AG$201,MATCH("C9|design_rule|cc_v2|rule::country_legal",Results_Long!$AK$2:$AK$201,0))),"n.e.",INDEX(Results_Long!$AG$2:$AG$201,MATCH("C9|design_rule|cc_v2|rule::country_legal",Results_Long!$AK$2:$AK$201,0))) -> n.e. | C18: =IF(ISNUMBER(SEARCH("excluded_structural",INDEX(Results_Long!$AJ$2:$AJ$201,MATCH("C9|design_rule|cc_v2|rule::country_legal",Results_Long!$AK$2:$AK$201,0)))),"excluded_structural",IF(ISNUMBER(SEARCH("excluded_df",INDEX(Results_Long!$AJ$2:$AJ$201,MATCH("C9|design_rule|cc_v2|rule::country_legal",Results_Long!$AK$2:$AK$201,0)))),"excluded_df",IF(ISNUMBER(SEARCH("excluded_pd",INDEX(Results_Long!$AJ$2:$AJ$201,MATCH("C9|design_rule|cc_v2|rule::country_legal",Results_Long!$AK$2:$AK$201,0)))),"excluded_pd","admitted"))) -> excluded_structural
A20: V1 (lean) — coefficients (z scale)
A21: Term | B21: b | C21: SE | D21: df | E21: p | F21: status
A22: intercept | B22: =IF(ISBLANK(INDEX(Results_Long!$K$2:$K$201,MATCH("C9|unified_cc_v1|cc_v1|intercept",Results_Long!$AK$2:$AK$201,0))),"n.e.",INDEX(Results_Long!$K$2:$K$201,MATCH("C9|unified_cc_v1|cc_v1|intercept",Results_Long!$AK$2:$AK$201,0))) -> -0.0078837665 | C22: =IF(ISBLANK(INDEX(Results_Long!$L$2:$L$201,MATCH("C9|unified_cc_v1|cc_v1|intercept",Results_Long!$AK$2:$AK$201,0))),"n.e.",INDEX(Results_Long!$L$2:$L$201,MATCH("C9|unified_cc_v1|cc_v1|intercept",Results_Long!$AK$2:$AK$201,0))) -> 0.023334076 | D22: =IF(ISBLANK(INDEX(Results_Long!$N$2:$N$201,MATCH("C9|unified_cc_v1|cc_v1|intercept",Results_Long!$AK$2:$AK$201,0))),"n.e.",INDEX(Results_Long!$N$2:$N$201,MATCH("C9|unified_cc_v1|cc_v1|intercept",Results_Long!$AK$2:$AK$201,0))) -> 25.068769 | E22: =IF(ISBLANK(INDEX(Results_Long!$O$2:$O$201,MATCH("C9|unified_cc_v1|cc_v1|intercept",Results_Long!$AK$2:$AK$201,0))),"—",INDEX(Results_Long!$O$2:$O$201,MATCH("C9|unified_cc_v1|cc_v1|intercept",Results_Long!$AK$2:$AK$201,0))) -> 0.73827798 | F22: =INDEX(Results_Long!$F$2:$F$201,MATCH("C9|unified_cc_v1|cc_v1|intercept",Results_Long!$AK$2:$AK$201,0)) -> 3LMA-RVE_CR2
A23: pp_mid_lag0 | B23: =IF(ISBLANK(INDEX(Results_Long!$K$2:$K$201,MATCH("C9|unified_cc_v1|cc_v1|pp_mid_lag0",Results_Long!$AK$2:$AK$201,0))),"n.e.",INDEX(Results_Long!$K$2:$K$201,MATCH("C9|unified_cc_v1|cc_v1|pp_mid_lag0",Results_Long!$AK$2:$AK$201,0))) -> 0.0077591816 | C23: =IF(ISBLANK(INDEX(Results_Long!$L$2:$L$201,MATCH("C9|unified_cc_v1|cc_v1|pp_mid_lag0",Results_Long!$AK$2:$AK$201,0))),"n.e.",INDEX(Results_Long!$L$2:$L$201,MATCH("C9|unified_cc_v1|cc_v1|pp_mid_lag0",Results_Long!$AK$2:$AK$201,0))) -> 0.025012161 | D23: =IF(ISBLANK(INDEX(Results_Long!$N$2:$N$201,MATCH("C9|unified_cc_v1|cc_v1|pp_mid_lag0",Results_Long!$AK$2:$AK$201,0))),"n.e.",INDEX(Results_Long!$N$2:$N$201,MATCH("C9|unified_cc_v1|cc_v1|pp_mid_lag0",Results_Long!$AK$2:$AK$201,0))) -> 5.1326846 | E23: =IF(ISBLANK(INDEX(Results_Long!$O$2:$O$201,MATCH("C9|unified_cc_v1|cc_v1|pp_mid_lag0",Results_Long!$AK$2:$AK$201,0))),"—",INDEX(Results_Long!$O$2:$O$201,MATCH("C9|unified_cc_v1|cc_v1|pp_mid_lag0",Results_Long!$AK$2:$AK$201,0))) -> 0.76859865 | F23: =INDEX(Results_Long!$F$2:$F$201,MATCH("C9|unified_cc_v1|cc_v1|pp_mid_lag0",Results_Long!$AK$2:$AK$201,0)) -> 3LMA-RVE_CR2
A24: CER_measuredisclosure | B24: =IF(ISBLANK(INDEX(Results_Long!$K$2:$K$201,MATCH("C9|unified_cc_v1|cc_v1|CER_measuredisclosure",Results_Long!$AK$2:$AK$201,0))),"n.e.",INDEX(Results_Long!$K$2:$K$201,MATCH("C9|unified_cc_v1|cc_v1|CER_measuredisclosure",Results_Long!$AK$2:$AK$201,0))) -> 0.0078403171 | C24: =IF(ISBLANK(INDEX(Results_Long!$L$2:$L$201,MATCH("C9|unified_cc_v1|cc_v1|CER_measuredisclosure",Results_Long!$AK$2:$AK$201,0))),"n.e.",INDEX(Results_Long!$L$2:$L$201,MATCH("C9|unified_cc_v1|cc_v1|CER_measuredisclosure",Results_Long!$AK$2:$AK$201,0))) -> 0.033582318 | D24: =IF(ISBLANK(INDEX(Results_Long!$N$2:$N$201,MATCH("C9|unified_cc_v1|cc_v1|CER_measuredisclosure",Results_Long!$AK$2:$AK$201,0))),"n.e.",INDEX(Results_Long!$N$2:$N$201,MATCH("C9|unified_cc_v1|cc_v1|CER_measuredisclosure",Results_Long!$AK$2:$AK$201,0))) -> 4.0325634 | E24: =IF(ISBLANK(INDEX(Results_Long!$O$2:$O$201,MATCH("C9|unified_cc_v1|cc_v1|CER_measuredisclosure",Results_Long!$AK$2:$AK$201,0))),"—",INDEX(Results_Long!$O$2:$O$201,MATCH("C9|unified_cc_v1|cc_v1|CER_measuredisclosure",Results_Long!$AK$2:$AK$201,0))) -> — | F24: =INDEX(Results_Long!$F$2:$F$201,MATCH("C9|unified_cc_v1|cc_v1|CER_measuredisclosure",Results_Long!$AK$2:$AK$201,0)) -> 3LMA-RVE_CR2
A25: COD_instrumentbond (yield) | B25: =IF(ISBLANK(INDEX(Results_Long!$K$2:$K$201,MATCH("C9|unified_cc_v1|cc_v1|COD_instrumentbond (yield)",Results_Long!$AK$2:$AK$201,0))),"n.e.",INDEX(Results_Long!$K$2:$K$201,MATCH("C9|unified_cc_v1|cc_v1|COD_instrumentbond (yield)",Results_Long!$AK$2:$AK$201,0))) -> -0.052026517 | C25: =IF(ISBLANK(INDEX(Results_Long!$L$2:$L$201,MATCH("C9|unified_cc_v1|cc_v1|COD_instrumentbond (yield)",Results_Long!$AK$2:$AK$201,0))),"n.e.",INDEX(Results_Long!$L$2:$L$201,MATCH("C9|unified_cc_v1|cc_v1|COD_instrumentbond (yield)",Results_Long!$AK$2:$AK$201,0))) -> 0.0201946 | D25: =IF(ISBLANK(INDEX(Results_Long!$N$2:$N$201,MATCH("C9|unified_cc_v1|cc_v1|COD_instrumentbond (yield)",Results_Long!$AK$2:$AK$201,0))),"n.e.",INDEX(Results_Long!$N$2:$N$201,MATCH("C9|unified_cc_v1|cc_v1|COD_instrumentbond (yield)",Results_Long!$AK$2:$AK$201,0))) -> 3.4916214 | E25: =IF(ISBLANK(INDEX(Results_Long!$O$2:$O$201,MATCH("C9|unified_cc_v1|cc_v1|COD_instrumentbond (yield)",Results_Long!$AK$2:$AK$201,0))),"—",INDEX(Results_Long!$O$2:$O$201,MATCH("C9|unified_cc_v1|cc_v1|COD_instrumentbond (yield)",Results_Long!$AK$2:$AK$201,0))) -> — | F25: =INDEX(Results_Long!$F$2:$F$201,MATCH("C9|unified_cc_v1|cc_v1|COD_instrumentbond (yield)",Results_Long!$AK$2:$AK$201,0)) -> 3LMA-RVE_CR2
A26: COD_instrumentderivativ (CDS spread) | B26: =IF(ISBLANK(INDEX(Results_Long!$K$2:$K$201,MATCH("C9|unified_cc_v1|cc_v1|COD_instrumentderivativ (CDS spread)",Results_Long!$AK$2:$AK$201,0))),"n.e.",INDEX(Results_Long!$K$2:$K$201,MATCH("C9|unified_cc_v1|cc_v1|COD_instrumentderivativ (CDS spread)",Results_Long!$AK$2:$AK$201,0))) -> -0.065533577 | C26: =IF(ISBLANK(INDEX(Results_Long!$L$2:$L$201,MATCH("C9|unified_cc_v1|cc_v1|COD_instrumentderivativ (CDS spread)",Results_Long!$AK$2:$AK$201,0))),"n.e.",INDEX(Results_Long!$L$2:$L$201,MATCH("C9|unified_cc_v1|cc_v1|COD_instrumentderivativ (CDS spread)",Results_Long!$AK$2:$AK$201,0))) -> 0.076314013 | D26: =IF(ISBLANK(INDEX(Results_Long!$N$2:$N$201,MATCH("C9|unified_cc_v1|cc_v1|COD_instrumentderivativ (CDS spread)",Results_Long!$AK$2:$AK$201,0))),"n.e.",INDEX(Results_Long!$N$2:$N$201,MATCH("C9|unified_cc_v1|cc_v1|COD_instrumentderivativ (CDS spread)",Results_Long!$AK$2:$AK$201,0))) -> 3.1071595 | E26: =IF(ISBLANK(INDEX(Results_Long!$O$2:$O$201,MATCH("C9|unified_cc_v1|cc_v1|COD_instrumentderivativ (CDS spread)",Results_Long!$AK$2:$AK$201,0))),"—",INDEX(Results_Long!$O$2:$O$201,MATCH("C9|unified_cc_v1|cc_v1|COD_instrumentderivativ (CDS spread)",Results_Long!$AK$2:$AK$201,0))) -> — | F26: =INDEX(Results_Long!$F$2:$F$201,MATCH("C9|unified_cc_v1|cc_v1|COD_instrumentderivativ (CDS spread)",Results_Long!$AK$2:$AK$201,0)) -> 3LMA-RVE_CR2
A27: COD_instrumentrating | B27: =IF(ISBLANK(INDEX(Results_Long!$K$2:$K$201,MATCH("C9|unified_cc_v1|cc_v1|COD_instrumentrating",Results_Long!$AK$2:$AK$201,0))),"n.e.",INDEX(Results_Long!$K$2:$K$201,MATCH("C9|unified_cc_v1|cc_v1|COD_instrumentrating",Results_Long!$AK$2:$AK$201,0))) -> -0.025299735 | C27: =IF(ISBLANK(INDEX(Results_Long!$L$2:$L$201,MATCH("C9|unified_cc_v1|cc_v1|COD_instrumentrating",Results_Long!$AK$2:$AK$201,0))),"n.e.",INDEX(Results_Long!$L$2:$L$201,MATCH("C9|unified_cc_v1|cc_v1|COD_instrumentrating",Results_Long!$AK$2:$AK$201,0))) -> 0.021672817 | D27: =IF(ISBLANK(INDEX(Results_Long!$N$2:$N$201,MATCH("C9|unified_cc_v1|cc_v1|COD_instrumentrating",Results_Long!$AK$2:$AK$201,0))),"n.e.",INDEX(Results_Long!$N$2:$N$201,MATCH("C9|unified_cc_v1|cc_v1|COD_instrumentrating",Results_Long!$AK$2:$AK$201,0))) -> 2.943333 | E27: =IF(ISBLANK(INDEX(Results_Long!$O$2:$O$201,MATCH("C9|unified_cc_v1|cc_v1|COD_instrumentrating",Results_Long!$AK$2:$AK$201,0))),"—",INDEX(Results_Long!$O$2:$O$201,MATCH("C9|unified_cc_v1|cc_v1|COD_instrumentrating",Results_Long!$AK$2:$AK$201,0))) -> — | F27: =INDEX(Results_Long!$F$2:$F$201,MATCH("C9|unified_cc_v1|cc_v1|COD_instrumentrating",Results_Long!$AK$2:$AK$201,0)) -> 3LMA-RVE_CR2
A28: regulation3with ETS/CT | B28: =IF(ISBLANK(INDEX(Results_Long!$K$2:$K$201,MATCH("C9|unified_cc_v1|cc_v1|regulation3with ETS/CT",Results_Long!$AK$2:$AK$201,0))),"n.e.",INDEX(Results_Long!$K$2:$K$201,MATCH("C9|unified_cc_v1|cc_v1|regulation3with ETS/CT",Results_Long!$AK$2:$AK$201,0))) -> 0.017545757 | C28: =IF(ISBLANK(INDEX(Results_Long!$L$2:$L$201,MATCH("C9|unified_cc_v1|cc_v1|regulation3with ETS/CT",Results_Long!$AK$2:$AK$201,0))),"n.e.",INDEX(Results_Long!$L$2:$L$201,MATCH("C9|unified_cc_v1|cc_v1|regulation3with ETS/CT",Results_Long!$AK$2:$AK$201,0))) -> 0.021392885 | D28: =IF(ISBLANK(INDEX(Results_Long!$N$2:$N$201,MATCH("C9|unified_cc_v1|cc_v1|regulation3with ETS/CT",Results_Long!$AK$2:$AK$201,0))),"n.e.",INDEX(Results_Long!$N$2:$N$201,MATCH("C9|unified_cc_v1|cc_v1|regulation3with ETS/CT",Results_Long!$AK$2:$AK$201,0))) -> 2.264787 | E28: =IF(ISBLANK(INDEX(Results_Long!$O$2:$O$201,MATCH("C9|unified_cc_v1|cc_v1|regulation3with ETS/CT",Results_Long!$AK$2:$AK$201,0))),"—",INDEX(Results_Long!$O$2:$O$201,MATCH("C9|unified_cc_v1|cc_v1|regulation3with ETS/CT",Results_Long!$AK$2:$AK$201,0))) -> — | F28: =INDEX(Results_Long!$F$2:$F$201,MATCH("C9|unified_cc_v1|cc_v1|regulation3with ETS/CT",Results_Long!$AK$2:$AK$201,0)) -> 3LMA-RVE_CR2
A29: country_region2_Europe | B29: =IF(ISBLANK(INDEX(Results_Long!$K$2:$K$201,MATCH("C9|unified_cc_v1|cc_v1|country_region2_Europe",Results_Long!$AK$2:$AK$201,0))),"n.e.",INDEX(Results_Long!$K$2:$K$201,MATCH("C9|unified_cc_v1|cc_v1|country_region2_Europe",Results_Long!$AK$2:$AK$201,0))) -> -0.2330559 | C29: =IF(ISBLANK(INDEX(Results_Long!$L$2:$L$201,MATCH("C9|unified_cc_v1|cc_v1|country_region2_Europe",Results_Long!$AK$2:$AK$201,0))),"n.e.",INDEX(Results_Long!$L$2:$L$201,MATCH("C9|unified_cc_v1|cc_v1|country_region2_Europe",Results_Long!$AK$2:$AK$201,0))) -> 0.1833766 | D29: =IF(ISBLANK(INDEX(Results_Long!$N$2:$N$201,MATCH("C9|unified_cc_v1|cc_v1|country_region2_Europe",Results_Long!$AK$2:$AK$201,0))),"n.e.",INDEX(Results_Long!$N$2:$N$201,MATCH("C9|unified_cc_v1|cc_v1|country_region2_Europe",Results_Long!$AK$2:$AK$201,0))) -> 14.501403 | E29: =IF(ISBLANK(INDEX(Results_Long!$O$2:$O$201,MATCH("C9|unified_cc_v1|cc_v1|country_region2_Europe",Results_Long!$AK$2:$AK$201,0))),"—",INDEX(Results_Long!$O$2:$O$201,MATCH("C9|unified_cc_v1|cc_v1|country_region2_Europe",Results_Long!$AK$2:$AK$201,0))) -> 0.223769 | F29: =INDEX(Results_Long!$F$2:$F$201,MATCH("C9|unified_cc_v1|cc_v1|country_region2_Europe",Results_Long!$AK$2:$AK$201,0)) -> 3LMA-RVE_CR2
A30: country_region3_AsiaPac | B30: =IF(ISBLANK(INDEX(Results_Long!$K$2:$K$201,MATCH("C9|unified_cc_v1|cc_v1|country_region3_AsiaPac",Results_Long!$AK$2:$AK$201,0))),"n.e.",INDEX(Results_Long!$K$2:$K$201,MATCH("C9|unified_cc_v1|cc_v1|country_region3_AsiaPac",Results_Long!$AK$2:$AK$201,0))) -> -0.030251193 | C30: =IF(ISBLANK(INDEX(Results_Long!$L$2:$L$201,MATCH("C9|unified_cc_v1|cc_v1|country_region3_AsiaPac",Results_Long!$AK$2:$AK$201,0))),"n.e.",INDEX(Results_Long!$L$2:$L$201,MATCH("C9|unified_cc_v1|cc_v1|country_region3_AsiaPac",Results_Long!$AK$2:$AK$201,0))) -> 0.024442997 | D30: =IF(ISBLANK(INDEX(Results_Long!$N$2:$N$201,MATCH("C9|unified_cc_v1|cc_v1|country_region3_AsiaPac",Results_Long!$AK$2:$AK$201,0))),"n.e.",INDEX(Results_Long!$N$2:$N$201,MATCH("C9|unified_cc_v1|cc_v1|country_region3_AsiaPac",Results_Long!$AK$2:$AK$201,0))) -> 45.931381 | E30: =IF(ISBLANK(INDEX(Results_Long!$O$2:$O$201,MATCH("C9|unified_cc_v1|cc_v1|country_region3_AsiaPac",Results_Long!$AK$2:$AK$201,0))),"—",INDEX(Results_Long!$O$2:$O$201,MATCH("C9|unified_cc_v1|cc_v1|country_region3_AsiaPac",Results_Long!$AK$2:$AK$201,0))) -> 0.22214571 | F30: =INDEX(Results_Long!$F$2:$F$201,MATCH("C9|unified_cc_v1|cc_v1|country_region3_AsiaPac",Results_Long!$AK$2:$AK$201,0)) -> 3LMA-RVE_CR2
A31: pp:CER_measuredisclosure | B31: =IF(ISBLANK(INDEX(Results_Long!$K$2:$K$201,MATCH("C9|unified_cc_v1|cc_v1|pp:CER_measuredisclosure",Results_Long!$AK$2:$AK$201,0))),"n.e.",INDEX(Results_Long!$K$2:$K$201,MATCH("C9|unified_cc_v1|cc_v1|pp:CER_measuredisclosure",Results_Long!$AK$2:$AK$201,0))) -> -0.04174981 | C31: =IF(ISBLANK(INDEX(Results_Long!$L$2:$L$201,MATCH("C9|unified_cc_v1|cc_v1|pp:CER_measuredisclosure",Results_Long!$AK$2:$AK$201,0))),"n.e.",INDEX(Results_Long!$L$2:$L$201,MATCH("C9|unified_cc_v1|cc_v1|pp:CER_measuredisclosure",Results_Long!$AK$2:$AK$201,0))) -> 0.036051584 | D31: =IF(ISBLANK(INDEX(Results_Long!$N$2:$N$201,MATCH("C9|unified_cc_v1|cc_v1|pp:CER_measuredisclosure",Results_Long!$AK$2:$AK$201,0))),"n.e.",INDEX(Results_Long!$N$2:$N$201,MATCH("C9|unified_cc_v1|cc_v1|pp:CER_measuredisclosure",Results_Long!$AK$2:$AK$201,0))) -> 3.3705303 | E31: =IF(ISBLANK(INDEX(Results_Long!$O$2:$O$201,MATCH("C9|unified_cc_v1|cc_v1|pp:CER_measuredisclosure",Results_Long!$AK$2:$AK$201,0))),"—",INDEX(Results_Long!$O$2:$O$201,MATCH("C9|unified_cc_v1|cc_v1|pp:CER_measuredisclosure",Results_Long!$AK$2:$AK$201,0))) -> — | F31: =INDEX(Results_Long!$F$2:$F$201,MATCH("C9|unified_cc_v1|cc_v1|pp:CER_measuredisclosure",Results_Long!$AK$2:$AK$201,0)) -> 3LMA-RVE_CR2
A32: pp:country_region2_Europe | B32: =IF(ISBLANK(INDEX(Results_Long!$K$2:$K$201,MATCH("C9|unified_cc_v1|cc_v1|pp:country_region2_Europe",Results_Long!$AK$2:$AK$201,0))),"n.e.",INDEX(Results_Long!$K$2:$K$201,MATCH("C9|unified_cc_v1|cc_v1|pp:country_region2_Europe",Results_Long!$AK$2:$AK$201,0))) -> 0.16787491 | C32: =IF(ISBLANK(INDEX(Results_Long!$L$2:$L$201,MATCH("C9|unified_cc_v1|cc_v1|pp:country_region2_Europe",Results_Long!$AK$2:$AK$201,0))),"n.e.",INDEX(Results_Long!$L$2:$L$201,MATCH("C9|unified_cc_v1|cc_v1|pp:country_region2_Europe",Results_Long!$AK$2:$AK$201,0))) -> 0.17489305 | D32: =IF(ISBLANK(INDEX(Results_Long!$N$2:$N$201,MATCH("C9|unified_cc_v1|cc_v1|pp:country_region2_Europe",Results_Long!$AK$2:$AK$201,0))),"n.e.",INDEX(Results_Long!$N$2:$N$201,MATCH("C9|unified_cc_v1|cc_v1|pp:country_region2_Europe",Results_Long!$AK$2:$AK$201,0))) -> 12.299341 | E32: =IF(ISBLANK(INDEX(Results_Long!$O$2:$O$201,MATCH("C9|unified_cc_v1|cc_v1|pp:country_region2_Europe",Results_Long!$AK$2:$AK$201,0))),"—",INDEX(Results_Long!$O$2:$O$201,MATCH("C9|unified_cc_v1|cc_v1|pp:country_region2_Europe",Results_Long!$AK$2:$AK$201,0))) -> 0.35561021 | F32: =INDEX(Results_Long!$F$2:$F$201,MATCH("C9|unified_cc_v1|cc_v1|pp:country_region2_Europe",Results_Long!$AK$2:$AK$201,0)) -> 3LMA-RVE_CR2
A33: pp:country_region3_AsiaPac | B33: =IF(ISBLANK(INDEX(Results_Long!$K$2:$K$201,MATCH("C9|unified_cc_v1|cc_v1|pp:country_region3_AsiaPac",Results_Long!$AK$2:$AK$201,0))),"n.e.",INDEX(Results_Long!$K$2:$K$201,MATCH("C9|unified_cc_v1|cc_v1|pp:country_region3_AsiaPac",Results_Long!$AK$2:$AK$201,0))) -> n.e. | C33: =IF(ISBLANK(INDEX(Results_Long!$L$2:$L$201,MATCH("C9|unified_cc_v1|cc_v1|pp:country_region3_AsiaPac",Results_Long!$AK$2:$AK$201,0))),"n.e.",INDEX(Results_Long!$L$2:$L$201,MATCH("C9|unified_cc_v1|cc_v1|pp:country_region3_AsiaPac",Results_Long!$AK$2:$AK$201,0))) -> n.e. | D33: =IF(ISBLANK(INDEX(Results_Long!$N$2:$N$201,MATCH("C9|unified_cc_v1|cc_v1|pp:country_region3_AsiaPac",Results_Long!$AK$2:$AK$201,0))),"n.e.",INDEX(Results_Long!$N$2:$N$201,MATCH("C9|unified_cc_v1|cc_v1|pp:country_region3_AsiaPac",Results_Long!$AK$2:$AK$201,0))) -> n.e. | E33: =IF(ISBLANK(INDEX(Results_Long!$O$2:$O$201,MATCH("C9|unified_cc_v1|cc_v1|pp:country_region3_AsiaPac",Results_Long!$AK$2:$AK$201,0))),"—",INDEX(Results_Long!$O$2:$O$201,MATCH("C9|unified_cc_v1|cc_v1|pp:country_region3_AsiaPac",Results_Long!$AK$2:$AK$201,0))) -> — | F33: =INDEX(Results_Long!$F$2:$F$201,MATCH("C9|unified_cc_v1|cc_v1|pp:country_region3_AsiaPac",Results_Long!$AK$2:$AK$201,0)) -> not_estimable
A34: pp:COD_instrument::coef1 | B34: =IF(ISBLANK(INDEX(Results_Long!$K$2:$K$201,MATCH("C9|unified_cc_v1|cc_v1|pp:COD_instrument::coef1",Results_Long!$AK$2:$AK$201,0))),"n.e.",INDEX(Results_Long!$K$2:$K$201,MATCH("C9|unified_cc_v1|cc_v1|pp:COD_instrument::coef1",Results_Long!$AK$2:$AK$201,0))) -> n.e. | C34: =IF(ISBLANK(INDEX(Results_Long!$L$2:$L$201,MATCH("C9|unified_cc_v1|cc_v1|pp:COD_instrument::coef1",Results_Long!$AK$2:$AK$201,0))),"n.e.",INDEX(Results_Long!$L$2:$L$201,MATCH("C9|unified_cc_v1|cc_v1|pp:COD_instrument::coef1",Results_Long!$AK$2:$AK$201,0))) -> n.e. | D34: =IF(ISBLANK(INDEX(Results_Long!$N$2:$N$201,MATCH("C9|unified_cc_v1|cc_v1|pp:COD_instrument::coef1",Results_Long!$AK$2:$AK$201,0))),"n.e.",INDEX(Results_Long!$N$2:$N$201,MATCH("C9|unified_cc_v1|cc_v1|pp:COD_instrument::coef1",Results_Long!$AK$2:$AK$201,0))) -> n.e. | E34: =IF(ISBLANK(INDEX(Results_Long!$O$2:$O$201,MATCH("C9|unified_cc_v1|cc_v1|pp:COD_instrument::coef1",Results_Long!$AK$2:$AK$201,0))),"—",INDEX(Results_Long!$O$2:$O$201,MATCH("C9|unified_cc_v1|cc_v1|pp:COD_instrument::coef1",Results_Long!$AK$2:$AK$201,0))) -> — | F34: =INDEX(Results_Long!$F$2:$F$201,MATCH("C9|unified_cc_v1|cc_v1|pp:COD_instrument::coef1",Results_Long!$AK$2:$AK$201,0)) -> not_estimable
A35: pp:COD_instrument::coef2 | B35: =IF(ISBLANK(INDEX(Results_Long!$K$2:$K$201,MATCH("C9|unified_cc_v1|cc_v1|pp:COD_instrument::coef2",Results_Long!$AK$2:$AK$201,0))),"n.e.",INDEX(Results_Long!$K$2:$K$201,MATCH("C9|unified_cc_v1|cc_v1|pp:COD_instrument::coef2",Results_Long!$AK$2:$AK$201,0))) -> n.e. | C35: =IF(ISBLANK(INDEX(Results_Long!$L$2:$L$201,MATCH("C9|unified_cc_v1|cc_v1|pp:COD_instrument::coef2",Results_Long!$AK$2:$AK$201,0))),"n.e.",INDEX(Results_Long!$L$2:$L$201,MATCH("C9|unified_cc_v1|cc_v1|pp:COD_instrument::coef2",Results_Long!$AK$2:$AK$201,0))) -> n.e. | D35: =IF(ISBLANK(INDEX(Results_Long!$N$2:$N$201,MATCH("C9|unified_cc_v1|cc_v1|pp:COD_instrument::coef2",Results_Long!$AK$2:$AK$201,0))),"n.e.",INDEX(Results_Long!$N$2:$N$201,MATCH("C9|unified_cc_v1|cc_v1|pp:COD_instrument::coef2",Results_Long!$AK$2:$AK$201,0))) -> n.e. | E35: =IF(ISBLANK(INDEX(Results_Long!$O$2:$O$201,MATCH("C9|unified_cc_v1|cc_v1|pp:COD_instrument::coef2",Results_Long!$AK$2:$AK$201,0))),"—",INDEX(Results_Long!$O$2:$O$201,MATCH("C9|unified_cc_v1|cc_v1|pp:COD_instrument::coef2",Results_Long!$AK$2:$AK$201,0))) -> — | F35: =INDEX(Results_Long!$F$2:$F$201,MATCH("C9|unified_cc_v1|cc_v1|pp:COD_instrument::coef2",Results_Long!$AK$2:$AK$201,0)) -> not_estimable
A36: pp:COD_instrument::coef3 | B36: =IF(ISBLANK(INDEX(Results_Long!$K$2:$K$201,MATCH("C9|unified_cc_v1|cc_v1|pp:COD_instrument::coef3",Results_Long!$AK$2:$AK$201,0))),"n.e.",INDEX(Results_Long!$K$2:$K$201,MATCH("C9|unified_cc_v1|cc_v1|pp:COD_instrument::coef3",Results_Long!$AK$2:$AK$201,0))) -> n.e. | C36: =IF(ISBLANK(INDEX(Results_Long!$L$2:$L$201,MATCH("C9|unified_cc_v1|cc_v1|pp:COD_instrument::coef3",Results_Long!$AK$2:$AK$201,0))),"n.e.",INDEX(Results_Long!$L$2:$L$201,MATCH("C9|unified_cc_v1|cc_v1|pp:COD_instrument::coef3",Results_Long!$AK$2:$AK$201,0))) -> n.e. | D36: =IF(ISBLANK(INDEX(Results_Long!$N$2:$N$201,MATCH("C9|unified_cc_v1|cc_v1|pp:COD_instrument::coef3",Results_Long!$AK$2:$AK$201,0))),"n.e.",INDEX(Results_Long!$N$2:$N$201,MATCH("C9|unified_cc_v1|cc_v1|pp:COD_instrument::coef3",Results_Long!$AK$2:$AK$201,0))) -> n.e. | E36: =IF(ISBLANK(INDEX(Results_Long!$O$2:$O$201,MATCH("C9|unified_cc_v1|cc_v1|pp:COD_instrument::coef3",Results_Long!$AK$2:$AK$201,0))),"—",INDEX(Results_Long!$O$2:$O$201,MATCH("C9|unified_cc_v1|cc_v1|pp:COD_instrument::coef3",Results_Long!$AK$2:$AK$201,0))) -> — | F36: =INDEX(Results_Long!$F$2:$F$201,MATCH("C9|unified_cc_v1|cc_v1|pp:COD_instrument::coef3",Results_Long!$AK$2:$AK$201,0)) -> not_estimable
A37: pp:regulation3::coef1 | B37: =IF(ISBLANK(INDEX(Results_Long!$K$2:$K$201,MATCH("C9|unified_cc_v1|cc_v1|pp:regulation3::coef1",Results_Long!$AK$2:$AK$201,0))),"n.e.",INDEX(Results_Long!$K$2:$K$201,MATCH("C9|unified_cc_v1|cc_v1|pp:regulation3::coef1",Results_Long!$AK$2:$AK$201,0))) -> n.e. | C37: =IF(ISBLANK(INDEX(Results_Long!$L$2:$L$201,MATCH("C9|unified_cc_v1|cc_v1|pp:regulation3::coef1",Results_Long!$AK$2:$AK$201,0))),"n.e.",INDEX(Results_Long!$L$2:$L$201,MATCH("C9|unified_cc_v1|cc_v1|pp:regulation3::coef1",Results_Long!$AK$2:$AK$201,0))) -> n.e. | D37: =IF(ISBLANK(INDEX(Results_Long!$N$2:$N$201,MATCH("C9|unified_cc_v1|cc_v1|pp:regulation3::coef1",Results_Long!$AK$2:$AK$201,0))),"n.e.",INDEX(Results_Long!$N$2:$N$201,MATCH("C9|unified_cc_v1|cc_v1|pp:regulation3::coef1",Results_Long!$AK$2:$AK$201,0))) -> n.e. | E37: =IF(ISBLANK(INDEX(Results_Long!$O$2:$O$201,MATCH("C9|unified_cc_v1|cc_v1|pp:regulation3::coef1",Results_Long!$AK$2:$AK$201,0))),"—",INDEX(Results_Long!$O$2:$O$201,MATCH("C9|unified_cc_v1|cc_v1|pp:regulation3::coef1",Results_Long!$AK$2:$AK$201,0))) -> — | F37: =INDEX(Results_Long!$F$2:$F$201,MATCH("C9|unified_cc_v1|cc_v1|pp:regulation3::coef1",Results_Long!$AK$2:$AK$201,0)) -> not_estimable
A38: Block HTZ | B38: F | C38: df | D38: p | E38: status
A39: block_HTZ::CER_measure | B39: =IF(ISBLANK(INDEX(Results_Long!$M$2:$M$201,MATCH("C9|unified_cc_v1|cc_v1|block_HTZ::CER_measure",Results_Long!$AK$2:$AK$201,0))),"n.e.",INDEX(Results_Long!$M$2:$M$201,MATCH("C9|unified_cc_v1|cc_v1|block_HTZ::CER_measure",Results_Long!$AK$2:$AK$201,0))) -> 1.3410973 | C39: =IF(ISBLANK(INDEX(Results_Long!$N$2:$N$201,MATCH("C9|unified_cc_v1|cc_v1|block_HTZ::CER_measure",Results_Long!$AK$2:$AK$201,0))),"n.e.",INDEX(Results_Long!$N$2:$N$201,MATCH("C9|unified_cc_v1|cc_v1|block_HTZ::CER_measure",Results_Long!$AK$2:$AK$201,0))) -> 3.3705303 | D39: =IF(ISBLANK(INDEX(Results_Long!$O$2:$O$201,MATCH("C9|unified_cc_v1|cc_v1|block_HTZ::CER_measure",Results_Long!$AK$2:$AK$201,0))),"—",INDEX(Results_Long!$O$2:$O$201,MATCH("C9|unified_cc_v1|cc_v1|block_HTZ::CER_measure",Results_Long!$AK$2:$AK$201,0))) -> 0.32226314 | E39: =INDEX(Results_Long!$F$2:$F$201,MATCH("C9|unified_cc_v1|cc_v1|block_HTZ::CER_measure",Results_Long!$AK$2:$AK$201,0)) -> 3LMA-RVE_CR2
A40: block_HTZ::COD_instrument | B40: =IF(ISBLANK(INDEX(Results_Long!$M$2:$M$201,MATCH("C9|unified_cc_v1|cc_v1|block_HTZ::COD_instrument",Results_Long!$AK$2:$AK$201,0))),"n.e.",INDEX(Results_Long!$M$2:$M$201,MATCH("C9|unified_cc_v1|cc_v1|block_HTZ::COD_instrument",Results_Long!$AK$2:$AK$201,0))) -> n.e. | C40: =IF(ISBLANK(INDEX(Results_Long!$N$2:$N$201,MATCH("C9|unified_cc_v1|cc_v1|block_HTZ::COD_instrument",Results_Long!$AK$2:$AK$201,0))),"n.e.",INDEX(Results_Long!$N$2:$N$201,MATCH("C9|unified_cc_v1|cc_v1|block_HTZ::COD_instrument",Results_Long!$AK$2:$AK$201,0))) -> n.e. | D40: =IF(ISBLANK(INDEX(Results_Long!$O$2:$O$201,MATCH("C9|unified_cc_v1|cc_v1|block_HTZ::COD_instrument",Results_Long!$AK$2:$AK$201,0))),"—",INDEX(Results_Long!$O$2:$O$201,MATCH("C9|unified_cc_v1|cc_v1|block_HTZ::COD_instrument",Results_Long!$AK$2:$AK$201,0))) -> — | E40: =INDEX(Results_Long!$F$2:$F$201,MATCH("C9|unified_cc_v1|cc_v1|block_HTZ::COD_instrument",Results_Long!$AK$2:$AK$201,0)) -> not_estimable
A41: block_HTZ::regulation3 | B41: =IF(ISBLANK(INDEX(Results_Long!$M$2:$M$201,MATCH("C9|unified_cc_v1|cc_v1|block_HTZ::regulation3",Results_Long!$AK$2:$AK$201,0))),"n.e.",INDEX(Results_Long!$M$2:$M$201,MATCH("C9|unified_cc_v1|cc_v1|block_HTZ::regulation3",Results_Long!$AK$2:$AK$201,0))) -> n.e. | C41: =IF(ISBLANK(INDEX(Results_Long!$N$2:$N$201,MATCH("C9|unified_cc_v1|cc_v1|block_HTZ::regulation3",Results_Long!$AK$2:$AK$201,0))),"n.e.",INDEX(Results_Long!$N$2:$N$201,MATCH("C9|unified_cc_v1|cc_v1|block_HTZ::regulation3",Results_Long!$AK$2:$AK$201,0))) -> n.e. | D41: =IF(ISBLANK(INDEX(Results_Long!$O$2:$O$201,MATCH("C9|unified_cc_v1|cc_v1|block_HTZ::regulation3",Results_Long!$AK$2:$AK$201,0))),"—",INDEX(Results_Long!$O$2:$O$201,MATCH("C9|unified_cc_v1|cc_v1|block_HTZ::regulation3",Results_Long!$AK$2:$AK$201,0))) -> — | E41: =INDEX(Results_Long!$F$2:$F$201,MATCH("C9|unified_cc_v1|cc_v1|block_HTZ::regulation3",Results_Long!$AK$2:$AK$201,0)) -> not_estimable
A42: block_HTZ::country_region | B42: =IF(ISBLANK(INDEX(Results_Long!$M$2:$M$201,MATCH("C9|unified_cc_v1|cc_v1|block_HTZ::country_region",Results_Long!$AK$2:$AK$201,0))),"n.e.",INDEX(Results_Long!$M$2:$M$201,MATCH("C9|unified_cc_v1|cc_v1|block_HTZ::country_region",Results_Long!$AK$2:$AK$201,0))) -> 0.92135394 | C42: =IF(ISBLANK(INDEX(Results_Long!$N$2:$N$201,MATCH("C9|unified_cc_v1|cc_v1|block_HTZ::country_region",Results_Long!$AK$2:$AK$201,0))),"n.e.",INDEX(Results_Long!$N$2:$N$201,MATCH("C9|unified_cc_v1|cc_v1|block_HTZ::country_region",Results_Long!$AK$2:$AK$201,0))) -> 12.299341 | D42: =IF(ISBLANK(INDEX(Results_Long!$O$2:$O$201,MATCH("C9|unified_cc_v1|cc_v1|block_HTZ::country_region",Results_Long!$AK$2:$AK$201,0))),"—",INDEX(Results_Long!$O$2:$O$201,MATCH("C9|unified_cc_v1|cc_v1|block_HTZ::country_region",Results_Long!$AK$2:$AK$201,0))) -> 0.35561021 | E42: =INDEX(Results_Long!$F$2:$F$201,MATCH("C9|unified_cc_v1|cc_v1|block_HTZ::country_region",Results_Long!$AK$2:$AK$201,0)) -> 3LMA-RVE_CR2
A44: V2 (full mains) — coefficients (z scale)
A45: Term | B45: b | C45: SE | D45: df | E45: p | F45: status
A46: intercept | B46: =IF(ISBLANK(INDEX(Results_Long!$K$2:$K$201,MATCH("C9|unified_cc_v2|cc_v2|intercept",Results_Long!$AK$2:$AK$201,0))),"n.e.",INDEX(Results_Long!$K$2:$K$201,MATCH("C9|unified_cc_v2|cc_v2|intercept",Results_Long!$AK$2:$AK$201,0))) -> -0.027009639 | C46: =IF(ISBLANK(INDEX(Results_Long!$L$2:$L$201,MATCH("C9|unified_cc_v2|cc_v2|intercept",Results_Long!$AK$2:$AK$201,0))),"n.e.",INDEX(Results_Long!$L$2:$L$201,MATCH("C9|unified_cc_v2|cc_v2|intercept",Results_Long!$AK$2:$AK$201,0))) -> 0.012422316 | D46: =IF(ISBLANK(INDEX(Results_Long!$N$2:$N$201,MATCH("C9|unified_cc_v2|cc_v2|intercept",Results_Long!$AK$2:$AK$201,0))),"n.e.",INDEX(Results_Long!$N$2:$N$201,MATCH("C9|unified_cc_v2|cc_v2|intercept",Results_Long!$AK$2:$AK$201,0))) -> 12.444012 | E46: =IF(ISBLANK(INDEX(Results_Long!$O$2:$O$201,MATCH("C9|unified_cc_v2|cc_v2|intercept",Results_Long!$AK$2:$AK$201,0))),"—",INDEX(Results_Long!$O$2:$O$201,MATCH("C9|unified_cc_v2|cc_v2|intercept",Results_Long!$AK$2:$AK$201,0))) -> 0.049634066 | F46: =INDEX(Results_Long!$F$2:$F$201,MATCH("C9|unified_cc_v2|cc_v2|intercept",Results_Long!$AK$2:$AK$201,0)) -> 3LMA-RVE_CR2
A47: pp_mid_lag0 | B47: =IF(ISBLANK(INDEX(Results_Long!$K$2:$K$201,MATCH("C9|unified_cc_v2|cc_v2|pp_mid_lag0",Results_Long!$AK$2:$AK$201,0))),"n.e.",INDEX(Results_Long!$K$2:$K$201,MATCH("C9|unified_cc_v2|cc_v2|pp_mid_lag0",Results_Long!$AK$2:$AK$201,0))) -> 0.012958479 | C47: =IF(ISBLANK(INDEX(Results_Long!$L$2:$L$201,MATCH("C9|unified_cc_v2|cc_v2|pp_mid_lag0",Results_Long!$AK$2:$AK$201,0))),"n.e.",INDEX(Results_Long!$L$2:$L$201,MATCH("C9|unified_cc_v2|cc_v2|pp_mid_lag0",Results_Long!$AK$2:$AK$201,0))) -> 0.015710731 | D47: =IF(ISBLANK(INDEX(Results_Long!$N$2:$N$201,MATCH("C9|unified_cc_v2|cc_v2|pp_mid_lag0",Results_Long!$AK$2:$AK$201,0))),"n.e.",INDEX(Results_Long!$N$2:$N$201,MATCH("C9|unified_cc_v2|cc_v2|pp_mid_lag0",Results_Long!$AK$2:$AK$201,0))) -> 12.045239 | E47: =IF(ISBLANK(INDEX(Results_Long!$O$2:$O$201,MATCH("C9|unified_cc_v2|cc_v2|pp_mid_lag0",Results_Long!$AK$2:$AK$201,0))),"—",INDEX(Results_Long!$O$2:$O$201,MATCH("C9|unified_cc_v2|cc_v2|pp_mid_lag0",Results_Long!$AK$2:$AK$201,0))) -> 0.42550867 | F47: =INDEX(Results_Long!$F$2:$F$201,MATCH("C9|unified_cc_v2|cc_v2|pp_mid_lag0",Results_Long!$AK$2:$AK$201,0)) -> 3LMA-RVE_CR2
A48: CER_measuredisclosure | B48: =IF(ISBLANK(INDEX(Results_Long!$K$2:$K$201,MATCH("C9|unified_cc_v2|cc_v2|CER_measuredisclosure",Results_Long!$AK$2:$AK$201,0))),"n.e.",INDEX(Results_Long!$K$2:$K$201,MATCH("C9|unified_cc_v2|cc_v2|CER_measuredisclosure",Results_Long!$AK$2:$AK$201,0))) -> -0.0039006255 | C48: =IF(ISBLANK(INDEX(Results_Long!$L$2:$L$201,MATCH("C9|unified_cc_v2|cc_v2|CER_measuredisclosure",Results_Long!$AK$2:$AK$201,0))),"n.e.",INDEX(Results_Long!$L$2:$L$201,MATCH("C9|unified_cc_v2|cc_v2|CER_measuredisclosure",Results_Long!$AK$2:$AK$201,0))) -> 0.019774451 | D48: =IF(ISBLANK(INDEX(Results_Long!$N$2:$N$201,MATCH("C9|unified_cc_v2|cc_v2|CER_measuredisclosure",Results_Long!$AK$2:$AK$201,0))),"n.e.",INDEX(Results_Long!$N$2:$N$201,MATCH("C9|unified_cc_v2|cc_v2|CER_measuredisclosure",Results_Long!$AK$2:$AK$201,0))) -> 7.9884882 | E48: =IF(ISBLANK(INDEX(Results_Long!$O$2:$O$201,MATCH("C9|unified_cc_v2|cc_v2|CER_measuredisclosure",Results_Long!$AK$2:$AK$201,0))),"—",INDEX(Results_Long!$O$2:$O$201,MATCH("C9|unified_cc_v2|cc_v2|CER_measuredisclosure",Results_Long!$AK$2:$AK$201,0))) -> 0.84855381 | F48: =INDEX(Results_Long!$F$2:$F$201,MATCH("C9|unified_cc_v2|cc_v2|CER_measuredisclosure",Results_Long!$AK$2:$AK$201,0)) -> 3LMA-RVE_CR2
A49: COD_instrumentbond (yield) | B49: =IF(ISBLANK(INDEX(Results_Long!$K$2:$K$201,MATCH("C9|unified_cc_v2|cc_v2|COD_instrumentbond (yield)",Results_Long!$AK$2:$AK$201,0))),"n.e.",INDEX(Results_Long!$K$2:$K$201,MATCH("C9|unified_cc_v2|cc_v2|COD_instrumentbond (yield)",Results_Long!$AK$2:$AK$201,0))) -> -0.040224745 | C49: =IF(ISBLANK(INDEX(Results_Long!$L$2:$L$201,MATCH("C9|unified_cc_v2|cc_v2|COD_instrumentbond (yield)",Results_Long!$AK$2:$AK$201,0))),"n.e.",INDEX(Results_Long!$L$2:$L$201,MATCH("C9|unified_cc_v2|cc_v2|COD_instrumentbond (yield)",Results_Long!$AK$2:$AK$201,0))) -> 0.012767246 | D49: =IF(ISBLANK(INDEX(Results_Long!$N$2:$N$201,MATCH("C9|unified_cc_v2|cc_v2|COD_instrumentbond (yield)",Results_Long!$AK$2:$AK$201,0))),"n.e.",INDEX(Results_Long!$N$2:$N$201,MATCH("C9|unified_cc_v2|cc_v2|COD_instrumentbond (yield)",Results_Long!$AK$2:$AK$201,0))) -> 6.3090256 | E49: =IF(ISBLANK(INDEX(Results_Long!$O$2:$O$201,MATCH("C9|unified_cc_v2|cc_v2|COD_instrumentbond (yield)",Results_Long!$AK$2:$AK$201,0))),"—",INDEX(Results_Long!$O$2:$O$201,MATCH("C9|unified_cc_v2|cc_v2|COD_instrumentbond (yield)",Results_Long!$AK$2:$AK$201,0))) -> 0.018512462 | F49: =INDEX(Results_Long!$F$2:$F$201,MATCH("C9|unified_cc_v2|cc_v2|COD_instrumentbond (yield)",Results_Long!$AK$2:$AK$201,0)) -> 3LMA-RVE_CR2
A50: COD_instrumentderivativ (CDS spread) | B50: =IF(ISBLANK(INDEX(Results_Long!$K$2:$K$201,MATCH("C9|unified_cc_v2|cc_v2|COD_instrumentderivativ (CDS spread)",Results_Long!$AK$2:$AK$201,0))),"n.e.",INDEX(Results_Long!$K$2:$K$201,MATCH("C9|unified_cc_v2|cc_v2|COD_instrumentderivativ (CDS spread)",Results_Long!$AK$2:$AK$201,0))) -> 0.0073684062 | C50: =IF(ISBLANK(INDEX(Results_Long!$L$2:$L$201,MATCH("C9|unified_cc_v2|cc_v2|COD_instrumentderivativ (CDS spread)",Results_Long!$AK$2:$AK$201,0))),"n.e.",INDEX(Results_Long!$L$2:$L$201,MATCH("C9|unified_cc_v2|cc_v2|COD_instrumentderivativ (CDS spread)",Results_Long!$AK$2:$AK$201,0))) -> 0.015015731 | D50: =IF(ISBLANK(INDEX(Results_Long!$N$2:$N$201,MATCH("C9|unified_cc_v2|cc_v2|COD_instrumentderivativ (CDS spread)",Results_Long!$AK$2:$AK$201,0))),"n.e.",INDEX(Results_Long!$N$2:$N$201,MATCH("C9|unified_cc_v2|cc_v2|COD_instrumentderivativ (CDS spread)",Results_Long!$AK$2:$AK$201,0))) -> 7.6639919 | E50: =IF(ISBLANK(INDEX(Results_Long!$O$2:$O$201,MATCH("C9|unified_cc_v2|cc_v2|COD_instrumentderivativ (CDS spread)",Results_Long!$AK$2:$AK$201,0))),"—",INDEX(Results_Long!$O$2:$O$201,MATCH("C9|unified_cc_v2|cc_v2|COD_instrumentderivativ (CDS spread)",Results_Long!$AK$2:$AK$201,0))) -> 0.63736957 | F50: =INDEX(Results_Long!$F$2:$F$201,MATCH("C9|unified_cc_v2|cc_v2|COD_instrumentderivativ (CDS spread)",Results_Long!$AK$2:$AK$201,0)) -> 3LMA-RVE_CR2
A51: COD_instrumentrating | B51: =IF(ISBLANK(INDEX(Results_Long!$K$2:$K$201,MATCH("C9|unified_cc_v2|cc_v2|COD_instrumentrating",Results_Long!$AK$2:$AK$201,0))),"n.e.",INDEX(Results_Long!$K$2:$K$201,MATCH("C9|unified_cc_v2|cc_v2|COD_instrumentrating",Results_Long!$AK$2:$AK$201,0))) -> -0.014806858 | C51: =IF(ISBLANK(INDEX(Results_Long!$L$2:$L$201,MATCH("C9|unified_cc_v2|cc_v2|COD_instrumentrating",Results_Long!$AK$2:$AK$201,0))),"n.e.",INDEX(Results_Long!$L$2:$L$201,MATCH("C9|unified_cc_v2|cc_v2|COD_instrumentrating",Results_Long!$AK$2:$AK$201,0))) -> 0.011024714 | D51: =IF(ISBLANK(INDEX(Results_Long!$N$2:$N$201,MATCH("C9|unified_cc_v2|cc_v2|COD_instrumentrating",Results_Long!$AK$2:$AK$201,0))),"n.e.",INDEX(Results_Long!$N$2:$N$201,MATCH("C9|unified_cc_v2|cc_v2|COD_instrumentrating",Results_Long!$AK$2:$AK$201,0))) -> 4.3051849 | E51: =IF(ISBLANK(INDEX(Results_Long!$O$2:$O$201,MATCH("C9|unified_cc_v2|cc_v2|COD_instrumentrating",Results_Long!$AK$2:$AK$201,0))),"—",INDEX(Results_Long!$O$2:$O$201,MATCH("C9|unified_cc_v2|cc_v2|COD_instrumentrating",Results_Long!$AK$2:$AK$201,0))) -> — | F51: =INDEX(Results_Long!$F$2:$F$201,MATCH("C9|unified_cc_v2|cc_v2|COD_instrumentrating",Results_Long!$AK$2:$AK$201,0)) -> 3LMA-RVE_CR2
A52: industrysensitive | B52: =IF(ISBLANK(INDEX(Results_Long!$K$2:$K$201,MATCH("C9|unified_cc_v2|cc_v2|industrysensitive",Results_Long!$AK$2:$AK$201,0))),"n.e.",INDEX(Results_Long!$K$2:$K$201,MATCH("C9|unified_cc_v2|cc_v2|industrysensitive",Results_Long!$AK$2:$AK$201,0))) -> 0.0051253766 | C52: =IF(ISBLANK(INDEX(Results_Long!$L$2:$L$201,MATCH("C9|unified_cc_v2|cc_v2|industrysensitive",Results_Long!$AK$2:$AK$201,0))),"n.e.",INDEX(Results_Long!$L$2:$L$201,MATCH("C9|unified_cc_v2|cc_v2|industrysensitive",Results_Long!$AK$2:$AK$201,0))) -> 0.016733123 | D52: =IF(ISBLANK(INDEX(Results_Long!$N$2:$N$201,MATCH("C9|unified_cc_v2|cc_v2|industrysensitive",Results_Long!$AK$2:$AK$201,0))),"n.e.",INDEX(Results_Long!$N$2:$N$201,MATCH("C9|unified_cc_v2|cc_v2|industrysensitive",Results_Long!$AK$2:$AK$201,0))) -> 13.65246 | E52: =IF(ISBLANK(INDEX(Results_Long!$O$2:$O$201,MATCH("C9|unified_cc_v2|cc_v2|industrysensitive",Results_Long!$AK$2:$AK$201,0))),"—",INDEX(Results_Long!$O$2:$O$201,MATCH("C9|unified_cc_v2|cc_v2|industrysensitive",Results_Long!$AK$2:$AK$201,0))) -> 0.76399656 | F52: =INDEX(Results_Long!$F$2:$F$201,MATCH("C9|unified_cc_v2|cc_v2|industrysensitive",Results_Long!$AK$2:$AK$201,0)) -> 3LMA-RVE_CR2
A53: regulation3with ETS/CT | B53: =IF(ISBLANK(INDEX(Results_Long!$K$2:$K$201,MATCH("C9|unified_cc_v2|cc_v2|regulation3with ETS/CT",Results_Long!$AK$2:$AK$201,0))),"n.e.",INDEX(Results_Long!$K$2:$K$201,MATCH("C9|unified_cc_v2|cc_v2|regulation3with ETS/CT",Results_Long!$AK$2:$AK$201,0))) -> 0.01744088 | C53: =IF(ISBLANK(INDEX(Results_Long!$L$2:$L$201,MATCH("C9|unified_cc_v2|cc_v2|regulation3with ETS/CT",Results_Long!$AK$2:$AK$201,0))),"n.e.",INDEX(Results_Long!$L$2:$L$201,MATCH("C9|unified_cc_v2|cc_v2|regulation3with ETS/CT",Results_Long!$AK$2:$AK$201,0))) -> 0.0081952973 | D53: =IF(ISBLANK(INDEX(Results_Long!$N$2:$N$201,MATCH("C9|unified_cc_v2|cc_v2|regulation3with ETS/CT",Results_Long!$AK$2:$AK$201,0))),"n.e.",INDEX(Results_Long!$N$2:$N$201,MATCH("C9|unified_cc_v2|cc_v2|regulation3with ETS/CT",Results_Long!$AK$2:$AK$201,0))) -> 8.5767142 | E53: =IF(ISBLANK(INDEX(Results_Long!$O$2:$O$201,MATCH("C9|unified_cc_v2|cc_v2|regulation3with ETS/CT",Results_Long!$AK$2:$AK$201,0))),"—",INDEX(Results_Long!$O$2:$O$201,MATCH("C9|unified_cc_v2|cc_v2|regulation3with ETS/CT",Results_Long!$AK$2:$AK$201,0))) -> 0.063695216 | F53: =INDEX(Results_Long!$F$2:$F$201,MATCH("C9|unified_cc_v2|cc_v2|regulation3with ETS/CT",Results_Long!$AK$2:$AK$201,0)) -> 3LMA-RVE_CR2
A54: country_region2_Europe | B54: =IF(ISBLANK(INDEX(Results_Long!$K$2:$K$201,MATCH("C9|unified_cc_v2|cc_v2|country_region2_Europe",Results_Long!$AK$2:$AK$201,0))),"n.e.",INDEX(Results_Long!$K$2:$K$201,MATCH("C9|unified_cc_v2|cc_v2|country_region2_Europe",Results_Long!$AK$2:$AK$201,0))) -> -0.030315514 | C54: =IF(ISBLANK(INDEX(Results_Long!$L$2:$L$201,MATCH("C9|unified_cc_v2|cc_v2|country_region2_Europe",Results_Long!$AK$2:$AK$201,0))),"n.e.",INDEX(Results_Long!$L$2:$L$201,MATCH("C9|unified_cc_v2|cc_v2|country_region2_Europe",Results_Long!$AK$2:$AK$201,0))) -> 0.033303097 | D54: =IF(ISBLANK(INDEX(Results_Long!$N$2:$N$201,MATCH("C9|unified_cc_v2|cc_v2|country_region2_Europe",Results_Long!$AK$2:$AK$201,0))),"n.e.",INDEX(Results_Long!$N$2:$N$201,MATCH("C9|unified_cc_v2|cc_v2|country_region2_Europe",Results_Long!$AK$2:$AK$201,0))) -> 2.5711444 | E54: =IF(ISBLANK(INDEX(Results_Long!$O$2:$O$201,MATCH("C9|unified_cc_v2|cc_v2|country_region2_Europe",Results_Long!$AK$2:$AK$201,0))),"—",INDEX(Results_Long!$O$2:$O$201,MATCH("C9|unified_cc_v2|cc_v2|country_region2_Europe",Results_Long!$AK$2:$AK$201,0))) -> — | F54: =INDEX(Results_Long!$F$2:$F$201,MATCH("C9|unified_cc_v2|cc_v2|country_region2_Europe",Results_Long!$AK$2:$AK$201,0)) -> 3LMA-RVE_CR2
A55: country_region3_AsiaPac | B55: =IF(ISBLANK(INDEX(Results_Long!$K$2:$K$201,MATCH("C9|unified_cc_v2|cc_v2|country_region3_AsiaPac",Results_Long!$AK$2:$AK$201,0))),"n.e.",INDEX(Results_Long!$K$2:$K$201,MATCH("C9|unified_cc_v2|cc_v2|country_region3_AsiaPac",Results_Long!$AK$2:$AK$201,0))) -> -0.054198691 | C55: =IF(ISBLANK(INDEX(Results_Long!$L$2:$L$201,MATCH("C9|unified_cc_v2|cc_v2|country_region3_AsiaPac",Results_Long!$AK$2:$AK$201,0))),"n.e.",INDEX(Results_Long!$L$2:$L$201,MATCH("C9|unified_cc_v2|cc_v2|country_region3_AsiaPac",Results_Long!$AK$2:$AK$201,0))) -> 0.01890509 | D55: =IF(ISBLANK(INDEX(Results_Long!$N$2:$N$201,MATCH("C9|unified_cc_v2|cc_v2|country_region3_AsiaPac",Results_Long!$AK$2:$AK$201,0))),"n.e.",INDEX(Results_Long!$N$2:$N$201,MATCH("C9|unified_cc_v2|cc_v2|country_region3_AsiaPac",Results_Long!$AK$2:$AK$201,0))) -> 1.3057877 | E55: =IF(ISBLANK(INDEX(Results_Long!$O$2:$O$201,MATCH("C9|unified_cc_v2|cc_v2|country_region3_AsiaPac",Results_Long!$AK$2:$AK$201,0))),"—",INDEX(Results_Long!$O$2:$O$201,MATCH("C9|unified_cc_v2|cc_v2|country_region3_AsiaPac",Results_Long!$AK$2:$AK$201,0))) -> — | F55: =INDEX(Results_Long!$F$2:$F$201,MATCH("C9|unified_cc_v2|cc_v2|country_region3_AsiaPac",Results_Long!$AK$2:$AK$201,0)) -> 3LMA-RVE_CR2
A56: country_econ2_developing | B56: =IF(ISBLANK(INDEX(Results_Long!$K$2:$K$201,MATCH("C9|unified_cc_v2|cc_v2|country_econ2_developing",Results_Long!$AK$2:$AK$201,0))),"n.e.",INDEX(Results_Long!$K$2:$K$201,MATCH("C9|unified_cc_v2|cc_v2|country_econ2_developing",Results_Long!$AK$2:$AK$201,0))) -> -0.074197353 | C56: =IF(ISBLANK(INDEX(Results_Long!$L$2:$L$201,MATCH("C9|unified_cc_v2|cc_v2|country_econ2_developing",Results_Long!$AK$2:$AK$201,0))),"n.e.",INDEX(Results_Long!$L$2:$L$201,MATCH("C9|unified_cc_v2|cc_v2|country_econ2_developing",Results_Long!$AK$2:$AK$201,0))) -> 0.03374828 | D56: =IF(ISBLANK(INDEX(Results_Long!$N$2:$N$201,MATCH("C9|unified_cc_v2|cc_v2|country_econ2_developing",Results_Long!$AK$2:$AK$201,0))),"n.e.",INDEX(Results_Long!$N$2:$N$201,MATCH("C9|unified_cc_v2|cc_v2|country_econ2_developing",Results_Long!$AK$2:$AK$201,0))) -> 10.218931 | E56: =IF(ISBLANK(INDEX(Results_Long!$O$2:$O$201,MATCH("C9|unified_cc_v2|cc_v2|country_econ2_developing",Results_Long!$AK$2:$AK$201,0))),"—",INDEX(Results_Long!$O$2:$O$201,MATCH("C9|unified_cc_v2|cc_v2|country_econ2_developing",Results_Long!$AK$2:$AK$201,0))) -> 0.052012849 | F56: =INDEX(Results_Long!$F$2:$F$201,MATCH("C9|unified_cc_v2|cc_v2|country_econ2_developing",Results_Long!$AK$2:$AK$201,0)) -> 3LMA-RVE_CR2
A57: country_culture2_non_western | B57: =IF(ISBLANK(INDEX(Results_Long!$K$2:$K$201,MATCH("C9|unified_cc_v2|cc_v2|country_culture2_non_western",Results_Long!$AK$2:$AK$201,0))),"n.e.",INDEX(Results_Long!$K$2:$K$201,MATCH("C9|unified_cc_v2|cc_v2|country_culture2_non_western",Results_Long!$AK$2:$AK$201,0))) -> 0.033786561 | C57: =IF(ISBLANK(INDEX(Results_Long!$L$2:$L$201,MATCH("C9|unified_cc_v2|cc_v2|country_culture2_non_western",Results_Long!$AK$2:$AK$201,0))),"n.e.",INDEX(Results_Long!$L$2:$L$201,MATCH("C9|unified_cc_v2|cc_v2|country_culture2_non_western",Results_Long!$AK$2:$AK$201,0))) -> 0.10013924 | D57: =IF(ISBLANK(INDEX(Results_Long!$N$2:$N$201,MATCH("C9|unified_cc_v2|cc_v2|country_culture2_non_western",Results_Long!$AK$2:$AK$201,0))),"n.e.",INDEX(Results_Long!$N$2:$N$201,MATCH("C9|unified_cc_v2|cc_v2|country_culture2_non_western",Results_Long!$AK$2:$AK$201,0))) -> 3.8990757 | E57: =IF(ISBLANK(INDEX(Results_Long!$O$2:$O$201,MATCH("C9|unified_cc_v2|cc_v2|country_culture2_non_western",Results_Long!$AK$2:$AK$201,0))),"—",INDEX(Results_Long!$O$2:$O$201,MATCH("C9|unified_cc_v2|cc_v2|country_culture2_non_western",Results_Long!$AK$2:$AK$201,0))) -> — | F57: =INDEX(Results_Long!$F$2:$F$201,MATCH("C9|unified_cc_v2|cc_v2|country_culture2_non_western",Results_Long!$AK$2:$AK$201,0)) -> 3LMA-RVE_CR2
A58: country_legal2_civil law | B58: =IF(ISBLANK(INDEX(Results_Long!$K$2:$K$201,MATCH("C9|unified_cc_v2|cc_v2|country_legal2_civil law",Results_Long!$AK$2:$AK$201,0))),"n.e.",INDEX(Results_Long!$K$2:$K$201,MATCH("C9|unified_cc_v2|cc_v2|country_legal2_civil law",Results_Long!$AK$2:$AK$201,0))) -> 0.069597421 | C58: =IF(ISBLANK(INDEX(Results_Long!$L$2:$L$201,MATCH("C9|unified_cc_v2|cc_v2|country_legal2_civil law",Results_Long!$AK$2:$AK$201,0))),"n.e.",INDEX(Results_Long!$L$2:$L$201,MATCH("C9|unified_cc_v2|cc_v2|country_legal2_civil law",Results_Long!$AK$2:$AK$201,0))) -> 0.09474017 | D58: =IF(ISBLANK(INDEX(Results_Long!$N$2:$N$201,MATCH("C9|unified_cc_v2|cc_v2|country_legal2_civil law",Results_Long!$AK$2:$AK$201,0))),"n.e.",INDEX(Results_Long!$N$2:$N$201,MATCH("C9|unified_cc_v2|cc_v2|country_legal2_civil law",Results_Long!$AK$2:$AK$201,0))) -> 2.0181148 | E58: =IF(ISBLANK(INDEX(Results_Long!$O$2:$O$201,MATCH("C9|unified_cc_v2|cc_v2|country_legal2_civil law",Results_Long!$AK$2:$AK$201,0))),"—",INDEX(Results_Long!$O$2:$O$201,MATCH("C9|unified_cc_v2|cc_v2|country_legal2_civil law",Results_Long!$AK$2:$AK$201,0))) -> — | F58: =INDEX(Results_Long!$F$2:$F$201,MATCH("C9|unified_cc_v2|cc_v2|country_legal2_civil law",Results_Long!$AK$2:$AK$201,0)) -> 3LMA-RVE_CR2
A59: pp:CER_measure::coef1 | B59: =IF(ISBLANK(INDEX(Results_Long!$K$2:$K$201,MATCH("C9|unified_cc_v2|cc_v2|pp:CER_measure::coef1",Results_Long!$AK$2:$AK$201,0))),"n.e.",INDEX(Results_Long!$K$2:$K$201,MATCH("C9|unified_cc_v2|cc_v2|pp:CER_measure::coef1",Results_Long!$AK$2:$AK$201,0))) -> n.e. | C59: =IF(ISBLANK(INDEX(Results_Long!$L$2:$L$201,MATCH("C9|unified_cc_v2|cc_v2|pp:CER_measure::coef1",Results_Long!$AK$2:$AK$201,0))),"n.e.",INDEX(Results_Long!$L$2:$L$201,MATCH("C9|unified_cc_v2|cc_v2|pp:CER_measure::coef1",Results_Long!$AK$2:$AK$201,0))) -> n.e. | D59: =IF(ISBLANK(INDEX(Results_Long!$N$2:$N$201,MATCH("C9|unified_cc_v2|cc_v2|pp:CER_measure::coef1",Results_Long!$AK$2:$AK$201,0))),"n.e.",INDEX(Results_Long!$N$2:$N$201,MATCH("C9|unified_cc_v2|cc_v2|pp:CER_measure::coef1",Results_Long!$AK$2:$AK$201,0))) -> n.e. | E59: =IF(ISBLANK(INDEX(Results_Long!$O$2:$O$201,MATCH("C9|unified_cc_v2|cc_v2|pp:CER_measure::coef1",Results_Long!$AK$2:$AK$201,0))),"—",INDEX(Results_Long!$O$2:$O$201,MATCH("C9|unified_cc_v2|cc_v2|pp:CER_measure::coef1",Results_Long!$AK$2:$AK$201,0))) -> — | F59: =INDEX(Results_Long!$F$2:$F$201,MATCH("C9|unified_cc_v2|cc_v2|pp:CER_measure::coef1",Results_Long!$AK$2:$AK$201,0)) -> not_estimable
A60: pp:COD_instrument::coef1 | B60: =IF(ISBLANK(INDEX(Results_Long!$K$2:$K$201,MATCH("C9|unified_cc_v2|cc_v2|pp:COD_instrument::coef1",Results_Long!$AK$2:$AK$201,0))),"n.e.",INDEX(Results_Long!$K$2:$K$201,MATCH("C9|unified_cc_v2|cc_v2|pp:COD_instrument::coef1",Results_Long!$AK$2:$AK$201,0))) -> n.e. | C60: =IF(ISBLANK(INDEX(Results_Long!$L$2:$L$201,MATCH("C9|unified_cc_v2|cc_v2|pp:COD_instrument::coef1",Results_Long!$AK$2:$AK$201,0))),"n.e.",INDEX(Results_Long!$L$2:$L$201,MATCH("C9|unified_cc_v2|cc_v2|pp:COD_instrument::coef1",Results_Long!$AK$2:$AK$201,0))) -> n.e. | D60: =IF(ISBLANK(INDEX(Results_Long!$N$2:$N$201,MATCH("C9|unified_cc_v2|cc_v2|pp:COD_instrument::coef1",Results_Long!$AK$2:$AK$201,0))),"n.e.",INDEX(Results_Long!$N$2:$N$201,MATCH("C9|unified_cc_v2|cc_v2|pp:COD_instrument::coef1",Results_Long!$AK$2:$AK$201,0))) -> n.e. | E60: =IF(ISBLANK(INDEX(Results_Long!$O$2:$O$201,MATCH("C9|unified_cc_v2|cc_v2|pp:COD_instrument::coef1",Results_Long!$AK$2:$AK$201,0))),"—",INDEX(Results_Long!$O$2:$O$201,MATCH("C9|unified_cc_v2|cc_v2|pp:COD_instrument::coef1",Results_Long!$AK$2:$AK$201,0))) -> — | F60: =INDEX(Results_Long!$F$2:$F$201,MATCH("C9|unified_cc_v2|cc_v2|pp:COD_instrument::coef1",Results_Long!$AK$2:$AK$201,0)) -> not_estimable
A61: pp:COD_instrument::coef2 | B61: =IF(ISBLANK(INDEX(Results_Long!$K$2:$K$201,MATCH("C9|unified_cc_v2|cc_v2|pp:COD_instrument::coef2",Results_Long!$AK$2:$AK$201,0))),"n.e.",INDEX(Results_Long!$K$2:$K$201,MATCH("C9|unified_cc_v2|cc_v2|pp:COD_instrument::coef2",Results_Long!$AK$2:$AK$201,0))) -> n.e. | C61: =IF(ISBLANK(INDEX(Results_Long!$L$2:$L$201,MATCH("C9|unified_cc_v2|cc_v2|pp:COD_instrument::coef2",Results_Long!$AK$2:$AK$201,0))),"n.e.",INDEX(Results_Long!$L$2:$L$201,MATCH("C9|unified_cc_v2|cc_v2|pp:COD_instrument::coef2",Results_Long!$AK$2:$AK$201,0))) -> n.e. | D61: =IF(ISBLANK(INDEX(Results_Long!$N$2:$N$201,MATCH("C9|unified_cc_v2|cc_v2|pp:COD_instrument::coef2",Results_Long!$AK$2:$AK$201,0))),"n.e.",INDEX(Results_Long!$N$2:$N$201,MATCH("C9|unified_cc_v2|cc_v2|pp:COD_instrument::coef2",Results_Long!$AK$2:$AK$201,0))) -> n.e. | E61: =IF(ISBLANK(INDEX(Results_Long!$O$2:$O$201,MATCH("C9|unified_cc_v2|cc_v2|pp:COD_instrument::coef2",Results_Long!$AK$2:$AK$201,0))),"—",INDEX(Results_Long!$O$2:$O$201,MATCH("C9|unified_cc_v2|cc_v2|pp:COD_instrument::coef2",Results_Long!$AK$2:$AK$201,0))) -> — | F61: =INDEX(Results_Long!$F$2:$F$201,MATCH("C9|unified_cc_v2|cc_v2|pp:COD_instrument::coef2",Results_Long!$AK$2:$AK$201,0)) -> not_estimable
A62: pp:COD_instrument::coef3 | B62: =IF(ISBLANK(INDEX(Results_Long!$K$2:$K$201,MATCH("C9|unified_cc_v2|cc_v2|pp:COD_instrument::coef3",Results_Long!$AK$2:$AK$201,0))),"n.e.",INDEX(Results_Long!$K$2:$K$201,MATCH("C9|unified_cc_v2|cc_v2|pp:COD_instrument::coef3",Results_Long!$AK$2:$AK$201,0))) -> n.e. | C62: =IF(ISBLANK(INDEX(Results_Long!$L$2:$L$201,MATCH("C9|unified_cc_v2|cc_v2|pp:COD_instrument::coef3",Results_Long!$AK$2:$AK$201,0))),"n.e.",INDEX(Results_Long!$L$2:$L$201,MATCH("C9|unified_cc_v2|cc_v2|pp:COD_instrument::coef3",Results_Long!$AK$2:$AK$201,0))) -> n.e. | D62: =IF(ISBLANK(INDEX(Results_Long!$N$2:$N$201,MATCH("C9|unified_cc_v2|cc_v2|pp:COD_instrument::coef3",Results_Long!$AK$2:$AK$201,0))),"n.e.",INDEX(Results_Long!$N$2:$N$201,MATCH("C9|unified_cc_v2|cc_v2|pp:COD_instrument::coef3",Results_Long!$AK$2:$AK$201,0))) -> n.e. | E62: =IF(ISBLANK(INDEX(Results_Long!$O$2:$O$201,MATCH("C9|unified_cc_v2|cc_v2|pp:COD_instrument::coef3",Results_Long!$AK$2:$AK$201,0))),"—",INDEX(Results_Long!$O$2:$O$201,MATCH("C9|unified_cc_v2|cc_v2|pp:COD_instrument::coef3",Results_Long!$AK$2:$AK$201,0))) -> — | F62: =INDEX(Results_Long!$F$2:$F$201,MATCH("C9|unified_cc_v2|cc_v2|pp:COD_instrument::coef3",Results_Long!$AK$2:$AK$201,0)) -> not_estimable
A63: pp:industry::coef1 | B63: =IF(ISBLANK(INDEX(Results_Long!$K$2:$K$201,MATCH("C9|unified_cc_v2|cc_v2|pp:industry::coef1",Results_Long!$AK$2:$AK$201,0))),"n.e.",INDEX(Results_Long!$K$2:$K$201,MATCH("C9|unified_cc_v2|cc_v2|pp:industry::coef1",Results_Long!$AK$2:$AK$201,0))) -> n.e. | C63: =IF(ISBLANK(INDEX(Results_Long!$L$2:$L$201,MATCH("C9|unified_cc_v2|cc_v2|pp:industry::coef1",Results_Long!$AK$2:$AK$201,0))),"n.e.",INDEX(Results_Long!$L$2:$L$201,MATCH("C9|unified_cc_v2|cc_v2|pp:industry::coef1",Results_Long!$AK$2:$AK$201,0))) -> n.e. | D63: =IF(ISBLANK(INDEX(Results_Long!$N$2:$N$201,MATCH("C9|unified_cc_v2|cc_v2|pp:industry::coef1",Results_Long!$AK$2:$AK$201,0))),"n.e.",INDEX(Results_Long!$N$2:$N$201,MATCH("C9|unified_cc_v2|cc_v2|pp:industry::coef1",Results_Long!$AK$2:$AK$201,0))) -> n.e. | E63: =IF(ISBLANK(INDEX(Results_Long!$O$2:$O$201,MATCH("C9|unified_cc_v2|cc_v2|pp:industry::coef1",Results_Long!$AK$2:$AK$201,0))),"—",INDEX(Results_Long!$O$2:$O$201,MATCH("C9|unified_cc_v2|cc_v2|pp:industry::coef1",Results_Long!$AK$2:$AK$201,0))) -> — | F63: =INDEX(Results_Long!$F$2:$F$201,MATCH("C9|unified_cc_v2|cc_v2|pp:industry::coef1",Results_Long!$AK$2:$AK$201,0)) -> not_estimable
A64: pp:regulation3::coef1 | B64: =IF(ISBLANK(INDEX(Results_Long!$K$2:$K$201,MATCH("C9|unified_cc_v2|cc_v2|pp:regulation3::coef1",Results_Long!$AK$2:$AK$201,0))),"n.e.",INDEX(Results_Long!$K$2:$K$201,MATCH("C9|unified_cc_v2|cc_v2|pp:regulation3::coef1",Results_Long!$AK$2:$AK$201,0))) -> n.e. | C64: =IF(ISBLANK(INDEX(Results_Long!$L$2:$L$201,MATCH("C9|unified_cc_v2|cc_v2|pp:regulation3::coef1",Results_Long!$AK$2:$AK$201,0))),"n.e.",INDEX(Results_Long!$L$2:$L$201,MATCH("C9|unified_cc_v2|cc_v2|pp:regulation3::coef1",Results_Long!$AK$2:$AK$201,0))) -> n.e. | D64: =IF(ISBLANK(INDEX(Results_Long!$N$2:$N$201,MATCH("C9|unified_cc_v2|cc_v2|pp:regulation3::coef1",Results_Long!$AK$2:$AK$201,0))),"n.e.",INDEX(Results_Long!$N$2:$N$201,MATCH("C9|unified_cc_v2|cc_v2|pp:regulation3::coef1",Results_Long!$AK$2:$AK$201,0))) -> n.e. | E64: =IF(ISBLANK(INDEX(Results_Long!$O$2:$O$201,MATCH("C9|unified_cc_v2|cc_v2|pp:regulation3::coef1",Results_Long!$AK$2:$AK$201,0))),"—",INDEX(Results_Long!$O$2:$O$201,MATCH("C9|unified_cc_v2|cc_v2|pp:regulation3::coef1",Results_Long!$AK$2:$AK$201,0))) -> — | F64: =INDEX(Results_Long!$F$2:$F$201,MATCH("C9|unified_cc_v2|cc_v2|pp:regulation3::coef1",Results_Long!$AK$2:$AK$201,0)) -> not_estimable
A65: pp:country_region::coef1 | B65: =IF(ISBLANK(INDEX(Results_Long!$K$2:$K$201,MATCH("C9|unified_cc_v2|cc_v2|pp:country_region::coef1",Results_Long!$AK$2:$AK$201,0))),"n.e.",INDEX(Results_Long!$K$2:$K$201,MATCH("C9|unified_cc_v2|cc_v2|pp:country_region::coef1",Results_Long!$AK$2:$AK$201,0))) -> n.e. | C65: =IF(ISBLANK(INDEX(Results_Long!$L$2:$L$201,MATCH("C9|unified_cc_v2|cc_v2|pp:country_region::coef1",Results_Long!$AK$2:$AK$201,0))),"n.e.",INDEX(Results_Long!$L$2:$L$201,MATCH("C9|unified_cc_v2|cc_v2|pp:country_region::coef1",Results_Long!$AK$2:$AK$201,0))) -> n.e. | D65: =IF(ISBLANK(INDEX(Results_Long!$N$2:$N$201,MATCH("C9|unified_cc_v2|cc_v2|pp:country_region::coef1",Results_Long!$AK$2:$AK$201,0))),"n.e.",INDEX(Results_Long!$N$2:$N$201,MATCH("C9|unified_cc_v2|cc_v2|pp:country_region::coef1",Results_Long!$AK$2:$AK$201,0))) -> n.e. | E65: =IF(ISBLANK(INDEX(Results_Long!$O$2:$O$201,MATCH("C9|unified_cc_v2|cc_v2|pp:country_region::coef1",Results_Long!$AK$2:$AK$201,0))),"—",INDEX(Results_Long!$O$2:$O$201,MATCH("C9|unified_cc_v2|cc_v2|pp:country_region::coef1",Results_Long!$AK$2:$AK$201,0))) -> — | F65: =INDEX(Results_Long!$F$2:$F$201,MATCH("C9|unified_cc_v2|cc_v2|pp:country_region::coef1",Results_Long!$AK$2:$AK$201,0)) -> not_estimable
A66: pp:country_region::coef2 | B66: =IF(ISBLANK(INDEX(Results_Long!$K$2:$K$201,MATCH("C9|unified_cc_v2|cc_v2|pp:country_region::coef2",Results_Long!$AK$2:$AK$201,0))),"n.e.",INDEX(Results_Long!$K$2:$K$201,MATCH("C9|unified_cc_v2|cc_v2|pp:country_region::coef2",Results_Long!$AK$2:$AK$201,0))) -> n.e. | C66: =IF(ISBLANK(INDEX(Results_Long!$L$2:$L$201,MATCH("C9|unified_cc_v2|cc_v2|pp:country_region::coef2",Results_Long!$AK$2:$AK$201,0))),"n.e.",INDEX(Results_Long!$L$2:$L$201,MATCH("C9|unified_cc_v2|cc_v2|pp:country_region::coef2",Results_Long!$AK$2:$AK$201,0))) -> n.e. | D66: =IF(ISBLANK(INDEX(Results_Long!$N$2:$N$201,MATCH("C9|unified_cc_v2|cc_v2|pp:country_region::coef2",Results_Long!$AK$2:$AK$201,0))),"n.e.",INDEX(Results_Long!$N$2:$N$201,MATCH("C9|unified_cc_v2|cc_v2|pp:country_region::coef2",Results_Long!$AK$2:$AK$201,0))) -> n.e. | E66: =IF(ISBLANK(INDEX(Results_Long!$O$2:$O$201,MATCH("C9|unified_cc_v2|cc_v2|pp:country_region::coef2",Results_Long!$AK$2:$AK$201,0))),"—",INDEX(Results_Long!$O$2:$O$201,MATCH("C9|unified_cc_v2|cc_v2|pp:country_region::coef2",Results_Long!$AK$2:$AK$201,0))) -> — | F66: =INDEX(Results_Long!$F$2:$F$201,MATCH("C9|unified_cc_v2|cc_v2|pp:country_region::coef2",Results_Long!$AK$2:$AK$201,0)) -> not_estimable
A67: pp:country_econ::coef1 | B67: =IF(ISBLANK(INDEX(Results_Long!$K$2:$K$201,MATCH("C9|unified_cc_v2|cc_v2|pp:country_econ::coef1",Results_Long!$AK$2:$AK$201,0))),"n.e.",INDEX(Results_Long!$K$2:$K$201,MATCH("C9|unified_cc_v2|cc_v2|pp:country_econ::coef1",Results_Long!$AK$2:$AK$201,0))) -> n.e. | C67: =IF(ISBLANK(INDEX(Results_Long!$L$2:$L$201,MATCH("C9|unified_cc_v2|cc_v2|pp:country_econ::coef1",Results_Long!$AK$2:$AK$201,0))),"n.e.",INDEX(Results_Long!$L$2:$L$201,MATCH("C9|unified_cc_v2|cc_v2|pp:country_econ::coef1",Results_Long!$AK$2:$AK$201,0))) -> n.e. | D67: =IF(ISBLANK(INDEX(Results_Long!$N$2:$N$201,MATCH("C9|unified_cc_v2|cc_v2|pp:country_econ::coef1",Results_Long!$AK$2:$AK$201,0))),"n.e.",INDEX(Results_Long!$N$2:$N$201,MATCH("C9|unified_cc_v2|cc_v2|pp:country_econ::coef1",Results_Long!$AK$2:$AK$201,0))) -> n.e. | E67: =IF(ISBLANK(INDEX(Results_Long!$O$2:$O$201,MATCH("C9|unified_cc_v2|cc_v2|pp:country_econ::coef1",Results_Long!$AK$2:$AK$201,0))),"—",INDEX(Results_Long!$O$2:$O$201,MATCH("C9|unified_cc_v2|cc_v2|pp:country_econ::coef1",Results_Long!$AK$2:$AK$201,0))) -> — | F67: =INDEX(Results_Long!$F$2:$F$201,MATCH("C9|unified_cc_v2|cc_v2|pp:country_econ::coef1",Results_Long!$AK$2:$AK$201,0)) -> not_estimable
A68: pp:country_culture::coef1 | B68: =IF(ISBLANK(INDEX(Results_Long!$K$2:$K$201,MATCH("C9|unified_cc_v2|cc_v2|pp:country_culture::coef1",Results_Long!$AK$2:$AK$201,0))),"n.e.",INDEX(Results_Long!$K$2:$K$201,MATCH("C9|unified_cc_v2|cc_v2|pp:country_culture::coef1",Results_Long!$AK$2:$AK$201,0))) -> n.e. | C68: =IF(ISBLANK(INDEX(Results_Long!$L$2:$L$201,MATCH("C9|unified_cc_v2|cc_v2|pp:country_culture::coef1",Results_Long!$AK$2:$AK$201,0))),"n.e.",INDEX(Results_Long!$L$2:$L$201,MATCH("C9|unified_cc_v2|cc_v2|pp:country_culture::coef1",Results_Long!$AK$2:$AK$201,0))) -> n.e. | D68: =IF(ISBLANK(INDEX(Results_Long!$N$2:$N$201,MATCH("C9|unified_cc_v2|cc_v2|pp:country_culture::coef1",Results_Long!$AK$2:$AK$201,0))),"n.e.",INDEX(Results_Long!$N$2:$N$201,MATCH("C9|unified_cc_v2|cc_v2|pp:country_culture::coef1",Results_Long!$AK$2:$AK$201,0))) -> n.e. | E68: =IF(ISBLANK(INDEX(Results_Long!$O$2:$O$201,MATCH("C9|unified_cc_v2|cc_v2|pp:country_culture::coef1",Results_Long!$AK$2:$AK$201,0))),"—",INDEX(Results_Long!$O$2:$O$201,MATCH("C9|unified_cc_v2|cc_v2|pp:country_culture::coef1",Results_Long!$AK$2:$AK$201,0))) -> — | F68: =INDEX(Results_Long!$F$2:$F$201,MATCH("C9|unified_cc_v2|cc_v2|pp:country_culture::coef1",Results_Long!$AK$2:$AK$201,0)) -> not_estimable
A69: pp:country_legal::coef1 | B69: =IF(ISBLANK(INDEX(Results_Long!$K$2:$K$201,MATCH("C9|unified_cc_v2|cc_v2|pp:country_legal::coef1",Results_Long!$AK$2:$AK$201,0))),"n.e.",INDEX(Results_Long!$K$2:$K$201,MATCH("C9|unified_cc_v2|cc_v2|pp:country_legal::coef1",Results_Long!$AK$2:$AK$201,0))) -> n.e. | C69: =IF(ISBLANK(INDEX(Results_Long!$L$2:$L$201,MATCH("C9|unified_cc_v2|cc_v2|pp:country_legal::coef1",Results_Long!$AK$2:$AK$201,0))),"n.e.",INDEX(Results_Long!$L$2:$L$201,MATCH("C9|unified_cc_v2|cc_v2|pp:country_legal::coef1",Results_Long!$AK$2:$AK$201,0))) -> n.e. | D69: =IF(ISBLANK(INDEX(Results_Long!$N$2:$N$201,MATCH("C9|unified_cc_v2|cc_v2|pp:country_legal::coef1",Results_Long!$AK$2:$AK$201,0))),"n.e.",INDEX(Results_Long!$N$2:$N$201,MATCH("C9|unified_cc_v2|cc_v2|pp:country_legal::coef1",Results_Long!$AK$2:$AK$201,0))) -> n.e. | E69: =IF(ISBLANK(INDEX(Results_Long!$O$2:$O$201,MATCH("C9|unified_cc_v2|cc_v2|pp:country_legal::coef1",Results_Long!$AK$2:$AK$201,0))),"—",INDEX(Results_Long!$O$2:$O$201,MATCH("C9|unified_cc_v2|cc_v2|pp:country_legal::coef1",Results_Long!$AK$2:$AK$201,0))) -> — | F69: =INDEX(Results_Long!$F$2:$F$201,MATCH("C9|unified_cc_v2|cc_v2|pp:country_legal::coef1",Results_Long!$AK$2:$AK$201,0)) -> not_estimable
A70: Block HTZ | B70: F | C70: df | D70: p | E70: status
A71: block_HTZ::CER_measure | B71: =IF(ISBLANK(INDEX(Results_Long!$M$2:$M$201,MATCH("C9|unified_cc_v2|cc_v2|block_HTZ::CER_measure",Results_Long!$AK$2:$AK$201,0))),"n.e.",INDEX(Results_Long!$M$2:$M$201,MATCH("C9|unified_cc_v2|cc_v2|block_HTZ::CER_measure",Results_Long!$AK$2:$AK$201,0))) -> n.e. | C71: =IF(ISBLANK(INDEX(Results_Long!$N$2:$N$201,MATCH("C9|unified_cc_v2|cc_v2|block_HTZ::CER_measure",Results_Long!$AK$2:$AK$201,0))),"n.e.",INDEX(Results_Long!$N$2:$N$201,MATCH("C9|unified_cc_v2|cc_v2|block_HTZ::CER_measure",Results_Long!$AK$2:$AK$201,0))) -> n.e. | D71: =IF(ISBLANK(INDEX(Results_Long!$O$2:$O$201,MATCH("C9|unified_cc_v2|cc_v2|block_HTZ::CER_measure",Results_Long!$AK$2:$AK$201,0))),"—",INDEX(Results_Long!$O$2:$O$201,MATCH("C9|unified_cc_v2|cc_v2|block_HTZ::CER_measure",Results_Long!$AK$2:$AK$201,0))) -> — | E71: =INDEX(Results_Long!$F$2:$F$201,MATCH("C9|unified_cc_v2|cc_v2|block_HTZ::CER_measure",Results_Long!$AK$2:$AK$201,0)) -> not_estimable
A72: block_HTZ::COD_instrument | B72: =IF(ISBLANK(INDEX(Results_Long!$M$2:$M$201,MATCH("C9|unified_cc_v2|cc_v2|block_HTZ::COD_instrument",Results_Long!$AK$2:$AK$201,0))),"n.e.",INDEX(Results_Long!$M$2:$M$201,MATCH("C9|unified_cc_v2|cc_v2|block_HTZ::COD_instrument",Results_Long!$AK$2:$AK$201,0))) -> n.e. | C72: =IF(ISBLANK(INDEX(Results_Long!$N$2:$N$201,MATCH("C9|unified_cc_v2|cc_v2|block_HTZ::COD_instrument",Results_Long!$AK$2:$AK$201,0))),"n.e.",INDEX(Results_Long!$N$2:$N$201,MATCH("C9|unified_cc_v2|cc_v2|block_HTZ::COD_instrument",Results_Long!$AK$2:$AK$201,0))) -> n.e. | D72: =IF(ISBLANK(INDEX(Results_Long!$O$2:$O$201,MATCH("C9|unified_cc_v2|cc_v2|block_HTZ::COD_instrument",Results_Long!$AK$2:$AK$201,0))),"—",INDEX(Results_Long!$O$2:$O$201,MATCH("C9|unified_cc_v2|cc_v2|block_HTZ::COD_instrument",Results_Long!$AK$2:$AK$201,0))) -> — | E72: =INDEX(Results_Long!$F$2:$F$201,MATCH("C9|unified_cc_v2|cc_v2|block_HTZ::COD_instrument",Results_Long!$AK$2:$AK$201,0)) -> not_estimable
A73: block_HTZ::industry | B73: =IF(ISBLANK(INDEX(Results_Long!$M$2:$M$201,MATCH("C9|unified_cc_v2|cc_v2|block_HTZ::industry",Results_Long!$AK$2:$AK$201,0))),"n.e.",INDEX(Results_Long!$M$2:$M$201,MATCH("C9|unified_cc_v2|cc_v2|block_HTZ::industry",Results_Long!$AK$2:$AK$201,0))) -> n.e. | C73: =IF(ISBLANK(INDEX(Results_Long!$N$2:$N$201,MATCH("C9|unified_cc_v2|cc_v2|block_HTZ::industry",Results_Long!$AK$2:$AK$201,0))),"n.e.",INDEX(Results_Long!$N$2:$N$201,MATCH("C9|unified_cc_v2|cc_v2|block_HTZ::industry",Results_Long!$AK$2:$AK$201,0))) -> n.e. | D73: =IF(ISBLANK(INDEX(Results_Long!$O$2:$O$201,MATCH("C9|unified_cc_v2|cc_v2|block_HTZ::industry",Results_Long!$AK$2:$AK$201,0))),"—",INDEX(Results_Long!$O$2:$O$201,MATCH("C9|unified_cc_v2|cc_v2|block_HTZ::industry",Results_Long!$AK$2:$AK$201,0))) -> — | E73: =INDEX(Results_Long!$F$2:$F$201,MATCH("C9|unified_cc_v2|cc_v2|block_HTZ::industry",Results_Long!$AK$2:$AK$201,0)) -> not_estimable
A74: block_HTZ::regulation3 | B74: =IF(ISBLANK(INDEX(Results_Long!$M$2:$M$201,MATCH("C9|unified_cc_v2|cc_v2|block_HTZ::regulation3",Results_Long!$AK$2:$AK$201,0))),"n.e.",INDEX(Results_Long!$M$2:$M$201,MATCH("C9|unified_cc_v2|cc_v2|block_HTZ::regulation3",Results_Long!$AK$2:$AK$201,0))) -> n.e. | C74: =IF(ISBLANK(INDEX(Results_Long!$N$2:$N$201,MATCH("C9|unified_cc_v2|cc_v2|block_HTZ::regulation3",Results_Long!$AK$2:$AK$201,0))),"n.e.",INDEX(Results_Long!$N$2:$N$201,MATCH("C9|unified_cc_v2|cc_v2|block_HTZ::regulation3",Results_Long!$AK$2:$AK$201,0))) -> n.e. | D74: =IF(ISBLANK(INDEX(Results_Long!$O$2:$O$201,MATCH("C9|unified_cc_v2|cc_v2|block_HTZ::regulation3",Results_Long!$AK$2:$AK$201,0))),"—",INDEX(Results_Long!$O$2:$O$201,MATCH("C9|unified_cc_v2|cc_v2|block_HTZ::regulation3",Results_Long!$AK$2:$AK$201,0))) -> — | E74: =INDEX(Results_Long!$F$2:$F$201,MATCH("C9|unified_cc_v2|cc_v2|block_HTZ::regulation3",Results_Long!$AK$2:$AK$201,0)) -> not_estimable
A75: block_HTZ::country_region | B75: =IF(ISBLANK(INDEX(Results_Long!$M$2:$M$201,MATCH("C9|unified_cc_v2|cc_v2|block_HTZ::country_region",Results_Long!$AK$2:$AK$201,0))),"n.e.",INDEX(Results_Long!$M$2:$M$201,MATCH("C9|unified_cc_v2|cc_v2|block_HTZ::country_region",Results_Long!$AK$2:$AK$201,0))) -> n.e. | C75: =IF(ISBLANK(INDEX(Results_Long!$N$2:$N$201,MATCH("C9|unified_cc_v2|cc_v2|block_HTZ::country_region",Results_Long!$AK$2:$AK$201,0))),"n.e.",INDEX(Results_Long!$N$2:$N$201,MATCH("C9|unified_cc_v2|cc_v2|block_HTZ::country_region",Results_Long!$AK$2:$AK$201,0))) -> n.e. | D75: =IF(ISBLANK(INDEX(Results_Long!$O$2:$O$201,MATCH("C9|unified_cc_v2|cc_v2|block_HTZ::country_region",Results_Long!$AK$2:$AK$201,0))),"—",INDEX(Results_Long!$O$2:$O$201,MATCH("C9|unified_cc_v2|cc_v2|block_HTZ::country_region",Results_Long!$AK$2:$AK$201,0))) -> — | E75: =INDEX(Results_Long!$F$2:$F$201,MATCH("C9|unified_cc_v2|cc_v2|block_HTZ::country_region",Results_Long!$AK$2:$AK$201,0)) -> not_estimable
A76: block_HTZ::country_econ | B76: =IF(ISBLANK(INDEX(Results_Long!$M$2:$M$201,MATCH("C9|unified_cc_v2|cc_v2|block_HTZ::country_econ",Results_Long!$AK$2:$AK$201,0))),"n.e.",INDEX(Results_Long!$M$2:$M$201,MATCH("C9|unified_cc_v2|cc_v2|block_HTZ::country_econ",Results_Long!$AK$2:$AK$201,0))) -> n.e. | C76: =IF(ISBLANK(INDEX(Results_Long!$N$2:$N$201,MATCH("C9|unified_cc_v2|cc_v2|block_HTZ::country_econ",Results_Long!$AK$2:$AK$201,0))),"n.e.",INDEX(Results_Long!$N$2:$N$201,MATCH("C9|unified_cc_v2|cc_v2|block_HTZ::country_econ",Results_Long!$AK$2:$AK$201,0))) -> n.e. | D76: =IF(ISBLANK(INDEX(Results_Long!$O$2:$O$201,MATCH("C9|unified_cc_v2|cc_v2|block_HTZ::country_econ",Results_Long!$AK$2:$AK$201,0))),"—",INDEX(Results_Long!$O$2:$O$201,MATCH("C9|unified_cc_v2|cc_v2|block_HTZ::country_econ",Results_Long!$AK$2:$AK$201,0))) -> — | E76: =INDEX(Results_Long!$F$2:$F$201,MATCH("C9|unified_cc_v2|cc_v2|block_HTZ::country_econ",Results_Long!$AK$2:$AK$201,0)) -> not_estimable
A77: block_HTZ::country_culture | B77: =IF(ISBLANK(INDEX(Results_Long!$M$2:$M$201,MATCH("C9|unified_cc_v2|cc_v2|block_HTZ::country_culture",Results_Long!$AK$2:$AK$201,0))),"n.e.",INDEX(Results_Long!$M$2:$M$201,MATCH("C9|unified_cc_v2|cc_v2|block_HTZ::country_culture",Results_Long!$AK$2:$AK$201,0))) -> n.e. | C77: =IF(ISBLANK(INDEX(Results_Long!$N$2:$N$201,MATCH("C9|unified_cc_v2|cc_v2|block_HTZ::country_culture",Results_Long!$AK$2:$AK$201,0))),"n.e.",INDEX(Results_Long!$N$2:$N$201,MATCH("C9|unified_cc_v2|cc_v2|block_HTZ::country_culture",Results_Long!$AK$2:$AK$201,0))) -> n.e. | D77: =IF(ISBLANK(INDEX(Results_Long!$O$2:$O$201,MATCH("C9|unified_cc_v2|cc_v2|block_HTZ::country_culture",Results_Long!$AK$2:$AK$201,0))),"—",INDEX(Results_Long!$O$2:$O$201,MATCH("C9|unified_cc_v2|cc_v2|block_HTZ::country_culture",Results_Long!$AK$2:$AK$201,0))) -> — | E77: =INDEX(Results_Long!$F$2:$F$201,MATCH("C9|unified_cc_v2|cc_v2|block_HTZ::country_culture",Results_Long!$AK$2:$AK$201,0)) -> not_estimable
A78: block_HTZ::country_legal | B78: =IF(ISBLANK(INDEX(Results_Long!$M$2:$M$201,MATCH("C9|unified_cc_v2|cc_v2|block_HTZ::country_legal",Results_Long!$AK$2:$AK$201,0))),"n.e.",INDEX(Results_Long!$M$2:$M$201,MATCH("C9|unified_cc_v2|cc_v2|block_HTZ::country_legal",Results_Long!$AK$2:$AK$201,0))) -> n.e. | C78: =IF(ISBLANK(INDEX(Results_Long!$N$2:$N$201,MATCH("C9|unified_cc_v2|cc_v2|block_HTZ::country_legal",Results_Long!$AK$2:$AK$201,0))),"n.e.",INDEX(Results_Long!$N$2:$N$201,MATCH("C9|unified_cc_v2|cc_v2|block_HTZ::country_legal",Results_Long!$AK$2:$AK$201,0))) -> n.e. | D78: =IF(ISBLANK(INDEX(Results_Long!$O$2:$O$201,MATCH("C9|unified_cc_v2|cc_v2|block_HTZ::country_legal",Results_Long!$AK$2:$AK$201,0))),"—",INDEX(Results_Long!$O$2:$O$201,MATCH("C9|unified_cc_v2|cc_v2|block_HTZ::country_legal",Results_Long!$AK$2:$AK$201,0))) -> — | E78: =INDEX(Results_Long!$F$2:$F$201,MATCH("C9|unified_cc_v2|cc_v2|block_HTZ::country_legal",Results_Long!$AK$2:$AK$201,0)) -> not_estimable
A80: Interpretation
A81: The conditional Paris coefficient is small and non-significant in both variants; the mechanical rule admitted the CER and region blocks in V1 and no block in V2 (four structural, four df exclusions) — all disclosed in the echo rows.
A82: Identification note (design fact): the complete-case post cell contains no US clusters, so the model matrix satisfies pp = pp x Europe + pp x AsiaPac exactly; pp:AsiaPac is the single rank drop and the conditional contrast is identified on Asia-Pacific and European post evidence.
A83: The intercept is the adjusted pre-period reference-cell mean — a nuisance parameter, not a claim quantity; in V2 it sits at the 0.05 boundary and is reported mechanically.
A85: Question | B85: Answer
A86: Why does V2 carry no interactions? | B86: On the all-eight complete case the post cell shrinks to nine clusters with a single level of every country dimension — the interactions are structurally non-identifiable; this is itself a composition finding [DEC-043].
A87: Is the pp coefficient comparable to the B1 headline? | B87: It is the same period contrast conditioned on the V1/V2 moderator sets and restricted to the classifiable complete case; the pooled headline lives in T2/B1 (single home).
A88: Why is pp:AsiaPac not estimable? | B88: Exact design identity on the US-free complete-case post cell; the region block HTZ is computed on the remaining column with q_eff disclosed [#27].
A90: Mechanical outcome: the conditional Paris contrast is not significant in either unified specification, with every block exclusion produced by the pre-registered mechanical rule and disclosed; wording per the resolved gate [DEC-044/DEC-047].

Sheet 10_Guards_Sensitivity
A1: Guards, sensitivity and design disclosure
A2: M-pre pre-trend guards [DEC-031c] · any-with coding sensitivity [Q11b] · NCE and coding-absence disclosure [DEC-048]
A3: All cells formula-linked to Results_Long
A5: M-pre pre-trend guards (pre domain, z scale)
A6: Term | B6: est | C6: df | D6: p | E6: status
A7: C3 · mpre_int::non-sensitive | B7: =IF(ISBLANK(INDEX(Results_Long!$K$2:$K$201,MATCH("C3|m_pre|pre_classified|mpre_int::non-sensitive",Results_Long!$AK$2:$AK$201,0))),"n.e.",INDEX(Results_Long!$K$2:$K$201,MATCH("C3|m_pre|pre_classified|mpre_int::non-sensitive",Results_Long!$AK$2:$AK$201,0))) -> -0.082118428 | C7: =IF(ISBLANK(INDEX(Results_Long!$N$2:$N$201,MATCH("C3|m_pre|pre_classified|mpre_int::non-sensitive",Results_Long!$AK$2:$AK$201,0))),"n.e.",INDEX(Results_Long!$N$2:$N$201,MATCH("C3|m_pre|pre_classified|mpre_int::non-sensitive",Results_Long!$AK$2:$AK$201,0))) -> 44.231166 | D7: =IF(ISBLANK(INDEX(Results_Long!$O$2:$O$201,MATCH("C3|m_pre|pre_classified|mpre_int::non-sensitive",Results_Long!$AK$2:$AK$201,0))),"—",INDEX(Results_Long!$O$2:$O$201,MATCH("C3|m_pre|pre_classified|mpre_int::non-sensitive",Results_Long!$AK$2:$AK$201,0))) -> 0.028465014 | E7: =INDEX(Results_Long!$F$2:$F$201,MATCH("C3|m_pre|pre_classified|mpre_int::non-sensitive",Results_Long!$AK$2:$AK$201,0)) -> 3LMA-RVE_CR2
A8: C3 · mpre_int::sensitive | B8: =IF(ISBLANK(INDEX(Results_Long!$K$2:$K$201,MATCH("C3|m_pre|pre_classified|mpre_int::sensitive",Results_Long!$AK$2:$AK$201,0))),"n.e.",INDEX(Results_Long!$K$2:$K$201,MATCH("C3|m_pre|pre_classified|mpre_int::sensitive",Results_Long!$AK$2:$AK$201,0))) -> -0.054533671 | C8: =IF(ISBLANK(INDEX(Results_Long!$N$2:$N$201,MATCH("C3|m_pre|pre_classified|mpre_int::sensitive",Results_Long!$AK$2:$AK$201,0))),"n.e.",INDEX(Results_Long!$N$2:$N$201,MATCH("C3|m_pre|pre_classified|mpre_int::sensitive",Results_Long!$AK$2:$AK$201,0))) -> 8.2267906 | D8: =IF(ISBLANK(INDEX(Results_Long!$O$2:$O$201,MATCH("C3|m_pre|pre_classified|mpre_int::sensitive",Results_Long!$AK$2:$AK$201,0))),"—",INDEX(Results_Long!$O$2:$O$201,MATCH("C3|m_pre|pre_classified|mpre_int::sensitive",Results_Long!$AK$2:$AK$201,0))) -> 0.12945566 | E8: =INDEX(Results_Long!$F$2:$F$201,MATCH("C3|m_pre|pre_classified|mpre_int::sensitive",Results_Long!$AK$2:$AK$201,0)) -> 3LMA-RVE_CR2
A9: C3 · mpre_slope::non-sensitive | B9: =IF(ISBLANK(INDEX(Results_Long!$K$2:$K$201,MATCH("C3|m_pre|pre_classified|mpre_slope::non-sensitive",Results_Long!$AK$2:$AK$201,0))),"n.e.",INDEX(Results_Long!$K$2:$K$201,MATCH("C3|m_pre|pre_classified|mpre_slope::non-sensitive",Results_Long!$AK$2:$AK$201,0))) -> -0.0034260387 | C9: =IF(ISBLANK(INDEX(Results_Long!$N$2:$N$201,MATCH("C3|m_pre|pre_classified|mpre_slope::non-sensitive",Results_Long!$AK$2:$AK$201,0))),"n.e.",INDEX(Results_Long!$N$2:$N$201,MATCH("C3|m_pre|pre_classified|mpre_slope::non-sensitive",Results_Long!$AK$2:$AK$201,0))) -> 13.158338 | D9: =IF(ISBLANK(INDEX(Results_Long!$O$2:$O$201,MATCH("C3|m_pre|pre_classified|mpre_slope::non-sensitive",Results_Long!$AK$2:$AK$201,0))),"—",INDEX(Results_Long!$O$2:$O$201,MATCH("C3|m_pre|pre_classified|mpre_slope::non-sensitive",Results_Long!$AK$2:$AK$201,0))) -> 0.12842868 | E9: =INDEX(Results_Long!$F$2:$F$201,MATCH("C3|m_pre|pre_classified|mpre_slope::non-sensitive",Results_Long!$AK$2:$AK$201,0)) -> 3LMA-RVE_CR2
A10: C3 · mpre_slope::sensitive | B10: =IF(ISBLANK(INDEX(Results_Long!$K$2:$K$201,MATCH("C3|m_pre|pre_classified|mpre_slope::sensitive",Results_Long!$AK$2:$AK$201,0))),"n.e.",INDEX(Results_Long!$K$2:$K$201,MATCH("C3|m_pre|pre_classified|mpre_slope::sensitive",Results_Long!$AK$2:$AK$201,0))) -> 0.0017175338 | C10: =IF(ISBLANK(INDEX(Results_Long!$N$2:$N$201,MATCH("C3|m_pre|pre_classified|mpre_slope::sensitive",Results_Long!$AK$2:$AK$201,0))),"n.e.",INDEX(Results_Long!$N$2:$N$201,MATCH("C3|m_pre|pre_classified|mpre_slope::sensitive",Results_Long!$AK$2:$AK$201,0))) -> 2.5971721 | D10: =IF(ISBLANK(INDEX(Results_Long!$O$2:$O$201,MATCH("C3|m_pre|pre_classified|mpre_slope::sensitive",Results_Long!$AK$2:$AK$201,0))),"—",INDEX(Results_Long!$O$2:$O$201,MATCH("C3|m_pre|pre_classified|mpre_slope::sensitive",Results_Long!$AK$2:$AK$201,0))) -> — | E10: =INDEX(Results_Long!$F$2:$F$201,MATCH("C3|m_pre|pre_classified|mpre_slope::sensitive",Results_Long!$AK$2:$AK$201,0)) -> 3LMA-RVE_CR2
A11: C3 · mpre_slope_HTZ | B11: =IF(ISBLANK(INDEX(Results_Long!$M$2:$M$201,MATCH("C3|m_pre|pre_classified|mpre_slope_HTZ",Results_Long!$AK$2:$AK$201,0))),"n.e.",INDEX(Results_Long!$M$2:$M$201,MATCH("C3|m_pre|pre_classified|mpre_slope_HTZ",Results_Long!$AK$2:$AK$201,0))) -> 1.3888713 | C11: =IF(ISBLANK(INDEX(Results_Long!$N$2:$N$201,MATCH("C3|m_pre|pre_classified|mpre_slope_HTZ",Results_Long!$AK$2:$AK$201,0))),"n.e.",INDEX(Results_Long!$N$2:$N$201,MATCH("C3|m_pre|pre_classified|mpre_slope_HTZ",Results_Long!$AK$2:$AK$201,0))) -> 3.5969356 | D11: =IF(ISBLANK(INDEX(Results_Long!$O$2:$O$201,MATCH("C3|m_pre|pre_classified|mpre_slope_HTZ",Results_Long!$AK$2:$AK$201,0))),"—",INDEX(Results_Long!$O$2:$O$201,MATCH("C3|m_pre|pre_classified|mpre_slope_HTZ",Results_Long!$AK$2:$AK$201,0))) -> 0.31063591 | E11: =INDEX(Results_Long!$F$2:$F$201,MATCH("C3|m_pre|pre_classified|mpre_slope_HTZ",Results_Long!$AK$2:$AK$201,0)) -> 3LMA-RVE_CR2
A12: C4 · mpre_int::without ETS/CT | B12: =IF(ISBLANK(INDEX(Results_Long!$K$2:$K$201,MATCH("C4|m_pre|pre_classified|mpre_int::without ETS/CT",Results_Long!$AK$2:$AK$201,0))),"n.e.",INDEX(Results_Long!$K$2:$K$201,MATCH("C4|m_pre|pre_classified|mpre_int::without ETS/CT",Results_Long!$AK$2:$AK$201,0))) -> -0.084391197 | C12: =IF(ISBLANK(INDEX(Results_Long!$N$2:$N$201,MATCH("C4|m_pre|pre_classified|mpre_int::without ETS/CT",Results_Long!$AK$2:$AK$201,0))),"n.e.",INDEX(Results_Long!$N$2:$N$201,MATCH("C4|m_pre|pre_classified|mpre_int::without ETS/CT",Results_Long!$AK$2:$AK$201,0))) -> 33.921994 | D12: =IF(ISBLANK(INDEX(Results_Long!$O$2:$O$201,MATCH("C4|m_pre|pre_classified|mpre_int::without ETS/CT",Results_Long!$AK$2:$AK$201,0))),"—",INDEX(Results_Long!$O$2:$O$201,MATCH("C4|m_pre|pre_classified|mpre_int::without ETS/CT",Results_Long!$AK$2:$AK$201,0))) -> 0.028410572 | E12: =INDEX(Results_Long!$F$2:$F$201,MATCH("C4|m_pre|pre_classified|mpre_int::without ETS/CT",Results_Long!$AK$2:$AK$201,0)) -> 3LMA-RVE_CR2
A13: C4 · mpre_int::with ETS/CT | B13: =IF(ISBLANK(INDEX(Results_Long!$K$2:$K$201,MATCH("C4|m_pre|pre_classified|mpre_int::with ETS/CT",Results_Long!$AK$2:$AK$201,0))),"n.e.",INDEX(Results_Long!$K$2:$K$201,MATCH("C4|m_pre|pre_classified|mpre_int::with ETS/CT",Results_Long!$AK$2:$AK$201,0))) -> 0.046413875 | C13: =IF(ISBLANK(INDEX(Results_Long!$N$2:$N$201,MATCH("C4|m_pre|pre_classified|mpre_int::with ETS/CT",Results_Long!$AK$2:$AK$201,0))),"n.e.",INDEX(Results_Long!$N$2:$N$201,MATCH("C4|m_pre|pre_classified|mpre_int::with ETS/CT",Results_Long!$AK$2:$AK$201,0))) -> 6.595795 | D13: =IF(ISBLANK(INDEX(Results_Long!$O$2:$O$201,MATCH("C4|m_pre|pre_classified|mpre_int::with ETS/CT",Results_Long!$AK$2:$AK$201,0))),"—",INDEX(Results_Long!$O$2:$O$201,MATCH("C4|m_pre|pre_classified|mpre_int::with ETS/CT",Results_Long!$AK$2:$AK$201,0))) -> 0.5313448 | E13: =INDEX(Results_Long!$F$2:$F$201,MATCH("C4|m_pre|pre_classified|mpre_int::with ETS/CT",Results_Long!$AK$2:$AK$201,0)) -> 3LMA-RVE_CR2
A14: C4 · mpre_slope::without ETS/CT | B14: =IF(ISBLANK(INDEX(Results_Long!$K$2:$K$201,MATCH("C4|m_pre|pre_classified|mpre_slope::without ETS/CT",Results_Long!$AK$2:$AK$201,0))),"n.e.",INDEX(Results_Long!$K$2:$K$201,MATCH("C4|m_pre|pre_classified|mpre_slope::without ETS/CT",Results_Long!$AK$2:$AK$201,0))) -> -0.0037454926 | C14: =IF(ISBLANK(INDEX(Results_Long!$N$2:$N$201,MATCH("C4|m_pre|pre_classified|mpre_slope::without ETS/CT",Results_Long!$AK$2:$AK$201,0))),"n.e.",INDEX(Results_Long!$N$2:$N$201,MATCH("C4|m_pre|pre_classified|mpre_slope::without ETS/CT",Results_Long!$AK$2:$AK$201,0))) -> 16.533678 | D14: =IF(ISBLANK(INDEX(Results_Long!$O$2:$O$201,MATCH("C4|m_pre|pre_classified|mpre_slope::without ETS/CT",Results_Long!$AK$2:$AK$201,0))),"—",INDEX(Results_Long!$O$2:$O$201,MATCH("C4|m_pre|pre_classified|mpre_slope::without ETS/CT",Results_Long!$AK$2:$AK$201,0))) -> 0.19430669 | E14: =INDEX(Results_Long!$F$2:$F$201,MATCH("C4|m_pre|pre_classified|mpre_slope::without ETS/CT",Results_Long!$AK$2:$AK$201,0)) -> 3LMA-RVE_CR2
A15: C4 · mpre_slope::with ETS/CT | B15: =IF(ISBLANK(INDEX(Results_Long!$K$2:$K$201,MATCH("C4|m_pre|pre_classified|mpre_slope::with ETS/CT",Results_Long!$AK$2:$AK$201,0))),"n.e.",INDEX(Results_Long!$K$2:$K$201,MATCH("C4|m_pre|pre_classified|mpre_slope::with ETS/CT",Results_Long!$AK$2:$AK$201,0))) -> 0.046345496 | C15: =IF(ISBLANK(INDEX(Results_Long!$N$2:$N$201,MATCH("C4|m_pre|pre_classified|mpre_slope::with ETS/CT",Results_Long!$AK$2:$AK$201,0))),"n.e.",INDEX(Results_Long!$N$2:$N$201,MATCH("C4|m_pre|pre_classified|mpre_slope::with ETS/CT",Results_Long!$AK$2:$AK$201,0))) -> 6.8931284 | D15: =IF(ISBLANK(INDEX(Results_Long!$O$2:$O$201,MATCH("C4|m_pre|pre_classified|mpre_slope::with ETS/CT",Results_Long!$AK$2:$AK$201,0))),"—",INDEX(Results_Long!$O$2:$O$201,MATCH("C4|m_pre|pre_classified|mpre_slope::with ETS/CT",Results_Long!$AK$2:$AK$201,0))) -> 0.30734989 | E15: =INDEX(Results_Long!$F$2:$F$201,MATCH("C4|m_pre|pre_classified|mpre_slope::with ETS/CT",Results_Long!$AK$2:$AK$201,0)) -> 3LMA-RVE_CR2
A16: C4 · mpre_slope_HTZ | B16: =IF(ISBLANK(INDEX(Results_Long!$M$2:$M$201,MATCH("C4|m_pre|pre_classified|mpre_slope_HTZ",Results_Long!$AK$2:$AK$201,0))),"n.e.",INDEX(Results_Long!$M$2:$M$201,MATCH("C4|m_pre|pre_classified|mpre_slope_HTZ",Results_Long!$AK$2:$AK$201,0))) -> 1.4185609 | C16: =IF(ISBLANK(INDEX(Results_Long!$N$2:$N$201,MATCH("C4|m_pre|pre_classified|mpre_slope_HTZ",Results_Long!$AK$2:$AK$201,0))),"n.e.",INDEX(Results_Long!$N$2:$N$201,MATCH("C4|m_pre|pre_classified|mpre_slope_HTZ",Results_Long!$AK$2:$AK$201,0))) -> 7.1896245 | D16: =IF(ISBLANK(INDEX(Results_Long!$O$2:$O$201,MATCH("C4|m_pre|pre_classified|mpre_slope_HTZ",Results_Long!$AK$2:$AK$201,0))),"—",INDEX(Results_Long!$O$2:$O$201,MATCH("C4|m_pre|pre_classified|mpre_slope_HTZ",Results_Long!$AK$2:$AK$201,0))) -> 0.27147238 | E16: =INDEX(Results_Long!$F$2:$F$201,MATCH("C4|m_pre|pre_classified|mpre_slope_HTZ",Results_Long!$AK$2:$AK$201,0)) -> 3LMA-RVE_CR2
A18: Regulation-coding sensitivity (spec panel; reference row first)
A19: Spec | B19: k_es | C19: est_z | D19: ci_z lo | E19: ci_z hi | F19: est_r | G19: ci_r lo | H19: ci_r hi | I19: df | J19: p
A20: end-anchored (canonical) — interaction HTZ | B20: =IF(ISBLANK(INDEX(Results_Long!$H$2:$H$201,MATCH("C4|paris_mid|defined_classified|interaction_HTZ",Results_Long!$AK$2:$AK$201,0))),"n.e.",INDEX(Results_Long!$H$2:$H$201,MATCH("C4|paris_mid|defined_classified|interaction_HTZ",Results_Long!$AK$2:$AK$201,0))) -> 1796 | C20: =IF(ISBLANK(INDEX(Results_Long!$K$2:$K$201,MATCH("C4|paris_mid|defined_classified|interaction_HTZ",Results_Long!$AK$2:$AK$201,0))),"n.e.",INDEX(Results_Long!$K$2:$K$201,MATCH("C4|paris_mid|defined_classified|interaction_HTZ",Results_Long!$AK$2:$AK$201,0))) -> n.e. | D20: =IF(ISBLANK(INDEX(Results_Long!$P$2:$P$201,MATCH("C4|paris_mid|defined_classified|interaction_HTZ",Results_Long!$AK$2:$AK$201,0))),"n.e.",INDEX(Results_Long!$P$2:$P$201,MATCH("C4|paris_mid|defined_classified|interaction_HTZ",Results_Long!$AK$2:$AK$201,0))) -> n.e. | E20: =IF(ISBLANK(INDEX(Results_Long!$Q$2:$Q$201,MATCH("C4|paris_mid|defined_classified|interaction_HTZ",Results_Long!$AK$2:$AK$201,0))),"n.e.",INDEX(Results_Long!$Q$2:$Q$201,MATCH("C4|paris_mid|defined_classified|interaction_HTZ",Results_Long!$AK$2:$AK$201,0))) -> n.e. | F20: =IF(ISBLANK(INDEX(Results_Long!$T$2:$T$201,MATCH("C4|paris_mid|defined_classified|interaction_HTZ",Results_Long!$AK$2:$AK$201,0))),"n.e.",INDEX(Results_Long!$T$2:$T$201,MATCH("C4|paris_mid|defined_classified|interaction_HTZ",Results_Long!$AK$2:$AK$201,0))) -> n.e. | G20: =IF(ISBLANK(INDEX(Results_Long!$U$2:$U$201,MATCH("C4|paris_mid|defined_classified|interaction_HTZ",Results_Long!$AK$2:$AK$201,0))),"n.e.",INDEX(Results_Long!$U$2:$U$201,MATCH("C4|paris_mid|defined_classified|interaction_HTZ",Results_Long!$AK$2:$AK$201,0))) -> n.e. | H20: =IF(ISBLANK(INDEX(Results_Long!$V$2:$V$201,MATCH("C4|paris_mid|defined_classified|interaction_HTZ",Results_Long!$AK$2:$AK$201,0))),"n.e.",INDEX(Results_Long!$V$2:$V$201,MATCH("C4|paris_mid|defined_classified|interaction_HTZ",Results_Long!$AK$2:$AK$201,0))) -> n.e. | I20: =IF(ISBLANK(INDEX(Results_Long!$N$2:$N$201,MATCH("C4|paris_mid|defined_classified|interaction_HTZ",Results_Long!$AK$2:$AK$201,0))),"n.e.",INDEX(Results_Long!$N$2:$N$201,MATCH("C4|paris_mid|defined_classified|interaction_HTZ",Results_Long!$AK$2:$AK$201,0))) -> 9.4938297 | J20: =IF(ISBLANK(INDEX(Results_Long!$O$2:$O$201,MATCH("C4|paris_mid|defined_classified|interaction_HTZ",Results_Long!$AK$2:$AK$201,0))),"—",INDEX(Results_Long!$O$2:$O$201,MATCH("C4|paris_mid|defined_classified|interaction_HTZ",Results_Long!$AK$2:$AK$201,0))) -> 0.38300481
