Workbook

Sheet 1_README
A1: TH-a (Block E/H fast frequentist battery) · README
A2: Template: docs/results_workbook_template.md (binding; 13-tab SOMA)
A3: Run 2026-07-24 22:46 (canonical) · verifier R/06_verify_outputs.R 17/17 PASS · chat artefact check 2026-07-26 18/18 PASS · output/TH_a_results.csv 177x36
A5: Item | B5: Value
A6: Workbook version | B6: v1.0 (built post-run by project chat; verifier never reads this file)
A7: Method one-liner | B7: Fast frequentist E/H battery on the 3L-RVE spine: TOST equivalence (E1/E2), gate configuration (E3), sup-break grid (H4), Zarea transplant (H6), cumulative MA (H7), rolling windows (H8), external comparison (H9), conditional p-curve (H10), within-study display (H11).
A8: Scope | B8: Block E (E1-E3) + Block H fast analyses (H4 grid, H6-H11); estimation set 2,713 ES / 115 studies / 114 clusters; period domain 2,705 / 113 / 112.
A9: Repo / commit basis | B9: rwitte-wu-research/FOMA-CER-COD-Paris; chain 5a99de6 -> e44fce7 (#12) -> fce9d3a (#13) -> dafd95e (#14); family commit lands on dafd95e (main = origin)
A10: Computational stack | B10: R 4.6.1 (ucrt) · metafor 5.0-1 · clubSandwich 0.7.0 · Matrix 1.7-5 · Windows 11 x64 (26200) · reference BLAS single-threaded + per-worker thread guards
A11: Scripts | B11: R/06_e_h_fast.R + R/06_verify_outputs.R (paired verifier, 17/17 PASS)
A12: Decision basis | B12: DEC-045 (E/H execution spec incl. supersessions S1-S9) · DEC-031f (optimizer ladder) · DEC-044 (framing A; language gate UNRESOLVED - see 3_Interpretation_Guide)
A13: Framing gate | B13: Framing gate [DEC-044]: all TOST flags and permutation p-values in this workbook are MECHANICAL values; no evidence-of-absence or verdict language is used anywhere; adjudication happens as the documented gate-resolution step after TH-b (H2a/H2b RoBMA).
A14: TAB-INDEX | B14: 1_README | 2_Methodology | 3_Interpretation_Guide | 4_Formula_Reference | 5_Data_Provenance | 6_E_TOST_Battery | 7_H4_Break_Grid | 8_H6_H7_Transpl_Cumul | 9_H8_H9_Rolling_External | 10_H10_H11_pcurve_within | Results_Long | Manuscript_Inputs | Manuscript_Text_Blocks

Sheet 2_Methodology
A1: TH-a (Block E/H fast frequentist battery) · Methodology
A2: Quantity | Formula / Construction | Reference (project notation)
A3: Run 2026-07-24 22:46 (canonical) · verifier R/06_verify_outputs.R 17/17 PASS · chat artefact check 2026-07-26 18/18 PASS · output/TH_a_results.csv 177x36
A5: Quantity | B5: Formula / Construction | C5: Reference
A6: Cell-means Paris model | B6: rma.mv with mods = ~ 0 + pp_cell on the period domain (2,705 ES / 113 studies / 112 clusters); diff = post - pre linear contrast; estimand identical to the T2/B1 moderator parameterization | C6: [DEC-024] [DEC-045 E-pins] [plan A.13]
A7: TOST equivalence machinery | B7: Two one-sided tests, each alpha = .05, equivalent to: 90% CI inside the band; TOST p = max(arm p); flag value = 1{90% CI inside band}; bands: E1 primary |r| = 0.070 (z = atanh = 0.070115), secondary 0.050; E2 secondary-SESOI band ±0.050 on the contrast | C7: Lakens (2017); Lakens et al. (2018) [PK]; [F27v2] [DEC-044 ladder]
A8: Inference spine | B8: 3-level REML (random = ~1 | cluster_id/study/esid), CR2 cluster-robust SEs, Satterthwaite df; inference unit = cluster_id; rho = 0.6 CS working correlation in V | C8: Hedges et al. (2010); Pustejovsky & Tipton (2022); Tipton & Pustejovsky (2015) [PK]; [DEC-031]
A9: Optimizer ladder | B9: nlminb -> BFGS -> Nelder-Mead with metafor convergence certification on EVERY spine fit (148 certificates this run; 148/0 rung-1/fallback) | C9: [DEC-031f R2/R3] [DEC-045 every-spine-fit pin]
A10: H4 sup-break grid | B10: Cell-means break model per candidate year 2008-2019; admissible = Satterthwaite df >= 5 on the break coefficient, computed ONCE on the observed design and held fixed for the TH-c permutation; observed statistic = sup |t| | C10: [DEC-024 transfer rule] [H-Q6/H-Q20] [DEC-045]
A11: H6 Zarea transplantation | B11: Zarea's Paris operationalization (study-midpoint rule WITH tie exclusion) applied within our 3L-RVE framework - the CODING is transplanted into the D31.1 spine, never the naive ES-level RE machinery | C11: [DEC-045/N8] (pinned wording)
A12: H7 cumulative MA | B12: Study-wise chronological refits; order = study median sample_mid, ties alphabetical; 113 steps; CI band from the first step with >= 10 clusters (step 10) | C12: [DEC-045/H-Q17] [Annex H N10]
A13: H8 rolling windows | B13: Width 6 y, step 1 y, anchor 1998 (min sample_mid 1998.5); tiers: >= 10 clusters full CR2 inference, 5-9 clusters descriptive point only, < 5 not estimated | C13: [DEC-045 S6]
A14: H9 external comparison | B14: Descriptive channel comparison against the COE companion STUDY-LEVEL estimate (Table 3, 75 units); explicitly NO test (SE provenance incompatible) | C14: [DEC-045/H-Q10/N12]
A15: H10 conditional p-curve | B15: N13 rule: conditional on >= 5 significant post-cell studies; selection = first-reported ES per post study (dat_prep row order); p reconstructed as 2*pnorm(-|zi|/sqrt(vi)); right-skew binomial + Stouffer, flatness vs. 33% power | C15: Simonsohn et al. (2014) [PK]; [Annex H/DEC-045 N13]
A16: H11 within-study display | B16: Studies with own pre- AND post-Paris ES, descriptive only, explicitly NO p-values; straddle inventory from pp_window_class == 'mixed' | C16: [DEC-045/N15/H-Q11]

Sheet 3_Interpretation_Guide
A1: TH-a (Block E/H fast frequentist battery) · Interpretation Guide
A2: How to read each reported quantity; thresholds with citations
A3: Framing gate [DEC-044]: all TOST flags and permutation p-values in this workbook are MECHANICAL values; no evidence-of-absence or verdict language is used anywhere; adjudication happens as the documented gate-resolution step after TH-b (H2a/H2b RoBMA).
A5: Quantity | B5: Meaning | C5: Decision rule
A6: TOST flag ('value') | B6: 1 = 90% CI inside the band, 0 = not; purely mechanical | C6: No equivalence language attached; gate-resolution step decides wording [DEC-044]
A7: TOST p | B7: max of the two one-sided arm p-values | C7: Compare to alpha = .05 mechanically; adjudication deferred
A8: diff rows | B8: Difference-of-z contrasts are z-only by convention; est_r = NA | C8: [template rule]
A9: Satterthwaite df | B9: Small-sample honest df per coefficient | C9: df >= 4 required for trustworthy CR2 t-inference (Tipton & Pustejovsky 2015 [PK]); H4 admissibility uses df >= 5 [H-Q6]
A10: H4 sup |t| | B10: Largest absolute break statistic over the admissible candidate set | C10: Significance is NOT read from the pointwise p column; the reference distribution is the TH-c cluster time-translation permutation (single-home: TH_c workbook Tab '9_H4_Perm_Sup')
A11: H7 steps 1-9 | B11: Cumulative estimates below the 10-cluster floor | C11: Point-only display; step_001 not_estimable by rule (single cluster; vcovCR guard, ERROR_LOG #12)
A12: H8 descriptive tier | B12: 5-9 cluster windows | C12: Point estimate only, no CI/p by design [DEC-045 S6]
A13: H9 rows | B13: Own pooled (debt) vs. COE companion study-level | C13: Descriptive size comparison only; no formal test [N12]
A14: H10 tests | B14: Right-skew = evidential value; flatness = test against 33% power | C14: Read per Simonsohn et al. (2014); conditional battery, N13
A15: Framing gate | B15: Framing gate [DEC-044]: all TOST flags and permutation p-values in this workbook are MECHANICAL values; no evidence-of-absence or verdict language is used anywhere; adjudication happens as the documented gate-resolution step after TH-b (H2a/H2b RoBMA). | C15: [DEC-044]

Sheet 4_Formula_Reference
A1: TH-a (Block E/H fast frequentist battery) · Formula Reference
A2: Exact calls as implemented (from run notes / run_meta)
A3: Run 2026-07-24 22:46 (canonical) · verifier R/06_verify_outputs.R 17/17 PASS · chat artefact check 2026-07-26 18/18 PASS · output/TH_a_results.csv 177x36
A5: Quantity | B5: R call | C5: Reference / script section
A6: Spine fit | B6: rma.mv(zi, V, mods = ~ 0 + pp_cell, random = ~ 1 | cluster_id/study/esid, method = 'REML', test = 't', sparse = TRUE) with optimizer ladder | C6: R/06 spine block
A7: CR2 inference | B7: clubSandwich::coef_test(fit, vcov = 'CR2', test = 'Satterthwaite'); CIs via conf_int(..., vcov = 'CR2') | C7: R/06
A8: Contrast (diff) | B8: clubSandwich::Wald_test / linear contrast c(-1, +1) on cell means, CR2, Satterthwaite df | C8: R/06 E2/H4/H6
A9: TOST arms | B9: pt((b - band)/se, df) upper arm; pt((b + band)/se, df, lower.tail = FALSE) lower arm; TOST p = max | C9: R/06 E-block [DEC-045 E-pins]
A10: 90% CI (TOST rows) | B10: b ± qt(.95, df) * se | C10: R/06
A11: Back-transform | B11: est_r = tanh(est_z); CI_r = tanh(CI_z) (never on diff rows) | C11: R/06 output writer
A12: H10 p reconstruction | B12: p_i = 2 * pnorm(-abs(zi)/sqrt(vi)); binomial: pbinom on p < .025 half-share; Stouffer on pp-values; flatness vs. 33%-power NCP (sign-corrected, ERROR_LOG #11) | C12: R/06 H10 [N13]
A13: H7/H8 refits | B13: Same spine per cumulative step / rolling window subset; window filter on sample_mid in [a, a+6) | C13: R/06 H7/H8

Sheet 5_Data_Provenance
A1: TH-a (Block E/H fast frequentist battery) · Data Provenance
A2: Estimation set, anchors, counters, environment, disclosures
A3: Run 2026-07-24 22:46 (canonical) · verifier R/06_verify_outputs.R 17/17 PASS · chat artefact check 2026-07-26 18/18 PASS · output/TH_a_results.csv 177x36
A5: Item | B5: Value | C5: Source
A6: Estimation set / domain | B6: 2,713 ES / 115 studies / 114 clusters (E1 pooled, full estimation set); period domain 2,705 / 113 / 112 for all Paris-cell analyses | C6: TH_a_results.csv; [DEC-045]
A7: dat_prep md5 | B7: 6702ef3dc45fe0b693b13f50ebd1576b (identical in TH_a_run_meta and TH_c_run_meta - cross-run anchor) | C7: run_meta both runs
A8: Run stamp / verifier | B8: 2026-07-24 22:46:16 · R/06_verify_outputs.R 17/17 PASS · chat-side artefact check 2026-07-26 18/18 PASS (anchors, arithmetic, inventories, cross-run) | C8: session log §1
A9: Runtime | B9: Not recorded in run_meta; projected 45-70 min per plan A.13 (fast frequentist batch) | C9: plan A.13
A10: Ladder balance | B10: 148 spine fits, ALL converged at rung 1 (nlminb, metafor-certified); zero fallbacks, zero failures [§6(ii)] | C10: TH_a_run_meta certificates
A11: H7 step_001 | B11: not_estimable by rule: single cluster, vcovCR guard fires (ERROR_LOG #12 lesson); all downstream steps estimable | C11: TH_a_results.csv H7
A12: H6 tie inventory | B12: 79 ES / 5 studies / 5 clusters tied at sample_mid = 2015.5 (Ho & Wong 2023; Kordschia 2020; Owolabi et al 2024; Ririmasse et al 2026; Xiang & Gong 2026); post cell 31 -> 26 studies under tie exclusion | C12: TH_design h6_tie_inventory
A13: H4 admissible set | B13: 12 years (2008-2019), Satterthwaite df >= 5 rule, computed once and held fixed for the TH-c permutation | C13: TH_design h4_admissible_years [H-Q20]
A14: H11 inventory | B14: 73 straddling studies; 72 pool across the break; single within-split study = Li et al (2022) | C14: TH_design h11_* rows
A15: Repo basis | B15: 5a99de6 -> e44fce7 (#12) -> fce9d3a (#13) -> dafd95e (#14); family commit lands on dafd95e (main = origin) | C15: session log §1
A16: Environment | B16: R 4.6.1 ucrt · Windows 11 x64 (26200) · locale German_Austria.utf8 / LC_NUMERIC = C · TZ Europe/Vienna · metafor 5.0-1, clubSandwich 0.7.0, Matrix 1.7-5, readr 2.2.0, here 1.0.2 | C16: TH_a_run_meta sessionInfo
A17: Companion caveat | B17: COE between-study variance (~0.00045) is a best-case lower bound vs. COD (~0.029): factor ~65 in variance, ~8 in MDE units - disclose whenever comparing across companions | C17: [project pin; see TH_c H1 S4 mapping]

Sheet 6_E_TOST_Battery
A1: TH-a (Block E/H fast frequentist battery) · Block E - equivalence battery (E1 pooled TOST · E2 Paris-contrast TOST · E3 gate configuration)
A2: Mechanical flags only; CI columns on tost rows carry the 90% CI (TOST convention); mean rows carry 95% CIs.
A3: Run 2026-07-24 22:46 (canonical) · verifier R/06_verify_outputs.R 17/17 PASS · chat artefact check 2026-07-26 18/18 PASS · output/TH_a_results.csv 177x36
A5: Panel row | B5: analysis_id | C5: spec | D5: subset | E5: term | F5: RL row | G5: k_es | H5: k_st | I5: k_cl | J5: est_z | K5: ci_lb_z | L5: ci_ub_z | M5: est_r | N5: ci_lb_r | O5: ci_ub_r | P5: se_z | Q5: t | R5: df | S5: p | T5: value | U5: note (verbatim)
A6: E1 pooled mean (full estimation set) | B6: E1 | C6: tost_pooled | D6: defined | E6: pooled_mean | F6: =SUMPRODUCT((Results_Long!$A$2:$A$178=$B6)*(Results_Long!$B$2:$B$178=$C6)*(Results_Long!$C$2:$C$178=$D6)*(Results_Long!$D$2:$D$178=$E6)*ROW(Results_Long!$A$2:$A$178)) -> 2 | G6: =IF(INDEX(Results_Long!$H:$H,$F6)="","NA",INDEX(Results_Long!$H:$H,$F6)) -> 2713 | H6: =IF(INDEX(Results_Long!$I:$I,$F6)="","NA",INDEX(Results_Long!$I:$I,$F6)) -> 115 | I6: =IF(INDEX(Results_Long!$J:$J,$F6)="","NA",INDEX(Results_Long!$J:$J,$F6)) -> 114 | J6: =IF(INDEX(Results_Long!$K:$K,$F6)="","NA",INDEX(Results_Long!$K:$K,$F6)) -> -0.058646737 | K6: =IF(INDEX(Results_Long!$P:$P,$F6)="","NA",INDEX(Results_Long!$P:$P,$F6)) -> -0.086102595 | L6: =IF(INDEX(Results_Long!$Q:$Q,$F6)="","NA",INDEX(Results_Long!$Q:$Q,$F6)) -> -0.031190879 | M6: =IF(INDEX(Results_Long!$T:$T,$F6)="","NA",INDEX(Results_Long!$T:$T,$F6)) -> -0.058579592 | N6: =IF(INDEX(Results_Long!$U:$U,$F6)="","NA",INDEX(Results_Long!$U:$U,$F6)) -> -0.085890445 | O6: =IF(INDEX(Results_Long!$V:$V,$F6)="","NA",INDEX(Results_Long!$V:$V,$F6)) -> -0.031180768 | P6: =IF(INDEX(Results_Long!$L:$L,$F6)="","NA",INDEX(Results_Long!$L:$L,$F6)) -> 0.01385655 | Q6: =IF(INDEX(Results_Long!$M:$M,$F6)="","NA",INDEX(Results_Long!$M:$M,$F6)) -> -4.2324199 | R6: =IF(INDEX(Results_Long!$N:$N,$F6)="","NA",INDEX(Results_Long!$N:$N,$F6)) -> 111.6718 | S6: =IF(INDEX(Results_Long!$O:$O,$F6)="","NA",INDEX(Results_Long!$O:$O,$F6)) -> 4.7619835e-05 | T6: =IF(INDEX(Results_Long!$AG:$AG,$F6)="","NA",INDEX(Results_Long!$AG:$AG,$F6)) -> NA | U6: =IF(INDEX(Results_Long!$AJ:$AJ,$F6)="","NA",INDEX(Results_Long!$AJ:$AJ,$F6)) -> rma.mv mods=~ 1; random ~1|cluster_id/study/esid; V blocks within cluster_id, rho=0.6; CR2/Satterthwaite on cluster_id [D31.1/A.2]; domain estimation set 2713/115/114 [DEC-042a]; TH-a refit of T1/A1; verifier identity vs committed output/T1_results.csv at 1e-6 [F65]; 95% CI on this row (TOST rows carry 90%)
A7: E1 TOST band |r| = 0.070 (PRIMARY) | B7: E1 | C7: tost_pooled | D7: defined | E7: tost_band_0.070 | F7: =SUMPRODUCT((Results_Long!$A$2:$A$178=$B7)*(Results_Long!$B$2:$B$178=$C7)*(Results_Long!$C$2:$C$178=$D7)*(Results_Long!$D$2:$D$178=$E7)*ROW(Results_Long!$A$2:$A$178)) -> 3 | G7: =IF(INDEX(Results_Long!$H:$H,$F7)="","NA",INDEX(Results_Long!$H:$H,$F7)) -> 2713 | H7: =IF(INDEX(Results_Long!$I:$I,$F7)="","NA",INDEX(Results_Long!$I:$I,$F7)) -> 115 | I7: =IF(INDEX(Results_Long!$J:$J,$F7)="","NA",INDEX(Results_Long!$J:$J,$F7)) -> 114 | J7: =IF(INDEX(Results_Long!$K:$K,$F7)="","NA",INDEX(Results_Long!$K:$K,$F7)) -> -0.058646737 | K7: =IF(INDEX(Results_Long!$P:$P,$F7)="","NA",INDEX(Results_Long!$P:$P,$F7)) -> -0.081629394 | L7: =IF(INDEX(Results_Long!$Q:$Q,$F7)="","NA",INDEX(Results_Long!$Q:$Q,$F7)) -> -0.035664079 | M7: =IF(INDEX(Results_Long!$T:$T,$F7)="","NA",INDEX(Results_Long!$T:$T,$F7)) -> NA | N7: =IF(INDEX(Results_Long!$U:$U,$F7)="","NA",INDEX(Results_Long!$U:$U,$F7)) -> NA | O7: =IF(INDEX(Results_Long!$V:$V,$F7)="","NA",INDEX(Results_Long!$V:$V,$F7)) -> NA | P7: =IF(INDEX(Results_Long!$L:$L,$F7)="","NA",INDEX(Results_Long!$L:$L,$F7)) -> 0.01385655 | Q7: =IF(INDEX(Results_Long!$M:$M,$F7)="","NA",INDEX(Results_Long!$M:$M,$F7)) -> NA | R7: =IF(INDEX(Results_Long!$N:$N,$F7)="","NA",INDEX(Results_Long!$N:$N,$F7)) -> 111.6718 | S7: =IF(INDEX(Results_Long!$O:$O,$F7)="","NA",INDEX(Results_Long!$O:$O,$F7)) -> 0.20482591 | T7: =IF(INDEX(Results_Long!$AG:$AG,$F7)="","NA",INDEX(Results_Long!$AG:$AG,$F7)) -> 0 | U7: =IF(INDEX(Results_Long!$AJ:$AJ,$F7)="","NA",INDEX(Results_Long!$AJ:$AJ,$F7)) -> TOST, two one-sided tests each alpha=.05 <=> 90% CI inside band [DEC-045 E-pins]; PRIMARY level band |r| = 0.070 (F27v2) -> z band atanh = 0.070114671; arm p (lower/upper) = 0.204826 / 7.26341e-16; TOST p = max(arms); CI columns carry the 90% CI (TOST convention); value = 1{90%-CI inside band} (mechanical flag, no verdict language); ex-ante expectation [DEC-044/DEC-045]: this arm is expected to FAIL (T1 CI edge -0.086); E2 adjudicates Tier 1; E1 calibrates the Tier-2 wording only
A8: E1 TOST band |r| = 0.050 (secondary) | B8: E1 | C8: tost_pooled | D8: defined | E8: tost_band_0.050 | F8: =SUMPRODUCT((Results_Long!$A$2:$A$178=$B8)*(Results_Long!$B$2:$B$178=$C8)*(Results_Long!$C$2:$C$178=$D8)*(Results_Long!$D$2:$D$178=$E8)*ROW(Results_Long!$A$2:$A$178)) -> 4 | G8: =IF(INDEX(Results_Long!$H:$H,$F8)="","NA",INDEX(Results_Long!$H:$H,$F8)) -> 2713 | H8: =IF(INDEX(Results_Long!$I:$I,$F8)="","NA",INDEX(Results_Long!$I:$I,$F8)) -> 115 | I8: =IF(INDEX(Results_Long!$J:$J,$F8)="","NA",INDEX(Results_Long!$J:$J,$F8)) -> 114 | J8: =IF(INDEX(Results_Long!$K:$K,$F8)="","NA",INDEX(Results_Long!$K:$K,$F8)) -> -0.058646737 | K8: =IF(INDEX(Results_Long!$P:$P,$F8)="","NA",INDEX(Results_Long!$P:$P,$F8)) -> -0.081629394 | L8: =IF(INDEX(Results_Long!$Q:$Q,$F8)="","NA",INDEX(Results_Long!$Q:$Q,$F8)) -> -0.035664079 | M8: =IF(INDEX(Results_Long!$T:$T,$F8)="","NA",INDEX(Results_Long!$T:$T,$F8)) -> NA | N8: =IF(INDEX(Results_Long!$U:$U,$F8)="","NA",INDEX(Results_Long!$U:$U,$F8)) -> NA | O8: =IF(INDEX(Results_Long!$V:$V,$F8)="","NA",INDEX(Results_Long!$V:$V,$F8)) -> NA | P8: =IF(INDEX(Results_Long!$L:$L,$F8)="","NA",INDEX(Results_Long!$L:$L,$F8)) -> 0.01385655 | Q8: =IF(INDEX(Results_Long!$M:$M,$F8)="","NA",INDEX(Results_Long!$M:$M,$F8)) -> NA | R8: =IF(INDEX(Results_Long!$N:$N,$F8)="","NA",INDEX(Results_Long!$N:$N,$F8)) -> 111.6718 | S8: =IF(INDEX(Results_Long!$O:$O,$F8)="","NA",INDEX(Results_Long!$O:$O,$F8)) -> 0.73206958 | T8: =IF(INDEX(Results_Long!$AG:$AG,$F8)="","NA",INDEX(Results_Long!$AG:$AG,$F8)) -> 0 | U8: =IF(INDEX(Results_Long!$AJ:$AJ,$F8)="","NA",INDEX(Results_Long!$AJ:$AJ,$F8)) -> TOST, two one-sided tests each alpha=.05 <=> 90% CI inside band [DEC-045 E-pins]; SECONDARY level band |r| = 0.05 -> z band atanh = 0.050041729; arm p (lower/upper) = 0.73207 / 1.41843e-12; TOST p = max(arms); CI columns carry the 90% CI (TOST convention); value = 1{90%-CI inside band} (mechanical flag, no verdict language)
A9: E2 cell pre (headline coding) | B9: E2 | C9: tost_paris | D9: defined | E9: cell_pre | F9: =SUMPRODUCT((Results_Long!$A$2:$A$178=$B9)*(Results_Long!$B$2:$B$178=$C9)*(Results_Long!$C$2:$C$178=$D9)*(Results_Long!$D$2:$D$178=$E9)*ROW(Results_Long!$A$2:$A$178)) -> 5 | G9: =IF(INDEX(Results_Long!$H:$H,$F9)="","NA",INDEX(Results_Long!$H:$H,$F9)) -> 1994 | H9: =IF(INDEX(Results_Long!$I:$I,$F9)="","NA",INDEX(Results_Long!$I:$I,$F9)) -> 83 | I9: =IF(INDEX(Results_Long!$J:$J,$F9)="","NA",INDEX(Results_Long!$J:$J,$F9)) -> 82 | J9: =IF(INDEX(Results_Long!$K:$K,$F9)="","NA",INDEX(Results_Long!$K:$K,$F9)) -> -0.061599157 | K9: =IF(INDEX(Results_Long!$P:$P,$F9)="","NA",INDEX(Results_Long!$P:$P,$F9)) -> -0.097603942 | L9: =IF(INDEX(Results_Long!$Q:$Q,$F9)="","NA",INDEX(Results_Long!$Q:$Q,$F9)) -> -0.025594371 | M9: =IF(INDEX(Results_Long!$T:$T,$F9)="","NA",INDEX(Results_Long!$T:$T,$F9)) -> -0.061521363 | N9: =IF(INDEX(Results_Long!$U:$U,$F9)="","NA",INDEX(Results_Long!$U:$U,$F9)) -> -0.097295177 | O9: =IF(INDEX(Results_Long!$V:$V,$F9)="","NA",INDEX(Results_Long!$V:$V,$F9)) -> -0.025588783 | P9: =IF(INDEX(Results_Long!$L:$L,$F9)="","NA",INDEX(Results_Long!$L:$L,$F9)) -> 0.018046114 | Q9: =IF(INDEX(Results_Long!$M:$M,$F9)="","NA",INDEX(Results_Long!$M:$M,$F9)) -> -3.4134304 | R9: =IF(INDEX(Results_Long!$N:$N,$F9)="","NA",INDEX(Results_Long!$N:$N,$F9)) -> 68.597113 | S9: =IF(INDEX(Results_Long!$O:$O,$F9)="","NA",INDEX(Results_Long!$O:$O,$F9)) -> 0.0010804696 | T9: =IF(INDEX(Results_Long!$AG:$AG,$F9)="","NA",INDEX(Results_Long!$AG:$AG,$F9)) -> NA | U9: =IF(INDEX(Results_Long!$AJ:$AJ,$F9)="","NA",INDEX(Results_Long!$AJ:$AJ,$F9)) -> rma.mv mods=~ 0 + pp_cell (cell-means; estimand identical to ~ pp_mid_lag0); random ~1|cluster_id/study/esid; V blocks within cluster_id, rho=0.6; CR2/Satterthwaite on cluster_id [D31.1/A.2]; domain period domain 2705/113/112 [DEC-042b]; cell mean at coding = 0 (pre)
A10: E2 cell post | B10: E2 | C10: tost_paris | D10: defined | E10: cell_post | F10: =SUMPRODUCT((Results_Long!$A$2:$A$178=$B10)*(Results_Long!$B$2:$B$178=$C10)*(Results_Long!$C$2:$C$178=$D10)*(Results_Long!$D$2:$D$178=$E10)*ROW(Results_Long!$A$2:$A$178)) -> 6 | G10: =IF(INDEX(Results_Long!$H:$H,$F10)="","NA",INDEX(Results_Long!$H:$H,$F10)) -> 711 | H10: =IF(INDEX(Results_Long!$I:$I,$F10)="","NA",INDEX(Results_Long!$I:$I,$F10)) -> 31 | I10: =IF(INDEX(Results_Long!$J:$J,$F10)="","NA",INDEX(Results_Long!$J:$J,$F10)) -> 31 | J10: =IF(INDEX(Results_Long!$K:$K,$F10)="","NA",INDEX(Results_Long!$K:$K,$F10)) -> -0.05142325 | K10: =IF(INDEX(Results_Long!$P:$P,$F10)="","NA",INDEX(Results_Long!$P:$P,$F10)) -> -0.072986923 | L10: =IF(INDEX(Results_Long!$Q:$Q,$F10)="","NA",INDEX(Results_Long!$Q:$Q,$F10)) -> -0.029859576 | M10: =IF(INDEX(Results_Long!$T:$T,$F10)="","NA",INDEX(Results_Long!$T:$T,$F10)) -> -0.051377971 | N10: =IF(INDEX(Results_Long!$U:$U,$F10)="","NA",INDEX(Results_Long!$U:$U,$F10)) -> -0.072857596 | O10: =IF(INDEX(Results_Long!$V:$V,$F10)="","NA",INDEX(Results_Long!$V:$V,$F10)) -> -0.029850705 | P10: =IF(INDEX(Results_Long!$L:$L,$F10)="","NA",INDEX(Results_Long!$L:$L,$F10)) -> 0.010329352 | Q10: =IF(INDEX(Results_Long!$M:$M,$F10)="","NA",INDEX(Results_Long!$M:$M,$F10)) -> -4.9783615 | R10: =IF(INDEX(Results_Long!$N:$N,$F10)="","NA",INDEX(Results_Long!$N:$N,$F10)) -> 19.756715 | S10: =IF(INDEX(Results_Long!$O:$O,$F10)="","NA",INDEX(Results_Long!$O:$O,$F10)) -> 7.4752952e-05 | T10: =IF(INDEX(Results_Long!$AG:$AG,$F10)="","NA",INDEX(Results_Long!$AG:$AG,$F10)) -> NA | U10: =IF(INDEX(Results_Long!$AJ:$AJ,$F10)="","NA",INDEX(Results_Long!$AJ:$AJ,$F10)) -> rma.mv mods=~ 0 + pp_cell (cell-means; estimand identical to ~ pp_mid_lag0); random ~1|cluster_id/study/esid; V blocks within cluster_id, rho=0.6; CR2/Satterthwaite on cluster_id [D31.1/A.2]; domain period domain 2705/113/112 [DEC-042b]; cell mean at coding = 1 (post)
A11: E2 diff = post - pre (z-only) | B11: E2 | C11: tost_paris | D11: defined | E11: diff | F11: =SUMPRODUCT((Results_Long!$A$2:$A$178=$B11)*(Results_Long!$B$2:$B$178=$C11)*(Results_Long!$C$2:$C$178=$D11)*(Results_Long!$D$2:$D$178=$E11)*ROW(Results_Long!$A$2:$A$178)) -> 7 | G11: =IF(INDEX(Results_Long!$H:$H,$F11)="","NA",INDEX(Results_Long!$H:$H,$F11)) -> 2705 | H11: =IF(INDEX(Results_Long!$I:$I,$F11)="","NA",INDEX(Results_Long!$I:$I,$F11)) -> 113 | I11: =IF(INDEX(Results_Long!$J:$J,$F11)="","NA",INDEX(Results_Long!$J:$J,$F11)) -> 112 | J11: =IF(INDEX(Results_Long!$K:$K,$F11)="","NA",INDEX(Results_Long!$K:$K,$F11)) -> 0.010175907 | K11: =IF(INDEX(Results_Long!$P:$P,$F11)="","NA",INDEX(Results_Long!$P:$P,$F11)) -> -0.028420631 | L11: =IF(INDEX(Results_Long!$Q:$Q,$F11)="","NA",INDEX(Results_Long!$Q:$Q,$F11)) -> 0.048772445 | M11: =IF(INDEX(Results_Long!$T:$T,$F11)="","NA",INDEX(Results_Long!$T:$T,$F11)) -> NA | N11: =IF(INDEX(Results_Long!$U:$U,$F11)="","NA",INDEX(Results_Long!$U:$U,$F11)) -> NA | O11: =IF(INDEX(Results_Long!$V:$V,$F11)="","NA",INDEX(Results_Long!$V:$V,$F11)) -> NA | P11: =IF(INDEX(Results_Long!$L:$L,$F11)="","NA",INDEX(Results_Long!$L:$L,$F11)) -> 0.018107282 | Q11: =IF(INDEX(Results_Long!$M:$M,$F11)="","NA",INDEX(Results_Long!$M:$M,$F11)) -> 0.56197868 | R11: =IF(INDEX(Results_Long!$N:$N,$F11)="","NA",INDEX(Results_Long!$N:$N,$F11)) -> 14.992066 | S11: =IF(INDEX(Results_Long!$O:$O,$F11)="","NA",INDEX(Results_Long!$O:$O,$F11)) -> 0.58243573 | T11: =IF(INDEX(Results_Long!$AG:$AG,$F11)="","NA",INDEX(Results_Long!$AG:$AG,$F11)) -> NA | U11: =IF(INDEX(Results_Long!$AJ:$AJ,$F11)="","NA",INDEX(Results_Long!$AJ:$AJ,$F11)) -> rma.mv mods=~ 0 + pp_cell (cell-means; estimand identical to ~ pp_mid_lag0); random ~1|cluster_id/study/esid; V blocks within cluster_id, rho=0.6; CR2/Satterthwaite on cluster_id [D31.1/A.2]; domain period domain 2705/113/112 [DEC-042b]; post-minus-pre contrast (-1, +1); cell-means parameterization [DEC-031e/A.11]; difference of Fisher-z means; no tanh transform of differences; TH-a refit of T2/B1 paris_mid; verifier identity vs committed output/T2_results.csv at 1e-6 [F65]
A12: E2 TOST band ±0.050 on diff | B12: E2 | C12: tost_paris | D12: defined | E12: tost_band_0.050 | F12: =SUMPRODUCT((Results_Long!$A$2:$A$178=$B12)*(Results_Long!$B$2:$B$178=$C12)*(Results_Long!$C$2:$C$178=$D12)*(Results_Long!$D$2:$D$178=$E12)*ROW(Results_Long!$A$2:$A$178)) -> 8 | G12: =IF(INDEX(Results_Long!$H:$H,$F12)="","NA",INDEX(Results_Long!$H:$H,$F12)) -> 2705 | H12: =IF(INDEX(Results_Long!$I:$I,$F12)="","NA",INDEX(Results_Long!$I:$I,$F12)) -> 113 | I12: =IF(INDEX(Results_Long!$J:$J,$F12)="","NA",INDEX(Results_Long!$J:$J,$F12)) -> 112 | J12: =IF(INDEX(Results_Long!$K:$K,$F12)="","NA",INDEX(Results_Long!$K:$K,$F12)) -> 0.010175907 | K12: =IF(INDEX(Results_Long!$P:$P,$F12)="","NA",INDEX(Results_Long!$P:$P,$F12)) -> -0.021568174 | L12: =IF(INDEX(Results_Long!$Q:$Q,$F12)="","NA",INDEX(Results_Long!$Q:$Q,$F12)) -> 0.041919988 | M12: =IF(INDEX(Results_Long!$T:$T,$F12)="","NA",INDEX(Results_Long!$T:$T,$F12)) -> NA | N12: =IF(INDEX(Results_Long!$U:$U,$F12)="","NA",INDEX(Results_Long!$U:$U,$F12)) -> NA | O12: =IF(INDEX(Results_Long!$V:$V,$F12)="","NA",INDEX(Results_Long!$V:$V,$F12)) -> NA | P12: =IF(INDEX(Results_Long!$L:$L,$F12)="","NA",INDEX(Results_Long!$L:$L,$F12)) -> 0.018107282 | Q12: =IF(INDEX(Results_Long!$M:$M,$F12)="","NA",INDEX(Results_Long!$M:$M,$F12)) -> NA | R12: =IF(INDEX(Results_Long!$N:$N,$F12)="","NA",INDEX(Results_Long!$N:$N,$F12)) -> 14.992066 | S12: =IF(INDEX(Results_Long!$O:$O,$F12)="","NA",INDEX(Results_Long!$O:$O,$F12)) -> 0.02197985 | T12: =IF(INDEX(Results_Long!$AG:$AG,$F12)="","NA",INDEX(Results_Long!$AG:$AG,$F12)) -> 1 | U12: =IF(INDEX(Results_Long!$AJ:$AJ,$F12)="","NA",INDEX(Results_Long!$AJ:$AJ,$F12)) -> TOST, two one-sided tests each alpha=.05 <=> 90% CI inside band [DEC-045 E-pins]; contrast band |dr| = 0.05 (secondary SESOI = the contrast band [DEC-031 Block E]); applied on the z-difference directly; |dz| read as |dr| (third-order approx, T8/B8 convention); arm p (lower/upper) = 0.00231753 / 0.0219798; TOST p = max(arms); CI columns carry the 90% CI (TOST convention); value = 1{90%-CI inside band} (mechanical flag, no verdict language); E2 adjudicates Tier 1 (the Paris null) [DEC-045 E-pins]; dose transfer NOT triggered (design df 31.9 [DEC-024/A.3])
A13: E3 gate config: E2 requirement | B13: E3 | C13: gate | D13: defined | E13: config_e2_requirement | F13: =SUMPRODUCT((Results_Long!$A$2:$A$178=$B13)*(Results_Long!$B$2:$B$178=$C13)*(Results_Long!$C$2:$C$178=$D13)*(Results_Long!$D$2:$D$178=$E13)*ROW(Results_Long!$A$2:$A$178)) -> 9 | G13: =IF(INDEX(Results_Long!$H:$H,$F13)="","NA",INDEX(Results_Long!$H:$H,$F13)) -> NA | H13: =IF(INDEX(Results_Long!$I:$I,$F13)="","NA",INDEX(Results_Long!$I:$I,$F13)) -> NA | I13: =IF(INDEX(Results_Long!$J:$J,$F13)="","NA",INDEX(Results_Long!$J:$J,$F13)) -> NA | J13: =IF(INDEX(Results_Long!$K:$K,$F13)="","NA",INDEX(Results_Long!$K:$K,$F13)) -> NA | K13: =IF(INDEX(Results_Long!$P:$P,$F13)="","NA",INDEX(Results_Long!$P:$P,$F13)) -> NA | L13: =IF(INDEX(Results_Long!$Q:$Q,$F13)="","NA",INDEX(Results_Long!$Q:$Q,$F13)) -> NA | M13: =IF(INDEX(Results_Long!$T:$T,$F13)="","NA",INDEX(Results_Long!$T:$T,$F13)) -> NA | N13: =IF(INDEX(Results_Long!$U:$U,$F13)="","NA",INDEX(Results_Long!$U:$U,$F13)) -> NA | O13: =IF(INDEX(Results_Long!$V:$V,$F13)="","NA",INDEX(Results_Long!$V:$V,$F13)) -> NA | P13: =IF(INDEX(Results_Long!$L:$L,$F13)="","NA",INDEX(Results_Long!$L:$L,$F13)) -> NA | Q13: =IF(INDEX(Results_Long!$M:$M,$F13)="","NA",INDEX(Results_Long!$M:$M,$F13)) -> NA | R13: =IF(INDEX(Results_Long!$N:$N,$F13)="","NA",INDEX(Results_Long!$N:$N,$F13)) -> NA | S13: =IF(INDEX(Results_Long!$O:$O,$F13)="","NA",INDEX(Results_Long!$O:$O,$F13)) -> NA | T13: =IF(INDEX(Results_Long!$AG:$AG,$F13)="","NA",INDEX(Results_Long!$AG:$AG,$F13)) -> NA | U13: =IF(INDEX(Results_Long!$AJ:$AJ,$F13)="","NA",INDEX(Results_Long!$AJ:$AJ,$F13)) -> Tier-1 evidence-of-absence wording REQUIRES an E2 PASS; E2 FAIL -> no Tier-1 EoA regardless of BF [DEC-045 ladder / H-Q21]
A14: E3 gate config: BF01 ladder | B14: E3 | C14: gate | D14: defined | E14: config_bf_ladder | F14: =SUMPRODUCT((Results_Long!$A$2:$A$178=$B14)*(Results_Long!$B$2:$B$178=$C14)*(Results_Long!$C$2:$C$178=$D14)*(Results_Long!$D$2:$D$178=$E14)*ROW(Results_Long!$A$2:$A$178)) -> 10 | G14: =IF(INDEX(Results_Long!$H:$H,$F14)="","NA",INDEX(Results_Long!$H:$H,$F14)) -> NA | H14: =IF(INDEX(Results_Long!$I:$I,$F14)="","NA",INDEX(Results_Long!$I:$I,$F14)) -> NA | I14: =IF(INDEX(Results_Long!$J:$J,$F14)="","NA",INDEX(Results_Long!$J:$J,$F14)) -> NA | J14: =IF(INDEX(Results_Long!$K:$K,$F14)="","NA",INDEX(Results_Long!$K:$K,$F14)) -> NA | K14: =IF(INDEX(Results_Long!$P:$P,$F14)="","NA",INDEX(Results_Long!$P:$P,$F14)) -> NA | L14: =IF(INDEX(Results_Long!$Q:$Q,$F14)="","NA",INDEX(Results_Long!$Q:$Q,$F14)) -> NA | M14: =IF(INDEX(Results_Long!$T:$T,$F14)="","NA",INDEX(Results_Long!$T:$T,$F14)) -> NA | N14: =IF(INDEX(Results_Long!$U:$U,$F14)="","NA",INDEX(Results_Long!$U:$U,$F14)) -> NA | O14: =IF(INDEX(Results_Long!$V:$V,$F14)="","NA",INDEX(Results_Long!$V:$V,$F14)) -> NA | P14: =IF(INDEX(Results_Long!$L:$L,$F14)="","NA",INDEX(Results_Long!$L:$L,$F14)) -> NA | Q14: =IF(INDEX(Results_Long!$M:$M,$F14)="","NA",INDEX(Results_Long!$M:$M,$F14)) -> NA | R14: =IF(INDEX(Results_Long!$N:$N,$F14)="","NA",INDEX(Results_Long!$N:$N,$F14)) -> NA | S14: =IF(INDEX(Results_Long!$O:$O,$F14)="","NA",INDEX(Results_Long!$O:$O,$F14)) -> NA | T14: =IF(INDEX(Results_Long!$AG:$AG,$F14)="","NA",INDEX(Results_Long!$AG:$AG,$F14)) -> NA | U14: =IF(INDEX(Results_Long!$AJ:$AJ,$F14)="","NA",INDEX(Results_Long!$AJ:$AJ,$F14)) -> with H2b: BF01 >= 3 full EoA; 1 < BF01 < 3 equivalence-based, BF disclosed as directionally supportive, not strong; BF01 <= 1 conflict disclosure, conservative wording; without RoBMA.reg: pre-registered configuration E2 + level BF (H2a) [DEC-045; Jeffreys/Lee-Wagenmakers bands pinned]
A15: E3 gate status | B15: E3 | C15: gate | D15: defined | E15: status | F15: =SUMPRODUCT((Results_Long!$A$2:$A$178=$B15)*(Results_Long!$B$2:$B$178=$C15)*(Results_Long!$C$2:$C$178=$D15)*(Results_Long!$D$2:$D$178=$E15)*ROW(Results_Long!$A$2:$A$178)) -> 11 | G15: =IF(INDEX(Results_Long!$H:$H,$F15)="","NA",INDEX(Results_Long!$H:$H,$F15)) -> NA | H15: =IF(INDEX(Results_Long!$I:$I,$F15)="","NA",INDEX(Results_Long!$I:$I,$F15)) -> NA | I15: =IF(INDEX(Results_Long!$J:$J,$F15)="","NA",INDEX(Results_Long!$J:$J,$F15)) -> NA | J15: =IF(INDEX(Results_Long!$K:$K,$F15)="","NA",INDEX(Results_Long!$K:$K,$F15)) -> NA | K15: =IF(INDEX(Results_Long!$P:$P,$F15)="","NA",INDEX(Results_Long!$P:$P,$F15)) -> NA | L15: =IF(INDEX(Results_Long!$Q:$Q,$F15)="","NA",INDEX(Results_Long!$Q:$Q,$F15)) -> NA | M15: =IF(INDEX(Results_Long!$T:$T,$F15)="","NA",INDEX(Results_Long!$T:$T,$F15)) -> NA | N15: =IF(INDEX(Results_Long!$U:$U,$F15)="","NA",INDEX(Results_Long!$U:$U,$F15)) -> NA | O15: =IF(INDEX(Results_Long!$V:$V,$F15)="","NA",INDEX(Results_Long!$V:$V,$F15)) -> NA | P15: =IF(INDEX(Results_Long!$L:$L,$F15)="","NA",INDEX(Results_Long!$L:$L,$F15)) -> NA | Q15: =IF(INDEX(Results_Long!$M:$M,$F15)="","NA",INDEX(Results_Long!$M:$M,$F15)) -> NA | R15: =IF(INDEX(Results_Long!$N:$N,$F15)="","NA",INDEX(Results_Long!$N:$N,$F15)) -> NA | S15: =IF(INDEX(Results_Long!$O:$O,$F15)="","NA",INDEX(Results_Long!$O:$O,$F15)) -> NA | T15: =IF(INDEX(Results_Long!$AG:$AG,$F15)="","NA",INDEX(Results_Long!$AG:$AG,$F15)) -> NA | U15: =IF(INDEX(Results_Long!$AJ:$AJ,$F15)="","NA",INDEX(Results_Long!$AJ:$AJ,$F15)) -> resolution deferred: documented post-run step after TH-b (N3), never an automatic rewrite [DEC-044/DEC-045]; ex-ante expectation carried on the E1 primary-band row
A17: Interpretation
A18: Mechanical reading only: 'value' = 1{90% CI inside band}; TOST p = max of the two one-sided arms.
A19: Ex-ante expectation pinned result-blind [DEC-044/DEC-045]: the E1 primary-band arm was EXPECTED to fail (T1 CI edge -0.086); E2 adjudicates Tier 1, E1 calibrates the Tier-2 wording only (see row notes, verbatim).
A20: E1/E2 flags feed the documented gate-resolution step together with the TH-b Bayes factors (H2b); no equivalence language is attached in this workbook.
A22: Question | B22: Answer
A23: Why a 90% CI on the TOST rows? | B23: Two one-sided tests at alpha = .05 each are jointly equivalent to the 90% two-sided CI lying inside the band (Lakens 2017; Lakens et al. 2018); the mean rows keep conventional 95% CIs.
A24: Why bands 0.070 and 0.050? | B24: |r| = 0.070 is the pre-registered primary SESOI (F27v2); ±0.05 is the secondary band of the DEC-044 claim ladder; both were pinned before any Block-E estimate existed [DEC-045 E-pins].
A25: Does an E2 pass already license 'evidence of absence'? | B25: No. The language gate combines E2 with the H2b BF01 ladder and resolves only as a documented post-TH-b step [DEC-044]; this workbook reports mechanical flags.
A27: Verdict: Mechanical outcome: E1 equivalence flags = 0 at both bands; E2 secondary-band flag = 1 (see 'value' column); adjudication deferred to the documented gate-resolution step [DEC-044].

Sheet 7_H4_Break_Grid
A1: TH-a (Block E/H fast frequentist battery) · H4 - sup-break grid over admissible candidate years (2008-2019)
A2: Break coefficient per candidate year, cell-means parameterization; observed statistic = sup |t|; reference distribution single-homed in the TH-c workbook (Tab '9_H4_Perm_Sup').
A3: Run 2026-07-24 22:46 (canonical) · verifier R/06_verify_outputs.R 17/17 PASS · chat artefact check 2026-07-26 18/18 PASS · output/TH_a_results.csv 177x36
A5: Panel row | B5: analysis_id | C5: spec | D5: subset | E5: term | F5: RL row | G5: k_es | H5: k_st | I5: k_cl | J5: est_z | K5: ci_lb_z | L5: ci_ub_z | M5: est_r | N5: ci_lb_r | O5: ci_ub_r | P5: se_z | Q5: t | R5: df | S5: p | T5: value | U5: note (verbatim) | V5: year | W5: |t| (helper)
A6: break 2008 | B6: H4 | C6: break_2008 | D6: defined | E6: break | F6: =SUMPRODUCT((Results_Long!$A$2:$A$178=$B6)*(Results_Long!$B$2:$B$178=$C6)*(Results_Long!$C$2:$C$178=$D6)*(Results_Long!$D$2:$D$178=$E6)*ROW(Results_Long!$A$2:$A$178)) -> 12 | G6: =IF(INDEX(Results_Long!$H:$H,$F6)="","NA",INDEX(Results_Long!$H:$H,$F6)) -> 2705 | H6: =IF(INDEX(Results_Long!$I:$I,$F6)="","NA",INDEX(Results_Long!$I:$I,$F6)) -> 113 | I6: =IF(INDEX(Results_Long!$J:$J,$F6)="","NA",INDEX(Results_Long!$J:$J,$F6)) -> 112 | J6: =IF(INDEX(Results_Long!$K:$K,$F6)="","NA",INDEX(Results_Long!$K:$K,$F6)) -> -0.024026676 | K6: =IF(INDEX(Results_Long!$P:$P,$F6)="","NA",INDEX(Results_Long!$P:$P,$F6)) -> -0.061604665 | L6: =IF(INDEX(Results_Long!$Q:$Q,$F6)="","NA",INDEX(Results_Long!$Q:$Q,$F6)) -> 0.013551313 | M6: =IF(INDEX(Results_Long!$T:$T,$F6)="","NA",INDEX(Results_Long!$T:$T,$F6)) -> NA | N6: =IF(INDEX(Results_Long!$U:$U,$F6)="","NA",INDEX(Results_Long!$U:$U,$F6)) -> NA | O6: =IF(INDEX(Results_Long!$V:$V,$F6)="","NA",INDEX(Results_Long!$V:$V,$F6)) -> NA | P6: =IF(INDEX(Results_Long!$L:$L,$F6)="","NA",INDEX(Results_Long!$L:$L,$F6)) -> 0.0176243 | Q6: =IF(INDEX(Results_Long!$M:$M,$F6)="","NA",INDEX(Results_Long!$M:$M,$F6)) -> -1.3632698 | R6: =IF(INDEX(Results_Long!$N:$N,$F6)="","NA",INDEX(Results_Long!$N:$N,$F6)) -> 14.942101 | S6: =IF(INDEX(Results_Long!$O:$O,$F6)="","NA",INDEX(Results_Long!$O:$O,$F6)) -> 0.19298764 | T6: =IF(INDEX(Results_Long!$AG:$AG,$F6)="","NA",INDEX(Results_Long!$AG:$AG,$F6)) -> NA | U6: =IF(INDEX(Results_Long!$AJ:$AJ,$F6)="","NA",INDEX(Results_Long!$AJ:$AJ,$F6)) -> rma.mv mods=~ 0 + pp_cell (break 2008, cell-means); random ~1|cluster_id/study/esid; V blocks within cluster_id, rho=0.6; CR2/Satterthwaite on cluster_id [D31.1/A.2]; domain period domain 2705/113/112; post cell: 2367 ES / 100 studies / 99 clusters; rule: share_2008 >= 0.5, ties to Post [F60/DEC-024]; candidate year of the sup-break grid [DEC-045/H-Q6]; difference of Fisher-z means | V6: 2008 | W6: =IF($Q6="NA","NA",ABS($Q6)) -> 1.3632698
A7: break 2009 | B7: H4 | C7: break_2009 | D7: defined | E7: break | F7: =SUMPRODUCT((Results_Long!$A$2:$A$178=$B7)*(Results_Long!$B$2:$B$178=$C7)*(Results_Long!$C$2:$C$178=$D7)*(Results_Long!$D$2:$D$178=$E7)*ROW(Results_Long!$A$2:$A$178)) -> 13 | G7: =IF(INDEX(Results_Long!$H:$H,$F7)="","NA",INDEX(Results_Long!$H:$H,$F7)) -> 2705 | H7: =IF(INDEX(Results_Long!$I:$I,$F7)="","NA",INDEX(Results_Long!$I:$I,$F7)) -> 113 | I7: =IF(INDEX(Results_Long!$J:$J,$F7)="","NA",INDEX(Results_Long!$J:$J,$F7)) -> 112 | J7: =IF(INDEX(Results_Long!$K:$K,$F7)="","NA",INDEX(Results_Long!$K:$K,$F7)) -> -0.039526755 | K7: =IF(INDEX(Results_Long!$P:$P,$F7)="","NA",INDEX(Results_Long!$P:$P,$F7)) -> -0.084603525 | L7: =IF(INDEX(Results_Long!$Q:$Q,$F7)="","NA",INDEX(Results_Long!$Q:$Q,$F7)) -> 0.0055500143 | M7: =IF(INDEX(Results_Long!$T:$T,$F7)="","NA",INDEX(Results_Long!$T:$T,$F7)) -> NA | N7: =IF(INDEX(Results_Long!$U:$U,$F7)="","NA",INDEX(Results_Long!$U:$U,$F7)) -> NA | O7: =IF(INDEX(Results_Long!$V:$V,$F7)="","NA",INDEX(Results_Long!$V:$V,$F7)) -> NA | P7: =IF(INDEX(Results_Long!$L:$L,$F7)="","NA",INDEX(Results_Long!$L:$L,$F7)) -> 0.018622444 | Q7: =IF(INDEX(Results_Long!$M:$M,$F7)="","NA",INDEX(Results_Long!$M:$M,$F7)) -> -2.1225332 | R7: =IF(INDEX(Results_Long!$N:$N,$F7)="","NA",INDEX(Results_Long!$N:$N,$F7)) -> 6.2816543 | S7: =IF(INDEX(Results_Long!$O:$O,$F7)="","NA",INDEX(Results_Long!$O:$O,$F7)) -> 0.075948862 | T7: =IF(INDEX(Results_Long!$AG:$AG,$F7)="","NA",INDEX(Results_Long!$AG:$AG,$F7)) -> NA | U7: =IF(INDEX(Results_Long!$AJ:$AJ,$F7)="","NA",INDEX(Results_Long!$AJ:$AJ,$F7)) -> rma.mv mods=~ 0 + pp_cell (break 2009, cell-means); random ~1|cluster_id/study/esid; V blocks within cluster_id, rho=0.6; CR2/Satterthwaite on cluster_id [D31.1/A.2]; domain period domain 2705/113/112; post cell: 2345 ES / 99 studies / 98 clusters; rule: share_2009 >= 0.5, ties to Post [F60/DEC-024]; candidate year of the sup-break grid [DEC-045/H-Q6]; difference of Fisher-z means | V7: 2009 | W7: =IF($Q7="NA","NA",ABS($Q7)) -> 2.1225332
A8: break 2010 | B8: H4 | C8: break_2010 | D8: defined | E8: break | F8: =SUMPRODUCT((Results_Long!$A$2:$A$178=$B8)*(Results_Long!$B$2:$B$178=$C8)*(Results_Long!$C$2:$C$178=$D8)*(Results_Long!$D$2:$D$178=$E8)*ROW(Results_Long!$A$2:$A$178)) -> 14 | G8: =IF(INDEX(Results_Long!$H:$H,$F8)="","NA",INDEX(Results_Long!$H:$H,$F8)) -> 2705 | H8: =IF(INDEX(Results_Long!$I:$I,$F8)="","NA",INDEX(Results_Long!$I:$I,$F8)) -> 113 | I8: =IF(INDEX(Results_Long!$J:$J,$F8)="","NA",INDEX(Results_Long!$J:$J,$F8)) -> 112 | J8: =IF(INDEX(Results_Long!$K:$K,$F8)="","NA",INDEX(Results_Long!$K:$K,$F8)) -> -0.036534391 | K8: =IF(INDEX(Results_Long!$P:$P,$F8)="","NA",INDEX(Results_Long!$P:$P,$F8)) -> -0.082461362 | L8: =IF(INDEX(Results_Long!$Q:$Q,$F8)="","NA",INDEX(Results_Long!$Q:$Q,$F8)) -> 0.0093925811 | M8: =IF(INDEX(Results_Long!$T:$T,$F8)="","NA",INDEX(Results_Long!$T:$T,$F8)) -> NA | N8: =IF(INDEX(Results_Long!$U:$U,$F8)="","NA",INDEX(Results_Long!$U:$U,$F8)) -> NA | O8: =IF(INDEX(Results_Long!$V:$V,$F8)="","NA",INDEX(Results_Long!$V:$V,$F8)) -> NA | P8: =IF(INDEX(Results_Long!$L:$L,$F8)="","NA",INDEX(Results_Long!$L:$L,$F8)) -> 0.019295162 | Q8: =IF(INDEX(Results_Long!$M:$M,$F8)="","NA",INDEX(Results_Long!$M:$M,$F8)) -> -1.8934483 | R8: =IF(INDEX(Results_Long!$N:$N,$F8)="","NA",INDEX(Results_Long!$N:$N,$F8)) -> 6.7804765 | S8: =IF(INDEX(Results_Long!$O:$O,$F8)="","NA",INDEX(Results_Long!$O:$O,$F8)) -> 0.10152293 | T8: =IF(INDEX(Results_Long!$AG:$AG,$F8)="","NA",INDEX(Results_Long!$AG:$AG,$F8)) -> NA | U8: =IF(INDEX(Results_Long!$AJ:$AJ,$F8)="","NA",INDEX(Results_Long!$AJ:$AJ,$F8)) -> rma.mv mods=~ 0 + pp_cell (break 2010, cell-means); random ~1|cluster_id/study/esid; V blocks within cluster_id, rho=0.6; CR2/Satterthwaite on cluster_id [D31.1/A.2]; domain period domain 2705/113/112; post cell: 2326 ES / 98 studies / 97 clusters; rule: share_2010 >= 0.5, ties to Post [F60/DEC-024]; candidate year of the sup-break grid [DEC-045/H-Q6]; difference of Fisher-z means | V8: 2010 | W8: =IF($Q8="NA","NA",ABS($Q8)) -> 1.8934483
A9: break 2011 | B9: H4 | C9: break_2011 | D9: defined | E9: break | F9: =SUMPRODUCT((Results_Long!$A$2:$A$178=$B9)*(Results_Long!$B$2:$B$178=$C9)*(Results_Long!$C$2:$C$178=$D9)*(Results_Long!$D$2:$D$178=$E9)*ROW(Results_Long!$A$2:$A$178)) -> 15 | G9: =IF(INDEX(Results_Long!$H:$H,$F9)="","NA",INDEX(Results_Long!$H:$H,$F9)) -> 2705 | H9: =IF(INDEX(Results_Long!$I:$I,$F9)="","NA",INDEX(Results_Long!$I:$I,$F9)) -> 113 | I9: =IF(INDEX(Results_Long!$J:$J,$F9)="","NA",INDEX(Results_Long!$J:$J,$F9)) -> 112 | J9: =IF(INDEX(Results_Long!$K:$K,$F9)="","NA",INDEX(Results_Long!$K:$K,$F9)) -> -0.033330835 | K9: =IF(INDEX(Results_Long!$P:$P,$F9)="","NA",INDEX(Results_Long!$P:$P,$F9)) -> -0.075693221 | L9: =IF(INDEX(Results_Long!$Q:$Q,$F9)="","NA",INDEX(Results_Long!$Q:$Q,$F9)) -> 0.0090315501 | M9: =IF(INDEX(Results_Long!$T:$T,$F9)="","NA",INDEX(Results_Long!$T:$T,$F9)) -> NA | N9: =IF(INDEX(Results_Long!$U:$U,$F9)="","NA",INDEX(Results_Long!$U:$U,$F9)) -> NA | O9: =IF(INDEX(Results_Long!$V:$V,$F9)="","NA",INDEX(Results_Long!$V:$V,$F9)) -> NA | P9: =IF(INDEX(Results_Long!$L:$L,$F9)="","NA",INDEX(Results_Long!$L:$L,$F9)) -> 0.018895156 | Q9: =IF(INDEX(Results_Long!$M:$M,$F9)="","NA",INDEX(Results_Long!$M:$M,$F9)) -> -1.7639884 | R9: =IF(INDEX(Results_Long!$N:$N,$F9)="","NA",INDEX(Results_Long!$N:$N,$F9)) -> 9.5644089 | S9: =IF(INDEX(Results_Long!$O:$O,$F9)="","NA",INDEX(Results_Long!$O:$O,$F9)) -> 0.10957911 | T9: =IF(INDEX(Results_Long!$AG:$AG,$F9)="","NA",INDEX(Results_Long!$AG:$AG,$F9)) -> NA | U9: =IF(INDEX(Results_Long!$AJ:$AJ,$F9)="","NA",INDEX(Results_Long!$AJ:$AJ,$F9)) -> rma.mv mods=~ 0 + pp_cell (break 2011, cell-means); random ~1|cluster_id/study/esid; V blocks within cluster_id, rho=0.6; CR2/Satterthwaite on cluster_id [D31.1/A.2]; domain period domain 2705/113/112; post cell: 2077 ES / 93 studies / 92 clusters; rule: share_2011 >= 0.5, ties to Post [F60/DEC-024]; candidate year of the sup-break grid [DEC-045/H-Q6]; difference of Fisher-z means | V9: 2011 | W9: =IF($Q9="NA","NA",ABS($Q9)) -> 1.7639884
A10: break 2012 | B10: H4 | C10: break_2012 | D10: defined | E10: break | F10: =SUMPRODUCT((Results_Long!$A$2:$A$178=$B10)*(Results_Long!$B$2:$B$178=$C10)*(Results_Long!$C$2:$C$178=$D10)*(Results_Long!$D$2:$D$178=$E10)*ROW(Results_Long!$A$2:$A$178)) -> 16 | G10: =IF(INDEX(Results_Long!$H:$H,$F10)="","NA",INDEX(Results_Long!$H:$H,$F10)) -> 2705 | H10: =IF(INDEX(Results_Long!$I:$I,$F10)="","NA",INDEX(Results_Long!$I:$I,$F10)) -> 113 | I10: =IF(INDEX(Results_Long!$J:$J,$F10)="","NA",INDEX(Results_Long!$J:$J,$F10)) -> 112 | J10: =IF(INDEX(Results_Long!$K:$K,$F10)="","NA",INDEX(Results_Long!$K:$K,$F10)) -> -0.00094643433 | K10: =IF(INDEX(Results_Long!$P:$P,$F10)="","NA",INDEX(Results_Long!$P:$P,$F10)) -> -0.038387516 | L10: =IF(INDEX(Results_Long!$Q:$Q,$F10)="","NA",INDEX(Results_Long!$Q:$Q,$F10)) -> 0.036494647 | M10: =IF(INDEX(Results_Long!$T:$T,$F10)="","NA",INDEX(Results_Long!$T:$T,$F10)) -> NA | N10: =IF(INDEX(Results_Long!$U:$U,$F10)="","NA",INDEX(Results_Long!$U:$U,$F10)) -> NA | O10: =IF(INDEX(Results_Long!$V:$V,$F10)="","NA",INDEX(Results_Long!$V:$V,$F10)) -> NA | P10: =IF(INDEX(Results_Long!$L:$L,$F10)="","NA",INDEX(Results_Long!$L:$L,$F10)) -> 0.017128675 | Q10: =IF(INDEX(Results_Long!$M:$M,$F10)="","NA",INDEX(Results_Long!$M:$M,$F10)) -> -0.055254382 | R10: =IF(INDEX(Results_Long!$N:$N,$F10)="","NA",INDEX(Results_Long!$N:$N,$F10)) -> 11.660405 | S10: =IF(INDEX(Results_Long!$O:$O,$F10)="","NA",INDEX(Results_Long!$O:$O,$F10)) -> 0.95687124 | T10: =IF(INDEX(Results_Long!$AG:$AG,$F10)="","NA",INDEX(Results_Long!$AG:$AG,$F10)) -> NA | U10: =IF(INDEX(Results_Long!$AJ:$AJ,$F10)="","NA",INDEX(Results_Long!$AJ:$AJ,$F10)) -> rma.mv mods=~ 0 + pp_cell (break 2012, cell-means); random ~1|cluster_id/study/esid; V blocks within cluster_id, rho=0.6; CR2/Satterthwaite on cluster_id [D31.1/A.2]; domain period domain 2705/113/112; post cell: 1769 ES / 82 studies / 81 clusters; rule: share_2012 >= 0.5, ties to Post [F60/DEC-024]; candidate year of the sup-break grid [DEC-045/H-Q6]; difference of Fisher-z means | V10: 2012 | W10: =IF($Q10="NA","NA",ABS($Q10)) -> 0.055254382
A11: break 2013 | B11: H4 | C11: break_2013 | D11: defined | E11: break | F11: =SUMPRODUCT((Results_Long!$A$2:$A$178=$B11)*(Results_Long!$B$2:$B$178=$C11)*(Results_Long!$C$2:$C$178=$D11)*(Results_Long!$D$2:$D$178=$E11)*ROW(Results_Long!$A$2:$A$178)) -> 17 | G11: =IF(INDEX(Results_Long!$H:$H,$F11)="","NA",INDEX(Results_Long!$H:$H,$F11)) -> 2705 | H11: =IF(INDEX(Results_Long!$I:$I,$F11)="","NA",INDEX(Results_Long!$I:$I,$F11)) -> 113 | I11: =IF(INDEX(Results_Long!$J:$J,$F11)="","NA",INDEX(Results_Long!$J:$J,$F11)) -> 112 | J11: =IF(INDEX(Results_Long!$K:$K,$F11)="","NA",INDEX(Results_Long!$K:$K,$F11)) -> 0.025954305 | K11: =IF(INDEX(Results_Long!$P:$P,$F11)="","NA",INDEX(Results_Long!$P:$P,$F11)) -> -0.020202989 | L11: =IF(INDEX(Results_Long!$Q:$Q,$F11)="","NA",INDEX(Results_Long!$Q:$Q,$F11)) -> 0.072111598 | M11: =IF(INDEX(Results_Long!$T:$T,$F11)="","NA",INDEX(Results_Long!$T:$T,$F11)) -> NA | N11: =IF(INDEX(Results_Long!$U:$U,$F11)="","NA",INDEX(Results_Long!$U:$U,$F11)) -> NA | O11: =IF(INDEX(Results_Long!$V:$V,$F11)="","NA",INDEX(Results_Long!$V:$V,$F11)) -> NA | P11: =IF(INDEX(Results_Long!$L:$L,$F11)="","NA",INDEX(Results_Long!$L:$L,$F11)) -> 0.021560617 | Q11: =IF(INDEX(Results_Long!$M:$M,$F11)="","NA",INDEX(Results_Long!$M:$M,$F11)) -> 1.203783 | R11: =IF(INDEX(Results_Long!$N:$N,$F11)="","NA",INDEX(Results_Long!$N:$N,$F11)) -> 14.28239 | S11: =IF(INDEX(Results_Long!$O:$O,$F11)="","NA",INDEX(Results_Long!$O:$O,$F11)) -> 0.24824616 | T11: =IF(INDEX(Results_Long!$AG:$AG,$F11)="","NA",INDEX(Results_Long!$AG:$AG,$F11)) -> NA | U11: =IF(INDEX(Results_Long!$AJ:$AJ,$F11)="","NA",INDEX(Results_Long!$AJ:$AJ,$F11)) -> rma.mv mods=~ 0 + pp_cell (break 2013, cell-means); random ~1|cluster_id/study/esid; V blocks within cluster_id, rho=0.6; CR2/Satterthwaite on cluster_id [D31.1/A.2]; domain period domain 2705/113/112; post cell: 1486 ES / 69 studies / 69 clusters; rule: share_2013 >= 0.5, ties to Post [F60/DEC-024]; candidate year of the sup-break grid [DEC-045/H-Q6]; difference of Fisher-z means | V11: 2013 | W11: =IF($Q11="NA","NA",ABS($Q11)) -> 1.203783
A12: break 2014 | B12: H4 | C12: break_2014 | D12: defined | E12: break | F12: =SUMPRODUCT((Results_Long!$A$2:$A$178=$B12)*(Results_Long!$B$2:$B$178=$C12)*(Results_Long!$C$2:$C$178=$D12)*(Results_Long!$D$2:$D$178=$E12)*ROW(Results_Long!$A$2:$A$178)) -> 18 | G12: =IF(INDEX(Results_Long!$H:$H,$F12)="","NA",INDEX(Results_Long!$H:$H,$F12)) -> 2705 | H12: =IF(INDEX(Results_Long!$I:$I,$F12)="","NA",INDEX(Results_Long!$I:$I,$F12)) -> 113 | I12: =IF(INDEX(Results_Long!$J:$J,$F12)="","NA",INDEX(Results_Long!$J:$J,$F12)) -> 112 | J12: =IF(INDEX(Results_Long!$K:$K,$F12)="","NA",INDEX(Results_Long!$K:$K,$F12)) -> 0.023149446 | K12: =IF(INDEX(Results_Long!$P:$P,$F12)="","NA",INDEX(Results_Long!$P:$P,$F12)) -> -0.024037398 | L12: =IF(INDEX(Results_Long!$Q:$Q,$F12)="","NA",INDEX(Results_Long!$Q:$Q,$F12)) -> 0.070336289 | M12: =IF(INDEX(Results_Long!$T:$T,$F12)="","NA",INDEX(Results_Long!$T:$T,$F12)) -> NA | N12: =IF(INDEX(Results_Long!$U:$U,$F12)="","NA",INDEX(Results_Long!$U:$U,$F12)) -> NA | O12: =IF(INDEX(Results_Long!$V:$V,$F12)="","NA",INDEX(Results_Long!$V:$V,$F12)) -> NA | P12: =IF(INDEX(Results_Long!$L:$L,$F12)="","NA",INDEX(Results_Long!$L:$L,$F12)) -> 0.022786093 | Q12: =IF(INDEX(Results_Long!$M:$M,$F12)="","NA",INDEX(Results_Long!$M:$M,$F12)) -> 1.0159463 | R12: =IF(INDEX(Results_Long!$N:$N,$F12)="","NA",INDEX(Results_Long!$N:$N,$F12)) -> 22.565949 | S12: =IF(INDEX(Results_Long!$O:$O,$F12)="","NA",INDEX(Results_Long!$O:$O,$F12)) -> 0.32042466 | T12: =IF(INDEX(Results_Long!$AG:$AG,$F12)="","NA",INDEX(Results_Long!$AG:$AG,$F12)) -> NA | U12: =IF(INDEX(Results_Long!$AJ:$AJ,$F12)="","NA",INDEX(Results_Long!$AJ:$AJ,$F12)) -> rma.mv mods=~ 0 + pp_cell (break 2014, cell-means); random ~1|cluster_id/study/esid; V blocks within cluster_id, rho=0.6; CR2/Satterthwaite on cluster_id [D31.1/A.2]; domain period domain 2705/113/112; post cell: 1269 ES / 55 studies / 55 clusters; rule: share_2014 >= 0.5, ties to Post [F60/DEC-024]; candidate year of the sup-break grid [DEC-045/H-Q6]; difference of Fisher-z means | V12: 2014 | W12: =IF($Q12="NA","NA",ABS($Q12)) -> 1.0159463
A13: break 2015 | B13: H4 | C13: break_2015 | D13: defined | E13: break | F13: =SUMPRODUCT((Results_Long!$A$2:$A$178=$B13)*(Results_Long!$B$2:$B$178=$C13)*(Results_Long!$C$2:$C$178=$D13)*(Results_Long!$D$2:$D$178=$E13)*ROW(Results_Long!$A$2:$A$178)) -> 19 | G13: =IF(INDEX(Results_Long!$H:$H,$F13)="","NA",INDEX(Results_Long!$H:$H,$F13)) -> 2705 | H13: =IF(INDEX(Results_Long!$I:$I,$F13)="","NA",INDEX(Results_Long!$I:$I,$F13)) -> 113 | I13: =IF(INDEX(Results_Long!$J:$J,$F13)="","NA",INDEX(Results_Long!$J:$J,$F13)) -> 112 | J13: =IF(INDEX(Results_Long!$K:$K,$F13)="","NA",INDEX(Results_Long!$K:$K,$F13)) -> 0.0023798646 | K13: =IF(INDEX(Results_Long!$P:$P,$F13)="","NA",INDEX(Results_Long!$P:$P,$F13)) -> -0.040290136 | L13: =IF(INDEX(Results_Long!$Q:$Q,$F13)="","NA",INDEX(Results_Long!$Q:$Q,$F13)) -> 0.045049866 | M13: =IF(INDEX(Results_Long!$T:$T,$F13)="","NA",INDEX(Results_Long!$T:$T,$F13)) -> NA | N13: =IF(INDEX(Results_Long!$U:$U,$F13)="","NA",INDEX(Results_Long!$U:$U,$F13)) -> NA | O13: =IF(INDEX(Results_Long!$V:$V,$F13)="","NA",INDEX(Results_Long!$V:$V,$F13)) -> NA | P13: =IF(INDEX(Results_Long!$L:$L,$F13)="","NA",INDEX(Results_Long!$L:$L,$F13)) -> 0.020323441 | Q13: =IF(INDEX(Results_Long!$M:$M,$F13)="","NA",INDEX(Results_Long!$M:$M,$F13)) -> 0.11709949 | R13: =IF(INDEX(Results_Long!$N:$N,$F13)="","NA",INDEX(Results_Long!$N:$N,$F13)) -> 18.166087 | S13: =IF(INDEX(Results_Long!$O:$O,$F13)="","NA",INDEX(Results_Long!$O:$O,$F13)) -> 0.90806615 | T13: =IF(INDEX(Results_Long!$AG:$AG,$F13)="","NA",INDEX(Results_Long!$AG:$AG,$F13)) -> NA | U13: =IF(INDEX(Results_Long!$AJ:$AJ,$F13)="","NA",INDEX(Results_Long!$AJ:$AJ,$F13)) -> rma.mv mods=~ 0 + pp_cell (break 2015, cell-means); random ~1|cluster_id/study/esid; V blocks within cluster_id, rho=0.6; CR2/Satterthwaite on cluster_id [D31.1/A.2]; domain period domain 2705/113/112; post cell: 784 ES / 38 studies / 38 clusters; rule: share_2015 >= 0.5, ties to Post [F60/DEC-024]; candidate year of the sup-break grid [DEC-045/H-Q6]; difference of Fisher-z means | V13: 2015 | W13: =IF($Q13="NA","NA",ABS($Q13)) -> 0.11709949
A14: break 2016 | B14: H4 | C14: break_2016 | D14: defined | E14: break | F14: =SUMPRODUCT((Results_Long!$A$2:$A$178=$B14)*(Results_Long!$B$2:$B$178=$C14)*(Results_Long!$C$2:$C$178=$D14)*(Results_Long!$D$2:$D$178=$E14)*ROW(Results_Long!$A$2:$A$178)) -> 20 | G14: =IF(INDEX(Results_Long!$H:$H,$F14)="","NA",INDEX(Results_Long!$H:$H,$F14)) -> 2705 | H14: =IF(INDEX(Results_Long!$I:$I,$F14)="","NA",INDEX(Results_Long!$I:$I,$F14)) -> 113 | I14: =IF(INDEX(Results_Long!$J:$J,$F14)="","NA",INDEX(Results_Long!$J:$J,$F14)) -> 112 | J14: =IF(INDEX(Results_Long!$K:$K,$F14)="","NA",INDEX(Results_Long!$K:$K,$F14)) -> 0.010175907 | K14: =IF(INDEX(Results_Long!$P:$P,$F14)="","NA",INDEX(Results_Long!$P:$P,$F14)) -> -0.028420631 | L14: =IF(INDEX(Results_Long!$Q:$Q,$F14)="","NA",INDEX(Results_Long!$Q:$Q,$F14)) -> 0.048772445 | M14: =IF(INDEX(Results_Long!$T:$T,$F14)="","NA",INDEX(Results_Long!$T:$T,$F14)) -> NA | N14: =IF(INDEX(Results_Long!$U:$U,$F14)="","NA",INDEX(Results_Long!$U:$U,$F14)) -> NA | O14: =IF(INDEX(Results_Long!$V:$V,$F14)="","NA",INDEX(Results_Long!$V:$V,$F14)) -> NA | P14: =IF(INDEX(Results_Long!$L:$L,$F14)="","NA",INDEX(Results_Long!$L:$L,$F14)) -> 0.018107282 | Q14: =IF(INDEX(Results_Long!$M:$M,$F14)="","NA",INDEX(Results_Long!$M:$M,$F14)) -> 0.56197868 | R14: =IF(INDEX(Results_Long!$N:$N,$F14)="","NA",INDEX(Results_Long!$N:$N,$F14)) -> 14.992066 | S14: =IF(INDEX(Results_Long!$O:$O,$F14)="","NA",INDEX(Results_Long!$O:$O,$F14)) -> 0.58243573 | T14: =IF(INDEX(Results_Long!$AG:$AG,$F14)="","NA",INDEX(Results_Long!$AG:$AG,$F14)) -> NA | U14: =IF(INDEX(Results_Long!$AJ:$AJ,$F14)="","NA",INDEX(Results_Long!$AJ:$AJ,$F14)) -> rma.mv mods=~ 0 + pp_cell (break 2016, cell-means); random ~1|cluster_id/study/esid; V blocks within cluster_id, rho=0.6; CR2/Satterthwaite on cluster_id [D31.1/A.2]; domain period domain 2705/113/112; post cell: 711 ES / 31 studies / 31 clusters; rule: share_2016 >= 0.5, ties to Post [F60/DEC-024]; candidate year of the sup-break grid [DEC-045/H-Q6]; difference of Fisher-z means | V14: 2016 | W14: =IF($Q14="NA","NA",ABS($Q14)) -> 0.56197868
A15: break 2017 | B15: H4 | C15: break_2017 | D15: defined | E15: break | F15: =SUMPRODUCT((Results_Long!$A$2:$A$178=$B15)*(Results_Long!$B$2:$B$178=$C15)*(Results_Long!$C$2:$C$178=$D15)*(Results_Long!$D$2:$D$178=$E15)*ROW(Results_Long!$A$2:$A$178)) -> 21 | G15: =IF(INDEX(Results_Long!$H:$H,$F15)="","NA",INDEX(Results_Long!$H:$H,$F15)) -> 2705 | H15: =IF(INDEX(Results_Long!$I:$I,$F15)="","NA",INDEX(Results_Long!$I:$I,$F15)) -> 113 | I15: =IF(INDEX(Results_Long!$J:$J,$F15)="","NA",INDEX(Results_Long!$J:$J,$F15)) -> 112 | J15: =IF(INDEX(Results_Long!$K:$K,$F15)="","NA",INDEX(Results_Long!$K:$K,$F15)) -> 0.0080340694 | K15: =IF(INDEX(Results_Long!$P:$P,$F15)="","NA",INDEX(Results_Long!$P:$P,$F15)) -> -0.031649894 | L15: =IF(INDEX(Results_Long!$Q:$Q,$F15)="","NA",INDEX(Results_Long!$Q:$Q,$F15)) -> 0.047718033 | M15: =IF(INDEX(Results_Long!$T:$T,$F15)="","NA",INDEX(Results_Long!$T:$T,$F15)) -> NA | N15: =IF(INDEX(Results_Long!$U:$U,$F15)="","NA",INDEX(Results_Long!$U:$U,$F15)) -> NA | O15: =IF(INDEX(Results_Long!$V:$V,$F15)="","NA",INDEX(Results_Long!$V:$V,$F15)) -> NA | P15: =IF(INDEX(Results_Long!$L:$L,$F15)="","NA",INDEX(Results_Long!$L:$L,$F15)) -> 0.018000133 | Q15: =IF(INDEX(Results_Long!$M:$M,$F15)="","NA",INDEX(Results_Long!$M:$M,$F15)) -> 0.4463339 | R15: =IF(INDEX(Results_Long!$N:$N,$F15)="","NA",INDEX(Results_Long!$N:$N,$F15)) -> 10.852183 | S15: =IF(INDEX(Results_Long!$O:$O,$F15)="","NA",INDEX(Results_Long!$O:$O,$F15)) -> 0.6641308 | T15: =IF(INDEX(Results_Long!$AG:$AG,$F15)="","NA",INDEX(Results_Long!$AG:$AG,$F15)) -> NA | U15: =IF(INDEX(Results_Long!$AJ:$AJ,$F15)="","NA",INDEX(Results_Long!$AJ:$AJ,$F15)) -> rma.mv mods=~ 0 + pp_cell (break 2017, cell-means); random ~1|cluster_id/study/esid; V blocks within cluster_id, rho=0.6; CR2/Satterthwaite on cluster_id [D31.1/A.2]; domain period domain 2705/113/112; post cell: 623 ES / 23 studies / 23 clusters; rule: share_2017 >= 0.5, ties to Post [F60/DEC-024]; candidate year of the sup-break grid [DEC-045/H-Q6]; difference of Fisher-z means | V15: 2017 | W15: =IF($Q15="NA","NA",ABS($Q15)) -> 0.4463339
A16: break 2018 | B16: H4 | C16: break_2018 | D16: defined | E16: break | F16: =SUMPRODUCT((Results_Long!$A$2:$A$178=$B16)*(Results_Long!$B$2:$B$178=$C16)*(Results_Long!$C$2:$C$178=$D16)*(Results_Long!$D$2:$D$178=$E16)*ROW(Results_Long!$A$2:$A$178)) -> 22 | G16: =IF(INDEX(Results_Long!$H:$H,$F16)="","NA",INDEX(Results_Long!$H:$H,$F16)) -> 2705 | H16: =IF(INDEX(Results_Long!$I:$I,$F16)="","NA",INDEX(Results_Long!$I:$I,$F16)) -> 113 | I16: =IF(INDEX(Results_Long!$J:$J,$F16)="","NA",INDEX(Results_Long!$J:$J,$F16)) -> 112 | J16: =IF(INDEX(Results_Long!$K:$K,$F16)="","NA",INDEX(Results_Long!$K:$K,$F16)) -> 0.0031230426 | K16: =IF(INDEX(Results_Long!$P:$P,$F16)="","NA",INDEX(Results_Long!$P:$P,$F16)) -> -0.04345977 | L16: =IF(INDEX(Results_Long!$Q:$Q,$F16)="","NA",INDEX(Results_Long!$Q:$Q,$F16)) -> 0.049705855 | M16: =IF(INDEX(Results_Long!$T:$T,$F16)="","NA",INDEX(Results_Long!$T:$T,$F16)) -> NA | N16: =IF(INDEX(Results_Long!$U:$U,$F16)="","NA",INDEX(Results_Long!$U:$U,$F16)) -> NA | O16: =IF(INDEX(Results_Long!$V:$V,$F16)="","NA",INDEX(Results_Long!$V:$V,$F16)) -> NA | P16: =IF(INDEX(Results_Long!$L:$L,$F16)="","NA",INDEX(Results_Long!$L:$L,$F16)) -> 0.022238266 | Q16: =IF(INDEX(Results_Long!$M:$M,$F16)="","NA",INDEX(Results_Long!$M:$M,$F16)) -> 0.14043553 | R16: =IF(INDEX(Results_Long!$N:$N,$F16)="","NA",INDEX(Results_Long!$N:$N,$F16)) -> 18.776144 | S16: =IF(INDEX(Results_Long!$O:$O,$F16)="","NA",INDEX(Results_Long!$O:$O,$F16)) -> 0.88981151 | T16: =IF(INDEX(Results_Long!$AG:$AG,$F16)="","NA",INDEX(Results_Long!$AG:$AG,$F16)) -> NA | U16: =IF(INDEX(Results_Long!$AJ:$AJ,$F16)="","NA",INDEX(Results_Long!$AJ:$AJ,$F16)) -> rma.mv mods=~ 0 + pp_cell (break 2018, cell-means); random ~1|cluster_id/study/esid; V blocks within cluster_id, rho=0.6; CR2/Satterthwaite on cluster_id [D31.1/A.2]; domain period domain 2705/113/112; post cell: 506 ES / 15 studies / 15 clusters; rule: share_2018 >= 0.5, ties to Post [F60/DEC-024]; candidate year of the sup-break grid [DEC-045/H-Q6]; difference of Fisher-z means | V16: 2018 | W16: =IF($Q16="NA","NA",ABS($Q16)) -> 0.14043553
A17: break 2019 | B17: H4 | C17: break_2019 | D17: defined | E17: break | F17: =SUMPRODUCT((Results_Long!$A$2:$A$178=$B17)*(Results_Long!$B$2:$B$178=$C17)*(Results_Long!$C$2:$C$178=$D17)*(Results_Long!$D$2:$D$178=$E17)*ROW(Results_Long!$A$2:$A$178)) -> 23 | G17: =IF(INDEX(Results_Long!$H:$H,$F17)="","NA",INDEX(Results_Long!$H:$H,$F17)) -> 2705 | H17: =IF(INDEX(Results_Long!$I:$I,$F17)="","NA",INDEX(Results_Long!$I:$I,$F17)) -> 113 | I17: =IF(INDEX(Results_Long!$J:$J,$F17)="","NA",INDEX(Results_Long!$J:$J,$F17)) -> 112 | J17: =IF(INDEX(Results_Long!$K:$K,$F17)="","NA",INDEX(Results_Long!$K:$K,$F17)) -> 0.0042056666 | K17: =IF(INDEX(Results_Long!$P:$P,$F17)="","NA",INDEX(Results_Long!$P:$P,$F17)) -> -0.044236954 | L17: =IF(INDEX(Results_Long!$Q:$Q,$F17)="","NA",INDEX(Results_Long!$Q:$Q,$F17)) -> 0.052648287 | M17: =IF(INDEX(Results_Long!$T:$T,$F17)="","NA",INDEX(Results_Long!$T:$T,$F17)) -> NA | N17: =IF(INDEX(Results_Long!$U:$U,$F17)="","NA",INDEX(Results_Long!$U:$U,$F17)) -> NA | O17: =IF(INDEX(Results_Long!$V:$V,$F17)="","NA",INDEX(Results_Long!$V:$V,$F17)) -> NA | P17: =IF(INDEX(Results_Long!$L:$L,$F17)="","NA",INDEX(Results_Long!$L:$L,$F17)) -> 0.022784454 | Q17: =IF(INDEX(Results_Long!$M:$M,$F17)="","NA",INDEX(Results_Long!$M:$M,$F17)) -> 0.18458491 | R17: =IF(INDEX(Results_Long!$N:$N,$F17)="","NA",INDEX(Results_Long!$N:$N,$F17)) -> 15.443904 | S17: =IF(INDEX(Results_Long!$O:$O,$F17)="","NA",INDEX(Results_Long!$O:$O,$F17)) -> 0.85595667 | T17: =IF(INDEX(Results_Long!$AG:$AG,$F17)="","NA",INDEX(Results_Long!$AG:$AG,$F17)) -> NA | U17: =IF(INDEX(Results_Long!$AJ:$AJ,$F17)="","NA",INDEX(Results_Long!$AJ:$AJ,$F17)) -> rma.mv mods=~ 0 + pp_cell (break 2019, cell-means); random ~1|cluster_id/study/esid; V blocks within cluster_id, rho=0.6; CR2/Satterthwaite on cluster_id [D31.1/A.2]; domain period domain 2705/113/112; post cell: 323 ES / 13 studies / 13 clusters; rule: share_2019 >= 0.5, ties to Post [F60/DEC-024]; candidate year of the sup-break grid [DEC-045/H-Q6]; difference of Fisher-z means | V17: 2019 | W17: =IF($Q17="NA","NA",ABS($Q17)) -> 0.18458491
A18: observed sup |t| (over admissible set) | B18: H4 | C18: sup_break | D18: defined | E18: observed_sup | F18: =SUMPRODUCT((Results_Long!$A$2:$A$178=$B18)*(Results_Long!$B$2:$B$178=$C18)*(Results_Long!$C$2:$C$178=$D18)*(Results_Long!$D$2:$D$178=$E18)*ROW(Results_Long!$A$2:$A$178)) -> 24 | G18: =IF(INDEX(Results_Long!$H:$H,$F18)="","NA",INDEX(Results_Long!$H:$H,$F18)) -> 2705 | H18: =IF(INDEX(Results_Long!$I:$I,$F18)="","NA",INDEX(Results_Long!$I:$I,$F18)) -> 113 | I18: =IF(INDEX(Results_Long!$J:$J,$F18)="","NA",INDEX(Results_Long!$J:$J,$F18)) -> 112 | J18: =IF(INDEX(Results_Long!$K:$K,$F18)="","NA",INDEX(Results_Long!$K:$K,$F18)) -> NA | K18: =IF(INDEX(Results_Long!$P:$P,$F18)="","NA",INDEX(Results_Long!$P:$P,$F18)) -> NA | L18: =IF(INDEX(Results_Long!$Q:$Q,$F18)="","NA",INDEX(Results_Long!$Q:$Q,$F18)) -> NA | M18: =IF(INDEX(Results_Long!$T:$T,$F18)="","NA",INDEX(Results_Long!$T:$T,$F18)) -> NA | N18: =IF(INDEX(Results_Long!$U:$U,$F18)="","NA",INDEX(Results_Long!$U:$U,$F18)) -> NA | O18: =IF(INDEX(Results_Long!$V:$V,$F18)="","NA",INDEX(Results_Long!$V:$V,$F18)) -> NA | P18: =IF(INDEX(Results_Long!$L:$L,$F18)="","NA",INDEX(Results_Long!$L:$L,$F18)) -> NA | Q18: =IF(INDEX(Results_Long!$M:$M,$F18)="","NA",INDEX(Results_Long!$M:$M,$F18)) -> NA | R18: =IF(INDEX(Results_Long!$N:$N,$F18)="","NA",INDEX(Results_Long!$N:$N,$F18)) -> NA | S18: =IF(INDEX(Results_Long!$O:$O,$F18)="","NA",INDEX(Results_Long!$O:$O,$F18)) -> NA | T18: =IF(INDEX(Results_Long!$AG:$AG,$F18)="","NA",INDEX(Results_Long!$AG:$AG,$F18)) -> 2.1225332 | U18: =IF(INDEX(Results_Long!$AJ:$AJ,$F18)="","NA",INDEX(Results_Long!$AJ:$AJ,$F18)) -> sup |t| over the ADMISSIBLE candidate years (df >= 5 on the break coefficient [DEC-024 transfer rule / H-Q6]); attained at 2009; admissible set computed ONCE on the observed design and held fixed for the TH-c permutation [H-Q20]; |t| by year: 2008=1.3633(df 14.9), 2009=2.1225(df 6.3), 2010=1.8934(df 6.8), 2011=1.7640(df 9.6), 2012=0.0553(df 11.7), 2013=1.2038(df 14.3), 2014=1.0159(df 22.6), 2015=0.1171(df 18.2), 2016=0.5620(df 15.0), 2017=0.4463(df 10.9), 2018=0.1404(df 18.8), 2019=0.1846(df 15.4); p_perm from TH-c
U20: max |t| over grid (helper): | W20: =MAX($W$6:$W$17) -> 2.1225332
U21: argmax year: | W21: =INDEX($V$6:$V$17,MATCH($W$20,$W$6:$W$17,0)) -> 2009
U22: identity check vs. observed_sup (must be 0): | W22: =$T$18-$W$20 -> 0
A24: Interpretation
A25: Admissibility = Satterthwaite df >= 5 on the break coefficient [DEC-024 transfer rule / H-Q6]; the set (12 years) was computed once on the observed design and held fixed for the TH-c permutation [H-Q20].
A26: Pointwise p-values in the grid are NOT the inferential object; the sup statistic is referred to the cluster time-translation permutation distribution (TH-c, single-home).
A27: The per-year |t| and df listing is carried verbatim in the observed_sup row note.
A29: Question | B29: Answer
A30: Why is the largest |t| at 2009 not read against its pointwise p? | B30: A supremum over 12 candidate years inflates the pointwise error rate; the pre-registered reference is the joint permutation distribution of the sup statistic [H-Q16/H-Q20], reported in the TH-c workbook.
A31: Several early years have low df - are those t-statistics trustworthy? | B31: Satterthwaite df are reported per year; low-df years (e.g. 2009: df 6.3) remain above the df >= 5 admissibility floor but below comfortable territory - exactly why the permutation, not the t-reference, carries the inference.
A33: Verdict: Mechanical outcome: observed supremum attained at the argmax year shown in the helper block (identity check = 0 vs. Results_Long); reference distribution single-homed in TH_c workbook Tab '9_H4_Perm_Sup'; adjudication deferred to the documented gate-resolution step [DEC-044].

Sheet 8_H6_H7_Transpl_Cumul
A1: TH-a (Block E/H fast frequentist battery) · H6 - Zarea-operationalization transplant · H7 - cumulative meta-analysis (113 steps)
A2: H6: midpoint rule WITH tie exclusion, run on the D31.1 3L-RVE spine (coding transplant, never Zarea's naive ES-level machinery). H7: chronological study-wise refits; CI band from step 10 (>= 10 clusters).
A3: Run 2026-07-24 22:46 (canonical) · verifier R/06_verify_outputs.R 17/17 PASS · chat artefact check 2026-07-26 18/18 PASS · output/TH_a_results.csv 177x36
A5: Panel row | B5: analysis_id | C5: spec | D5: subset | E5: term | F5: RL row | G5: k_es | H5: k_st | I5: k_cl | J5: est_z | K5: ci_lb_z | L5: ci_ub_z | M5: est_r | N5: ci_lb_r | O5: ci_ub_r | P5: se_z | Q5: t | R5: df | S5: p | T5: value | U5: note (verbatim)
A6: H6 cell pre (midpoint rule) | B6: H6 | C6: zarea_transplant | D6: defined | E6: cell_pre | F6: =SUMPRODUCT((Results_Long!$A$2:$A$178=$B6)*(Results_Long!$B$2:$B$178=$C6)*(Results_Long!$C$2:$C$178=$D6)*(Results_Long!$D$2:$D$178=$E6)*ROW(Results_Long!$A$2:$A$178)) -> 25 | G6: =IF(INDEX(Results_Long!$H:$H,$F6)="","NA",INDEX(Results_Long!$H:$H,$F6)) -> 1994 | H6: =IF(INDEX(Results_Long!$I:$I,$F6)="","NA",INDEX(Results_Long!$I:$I,$F6)) -> 83 | I6: =IF(INDEX(Results_Long!$J:$J,$F6)="","NA",INDEX(Results_Long!$J:$J,$F6)) -> 82 | J6: =IF(INDEX(Results_Long!$K:$K,$F6)="","NA",INDEX(Results_Long!$K:$K,$F6)) -> -0.061822115 | K6: =IF(INDEX(Results_Long!$P:$P,$F6)="","NA",INDEX(Results_Long!$P:$P,$F6)) -> -0.098026895 | L6: =IF(INDEX(Results_Long!$Q:$Q,$F6)="","NA",INDEX(Results_Long!$Q:$Q,$F6)) -> -0.025617335 | M6: =IF(INDEX(Results_Long!$T:$T,$F6)="","NA",INDEX(Results_Long!$T:$T,$F6)) -> -0.061743474 | N6: =IF(INDEX(Results_Long!$U:$U,$F6)="","NA",INDEX(Results_Long!$U:$U,$F6)) -> -0.097714108 | O6: =IF(INDEX(Results_Long!$V:$V,$F6)="","NA",INDEX(Results_Long!$V:$V,$F6)) -> -0.025611733 | P6: =IF(INDEX(Results_Long!$L:$L,$F6)="","NA",INDEX(Results_Long!$L:$L,$F6)) -> 0.018152136 | Q6: =IF(INDEX(Results_Long!$M:$M,$F6)="","NA",INDEX(Results_Long!$M:$M,$F6)) -> -3.4057763 | R6: =IF(INDEX(Results_Long!$N:$N,$F6)="","NA",INDEX(Results_Long!$N:$N,$F6)) -> 69.836894 | S6: =IF(INDEX(Results_Long!$O:$O,$F6)="","NA",INDEX(Results_Long!$O:$O,$F6)) -> 0.0010975022 | T6: =IF(INDEX(Results_Long!$AG:$AG,$F6)="","NA",INDEX(Results_Long!$AG:$AG,$F6)) -> NA | U6: =IF(INDEX(Results_Long!$AJ:$AJ,$F6)="","NA",INDEX(Results_Long!$AJ:$AJ,$F6)) -> rma.mv mods=~ 0 + pp_cell (midpoint rule, ties EXCLUDED); random ~1|cluster_id/study/esid; V blocks within cluster_id, rho=0.6; CR2/Satterthwaite on cluster_id [D31.1/A.2]; domain tie-excluded domain 2626/108/107 (79 tie ES / 5 studies / 5 clusters at sample_mid = 2015.5 removed [DEC-045/H-Q8]); cell mean at coding = 0 (pre)
A7: H6 cell post (ties excluded) | B7: H6 | C7: zarea_transplant | D7: defined | E7: cell_post | F7: =SUMPRODUCT((Results_Long!$A$2:$A$178=$B7)*(Results_Long!$B$2:$B$178=$C7)*(Results_Long!$C$2:$C$178=$D7)*(Results_Long!$D$2:$D$178=$E7)*ROW(Results_Long!$A$2:$A$178)) -> 26 | G7: =IF(INDEX(Results_Long!$H:$H,$F7)="","NA",INDEX(Results_Long!$H:$H,$F7)) -> 632 | H7: =IF(INDEX(Results_Long!$I:$I,$F7)="","NA",INDEX(Results_Long!$I:$I,$F7)) -> 26 | I7: =IF(INDEX(Results_Long!$J:$J,$F7)="","NA",INDEX(Results_Long!$J:$J,$F7)) -> 26 | J7: =IF(INDEX(Results_Long!$K:$K,$F7)="","NA",INDEX(Results_Long!$K:$K,$F7)) -> -0.05123144 | K7: =IF(INDEX(Results_Long!$P:$P,$F7)="","NA",INDEX(Results_Long!$P:$P,$F7)) -> -0.075648314 | L7: =IF(INDEX(Results_Long!$Q:$Q,$F7)="","NA",INDEX(Results_Long!$Q:$Q,$F7)) -> -0.026814566 | M7: =IF(INDEX(Results_Long!$T:$T,$F7)="","NA",INDEX(Results_Long!$T:$T,$F7)) -> -0.051186665 | N7: =IF(INDEX(Results_Long!$U:$U,$F7)="","NA",INDEX(Results_Long!$U:$U,$F7)) -> -0.07550434 | O7: =IF(INDEX(Results_Long!$V:$V,$F7)="","NA",INDEX(Results_Long!$V:$V,$F7)) -> -0.026808141 | P7: =IF(INDEX(Results_Long!$L:$L,$F7)="","NA",INDEX(Results_Long!$L:$L,$F7)) -> 0.011479554 | Q7: =IF(INDEX(Results_Long!$M:$M,$F7)="","NA",INDEX(Results_Long!$M:$M,$F7)) -> -4.4628425 | R7: =IF(INDEX(Results_Long!$N:$N,$F7)="","NA",INDEX(Results_Long!$N:$N,$F7)) -> 15.370101 | S7: =IF(INDEX(Results_Long!$O:$O,$F7)="","NA",INDEX(Results_Long!$O:$O,$F7)) -> 0.00043074667 | T7: =IF(INDEX(Results_Long!$AG:$AG,$F7)="","NA",INDEX(Results_Long!$AG:$AG,$F7)) -> NA | U7: =IF(INDEX(Results_Long!$AJ:$AJ,$F7)="","NA",INDEX(Results_Long!$AJ:$AJ,$F7)) -> rma.mv mods=~ 0 + pp_cell (midpoint rule, ties EXCLUDED); random ~1|cluster_id/study/esid; V blocks within cluster_id, rho=0.6; CR2/Satterthwaite on cluster_id [D31.1/A.2]; domain tie-excluded domain 2626/108/107 (79 tie ES / 5 studies / 5 clusters at sample_mid = 2015.5 removed [DEC-045/H-Q8]); cell mean at coding = 1 (post)
A8: H6 diff = post - pre (z-only) | B8: H6 | C8: zarea_transplant | D8: defined | E8: diff | F8: =SUMPRODUCT((Results_Long!$A$2:$A$178=$B8)*(Results_Long!$B$2:$B$178=$C8)*(Results_Long!$C$2:$C$178=$D8)*(Results_Long!$D$2:$D$178=$E8)*ROW(Results_Long!$A$2:$A$178)) -> 27 | G8: =IF(INDEX(Results_Long!$H:$H,$F8)="","NA",INDEX(Results_Long!$H:$H,$F8)) -> 2626 | H8: =IF(INDEX(Results_Long!$I:$I,$F8)="","NA",INDEX(Results_Long!$I:$I,$F8)) -> 108 | I8: =IF(INDEX(Results_Long!$J:$J,$F8)="","NA",INDEX(Results_Long!$J:$J,$F8)) -> 107 | J8: =IF(INDEX(Results_Long!$K:$K,$F8)="","NA",INDEX(Results_Long!$K:$K,$F8)) -> 0.010590675 | K8: =IF(INDEX(Results_Long!$P:$P,$F8)="","NA",INDEX(Results_Long!$P:$P,$F8)) -> -0.02944123 | L8: =IF(INDEX(Results_Long!$Q:$Q,$F8)="","NA",INDEX(Results_Long!$Q:$Q,$F8)) -> 0.050622581 | M8: =IF(INDEX(Results_Long!$T:$T,$F8)="","NA",INDEX(Results_Long!$T:$T,$F8)) -> NA | N8: =IF(INDEX(Results_Long!$U:$U,$F8)="","NA",INDEX(Results_Long!$U:$U,$F8)) -> NA | O8: =IF(INDEX(Results_Long!$V:$V,$F8)="","NA",INDEX(Results_Long!$V:$V,$F8)) -> NA | P8: =IF(INDEX(Results_Long!$L:$L,$F8)="","NA",INDEX(Results_Long!$L:$L,$F8)) -> 0.018297042 | Q8: =IF(INDEX(Results_Long!$M:$M,$F8)="","NA",INDEX(Results_Long!$M:$M,$F8)) -> 0.57881899 | R8: =IF(INDEX(Results_Long!$N:$N,$F8)="","NA",INDEX(Results_Long!$N:$N,$F8)) -> 11.567172 | S8: =IF(INDEX(Results_Long!$O:$O,$F8)="","NA",INDEX(Results_Long!$O:$O,$F8)) -> 0.57380956 | T8: =IF(INDEX(Results_Long!$AG:$AG,$F8)="","NA",INDEX(Results_Long!$AG:$AG,$F8)) -> NA | U8: =IF(INDEX(Results_Long!$AJ:$AJ,$F8)="","NA",INDEX(Results_Long!$AJ:$AJ,$F8)) -> rma.mv mods=~ 0 + pp_cell (midpoint rule, ties EXCLUDED); random ~1|cluster_id/study/esid; V blocks within cluster_id, rho=0.6; CR2/Satterthwaite on cluster_id [D31.1/A.2]; domain tie-excluded domain 2626/108/107 (79 tie ES / 5 studies / 5 clusters at sample_mid = 2015.5 removed [DEC-045/H-Q8]); post-minus-pre contrast (-1, +1); cell-means parameterization [DEC-031e/A.11]; difference of Fisher-z means; no tanh transform of differences; under Zarea's Paris operationalization (midpoint + tie-exclusion), applied within our 3L-RVE framework [DEC-045 wording pin]; post cell 31 -> 26 studies under the tie-exclusion rule
A10: Panel row | B10: analysis_id | C10: spec | D10: subset | E10: term | F10: RL row | G10: df_Satt | H10: value | I10: note (verbatim)
A11: H6 tie inventory (design) | B11: TH_design | C11: design | D11: defined | E11: h6_tie_inventory | F11: =SUMPRODUCT((Results_Long!$A$2:$A$178=$B11)*(Results_Long!$B$2:$B$178=$C11)*(Results_Long!$C$2:$C$178=$D11)*(Results_Long!$D$2:$D$178=$E11)*ROW(Results_Long!$A$2:$A$178)) -> 171 | G11: =IF(INDEX(Results_Long!$N:$N,$F11)="","NA",INDEX(Results_Long!$N:$N,$F11)) -> NA | H11: =IF(INDEX(Results_Long!$AG:$AG,$F11)="","NA",INDEX(Results_Long!$AG:$AG,$F11)) -> 79 | I11: =IF(INDEX(Results_Long!$AJ:$AJ,$F11)="","NA",INDEX(Results_Long!$AJ:$AJ,$F11)) -> tie ES at sample_mid = 2015.5: 79 ES / 5 studies / 5 clusters (Ho & Wong 2023; Kordschia 2020; Owolabi et al 2024; Ririmasse et al 2026; Xiang & Gong 2026); post cell 31 -> 26 studies under the Zarea tie-exclusion rule [DEC-045/H-Q8]
A13: Panel row | B13: analysis_id | C13: spec | D13: subset | E13: term | F13: RL row | G13: k_es | H13: k_st | I13: k_cl | J13: est_z | K13: ci_lb_z | L13: ci_ub_z | M13: est_r | N13: ci_lb_r | O13: ci_ub_r | P13: se_z | Q13: t | R13: df | S13: p | T13: value | U13: note (verbatim)
A14: step_001 (+ Nandy, Lodh (2012)) | B14: H7 | C14: cumulative | D14: Nandy, Lodh (2012) | E14: step_001 | F14: =SUMPRODUCT((Results_Long!$A$2:$A$178=$B14)*(Results_Long!$B$2:$B$178=$C14)*(Results_Long!$C$2:$C$178=$D14)*(Results_Long!$D$2:$D$178=$E14)*ROW(Results_Long!$A$2:$A$178)) -> 28 | G14: =IF(INDEX(Results_Long!$H:$H,$F14)="","NA",INDEX(Results_Long!$H:$H,$F14)) -> 6 | H14: =IF(INDEX(Results_Long!$I:$I,$F14)="","NA",INDEX(Results_Long!$I:$I,$F14)) -> 1 | I14: =IF(INDEX(Results_Long!$J:$J,$F14)="","NA",INDEX(Results_Long!$J:$J,$F14)) -> 1 | J14: =IF(INDEX(Results_Long!$K:$K,$F14)="","NA",INDEX(Results_Long!$K:$K,$F14)) -> NA | K14: =IF(INDEX(Results_Long!$P:$P,$F14)="","NA",INDEX(Results_Long!$P:$P,$F14)) -> NA | L14: =IF(INDEX(Results_Long!$Q:$Q,$F14)="","NA",INDEX(Results_Long!$Q:$Q,$F14)) -> NA | M14: =IF(INDEX(Results_Long!$T:$T,$F14)="","NA",INDEX(Results_Long!$T:$T,$F14)) -> NA | N14: =IF(INDEX(Results_Long!$U:$U,$F14)="","NA",INDEX(Results_Long!$U:$U,$F14)) -> NA | O14: =IF(INDEX(Results_Long!$V:$V,$F14)="","NA",INDEX(Results_Long!$V:$V,$F14)) -> NA | P14: =IF(INDEX(Results_Long!$L:$L,$F14)="","NA",INDEX(Results_Long!$L:$L,$F14)) -> NA | Q14: =IF(INDEX(Results_Long!$M:$M,$F14)="","NA",INDEX(Results_Long!$M:$M,$F14)) -> NA | R14: =IF(INDEX(Results_Long!$N:$N,$F14)="","NA",INDEX(Results_Long!$N:$N,$F14)) -> NA | S14: =IF(INDEX(Results_Long!$O:$O,$F14)="","NA",INDEX(Results_Long!$O:$O,$F14)) -> NA | T14: =IF(INDEX(Results_Long!$AG:$AG,$F14)="","NA",INDEX(Results_Long!$AG:$AG,$F14)) -> NA | U14: =IF(INDEX(Results_Long!$AJ:$AJ,$F14)="","NA",INDEX(Results_Long!$AJ:$AJ,$F14)) -> cumulative 3L refit after adding study 'Nandy, Lodh (2012)' (median sample_mid = 1998.50); ordering: study-wise median sample_mid, ties alphabetical [DEC-045/H-Q17]; not_estimable: Cluster-robust variance estimation will not work when the data only includes a single cluster.; planned key retained (budget 177) [DEC-045; package-review robustness fix 2026-07-22 + runtime fix 2026-07-24]
A15: step_002 (+ Chava (2010)) | B15: H7 | C15: cumulative | D15: Chava (2010) | E15: step_002 | F15: =SUMPRODUCT((Results_Long!$A$2:$A$178=$B15)*(Results_Long!$B$2:$B$178=$C15)*(Results_Long!$C$2:$C$178=$D15)*(Results_Long!$D$2:$D$178=$E15)*ROW(Results_Long!$A$2:$A$178)) -> 29 | G15: =IF(INDEX(Results_Long!$H:$H,$F15)="","NA",INDEX(Results_Long!$H:$H,$F15)) -> 56 | H15: =IF(INDEX(Results_Long!$I:$I,$F15)="","NA",INDEX(Results_Long!$I:$I,$F15)) -> 2 | I15: =IF(INDEX(Results_Long!$J:$J,$F15)="","NA",INDEX(Results_Long!$J:$J,$F15)) -> 2 | J15: =IF(INDEX(Results_Long!$K:$K,$F15)="","NA",INDEX(Results_Long!$K:$K,$F15)) -> -0.0072015185 | K15: =IF(INDEX(Results_Long!$P:$P,$F15)="","NA",INDEX(Results_Long!$P:$P,$F15)) -> -0.19112123 | L15: =IF(INDEX(Results_Long!$Q:$Q,$F15)="","NA",INDEX(Results_Long!$Q:$Q,$F15)) -> 0.1767182 | M15: =IF(INDEX(Results_Long!$T:$T,$F15)="","NA",INDEX(Results_Long!$T:$T,$F15)) -> -0.007201394 | N15: =IF(INDEX(Results_Long!$U:$U,$F15)="","NA",INDEX(Results_Long!$U:$U,$F15)) -> -0.18882769 | O15: =IF(INDEX(Results_Long!$V:$V,$F15)="","NA",INDEX(Results_Long!$V:$V,$F15)) -> 0.17490129 | P15: =IF(INDEX(Results_Long!$L:$L,$F15)="","NA",INDEX(Results_Long!$L:$L,$F15)) -> 0.014662319 | Q15: =IF(INDEX(Results_Long!$M:$M,$F15)="","NA",INDEX(Results_Long!$M:$M,$F15)) -> -0.49115821 | R15: =IF(INDEX(Results_Long!$N:$N,$F15)="","NA",INDEX(Results_Long!$N:$N,$F15)) -> 1.0054808 | S15: =IF(INDEX(Results_Long!$O:$O,$F15)="","NA",INDEX(Results_Long!$O:$O,$F15)) -> 0.7089959 | T15: =IF(INDEX(Results_Long!$AG:$AG,$F15)="","NA",INDEX(Results_Long!$AG:$AG,$F15)) -> NA | U15: =IF(INDEX(Results_Long!$AJ:$AJ,$F15)="","NA",INDEX(Results_Long!$AJ:$AJ,$F15)) -> cumulative 3L refit after adding study 'Chava (2010)' (median sample_mid = 1999.00); ordering: study-wise median sample_mid, ties alphabetical [DEC-045/H-Q17]; display floor: point-only in the figure (clusters = 2 < 10) [DEC-045/H-Q17; presentational only, CI retained here]
A16: step_003 (+ Schneider (2010)) | B16: H7 | C16: cumulative | D16: Schneider (2010) | E16: step_003 | F16: =SUMPRODUCT((Results_Long!$A$2:$A$178=$B16)*(Results_Long!$B$2:$B$178=$C16)*(Results_Long!$C$2:$C$178=$D16)*(Results_Long!$D$2:$D$178=$E16)*ROW(Results_Long!$A$2:$A$178)) -> 30 | G16: =IF(INDEX(Results_Long!$H:$H,$F16)="","NA",INDEX(Results_Long!$H:$H,$F16)) -> 66 | H16: =IF(INDEX(Results_Long!$I:$I,$F16)="","NA",INDEX(Results_Long!$I:$I,$F16)) -> 3 | I16: =IF(INDEX(Results_Long!$J:$J,$F16)="","NA",INDEX(Results_Long!$J:$J,$F16)) -> 3 | J16: =IF(INDEX(Results_Long!$K:$K,$F16)="","NA",INDEX(Results_Long!$K:$K,$F16)) -> -0.018552883 | K16: =IF(INDEX(Results_Long!$P:$P,$F16)="","NA",INDEX(Results_Long!$P:$P,$F16)) -> -0.062860906 | L16: =IF(INDEX(Results_Long!$Q:$Q,$F16)="","NA",INDEX(Results_Long!$Q:$Q,$F16)) -> 0.02575514 | M16: =IF(INDEX(Results_Long!$T:$T,$F16)="","NA",INDEX(Results_Long!$T:$T,$F16)) -> -0.018550755 | N16: =IF(INDEX(Results_Long!$U:$U,$F16)="","NA",INDEX(Results_Long!$U:$U,$F16)) -> -0.062778239 | O16: =IF(INDEX(Results_Long!$V:$V,$F16)="","NA",INDEX(Results_Long!$V:$V,$F16)) -> 0.025749447 | P16: =IF(INDEX(Results_Long!$L:$L,$F16)="","NA",INDEX(Results_Long!$L:$L,$F16)) -> 0.0049557972 | Q16: =IF(INDEX(Results_Long!$M:$M,$F16)="","NA",INDEX(Results_Long!$M:$M,$F16)) -> -3.7436728 | R16: =IF(INDEX(Results_Long!$N:$N,$F16)="","NA",INDEX(Results_Long!$N:$N,$F16)) -> 1.1791658 | S16: =IF(INDEX(Results_Long!$O:$O,$F16)="","NA",INDEX(Results_Long!$O:$O,$F16)) -> 0.13586355 | T16: =IF(INDEX(Results_Long!$AG:$AG,$F16)="","NA",INDEX(Results_Long!$AG:$AG,$F16)) -> NA | U16: =IF(INDEX(Results_Long!$AJ:$AJ,$F16)="","NA",INDEX(Results_Long!$AJ:$AJ,$F16)) -> cumulative 3L refit after adding study 'Schneider (2010)' (median sample_mid = 1999.00); ordering: study-wise median sample_mid, ties alphabetical [DEC-045/H-Q17]; display floor: point-only in the figure (clusters = 3 < 10) [DEC-045/H-Q17; presentational only, CI retained here]
A17: step_004 (+ Chava (2014)) | B17: H7 | C17: cumulative | D17: Chava (2014) | E17: step_004 | F17: =SUMPRODUCT((Results_Long!$A$2:$A$178=$B17)*(Results_Long!$B$2:$B$178=$C17)*(Results_Long!$C$2:$C$178=$D17)*(Results_Long!$D$2:$D$178=$E17)*ROW(Results_Long!$A$2:$A$178)) -> 31 | G17: =IF(INDEX(Results_Long!$H:$H,$F17)="","NA",INDEX(Results_Long!$H:$H,$F17)) -> 88 | H17: =IF(INDEX(Results_Long!$I:$I,$F17)="","NA",INDEX(Results_Long!$I:$I,$F17)) -> 4 | I17: =IF(INDEX(Results_Long!$J:$J,$F17)="","NA",INDEX(Results_Long!$J:$J,$F17)) -> 4 | J17: =IF(INDEX(Results_Long!$K:$K,$F17)="","NA",INDEX(Results_Long!$K:$K,$F17)) -> -0.018932757 | K17: =IF(INDEX(Results_Long!$P:$P,$F17)="","NA",INDEX(Results_Long!$P:$P,$F17)) -> -0.037709965 | L17: =IF(INDEX(Results_Long!$Q:$Q,$F17)="","NA",INDEX(Results_Long!$Q:$Q,$F17)) -> -0.00015554801 | M17: =IF(INDEX(Results_Long!$T:$T,$F17)="","NA",INDEX(Results_Long!$T:$T,$F17)) -> -0.018930495 | N17: =IF(INDEX(Results_Long!$U:$U,$F17)="","NA",INDEX(Results_Long!$U:$U,$F17)) -> -0.0376921 | O17: =IF(INDEX(Results_Long!$V:$V,$F17)="","NA",INDEX(Results_Long!$V:$V,$F17)) -> -0.00015554801 | P17: =IF(INDEX(Results_Long!$L:$L,$F17)="","NA",INDEX(Results_Long!$L:$L,$F17)) -> 0.003105035 | Q17: =IF(INDEX(Results_Long!$M:$M,$F17)="","NA",INDEX(Results_Long!$M:$M,$F17)) -> -6.0974374 | R17: =IF(INDEX(Results_Long!$N:$N,$F17)="","NA",INDEX(Results_Long!$N:$N,$F17)) -> 1.4945754 | S17: =IF(INDEX(Results_Long!$O:$O,$F17)="","NA",INDEX(Results_Long!$O:$O,$F17)) -> 0.049404297 | T17: =IF(INDEX(Results_Long!$AG:$AG,$F17)="","NA",INDEX(Results_Long!$AG:$AG,$F17)) -> NA | U17: =IF(INDEX(Results_Long!$AJ:$AJ,$F17)="","NA",INDEX(Results_Long!$AJ:$AJ,$F17)) -> cumulative 3L refit after adding study 'Chava (2014)' (median sample_mid = 1999.50); ordering: study-wise median sample_mid, ties alphabetical [DEC-045/H-Q17]; display floor: point-only in the figure (clusters = 4 < 10) [DEC-045/H-Q17; presentational only, CI retained here]
A18: step_005 (+ Oikonomou et al (2014)) | B18: H7 | C18: cumulative | D18: Oikonomou et al (2014) | E18: step_005 | F18: =SUMPRODUCT((Results_Long!$A$2:$A$178=$B18)*(Results_Long!$B$2:$B$178=$C18)*(Results_Long!$C$2:$C$178=$D18)*(Results_Long!$D$2:$D$178=$E18)*ROW(Results_Long!$A$2:$A$178)) -> 32 | G18: =IF(INDEX(Results_Long!$H:$H,$F18)="","NA",INDEX(Results_Long!$H:$H,$F18)) -> 93 | H18: =IF(INDEX(Results_Long!$I:$I,$F18)="","NA",INDEX(Results_Long!$I:$I,$F18)) -> 5 | I18: =IF(INDEX(Results_Long!$J:$J,$F18)="","NA",INDEX(Results_Long!$J:$J,$F18)) -> 5 | J18: =IF(INDEX(Results_Long!$K:$K,$F18)="","NA",INDEX(Results_Long!$K:$K,$F18)) -> -0.019043497 | K18: =IF(INDEX(Results_Long!$P:$P,$F18)="","NA",INDEX(Results_Long!$P:$P,$F18)) -> -0.031929988 | L18: =IF(INDEX(Results_Long!$Q:$Q,$F18)="","NA",INDEX(Results_Long!$Q:$Q,$F18)) -> -0.0061570055 | M18: =IF(INDEX(Results_Long!$T:$T,$F18)="","NA",INDEX(Results_Long!$T:$T,$F18)) -> -0.019041195 | N18: =IF(INDEX(Results_Long!$U:$U,$F18)="","NA",INDEX(Results_Long!$U:$U,$F18)) -> -0.031919141 | O18: =IF(INDEX(Results_Long!$V:$V,$F18)="","NA",INDEX(Results_Long!$V:$V,$F18)) -> -0.0061569277 | P18: =IF(INDEX(Results_Long!$L:$L,$F18)="","NA",INDEX(Results_Long!$L:$L,$F18)) -> 0.0028442398 | Q18: =IF(INDEX(Results_Long!$M:$M,$F18)="","NA",INDEX(Results_Long!$M:$M,$F18)) -> -6.6954611 | R18: =IF(INDEX(Results_Long!$N:$N,$F18)="","NA",INDEX(Results_Long!$N:$N,$F18)) -> 1.8985222 | S18: =IF(INDEX(Results_Long!$O:$O,$F18)="","NA",INDEX(Results_Long!$O:$O,$F18)) -> 0.024628536 | T18: =IF(INDEX(Results_Long!$AG:$AG,$F18)="","NA",INDEX(Results_Long!$AG:$AG,$F18)) -> NA | U18: =IF(INDEX(Results_Long!$AJ:$AJ,$F18)="","NA",INDEX(Results_Long!$AJ:$AJ,$F18)) -> cumulative 3L refit after adding study 'Oikonomou et al (2014)' (median sample_mid = 2000.00); ordering: study-wise median sample_mid, ties alphabetical [DEC-045/H-Q17]; display floor: point-only in the figure (clusters = 5 < 10) [DEC-045/H-Q17; presentational only, CI retained here]
A19: step_006 (+ Bauer, Hann (2010)) | B19: H7 | C19: cumulative | D19: Bauer, Hann (2010) | E19: step_006 | F19: =SUMPRODUCT((Results_Long!$A$2:$A$178=$B19)*(Results_Long!$B$2:$B$178=$C19)*(Results_Long!$C$2:$C$178=$D19)*(Results_Long!$D$2:$D$178=$E19)*ROW(Results_Long!$A$2:$A$178)) -> 33 | G19: =IF(INDEX(Results_Long!$H:$H,$F19)="","NA",INDEX(Results_Long!$H:$H,$F19)) -> 259 | H19: =IF(INDEX(Results_Long!$I:$I,$F19)="","NA",INDEX(Results_Long!$I:$I,$F19)) -> 6 | I19: =IF(INDEX(Results_Long!$J:$J,$F19)="","NA",INDEX(Results_Long!$J:$J,$F19)) -> 6 | J19: =IF(INDEX(Results_Long!$K:$K,$F19)="","NA",INDEX(Results_Long!$K:$K,$F19)) -> -0.014547589 | K19: =IF(INDEX(Results_Long!$P:$P,$F19)="","NA",INDEX(Results_Long!$P:$P,$F19)) -> -0.027804105 | L19: =IF(INDEX(Results_Long!$Q:$Q,$F19)="","NA",INDEX(Results_Long!$Q:$Q,$F19)) -> -0.0012910721 | M19: =IF(INDEX(Results_Long!$T:$T,$F19)="","NA",INDEX(Results_Long!$T:$T,$F19)) -> -0.014546562 | N19: =IF(INDEX(Results_Long!$U:$U,$F19)="","NA",INDEX(Results_Long!$U:$U,$F19)) -> -0.027796942 | O19: =IF(INDEX(Results_Long!$V:$V,$F19)="","NA",INDEX(Results_Long!$V:$V,$F19)) -> -0.0012910714 | P19: =IF(INDEX(Results_Long!$L:$L,$F19)="","NA",INDEX(Results_Long!$L:$L,$F19)) -> 0.004138091 | Q19: =IF(INDEX(Results_Long!$M:$M,$F19)="","NA",INDEX(Results_Long!$M:$M,$F19)) -> -3.5155313 | R19: =IF(INDEX(Results_Long!$N:$N,$F19)="","NA",INDEX(Results_Long!$N:$N,$F19)) -> 2.9654357 | S19: =IF(INDEX(Results_Long!$O:$O,$F19)="","NA",INDEX(Results_Long!$O:$O,$F19)) -> 0.039763828 | T19: =IF(INDEX(Results_Long!$AG:$AG,$F19)="","NA",INDEX(Results_Long!$AG:$AG,$F19)) -> NA | U19: =IF(INDEX(Results_Long!$AJ:$AJ,$F19)="","NA",INDEX(Results_Long!$AJ:$AJ,$F19)) -> cumulative 3L refit after adding study 'Bauer, Hann (2010)' (median sample_mid = 2000.50); ordering: study-wise median sample_mid, ties alphabetical [DEC-045/H-Q17]; display floor: point-only in the figure (clusters = 6 < 10) [DEC-045/H-Q17; presentational only, CI retained here]
A20: step_007 (+ Ge, Liu (2015)) | B20: H7 | C20: cumulative | D20: Ge, Liu (2015) | E20: step_007 | F20: =SUMPRODUCT((Results_Long!$A$2:$A$178=$B20)*(Results_Long!$B$2:$B$178=$C20)*(Results_Long!$C$2:$C$178=$D20)*(Results_Long!$D$2:$D$178=$E20)*ROW(Results_Long!$A$2:$A$178)) -> 34 | G20: =IF(INDEX(Results_Long!$H:$H,$F20)="","NA",INDEX(Results_Long!$H:$H,$F20)) -> 263 | H20: =IF(INDEX(Results_Long!$I:$I,$F20)="","NA",INDEX(Results_Long!$I:$I,$F20)) -> 7 | I20: =IF(INDEX(Results_Long!$J:$J,$F20)="","NA",INDEX(Results_Long!$J:$J,$F20)) -> 7 | J20: =IF(INDEX(Results_Long!$K:$K,$F20)="","NA",INDEX(Results_Long!$K:$K,$F20)) -> -0.016967173 | K20: =IF(INDEX(Results_Long!$P:$P,$F20)="","NA",INDEX(Results_Long!$P:$P,$F20)) -> -0.029959356 | L20: =IF(INDEX(Results_Long!$Q:$Q,$F20)="","NA",INDEX(Results_Long!$Q:$Q,$F20)) -> -0.0039749903 | M20: =IF(INDEX(Results_Long!$T:$T,$F20)="","NA",INDEX(Results_Long!$T:$T,$F20)) -> -0.016965545 | N20: =IF(INDEX(Results_Long!$U:$U,$F20)="","NA",INDEX(Results_Long!$U:$U,$F20)) -> -0.029950396 | O20: =IF(INDEX(Results_Long!$V:$V,$F20)="","NA",INDEX(Results_Long!$V:$V,$F20)) -> -0.0039749694 | P20: =IF(INDEX(Results_Long!$L:$L,$F20)="","NA",INDEX(Results_Long!$L:$L,$F20)) -> 0.0044253637 | Q20: =IF(INDEX(Results_Long!$M:$M,$F20)="","NA",INDEX(Results_Long!$M:$M,$F20)) -> -3.8340742 | R20: =IF(INDEX(Results_Long!$N:$N,$F20)="","NA",INDEX(Results_Long!$N:$N,$F20)) -> 3.510897 | S20: =IF(INDEX(Results_Long!$O:$O,$F20)="","NA",INDEX(Results_Long!$O:$O,$F20)) -> 0.023584393 | T20: =IF(INDEX(Results_Long!$AG:$AG,$F20)="","NA",INDEX(Results_Long!$AG:$AG,$F20)) -> NA | U20: =IF(INDEX(Results_Long!$AJ:$AJ,$F20)="","NA",INDEX(Results_Long!$AJ:$AJ,$F20)) -> cumulative 3L refit after adding study 'Ge, Liu (2015)' (median sample_mid = 2000.50); ordering: study-wise median sample_mid, ties alphabetical [DEC-045/H-Q17]; display floor: point-only in the figure (clusters = 7 < 10) [DEC-045/H-Q17; presentational only, CI retained here]
A21: step_008 (+ Jiraporn et al (2014)) | B21: H7 | C21: cumulative | D21: Jiraporn et al (2014) | E21: step_008 | F21: =SUMPRODUCT((Results_Long!$A$2:$A$178=$B21)*(Results_Long!$B$2:$B$178=$C21)*(Results_Long!$C$2:$C$178=$D21)*(Results_Long!$D$2:$D$178=$E21)*ROW(Results_Long!$A$2:$A$178)) -> 35 | G21: =IF(INDEX(Results_Long!$H:$H,$F21)="","NA",INDEX(Results_Long!$H:$H,$F21)) -> 264 | H21: =IF(INDEX(Results_Long!$I:$I,$F21)="","NA",INDEX(Results_Long!$I:$I,$F21)) -> 8 | I21: =IF(INDEX(Results_Long!$J:$J,$F21)="","NA",INDEX(Results_Long!$J:$J,$F21)) -> 8 | J21: =IF(INDEX(Results_Long!$K:$K,$F21)="","NA",INDEX(Results_Long!$K:$K,$F21)) -> -0.017343621 | K21: =IF(INDEX(Results_Long!$P:$P,$F21)="","NA",INDEX(Results_Long!$P:$P,$F21)) -> -0.029993099 | L21: =IF(INDEX(Results_Long!$Q:$Q,$F21)="","NA",INDEX(Results_Long!$Q:$Q,$F21)) -> -0.0046941438 | M21: =IF(INDEX(Results_Long!$T:$T,$F21)="","NA",INDEX(Results_Long!$T:$T,$F21)) -> -0.017341883 | N21: =IF(INDEX(Results_Long!$U:$U,$F21)="","NA",INDEX(Results_Long!$U:$U,$F21)) -> -0.029984109 | O21: =IF(INDEX(Results_Long!$V:$V,$F21)="","NA",INDEX(Results_Long!$V:$V,$F21)) -> -0.0046941093 | P21: =IF(INDEX(Results_Long!$L:$L,$F21)="","NA",INDEX(Results_Long!$L:$L,$F21)) -> 0.0043890541 | Q21: =IF(INDEX(Results_Long!$M:$M,$F21)="","NA",INDEX(Results_Long!$M:$M,$F21)) -> -3.9515625 | R21: =IF(INDEX(Results_Long!$N:$N,$F21)="","NA",INDEX(Results_Long!$N:$N,$F21)) -> 3.6574978 | S21: =IF(INDEX(Results_Long!$O:$O,$F21)="","NA",INDEX(Results_Long!$O:$O,$F21)) -> 0.019951466 | T21: =IF(INDEX(Results_Long!$AG:$AG,$F21)="","NA",INDEX(Results_Long!$AG:$AG,$F21)) -> NA | U21: =IF(INDEX(Results_Long!$AJ:$AJ,$F21)="","NA",INDEX(Results_Long!$AJ:$AJ,$F21)) -> cumulative 3L refit after adding study 'Jiraporn et al (2014)' (median sample_mid = 2001.00); ordering: study-wise median sample_mid, ties alphabetical [DEC-045/H-Q17]; display floor: point-only in the figure (clusters = 8 < 10) [DEC-045/H-Q17; presentational only, CI retained here]
A22: step_009 (+ Chen et al (2020)) | B22: H7 | C22: cumulative | D22: Chen et al (2020) | E22: step_009 | F22: =SUMPRODUCT((Results_Long!$A$2:$A$178=$B22)*(Results_Long!$B$2:$B$178=$C22)*(Results_Long!$C$2:$C$178=$D22)*(Results_Long!$D$2:$D$178=$E22)*ROW(Results_Long!$A$2:$A$178)) -> 36 | G22: =IF(INDEX(Results_Long!$H:$H,$F22)="","NA",INDEX(Results_Long!$H:$H,$F22)) -> 312 | H22: =IF(INDEX(Results_Long!$I:$I,$F22)="","NA",INDEX(Results_Long!$I:$I,$F22)) -> 9 | I22: =IF(INDEX(Results_Long!$J:$J,$F22)="","NA",INDEX(Results_Long!$J:$J,$F22)) -> 9 | J22: =IF(INDEX(Results_Long!$K:$K,$F22)="","NA",INDEX(Results_Long!$K:$K,$F22)) -> -0.01487142 | K22: =IF(INDEX(Results_Long!$P:$P,$F22)="","NA",INDEX(Results_Long!$P:$P,$F22)) -> -0.024835838 | L22: =IF(INDEX(Results_Long!$Q:$Q,$F22)="","NA",INDEX(Results_Long!$Q:$Q,$F22)) -> -0.0049070021 | M22: =IF(INDEX(Results_Long!$T:$T,$F22)="","NA",INDEX(Results_Long!$T:$T,$F22)) -> -0.014870324 | N22: =IF(INDEX(Results_Long!$U:$U,$F22)="","NA",INDEX(Results_Long!$U:$U,$F22)) -> -0.024830733 | O22: =IF(INDEX(Results_Long!$V:$V,$F22)="","NA",INDEX(Results_Long!$V:$V,$F22)) -> -0.0049069627 | P22: =IF(INDEX(Results_Long!$L:$L,$F22)="","NA",INDEX(Results_Long!$L:$L,$F22)) -> 0.0036812778 | Q22: =IF(INDEX(Results_Long!$M:$M,$F22)="","NA",INDEX(Results_Long!$M:$M,$F22)) -> -4.039744 | R22: =IF(INDEX(Results_Long!$N:$N,$F22)="","NA",INDEX(Results_Long!$N:$N,$F22)) -> 4.277715 | S22: =IF(INDEX(Results_Long!$O:$O,$F22)="","NA",INDEX(Results_Long!$O:$O,$F22)) -> 0.013640022 | T22: =IF(INDEX(Results_Long!$AG:$AG,$F22)="","NA",INDEX(Results_Long!$AG:$AG,$F22)) -> NA | U22: =IF(INDEX(Results_Long!$AJ:$AJ,$F22)="","NA",INDEX(Results_Long!$AJ:$AJ,$F22)) -> cumulative 3L refit after adding study 'Chen et al (2020)' (median sample_mid = 2001.50); ordering: study-wise median sample_mid, ties alphabetical [DEC-045/H-Q17]; display floor: point-only in the figure (clusters = 9 < 10) [DEC-045/H-Q17; presentational only, CI retained here]
A23: step_010 (+ Chen, Gao (2011)) | B23: H7 | C23: cumulative | D23: Chen, Gao (2011) | E23: step_010 | F23: =SUMPRODUCT((Results_Long!$A$2:$A$178=$B23)*(Results_Long!$B$2:$B$178=$C23)*(Results_Long!$C$2:$C$178=$D23)*(Results_Long!$D$2:$D$178=$E23)*ROW(Results_Long!$A$2:$A$178)) -> 37 | G23: =IF(INDEX(Results_Long!$H:$H,$F23)="","NA",INDEX(Results_Long!$H:$H,$F23)) -> 316 | H23: =IF(INDEX(Results_Long!$I:$I,$F23)="","NA",INDEX(Results_Long!$I:$I,$F23)) -> 10 | I23: =IF(INDEX(Results_Long!$J:$J,$F23)="","NA",INDEX(Results_Long!$J:$J,$F23)) -> 10 | J23: =IF(INDEX(Results_Long!$K:$K,$F23)="","NA",INDEX(Results_Long!$K:$K,$F23)) -> -0.015354927 | K23: =IF(INDEX(Results_Long!$P:$P,$F23)="","NA",INDEX(Results_Long!$P:$P,$F23)) -> -0.025124475 | L23: =IF(INDEX(Results_Long!$Q:$Q,$F23)="","NA",INDEX(Results_Long!$Q:$Q,$F23)) -> -0.0055853785 | M23: =IF(INDEX(Results_Long!$T:$T,$F23)="","NA",INDEX(Results_Long!$T:$T,$F23)) -> -0.01535372 | N23: =IF(INDEX(Results_Long!$U:$U,$F23)="","NA",INDEX(Results_Long!$U:$U,$F23)) -> -0.025119189 | O23: =IF(INDEX(Results_Long!$V:$V,$F23)="","NA",INDEX(Results_Long!$V:$V,$F23)) -> -0.0055853205 | P23: =IF(INDEX(Results_Long!$L:$L,$F23)="","NA",INDEX(Results_Long!$L:$L,$F23)) -> 0.0036193689 | Q23: =IF(INDEX(Results_Long!$M:$M,$F23)="","NA",INDEX(Results_Long!$M:$M,$F23)) -> -4.242432 | R23: =IF(INDEX(Results_Long!$N:$N,$F23)="","NA",INDEX(Results_Long!$N:$N,$F23)) -> 4.3108577 | S23: =IF(INDEX(Results_Long!$O:$O,$F23)="","NA",INDEX(Results_Long!$O:$O,$F23)) -> 0.011272897 | T23: =IF(INDEX(Results_Long!$AG:$AG,$F23)="","NA",INDEX(Results_Long!$AG:$AG,$F23)) -> NA | U23: =IF(INDEX(Results_Long!$AJ:$AJ,$F23)="","NA",INDEX(Results_Long!$AJ:$AJ,$F23)) -> cumulative 3L refit after adding study 'Chen, Gao (2011)' (median sample_mid = 2005.00); ordering: study-wise median sample_mid, ties alphabetical [DEC-045/H-Q17]; full display (CI band)
A24: step_011 (+ Chodnicka-Jaworska (2022)) | B24: H7 | C24: cumulative | D24: Chodnicka-Jaworska (2022) | E24: step_011 | F24: =SUMPRODUCT((Results_Long!$A$2:$A$178=$B24)*(Results_Long!$B$2:$B$178=$C24)*(Results_Long!$C$2:$C$178=$D24)*(Results_Long!$D$2:$D$178=$E24)*ROW(Results_Long!$A$2:$A$178)) -> 38 | G24: =IF(INDEX(Results_Long!$H:$H,$F24)="","NA",INDEX(Results_Long!$H:$H,$F24)) -> 326 | H24: =IF(INDEX(Results_Long!$I:$I,$F24)="","NA",INDEX(Results_Long!$I:$I,$F24)) -> 11 | I24: =IF(INDEX(Results_Long!$J:$J,$F24)="","NA",INDEX(Results_Long!$J:$J,$F24)) -> 11 | J24: =IF(INDEX(Results_Long!$K:$K,$F24)="","NA",INDEX(Results_Long!$K:$K,$F24)) -> -0.016859844 | K24: =IF(INDEX(Results_Long!$P:$P,$F24)="","NA",INDEX(Results_Long!$P:$P,$F24)) -> -0.024998329 | L24: =IF(INDEX(Results_Long!$Q:$Q,$F24)="","NA",INDEX(Results_Long!$Q:$Q,$F24)) -> -0.0087213592 | M24: =IF(INDEX(Results_Long!$T:$T,$F24)="","NA",INDEX(Results_Long!$T:$T,$F24)) -> -0.016858247 | N24: =IF(INDEX(Results_Long!$U:$U,$F24)="","NA",INDEX(Results_Long!$U:$U,$F24)) -> -0.024993123 | O24: =IF(INDEX(Results_Long!$V:$V,$F24)="","NA",INDEX(Results_Long!$V:$V,$F24)) -> -0.0087211381 | P24: =IF(INDEX(Results_Long!$L:$L,$F24)="","NA",INDEX(Results_Long!$L:$L,$F24)) -> 0.003061245 | Q24: =IF(INDEX(Results_Long!$M:$M,$F24)="","NA",INDEX(Results_Long!$M:$M,$F24)) -> -5.5075122 | R24: =IF(INDEX(Results_Long!$N:$N,$F24)="","NA",INDEX(Results_Long!$N:$N,$F24)) -> 4.501777 | S24: =IF(INDEX(Results_Long!$O:$O,$F24)="","NA",INDEX(Results_Long!$O:$O,$F24)) -> 0.0037294 | T24: =IF(INDEX(Results_Long!$AG:$AG,$F24)="","NA",INDEX(Results_Long!$AG:$AG,$F24)) -> NA | U24: =IF(INDEX(Results_Long!$AJ:$AJ,$F24)="","NA",INDEX(Results_Long!$AJ:$AJ,$F24)) -> cumulative 3L refit after adding study 'Chodnicka-Jaworska (2022)' (median sample_mid = 2005.50); ordering: study-wise median sample_mid, ties alphabetical [DEC-045/H-Q17]; full display (CI band)
A25: step_012 (+ Erragragui (2018)) | B25: H7 | C25: cumulative | D25: Erragragui (2018) | E25: step_012 | F25: =SUMPRODUCT((Results_Long!$A$2:$A$178=$B25)*(Results_Long!$B$2:$B$178=$C25)*(Results_Long!$C$2:$C$178=$D25)*(Results_Long!$D$2:$D$178=$E25)*ROW(Results_Long!$A$2:$A$178)) -> 39 | G25: =IF(INDEX(Results_Long!$H:$H,$F25)="","NA",INDEX(Results_Long!$H:$H,$F25)) -> 330 | H25: =IF(INDEX(Results_Long!$I:$I,$F25)="","NA",INDEX(Results_Long!$I:$I,$F25)) -> 12 | I25: =IF(INDEX(Results_Long!$J:$J,$F25)="","NA",INDEX(Results_Long!$J:$J,$F25)) -> 12 | J25: =IF(INDEX(Results_Long!$K:$K,$F25)="","NA",INDEX(Results_Long!$K:$K,$F25)) -> -0.018018411 | K25: =IF(INDEX(Results_Long!$P:$P,$F25)="","NA",INDEX(Results_Long!$P:$P,$F25)) -> -0.026823171 | L25: =IF(INDEX(Results_Long!$Q:$Q,$F25)="","NA",INDEX(Results_Long!$Q:$Q,$F25)) -> -0.0092136498 | M25: =IF(INDEX(Results_Long!$T:$T,$F25)="","NA",INDEX(Results_Long!$T:$T,$F25)) -> -0.018016461 | N25: =IF(INDEX(Results_Long!$U:$U,$F25)="","NA",INDEX(Results_Long!$U:$U,$F25)) -> -0.02681674 | O25: =IF(INDEX(Results_Long!$V:$V,$F25)="","NA",INDEX(Results_Long!$V:$V,$F25)) -> -0.0092133891 | P25: =IF(INDEX(Results_Long!$L:$L,$F25)="","NA",INDEX(Results_Long!$L:$L,$F25)) -> 0.0033811337 | Q25: =IF(INDEX(Results_Long!$M:$M,$F25)="","NA",INDEX(Results_Long!$M:$M,$F25)) -> -5.3291033 | R25: =IF(INDEX(Results_Long!$N:$N,$F25)="","NA",INDEX(Results_Long!$N:$N,$F25)) -> 4.7944537 | S25: =IF(INDEX(Results_Long!$O:$O,$F25)="","NA",INDEX(Results_Long!$O:$O,$F25)) -> 0.0035333549 | T25: =IF(INDEX(Results_Long!$AG:$AG,$F25)="","NA",INDEX(Results_Long!$AG:$AG,$F25)) -> NA | U25: =IF(INDEX(Results_Long!$AJ:$AJ,$F25)="","NA",INDEX(Results_Long!$AJ:$AJ,$F25)) -> cumulative 3L refit after adding study 'Erragragui (2018)' (median sample_mid = 2005.50); ordering: study-wise median sample_mid, ties alphabetical [DEC-045/H-Q17]; full display (CI band)
... A126: step_113 (+ Cicchini et al (2026)) | B126: H7 | C126: cumulative | D126: Cicchini et al (2026) | E126: step_113 | F126: =SUMPRODUCT((Results_Long!$A$2:$A$178=$B126)*(Results_Long!$B$2:$B$178=$C126)*(Results_Long!$C$2:$C$178=$D126)*(Results_Long!$D$2:$D$178=$E126)*ROW(Results_Long!$A$2:$A$178)) -> 140 | G126: =IF(INDEX(Results_Long!$H:$H,$F126)="","NA",INDEX(Results_Long!$H:$H,$F126)) -> 2705 | H126: =IF(INDEX(Results_Long!$I:$I,$F126)="","NA",INDEX(Results_Long!$I:$I,$F126)) -> 113 | I126: =IF(INDEX(Results_Long!$J:$J,$F126)="","NA",INDEX(Results_Long!$J:$J,$F126)) -> 112 | J126: =IF(INDEX(Results_Long!$K:$K,$F126)="","NA",INDEX(Results_Long!$K:$K,$F126)) -> -0.05877906 | K126: =IF(INDEX(Results_Long!$P:$P,$F126)="","NA",INDEX(Results_Long!$P:$P,$F126)) -> -0.086741752 | L126: =IF(INDEX(Results_Long!$Q:$Q,$F126)="","NA",INDEX(Results_Long!$Q:$Q,$F126)) -> -0.030816367 | M126: =IF(INDEX(Results_Long!$T:$T,$F126)="","NA",INDEX(Results_Long!$T:$T,$F126)) -> -0.05871146 | N126: =IF(INDEX(Results_Long!$U:$U,$F126)="","NA",INDEX(Results_Long!$U:$U,$F126)) -> -0.086524853 | O126: =IF(INDEX(Results_Long!$V:$V,$F126)="","NA",INDEX(Results_Long!$V:$V,$F126)) -> -0.030806616 | P126: =IF(INDEX(Results_Long!$L:$L,$F126)="","NA",INDEX(Results_Long!$L:$L,$F126)) -> 0.014109739 | Q126: =IF(INDEX(Results_Long!$M:$M,$F126)="","NA",INDEX(Results_Long!$M:$M,$F126)) -> -4.1658504 | R126: =IF(INDEX(Results_Long!$N:$N,$F126)="","NA",INDEX(Results_Long!$N:$N,$F126)) -> 109.82248 | S126: =IF(INDEX(Results_Long!$O:$O,$F126)="","NA",INDEX(Results_Long!$O:$O,$F126)) -> 6.2015541e-05 | T126: =IF(INDEX(Results_Long!$AG:$AG,$F126)="","NA",INDEX(Results_Long!$AG:$AG,$F126)) -> NA | U126: =IF(INDEX(Results_Long!$AJ:$AJ,$F126)="","NA",INDEX(Results_Long!$AJ:$AJ,$F126)) -> cumulative 3L refit after adding study 'Cicchini et al (2026)' (median sample_mid = 2022.50); ordering: study-wise median sample_mid, ties alphabetical [DEC-045/H-Q17]; full display (CI band)
A128: Panel row | B128: analysis_id | C128: spec | D128: subset | E128: term | F128: RL row | G128: df_Satt | H128: value | I128: note (verbatim)
A129: H7 floor step (design) | B129: TH_design | C129: design | D129: defined | E129: h7_floor_step | F129: =SUMPRODUCT((Results_Long!$A$2:$A$178=$B129)*(Results_Long!$B$2:$B$178=$C129)*(Results_Long!$C$2:$C$178=$D129)*(Results_Long!$D$2:$D$178=$E129)*ROW(Results_Long!$A$2:$A$178)) -> 173 | G129: =IF(INDEX(Results_Long!$N:$N,$F129)="","NA",INDEX(Results_Long!$N:$N,$F129)) -> NA | H129: =IF(INDEX(Results_Long!$AG:$AG,$F129)="","NA",INDEX(Results_Long!$AG:$AG,$F129)) -> 10 | I129: =IF(INDEX(Results_Long!$AJ:$AJ,$F129)="","NA",INDEX(Results_Long!$AJ:$AJ,$F129)) -> first cumulative step with >= 10 clusters (CI band from here; steps 1-9 point-only in the figure) [DEC-045/H-Q17]; floor study = 'Chen, Gao (2011)'
A130: H7 ordering rule (design) | B130: TH_design | C130: design | D130: defined | E130: h7_order_head | F130: =SUMPRODUCT((Results_Long!$A$2:$A$178=$B130)*(Results_Long!$B$2:$B$178=$C130)*(Results_Long!$C$2:$C$178=$D130)*(Results_Long!$D$2:$D$178=$E130)*ROW(Results_Long!$A$2:$A$178)) -> 174 | G130: =IF(INDEX(Results_Long!$N:$N,$F130)="","NA",INDEX(Results_Long!$N:$N,$F130)) -> NA | H130: =IF(INDEX(Results_Long!$AG:$AG,$F130)="","NA",INDEX(Results_Long!$AG:$AG,$F130)) -> NA | I130: =IF(INDEX(Results_Long!$AJ:$AJ,$F130)="","NA",INDEX(Results_Long!$AJ:$AJ,$F130)) -> ordering: study-wise median sample_mid, ties alphabetical; first 5: Nandy, Lodh (2012) (1998.50); Chava (2010) (1999.00); Schneider (2010) (1999.00); Chava (2014) (1999.50); Oikonomou et al (2014) (2000.00)
A132: Interpretation
A133: H6: the pinned claim wording is 'under Zarea's Paris operationalization (midpoint + tie-exclusion), applied within our 3L-RVE framework' - NEVER 'under Zarea's method' [DEC-045/N8].
A134: H7: step_001 is not_estimable by rule (single cluster; vcovCR guard, ERROR_LOG #12); steps 1-9 are point-only in the figure, the CI band starts at step 10 (floor study Chen, Gao 2011).
A135: H7: the final step reproduces the period-domain pooled value by construction (visible in the last table row).
A137: Question | B137: Answer
A138: Why exclude ties in H6? | B138: The tie exclusion is part of Zarea's operationalization being transplanted; the inventory row quantifies it on v12 (79 ES / 5 studies at sample_mid = 2015.5; post cell 31 -> 26 studies).
A139: Is the cumulative trajectory an inferential claim? | B139: No - it is a stability display; inference lives in the pre-registered E/H tests. The 10-cluster floor prevents over-reading early low-df refits.
A141: Verdict: Mechanical outcome: H6 contrast tabulated with its design inventory; H7 trajectory tabulated in full with the floor rule applied; adjudication deferred to the documented gate-resolution step [DEC-044].

Sheet 9_H8_H9_Rolling_External
A1: TH-a (Block E/H fast frequentist battery) · H8 - rolling 6-year windows (21 windows) · H9 - external size comparison (COE companion)
A2: H8 tiers [DEC-045 S6]: >= 10 clusters full CR2 inference; 5-9 clusters descriptive point-only; < 5 not estimated. H9: descriptive channel comparison, explicitly no test.
A3: Run 2026-07-24 22:46 (canonical) · verifier R/06_verify_outputs.R 17/17 PASS · chat artefact check 2026-07-26 18/18 PASS · output/TH_a_results.csv 177x36
A5: Panel row | B5: analysis_id | C5: spec | D5: subset | E5: term | F5: RL row | G5: k_es | H5: k_st | I5: k_cl | J5: est_z | K5: ci_lb_z | L5: ci_ub_z | M5: est_r | N5: ci_lb_r | O5: ci_ub_r | P5: se_z | Q5: t | R5: df | S5: p | T5: value | U5: note (verbatim) | V5: tier (derived)
A6: window 1998-2003 | B6: H8 | C6: rolling | D6: 1998-2003 | E6: window_mean | F6: =SUMPRODUCT((Results_Long!$A$2:$A$178=$B6)*(Results_Long!$B$2:$B$178=$C6)*(Results_Long!$C$2:$C$178=$D6)*(Results_Long!$D$2:$D$178=$E6)*ROW(Results_Long!$A$2:$A$178)) -> 141 | G6: =IF(INDEX(Results_Long!$H:$H,$F6)="","NA",INDEX(Results_Long!$H:$H,$F6)) -> 312 | H6: =IF(INDEX(Results_Long!$I:$I,$F6)="","NA",INDEX(Results_Long!$I:$I,$F6)) -> 9 | I6: =IF(INDEX(Results_Long!$J:$J,$F6)="","NA",INDEX(Results_Long!$J:$J,$F6)) -> 9 | J6: =IF(INDEX(Results_Long!$K:$K,$F6)="","NA",INDEX(Results_Long!$K:$K,$F6)) -> -0.01487142 | K6: =IF(INDEX(Results_Long!$P:$P,$F6)="","NA",INDEX(Results_Long!$P:$P,$F6)) -> NA | L6: =IF(INDEX(Results_Long!$Q:$Q,$F6)="","NA",INDEX(Results_Long!$Q:$Q,$F6)) -> NA | M6: =IF(INDEX(Results_Long!$T:$T,$F6)="","NA",INDEX(Results_Long!$T:$T,$F6)) -> -0.014870324 | N6: =IF(INDEX(Results_Long!$U:$U,$F6)="","NA",INDEX(Results_Long!$U:$U,$F6)) -> NA | O6: =IF(INDEX(Results_Long!$V:$V,$F6)="","NA",INDEX(Results_Long!$V:$V,$F6)) -> NA | P6: =IF(INDEX(Results_Long!$L:$L,$F6)="","NA",INDEX(Results_Long!$L:$L,$F6)) -> NA | Q6: =IF(INDEX(Results_Long!$M:$M,$F6)="","NA",INDEX(Results_Long!$M:$M,$F6)) -> NA | R6: =IF(INDEX(Results_Long!$N:$N,$F6)="","NA",INDEX(Results_Long!$N:$N,$F6)) -> NA | S6: =IF(INDEX(Results_Long!$O:$O,$F6)="","NA",INDEX(Results_Long!$O:$O,$F6)) -> NA | T6: =IF(INDEX(Results_Long!$AG:$AG,$F6)="","NA",INDEX(Results_Long!$AG:$AG,$F6)) -> NA | U6: =IF(INDEX(Results_Long!$AJ:$AJ,$F6)="","NA",INDEX(Results_Long!$AJ:$AJ,$F6)) -> descriptive tier (5-9 clusters: 9) [DEC-045 S6]: estimate only; se/CI/p suppressed by rule; window [1998, 2004) on sample_mid | V6: =IF($I6="NA","NA",IF($I6>=10,"full CR2",IF($I6>=5,"descriptive (5-9)","not estimable (<5)"))) -> descriptive (5-9)
A7: window 1999-2004 | B7: H8 | C7: rolling | D7: 1999-2004 | E7: window_mean | F7: =SUMPRODUCT((Results_Long!$A$2:$A$178=$B7)*(Results_Long!$B$2:$B$178=$C7)*(Results_Long!$C$2:$C$178=$D7)*(Results_Long!$D$2:$D$178=$E7)*ROW(Results_Long!$A$2:$A$178)) -> 142 | G7: =IF(INDEX(Results_Long!$H:$H,$F7)="","NA",INDEX(Results_Long!$H:$H,$F7)) -> 306 | H7: =IF(INDEX(Results_Long!$I:$I,$F7)="","NA",INDEX(Results_Long!$I:$I,$F7)) -> 8 | I7: =IF(INDEX(Results_Long!$J:$J,$F7)="","NA",INDEX(Results_Long!$J:$J,$F7)) -> 8 | J7: =IF(INDEX(Results_Long!$K:$K,$F7)="","NA",INDEX(Results_Long!$K:$K,$F7)) -> -0.01518672 | K7: =IF(INDEX(Results_Long!$P:$P,$F7)="","NA",INDEX(Results_Long!$P:$P,$F7)) -> NA | L7: =IF(INDEX(Results_Long!$Q:$Q,$F7)="","NA",INDEX(Results_Long!$Q:$Q,$F7)) -> NA | M7: =IF(INDEX(Results_Long!$T:$T,$F7)="","NA",INDEX(Results_Long!$T:$T,$F7)) -> -0.015185553 | N7: =IF(INDEX(Results_Long!$U:$U,$F7)="","NA",INDEX(Results_Long!$U:$U,$F7)) -> NA | O7: =IF(INDEX(Results_Long!$V:$V,$F7)="","NA",INDEX(Results_Long!$V:$V,$F7)) -> NA | P7: =IF(INDEX(Results_Long!$L:$L,$F7)="","NA",INDEX(Results_Long!$L:$L,$F7)) -> NA | Q7: =IF(INDEX(Results_Long!$M:$M,$F7)="","NA",INDEX(Results_Long!$M:$M,$F7)) -> NA | R7: =IF(INDEX(Results_Long!$N:$N,$F7)="","NA",INDEX(Results_Long!$N:$N,$F7)) -> NA | S7: =IF(INDEX(Results_Long!$O:$O,$F7)="","NA",INDEX(Results_Long!$O:$O,$F7)) -> NA | T7: =IF(INDEX(Results_Long!$AG:$AG,$F7)="","NA",INDEX(Results_Long!$AG:$AG,$F7)) -> NA | U7: =IF(INDEX(Results_Long!$AJ:$AJ,$F7)="","NA",INDEX(Results_Long!$AJ:$AJ,$F7)) -> descriptive tier (5-9 clusters: 8) [DEC-045 S6]: estimate only; se/CI/p suppressed by rule; window [1999, 2005) on sample_mid | V7: =IF($I7="NA","NA",IF($I7>=10,"full CR2",IF($I7>=5,"descriptive (5-9)","not estimable (<5)"))) -> descriptive (5-9)
A8: window 2000-2005 | B8: H8 | C8: rolling | D8: 2000-2005 | E8: window_mean | F8: =SUMPRODUCT((Results_Long!$A$2:$A$178=$B8)*(Results_Long!$B$2:$B$178=$C8)*(Results_Long!$C$2:$C$178=$D8)*(Results_Long!$D$2:$D$178=$E8)*ROW(Results_Long!$A$2:$A$178)) -> 143 | G8: =IF(INDEX(Results_Long!$H:$H,$F8)="","NA",INDEX(Results_Long!$H:$H,$F8)) -> 242 | H8: =IF(INDEX(Results_Long!$I:$I,$F8)="","NA",INDEX(Results_Long!$I:$I,$F8)) -> 8 | I8: =IF(INDEX(Results_Long!$J:$J,$F8)="","NA",INDEX(Results_Long!$J:$J,$F8)) -> 8 | J8: =IF(INDEX(Results_Long!$K:$K,$F8)="","NA",INDEX(Results_Long!$K:$K,$F8)) -> -0.016355716 | K8: =IF(INDEX(Results_Long!$P:$P,$F8)="","NA",INDEX(Results_Long!$P:$P,$F8)) -> NA | L8: =IF(INDEX(Results_Long!$Q:$Q,$F8)="","NA",INDEX(Results_Long!$Q:$Q,$F8)) -> NA | M8: =IF(INDEX(Results_Long!$T:$T,$F8)="","NA",INDEX(Results_Long!$T:$T,$F8)) -> -0.016354258 | N8: =IF(INDEX(Results_Long!$U:$U,$F8)="","NA",INDEX(Results_Long!$U:$U,$F8)) -> NA | O8: =IF(INDEX(Results_Long!$V:$V,$F8)="","NA",INDEX(Results_Long!$V:$V,$F8)) -> NA | P8: =IF(INDEX(Results_Long!$L:$L,$F8)="","NA",INDEX(Results_Long!$L:$L,$F8)) -> NA | Q8: =IF(INDEX(Results_Long!$M:$M,$F8)="","NA",INDEX(Results_Long!$M:$M,$F8)) -> NA | R8: =IF(INDEX(Results_Long!$N:$N,$F8)="","NA",INDEX(Results_Long!$N:$N,$F8)) -> NA | S8: =IF(INDEX(Results_Long!$O:$O,$F8)="","NA",INDEX(Results_Long!$O:$O,$F8)) -> NA | T8: =IF(INDEX(Results_Long!$AG:$AG,$F8)="","NA",INDEX(Results_Long!$AG:$AG,$F8)) -> NA | U8: =IF(INDEX(Results_Long!$AJ:$AJ,$F8)="","NA",INDEX(Results_Long!$AJ:$AJ,$F8)) -> descriptive tier (5-9 clusters: 8) [DEC-045 S6]: estimate only; se/CI/p suppressed by rule; window [2000, 2006) on sample_mid | V8: =IF($I8="NA","NA",IF($I8>=10,"full CR2",IF($I8>=5,"descriptive (5-9)","not estimable (<5)"))) -> descriptive (5-9)
A9: window 2001-2006 | B9: H8 | C9: rolling | D9: 2001-2006 | E9: window_mean | F9: =SUMPRODUCT((Results_Long!$A$2:$A$178=$B9)*(Results_Long!$B$2:$B$178=$C9)*(Results_Long!$C$2:$C$178=$D9)*(Results_Long!$D$2:$D$178=$E9)*ROW(Results_Long!$A$2:$A$178)) -> 144 | G9: =IF(INDEX(Results_Long!$H:$H,$F9)="","NA",INDEX(Results_Long!$H:$H,$F9)) -> 75 | H9: =IF(INDEX(Results_Long!$I:$I,$F9)="","NA",INDEX(Results_Long!$I:$I,$F9)) -> 6 | I9: =IF(INDEX(Results_Long!$J:$J,$F9)="","NA",INDEX(Results_Long!$J:$J,$F9)) -> 6 | J9: =IF(INDEX(Results_Long!$K:$K,$F9)="","NA",INDEX(Results_Long!$K:$K,$F9)) -> -0.039045798 | K9: =IF(INDEX(Results_Long!$P:$P,$F9)="","NA",INDEX(Results_Long!$P:$P,$F9)) -> NA | L9: =IF(INDEX(Results_Long!$Q:$Q,$F9)="","NA",INDEX(Results_Long!$Q:$Q,$F9)) -> NA | M9: =IF(INDEX(Results_Long!$T:$T,$F9)="","NA",INDEX(Results_Long!$T:$T,$F9)) -> -0.039025967 | N9: =IF(INDEX(Results_Long!$U:$U,$F9)="","NA",INDEX(Results_Long!$U:$U,$F9)) -> NA | O9: =IF(INDEX(Results_Long!$V:$V,$F9)="","NA",INDEX(Results_Long!$V:$V,$F9)) -> NA | P9: =IF(INDEX(Results_Long!$L:$L,$F9)="","NA",INDEX(Results_Long!$L:$L,$F9)) -> NA | Q9: =IF(INDEX(Results_Long!$M:$M,$F9)="","NA",INDEX(Results_Long!$M:$M,$F9)) -> NA | R9: =IF(INDEX(Results_Long!$N:$N,$F9)="","NA",INDEX(Results_Long!$N:$N,$F9)) -> NA | S9: =IF(INDEX(Results_Long!$O:$O,$F9)="","NA",INDEX(Results_Long!$O:$O,$F9)) -> NA | T9: =IF(INDEX(Results_Long!$AG:$AG,$F9)="","NA",INDEX(Results_Long!$AG:$AG,$F9)) -> NA | U9: =IF(INDEX(Results_Long!$AJ:$AJ,$F9)="","NA",INDEX(Results_Long!$AJ:$AJ,$F9)) -> descriptive tier (5-9 clusters: 6) [DEC-045 S6]: estimate only; se/CI/p suppressed by rule; window [2001, 2007) on sample_mid | V9: =IF($I9="NA","NA",IF($I9>=10,"full CR2",IF($I9>=5,"descriptive (5-9)","not estimable (<5)"))) -> descriptive (5-9)
A10: window 2002-2007 | B10: H8 | C10: rolling | D10: 2002-2007 | E10: window_mean | F10: =SUMPRODUCT((Results_Long!$A$2:$A$178=$B10)*(Results_Long!$B$2:$B$178=$C10)*(Results_Long!$C$2:$C$178=$D10)*(Results_Long!$D$2:$D$178=$E10)*ROW(Results_Long!$A$2:$A$178)) -> 145 | G10: =IF(INDEX(Results_Long!$H:$H,$F10)="","NA",INDEX(Results_Long!$H:$H,$F10)) -> 26 | H10: =IF(INDEX(Results_Long!$I:$I,$F10)="","NA",INDEX(Results_Long!$I:$I,$F10)) -> 4 | I10: =IF(INDEX(Results_Long!$J:$J,$F10)="","NA",INDEX(Results_Long!$J:$J,$F10)) -> 4 | J10: =IF(INDEX(Results_Long!$K:$K,$F10)="","NA",INDEX(Results_Long!$K:$K,$F10)) -> NA | K10: =IF(INDEX(Results_Long!$P:$P,$F10)="","NA",INDEX(Results_Long!$P:$P,$F10)) -> NA | L10: =IF(INDEX(Results_Long!$Q:$Q,$F10)="","NA",INDEX(Results_Long!$Q:$Q,$F10)) -> NA | M10: =IF(INDEX(Results_Long!$T:$T,$F10)="","NA",INDEX(Results_Long!$T:$T,$F10)) -> NA | N10: =IF(INDEX(Results_Long!$U:$U,$F10)="","NA",INDEX(Results_Long!$U:$U,$F10)) -> NA | O10: =IF(INDEX(Results_Long!$V:$V,$F10)="","NA",INDEX(Results_Long!$V:$V,$F10)) -> NA | P10: =IF(INDEX(Results_Long!$L:$L,$F10)="","NA",INDEX(Results_Long!$L:$L,$F10)) -> NA | Q10: =IF(INDEX(Results_Long!$M:$M,$F10)="","NA",INDEX(Results_Long!$M:$M,$F10)) -> NA | R10: =IF(INDEX(Results_Long!$N:$N,$F10)="","NA",INDEX(Results_Long!$N:$N,$F10)) -> NA | S10: =IF(INDEX(Results_Long!$O:$O,$F10)="","NA",INDEX(Results_Long!$O:$O,$F10)) -> NA | T10: =IF(INDEX(Results_Long!$AG:$AG,$F10)="","NA",INDEX(Results_Long!$AG:$AG,$F10)) -> NA | U10: =IF(INDEX(Results_Long!$AJ:$AJ,$F10)="","NA",INDEX(Results_Long!$AJ:$AJ,$F10)) -> not_estimable: 4 clusters < 5 [DEC-045 S6 tier]; window [2002, 2008); no fit attempted | V10: =IF($I10="NA","NA",IF($I10>=10,"full CR2",IF($I10>=5,"descriptive (5-9)","not estimable (<5)"))) -> not estimable (<5)
A11: window 2003-2008 | B11: H8 | C11: rolling | D11: 2003-2008 | E11: window_mean | F11: =SUMPRODUCT((Results_Long!$A$2:$A$178=$B11)*(Results_Long!$B$2:$B$178=$C11)*(Results_Long!$C$2:$C$178=$D11)*(Results_Long!$D$2:$D$178=$E11)*ROW(Results_Long!$A$2:$A$178)) -> 146 | G11: =IF(INDEX(Results_Long!$H:$H,$F11)="","NA",INDEX(Results_Long!$H:$H,$F11)) -> 67 | H11: =IF(INDEX(Results_Long!$I:$I,$F11)="","NA",INDEX(Results_Long!$I:$I,$F11)) -> 7 | I11: =IF(INDEX(Results_Long!$J:$J,$F11)="","NA",INDEX(Results_Long!$J:$J,$F11)) -> 7 | J11: =IF(INDEX(Results_Long!$K:$K,$F11)="","NA",INDEX(Results_Long!$K:$K,$F11)) -> -0.064797513 | K11: =IF(INDEX(Results_Long!$P:$P,$F11)="","NA",INDEX(Results_Long!$P:$P,$F11)) -> NA | L11: =IF(INDEX(Results_Long!$Q:$Q,$F11)="","NA",INDEX(Results_Long!$Q:$Q,$F11)) -> NA | M11: =IF(INDEX(Results_Long!$T:$T,$F11)="","NA",INDEX(Results_Long!$T:$T,$F11)) -> -0.064706976 | N11: =IF(INDEX(Results_Long!$U:$U,$F11)="","NA",INDEX(Results_Long!$U:$U,$F11)) -> NA | O11: =IF(INDEX(Results_Long!$V:$V,$F11)="","NA",INDEX(Results_Long!$V:$V,$F11)) -> NA | P11: =IF(INDEX(Results_Long!$L:$L,$F11)="","NA",INDEX(Results_Long!$L:$L,$F11)) -> NA | Q11: =IF(INDEX(Results_Long!$M:$M,$F11)="","NA",INDEX(Results_Long!$M:$M,$F11)) -> NA | R11: =IF(INDEX(Results_Long!$N:$N,$F11)="","NA",INDEX(Results_Long!$N:$N,$F11)) -> NA | S11: =IF(INDEX(Results_Long!$O:$O,$F11)="","NA",INDEX(Results_Long!$O:$O,$F11)) -> NA | T11: =IF(INDEX(Results_Long!$AG:$AG,$F11)="","NA",INDEX(Results_Long!$AG:$AG,$F11)) -> NA | U11: =IF(INDEX(Results_Long!$AJ:$AJ,$F11)="","NA",INDEX(Results_Long!$AJ:$AJ,$F11)) -> descriptive tier (5-9 clusters: 7) [DEC-045 S6]: estimate only; se/CI/p suppressed by rule; window [2003, 2009) on sample_mid | V11: =IF($I11="NA","NA",IF($I11>=10,"full CR2",IF($I11>=5,"descriptive (5-9)","not estimable (<5)"))) -> descriptive (5-9)
A12: window 2004-2009 | B12: H8 | C12: rolling | D12: 2004-2009 | E12: window_mean | F12: =SUMPRODUCT((Results_Long!$A$2:$A$178=$B12)*(Results_Long!$B$2:$B$178=$C12)*(Results_Long!$C$2:$C$178=$D12)*(Results_Long!$D$2:$D$178=$E12)*ROW(Results_Long!$A$2:$A$178)) -> 147 | G12: =IF(INDEX(Results_Long!$H:$H,$F12)="","NA",INDEX(Results_Long!$H:$H,$F12)) -> 85 | H12: =IF(INDEX(Results_Long!$I:$I,$F12)="","NA",INDEX(Results_Long!$I:$I,$F12)) -> 8 | I12: =IF(INDEX(Results_Long!$J:$J,$F12)="","NA",INDEX(Results_Long!$J:$J,$F12)) -> 8 | J12: =IF(INDEX(Results_Long!$K:$K,$F12)="","NA",INDEX(Results_Long!$K:$K,$F12)) -> -0.071015843 | K12: =IF(INDEX(Results_Long!$P:$P,$F12)="","NA",INDEX(Results_Long!$P:$P,$F12)) -> NA | L12: =IF(INDEX(Results_Long!$Q:$Q,$F12)="","NA",INDEX(Results_Long!$Q:$Q,$F12)) -> NA | M12: =IF(INDEX(Results_Long!$T:$T,$F12)="","NA",INDEX(Results_Long!$T:$T,$F12)) -> -0.070896699 | N12: =IF(INDEX(Results_Long!$U:$U,$F12)="","NA",INDEX(Results_Long!$U:$U,$F12)) -> NA | O12: =IF(INDEX(Results_Long!$V:$V,$F12)="","NA",INDEX(Results_Long!$V:$V,$F12)) -> NA | P12: =IF(INDEX(Results_Long!$L:$L,$F12)="","NA",INDEX(Results_Long!$L:$L,$F12)) -> NA | Q12: =IF(INDEX(Results_Long!$M:$M,$F12)="","NA",INDEX(Results_Long!$M:$M,$F12)) -> NA | R12: =IF(INDEX(Results_Long!$N:$N,$F12)="","NA",INDEX(Results_Long!$N:$N,$F12)) -> NA | S12: =IF(INDEX(Results_Long!$O:$O,$F12)="","NA",INDEX(Results_Long!$O:$O,$F12)) -> NA | T12: =IF(INDEX(Results_Long!$AG:$AG,$F12)="","NA",INDEX(Results_Long!$AG:$AG,$F12)) -> NA | U12: =IF(INDEX(Results_Long!$AJ:$AJ,$F12)="","NA",INDEX(Results_Long!$AJ:$AJ,$F12)) -> descriptive tier (5-9 clusters: 8) [DEC-045 S6]: estimate only; se/CI/p suppressed by rule; window [2004, 2010) on sample_mid | V12: =IF($I12="NA","NA",IF($I12>=10,"full CR2",IF($I12>=5,"descriptive (5-9)","not estimable (<5)"))) -> descriptive (5-9)
A13: window 2005-2010 | B13: H8 | C13: rolling | D13: 2005-2010 | E13: window_mean | F13: =SUMPRODUCT((Results_Long!$A$2:$A$178=$B13)*(Results_Long!$B$2:$B$178=$C13)*(Results_Long!$C$2:$C$178=$D13)*(Results_Long!$D$2:$D$178=$E13)*ROW(Results_Long!$A$2:$A$178)) -> 148 | G13: =IF(INDEX(Results_Long!$H:$H,$F13)="","NA",INDEX(Results_Long!$H:$H,$F13)) -> 436 | H13: =IF(INDEX(Results_Long!$I:$I,$F13)="","NA",INDEX(Results_Long!$I:$I,$F13)) -> 18 | I13: =IF(INDEX(Results_Long!$J:$J,$F13)="","NA",INDEX(Results_Long!$J:$J,$F13)) -> 18 | J13: =IF(INDEX(Results_Long!$K:$K,$F13)="","NA",INDEX(Results_Long!$K:$K,$F13)) -> -0.041300989 | K13: =IF(INDEX(Results_Long!$P:$P,$F13)="","NA",INDEX(Results_Long!$P:$P,$F13)) -> -0.063075731 | L13: =IF(INDEX(Results_Long!$Q:$Q,$F13)="","NA",INDEX(Results_Long!$Q:$Q,$F13)) -> -0.019526247 | M13: =IF(INDEX(Results_Long!$T:$T,$F13)="","NA",INDEX(Results_Long!$T:$T,$F13)) -> -0.041277522 | N13: =IF(INDEX(Results_Long!$U:$U,$F13)="","NA",INDEX(Results_Long!$U:$U,$F13)) -> -0.062992214 | O13: =IF(INDEX(Results_Long!$V:$V,$F13)="","NA",INDEX(Results_Long!$V:$V,$F13)) -> -0.019523766 | P13: =IF(INDEX(Results_Long!$L:$L,$F13)="","NA",INDEX(Results_Long!$L:$L,$F13)) -> 0.010205514 | Q13: =IF(INDEX(Results_Long!$M:$M,$F13)="","NA",INDEX(Results_Long!$M:$M,$F13)) -> -4.046929 | R13: =IF(INDEX(Results_Long!$N:$N,$F13)="","NA",INDEX(Results_Long!$N:$N,$F13)) -> 14.8264 | S13: =IF(INDEX(Results_Long!$O:$O,$F13)="","NA",INDEX(Results_Long!$O:$O,$F13)) -> 0.0010770774 | T13: =IF(INDEX(Results_Long!$AG:$AG,$F13)="","NA",INDEX(Results_Long!$AG:$AG,$F13)) -> NA | U13: =IF(INDEX(Results_Long!$AJ:$AJ,$F13)="","NA",INDEX(Results_Long!$AJ:$AJ,$F13)) -> full-inference tier (>= 10 clusters: 18) [DEC-045 S6]; window [2005, 2011) on sample_mid; width 6 y, step 1 y, anchor 1998 | V13: =IF($I13="NA","NA",IF($I13>=10,"full CR2",IF($I13>=5,"descriptive (5-9)","not estimable (<5)"))) -> full CR2
A14: window 2006-2011 | B14: H8 | C14: rolling | D14: 2006-2011 | E14: window_mean | F14: =SUMPRODUCT((Results_Long!$A$2:$A$178=$B14)*(Results_Long!$B$2:$B$178=$C14)*(Results_Long!$C$2:$C$178=$D14)*(Results_Long!$D$2:$D$178=$E14)*ROW(Results_Long!$A$2:$A$178)) -> 149 | G14: =IF(INDEX(Results_Long!$H:$H,$F14)="","NA",INDEX(Results_Long!$H:$H,$F14)) -> 674 | H14: =IF(INDEX(Results_Long!$I:$I,$F14)="","NA",INDEX(Results_Long!$I:$I,$F14)) -> 24 | I14: =IF(INDEX(Results_Long!$J:$J,$F14)="","NA",INDEX(Results_Long!$J:$J,$F14)) -> 24 | J14: =IF(INDEX(Results_Long!$K:$K,$F14)="","NA",INDEX(Results_Long!$K:$K,$F14)) -> -0.052902864 | K14: =IF(INDEX(Results_Long!$P:$P,$F14)="","NA",INDEX(Results_Long!$P:$P,$F14)) -> -0.075234653 | L14: =IF(INDEX(Results_Long!$Q:$Q,$F14)="","NA",INDEX(Results_Long!$Q:$Q,$F14)) -> -0.030571075 | M14: =IF(INDEX(Results_Long!$T:$T,$F14)="","NA",INDEX(Results_Long!$T:$T,$F14)) -> -0.052853566 | N14: =IF(INDEX(Results_Long!$U:$U,$F14)="","NA",INDEX(Results_Long!$U:$U,$F14)) -> -0.075093025 | O14: =IF(INDEX(Results_Long!$V:$V,$F14)="","NA",INDEX(Results_Long!$V:$V,$F14)) -> -0.030561555 | P14: =IF(INDEX(Results_Long!$L:$L,$F14)="","NA",INDEX(Results_Long!$L:$L,$F14)) -> 0.010733015 | Q14: =IF(INDEX(Results_Long!$M:$M,$F14)="","NA",INDEX(Results_Long!$M:$M,$F14)) -> -4.9289844 | R14: =IF(INDEX(Results_Long!$N:$N,$F14)="","NA",INDEX(Results_Long!$N:$N,$F14)) -> 20.827496 | S14: =IF(INDEX(Results_Long!$O:$O,$F14)="","NA",INDEX(Results_Long!$O:$O,$F14)) -> 7.2489785e-05 | T14: =IF(INDEX(Results_Long!$AG:$AG,$F14)="","NA",INDEX(Results_Long!$AG:$AG,$F14)) -> NA | U14: =IF(INDEX(Results_Long!$AJ:$AJ,$F14)="","NA",INDEX(Results_Long!$AJ:$AJ,$F14)) -> full-inference tier (>= 10 clusters: 24) [DEC-045 S6]; window [2006, 2012) on sample_mid; width 6 y, step 1 y, anchor 1998 | V14: =IF($I14="NA","NA",IF($I14>=10,"full CR2",IF($I14>=5,"descriptive (5-9)","not estimable (<5)"))) -> full CR2
A15: window 2007-2012 | B15: H8 | C15: rolling | D15: 2007-2012 | E15: window_mean | F15: =SUMPRODUCT((Results_Long!$A$2:$A$178=$B15)*(Results_Long!$B$2:$B$178=$C15)*(Results_Long!$C$2:$C$178=$D15)*(Results_Long!$D$2:$D$178=$E15)*ROW(Results_Long!$A$2:$A$178)) -> 150 | G15: =IF(INDEX(Results_Long!$H:$H,$F15)="","NA",INDEX(Results_Long!$H:$H,$F15)) -> 1008 | H15: =IF(INDEX(Results_Long!$I:$I,$F15)="","NA",INDEX(Results_Long!$I:$I,$F15)) -> 43 | I15: =IF(INDEX(Results_Long!$J:$J,$F15)="","NA",INDEX(Results_Long!$J:$J,$F15)) -> 42 | J15: =IF(INDEX(Results_Long!$K:$K,$F15)="","NA",INDEX(Results_Long!$K:$K,$F15)) -> -0.086801725 | K15: =IF(INDEX(Results_Long!$P:$P,$F15)="","NA",INDEX(Results_Long!$P:$P,$F15)) -> -0.16763356 | L15: =IF(INDEX(Results_Long!$Q:$Q,$F15)="","NA",INDEX(Results_Long!$Q:$Q,$F15)) -> -0.0059698889 | M15: =IF(INDEX(Results_Long!$T:$T,$F15)="","NA",INDEX(Results_Long!$T:$T,$F15)) -> -0.086584377 | N15: =IF(INDEX(Results_Long!$U:$U,$F15)="","NA",INDEX(Results_Long!$U:$U,$F15)) -> -0.16608079 | O15: =IF(INDEX(Results_Long!$V:$V,$F15)="","NA",INDEX(Results_Long!$V:$V,$F15)) -> -0.005969818 | P15: =IF(INDEX(Results_Long!$L:$L,$F15)="","NA",INDEX(Results_Long!$L:$L,$F15)) -> 0.040022875 | Q15: =IF(INDEX(Results_Long!$M:$M,$F15)="","NA",INDEX(Results_Long!$M:$M,$F15)) -> -2.1688028 | R15: =IF(INDEX(Results_Long!$N:$N,$F15)="","NA",INDEX(Results_Long!$N:$N,$F15)) -> 40.933297 | S15: =IF(INDEX(Results_Long!$O:$O,$F15)="","NA",INDEX(Results_Long!$O:$O,$F15)) -> 0.035960827 | T15: =IF(INDEX(Results_Long!$AG:$AG,$F15)="","NA",INDEX(Results_Long!$AG:$AG,$F15)) -> NA | U15: =IF(INDEX(Results_Long!$AJ:$AJ,$F15)="","NA",INDEX(Results_Long!$AJ:$AJ,$F15)) -> full-inference tier (>= 10 clusters: 42) [DEC-045 S6]; window [2007, 2013) on sample_mid; width 6 y, step 1 y, anchor 1998 | V15: =IF($I15="NA","NA",IF($I15>=10,"full CR2",IF($I15>=5,"descriptive (5-9)","not estimable (<5)"))) -> full CR2
A16: window 2008-2013 | B16: H8 | C16: rolling | D16: 2008-2013 | E16: window_mean | F16: =SUMPRODUCT((Results_Long!$A$2:$A$178=$B16)*(Results_Long!$B$2:$B$178=$C16)*(Results_Long!$C$2:$C$178=$D16)*(Results_Long!$D$2:$D$178=$E16)*ROW(Results_Long!$A$2:$A$178)) -> 151 | G16: =IF(INDEX(Results_Long!$H:$H,$F16)="","NA",INDEX(Results_Long!$H:$H,$F16)) -> 1368 | H16: =IF(INDEX(Results_Long!$I:$I,$F16)="","NA",INDEX(Results_Long!$I:$I,$F16)) -> 54 | I16: =IF(INDEX(Results_Long!$J:$J,$F16)="","NA",INDEX(Results_Long!$J:$J,$F16)) -> 53 | J16: =IF(INDEX(Results_Long!$K:$K,$F16)="","NA",INDEX(Results_Long!$K:$K,$F16)) -> -0.07352868 | K16: =IF(INDEX(Results_Long!$P:$P,$F16)="","NA",INDEX(Results_Long!$P:$P,$F16)) -> -0.13761513 | L16: =IF(INDEX(Results_Long!$Q:$Q,$F16)="","NA",INDEX(Results_Long!$Q:$Q,$F16)) -> -0.0094422288 | M16: =IF(INDEX(Results_Long!$T:$T,$F16)="","NA",INDEX(Results_Long!$T:$T,$F16)) -> -0.073396456 | N16: =IF(INDEX(Results_Long!$U:$U,$F16)="","NA",INDEX(Results_Long!$U:$U,$F16)) -> -0.13675295 | O16: =IF(INDEX(Results_Long!$V:$V,$F16)="","NA",INDEX(Results_Long!$V:$V,$F16)) -> -0.0094419482 | P16: =IF(INDEX(Results_Long!$L:$L,$F16)="","NA",INDEX(Results_Long!$L:$L,$F16)) -> 0.031936072 | Q16: =IF(INDEX(Results_Long!$M:$M,$F16)="","NA",INDEX(Results_Long!$M:$M,$F16)) -> -2.3023708 | R16: =IF(INDEX(Results_Long!$N:$N,$F16)="","NA",INDEX(Results_Long!$N:$N,$F16)) -> 51.930739 | S16: =IF(INDEX(Results_Long!$O:$O,$F16)="","NA",INDEX(Results_Long!$O:$O,$F16)) -> 0.025354623 | T16: =IF(INDEX(Results_Long!$AG:$AG,$F16)="","NA",INDEX(Results_Long!$AG:$AG,$F16)) -> NA | U16: =IF(INDEX(Results_Long!$AJ:$AJ,$F16)="","NA",INDEX(Results_Long!$AJ:$AJ,$F16)) -> full-inference tier (>= 10 clusters: 53) [DEC-045 S6]; window [2008, 2014) on sample_mid; width 6 y, step 1 y, anchor 1998 | V16: =IF($I16="NA","NA",IF($I16>=10,"full CR2",IF($I16>=5,"descriptive (5-9)","not estimable (<5)"))) -> full CR2
A17: window 2009-2014 | B17: H8 | C17: rolling | D17: 2009-2014 | E17: window_mean | F17: =SUMPRODUCT((Results_Long!$A$2:$A$178=$B17)*(Results_Long!$B$2:$B$178=$C17)*(Results_Long!$C$2:$C$178=$D17)*(Results_Long!$D$2:$D$178=$E17)*ROW(Results_Long!$A$2:$A$178)) -> 152 | G17: =IF(INDEX(Results_Long!$H:$H,$F17)="","NA",INDEX(Results_Long!$H:$H,$F17)) -> 1552 | H17: =IF(INDEX(Results_Long!$I:$I,$F17)="","NA",INDEX(Results_Long!$I:$I,$F17)) -> 63 | I17: =IF(INDEX(Results_Long!$J:$J,$F17)="","NA",INDEX(Results_Long!$J:$J,$F17)) -> 62 | J17: =IF(INDEX(Results_Long!$K:$K,$F17)="","NA",INDEX(Results_Long!$K:$K,$F17)) -> -0.066472226 | K17: =IF(INDEX(Results_Long!$P:$P,$F17)="","NA",INDEX(Results_Long!$P:$P,$F17)) -> -0.11790997 | L17: =IF(INDEX(Results_Long!$Q:$Q,$F17)="","NA",INDEX(Results_Long!$Q:$Q,$F17)) -> -0.015034483 | M17: =IF(INDEX(Results_Long!$T:$T,$F17)="","NA",INDEX(Results_Long!$T:$T,$F17)) -> -0.066374495 | N17: =IF(INDEX(Results_Long!$U:$U,$F17)="","NA",INDEX(Results_Long!$U:$U,$F17)) -> -0.11736657 | O17: =IF(INDEX(Results_Long!$V:$V,$F17)="","NA",INDEX(Results_Long!$V:$V,$F17)) -> -0.015033351 | P17: =IF(INDEX(Results_Long!$L:$L,$F17)="","NA",INDEX(Results_Long!$L:$L,$F17)) -> 0.025720734 | Q17: =IF(INDEX(Results_Long!$M:$M,$F17)="","NA",INDEX(Results_Long!$M:$M,$F17)) -> -2.584383 | R17: =IF(INDEX(Results_Long!$N:$N,$F17)="","NA",INDEX(Results_Long!$N:$N,$F17)) -> 60.652658 | S17: =IF(INDEX(Results_Long!$O:$O,$F17)="","NA",INDEX(Results_Long!$O:$O,$F17)) -> 0.012178641 | T17: =IF(INDEX(Results_Long!$AG:$AG,$F17)="","NA",INDEX(Results_Long!$AG:$AG,$F17)) -> NA | U17: =IF(INDEX(Results_Long!$AJ:$AJ,$F17)="","NA",INDEX(Results_Long!$AJ:$AJ,$F17)) -> full-inference tier (>= 10 clusters: 62) [DEC-045 S6]; window [2009, 2015) on sample_mid; width 6 y, step 1 y, anchor 1998 | V17: =IF($I17="NA","NA",IF($I17>=10,"full CR2",IF($I17>=5,"descriptive (5-9)","not estimable (<5)"))) -> full CR2
... A26: window 2018-2023 | B26: H8 | C26: rolling | D26: 2018-2023 | E26: window_mean | F26: =SUMPRODUCT((Results_Long!$A$2:$A$178=$B26)*(Results_Long!$B$2:$B$178=$C26)*(Results_Long!$C$2:$C$178=$D26)*(Results_Long!$D$2:$D$178=$E26)*ROW(Results_Long!$A$2:$A$178)) -> 161 | G26: =IF(INDEX(Results_Long!$H:$H,$F26)="","NA",INDEX(Results_Long!$H:$H,$F26)) -> 336 | H26: =IF(INDEX(Results_Long!$I:$I,$F26)="","NA",INDEX(Results_Long!$I:$I,$F26)) -> 14 | I26: =IF(INDEX(Results_Long!$J:$J,$F26)="","NA",INDEX(Results_Long!$J:$J,$F26)) -> 14 | J26: =IF(INDEX(Results_Long!$K:$K,$F26)="","NA",INDEX(Results_Long!$K:$K,$F26)) -> -0.05338347 | K26: =IF(INDEX(Results_Long!$P:$P,$F26)="","NA",INDEX(Results_Long!$P:$P,$F26)) -> -0.086601891 | L26: =IF(INDEX(Results_Long!$Q:$Q,$F26)="","NA",INDEX(Results_Long!$Q:$Q,$F26)) -> -0.020165048 | M26: =IF(INDEX(Results_Long!$T:$T,$F26)="","NA",INDEX(Results_Long!$T:$T,$F26)) -> -0.053332817 | N26: =IF(INDEX(Results_Long!$U:$U,$F26)="","NA",INDEX(Results_Long!$U:$U,$F26)) -> -0.086386037 | O26: =IF(INDEX(Results_Long!$V:$V,$F26)="","NA",INDEX(Results_Long!$V:$V,$F26)) -> -0.020162316 | P26: =IF(INDEX(Results_Long!$L:$L,$F26)="","NA",INDEX(Results_Long!$L:$L,$F26)) -> 0.015324113 | Q26: =IF(INDEX(Results_Long!$M:$M,$F26)="","NA",INDEX(Results_Long!$M:$M,$F26)) -> -3.4836255 | R26: =IF(INDEX(Results_Long!$N:$N,$F26)="","NA",INDEX(Results_Long!$N:$N,$F26)) -> 12.580064 | S26: =IF(INDEX(Results_Long!$O:$O,$F26)="","NA",INDEX(Results_Long!$O:$O,$F26)) -> 0.0042267156 | T26: =IF(INDEX(Results_Long!$AG:$AG,$F26)="","NA",INDEX(Results_Long!$AG:$AG,$F26)) -> NA | U26: =IF(INDEX(Results_Long!$AJ:$AJ,$F26)="","NA",INDEX(Results_Long!$AJ:$AJ,$F26)) -> full-inference tier (>= 10 clusters: 14) [DEC-045 S6]; window [2018, 2024) on sample_mid; width 6 y, step 1 y, anchor 1998 | V26: =IF($I26="NA","NA",IF($I26>=10,"full CR2",IF($I26>=5,"descriptive (5-9)","not estimable (<5)"))) -> full CR2
A28: Panel row | B28: analysis_id | C28: spec | D28: subset | E28: term | F28: RL row | G28: k_es | H28: k_st | I28: k_cl | J28: est_z | K28: ci_lb_z | L28: ci_ub_z | M28: est_r | N28: ci_lb_r | O28: ci_ub_r | P28: se_z | Q28: t | R28: df | S28: p | T28: value | U28: note (verbatim)
A29: H9 own pooled (debt side, descriptive channel) | B29: H9 | C29: external_size | D29: defined | E29: own_pooled | F29: =SUMPRODUCT((Results_Long!$A$2:$A$178=$B29)*(Results_Long!$B$2:$B$178=$C29)*(Results_Long!$C$2:$C$178=$D29)*(Results_Long!$D$2:$D$178=$E29)*ROW(Results_Long!$A$2:$A$178)) -> 162 | G29: =IF(INDEX(Results_Long!$H:$H,$F29)="","NA",INDEX(Results_Long!$H:$H,$F29)) -> 2713 | H29: =IF(INDEX(Results_Long!$I:$I,$F29)="","NA",INDEX(Results_Long!$I:$I,$F29)) -> 115 | I29: =IF(INDEX(Results_Long!$J:$J,$F29)="","NA",INDEX(Results_Long!$J:$J,$F29)) -> 114 | J29: =IF(INDEX(Results_Long!$K:$K,$F29)="","NA",INDEX(Results_Long!$K:$K,$F29)) -> -0.058646737 | K29: =IF(INDEX(Results_Long!$P:$P,$F29)="","NA",INDEX(Results_Long!$P:$P,$F29)) -> NA | L29: =IF(INDEX(Results_Long!$Q:$Q,$F29)="","NA",INDEX(Results_Long!$Q:$Q,$F29)) -> NA | M29: =IF(INDEX(Results_Long!$T:$T,$F29)="","NA",INDEX(Results_Long!$T:$T,$F29)) -> -0.058579592 | N29: =IF(INDEX(Results_Long!$U:$U,$F29)="","NA",INDEX(Results_Long!$U:$U,$F29)) -> -0.085890445 | O29: =IF(INDEX(Results_Long!$V:$V,$F29)="","NA",INDEX(Results_Long!$V:$V,$F29)) -> -0.031180768 | P29: =IF(INDEX(Results_Long!$L:$L,$F29)="","NA",INDEX(Results_Long!$L:$L,$F29)) -> NA | Q29: =IF(INDEX(Results_Long!$M:$M,$F29)="","NA",INDEX(Results_Long!$M:$M,$F29)) -> NA | R29: =IF(INDEX(Results_Long!$N:$N,$F29)="","NA",INDEX(Results_Long!$N:$N,$F29)) -> NA | S29: =IF(INDEX(Results_Long!$O:$O,$F29)="","NA",INDEX(Results_Long!$O:$O,$F29)) -> NA | T29: =IF(INDEX(Results_Long!$AG:$AG,$F29)="","NA",INDEX(Results_Long!$AG:$AG,$F29)) -> NA | U29: =IF(INDEX(Results_Long!$AJ:$AJ,$F29)="","NA",INDEX(Results_Long!$AJ:$AJ,$F29)) -> debt-side pooled mean (E1 refit of T1/A1); descriptive channel-level size comparison, NO formal z-test [DEC-045/H-Q9; N12 scope shift disclosed]
A30: H9 COE companion study-level (Table 3) | B30: H9 | C30: external_size | D30: defined | E30: coe_study_level | F30: =SUMPRODUCT((Results_Long!$A$2:$A$178=$B30)*(Results_Long!$B$2:$B$178=$C30)*(Results_Long!$C$2:$C$178=$D30)*(Results_Long!$D$2:$D$178=$E30)*ROW(Results_Long!$A$2:$A$178)) -> 163 | G30: =IF(INDEX(Results_Long!$H:$H,$F30)="","NA",INDEX(Results_Long!$H:$H,$F30)) -> NA | H30: =IF(INDEX(Results_Long!$I:$I,$F30)="","NA",INDEX(Results_Long!$I:$I,$F30)) -> 75 | I30: =IF(INDEX(Results_Long!$J:$J,$F30)="","NA",INDEX(Results_Long!$J:$J,$F30)) -> NA | J30: =IF(INDEX(Results_Long!$K:$K,$F30)="","NA",INDEX(Results_Long!$K:$K,$F30)) -> NA | K30: =IF(INDEX(Results_Long!$P:$P,$F30)="","NA",INDEX(Results_Long!$P:$P,$F30)) -> NA | L30: =IF(INDEX(Results_Long!$Q:$Q,$F30)="","NA",INDEX(Results_Long!$Q:$Q,$F30)) -> NA | M30: =IF(INDEX(Results_Long!$T:$T,$F30)="","NA",INDEX(Results_Long!$T:$T,$F30)) -> -0.039 | N30: =IF(INDEX(Results_Long!$U:$U,$F30)="","NA",INDEX(Results_Long!$U:$U,$F30)) -> -0.046 | O30: =IF(INDEX(Results_Long!$V:$V,$F30)="","NA",INDEX(Results_Long!$V:$V,$F30)) -> -0.032 | P30: =IF(INDEX(Results_Long!$L:$L,$F30)="","NA",INDEX(Results_Long!$L:$L,$F30)) -> NA | Q30: =IF(INDEX(Results_Long!$M:$M,$F30)="","NA",INDEX(Results_Long!$M:$M,$F30)) -> NA | R30: =IF(INDEX(Results_Long!$N:$N,$F30)="","NA",INDEX(Results_Long!$N:$N,$F30)) -> NA | S30: =IF(INDEX(Results_Long!$O:$O,$F30)="","NA",INDEX(Results_Long!$O:$O,$F30)) -> NA | T30: =IF(INDEX(Results_Long!$AG:$AG,$F30)="","NA",INDEX(Results_Long!$AG:$AG,$F30)) -> NA | U30: =IF(INDEX(Results_Long!$AJ:$AJ,$F30)="","NA",INDEX(Results_Long!$AJ:$AJ,$F30)) -> COE companion STUDY-LEVEL row (Table 3, 75 units; NOT the ES-level -0.041 figure); SE provenance disclosure: COE main model = naive inverse variance at ES level, k = 1,139, no cluster-robust inference; overlap disclosure: 7/120 corpus, 6/115 estimation set, 5/113 period domain; 60/2,713 est ES (2.2%); 0 shared effect sizes [DEC-045/H-Q10]
A32: Interpretation
A33: H8: window means are displayed on both scales; CI/p columns show NA in the descriptive tier by design.
A34: H9: size comparison only. SE provenance disclosure (row note, verbatim): the COE main model is naive inverse-variance at ES level (k = 1,139) without cluster-robust inference; overlap 7/120 corpus, 6/115 estimation set, 5/113 period domain; 60/2,713 ES (2.2%); 0 shared effect sizes.
A35: Companion caveat [project pin]: COE between-study variance is a best-case lower bound (factor ~65 in variance, ~8 in MDE units vs. COD) - any cross-channel comparison must carry this disclosure.
A37: Question | B37: Answer
A38: Why no test in H9? | B38: The two channels differ in inference machinery (naive IV vs. CR2 3L-RVE), unit structure and overlap; a formal contrast would be uninterpretable - N12 was reduced to a descriptive size comparison by author ruling [H-Q10].
A39: Why do some windows lack CIs? | B39: 5-9-cluster windows are descriptive-tier by design [DEC-045 S6]; CR2 small-sample inference below ~10 clusters is not trustworthy (Tipton & Pustejovsky 2015).
A41: Verdict: Mechanical outcome: 21 window means tabulated with tier flags; H9 descriptive comparison tabulated with full SE-provenance disclosure; adjudication deferred to the documented gate-resolution step [DEC-044].

Sheet 10_H10_H11_pcurve_within
A1: TH-a (Block E/H fast frequentist battery) · H10 - conditional p-curve (post cell) · H11 - within-study display (Li et al 2022)
A2: H10: N13 rule, first-reported ES per significant post study, p reconstructed in z-metric. H11: descriptive only, explicitly no p-values [N15].
A3: Run 2026-07-24 22:46 (canonical) · verifier R/06_verify_outputs.R 17/17 PASS · chat artefact check 2026-07-26 18/18 PASS · output/TH_a_results.csv 177x36
A5: Panel row | B5: analysis_id | C5: spec | D5: subset | E5: term | F5: RL row | G5: k_es | H5: k_st | I5: k_cl | J5: est_z | K5: ci_lb_z | L5: ci_ub_z | M5: est_r | N5: ci_lb_r | O5: ci_ub_r | P5: se_z | Q5: t | R5: df | S5: p | T5: value | U5: note (verbatim)
A6: H10 significant post studies (of 31) | B6: H10 | C6: pcurve | D6: defined | E6: count_significant | F6: =SUMPRODUCT((Results_Long!$A$2:$A$178=$B6)*(Results_Long!$B$2:$B$178=$C6)*(Results_Long!$C$2:$C$178=$D6)*(Results_Long!$D$2:$D$178=$E6)*ROW(Results_Long!$A$2:$A$178)) -> 164 | G6: =IF(INDEX(Results_Long!$H:$H,$F6)="","NA",INDEX(Results_Long!$H:$H,$F6)) -> 31 | H6: =IF(INDEX(Results_Long!$I:$I,$F6)="","NA",INDEX(Results_Long!$I:$I,$F6)) -> 31 | I6: =IF(INDEX(Results_Long!$J:$J,$F6)="","NA",INDEX(Results_Long!$J:$J,$F6)) -> 31 | J6: =IF(INDEX(Results_Long!$K:$K,$F6)="","NA",INDEX(Results_Long!$K:$K,$F6)) -> NA | K6: =IF(INDEX(Results_Long!$P:$P,$F6)="","NA",INDEX(Results_Long!$P:$P,$F6)) -> NA | L6: =IF(INDEX(Results_Long!$Q:$Q,$F6)="","NA",INDEX(Results_Long!$Q:$Q,$F6)) -> NA | M6: =IF(INDEX(Results_Long!$T:$T,$F6)="","NA",INDEX(Results_Long!$T:$T,$F6)) -> NA | N6: =IF(INDEX(Results_Long!$U:$U,$F6)="","NA",INDEX(Results_Long!$U:$U,$F6)) -> NA | O6: =IF(INDEX(Results_Long!$V:$V,$F6)="","NA",INDEX(Results_Long!$V:$V,$F6)) -> NA | P6: =IF(INDEX(Results_Long!$L:$L,$F6)="","NA",INDEX(Results_Long!$L:$L,$F6)) -> NA | Q6: =IF(INDEX(Results_Long!$M:$M,$F6)="","NA",INDEX(Results_Long!$M:$M,$F6)) -> NA | R6: =IF(INDEX(Results_Long!$N:$N,$F6)="","NA",INDEX(Results_Long!$N:$N,$F6)) -> NA | S6: =IF(INDEX(Results_Long!$O:$O,$F6)="","NA",INDEX(Results_Long!$O:$O,$F6)) -> NA | T6: =IF(INDEX(Results_Long!$AG:$AG,$F6)="","NA",INDEX(Results_Long!$AG:$AG,$F6)) -> 28 | U6: =IF(INDEX(Results_Long!$AJ:$AJ,$F6)="","NA",INDEX(Results_Long!$AJ:$AJ,$F6)) -> N13 rule [Annex H/DEC-045]: conditional on >= 5 significant study-level post-cell p; selection = first-reported ES per post study (dat_prep row order); p reconstructed as 2*pnorm(-|zi|/sqrt(vi)) (z-metric; converted-r accuracy caveat)
A7: H10 right-skew binomial p | B7: H10 | C7: pcurve | D7: defined | E7: right_skew_binomial | F7: =SUMPRODUCT((Results_Long!$A$2:$A$178=$B7)*(Results_Long!$B$2:$B$178=$C7)*(Results_Long!$C$2:$C$178=$D7)*(Results_Long!$D$2:$D$178=$E7)*ROW(Results_Long!$A$2:$A$178)) -> 165 | G7: =IF(INDEX(Results_Long!$H:$H,$F7)="","NA",INDEX(Results_Long!$H:$H,$F7)) -> NA | H7: =IF(INDEX(Results_Long!$I:$I,$F7)="","NA",INDEX(Results_Long!$I:$I,$F7)) -> 28 | I7: =IF(INDEX(Results_Long!$J:$J,$F7)="","NA",INDEX(Results_Long!$J:$J,$F7)) -> NA | J7: =IF(INDEX(Results_Long!$K:$K,$F7)="","NA",INDEX(Results_Long!$K:$K,$F7)) -> NA | K7: =IF(INDEX(Results_Long!$P:$P,$F7)="","NA",INDEX(Results_Long!$P:$P,$F7)) -> NA | L7: =IF(INDEX(Results_Long!$Q:$Q,$F7)="","NA",INDEX(Results_Long!$Q:$Q,$F7)) -> NA | M7: =IF(INDEX(Results_Long!$T:$T,$F7)="","NA",INDEX(Results_Long!$T:$T,$F7)) -> NA | N7: =IF(INDEX(Results_Long!$U:$U,$F7)="","NA",INDEX(Results_Long!$U:$U,$F7)) -> NA | O7: =IF(INDEX(Results_Long!$V:$V,$F7)="","NA",INDEX(Results_Long!$V:$V,$F7)) -> NA | P7: =IF(INDEX(Results_Long!$L:$L,$F7)="","NA",INDEX(Results_Long!$L:$L,$F7)) -> NA | Q7: =IF(INDEX(Results_Long!$M:$M,$F7)="","NA",INDEX(Results_Long!$M:$M,$F7)) -> NA | R7: =IF(INDEX(Results_Long!$N:$N,$F7)="","NA",INDEX(Results_Long!$N:$N,$F7)) -> NA | S7: =IF(INDEX(Results_Long!$O:$O,$F7)="","NA",INDEX(Results_Long!$O:$O,$F7)) -> NA | T7: =IF(INDEX(Results_Long!$AG:$AG,$F7)="","NA",INDEX(Results_Long!$AG:$AG,$F7)) -> 1.5161932e-06 | U7: =IF(INDEX(Results_Long!$AJ:$AJ,$F7)="","NA",INDEX(Results_Long!$AJ:$AJ,$F7)) -> N13 rule [Annex H/DEC-045]: conditional on >= 5 significant study-level post-cell p; selection = first-reported ES per post study (dat_prep row order); p reconstructed as 2*pnorm(-|zi|/sqrt(vi)) (z-metric; converted-r accuracy caveat); share of significant p < .025: 26/28; one-sided binomial vs 0.5 [Simonsohn et al. 2014]
A8: H10 right-skew Stouffer p | B8: H10 | C8: pcurve | D8: defined | E8: right_skew_stouffer | F8: =SUMPRODUCT((Results_Long!$A$2:$A$178=$B8)*(Results_Long!$B$2:$B$178=$C8)*(Results_Long!$C$2:$C$178=$D8)*(Results_Long!$D$2:$D$178=$E8)*ROW(Results_Long!$A$2:$A$178)) -> 166 | G8: =IF(INDEX(Results_Long!$H:$H,$F8)="","NA",INDEX(Results_Long!$H:$H,$F8)) -> NA | H8: =IF(INDEX(Results_Long!$I:$I,$F8)="","NA",INDEX(Results_Long!$I:$I,$F8)) -> 28 | I8: =IF(INDEX(Results_Long!$J:$J,$F8)="","NA",INDEX(Results_Long!$J:$J,$F8)) -> NA | J8: =IF(INDEX(Results_Long!$K:$K,$F8)="","NA",INDEX(Results_Long!$K:$K,$F8)) -> NA | K8: =IF(INDEX(Results_Long!$P:$P,$F8)="","NA",INDEX(Results_Long!$P:$P,$F8)) -> NA | L8: =IF(INDEX(Results_Long!$Q:$Q,$F8)="","NA",INDEX(Results_Long!$Q:$Q,$F8)) -> NA | M8: =IF(INDEX(Results_Long!$T:$T,$F8)="","NA",INDEX(Results_Long!$T:$T,$F8)) -> NA | N8: =IF(INDEX(Results_Long!$U:$U,$F8)="","NA",INDEX(Results_Long!$U:$U,$F8)) -> NA | O8: =IF(INDEX(Results_Long!$V:$V,$F8)="","NA",INDEX(Results_Long!$V:$V,$F8)) -> NA | P8: =IF(INDEX(Results_Long!$L:$L,$F8)="","NA",INDEX(Results_Long!$L:$L,$F8)) -> NA | Q8: =IF(INDEX(Results_Long!$M:$M,$F8)="","NA",INDEX(Results_Long!$M:$M,$F8)) -> NA | R8: =IF(INDEX(Results_Long!$N:$N,$F8)="","NA",INDEX(Results_Long!$N:$N,$F8)) -> NA | S8: =IF(INDEX(Results_Long!$O:$O,$F8)="","NA",INDEX(Results_Long!$O:$O,$F8)) -> NA | T8: =IF(INDEX(Results_Long!$AG:$AG,$F8)="","NA",INDEX(Results_Long!$AG:$AG,$F8)) -> 2.0586452e-119 | U8: =IF(INDEX(Results_Long!$AJ:$AJ,$F8)="","NA",INDEX(Results_Long!$AJ:$AJ,$F8)) -> N13 rule [Annex H/DEC-045]: conditional on >= 5 significant study-level post-cell p; selection = first-reported ES per post study (dat_prep row order); p reconstructed as 2*pnorm(-|zi|/sqrt(vi)) (z-metric; converted-r accuracy caveat); Stouffer z on pp = p/.05: z = -23.2043; right-skew p = pnorm(z)
A9: H10 flatness vs. 33% power (pp) | B9: H10 | C9: pcurve | D9: defined | E9: flatness_vs_33 | F9: =SUMPRODUCT((Results_Long!$A$2:$A$178=$B9)*(Results_Long!$B$2:$B$178=$C9)*(Results_Long!$C$2:$C$178=$D9)*(Results_Long!$D$2:$D$178=$E9)*ROW(Results_Long!$A$2:$A$178)) -> 167 | G9: =IF(INDEX(Results_Long!$H:$H,$F9)="","NA",INDEX(Results_Long!$H:$H,$F9)) -> NA | H9: =IF(INDEX(Results_Long!$I:$I,$F9)="","NA",INDEX(Results_Long!$I:$I,$F9)) -> 28 | I9: =IF(INDEX(Results_Long!$J:$J,$F9)="","NA",INDEX(Results_Long!$J:$J,$F9)) -> NA | J9: =IF(INDEX(Results_Long!$K:$K,$F9)="","NA",INDEX(Results_Long!$K:$K,$F9)) -> NA | K9: =IF(INDEX(Results_Long!$P:$P,$F9)="","NA",INDEX(Results_Long!$P:$P,$F9)) -> NA | L9: =IF(INDEX(Results_Long!$Q:$Q,$F9)="","NA",INDEX(Results_Long!$Q:$Q,$F9)) -> NA | M9: =IF(INDEX(Results_Long!$T:$T,$F9)="","NA",INDEX(Results_Long!$T:$T,$F9)) -> NA | N9: =IF(INDEX(Results_Long!$U:$U,$F9)="","NA",INDEX(Results_Long!$U:$U,$F9)) -> NA | O9: =IF(INDEX(Results_Long!$V:$V,$F9)="","NA",INDEX(Results_Long!$V:$V,$F9)) -> NA | P9: =IF(INDEX(Results_Long!$L:$L,$F9)="","NA",INDEX(Results_Long!$L:$L,$F9)) -> NA | Q9: =IF(INDEX(Results_Long!$M:$M,$F9)="","NA",INDEX(Results_Long!$M:$M,$F9)) -> NA | R9: =IF(INDEX(Results_Long!$N:$N,$F9)="","NA",INDEX(Results_Long!$N:$N,$F9)) -> NA | S9: =IF(INDEX(Results_Long!$O:$O,$F9)="","NA",INDEX(Results_Long!$O:$O,$F9)) -> NA | T9: =IF(INDEX(Results_Long!$AG:$AG,$F9)="","NA",INDEX(Results_Long!$AG:$AG,$F9)) -> 1 | U9: =IF(INDEX(Results_Long!$AJ:$AJ,$F9)="","NA",INDEX(Results_Long!$AJ:$AJ,$F9)) -> N13 rule [Annex H/DEC-045]: conditional on >= 5 significant study-level post-cell p; selection = first-reported ES per post study (dat_prep row order); p reconstructed as 2*pnorm(-|zi|/sqrt(vi)) (z-metric; converted-r accuracy caveat); NCP_33 = 1.529236685 (= qnorm(.975) - qnorm(2/3)); Stouffer z on pp33: z = -20.0115; flatter-than-33% p = 1 - pnorm(z); pp33 clip share (upper/lower) = 0/9 of 28
A11: Panel row | B11: analysis_id | C11: spec | D11: subset | E11: term | F11: RL row | G11: k_es | H11: k_st | I11: k_cl | J11: est_z | K11: ci_lb_z | L11: ci_ub_z | M11: est_r | N11: ci_lb_r | O11: ci_ub_r | P11: se_z | Q11: t | R11: df | S11: p | T11: value | U11: note (verbatim)
A12: H11 pre mean (12 ES) | B12: H11 | C12: within_study | D12: Li et al (2022) | E12: pre_mean | F12: =SUMPRODUCT((Results_Long!$A$2:$A$178=$B12)*(Results_Long!$B$2:$B$178=$C12)*(Results_Long!$C$2:$C$178=$D12)*(Results_Long!$D$2:$D$178=$E12)*ROW(Results_Long!$A$2:$A$178)) -> 168 | G12: =IF(INDEX(Results_Long!$H:$H,$F12)="","NA",INDEX(Results_Long!$H:$H,$F12)) -> 12 | H12: =IF(INDEX(Results_Long!$I:$I,$F12)="","NA",INDEX(Results_Long!$I:$I,$F12)) -> 1 | I12: =IF(INDEX(Results_Long!$J:$J,$F12)="","NA",INDEX(Results_Long!$J:$J,$F12)) -> 1 | J12: =IF(INDEX(Results_Long!$K:$K,$F12)="","NA",INDEX(Results_Long!$K:$K,$F12)) -> -0.052348083 | K12: =IF(INDEX(Results_Long!$P:$P,$F12)="","NA",INDEX(Results_Long!$P:$P,$F12)) -> NA | L12: =IF(INDEX(Results_Long!$Q:$Q,$F12)="","NA",INDEX(Results_Long!$Q:$Q,$F12)) -> NA | M12: =IF(INDEX(Results_Long!$T:$T,$F12)="","NA",INDEX(Results_Long!$T:$T,$F12)) -> -0.052300318 | N12: =IF(INDEX(Results_Long!$U:$U,$F12)="","NA",INDEX(Results_Long!$U:$U,$F12)) -> NA | O12: =IF(INDEX(Results_Long!$V:$V,$F12)="","NA",INDEX(Results_Long!$V:$V,$F12)) -> NA | P12: =IF(INDEX(Results_Long!$L:$L,$F12)="","NA",INDEX(Results_Long!$L:$L,$F12)) -> NA | Q12: =IF(INDEX(Results_Long!$M:$M,$F12)="","NA",INDEX(Results_Long!$M:$M,$F12)) -> NA | R12: =IF(INDEX(Results_Long!$N:$N,$F12)="","NA",INDEX(Results_Long!$N:$N,$F12)) -> NA | S12: =IF(INDEX(Results_Long!$O:$O,$F12)="","NA",INDEX(Results_Long!$O:$O,$F12)) -> NA | T12: =IF(INDEX(Results_Long!$AG:$AG,$F12)="","NA",INDEX(Results_Long!$AG:$AG,$F12)) -> 0.034291927 | U12: =IF(INDEX(Results_Long!$AJ:$AJ,$F12)="","NA",INDEX(Results_Long!$AJ:$AJ,$F12)) -> N15 within-study display: descriptive only, explicitly NO p-values (single both-period cluster) [DEC-045/H-Q11; DEC-008 partial reopen]; unweighted mean of Fisher-z within cell; value = SD
A13: H11 post mean (5 ES) | B13: H11 | C13: within_study | D13: Li et al (2022) | E13: post_mean | F13: =SUMPRODUCT((Results_Long!$A$2:$A$178=$B13)*(Results_Long!$B$2:$B$178=$C13)*(Results_Long!$C$2:$C$178=$D13)*(Results_Long!$D$2:$D$178=$E13)*ROW(Results_Long!$A$2:$A$178)) -> 169 | G13: =IF(INDEX(Results_Long!$H:$H,$F13)="","NA",INDEX(Results_Long!$H:$H,$F13)) -> 5 | H13: =IF(INDEX(Results_Long!$I:$I,$F13)="","NA",INDEX(Results_Long!$I:$I,$F13)) -> 1 | I13: =IF(INDEX(Results_Long!$J:$J,$F13)="","NA",INDEX(Results_Long!$J:$J,$F13)) -> 1 | J13: =IF(INDEX(Results_Long!$K:$K,$F13)="","NA",INDEX(Results_Long!$K:$K,$F13)) -> -0.016230795 | K13: =IF(INDEX(Results_Long!$P:$P,$F13)="","NA",INDEX(Results_Long!$P:$P,$F13)) -> NA | L13: =IF(INDEX(Results_Long!$Q:$Q,$F13)="","NA",INDEX(Results_Long!$Q:$Q,$F13)) -> NA | M13: =IF(INDEX(Results_Long!$T:$T,$F13)="","NA",INDEX(Results_Long!$T:$T,$F13)) -> -0.01622937 | N13: =IF(INDEX(Results_Long!$U:$U,$F13)="","NA",INDEX(Results_Long!$U:$U,$F13)) -> NA | O13: =IF(INDEX(Results_Long!$V:$V,$F13)="","NA",INDEX(Results_Long!$V:$V,$F13)) -> NA | P13: =IF(INDEX(Results_Long!$L:$L,$F13)="","NA",INDEX(Results_Long!$L:$L,$F13)) -> NA | Q13: =IF(INDEX(Results_Long!$M:$M,$F13)="","NA",INDEX(Results_Long!$M:$M,$F13)) -> NA | R13: =IF(INDEX(Results_Long!$N:$N,$F13)="","NA",INDEX(Results_Long!$N:$N,$F13)) -> NA | S13: =IF(INDEX(Results_Long!$O:$O,$F13)="","NA",INDEX(Results_Long!$O:$O,$F13)) -> NA | T13: =IF(INDEX(Results_Long!$AG:$AG,$F13)="","NA",INDEX(Results_Long!$AG:$AG,$F13)) -> 0.03254926 | U13: =IF(INDEX(Results_Long!$AJ:$AJ,$F13)="","NA",INDEX(Results_Long!$AJ:$AJ,$F13)) -> N15 within-study display: descriptive only, explicitly NO p-values (single both-period cluster) [DEC-045/H-Q11; DEC-008 partial reopen]; unweighted mean of Fisher-z within cell; value = SD
A14: H11 within diff (z-only, descriptive) | B14: H11 | C14: within_study | D14: Li et al (2022) | E14: within_diff | F14: =SUMPRODUCT((Results_Long!$A$2:$A$178=$B14)*(Results_Long!$B$2:$B$178=$C14)*(Results_Long!$C$2:$C$178=$D14)*(Results_Long!$D$2:$D$178=$E14)*ROW(Results_Long!$A$2:$A$178)) -> 170 | G14: =IF(INDEX(Results_Long!$H:$H,$F14)="","NA",INDEX(Results_Long!$H:$H,$F14)) -> 17 | H14: =IF(INDEX(Results_Long!$I:$I,$F14)="","NA",INDEX(Results_Long!$I:$I,$F14)) -> 1 | I14: =IF(INDEX(Results_Long!$J:$J,$F14)="","NA",INDEX(Results_Long!$J:$J,$F14)) -> 1 | J14: =IF(INDEX(Results_Long!$K:$K,$F14)="","NA",INDEX(Results_Long!$K:$K,$F14)) -> 0.036117287 | K14: =IF(INDEX(Results_Long!$P:$P,$F14)="","NA",INDEX(Results_Long!$P:$P,$F14)) -> NA | L14: =IF(INDEX(Results_Long!$Q:$Q,$F14)="","NA",INDEX(Results_Long!$Q:$Q,$F14)) -> NA | M14: =IF(INDEX(Results_Long!$T:$T,$F14)="","NA",INDEX(Results_Long!$T:$T,$F14)) -> NA | N14: =IF(INDEX(Results_Long!$U:$U,$F14)="","NA",INDEX(Results_Long!$U:$U,$F14)) -> NA | O14: =IF(INDEX(Results_Long!$V:$V,$F14)="","NA",INDEX(Results_Long!$V:$V,$F14)) -> NA | P14: =IF(INDEX(Results_Long!$L:$L,$F14)="","NA",INDEX(Results_Long!$L:$L,$F14)) -> NA | Q14: =IF(INDEX(Results_Long!$M:$M,$F14)="","NA",INDEX(Results_Long!$M:$M,$F14)) -> NA | R14: =IF(INDEX(Results_Long!$N:$N,$F14)="","NA",INDEX(Results_Long!$N:$N,$F14)) -> NA | S14: =IF(INDEX(Results_Long!$O:$O,$F14)="","NA",INDEX(Results_Long!$O:$O,$F14)) -> NA | T14: =IF(INDEX(Results_Long!$AG:$AG,$F14)="","NA",INDEX(Results_Long!$AG:$AG,$F14)) -> NA | U14: =IF(INDEX(Results_Long!$AJ:$AJ,$F14)="","NA",INDEX(Results_Long!$AJ:$AJ,$F14)) -> N15 within-study display: descriptive only, explicitly NO p-values (single both-period cluster) [DEC-045/H-Q11; DEC-008 partial reopen]; unweighted mean of Fisher-z within cell; value = SD; post-minus-pre difference of unweighted cell means; z-only, no CI/p by rule
A16: Panel row | B16: analysis_id | C16: spec | D16: subset | E16: term | F16: RL row | G16: df_Satt | H16: value | I16: note (verbatim)
A17: H11 straddle inventory (design) | B17: TH_design | C17: design | D17: defined | E17: h11_straddle_studies | F17: =SUMPRODUCT((Results_Long!$A$2:$A$178=$B17)*(Results_Long!$B$2:$B$178=$C17)*(Results_Long!$C$2:$C$178=$D17)*(Results_Long!$D$2:$D$178=$E17)*ROW(Results_Long!$A$2:$A$178)) -> 177 | G17: =IF(INDEX(Results_Long!$N:$N,$F17)="","NA",INDEX(Results_Long!$N:$N,$F17)) -> NA | H17: =IF(INDEX(Results_Long!$AG:$AG,$F17)="","NA",INDEX(Results_Long!$AG:$AG,$F17)) -> 73 | I17: =IF(INDEX(Results_Long!$AJ:$AJ,$F17)="","NA",INDEX(Results_Long!$AJ:$AJ,$F17)) -> studies with any pp_window_class == 'mixed' on the estimation set (straddle the break) [DEC-045/H-Q11]
A18: H11 pool-across count (design) | B18: TH_design | C18: design | D18: defined | E18: h11_pool_across | F18: =SUMPRODUCT((Results_Long!$A$2:$A$178=$B18)*(Results_Long!$B$2:$B$178=$C18)*(Results_Long!$C$2:$C$178=$D18)*(Results_Long!$D$2:$D$178=$E18)*ROW(Results_Long!$A$2:$A$178)) -> 178 | G18: =IF(INDEX(Results_Long!$N:$N,$F18)="","NA",INDEX(Results_Long!$N:$N,$F18)) -> NA | H18: =IF(INDEX(Results_Long!$AG:$AG,$F18)="","NA",INDEX(Results_Long!$AG:$AG,$F18)) -> 72 | I18: =IF(INDEX(Results_Long!$AJ:$AJ,$F18)="","NA",INDEX(Results_Long!$AJ:$AJ,$F18)) -> straddling studies minus the single within-split study (Li et al 2022) = studies that pool across the break ('Paris blindness' introduction module)
A19: H10 selection rule (design) | B19: TH_design | C19: design | D19: defined | E19: h10_selection_rule | F19: =SUMPRODUCT((Results_Long!$A$2:$A$178=$B19)*(Results_Long!$B$2:$B$178=$C19)*(Results_Long!$C$2:$C$178=$D19)*(Results_Long!$D$2:$D$178=$E19)*ROW(Results_Long!$A$2:$A$178)) -> 176 | G19: =IF(INDEX(Results_Long!$N:$N,$F19)="","NA",INDEX(Results_Long!$N:$N,$F19)) -> NA | H19: =IF(INDEX(Results_Long!$AG:$AG,$F19)="","NA",INDEX(Results_Long!$AG:$AG,$F19)) -> NA | I19: =IF(INDEX(Results_Long!$AJ:$AJ,$F19)="","NA",INDEX(Results_Long!$AJ:$AJ,$F19)) -> first-reported ES per post study = first occurrence in dat_prep row order (pinned) [DEC-045/N13]
A21: Interpretation
A22: H10 is a conditional battery (>= 5 significant post studies required; condition met at 28/31); it speaks to evidential value of the significant post-cell literature, not to the Paris contrast itself.
A23: H11: exactly one study reports own pre- AND post-Paris effect sizes; 73 studies straddle the break, 72 pool across it without period-specific estimates (design rows above).
A24: The H10 flatness pp-value of 1 is a mechanical test outcome (sign-corrected NCP per ERROR_LOG #11), tabulated without verdict language.
A26: Question | B26: Answer
A27: Why reconstruct p-values instead of using reported ones? | B27: Uniform z-metric reconstruction (2*pnorm(-|zi|/sqrt(vi))) avoids heterogeneous rounding/reporting conventions; the converted-r accuracy caveat is carried in the row note [N13].
A28: Why only one within-study contrast? | B28: Inventory fact of the literature: a single study (Li et al 2022) splits its own design at the break - the display motivates the pooled-across-the-break framing module without testing anything [N15].
A30: Verdict: Mechanical outcome: p-curve battery and within-study display tabulated with their design inventories; adjudication deferred to the documented gate-resolution step [DEC-044].

Sheet Results_Long
A1: analysis_id | B1: spec | C1: subset | D1: term | E1: metric | F1: estimator | G1: rho | H1: k_es | I1: k_study | J1: k_cluster | K1: est_z | L1: se_z | M1: t_stat | N1: df | O1: p | P1: ci_lb_z | Q1: ci_ub_z | R1: pi_lb_z | S1: pi_ub_z | T1: est_r | U1: ci_lb_r | V1: ci_ub_r | W1: pi_lb_r | X1: pi_ub_r | Y1: sigma2_cluster | Z1: sigma2_study | AA1: sigma2_esid | AB1: pct_cluster | AC1: pct_study | AD1: pct_esid | AE1: pct_sampling | AF1: typical_v | AG1: value | AH1: ms_input | AI1: ms_label | AJ1: note
A2: E1 | B2: tost_pooled | C2: defined | D2: pooled_mean | E2: Fisher_z | F2: 3LMA-RVE_CR2 | G2: 0.6 | H2: 2713 | I2: 115 | J2: 114 | K2: -0.058646737 | L2: 0.01385655 | M2: -4.2324199 | N2: 111.6718 | O2: 4.7619835e-05 | P2: -0.086102595 | Q2: -0.031190879 | T2: -0.058579592 | U2: -0.085890445 | V2: -0.031180768 | Y2: 0.019745549 | Z2: 1.0209213e-09 | AA2: 0.011883179 | AH2: FALSE | AJ2: rma.mv mods=~ 1; random ~1|cluster_id/study/esid; V blocks within cluster_id, rho=0.6; CR2/Satterthwaite on cluster_id [D31.1/A.2]; domain estimation set 2713/115/114 [DEC-042a]; TH-a refit of T1/A1; verifier identity vs committed output/T1_results.csv at 1e-6 [F65]; 95% CI on this row (TOST rows carry 90%)
A3: E1 | B3: tost_pooled | C3: defined | D3: tost_band_0.070 | E3: Fisher_z | F3: 3LMA-RVE_CR2 | G3: 0.6 | H3: 2713 | I3: 115 | J3: 114 | K3: -0.058646737 | L3: 0.01385655 | N3: 111.6718 | O3: 0.20482591 | P3: -0.081629394 | Q3: -0.035664079 | Y3: 0.019745549 | Z3: 1.0209213e-09 | AA3: 0.011883179 | AG3: 0 | AH3: TRUE | AI3: e1_tost_primary | AJ3: TOST, two one-sided tests each alpha=.05 <=> 90% CI inside band [DEC-045 E-pins]; PRIMARY level band |r| = 0.070 (F27v2) -> z band atanh = 0.070114671; arm p (lower/upper) = 0.204826 / 7.26341e-16; TOST p = max(arms); CI columns carry the 90% CI (TOST convention); value = 1{90%-CI inside band} (mechanical flag, no verdict language); ex-ante expectation [DEC-044/DEC-045]: this arm is expected to FAIL (T1 CI edge -0.086); E2 adjudicates Tier 1; E1 calibrates the Tier-2 wording only
A4: E1 | B4: tost_pooled | C4: defined | D4: tost_band_0.050 | E4: Fisher_z | F4: 3LMA-RVE_CR2 | G4: 0.6 | H4: 2713 | I4: 115 | J4: 114 | K4: -0.058646737 | L4: 0.01385655 | N4: 111.6718 | O4: 0.73206958 | P4: -0.081629394 | Q4: -0.035664079 | Y4: 0.019745549 | Z4: 1.0209213e-09 | AA4: 0.011883179 | AG4: 0 | AH4: FALSE | AJ4: TOST, two one-sided tests each alpha=.05 <=> 90% CI inside band [DEC-045 E-pins]; SECONDARY level band |r| = 0.05 -> z band atanh = 0.050041729; arm p (lower/upper) = 0.73207 / 1.41843e-12; TOST p = max(arms); CI columns carry the 90% CI (TOST convention); value = 1{90%-CI inside band} (mechanical flag, no verdict language)
A5: E2 | B5: tost_paris | C5: defined | D5: cell_pre | E5: Fisher_z | F5: 3LMA-RVE_CR2 | G5: 0.6 | H5: 1994 | I5: 83 | J5: 82 | K5: -0.061599157 | L5: 0.018046114 | M5: -3.4134304 | N5: 68.597113 | O5: 0.0010804696 | P5: -0.097603942 | Q5: -0.025594371 | T5: -0.061521363 | U5: -0.097295177 | V5: -0.025588783 | Y5: 0.020466604 | Z5: 1.8647279e-09 | AA5: 0.011878551 | AH5: FALSE | AJ5: rma.mv mods=~ 0 + pp_cell (cell-means; estimand identical to ~ pp_mid_lag0); random ~1|cluster_id/study/esid; V blocks within cluster_id, rho=0.6; CR2/Satterthwaite on cluster_id [D31.1/A.2]; domain period domain 2705/113/112 [DEC-042b]; cell mean at coding = 0 (pre)
A6: E2 | B6: tost_paris | C6: defined | D6: cell_post | E6: Fisher_z | F6: 3LMA-RVE_CR2 | G6: 0.6 | H6: 711 | I6: 31 | J6: 31 | K6: -0.05142325 | L6: 0.010329352 | M6: -4.9783615 | N6: 19.756715 | O6: 7.4752952e-05 | P6: -0.072986923 | Q6: -0.029859576 | T6: -0.051377971 | U6: -0.072857596 | V6: -0.029850705 | Y6: 0.020466604 | Z6: 1.8647279e-09 | AA6: 0.011878551 | AH6: FALSE | AJ6: rma.mv mods=~ 0 + pp_cell (cell-means; estimand identical to ~ pp_mid_lag0); random ~1|cluster_id/study/esid; V blocks within cluster_id, rho=0.6; CR2/Satterthwaite on cluster_id [D31.1/A.2]; domain period domain 2705/113/112 [DEC-042b]; cell mean at coding = 1 (post)
A7: E2 | B7: tost_paris | C7: defined | D7: diff | E7: Fisher_z | F7: 3LMA-RVE_CR2 | G7: 0.6 | H7: 2705 | I7: 113 | J7: 112 | K7: 0.010175907 | L7: 0.018107282 | M7: 0.56197868 | N7: 14.992066 | O7: 0.58243573 | P7: -0.028420631 | Q7: 0.048772445 | Y7: 0.020466604 | Z7: 1.8647279e-09 | AA7: 0.011878551 | AH7: FALSE | AJ7: rma.mv mods=~ 0 + pp_cell (cell-means; estimand identical to ~ pp_mid_lag0); random ~1|cluster_id/study/esid; V blocks within cluster_id, rho=0.6; CR2/Satterthwaite on cluster_id [D31.1/A.2]; domain period domain 2705/113/112 [DEC-042b]; post-minus-pre contrast (-1, +1); cell-means parameterization [DEC-031e/A.11]; difference of Fisher-z means; no tanh transform of differences; TH-a refit of T2/B1 paris_mid; verifier identity vs committed output/T2_results.csv at 1e-6 [F65]
A8: E2 | B8: tost_paris | C8: defined | D8: tost_band_0.050 | E8: Fisher_z | F8: 3LMA-RVE_CR2 | G8: 0.6 | H8: 2705 | I8: 113 | J8: 112 | K8: 0.010175907 | L8: 0.018107282 | N8: 14.992066 | O8: 0.02197985 | P8: -0.021568174 | Q8: 0.041919988 | Y8: 0.020466604 | Z8: 1.8647279e-09 | AA8: 0.011878551 | AG8: 1 | AH8: TRUE | AI8: e2_tost_contrast | AJ8: TOST, two one-sided tests each alpha=.05 <=> 90% CI inside band [DEC-045 E-pins]; contrast band |dr| = 0.05 (secondary SESOI = the contrast band [DEC-031 Block E]); applied on the z-difference directly; |dz| read as |dr| (third-order approx, T8/B8 convention); arm p (lower/upper) = 0.00231753 / 0.0219798; TOST p = max(arms); CI columns carry the 90% CI (TOST convention); value = 1{90%-CI inside band} (mechanical flag, no verdict language); E2 adjudicates Tier 1 (the Paris null) [DEC-045 E-pins]; dose transfer NOT triggered (design df 31.9 [DEC-024/A.3])
A9: E3 | B9: gate | C9: defined | D9: config_e2_requirement | E9: count | F9: descriptive | AH9: FALSE | AJ9: Tier-1 evidence-of-absence wording REQUIRES an E2 PASS; E2 FAIL -> no Tier-1 EoA regardless of BF [DEC-045 ladder / H-Q21]
A10: E3 | B10: gate | C10: defined | D10: config_bf_ladder | E10: count | F10: descriptive | AH10: FALSE | AJ10: with H2b: BF01 >= 3 full EoA; 1 < BF01 < 3 equivalence-based, BF disclosed as directionally supportive, not strong; BF01 <= 1 conflict disclosure, conservative wording; without RoBMA.reg: pre-registered configuration E2 + level BF (H2a) [DEC-045; Jeffreys/Lee-Wagenmakers bands pinned]
A11: E3 | B11: gate | C11: defined | D11: status | E11: count | F11: descriptive | AH11: FALSE | AJ11: resolution deferred: documented post-run step after TH-b (N3), never an automatic rewrite [DEC-044/DEC-045]; ex-ante expectation carried on the E1 primary-band row
A12: H4 | B12: break_2008 | C12: defined | D12: break | E12: Fisher_z | F12: 3LMA-RVE_CR2 | G12: 0.6 | H12: 2705 | I12: 113 | J12: 112 | K12: -0.024026676 | L12: 0.0176243 | M12: -1.3632698 | N12: 14.942101 | O12: 0.19298764 | P12: -0.061604665 | Q12: 0.013551313 | Y12: 0.020430519 | Z12: 2.8698897e-09 | AA12: 0.01187772 | AH12: FALSE | AJ12: rma.mv mods=~ 0 + pp_cell (break 2008, cell-means); random ~1|cluster_id/study/esid; V blocks within cluster_id, rho=0.6; CR2/Satterthwaite on cluster_id [D31.1/A.2]; domain period domain 2705/113/112; post cell: 2367 ES / 100 studies / 99 clusters; rule: share_2008 >= 0.5, ties to Post [F60/DEC-024]; candidate year of the sup-break grid [DEC-045/H-Q6]; difference of Fisher-z means
A13: H4 | B13: break_2009 | C13: defined | D13: break | E13: Fisher_z | F13: 3LMA-RVE_CR2 | G13: 0.6 | H13: 2705 | I13: 113 | J13: 112 | K13: -0.039526755 | L13: 0.018622444 | M13: -2.1225332 | N13: 6.2816543 | O13: 0.075948862 | P13: -0.084603525 | Q13: 0.0055500143 | Y13: 0.020411456 | Z13: 2.3469329e-09 | AA13: 0.011872655 | AH13: FALSE | AJ13: rma.mv mods=~ 0 + pp_cell (break 2009, cell-means); random ~1|cluster_id/study/esid; V blocks within cluster_id, rho=0.6; CR2/Satterthwaite on cluster_id [D31.1/A.2]; domain period domain 2705/113/112; post cell: 2345 ES / 99 studies / 98 clusters; rule: share_2009 >= 0.5, ties to Post [F60/DEC-024]; candidate year of the sup-break grid [DEC-045/H-Q6]; difference of Fisher-z means
A14: H4 | B14: break_2010 | C14: defined | D14: break | E14: Fisher_z | F14: 3LMA-RVE_CR2 | G14: 0.6 | H14: 2705 | I14: 113 | J14: 112 | K14: -0.036534391 | L14: 0.019295162 | M14: -1.8934483 | N14: 6.7804765 | O14: 0.10152293 | P14: -0.082461362 | Q14: 0.0093925811 | Y14: 0.020438618 | Z14: 3.0723396e-09 | AA14: 0.011873276 | AH14: FALSE | AJ14: rma.mv mods=~ 0 + pp_cell (break 2010, cell-means); random ~1|cluster_id/study/esid; V blocks within cluster_id, rho=0.6; CR2/Satterthwaite on cluster_id [D31.1/A.2]; domain period domain 2705/113/112; post cell: 2326 ES / 98 studies / 97 clusters; rule: share_2010 >= 0.5, ties to Post [F60/DEC-024]; candidate year of the sup-break grid [DEC-045/H-Q6]; difference of Fisher-z means
A15: H4 | B15: break_2011 | C15: defined | D15: break | E15: Fisher_z | F15: 3LMA-RVE_CR2 | G15: 0.6 | H15: 2705 | I15: 113 | J15: 112 | K15: -0.033330835 | L15: 0.018895156 | M15: -1.7639884 | N15: 9.5644089 | O15: 0.10957911 | P15: -0.075693221 | Q15: 0.0090315501 | Y15: 0.0204456 | Z15: 2.6142793e-09 | AA15: 0.011873027 | AH15: FALSE | AJ15: rma.mv mods=~ 0 + pp_cell (break 2011, cell-means); random ~1|cluster_id/study/esid; V blocks within cluster_id, rho=0.6; CR2/Satterthwaite on cluster_id [D31.1/A.2]; domain period domain 2705/113/112; post cell: 2077 ES / 93 studies / 92 clusters; rule: share_2011 >= 0.5, ties to Post [F60/DEC-024]; candidate year of the sup-break grid [DEC-045/H-Q6]; difference of Fisher-z means
A16: H4 | B16: break_2012 | C16: defined | D16: break | E16: Fisher_z | F16: 3LMA-RVE_CR2 | G16: 0.6 | H16: 2705 | I16: 113 | J16: 112 | K16: -0.00094643433 | L16: 0.017128675 | M16: -0.055254382 | N16: 11.660405 | O16: 0.95687124 | P16: -0.038387516 | Q16: 0.036494647 | Y16: 0.02042065 | Z16: 2.1839896e-09 | AA16: 0.011880304 | AH16: FALSE | AJ16: rma.mv mods=~ 0 + pp_cell (break 2012, cell-means); random ~1|cluster_id/study/esid; V blocks within cluster_id, rho=0.6; CR2/Satterthwaite on cluster_id [D31.1/A.2]; domain period domain 2705/113/112; post cell: 1769 ES / 82 studies / 81 clusters; rule: share_2012 >= 0.5, ties to Post [F60/DEC-024]; candidate year of the sup-break grid [DEC-045/H-Q6]; difference of Fisher-z means
A17: H4 | B17: break_2013 | C17: defined | D17: break | E17: Fisher_z | F17: 3LMA-RVE_CR2 | G17: 0.6 | H17: 2705 | I17: 113 | J17: 112 | K17: 0.025954305 | L17: 0.021560617 | M17: 1.203783 | N17: 14.28239 | O17: 0.24824616 | P17: -0.020202989 | Q17: 0.072111598 | Y17: 0.020221383 | Z17: 2.9251783e-09 | AA17: 0.011879308 | AH17: FALSE | AJ17: rma.mv mods=~ 0 + pp_cell (break 2013, cell-means); random ~1|cluster_id/study/esid; V blocks within cluster_id, rho=0.6; CR2/Satterthwaite on cluster_id [D31.1/A.2]; domain period domain 2705/113/112; post cell: 1486 ES / 69 studies / 69 clusters; rule: share_2013 >= 0.5, ties to Post [F60/DEC-024]; candidate year of the sup-break grid [DEC-045/H-Q6]; difference of Fisher-z means
A18: H4 | B18: break_2014 | C18: defined | D18: break | E18: Fisher_z | F18: 3LMA-RVE_CR2 | G18: 0.6 | H18: 2705 | I18: 113 | J18: 112 | K18: 0.023149446 | L18: 0.022786093 | M18: 1.0159463 | N18: 22.565949 | O18: 0.32042466 | P18: -0.024037398 | Q18: 0.070336289 | Y18: 0.020387974 | Z18: 2.3881269e-09 | AA18: 0.011877073 | AH18: FALSE | AJ18: rma.mv mods=~ 0 + pp_cell (break 2014, cell-means); random ~1|cluster_id/study/esid; V blocks within cluster_id, rho=0.6; CR2/Satterthwaite on cluster_id [D31.1/A.2]; domain period domain 2705/113/112; post cell: 1269 ES / 55 studies / 55 clusters; rule: share_2014 >= 0.5, ties to Post [F60/DEC-024]; candidate year of the sup-break grid [DEC-045/H-Q6]; difference of Fisher-z means
A19: H4 | B19: break_2015 | C19: defined | D19: break | E19: Fisher_z | F19: 3LMA-RVE_CR2 | G19: 0.6 | H19: 2705 | I19: 113 | J19: 112 | K19: 0.0023798646 | L19: 0.020323441 | M19: 0.11709949 | N19: 18.166087 | O19: 0.90806615 | P19: -0.040290136 | Q19: 0.045049866 | Y19: 0.020456037 | Z19: 1.8919627e-09 | AA19: 0.011879431 | AH19: FALSE | AJ19: rma.mv mods=~ 0 + pp_cell (break 2015, cell-means); random ~1|cluster_id/study/esid; V blocks within cluster_id, rho=0.6; CR2/Satterthwaite on cluster_id [D31.1/A.2]; domain period domain 2705/113/112; post cell: 784 ES / 38 studies / 38 clusters; rule: share_2015 >= 0.5, ties to Post [F60/DEC-024]; candidate year of the sup-break grid [DEC-045/H-Q6]; difference of Fisher-z means
A20: H4 | B20: break_2016 | C20: defined | D20: break | E20: Fisher_z | F20: 3LMA-RVE_CR2 | G20: 0.6 | H20: 2705 | I20: 113 | J20: 112 | K20: 0.010175907 | L20: 0.018107282 | M20: 0.56197868 | N20: 14.992066 | O20: 0.58243573 | P20: -0.028420631 | Q20: 0.048772445 | Y20: 0.020466604 | Z20: 1.8647279e-09 | AA20: 0.011878551 | AH20: FALSE | AJ20: rma.mv mods=~ 0 + pp_cell (break 2016, cell-means); random ~1|cluster_id/study/esid; V blocks within cluster_id, rho=0.6; CR2/Satterthwaite on cluster_id [D31.1/A.2]; domain period domain 2705/113/112; post cell: 711 ES / 31 studies / 31 clusters; rule: share_2016 >= 0.5, ties to Post [F60/DEC-024]; candidate year of the sup-break grid [DEC-045/H-Q6]; difference of Fisher-z means
A21: H4 | B21: break_2017 | C21: defined | D21: break | E21: Fisher_z | F21: 3LMA-RVE_CR2 | G21: 0.6 | H21: 2705 | I21: 113 | J21: 112 | K21: 0.0080340694 | L21: 0.018000133 | M21: 0.4463339 | N21: 10.852183 | O21: 0.6641308 | P21: -0.031649894 | Q21: 0.047718033 | Y21: 0.020455773 | Z21: 2.7537703e-09 | AA21: 0.011879083 | AH21: FALSE | AJ21: rma.mv mods=~ 0 + pp_cell (break 2017, cell-means); random ~1|cluster_id/study/esid; V blocks within cluster_id, rho=0.6; CR2/Satterthwaite on cluster_id [D31.1/A.2]; domain period domain 2705/113/112; post cell: 623 ES / 23 studies / 23 clusters; rule: share_2017 >= 0.5, ties to Post [F60/DEC-024]; candidate year of the sup-break grid [DEC-045/H-Q6]; difference of Fisher-z means
A22: H4 | B22: break_2018 | C22: defined | D22: break | E22: Fisher_z | F22: 3LMA-RVE_CR2 | G22: 0.6 | H22: 2705 | I22: 113 | J22: 112 | K22: 0.0031230426 | L22: 0.022238266 | M22: 0.14043553 | N22: 18.776144 | O22: 0.88981151 | P22: -0.04345977 | Q22: 0.049705855 | Y22: 0.020509643 | Z22: 2.0381968e-09 | AA22: 0.011878095 | AH22: FALSE | AJ22: rma.mv mods=~ 0 + pp_cell (break 2018, cell-means); random ~1|cluster_id/study/esid; V blocks within cluster_id, rho=0.6; CR2/Satterthwaite on cluster_id [D31.1/A.2]; domain period domain 2705/113/112; post cell: 506 ES / 15 studies / 15 clusters; rule: share_2018 >= 0.5, ties to Post [F60/DEC-024]; candidate year of the sup-break grid [DEC-045/H-Q6]; difference of Fisher-z means
A23: H4 | B23: break_2019 | C23: defined | D23: break | E23: Fisher_z | F23: 3LMA-RVE_CR2 | G23: 0.6 | H23: 2705 | I23: 113 | J23: 112 | K23: 0.0042056666 | L23: 0.022784454 | M23: 0.18458491 | N23: 15.443904 | O23: 0.85595667 | P23: -0.044236954 | Q23: 0.052648287 | Y23: 0.020509233 | Z23: 1.2185734e-09 | AA23: 0.011878085 | AH23: FALSE | AJ23: rma.mv mods=~ 0 + pp_cell (break 2019, cell-means); random ~1|cluster_id/study/esid; V blocks within cluster_id, rho=0.6; CR2/Satterthwaite on cluster_id [D31.1/A.2]; domain period domain 2705/113/112; post cell: 323 ES / 13 studies / 13 clusters; rule: share_2019 >= 0.5, ties to Post [F60/DEC-024]; candidate year of the sup-break grid [DEC-045/H-Q6]; difference of Fisher-z means
A24: H4 | B24: sup_break | C24: defined | D24: observed_sup | E24: rank | F24: 3LMA-RVE_CR2 | G24: 0.6 | H24: 2705 | I24: 113 | J24: 112 | AG24: 2.1225332 | AH24: TRUE | AI24: h4_sup_observed | AJ24: sup |t| over the ADMISSIBLE candidate years (df >= 5 on the break coefficient [DEC-024 transfer rule / H-Q6]); attained at 2009; admissible set computed ONCE on the observed design and held fixed for the TH-c permutation [H-Q20]; |t| by year: 2008=1.3633(df 14.9), 2009=2.1225(df 6.3), 2010=1.8934(df 6.8), 2011=1.7640(df 9.6), 2012=0.0553(df 11.7), 2013=1.2038(df 14.3), 2014=1.0159(df 22.6), 2015=0.1171(df 18.2), 2016=0.5620(df 15.0), 2017=0.4463(df 10.9), 2018=0.1404(df 18.8), 2019=0.1846(df 15.4); p_perm from TH-c
A25: H6 | B25: zarea_transplant | C25: defined | D25: cell_pre | E25: Fisher_z | F25: 3LMA-RVE_CR2 | G25: 0.6 | H25: 1994 | I25: 83 | J25: 82 | K25: -0.061822115 | L25: 0.018152136 | M25: -3.4057763 | N25: 69.836894 | O25: 0.0010975022 | P25: -0.098026895 | Q25: -0.025617335 | T25: -0.061743474 | U25: -0.097714108 | V25: -0.025611733 | Y25: 0.021659327 | Z25: 2.0461748e-09 | AA25: 0.012025016 | AH25: FALSE | AJ25: rma.mv mods=~ 0 + pp_cell (midpoint rule, ties EXCLUDED); random ~1|cluster_id/study/esid; V blocks within cluster_id, rho=0.6; CR2/Satterthwaite on cluster_id [D31.1/A.2]; domain tie-excluded domain 2626/108/107 (79 tie ES / 5 studies / 5 clusters at sample_mid = 2015.5 removed [DEC-045/H-Q8]); cell mean at coding = 0 (pre)
A26: H6 | B26: zarea_transplant | C26: defined | D26: cell_post | E26: Fisher_z | F26: 3LMA-RVE_CR2 | G26: 0.6 | H26: 632 | I26: 26 | J26: 26 | K26: -0.05123144 | L26: 0.011479554 | M26: -4.4628425 | N26: 15.370101 | O26: 0.00043074667 | P26: -0.075648314 | Q26: -0.026814566 | T26: -0.051186665 | U26: -0.07550434 | V26: -0.026808141 | Y26: 0.021659327 | Z26: 2.0461748e-09 | AA26: 0.012025016 | AH26: FALSE | AJ26: rma.mv mods=~ 0 + pp_cell (midpoint rule, ties EXCLUDED); random ~1|cluster_id/study/esid; V blocks within cluster_id, rho=0.6; CR2/Satterthwaite on cluster_id [D31.1/A.2]; domain tie-excluded domain 2626/108/107 (79 tie ES / 5 studies / 5 clusters at sample_mid = 2015.5 removed [DEC-045/H-Q8]); cell mean at coding = 1 (post)
A27: H6 | B27: zarea_transplant | C27: defined | D27: diff | E27: Fisher_z | F27: 3LMA-RVE_CR2 | G27: 0.6 | H27: 2626 | I27: 108 | J27: 107 | K27: 0.010590675 | L27: 0.018297042 | M27: 0.57881899 | N27: 11.567172 | O27: 0.57380956 | P27: -0.02944123 | Q27: 0.050622581 | Y27: 0.021659327 | Z27: 2.0461748e-09 | AA27: 0.012025016 | AH27: TRUE | AI27: h6_zarea_diff | AJ27: rma.mv mods=~ 0 + pp_cell (midpoint rule, ties EXCLUDED); random ~1|cluster_id/study/esid; V blocks within cluster_id, rho=0.6; CR2/Satterthwaite on cluster_id [D31.1/A.2]; domain tie-excluded domain 2626/108/107 (79 tie ES / 5 studies / 5 clusters at sample_mid = 2015.5 removed [DEC-045/H-Q8]); post-minus-pre contrast (-1, +1); cell-means parameterization [DEC-031e/A.11]; difference of Fisher-z means; no tanh transform of differences; under Zarea's Paris operationalization (midpoint + tie-exclusion), applied within our 3L-RVE framework [DEC-045 wording pin]; post cell 31 -> 26 studies under the tie-exclusion rule
A28: H7 | B28: cumulative | C28: Nandy, Lodh (2012) | D28: step_001 | E28: Fisher_z | F28: 3LMA-RVE_CR2 | G28: 0.6 | H28: 6 | I28: 1 | J28: 1 | AH28: FALSE | AJ28: cumulative 3L refit after adding study 'Nandy, Lodh (2012)' (median sample_mid = 1998.50); ordering: study-wise median sample_mid, ties alphabetical [DEC-045/H-Q17]; not_estimable: Cluster-robust variance estimation will not work when the data only includes a single cluster.; planned key retained (budget 177) [DEC-045; package-review robustness fix 2026-07-22 + runtime fix 2026-07-24]
A29: H7 | B29: cumulative | C29: Chava (2010) | D29: step_002 | E29: Fisher_z | F29: 3LMA-RVE_CR2 | G29: 0.6 | H29: 56 | I29: 2 | J29: 2 | K29: -0.0072015185 | L29: 0.014662319 | M29: -0.49115821 | N29: 1.0054808 | O29: 0.7089959 | P29: -0.19112123 | Q29: 0.1767182 | T29: -0.007201394 | U29: -0.18882769 | V29: 0.17490129 | Y29: 0.00017930258 | Z29: 0.00017930258 | AA29: 0.00040593621 | AH29: FALSE | AJ29: cumulative 3L refit after adding study 'Chava (2010)' (median sample_mid = 1999.00); ordering: study-wise median sample_mid, ties alphabetical [DEC-045/H-Q17]; display floor: point-only in the figure (clusters = 2 < 10) [DEC-045/H-Q17; presentational only, CI retained here]
A30: H7 | B30: cumulative | C30: Schneider (2010) | D30: step_003 | E30: Fisher_z | F30: 3LMA-RVE_CR2 | G30: 0.6 | H30: 66 | I30: 3 | J30: 3 | K30: -0.018552883 | L30: 0.0049557972 | M30: -3.7436728 | N30: 1.1791658 | O30: 0.13586355 | P30: -0.062860906 | Q30: 0.02575514 | T30: -0.018550755 | U30: -0.062778239 | V30: 0.025749447 | Y30: 4.4198122e-12 | Z30: 4.4198139e-12 | AA30: 0.012751442 | AH30: FALSE | AJ30: cumulative 3L refit after adding study 'Schneider (2010)' (median sample_mid = 1999.00); ordering: study-wise median sample_mid, ties alphabetical [DEC-045/H-Q17]; display floor: point-only in the figure (clusters = 3 < 10) [DEC-045/H-Q17; presentational only, CI retained here]
A31: H7 | B31: cumulative | C31: Chava (2014) | D31: step_004 | E31: Fisher_z | F31: 3LMA-RVE_CR2 | G31: 0.6 | H31: 88 | I31: 4 | J31: 4 | K31: -0.018932757 | L31: 0.003105035 | M31: -6.0974374 | N31: 1.4945754 | O31: 0.049404297 | P31: -0.037709965 | Q31: -0.00015554801 | T31: -0.018930495 | U31: -0.0376921 | V31: -0.00015554801 | Y31: 2.279936e-12 | Z31: 2.279936e-12 | AA31: 0.0081442559 | AH31: FALSE | AJ31: cumulative 3L refit after adding study 'Chava (2014)' (median sample_mid = 1999.50); ordering: study-wise median sample_mid, ties alphabetical [DEC-045/H-Q17]; display floor: point-only in the figure (clusters = 4 < 10) [DEC-045/H-Q17; presentational only, CI retained here]
A32: H7 | B32: cumulative | C32: Oikonomou et al (2014) | D32: step_005 | E32: Fisher_z | F32: 3LMA-RVE_CR2 | G32: 0.6 | H32: 93 | I32: 5 | J32: 5 | K32: -0.019043497 | L32: 0.0028442398 | M32: -6.6954611 | N32: 1.8985222 | O32: 0.024628536 | P32: -0.031929988 | Q32: -0.0061570055 | T32: -0.019041195 | U32: -0.031919141 | V32: -0.0061569277 | Y32: 1.854757e-12 | Z32: 1.8547563e-12 | AA32: 0.0075314357 | AH32: FALSE | AJ32: cumulative 3L refit after adding study 'Oikonomou et al (2014)' (median sample_mid = 2000.00); ordering: study-wise median sample_mid, ties alphabetical [DEC-045/H-Q17]; display floor: point-only in the figure (clusters = 5 < 10) [DEC-045/H-Q17; presentational only, CI retained here]
A33: H7 | B33: cumulative | C33: Bauer, Hann (2010) | D33: step_006 | E33: Fisher_z | F33: 3LMA-RVE_CR2 | G33: 0.6 | H33: 259 | I33: 6 | J33: 6 | K33: -0.014547589 | L33: 0.004138091 | M33: -3.5155313 | N33: 2.9654357 | O33: 0.039763828 | P33: -0.027804105 | Q33: -0.0012910721 | T33: -0.014546562 | U33: -0.027796942 | V33: -0.0012910714 | Y33: 3.5616041e-12 | Z33: 3.561603e-12 | AA33: 0.001938875 | AH33: FALSE | AJ33: cumulative 3L refit after adding study 'Bauer, Hann (2010)' (median sample_mid = 2000.50); ordering: study-wise median sample_mid, ties alphabetical [DEC-045/H-Q17]; display floor: point-only in the figure (clusters = 6 < 10) [DEC-045/H-Q17; presentational only, CI retained here]
A34: H7 | B34: cumulative | C34: Ge, Liu (2015) | D34: step_007 | E34: Fisher_z | F34: 3LMA-RVE_CR2 | G34: 0.6 | H34: 263 | I34: 7 | J34: 7 | K34: -0.016967173 | L34: 0.0044253637 | M34: -3.8340742 | N34: 3.510897 | O34: 0.023584393 | P34: -0.029959356 | Q34: -0.0039749903 | T34: -0.016965545 | U34: -0.029950396 | V34: -0.0039749694 | Y34: 4.1470595e-12 | Z34: 4.1470587e-12 | AA34: 0.0019161162 | AH34: FALSE | AJ34: cumulative 3L refit after adding study 'Ge, Liu (2015)' (median sample_mid = 2000.50); ordering: study-wise median sample_mid, ties alphabetical [DEC-045/H-Q17]; display floor: point-only in the figure (clusters = 7 < 10) [DEC-045/H-Q17; presentational only, CI retained here]
A35: H7 | B35: cumulative | C35: Jiraporn et al (2014) | D35: step_008 | E35: Fisher_z | F35: 3LMA-RVE_CR2 | G35: 0.6 | H35: 264 | I35: 8 | J35: 8 | K35: -0.017343621 | L35: 0.0043890541 | M35: -3.9515625 | N35: 3.6574978 | O35: 0.019951466 | P35: -0.029993099 | Q35: -0.0046941438 | T35: -0.017341883 | U35: -0.029984109 | V35: -0.0046941093 | Y35: 3.8958678e-12 | Z35: 3.8958672e-12 | AA35: 0.0019063775 | AH35: FALSE | AJ35: cumulative 3L refit after adding study 'Jiraporn et al (2014)' (median sample_mid = 2001.00); ordering: study-wise median sample_mid, ties alphabetical [DEC-045/H-Q17]; display floor: point-only in the figure (clusters = 8 < 10) [DEC-045/H-Q17; presentational only, CI retained here]
A36: H7 | B36: cumulative | C36: Chen et al (2020) | D36: step_009 | E36: Fisher_z | F36: 3LMA-RVE_CR2 | G36: 0.6 | H36: 312 | I36: 9 | J36: 9 | K36: -0.01487142 | L36: 0.0036812778 | M36: -4.039744 | N36: 4.277715 | O36: 0.013640022 | P36: -0.024835838 | Q36: -0.0049070021 | T36: -0.014870324 | U36: -0.024830733 | V36: -0.0049069627 | Y36: 3.2384722e-12 | Z36: 3.2384684e-12 | AA36: 0.001878952 | AH36: FALSE | AJ36: cumulative 3L refit after adding study 'Chen et al (2020)' (median sample_mid = 2001.50); ordering: study-wise median sample_mid, ties alphabetical [DEC-045/H-Q17]; display floor: point-only in the figure (clusters = 9 < 10) [DEC-045/H-Q17; presentational only, CI retained here]
A37: H7 | B37: cumulative | C37: Chen, Gao (2011) | D37: step_010 | E37: Fisher_z | F37: 3LMA-RVE_CR2 | G37: 0.6 | H37: 316 | I37: 10 | J37: 10 | K37: -0.015354927 | L37: 0.0036193689 | M37: -4.242432 | N37: 4.3108577 | O37: 0.011272897 | P37: -0.025124475 | Q37: -0.0055853785 | T37: -0.01535372 | U37: -0.025119189 | V37: -0.0055853205 | Y37: 2.8267928e-12 | Z37: 2.826792e-12 | AA37: 0.0019697966 | AH37: FALSE | AJ37: cumulative 3L refit after adding study 'Chen, Gao (2011)' (median sample_mid = 2005.00); ordering: study-wise median sample_mid, ties alphabetical [DEC-045/H-Q17]; full display (CI band)
A38: H7 | B38: cumulative | C38: Chodnicka-Jaworska (2022) | D38: step_011 | E38: Fisher_z | F38: 3LMA-RVE_CR2 | G38: 0.6 | H38: 326 | I38: 11 | J38: 11 | K38: -0.016859844 | L38: 0.003061245 | M38: -5.5075122 | N38: 4.501777 | O38: 0.0037294 | P38: -0.024998329 | Q38: -0.0087213592 | T38: -0.016858247 | U38: -0.024993123 | V38: -0.0087211381 | Y38: 3.3238466e-12 | Z38: 3.3238472e-12 | AA38: 0.0026523194 | AH38: FALSE | AJ38: cumulative 3L refit after adding study 'Chodnicka-Jaworska (2022)' (median sample_mid = 2005.50); ordering: study-wise median sample_mid, ties alphabetical [DEC-045/H-Q17]; full display (CI band)
A39: H7 | B39: cumulative | C39: Erragragui (2018) | D39: step_012 | E39: Fisher_z | F39: 3LMA-RVE_CR2 | G39: 0.6 | H39: 330 | I39: 12 | J39: 12 | K39: -0.018018411 | L39: 0.0033811337 | M39: -5.3291033 | N39: 4.7944537 | O39: 0.0035333549 | P39: -0.026823171 | Q39: -0.0092136498 | T39: -0.018016461 | U39: -0.02681674 | V39: -0.0092133891 | Y39: 3.1448736e-12 | Z39: 3.1448747e-12 | AA39: 0.002617632 | AH39: FALSE | AJ39: cumulative 3L refit after adding study 'Erragragui (2018)' (median sample_mid = 2005.50); ordering: study-wise median sample_mid, ties alphabetical [DEC-045/H-Q17]; full display (CI band)
A40: H7 | B40: cumulative | C40: Zheng (2021) | D40: step_013 | E40: Fisher_z | F40: 3LMA-RVE_CR2 | G40: 0.6 | H40: 338 | I40: 13 | J40: 13 | K40: -0.021172504 | L40: 0.004921243 | M40: -4.3022675 | N40: 5.5368831 | O40: 0.0061075546 | P40: -0.033462767 | Q40: -0.0088822403 | T40: -0.02116934 | U40: -0.033450282 | V40: -0.0088820068 | Y40: 2.8092038e-11 | Z40: 2.8092032e-11 | AA40: 0.002576339 | AH40: FALSE | AJ40: cumulative 3L refit after adding study 'Zheng (2021)' (median sample_mid = 2006.50); ordering: study-wise median sample_mid, ties alphabetical [DEC-045/H-Q17]; full display (CI band)
... A140: H7 | B140: cumulative | C140: Cicchini et al (2026) | D140: step_113 | E140: Fisher_z | F140: 3LMA-RVE_CR2 | G140: 0.6 | H140: 2705 | I140: 113 | J140: 112 | K140: -0.05877906 | L140: 0.014109739 | M140: -4.1658504 | N140: 109.82248 | O140: 6.2015541e-05 | P140: -0.086741752 | Q140: -0.030816367 | T140: -0.05871146 | U140: -0.086524853 | V140: -0.030806616 | Y140: 0.020213223 | Z140: 3.8523599e-10 | AA140: 0.011880597 | AH140: FALSE | AJ140: cumulative 3L refit after adding study 'Cicchini et al (2026)' (median sample_mid = 2022.50); ordering: study-wise median sample_mid, ties alphabetical [DEC-045/H-Q17]; full display (CI band)
A141: H8 | B141: rolling | C141: 1998-2003 | D141: window_mean | E141: Fisher_z | F141: 3LMA-RVE_CR2 | G141: 0.6 | H141: 312 | I141: 9 | J141: 9 | K141: -0.01487142 | T141: -0.014870324 | Y141: 3.2384722e-12 | Z141: 3.2384684e-12 | AA141: 0.001878952 | AH141: FALSE | AJ141: descriptive tier (5-9 clusters: 9) [DEC-045 S6]: estimate only; se/CI/p suppressed by rule; window [1998, 2004) on sample_mid
A142: H8 | B142: rolling | C142: 1999-2004 | D142: window_mean | E142: Fisher_z | F142: 3LMA-RVE_CR2 | G142: 0.6 | H142: 306 | I142: 8 | J142: 8 | K142: -0.01518672 | T142: -0.015185553 | Y142: 5.3732707e-12 | Z142: 5.373271e-12 | AA142: 0.0018608641 | AH142: FALSE | AJ142: descriptive tier (5-9 clusters: 8) [DEC-045 S6]: estimate only; se/CI/p suppressed by rule; window [1999, 2005) on sample_mid
A143: H8 | B143: rolling | C143: 2000-2005 | D143: window_mean | E143: Fisher_z | F143: 3LMA-RVE_CR2 | G143: 0.6 | H143: 242 | I143: 8 | J143: 8 | K143: -0.016355716 | T143: -0.016354258 | Y143: 6.1079517e-06 | Z143: 6.1079516e-06 | AA143: 0.0017298443 | AH143: FALSE | AJ143: descriptive tier (5-9 clusters: 8) [DEC-045 S6]: estimate only; se/CI/p suppressed by rule; window [2000, 2006) on sample_mid
A144: H8 | B144: rolling | C144: 2001-2006 | D144: window_mean | E144: Fisher_z | F144: 3LMA-RVE_CR2 | G144: 0.6 | H144: 75 | I144: 6 | J144: 6 | K144: -0.039045798 | T144: -0.039025967 | Y144: 0.00015879925 | Z144: 0.00015879925 | AA144: 0.0062158481 | AH144: FALSE | AJ144: descriptive tier (5-9 clusters: 6) [DEC-045 S6]: estimate only; se/CI/p suppressed by rule; window [2001, 2007) on sample_mid
A145: H8 | B145: rolling | C145: 2002-2007 | D145: window_mean | E145: Fisher_z | F145: 3LMA-RVE_CR2 | G145: 0.6 | H145: 26 | I145: 4 | J145: 4 | AH145: FALSE | AJ145: not_estimable: 4 clusters < 5 [DEC-045 S6 tier]; window [2002, 2008); no fit attempted
A146: H8 | B146: rolling | C146: 2003-2008 | D146: window_mean | E146: Fisher_z | F146: 3LMA-RVE_CR2 | G146: 0.6 | H146: 67 | I146: 7 | J146: 7 | K146: -0.064797513 | T146: -0.064706976 | Y146: 3.5675904e-12 | Z146: 3.5675906e-12 | AA146: 0.010422605 | AH146: FALSE | AJ146: descriptive tier (5-9 clusters: 7) [DEC-045 S6]: estimate only; se/CI/p suppressed by rule; window [2003, 2009) on sample_mid
A147: H8 | B147: rolling | C147: 2004-2009 | D147: window_mean | E147: Fisher_z | F147: 3LMA-RVE_CR2 | G147: 0.6 | H147: 85 | I147: 8 | J147: 8 | K147: -0.071015843 | T147: -0.070896699 | Y147: 2.6712831e-12 | Z147: 2.6712838e-12 | AA147: 0.011561639 | AH147: FALSE | AJ147: descriptive tier (5-9 clusters: 8) [DEC-045 S6]: estimate only; se/CI/p suppressed by rule; window [2004, 2010) on sample_mid
A148: H8 | B148: rolling | C148: 2005-2010 | D148: window_mean | E148: Fisher_z | F148: 3LMA-RVE_CR2 | G148: 0.6 | H148: 436 | I148: 18 | J148: 18 | K148: -0.041300989 | L148: 0.010205514 | M148: -4.046929 | N148: 14.8264 | O148: 0.0010770774 | P148: -0.063075731 | Q148: -0.019526247 | T148: -0.041277522 | U148: -0.062992214 | V148: -0.019523766 | Y148: 0.00056783128 | Z148: 0.00056783135 | AA148: 0.0032280909 | AH148: FALSE | AJ148: full-inference tier (>= 10 clusters: 18) [DEC-045 S6]; window [2005, 2011) on sample_mid; width 6 y, step 1 y, anchor 1998
A149: H8 | B149: rolling | C149: 2006-2011 | D149: window_mean | E149: Fisher_z | F149: 3LMA-RVE_CR2 | G149: 0.6 | H149: 674 | I149: 24 | J149: 24 | K149: -0.052902864 | L149: 0.010733015 | M149: -4.9289844 | N149: 20.827496 | O149: 7.2489785e-05 | P149: -0.075234653 | Q149: -0.030571075 | T149: -0.052853566 | U149: -0.075093025 | V149: -0.030561555 | Y149: 0.00088373919 | Z149: 0.00088373959 | AA149: 0.0071329189 | AH149: FALSE | AJ149: full-inference tier (>= 10 clusters: 24) [DEC-045 S6]; window [2006, 2012) on sample_mid; width 6 y, step 1 y, anchor 1998
A150: H8 | B150: rolling | C150: 2007-2012 | D150: window_mean | E150: Fisher_z | F150: 3LMA-RVE_CR2 | G150: 0.6 | H150: 1008 | I150: 43 | J150: 42 | K150: -0.086801725 | L150: 0.040022875 | M150: -2.1688028 | N150: 40.933297 | O150: 0.035960827 | P150: -0.16763356 | Q150: -0.0059698889 | T150: -0.086584377 | U150: -0.16608079 | V150: -0.005969818 | Y150: 0.065028405 | Z150: 9.1228079e-10 | AA150: 0.011744128 | AH150: FALSE | AJ150: full-inference tier (>= 10 clusters: 42) [DEC-045 S6]; window [2007, 2013) on sample_mid; width 6 y, step 1 y, anchor 1998
A151: H8 | B151: rolling | C151: 2008-2013 | D151: window_mean | E151: Fisher_z | F151: 3LMA-RVE_CR2 | G151: 0.6 | H151: 1368 | I151: 54 | J151: 53 | K151: -0.07352868 | L151: 0.031936072 | M151: -2.3023708 | N151: 51.930739 | O151: 0.025354623 | P151: -0.13761513 | Q151: -0.0094422288 | T151: -0.073396456 | U151: -0.13675295 | V151: -0.0094419482 | Y151: 0.052402681 | Z151: 1.3686399e-09 | AA151: 0.0091350022 | AH151: FALSE | AJ151: full-inference tier (>= 10 clusters: 53) [DEC-045 S6]; window [2008, 2014) on sample_mid; width 6 y, step 1 y, anchor 1998
A152: H8 | B152: rolling | C152: 2009-2014 | D152: window_mean | E152: Fisher_z | F152: 3LMA-RVE_CR2 | G152: 0.6 | H152: 1552 | I152: 63 | J152: 62 | K152: -0.066472226 | L152: 0.025720734 | M152: -2.584383 | N152: 60.652658 | O152: 0.012178641 | P152: -0.11790997 | Q152: -0.015034483 | T152: -0.066374495 | U152: -0.11736657 | V152: -0.015033351 | Y152: 0.038430974 | Z152: 1.859739e-09 | AA152: 0.016773351 | AH152: FALSE | AJ152: full-inference tier (>= 10 clusters: 62) [DEC-045 S6]; window [2009, 2015) on sample_mid; width 6 y, step 1 y, anchor 1998
A153: H8 | B153: rolling | C153: 2010-2015 | D153: window_mean | E153: Fisher_z | F153: 3LMA-RVE_CR2 | G153: 0.6 | H153: 1676 | I153: 72 | J153: 71 | K153: -0.062432418 | L153: 0.022271271 | M153: -2.8032714 | N153: 69.469691 | O153: 0.0065519431 | P153: -0.10685703 | Q153: -0.018007806 | T153: -0.062351428 | U153: -0.10645217 | V153: -0.01800586 | Y153: 0.032653348 | Z153: 1.2570702e-09 | AA153: 0.016017807 | AH153: FALSE | AJ153: full-inference tier (>= 10 clusters: 71) [DEC-045 S6]; window [2010, 2016) on sample_mid; width 6 y, step 1 y, anchor 1998
A154: H8 | B154: rolling | C154: 2011-2016 | D154: window_mean | E154: Fisher_z | F154: 3LMA-RVE_CR2 | G154: 0.6 | H154: 1339 | I154: 65 | J154: 64 | K154: -0.065468399 | L154: 0.024284854 | M154: -2.6958531 | N154: 62.405185 | O154: 0.0090126824 | P154: -0.11400686 | Q154: -0.016929936 | T154: -0.065375024 | U154: -0.11351548 | V154: -0.016928319 | Y154: 0.034497129 | Z154: 1.3679623e-09 | AA154: 0.019559066 | AH154: FALSE | AJ154: full-inference tier (>= 10 clusters: 64) [DEC-045 S6]; window [2011, 2017) on sample_mid; width 6 y, step 1 y, anchor 1998
A155: H8 | B155: rolling | C155: 2012-2017 | D155: window_mean | E155: Fisher_z | F155: 3LMA-RVE_CR2 | G155: 0.6 | H155: 1365 | I155: 64 | J155: 63 | K155: -0.063369749 | L155: 0.025091274 | M155: -2.5255692 | N155: 61.535778 | O155: 0.014141322 | P155: -0.11353402 | Q155: -0.013205479 | T155: -0.06328506 | U155: -0.11304871 | V155: -0.013204711 | Y155: 0.036683453 | Z155: 1.158869e-09 | AA155: 0.01756702 | AH155: FALSE | AJ155: full-inference tier (>= 10 clusters: 63) [DEC-045 S6]; window [2012, 2018) on sample_mid; width 6 y, step 1 y, anchor 1998
A156: H8 | B156: rolling | C156: 2013-2018 | D156: window_mean | E156: Fisher_z | F156: 3LMA-RVE_CR2 | G156: 0.6 | H156: 1097 | I156: 46 | J156: 46 | K156: -0.038931966 | L156: 0.0076260061 | M156: -5.105158 | N156: 36.284313 | O156: 1.0683447e-05 | P156: -0.054394016 | Q156: -0.023469916 | T156: -0.038912308 | U156: -0.054340434 | V156: -0.023465607 | Y156: 0.00058085583 | Z156: 0.00058085583 | AA156: 0.01549124 | AH156: FALSE | AJ156: full-inference tier (>= 10 clusters: 46) [DEC-045 S6]; window [2013, 2019) on sample_mid; width 6 y, step 1 y, anchor 1998
A157: H8 | B157: rolling | C157: 2014-2019 | D157: window_mean | E157: Fisher_z | F157: 3LMA-RVE_CR2 | G157: 0.6 | H157: 823 | I157: 41 | J157: 41 | K157: -0.041259598 | L157: 0.0078480138 | M157: -5.25733 | N157: 28.454147 | O157: 1.310335e-05 | P157: -0.057323974 | Q157: -0.025195222 | T157: -0.041236201 | U157: -0.057261267 | V157: -0.025189892 | Y157: 0.00032638213 | Z157: 0.00032638215 | AA157: 0.020641044 | AH157: FALSE | AJ157: full-inference tier (>= 10 clusters: 41) [DEC-045 S6]; window [2014, 2020) on sample_mid; width 6 y, step 1 y, anchor 1998
A158: H8 | B158: rolling | C158: 2015-2020 | D158: window_mean | E158: Fisher_z | F158: 3LMA-RVE_CR2 | G158: 0.6 | H158: 754 | I158: 35 | J158: 35 | K158: -0.047836984 | L158: 0.0077681801 | M158: -6.1580683 | N158: 30.179561 | O158: 8.7511117e-07 | P158: -0.063697767 | Q158: -0.031976201 | T158: -0.047800527 | U158: -0.063611757 | V158: -0.031965307 | Y158: 0.00062931875 | Z158: 0.00062931879 | AA158: 0.004676045 | AH158: FALSE | AJ158: full-inference tier (>= 10 clusters: 35) [DEC-045 S6]; window [2015, 2021) on sample_mid; width 6 y, step 1 y, anchor 1998
A159: H8 | B159: rolling | C159: 2016-2021 | D159: window_mean | E159: Fisher_z | F159: 3LMA-RVE_CR2 | G159: 0.6 | H159: 612 | I159: 25 | J159: 25 | K159: -0.050845323 | L159: 0.0094386895 | M159: -5.3869049 | N159: 21.741826 | O159: 2.1571888e-05 | P159: -0.070433452 | Q159: -0.031257193 | T159: -0.050801552 | U159: -0.070317212 | V159: -0.031247018 | Y159: 0.00073331197 | Z159: 0.00073331185 | AA159: 0.0040202233 | AH159: FALSE | AJ159: full-inference tier (>= 10 clusters: 25) [DEC-045 S6]; window [2016, 2022) on sample_mid; width 6 y, step 1 y, anchor 1998
... A161: H8 | B161: rolling | C161: 2018-2023 | D161: window_mean | E161: Fisher_z | F161: 3LMA-RVE_CR2 | G161: 0.6 | H161: 336 | I161: 14 | J161: 14 | K161: -0.05338347 | L161: 0.015324113 | M161: -3.4836255 | N161: 12.580064 | O161: 0.0042267156 | P161: -0.086601891 | Q161: -0.020165048 | T161: -0.053332817 | U161: -0.086386037 | V161: -0.020162316 | Y161: 0.0012891491 | Z161: 0.0012891489 | AA161: 0.0046404474 | AH161: FALSE | AJ161: full-inference tier (>= 10 clusters: 14) [DEC-045 S6]; window [2018, 2024) on sample_mid; width 6 y, step 1 y, anchor 1998
A162: H9 | B162: external_size | C162: defined | D162: own_pooled | E162: Fisher_z | F162: descriptive | G162: 0.6 | H162: 2713 | I162: 115 | J162: 114 | K162: -0.058646737 | T162: -0.058579592 | U162: -0.085890445 | V162: -0.031180768 | AH162: FALSE | AJ162: debt-side pooled mean (E1 refit of T1/A1); descriptive channel-level size comparison, NO formal z-test [DEC-045/H-Q9; N12 scope shift disclosed]
A163: H9 | B163: external_size | C163: defined | D163: coe_study_level | E163: Fisher_z | F163: descriptive | I163: 75 | T163: -0.039 | U163: -0.046 | V163: -0.032 | AH163: FALSE | AJ163: COE companion STUDY-LEVEL row (Table 3, 75 units; NOT the ES-level -0.041 figure); SE provenance disclosure: COE main model = naive inverse variance at ES level, k = 1,139, no cluster-robust inference; overlap disclosure: 7/120 corpus, 6/115 estimation set, 5/113 period domain; 60/2,713 est ES (2.2%); 0 shared effect sizes [DEC-045/H-Q10]
A164: H10 | B164: pcurve | C164: defined | D164: count_significant | E164: count | F164: descriptive | G164: 0.6 | H164: 31 | I164: 31 | J164: 31 | AG164: 28 | AH164: FALSE | AJ164: N13 rule [Annex H/DEC-045]: conditional on >= 5 significant study-level post-cell p; selection = first-reported ES per post study (dat_prep row order); p reconstructed as 2*pnorm(-|zi|/sqrt(vi)) (z-metric; converted-r accuracy caveat)
A165: H10 | B165: pcurve | C165: defined | D165: right_skew_binomial | E165: count | F165: descriptive | G165: 0.6 | I165: 28 | AG165: 1.5161932e-06 | AH165: FALSE | AJ165: N13 rule [Annex H/DEC-045]: conditional on >= 5 significant study-level post-cell p; selection = first-reported ES per post study (dat_prep row order); p reconstructed as 2*pnorm(-|zi|/sqrt(vi)) (z-metric; converted-r accuracy caveat); share of significant p < .025: 26/28; one-sided binomial vs 0.5 [Simonsohn et al. 2014]
A166: H10 | B166: pcurve | C166: defined | D166: right_skew_stouffer | E166: count | F166: descriptive | G166: 0.6 | I166: 28 | AG166: 2.0586452e-119 | AH166: FALSE | AJ166: N13 rule [Annex H/DEC-045]: conditional on >= 5 significant study-level post-cell p; selection = first-reported ES per post study (dat_prep row order); p reconstructed as 2*pnorm(-|zi|/sqrt(vi)) (z-metric; converted-r accuracy caveat); Stouffer z on pp = p/.05: z = -23.2043; right-skew p = pnorm(z)
A167: H10 | B167: pcurve | C167: defined | D167: flatness_vs_33 | E167: count | F167: descriptive | G167: 0.6 | I167: 28 | AG167: 1 | AH167: FALSE | AJ167: N13 rule [Annex H/DEC-045]: conditional on >= 5 significant study-level post-cell p; selection = first-reported ES per post study (dat_prep row order); p reconstructed as 2*pnorm(-|zi|/sqrt(vi)) (z-metric; converted-r accuracy caveat); NCP_33 = 1.529236685 (= qnorm(.975) - qnorm(2/3)); Stouffer z on pp33: z = -20.0115; flatter-than-33% p = 1 - pnorm(z); pp33 clip share (upper/lower) = 0/9 of 28
A168: H11 | B168: within_study | C168: Li et al (2022) | D168: pre_mean | E168: Fisher_z | F168: descriptive | G168: 0.6 | H168: 12 | I168: 1 | J168: 1 | K168: -0.052348083 | T168: -0.052300318 | AG168: 0.034291927 | AH168: FALSE | AJ168: N15 within-study display: descriptive only, explicitly NO p-values (single both-period cluster) [DEC-045/H-Q11; DEC-008 partial reopen]; unweighted mean of Fisher-z within cell; value = SD
A169: H11 | B169: within_study | C169: Li et al (2022) | D169: post_mean | E169: Fisher_z | F169: descriptive | G169: 0.6 | H169: 5 | I169: 1 | J169: 1 | K169: -0.016230795 | T169: -0.01622937 | AG169: 0.03254926 | AH169: FALSE | AJ169: N15 within-study display: descriptive only, explicitly NO p-values (single both-period cluster) [DEC-045/H-Q11; DEC-008 partial reopen]; unweighted mean of Fisher-z within cell; value = SD
A170: H11 | B170: within_study | C170: Li et al (2022) | D170: within_diff | E170: Fisher_z | F170: descriptive | G170: 0.6 | H170: 17 | I170: 1 | J170: 1 | K170: 0.036117287 | AH170: FALSE | AJ170: N15 within-study display: descriptive only, explicitly NO p-values (single both-period cluster) [DEC-045/H-Q11; DEC-008 partial reopen]; unweighted mean of Fisher-z within cell; value = SD; post-minus-pre difference of unweighted cell means; z-only, no CI/p by rule
A171: TH_design | B171: design | C171: defined | D171: h6_tie_inventory | E171: count | F171: descriptive | AG171: 79 | AH171: FALSE | AJ171: tie ES at sample_mid = 2015.5: 79 ES / 5 studies / 5 clusters (Ho & Wong 2023; Kordschia 2020; Owolabi et al 2024; Ririmasse et al 2026; Xiang & Gong 2026); post cell 31 -> 26 studies under the Zarea tie-exclusion rule [DEC-045/H-Q8]
A172: TH_design | B172: design | C172: defined | D172: h4_admissible_years | E172: count | F172: descriptive | AG172: 12 | AH172: FALSE | AJ172: candidate years with break-coefficient Satterthwaite df >= 5, computed ONCE on the observed design and held fixed for the TH-c permutation [DEC-045/H-Q6/H-Q20]: 2008, 2009, 2010, 2011, 2012, 2013, 2014, 2015, 2016, 2017, 2018, 2019
A173: TH_design | B173: design | C173: defined | D173: h7_floor_step | E173: count | F173: descriptive | AG173: 10 | AH173: FALSE | AJ173: first cumulative step with >= 10 clusters (CI band from here; steps 1-9 point-only in the figure) [DEC-045/H-Q17]; floor study = 'Chen, Gao (2011)'
A174: TH_design | B174: design | C174: defined | D174: h7_order_head | E174: count | F174: descriptive | AH174: FALSE | AJ174: ordering: study-wise median sample_mid, ties alphabetical; first 5: Nandy, Lodh (2012) (1998.50); Chava (2010) (1999.00); Schneider (2010) (1999.00); Chava (2014) (1999.50); Oikonomou et al (2014) (2000.00)
A175: TH_design | B175: design | C175: defined | D175: h8_window_anchor | E175: year | F175: descriptive | AG175: 1998 | AH175: FALSE | AJ175: derived design constant: min sample_mid = 1998.5 -> anchor 1998; width 6 y, step 1 y -> 21 windows [DEC-045 S6]
A176: TH_design | B176: design | C176: defined | D176: h10_selection_rule | E176: count | F176: descriptive | AH176: FALSE | AJ176: first-reported ES per post study = first occurrence in dat_prep row order (pinned) [DEC-045/N13]
A177: TH_design | B177: design | C177: defined | D177: h11_straddle_studies | E177: count | F177: descriptive | AG177: 73 | AH177: FALSE | AJ177: studies with any pp_window_class == 'mixed' on the estimation set (straddle the break) [DEC-045/H-Q11]
A178: TH_design | B178: design | C178: defined | D178: h11_pool_across | E178: count | F178: descriptive | AG178: 72 | AH178: FALSE | AJ178: straddling studies minus the single within-split study (Li et al 2022) = studies that pool across the break ('Paris blindness' introduction module)

Sheet Manuscript_Inputs
A1: TH-a (Block E/H fast frequentist battery) · Manuscript Inputs (ms_input = TRUE rows; every cell formula-derived from Results_Long)
A2: Paste-ready strings via locale-neutral digit arithmetic (no TEXT format codes, no CONCAT) - pinned convention
A3: Run 2026-07-24 22:46 (canonical) · verifier R/06_verify_outputs.R 17/17 PASS · chat artefact check 2026-07-26 18/18 PASS · output/TH_a_results.csv 177x36
A5: ms_label | B5: Quantity | C5: c1 | D5: c2 | E5: c3 | F5: c4 | G5: c5 | H5: Paste-ready string (formula-derived) | I5: Source pointer | J5: note (verbatim)
A6: e1_tost_primary | B6: E1 TOST at the primary band (p, 90% CI, flag) + pooled z | C6: =IF(INDEX(Results_Long!$O:$O,SUMPRODUCT((Results_Long!$A$2:$A$178="E1")*(Results_Long!$B$2:$B$178="tost_pooled")*(Results_Long!$C$2:$C$178="defined")*(Results_Long!$D$2:$D$178="tost_band_0.070")*ROW(Results_Long!$A$2:$A$178)))="","NA",INDEX(Results_Long!$O:$O,SUMPRODUCT((Results_Long!$A$2:$A$178="E1")*(Results_Long!$B$2:$B$178="tost_pooled")*(Results_Long!$C$2:$C$178="defined")*(Results_Long!$D$2:$D$178="tost_band_0.070")*ROW(Results_Long!$A$2:$A$178)))) -> 0.20482591 | D6: =IF(INDEX(Results_Long!$P:$P,SUMPRODUCT((Results_Long!$A$2:$A$178="E1")*(Results_Long!$B$2:$B$178="tost_pooled")*(Results_Long!$C$2:$C$178="defined")*(Results_Long!$D$2:$D$178="tost_band_0.070")*ROW(Results_Long!$A$2:$A$178)))="","NA",INDEX(Results_Long!$P:$P,SUMPRODUCT((Results_Long!$A$2:$A$178="E1")*(Results_Long!$B$2:$B$178="tost_pooled")*(Results_Long!$C$2:$C$178="defined")*(Results_Long!$D$2:$D$178="tost_band_0.070")*ROW(Results_Long!$A$2:$A$178)))) -> -0.081629394 | E6: =IF(INDEX(Results_Long!$Q:$Q,SUMPRODUCT((Results_Long!$A$2:$A$178="E1")*(Results_Long!$B$2:$B$178="tost_pooled")*(Results_Long!$C$2:$C$178="defined")*(Results_Long!$D$2:$D$178="tost_band_0.070")*ROW(Results_Long!$A$2:$A$178)))="","NA",INDEX(Results_Long!$Q:$Q,SUMPRODUCT((Results_Long!$A$2:$A$178="E1")*(Results_Long!$B$2:$B$178="tost_pooled")*(Results_Long!$C$2:$C$178="defined")*(Results_Long!$D$2:$D$178="tost_band_0.070")*ROW(Results_Long!$A$2:$A$178)))) -> -0.035664079 | F6: =IF(INDEX(Results_Long!$AG:$AG,SUMPRODUCT((Results_Long!$A$2:$A$178="E1")*(Results_Long!$B$2:$B$178="tost_pooled")*(Results_Long!$C$2:$C$178="defined")*(Results_Long!$D$2:$D$178="tost_band_0.070")*ROW(Results_Long!$A$2:$A$178)))="","NA",INDEX(Results_Long!$AG:$AG,SUMPRODUCT((Results_Long!$A$2:$A$178="E1")*(Results_Long!$B$2:$B$178="tost_pooled")*(Results_Long!$C$2:$C$178="defined")*(Results_Long!$D$2:$D$178="tost_band_0.070")*ROW(Results_Long!$A$2:$A$178)))) -> 0 | G6: =IF(INDEX(Results_Long!$K:$K,SUMPRODUCT((Results_Long!$A$2:$A$178="E1")*(Results_Long!$B$2:$B$178="tost_pooled")*(Results_Long!$C$2:$C$178="defined")*(Results_Long!$D$2:$D$178="pooled_mean")*ROW(Results_Long!$A$2:$A$178)))="","NA",INDEX(Results_Long!$K:$K,SUMPRODUCT((Results_Long!$A$2:$A$178="E1")*(Results_Long!$B$2:$B$178="tost_pooled")*(Results_Long!$C$2:$C$178="defined")*(Results_Long!$D$2:$D$178="pooled_mean")*ROW(Results_Long!$A$2:$A$178)))) -> -0.058646737 | H6: ="TOST (primary band |r| = 0.070): "&IF($C6="NA","p = NA",IF($C6<0.0001,"p < 0.0001","p = "&IF($C6="NA","NA",IF($C6<0,"-","")&INT(ROUND(ABS($C6)*10000,0)/10000)&"."&REPT("0",4-LEN(MOD(ROUND(ABS($C6)*10000,0),10000)))&MOD(ROUND(ABS($C6)*10000,0),10000))))&"; 90% CI ["&IF($D6="NA","NA",IF($D6<0,"-","")&INT(ROUND(ABS($D6)*10000,0)/10000)&"."&REPT("0",4-LEN(MOD(ROUND(ABS($D6)*10000,0),10000)))&MOD(ROUND(ABS($D6)*10000,0),10000))&"; "&IF($E6="NA","NA",IF($E6<0,"-","")&INT(ROUND(ABS($E6)*10000,0)/10000)&"."&REPT("0",4-LEN(MOD(ROUND(ABS($E6)*10000,0),10000)))&MOD(ROUND(ABS($E6)*10000,0),10000))&"]; flag = "&IF($F6="NA","NA",ROUND($F6,0))&"; pooled z = "&IF($G6="NA","NA",IF($G6<0,"-","")&INT(ROUND(ABS($G6)*10000,0)/10000)&"."&REPT("0",4-LEN(MOD(ROUND(ABS($G6)*10000,0),10000)))&MOD(ROUND(ABS($G6)*10000,0),10000)) -> TOST (primary band |r| = 0.070): p = 0.2048; 90% CI [-0.0816; -0.0357]; flag = 0; pooled z = -0.0586 | I6: TH_a_results.csv E1 (band 0.070 + pooled_mean) | J6: =IF(INDEX(Results_Long!$AJ:$AJ,SUMPRODUCT((Results_Long!$A$2:$A$178="E1")*(Results_Long!$B$2:$B$178="tost_pooled")*(Results_Long!$C$2:$C$178="defined")*(Results_Long!$D$2:$D$178="tost_band_0.070")*ROW(Results_Long!$A$2:$A$178)))="","NA",INDEX(Results_Long!$AJ:$AJ,SUMPRODUCT((Results_Long!$A$2:$A$178="E1")*(Results_Long!$B$2:$B$178="tost_pooled")*(Results_Long!$C$2:$C$178="defined")*(Results_Long!$D$2:$D$178="tost_band_0.070")*ROW(Results_Long!$A$2:$A$178)))) -> TOST, two one-sided tests each alpha=.05 <=> 90% CI inside band [DEC-045 E-pins]; PRIMARY level band |r| = 0.070 (F27v2) -> z band atanh = 0.070114671; arm p (lower/upper) = 0.204826 / 7.26341e-16; TOST p = max(arms); CI columns carry the 90% CI (TOST convention); value = 1{90%-CI inside band} (mechanical flag, no verdict language); ex-ante expectation [DEC-044/DEC-045]: this arm is expected to FAIL (T1 CI edge -0.086); E2 adjudicates Tier 1; E1 calibrates the Tier-2 wording only
