Workbook

Sheet 1_README
A1: FOMA CER–COD–Paris · Run TH-b (Bayes battery H2a/H2b) — results workbook
A2: Template: docs/results_workbook_template.md (10-tab cut per author ruling B-Q4, 2026-07-26)
A3: Run 2026-07-27 16:22:52 CEST · verifier R/07_verify_outputs.R O0–O14 ALL PASS (exit 0)
A5: Item | B5: Value
A6: Version | B6: TH-b v1 (canonical run 3; runs 1–2 halted by design — ERROR_LOG #17/#18)
A7: Method | B7: Robust Bayesian model-averaged meta-analysis (RoBMA 3.6.1): H2a pooled level (36-model space), H2b Paris-period moderation via RoBMA.reg (72-model space)
A8: Scope | B8: H2a: k = 114 one-effect-per-cluster aggregates, 3 effect-prior sets. H2b: 113 cluster×period aggregate rows (82 pre + 31 post), 3 moderation-prior sets. Single-home: level cells → T2/B1; frequentist selection models → T5; this run carries the Bayes gate inputs [DEC-044/045].
A9: Repo / anchors | B9: rwitte-wu-research/FOMA-CER-COD-Paris · Block-1 a4719ed → fix 1b6eab8 (#17) → fix 4cf8fe6 (#18); outputs committed with Block 2
A10: Computational stack | B10: R 4.6.1 · RoBMA 3.6.1 · BayesTools 0.2.23 · rjags 4-17 · JAGS 4.3.2 · seed 20260710 · sequential chains + single-thread Rblas [DEC-046]
A11: Scripts | B11: R/07_robma.R + paired verifier R/07_verify_outputs.R (foundational pair, pre-execution diff review B-Q1)
A12: Decision basis | B12: DEC-031b (prior sets; COE companion = only admissible external prior source) · DEC-042a/b (domains) · DEC-044 (framing gate) · DEC-045 (H2a/H2b pins) · DEC-046 (F66 closure: version + y/se scale-path pins)
A13: Recalc | B13: Container recalc pass executed (LibreOffice headless) + spot verification vs CSV; re-calculate on open (Ctrl+Alt+F9) after any edit
A14: Framing status | B14: NONE. Mechanical values and pinned band labels only; adjudication deferred to the documented gate-resolution step [DEC-044].
A16: TAB-INDEX
A17: 1_README | B17: this tab
A18: 2_Methodology | B18: model space, priors (full precision), pins
A19: 3_Interpretation_Guide | B19: BF01 semantics, band ladder, saturation, mixture quantiles
A20: 4_Formula_Reference | B20: derivation map into Results_Long
A21: 5_Data_Provenance | B21: contract, structure, timings/κ, diagnostics, run history
A22: 6_H2a_Level | B22: pooled-level panel + Q&A + verdict
A23: 7_H2b_Moderation | B23: moderation panel + Q&A + verdict
A24: Results_Long | B24: verbatim run CSV — single formula source
A25: Manuscript_Inputs | B25: ms_input rows, formula-derived paste strings
A26: Manuscript_Text_Blocks | B26: TB-52…TB-56 (numbers hardcoded, provenance header)

Sheet 2_Methodology
A1: Methodology — TH-b Bayes battery
A2: Authority: DEC-045 (spec) · DEC-046 (stack + scale path) · DEC-031b (priors)
A3: All priors act verbatim on the Fisher-z scale (y/se route; transformation = prior_scale = "none").
A5: Item | B5: Specification
A6: Model space H2a | B6: 36 models: {Spike(0), effect prior} × {Spike(0), InvGamma(1, 0.15)} × 9 publication-selection components (6 weight functions, PET ~ Cauchy(0,1)[0,∞], PEESE ~ Cauchy(0,5)[0,∞], none). Package construction echoed verbatim in TH_b_run_meta.txt FITMETA blocks.
A7: Model space H2b | B7: 72 models: the 36-model space crossed with period-moderator inclusion/exclusion; RoBMA.reg(~ period, test_predictors = "period"); factor levels c("pre","post"), reference = pre.
A8: Input | B8: One-effect-per-cluster aggregates (metafor aggregate.escalc, struct = "CS", rho = 0.6; T1/A5 convention [DEC-031g/F65]); H2a k = 114; H2b 113 cluster×period rows (per-cell D2 aggregation; Li et al (2022) = single both-period cluster, disclosed).
A9: Orientation | B9: effect_direction = "negative" for all fits (P-T5-2 transfer [DEC-046]); estimates reported on the original scale.
A10: H2a effect priors | B10: psma_default: package defaults (effect slab Normal(0, 1) on z — evidenced in FITMETA) · coe_informed: Normal(−0.041, 0.0211734694) with σ = 0.083/3.92 [DEC-031b provenance arithmetic] · coe_wide: Normal(−0.041, 0.0423469388) = 2σ.
A11: H2b period priors | B11: contrast_informed: treatment-contrast Normal(0, 0.025) [secondary SESOI ±0.05 ≈ ±2σ, DEC-045] (PRIMARY) · contrast_wide: Normal(0, 0.050) · factor_default: package default = mean-difference contrast mNormal(0, 0.25) (evidenced in FITMETA; no memory-hardcoding). H2b level/heterogeneity/bias priors = package defaults; level inference single-homed in H2a.
A12: Prior print-rounding note | B12: FITMETA prior echoes are BayesTools 2-dp print renderings ("Normal(-0.04, 0.02)", "Normal(0, 0.03)"); the calls used the full-precision constants in the run_meta constants line, asserted by verifier O8b. The print string is display, not the call.
A13: MCMC | B13: 3.x defaults: 3 chains × 5,000 samples, 2,000 burn-in, 500 adapt, autofit = TRUE; seed 20260710; parallel = FALSE.
A14: Guards | B14: [R7-PRE] 3-probe smoke test (level, regression, saturation) before canonical fits; not-estimable signature list {converg, r-hat, rhat, effective sample size, bridge sampl, node inconsistent, unable to initialize}; saturated BF pairs Inf/0 legitimate [#18].

Sheet 3_Interpretation_Guide
A1: Interpretation guide (mechanical semantics only)
A2: BF01 = 1/BF10 = evidence FOR the null of the named component (inclusion Bayes factor inverted).
A3: Band labels are pinned mechanical labels — adjudication is deferred [DEC-044].
A5: Concept | B5: Mechanical reading
A6: BF01 band ladder (pinned) | B6: 1–3 anecdotal · 3–10 moderate · 10–30 strong · >30 very strong. Gate mapping [E3/DEC-045]: BF01 ≥ 3 = "full" register input; 1–3 = equivalence-register input. Values < 1 favour component inclusion — read via BF10 = 1/BF01 with the same ladder.
A7: Saturation (Inf/0) | B7: A saturated pair (BF10 = Inf, BF01 = 0) means the posterior inclusion probability hit the floating-point boundary — evidence beyond double-precision resolution, not an error [#18]. Here: heterogeneity in all three H2a sets.
A8: Mixture quantiles / exact-zero CI bounds | B8: Model-averaged intervals mix the Spike(0) mass with the slab posterior. With BF01(effect) = 7.03, the posterior spike mass is BF01/(1+BF01) ≈ 87.5%, so the 2.5% or 97.5% quantile can sit exactly at 0. An exact-zero bound is mixture arithmetic, not truncation.
A9: Why default μ can differ in sign | B9: Under the diffuse default slab Normal(0, 1), the slab posterior is dominated by the strongly included publication-selection components (BF10_bias = 94.7), whose corrected location differs from the unadjusted pooled value. The COE-informed set anchors the calibrated magnitude; prior sensitivity across sets is reported mechanically.
A10: Contrast rows | B10: Differences of Fisher-z are reported z-only by convention (no tanh of differences); est_r = NA on z_diff rows.
A11: Single-home map | B11: Level pre/post cells → T2/B1 · frequentist selection models (FAT-PET-PEESE, selection) → T5/Block D · Paris×exposure interactions → their one designated location · this workbook → Bayes gate inputs only.
A12: Framing gate | B12: Verbatim: results are mechanical values with pinned labels; wording tier (evidence-of-absence vs equivalence register) is decided at the documented gate-resolution step [DEC-044] — nothing in this workbook pre-empts it.

Sheet 4_Formula_Reference
A1: Formula reference
A2: Every derived cell resolves into Results_Long via INDEX/MATCH on the 4-key helper column AK.
A3: Key = analysis_id|spec|subset|term. No XLOOKUP/FILTER (LibreOffice recalc); no TEXT() format codes (locale-neutral refinement vs template).
A5: Derived quantity | B5: Formula pattern
A6: Panel numbers (tabs 6/7) | B6: =INDEX(results_long!<col>,MATCH("<4-key>",Results_Long!AK:AK,0)) — columns est_z/ci_lb_z/ci_ub_z/est_r/ci_lb_r/ci_ub_r/value. -> #N/A
A7: est_r on μ rows | B7: est_r = TANH(est_z), written by the run script; workbook re-displays, never recomputes.
A8: BF10 from BF01 | B8: =1/<BF1 cell>; saturated: BF1 = 0 ⇒ BF10 = Inf (displayed "saturated"). -> #N/A
A9: Posterior spike mass | B9: =BF1/(1+BF1) on component ROWS(equal prior odds; mechanical). -> #VALUE!
A10: Manuscript_Inputs strings | B10: Assembled arithmetically: sign & INT part & "." & zero-padded fraction (ROUND/INT/REPT/RIGHT + &). Locale-neutral by construction; deviation from template TEXT() per the locale-neutral refinement, disclosed.
A11: Band labels | B11: =IF(BF1=0,"saturated",IF(BF1<1,"favours inclusion (read BF10)",IF(BF1<3,"anecdotal",IF(BF1<10,"moderate",IF(BF1<30,"strong","very strong"))))) -> saturated

Sheet 5_Data_Provenance
A1: Data provenance & run record
A2: Run 3 of 3 (runs 1–2: designed halts, ERROR_LOG #17/#18; no outputs, tree clean).
A3: Executor: Claude Code per docs/cc_prompt_THb.md; author-sanctioned deviations disclosed below.
A5: Item | B5: Value | C5: Source
A6: Estimation set / domains | B6: 2,713 ES / 115 studies / 114 clusters [DEC-042a]; period domain 2,705 / 113 / 112 [DEC-042b]; 8 ES / 2 studies NA-window | C6: TH_b_run_meta.txt
A7: dat_prep contract | B7: md5 6702ef3dc45fe0b693b13f50ebd1576b == pin; n 2,713; seed 20260710 | C7: verifier O6a/O6b
A8: H2b structure | B8: 113 rows = 82 pre + 31 post; 112 unique clusters; both-period n = 1: Li et al (2022) | C8: verifier O7/O7b
A9: F65 identity | B9: T1/A5 anchor located BY VALUE (1e-9), refit identity ≤ 1e-6, df = 113, display canary −0.062 | C9: verifier O6c–O6e
A10: Run timestamp / wall clock | B10: launch 11:43:33 → exit 16:22:52 = 4 h 39 min (Step 1); verifier exit 0 | C10: CC report
A11: Verifier line | B11: O0–O14 ALL PASS; 12 BFPAIR lines consistent (finite product ≡ 1; saturated pairs exact); 0 not_estimable rows — all 30 rows from real estimates | C11: R/07_verify_outputs.R
A12: Per-fit timings (TFIT, s) | B12: h2a: 2057.2 / 2014.8 / 1288.7 · h2b: 3024.8 / 3848.7 / 4126.9 · sum 16,361.1 s = 4.54 h | C12: TH_b_run_meta.txt
A13: Projection vs actual | B13: T = 3t + 3κt = 18,530 s (κ = 2.5) vs 16,361 s actual (88%); κ_emp = 1.71 / 2.18 / 2.34 (mean 2.08, max 2.34) — pin conservative, GO margin validated | C13: DEC-046 · TFIT
A14: t-variance note | B14: fit 1 = 2,057 s vs t_RoBMA = 1,764.8 s (+16.6%) at identical spec/seed — system-load band; coe_wide 27% below reference (plausible autofit early termination) | C14: TFIT vs DEC-046
A15: Diagnostics — h2b_factor_default | B15: 23 warnings: 16× adaptation not completed (500 it), Model 56 R-hat 1.174, ESS down to 98; listed signatures = metadata per design (fit returned, extraction clean). PRIMARY H2b fit (contrast_informed) carried 1 benign warning only | C15: FITMETA
A16: Saturation record | B16: heterogeneity BF pairs Inf/0 in all three H2a sets — legitimate per #18 policy; run-2 halt evidence: thb_console_run2.log | C16: BFPAIR · #18
... A19: Result-blind ledger | B19: pre-acceptance leak limited to run-2 halt value (BF10_het fit 1 = Inf, non-gate); gate quantities first read at this workbook build [DEC-044] | C19: #18 · this build

Sheet 6_H2a_Level
A1: H2a — pooled level (RoBMA model averaging, k = 114 aggregates)
A2: Estimates: model-averaged posterior mean, 95% central CI (mixture quantiles — exact-zero bounds are spike arithmetic).
A3: Reference: DEC-031b prior ladder; PSMA defaults = primary.
A5: Spec | B5: k | C5: est_z | D5: CI_lb_z | E5: CI_ub_z | F5: est_r | G5: CI_lb_r | H5: CI_ub_r | I5: BF01_effect | J5: band (effect) | K5: BF01_bias | L5: bias reading | M5: P(spike) | N5: tau | O5: tau 95% CI
A6: PSMA defaults (primary) | B6: 114 | C6: =INDEX(Results_Long!K:K,MATCH("H2a|psma_default|full|mu_avg",Results_Long!AK:AK,0)) -> 0.0081709402 | D6: =INDEX(Results_Long!P:P,MATCH("H2a|psma_default|full|mu_avg",Results_Long!AK:AK,0)) -> 0 | E6: =INDEX(Results_Long!Q:Q,MATCH("H2a|psma_default|full|mu_avg",Results_Long!AK:AK,0)) -> 0.11030527 | F6: =INDEX(Results_Long!T:T,MATCH("H2a|psma_default|full|mu_avg",Results_Long!AK:AK,0)) -> 0.0081707583 | G6: =INDEX(Results_Long!U:U,MATCH("H2a|psma_default|full|mu_avg",Results_Long!AK:AK,0)) -> 0 | H6: =INDEX(Results_Long!V:V,MATCH("H2a|psma_default|full|mu_avg",Results_Long!AK:AK,0)) -> 0.10986006 | I6: =INDEX(Results_Long!AG:AG,MATCH("H2a|psma_default|full|bf01_effect",Results_Long!AK:AK,0)) -> 7.0327785 | J6: =IF(I6=0,"saturated",IF(I6<1,"favours inclusion (read BF10)",IF(I6<3,"anecdotal",IF(I6<10,"moderate",IF(I6<30,"strong","very strong"))))) -> moderate | K6: =INDEX(Results_Long!AG:AG,MATCH("H2a|psma_default|full|bf01_bias",Results_Long!AK:AK,0)) -> 0.010554327 | L6: =IF(K6=0,"saturated","BF10 = "&ROUND(1/K6,1)&" — favours inclusion") -> BF10 = 94.7 — favours inclusion | M6: =I6/(1+I6) -> 0.87551007 | N6: =INDEX(Results_Long!K:K,MATCH("H2a|psma_default|full|tau_avg",Results_Long!AK:AK,0)) -> 0.26616287 | O6: ="["&ROUND(INDEX(Results_Long!P:P,MATCH("H2a|psma_default|full|tau_avg",Results_Long!AK:AK,0)),3)&"; "&ROUND(INDEX(Results_Long!Q:Q,MATCH("H2a|psma_default|full|tau_avg",Results_Long!AK:AK,0)),3)&"]" -> [0.234; 0.306]
A7: COE-informed | B7: 114 | C7: =INDEX(Results_Long!K:K,MATCH("H2a|coe_informed|full|mu_avg",Results_Long!AK:AK,0)) -> -0.0094975802 | D7: =INDEX(Results_Long!P:P,MATCH("H2a|coe_informed|full|mu_avg",Results_Long!AK:AK,0)) -> -0.062434078 | E7: =INDEX(Results_Long!Q:Q,MATCH("H2a|coe_informed|full|mu_avg",Results_Long!AK:AK,0)) -> 0 | F7: =INDEX(Results_Long!T:T,MATCH("H2a|coe_informed|full|mu_avg",Results_Long!AK:AK,0)) -> -0.0094972946 | G7: =INDEX(Results_Long!U:U,MATCH("H2a|coe_informed|full|mu_avg",Results_Long!AK:AK,0)) -> -0.062353081 | H7: =INDEX(Results_Long!V:V,MATCH("H2a|coe_informed|full|mu_avg",Results_Long!AK:AK,0)) -> 0 | I7: =INDEX(Results_Long!AG:AG,MATCH("H2a|coe_informed|full|bf01_effect",Results_Long!AK:AK,0)) -> 2.3846462 | J7: =IF(I7=0,"saturated",IF(I7<1,"favours inclusion (read BF10)",IF(I7<3,"anecdotal",IF(I7<10,"moderate",IF(I7<30,"strong","very strong"))))) -> anecdotal | K7: =INDEX(Results_Long!AG:AG,MATCH("H2a|coe_informed|full|bf01_bias",Results_Long!AK:AK,0)) -> 0.090226363 | L7: =IF(K7=0,"saturated","BF10 = "&ROUND(1/K7,1)&" — favours inclusion") -> BF10 = 11.1 — favours inclusion | M7: =I7/(1+I7) -> 0.70454814 | N7: =INDEX(Results_Long!K:K,MATCH("H2a|coe_informed|full|tau_avg",Results_Long!AK:AK,0)) -> 0.26404121 | O7: ="["&ROUND(INDEX(Results_Long!P:P,MATCH("H2a|coe_informed|full|tau_avg",Results_Long!AK:AK,0)),3)&"; "&ROUND(INDEX(Results_Long!Q:Q,MATCH("H2a|coe_informed|full|tau_avg",Results_Long!AK:AK,0)),3)&"]" -> [0.232; 0.302]
A8: wide (2σ) | B8: 114 | C8: =INDEX(Results_Long!K:K,MATCH("H2a|coe_wide|full|mu_avg",Results_Long!AK:AK,0)) -> -0.0010362035 | D8: =INDEX(Results_Long!P:P,MATCH("H2a|coe_wide|full|mu_avg",Results_Long!AK:AK,0)) -> -0.065578719 | E8: =INDEX(Results_Long!Q:Q,MATCH("H2a|coe_wide|full|mu_avg",Results_Long!AK:AK,0)) -> 0.051649252 | F8: =INDEX(Results_Long!T:T,MATCH("H2a|coe_wide|full|mu_avg",Results_Long!AK:AK,0)) -> -0.0010362032 | G8: =INDEX(Results_Long!U:U,MATCH("H2a|coe_wide|full|mu_avg",Results_Long!AK:AK,0)) -> -0.065484872 | H8: =INDEX(Results_Long!V:V,MATCH("H2a|coe_wide|full|mu_avg",Results_Long!AK:AK,0)) -> 0.051603373 | I8: =INDEX(Results_Long!AG:AG,MATCH("H2a|coe_wide|full|bf01_effect",Results_Long!AK:AK,0)) -> 1.6935977 | J8: =IF(I8=0,"saturated",IF(I8<1,"favours inclusion (read BF10)",IF(I8<3,"anecdotal",IF(I8<10,"moderate",IF(I8<30,"strong","very strong"))))) -> anecdotal | K8: =INDEX(Results_Long!AG:AG,MATCH("H2a|coe_wide|full|bf01_bias",Results_Long!AK:AK,0)) -> 0.059387472 | L8: =IF(K8=0,"saturated","BF10 = "&ROUND(1/K8,1)&" — favours inclusion") -> BF10 = 16.8 — favours inclusion | M8: =I8/(1+I8) -> 0.62874931 | N8: =INDEX(Results_Long!K:K,MATCH("H2a|coe_wide|full|tau_avg",Results_Long!AK:AK,0)) -> 0.26525439 | O8: ="["&ROUND(INDEX(Results_Long!P:P,MATCH("H2a|coe_wide|full|tau_avg",Results_Long!AK:AK,0)),3)&"; "&ROUND(INDEX(Results_Long!Q:Q,MATCH("H2a|coe_wide|full|tau_avg",Results_Long!AK:AK,0)),3)&"]" -> [0.232; 0.304]
A10: BF01_heterogeneity = 0 (saturated, BF10 = Inf) in all three sets [#18]; row carried verbatim in Results_Long and omitted from the panel for that reason.
A12: Interpretation (mechanical)
A13: BF01(effect) = 7.03 / 2.38 / 1.69 across default / informed / wide priors — band labels moderate / anecdotal / anecdotal; posterior spike mass 87.5% / 70.5% / 62.9%.
A14: Model-averaged μ ranges −0.009 … +0.008 with spike-bounded 95% intervals; ordering follows prior width (mechanical prior sensitivity, cf. tab 3).
A15: Publication-selection block strongly included in every set (BF10_bias = 94.7 / 11.1 / 16.8); frequentist selection results are single-homed in T5/Block D.
A16: Between-aggregate τ ≈ 0.264–0.267 on z with saturated heterogeneity support — consistent with the between-cluster dominance on file since T1/A2.
A18: Question | B18: Answer
A19: Why k = 114 aggregates instead of RoBMA(cluster = ) / spike-and-slab 3-level? | B19: Pre-registered D2 aggregation pin [DEC-031b/045]: the T1/A5 one-effect-per-cluster convention is the project-wide inference unit; the RoBMA 3.6.1 cluster/ss three-level path is approximative and was not pre-registered. Aggregation identity is verifier-anchored (O6, F65 pattern).
A20: Why is the default-set μ positive when the frequentist pooled estimate is −0.062? | B20: Mixture arithmetic: 87.5% posterior mass sits on Spike(0), and the remaining slab mass is dominated by the strongly included selection components whose corrected location is positive. The COE-informed set (μ = −0.009) anchors the calibrated read; sensitivity across sets is the mechanical finding.
A21: The run_meta prior echo says Normal(-0.04, 0.02) — is the σ wrong? | B21: No: BayesTools prints priors at 2 dp. The calls carried σ = 0.0211734694 = 0.083/3.92 (constants line, verifier O8b); print string ≠ call.
A22: Is BF01 = 7.03 under Normal(0, 1) not just prior diffuseness? | B22: The default slab is deliberately scale-diffuse on z (package default under the y route, DEC-046) — that is exactly why the DEC-031b ladder pairs it with the COE-informed prior; the ladder spread (7.03 → 2.38) quantifies the prior dependence mechanically.
A23: Why is heterogeneity BF01 exactly 0? | B23: Saturation: posterior inclusion probability at the floating-point boundary (τ²-dominant data, k = 114). Legitimate raw pair Inf/0 per the #18 policy; verifier O9 checks exact complementarity.
A25: Verdict — Mechanical outcome: BF01(effect) = 7.03 (PSMA defaults, primary) / 2.38 (COE-informed) / 1.69 (wide); model-averaged μ between −0.009 and +0.008 with spike-bounded intervals; heterogeneity saturated; bias block strongly included (BF10 = 94.7 / 11.1 / 16.8); adjudication deferred to the documented gate-resolution step [DEC-044].

Sheet 7_H2b_Moderation
A1: H2b — Paris-period moderation (RoBMA.reg, 113 cluster×period rows: 82 pre + 31 post)
A2: Contrast = post − pre on Fisher-z (treatment contrast, reference = pre); z-only by convention.
A3: Primary = contrast-informed Normal(0, 0.025) [secondary SESOI, DEC-045].
A5: Spec | B5: rows | C5: coef_z (Δ) | D5: CI_lb_z | E5: CI_ub_z | F5: BF01_period | G5: band (period) | H5: P(spike) | I5: tau | J5: tau 95% CI | K5: Notes
A6: contrast-informed (primary) | B6: 113 | C6: =INDEX(Results_Long!K:K,MATCH("H2b|contrast_informed|defined|coef_period",Results_Long!AK:AK,0)) -> 0.0033709677 | D6: =INDEX(Results_Long!P:P,MATCH("H2b|contrast_informed|defined|coef_period",Results_Long!AK:AK,0)) -> -0.031265933 | E6: =INDEX(Results_Long!Q:Q,MATCH("H2b|contrast_informed|defined|coef_period",Results_Long!AK:AK,0)) -> 0.044514467 | F6: =INDEX(Results_Long!AG:AG,MATCH("H2b|contrast_informed|defined|bf01_period",Results_Long!AK:AK,0)) -> 1.0349179 | G6: =IF(F6=0,"saturated",IF(F6<1,"favours inclusion (read BF10)",IF(F6<3,"anecdotal",IF(F6<10,"moderate",IF(F6<30,"strong","very strong"))))) -> anecdotal | H6: =F6/(1+F6) -> 0.50857969 | I6: =INDEX(Results_Long!K:K,MATCH("H2b|contrast_informed|defined|tau_avg",Results_Long!AK:AK,0)) -> 0.2670922 | J6: ="["&ROUND(INDEX(Results_Long!P:P,MATCH("H2b|contrast_informed|defined|tau_avg",Results_Long!AK:AK,0)),3)&"; "&ROUND(INDEX(Results_Long!Q:Q,MATCH("H2b|contrast_informed|defined|tau_avg",Results_Long!AK:AK,0)),3)&"]" -> [0.235; 0.306]
A7: contrast-wide | B7: 113 | C7: =INDEX(Results_Long!K:K,MATCH("H2b|contrast_wide|defined|coef_period",Results_Long!AK:AK,0)) -> 0.0086887497 | D7: =INDEX(Results_Long!P:P,MATCH("H2b|contrast_wide|defined|coef_period",Results_Long!AK:AK,0)) -> -0.044825406 | E7: =INDEX(Results_Long!Q:Q,MATCH("H2b|contrast_wide|defined|coef_period",Results_Long!AK:AK,0)) -> 0.079460463 | F7: =INDEX(Results_Long!AG:AG,MATCH("H2b|contrast_wide|defined|bf01_period",Results_Long!AK:AK,0)) -> 1.1669526 | G7: =IF(F7=0,"saturated",IF(F7<1,"favours inclusion (read BF10)",IF(F7<3,"anecdotal",IF(F7<10,"moderate",IF(F7<30,"strong","very strong"))))) -> anecdotal | H7: =F7/(1+F7) -> 0.53852244 | I7: =INDEX(Results_Long!K:K,MATCH("H2b|contrast_wide|defined|tau_avg",Results_Long!AK:AK,0)) -> 0.26726931 | J7: ="["&ROUND(INDEX(Results_Long!P:P,MATCH("H2b|contrast_wide|defined|tau_avg",Results_Long!AK:AK,0)),3)&"; "&ROUND(INDEX(Results_Long!Q:Q,MATCH("H2b|contrast_wide|defined|tau_avg",Results_Long!AK:AK,0)),3)&"]" -> [0.235; 0.307]
A8: package default (mNormal(0, 0.25), meandif) | B8: 113 | C8: — (see note) | F8: =INDEX(Results_Long!AG:AG,MATCH("H2b|factor_default|defined|bf01_period",Results_Long!AK:AK,0)) -> 8.4916592 | G8: =IF(F8=0,"saturated",IF(F8<1,"favours inclusion (read BF10)",IF(F8<3,"anecdotal",IF(F8<10,"moderate",IF(F8<30,"strong","very strong"))))) -> moderate | H8: =F8/(1+F8) -> 0.89464434 | I8: =INDEX(Results_Long!K:K,MATCH("H2b|factor_default|defined|tau_avg",Results_Long!AK:AK,0)) -> 0.26728219 | J8: ="["&ROUND(INDEX(Results_Long!P:P,MATCH("H2b|factor_default|defined|tau_avg",Results_Long!AK:AK,0)),3)&"; "&ROUND(INDEX(Results_Long!Q:Q,MATCH("H2b|factor_default|defined|tau_avg",Results_Long!AK:AK,0)),3)&"]" -> [0.235; 0.306] | K8: DIAGNOSTIC CAVEAT: 23 warnings (16× adaptation not completed; Model 56 R-hat 1.174; ESS min 98). Coefficient row intentionally not reported (package-internal parameterization; contrast claims live on the treatment fits) [DEC-046].
A11: Interpretation (mechanical)
A12: Primary BF01(period) = 1.03 — inside the 1–3 band ⇒ per the pinned E3 mapping this is an equivalence-register input, not a ≥3 "full" input; wide prior: 1.17.
A13: Package-default prior yields BF01 = 8.49 (moderate band) — reported with the disclosed convergence caveats and the diffuse-prior mechanics of tab 3; the primary carries the pre-specified SESOI scale.
A14: Contrast +0.003 z [−0.031; +0.045] (informed) and +0.009 [−0.045; +0.079] (wide) — both inside the ±0.05 secondary band; coherent with the frequentist E2 contrast (+0.010, p = .582, p_TOST = .022).
A15: τ ≈ 0.267 in every set: adding the period term leaves the heterogeneity level unchanged (mechanical).
A17: Question | B17: Answer
A18: Why no coefficient for the package-default set? | B18: Its contrast is the package-internal mean-difference parameterization (mNormal(0, 0.25), evidenced in FITMETA); reporting its coefficient would mix parameterizations. Contrast estimates are claimed only on the treatment-contrast fits; the default set contributes its BF (deterministic row budget, disclosed) [DEC-046].
A19: Why are the H2b level priors package defaults rather than COE-informed? | B19: Level inference is single-homed in H2a; H2b pre-specifies only the moderator prior [DEC-045]. The intercept prior does not carry the moderation claim.
A20: Model 56 shows R-hat 1.174 — why is the fit not not_estimable? | B20: Listed non-convergence signatures are metadata by design (P-T5-4 analog): the fit returned and extraction verified. The caveat is disclosed at the affected (non-primary) set; the primary fit carried one benign warning (72-model notice).
A21: Are the three BF01 values comparable? | B21: Only mechanically: inclusion BFs are prior-dependent, and the default set uses a different contrast parameterization and width. The pre-specified comparison object is the contrast-informed value; the others bracket prior sensitivity.
A22: BF01 = 1.03 — does that decide the wording tier? | B22: No. Band membership (1–3) is a mechanical gate input; the tier decision is the documented resolution step [DEC-044] and gets its own DEC.
A24: Verdict — Mechanical outcome: BF01(period) = 1.03 (contrast-informed, primary) / 1.17 (wide) / 8.49 (package default, with disclosed convergence caveats); contrast +0.003 z [−0.031; +0.045]; adjudication deferred to the documented gate-resolution step [DEC-044].

Sheet Results_Long
A1: analysis_id | B1: spec | C1: subset | D1: term | E1: metric | F1: estimator | G1: rho | H1: k_es | I1: k_study | J1: k_cluster | K1: est_z | L1: se_z | M1: t_stat | N1: df | O1: p | P1: ci_lb_z | Q1: ci_ub_z | R1: pi_lb_z | S1: pi_ub_z | T1: est_r | U1: ci_lb_r | V1: ci_ub_r | W1: pi_lb_r | X1: pi_ub_r | Y1: sigma2_cluster | Z1: sigma2_study | AA1: sigma2_esid | AB1: pct_cluster | AC1: pct_study | AD1: pct_esid | AE1: pct_sampling | AF1: typical_v | AG1: value | AH1: ms_input | AI1: ms_label | AJ1: note | AK1: wb_key (workbook helper, not in CSV)
A2: H2a | B2: psma_default | C2: full | D2: mu_avg | E2: Fisher_z | F2: RoBMA_3.6.1 | G2: 0.6 | H2: 2713 | I2: 115 | J2: 114 | K2: 0.0081709402 | P2: 0 | Q2: 0.11030527 | T2: 0.0081707583 | U2: 0 | V2: 0.10986006 | AH2: TRUE | AI2: robma_mu_primary | AJ2: RoBMA 3.6.1 [DEC-046]; y/se input, transformation="none", prior_scale="none" (priors act on Fisher-z verbatim); effect_direction="negative" [P-T5-2]; seed 20260710; sequential chains, 3.x defaults incl. autofit=TRUE; one-effect-per-cluster aggregates: metafor aggregate.escalc, struct="CS", rho=0.6 (T1/A5 convention [DEC-031g/F65]); PSMA package defaults (primary [DEC-031b]); default priors echoed verbatim in run_meta; estimation set 2713/115/114 [DEC-042a]; k = 114 aggregates; model-averaged posterior mean, 95% central CI; summary row 'mu' | AK2: =A2&"|"&B2&"|"&C2&"|"&D2 -> H2a|psma_default|full|mu_avg
A3: H2a | B3: psma_default | C3: full | D3: tau_avg | E3: tau | F3: RoBMA_3.6.1 | G3: 0.6 | H3: 2713 | I3: 115 | J3: 114 | K3: 0.26616287 | P3: 0.23365346 | Q3: 0.30607817 | AH3: FALSE | AJ3: RoBMA 3.6.1 [DEC-046]; y/se input, transformation="none", prior_scale="none" (priors act on Fisher-z verbatim); effect_direction="negative" [P-T5-2]; seed 20260710; sequential chains, 3.x defaults incl. autofit=TRUE; one-effect-per-cluster aggregates: metafor aggregate.escalc, struct="CS", rho=0.6 (T1/A5 convention [DEC-031g/F65]); PSMA package defaults (primary [DEC-031b]); default priors echoed verbatim in run_meta; estimation set 2713/115/114 [DEC-042a]; k = 114 aggregates; model-averaged tau on the Fisher-z scale; no tanh (scale parameter) | AK3: =A3&"|"&B3&"|"&C3&"|"&D3 -> H2a|psma_default|full|tau_avg
A4: H2a | B4: psma_default | C4: full | D4: bf01_effect | E4: BF01 | F4: RoBMA_3.6.1 | G4: 0.6 | H4: 2713 | I4: 115 | J4: 114 | AG4: 7.0327785 | AH4: TRUE | AI4: bf01_level_primary | AJ4: RoBMA 3.6.1 [DEC-046]; y/se input, transformation="none", prior_scale="none" (priors act on Fisher-z verbatim); effect_direction="negative" [P-T5-2]; seed 20260710; sequential chains, 3.x defaults incl. autofit=TRUE; one-effect-per-cluster aggregates: metafor aggregate.escalc, struct="CS", rho=0.6 (T1/A5 convention [DEC-031g/F65]); PSMA package defaults (primary [DEC-031b]); default priors echoed verbatim in run_meta; estimation set 2713/115/114 [DEC-042a]; k = 114 aggregates; inclusion BF10 (effect) = 0.142191; BF01 = 1/BF10 quantifies evidence FOR the null of the effect component; raw value, band labelling downstream [DEC-044] | AK4: =A4&"|"&B4&"|"&C4&"|"&D4 -> H2a|psma_default|full|bf01_effect
A5: H2a | B5: psma_default | C5: full | D5: bf01_heterogeneity | E5: BF01 | F5: RoBMA_3.6.1 | G5: 0.6 | H5: 2713 | I5: 115 | J5: 114 | AG5: 0 | AH5: FALSE | AJ5: RoBMA 3.6.1 [DEC-046]; y/se input, transformation="none", prior_scale="none" (priors act on Fisher-z verbatim); effect_direction="negative" [P-T5-2]; seed 20260710; sequential chains, 3.x defaults incl. autofit=TRUE; one-effect-per-cluster aggregates: metafor aggregate.escalc, struct="CS", rho=0.6 (T1/A5 convention [DEC-031g/F65]); PSMA package defaults (primary [DEC-031b]); default priors echoed verbatim in run_meta; estimation set 2713/115/114 [DEC-042a]; k = 114 aggregates; inclusion BF10 (heterogeneity) = Inf; BF01 = 1/BF10; SATURATED: posterior inclusion probability at the floating-point boundary — BF beyond double-precision resolution, raw pair Inf/0 preserved [#18] | AK5: =A5&"|"&B5&"|"&C5&"|"&D5 -> H2a|psma_default|full|bf01_heterogeneity
A6: H2a | B6: psma_default | C6: full | D6: bf01_bias | E6: BF01 | F6: RoBMA_3.6.1 | G6: 0.6 | H6: 2713 | I6: 115 | J6: 114 | AG6: 0.010554327 | AH6: FALSE | AJ6: RoBMA 3.6.1 [DEC-046]; y/se input, transformation="none", prior_scale="none" (priors act on Fisher-z verbatim); effect_direction="negative" [P-T5-2]; seed 20260710; sequential chains, 3.x defaults incl. autofit=TRUE; one-effect-per-cluster aggregates: metafor aggregate.escalc, struct="CS", rho=0.6 (T1/A5 convention [DEC-031g/F65]); PSMA package defaults (primary [DEC-031b]); default priors echoed verbatim in run_meta; estimation set 2713/115/114 [DEC-042a]; k = 114 aggregates; inclusion BF10 (publication bias) = 94.7479; BF01 = 1/BF10 | AK6: =A6&"|"&B6&"|"&C6&"|"&D6 -> H2a|psma_default|full|bf01_bias
A7: H2a | B7: coe_informed | C7: full | D7: mu_avg | E7: Fisher_z | F7: RoBMA_3.6.1 | G7: 0.6 | H7: 2713 | I7: 115 | J7: 114 | K7: -0.0094975802 | P7: -0.062434078 | Q7: 0 | T7: -0.0094972946 | U7: -0.062353081 | V7: 0 | AH7: FALSE | AJ7: RoBMA 3.6.1 [DEC-046]; y/se input, transformation="none", prior_scale="none" (priors act on Fisher-z verbatim); effect_direction="negative" [P-T5-2]; seed 20260710; sequential chains, 3.x defaults incl. autofit=TRUE; one-effect-per-cluster aggregates: metafor aggregate.escalc, struct="CS", rho=0.6 (T1/A5 convention [DEC-031g/F65]); COE-informed effect prior Normal(-0.041, 0.021173); sigma = 0.083/3.92 = 0.0212 [DEC-031b provenance arithmetic]; COE companion = only admissible external prior source; estimation set 2713/115/114 [DEC-042a]; k = 114 aggregates; model-averaged posterior mean, 95% central CI; summary row 'mu' | AK7: =A7&"|"&B7&"|"&C7&"|"&D7 -> H2a|coe_informed|full|mu_avg
A8: H2a | B8: coe_informed | C8: full | D8: tau_avg | E8: tau | F8: RoBMA_3.6.1 | G8: 0.6 | H8: 2713 | I8: 115 | J8: 114 | K8: 0.26404121 | P8: 0.23215249 | Q8: 0.30178222 | AH8: FALSE | AJ8: RoBMA 3.6.1 [DEC-046]; y/se input, transformation="none", prior_scale="none" (priors act on Fisher-z verbatim); effect_direction="negative" [P-T5-2]; seed 20260710; sequential chains, 3.x defaults incl. autofit=TRUE; one-effect-per-cluster aggregates: metafor aggregate.escalc, struct="CS", rho=0.6 (T1/A5 convention [DEC-031g/F65]); COE-informed effect prior Normal(-0.041, 0.021173); sigma = 0.083/3.92 = 0.0212 [DEC-031b provenance arithmetic]; COE companion = only admissible external prior source; estimation set 2713/115/114 [DEC-042a]; k = 114 aggregates; model-averaged tau on the Fisher-z scale; no tanh (scale parameter) | AK8: =A8&"|"&B8&"|"&C8&"|"&D8 -> H2a|coe_informed|full|tau_avg
A9: H2a | B9: coe_informed | C9: full | D9: bf01_effect | E9: BF01 | F9: RoBMA_3.6.1 | G9: 0.6 | H9: 2713 | I9: 115 | J9: 114 | AG9: 2.3846462 | AH9: FALSE | AJ9: RoBMA 3.6.1 [DEC-046]; y/se input, transformation="none", prior_scale="none" (priors act on Fisher-z verbatim); effect_direction="negative" [P-T5-2]; seed 20260710; sequential chains, 3.x defaults incl. autofit=TRUE; one-effect-per-cluster aggregates: metafor aggregate.escalc, struct="CS", rho=0.6 (T1/A5 convention [DEC-031g/F65]); COE-informed effect prior Normal(-0.041, 0.021173); sigma = 0.083/3.92 = 0.0212 [DEC-031b provenance arithmetic]; COE companion = only admissible external prior source; estimation set 2713/115/114 [DEC-042a]; k = 114 aggregates; inclusion BF10 (effect) = 0.419349; BF01 = 1/BF10 quantifies evidence FOR the null of the effect component; raw value, band labelling downstream [DEC-044] | AK9: =A9&"|"&B9&"|"&C9&"|"&D9 -> H2a|coe_informed|full|bf01_effect
A10: H2a | B10: coe_informed | C10: full | D10: bf01_heterogeneity | E10: BF01 | F10: RoBMA_3.6.1 | G10: 0.6 | H10: 2713 | I10: 115 | J10: 114 | AG10: 0 | AH10: FALSE | AJ10: RoBMA 3.6.1 [DEC-046]; y/se input, transformation="none", prior_scale="none" (priors act on Fisher-z verbatim); effect_direction="negative" [P-T5-2]; seed 20260710; sequential chains, 3.x defaults incl. autofit=TRUE; one-effect-per-cluster aggregates: metafor aggregate.escalc, struct="CS", rho=0.6 (T1/A5 convention [DEC-031g/F65]); COE-informed effect prior Normal(-0.041, 0.021173); sigma = 0.083/3.92 = 0.0212 [DEC-031b provenance arithmetic]; COE companion = only admissible external prior source; estimation set 2713/115/114 [DEC-042a]; k = 114 aggregates; inclusion BF10 (heterogeneity) = Inf; BF01 = 1/BF10; SATURATED: posterior inclusion probability at the floating-point boundary — BF beyond double-precision resolution, raw pair Inf/0 preserved [#18] | AK10: =A10&"|"&B10&"|"&C10&"|"&D10 -> H2a|coe_informed|full|bf01_heterogeneity
A11: H2a | B11: coe_informed | C11: full | D11: bf01_bias | E11: BF01 | F11: RoBMA_3.6.1 | G11: 0.6 | H11: 2713 | I11: 115 | J11: 114 | AG11: 0.090226363 | AH11: FALSE | AJ11: RoBMA 3.6.1 [DEC-046]; y/se input, transformation="none", prior_scale="none" (priors act on Fisher-z verbatim); effect_direction="negative" [P-T5-2]; seed 20260710; sequential chains, 3.x defaults incl. autofit=TRUE; one-effect-per-cluster aggregates: metafor aggregate.escalc, struct="CS", rho=0.6 (T1/A5 convention [DEC-031g/F65]); COE-informed effect prior Normal(-0.041, 0.021173); sigma = 0.083/3.92 = 0.0212 [DEC-031b provenance arithmetic]; COE companion = only admissible external prior source; estimation set 2713/115/114 [DEC-042a]; k = 114 aggregates; inclusion BF10 (publication bias) = 11.0832; BF01 = 1/BF10 | AK11: =A11&"|"&B11&"|"&C11&"|"&D11 -> H2a|coe_informed|full|bf01_bias
A12: H2a | B12: coe_wide | C12: full | D12: mu_avg | E12: Fisher_z | F12: RoBMA_3.6.1 | G12: 0.6 | H12: 2713 | I12: 115 | J12: 114 | K12: -0.0010362035 | P12: -0.065578719 | Q12: 0.051649252 | T12: -0.0010362032 | U12: -0.065484872 | V12: 0.051603373 | AH12: FALSE | AJ12: RoBMA 3.6.1 [DEC-046]; y/se input, transformation="none", prior_scale="none" (priors act on Fisher-z verbatim); effect_direction="negative" [P-T5-2]; seed 20260710; sequential chains, 3.x defaults incl. autofit=TRUE; one-effect-per-cluster aggregates: metafor aggregate.escalc, struct="CS", rho=0.6 (T1/A5 convention [DEC-031g/F65]); wide effect prior Normal(-0.041, 0.042347) = 2 x COE sigma (~0.042) [DEC-045]; estimation set 2713/115/114 [DEC-042a]; k = 114 aggregates; model-averaged posterior mean, 95% central CI; summary row 'mu' | AK12: =A12&"|"&B12&"|"&C12&"|"&D12 -> H2a|coe_wide|full|mu_avg
A13: H2a | B13: coe_wide | C13: full | D13: tau_avg | E13: tau | F13: RoBMA_3.6.1 | G13: 0.6 | H13: 2713 | I13: 115 | J13: 114 | K13: 0.26525439 | P13: 0.23248238 | Q13: 0.30353637 | AH13: FALSE | AJ13: RoBMA 3.6.1 [DEC-046]; y/se input, transformation="none", prior_scale="none" (priors act on Fisher-z verbatim); effect_direction="negative" [P-T5-2]; seed 20260710; sequential chains, 3.x defaults incl. autofit=TRUE; one-effect-per-cluster aggregates: metafor aggregate.escalc, struct="CS", rho=0.6 (T1/A5 convention [DEC-031g/F65]); wide effect prior Normal(-0.041, 0.042347) = 2 x COE sigma (~0.042) [DEC-045]; estimation set 2713/115/114 [DEC-042a]; k = 114 aggregates; model-averaged tau on the Fisher-z scale; no tanh (scale parameter) | AK13: =A13&"|"&B13&"|"&C13&"|"&D13 -> H2a|coe_wide|full|tau_avg
A14: H2a | B14: coe_wide | C14: full | D14: bf01_effect | E14: BF01 | F14: RoBMA_3.6.1 | G14: 0.6 | H14: 2713 | I14: 115 | J14: 114 | AG14: 1.6935977 | AH14: FALSE | AJ14: RoBMA 3.6.1 [DEC-046]; y/se input, transformation="none", prior_scale="none" (priors act on Fisher-z verbatim); effect_direction="negative" [P-T5-2]; seed 20260710; sequential chains, 3.x defaults incl. autofit=TRUE; one-effect-per-cluster aggregates: metafor aggregate.escalc, struct="CS", rho=0.6 (T1/A5 convention [DEC-031g/F65]); wide effect prior Normal(-0.041, 0.042347) = 2 x COE sigma (~0.042) [DEC-045]; estimation set 2713/115/114 [DEC-042a]; k = 114 aggregates; inclusion BF10 (effect) = 0.590459; BF01 = 1/BF10 quantifies evidence FOR the null of the effect component; raw value, band labelling downstream [DEC-044] | AK14: =A14&"|"&B14&"|"&C14&"|"&D14 -> H2a|coe_wide|full|bf01_effect
A15: H2a | B15: coe_wide | C15: full | D15: bf01_heterogeneity | E15: BF01 | F15: RoBMA_3.6.1 | G15: 0.6 | H15: 2713 | I15: 115 | J15: 114 | AG15: 0 | AH15: FALSE | AJ15: RoBMA 3.6.1 [DEC-046]; y/se input, transformation="none", prior_scale="none" (priors act on Fisher-z verbatim); effect_direction="negative" [P-T5-2]; seed 20260710; sequential chains, 3.x defaults incl. autofit=TRUE; one-effect-per-cluster aggregates: metafor aggregate.escalc, struct="CS", rho=0.6 (T1/A5 convention [DEC-031g/F65]); wide effect prior Normal(-0.041, 0.042347) = 2 x COE sigma (~0.042) [DEC-045]; estimation set 2713/115/114 [DEC-042a]; k = 114 aggregates; inclusion BF10 (heterogeneity) = Inf; BF01 = 1/BF10; SATURATED: posterior inclusion probability at the floating-point boundary — BF beyond double-precision resolution, raw pair Inf/0 preserved [#18] | AK15: =A15&"|"&B15&"|"&C15&"|"&D15 -> H2a|coe_wide|full|bf01_heterogeneity
A16: H2a | B16: coe_wide | C16: full | D16: bf01_bias | E16: BF01 | F16: RoBMA_3.6.1 | G16: 0.6 | H16: 2713 | I16: 115 | J16: 114 | AG16: 0.059387472 | AH16: FALSE | AJ16: RoBMA 3.6.1 [DEC-046]; y/se input, transformation="none", prior_scale="none" (priors act on Fisher-z verbatim); effect_direction="negative" [P-T5-2]; seed 20260710; sequential chains, 3.x defaults incl. autofit=TRUE; one-effect-per-cluster aggregates: metafor aggregate.escalc, struct="CS", rho=0.6 (T1/A5 convention [DEC-031g/F65]); wide effect prior Normal(-0.041, 0.042347) = 2 x COE sigma (~0.042) [DEC-045]; estimation set 2713/115/114 [DEC-042a]; k = 114 aggregates; inclusion BF10 (publication bias) = 16.8386; BF01 = 1/BF10 | AK16: =A16&"|"&B16&"|"&C16&"|"&D16 -> H2a|coe_wide|full|bf01_bias
A17: H2b | B17: contrast_informed | C17: defined | D17: coef_period | E17: z_diff | F17: RoBMA_3.6.1 | G17: 0.6 | H17: 2705 | I17: 113 | J17: 113 | K17: 0.0033709677 | P17: -0.031265933 | Q17: 0.044514467 | AH17: TRUE | AI17: robma_contrast_primary | AJ17: RoBMA 3.6.1 [DEC-046]; y/se input, transformation="none", prior_scale="none" (priors act on Fisher-z verbatim); effect_direction="negative" [P-T5-2]; seed 20260710; sequential chains, 3.x defaults incl. autofit=TRUE; one-effect-per-cluster aggregates: metafor aggregate.escalc, struct="CS", rho=0.6 (T1/A5 convention [DEC-031g/F65]); RoBMA.reg [DEC-045: only admissible moderation route]; contrast prior Normal(0, 0.025) on the post-minus-pre period contrast (treatment contrast, ref = pre); sigma from the SECONDARY SESOI +-0.05 ~ +-2 sigma [DEC-045]; period domain 2705/113/112 [DEC-042b]; 113 cluster x period rows (pre 82 + post 31; both-period cluster n = 1, disclosed: Li et al (2022)); post-minus-pre contrast on the Fisher-z scale; z-only, no tanh transform of differences; summary row 'period[post]' | AK17: =A17&"|"&B17&"|"&C17&"|"&D17 -> H2b|contrast_informed|defined|coef_period
A18: H2b | B18: contrast_informed | C18: defined | D18: bf01_period | E18: BF01 | F18: RoBMA_3.6.1 | G18: 0.6 | H18: 2705 | I18: 113 | J18: 113 | AG18: 1.0349179 | AH18: TRUE | AI18: bf01_moderation_primary | AJ18: RoBMA 3.6.1 [DEC-046]; y/se input, transformation="none", prior_scale="none" (priors act on Fisher-z verbatim); effect_direction="negative" [P-T5-2]; seed 20260710; sequential chains, 3.x defaults incl. autofit=TRUE; one-effect-per-cluster aggregates: metafor aggregate.escalc, struct="CS", rho=0.6 (T1/A5 convention [DEC-031g/F65]); RoBMA.reg [DEC-045: only admissible moderation route]; contrast prior Normal(0, 0.025) on the post-minus-pre period contrast (treatment contrast, ref = pre); sigma from the SECONDARY SESOI +-0.05 ~ +-2 sigma [DEC-045]; period domain 2705/113/112 [DEC-042b]; 113 cluster x period rows (pre 82 + post 31; both-period cluster n = 1, disclosed: Li et al (2022)); inclusion BF10 (period moderator) = 0.96626; BF01 = 1/BF10 quantifies evidence FOR the null of Paris moderation; raw value, band labelling downstream [DEC-044] | AK18: =A18&"|"&B18&"|"&C18&"|"&D18 -> H2b|contrast_informed|defined|bf01_period
A19: H2b | B19: contrast_informed | C19: defined | D19: tau_avg | E19: tau | F19: RoBMA_3.6.1 | G19: 0.6 | H19: 2705 | I19: 113 | J19: 113 | K19: 0.2670922 | P19: 0.2349918 | Q19: 0.30632159 | AH19: FALSE | AJ19: RoBMA 3.6.1 [DEC-046]; y/se input, transformation="none", prior_scale="none" (priors act on Fisher-z verbatim); effect_direction="negative" [P-T5-2]; seed 20260710; sequential chains, 3.x defaults incl. autofit=TRUE; one-effect-per-cluster aggregates: metafor aggregate.escalc, struct="CS", rho=0.6 (T1/A5 convention [DEC-031g/F65]); RoBMA.reg [DEC-045: only admissible moderation route]; contrast prior Normal(0, 0.025) on the post-minus-pre period contrast (treatment contrast, ref = pre); sigma from the SECONDARY SESOI +-0.05 ~ +-2 sigma [DEC-045]; period domain 2705/113/112 [DEC-042b]; 113 cluster x period rows (pre 82 + post 31; both-period cluster n = 1, disclosed: Li et al (2022)); model-averaged tau on the Fisher-z scale | AK19: =A19&"|"&B19&"|"&C19&"|"&D19 -> H2b|contrast_informed|defined|tau_avg
A20: H2b | B20: contrast_wide | C20: defined | D20: coef_period | E20: z_diff | F20: RoBMA_3.6.1 | G20: 0.6 | H20: 2705 | I20: 113 | J20: 113 | K20: 0.0086887497 | P20: -0.044825406 | Q20: 0.079460463 | AH20: FALSE | AJ20: RoBMA 3.6.1 [DEC-046]; y/se input, transformation="none", prior_scale="none" (priors act on Fisher-z verbatim); effect_direction="negative" [P-T5-2]; seed 20260710; sequential chains, 3.x defaults incl. autofit=TRUE; one-effect-per-cluster aggregates: metafor aggregate.escalc, struct="CS", rho=0.6 (T1/A5 convention [DEC-031g/F65]); RoBMA.reg [DEC-045: only admissible moderation route]; wide contrast prior Normal(0, 0.050), treatment contrast (ref = pre) [DEC-045]; period domain 2705/113/112 [DEC-042b]; 113 cluster x period rows (pre 82 + post 31; both-period cluster n = 1, disclosed: Li et al (2022)); post-minus-pre contrast on the Fisher-z scale; z-only, no tanh transform of differences; summary row 'period[post]' | AK20: =A20&"|"&B20&"|"&C20&"|"&D20 -> H2b|contrast_wide|defined|coef_period
A21: H2b | B21: contrast_wide | C21: defined | D21: bf01_period | E21: BF01 | F21: RoBMA_3.6.1 | G21: 0.6 | H21: 2705 | I21: 113 | J21: 113 | AG21: 1.1669526 | AH21: FALSE | AJ21: RoBMA 3.6.1 [DEC-046]; y/se input, transformation="none", prior_scale="none" (priors act on Fisher-z verbatim); effect_direction="negative" [P-T5-2]; seed 20260710; sequential chains, 3.x defaults incl. autofit=TRUE; one-effect-per-cluster aggregates: metafor aggregate.escalc, struct="CS", rho=0.6 (T1/A5 convention [DEC-031g/F65]); RoBMA.reg [DEC-045: only admissible moderation route]; wide contrast prior Normal(0, 0.050), treatment contrast (ref = pre) [DEC-045]; period domain 2705/113/112 [DEC-042b]; 113 cluster x period rows (pre 82 + post 31; both-period cluster n = 1, disclosed: Li et al (2022)); inclusion BF10 (period moderator) = 0.856933; BF01 = 1/BF10 quantifies evidence FOR the null of Paris moderation; raw value, band labelling downstream [DEC-044] | AK21: =A21&"|"&B21&"|"&C21&"|"&D21 -> H2b|contrast_wide|defined|bf01_period
A22: H2b | B22: contrast_wide | C22: defined | D22: tau_avg | E22: tau | F22: RoBMA_3.6.1 | G22: 0.6 | H22: 2705 | I22: 113 | J22: 113 | K22: 0.26726931 | P22: 0.2345787 | Q22: 0.30666886 | AH22: FALSE | AJ22: RoBMA 3.6.1 [DEC-046]; y/se input, transformation="none", prior_scale="none" (priors act on Fisher-z verbatim); effect_direction="negative" [P-T5-2]; seed 20260710; sequential chains, 3.x defaults incl. autofit=TRUE; one-effect-per-cluster aggregates: metafor aggregate.escalc, struct="CS", rho=0.6 (T1/A5 convention [DEC-031g/F65]); RoBMA.reg [DEC-045: only admissible moderation route]; wide contrast prior Normal(0, 0.050), treatment contrast (ref = pre) [DEC-045]; period domain 2705/113/112 [DEC-042b]; 113 cluster x period rows (pre 82 + post 31; both-period cluster n = 1, disclosed: Li et al (2022)); model-averaged tau on the Fisher-z scale | AK22: =A22&"|"&B22&"|"&C22&"|"&D22 -> H2b|contrast_wide|defined|tau_avg
A23: H2b | B23: factor_default | C23: defined | D23: bf01_period | E23: BF01 | F23: RoBMA_3.6.1 | G23: 0.6 | H23: 2705 | I23: 113 | J23: 113 | AG23: 8.4916592 | AH23: FALSE | AJ23: RoBMA 3.6.1 [DEC-046]; y/se input, transformation="none", prior_scale="none" (priors act on Fisher-z verbatim); effect_direction="negative" [P-T5-2]; seed 20260710; sequential chains, 3.x defaults incl. autofit=TRUE; one-effect-per-cluster aggregates: metafor aggregate.escalc, struct="CS", rho=0.6 (T1/A5 convention [DEC-031g/F65]); RoBMA.reg [DEC-045: only admissible moderation route]; package default factor prior and contrast (echoed verbatim in run_meta); coefficient row intentionally not reported for this set (package-internal parameterization; contrast estimate claims live on the treatment-contrast fits) [DEC-046]; period domain 2705/113/112 [DEC-042b]; 113 cluster x period rows (pre 82 + post 31; both-period cluster n = 1, disclosed: Li et al (2022)); inclusion BF10 (period moderator) = 0.117763; BF01 = 1/BF10 quantifies evidence FOR the null of Paris moderation; raw value, band labelling downstream [DEC-044] | AK23: =A23&"|"&B23&"|"&C23&"|"&D23 -> H2b|factor_default|defined|bf01_period
A24: H2b | B24: factor_default | C24: defined | D24: tau_avg | E24: tau | F24: RoBMA_3.6.1 | G24: 0.6 | H24: 2705 | I24: 113 | J24: 113 | K24: 0.26728219 | P24: 0.23508539 | Q24: 0.30590931 | AH24: FALSE | AJ24: RoBMA 3.6.1 [DEC-046]; y/se input, transformation="none", prior_scale="none" (priors act on Fisher-z verbatim); effect_direction="negative" [P-T5-2]; seed 20260710; sequential chains, 3.x defaults incl. autofit=TRUE; one-effect-per-cluster aggregates: metafor aggregate.escalc, struct="CS", rho=0.6 (T1/A5 convention [DEC-031g/F65]); RoBMA.reg [DEC-045: only admissible moderation route]; package default factor prior and contrast (echoed verbatim in run_meta); coefficient row intentionally not reported for this set (package-internal parameterization; contrast estimate claims live on the treatment-contrast fits) [DEC-046]; period domain 2705/113/112 [DEC-042b]; 113 cluster x period rows (pre 82 + post 31; both-period cluster n = 1, disclosed: Li et al (2022)); model-averaged tau on the Fisher-z scale | AK24: =A24&"|"&B24&"|"&C24&"|"&D24 -> H2b|factor_default|defined|tau_avg
A25: TH_b_design | B25: design | C25: full | D25: subset_estimation | E25: count | F25: descriptive | AG25: 2713 | AH25: FALSE | AJ25: 2713 ES / 115 studies / 114 clusters [DEC-042a]; H2a domain | AK25: =A25&"|"&B25&"|"&C25&"|"&D25 -> TH_b_design|design|full|subset_estimation
A26: TH_b_design | B26: design | C26: full | D26: agg_k_full | E26: count | F26: descriptive | AG26: 114 | AH26: FALSE | AJ26: one-effect-per-cluster aggregates: metafor aggregate.escalc, struct="CS", rho=0.6 (T1/A5 convention [DEC-031g/F65]); H2a basis | AK26: =A26&"|"&B26&"|"&C26&"|"&D26 -> TH_b_design|design|full|agg_k_full
A27: TH_b_design | B27: design | C27: full | D27: h2b_domain_es | E27: count | F27: descriptive | AG27: 2705 | AH27: FALSE | AJ27: 2705 ES / 113 studies / 112 clusters [DEC-042b]; H2b domain | AK27: =A27&"|"&B27&"|"&C27&"|"&D27 -> TH_b_design|design|full|h2b_domain_es
A28: TH_b_design | B28: design | C28: full | D28: h2b_rows | E28: count | F28: descriptive | AG28: 113 | AH28: FALSE | AJ28: cluster x period aggregate rows [DEC-045]; per-cell D2 aggregation | AK28: =A28&"|"&B28&"|"&C28&"|"&D28 -> TH_b_design|design|full|h2b_rows
A29: TH_b_design | B29: design | C29: full | D29: h2b_rows_pre | E29: count | F29: descriptive | AG29: 82 | AH29: FALSE | AJ29: pre-cell aggregates (= 113 - 31, arithmetic pin) | AK29: =A29&"|"&B29&"|"&C29&"|"&D29 -> TH_b_design|design|full|h2b_rows_pre
A30: TH_b_design | B30: design | C30: full | D30: h2b_rows_post | E30: count | F30: descriptive | AG30: 31 | AH30: FALSE | AJ30: post-cell aggregates [DEC-042b; v12 design constant] | AK30: =A30&"|"&B30&"|"&C30&"|"&D30 -> TH_b_design|design|full|h2b_rows_post
A31: TH_b_design | B31: design | C31: full | D31: h2b_both_period_clusters | E31: count | F31: descriptive | AG31: 1 | AH31: FALSE | AJ31: single both-period cluster (disclosed): Li et al (2022) [DEC-045] | AK31: =A31&"|"&B31&"|"&C31&"|"&D31 -> TH_b_design|design|full|h2b_both_period_clusters

Sheet Manuscript_Inputs
A1: Manuscript inputs — ms_input = TRUE rows (formula-derived from Results_Long)
A2: String assembly is arithmetic (sign & INT & "." & padded fraction) — locale-neutral; deviation from template TEXT() disclosed (tab 4).
A3: Columns E–J are visible calc helpers (ABS-rounded value + INT part per number).
A5: ms_label | B5: v1 | C5: v2 | D5: v3 | E5: a1 | F5: i1 | G5: a2 | H5: i2 | I5: a3 | J5: i3 | K5: paste-ready string (EN)
A6: robma_mu_primary | B6: =INDEX(Results_Long!K:K,MATCH("H2a|psma_default|full|mu_avg",Results_Long!AK:AK,0)) -> 0.0081709402 | C6: =INDEX(Results_Long!P:P,MATCH("H2a|psma_default|full|mu_avg",Results_Long!AK:AK,0)) -> 0 | D6: =INDEX(Results_Long!Q:Q,MATCH("H2a|psma_default|full|mu_avg",Results_Long!AK:AK,0)) -> 0.11030527 | E6: =ROUND(ABS(B6),3) -> 0.008 | F6: =INT(E6) -> 0 | G6: =ROUND(ABS(C6),3) -> 0 | H6: =INT(G6) -> 0 | I6: =ROUND(ABS(D6),3) -> 0.11 | J6: =INT(I6) -> 0 | K6: ="Model-averaged pooled association (RoBMA, PSMA defaults): z = "&IF(B6<0,"-","")&F6&"."&RIGHT(REPT("0",3)&ROUND((E6-F6)*10^3,0),3)&" (95% CI "&IF(C6<0,"-","")&H6&"."&RIGHT(REPT("0",3)&ROUND((G6-H6)*10^3,0),3)&" to "&IF(D6<0,"-","")&J6&"."&RIGHT(REPT("0",3)&ROUND((I6-J6)*10^3,0),3)&")." -> Model-averaged pooled association (RoBMA, PSMA defaults): z = 0.008 (95% CI 0.000 to 0.110).
A7: bf01_level_primary | B7: =INDEX(Results_Long!AG:AG,MATCH("H2a|psma_default|full|bf01_effect",Results_Long!AK:AK,0)) -> 7.0327785 | C7: =1/B7 -> 0.14219131 | E7: =ROUND(ABS(B7),2) -> 7.03 | F7: =INT(E7) -> 7 | G7: =ROUND(ABS(C7),3) -> 0.142 | H7: =INT(G7) -> 0 | K7: ="Inclusion Bayes factor, pooled-effect component (PSMA defaults): BF01 = "&IF(B7<0,"-","")&F7&"."&RIGHT(REPT("0",2)&ROUND((E7-F7)*10^2,0),2)&" (BF10 = "&IF(C7<0,"-","")&H7&"."&RIGHT(REPT("0",3)&ROUND((G7-H7)*10^3,0),3)&")." -> Inclusion Bayes factor, pooled-effect component (PSMA defaults): BF01 = 7.03 (BF10 = 0.142).
A8: bf01_moderation_primary | B8: =INDEX(Results_Long!AG:AG,MATCH("H2b|contrast_informed|defined|bf01_period",Results_Long!AK:AK,0)) -> 1.0349179 | C8: =1/B8 -> 0.96626018 | E8: =ROUND(ABS(B8),2) -> 1.03 | F8: =INT(E8) -> 1 | G8: =ROUND(ABS(C8),3) -> 0.966 | H8: =INT(G8) -> 0 | K8: ="Inclusion Bayes factor, Paris-period moderator (contrast-informed prior): BF01 = "&IF(B8<0,"-","")&F8&"."&RIGHT(REPT("0",2)&ROUND((E8-F8)*10^2,0),2)&" (BF10 = "&IF(C8<0,"-","")&H8&"."&RIGHT(REPT("0",3)&ROUND((G8-H8)*10^3,0),3)&")." -> Inclusion Bayes factor, Paris-period moderator (contrast-informed prior): BF01 = 1.03 (BF10 = 0.966).
A9: robma_contrast_primary | B9: =INDEX(Results_Long!K:K,MATCH("H2b|contrast_informed|defined|coef_period",Results_Long!AK:AK,0)) -> 0.0033709677 | C9: =INDEX(Results_Long!P:P,MATCH("H2b|contrast_informed|defined|coef_period",Results_Long!AK:AK,0)) -> -0.031265933 | D9: =INDEX(Results_Long!Q:Q,MATCH("H2b|contrast_informed|defined|coef_period",Results_Long!AK:AK,0)) -> 0.044514467 | E9: =ROUND(ABS(B9),3) -> 0.003 | F9: =INT(E9) -> 0 | G9: =ROUND(ABS(C9),3) -> 0.031 | H9: =INT(G9) -> 0 | I9: =ROUND(ABS(D9),3) -> 0.045 | J9: =INT(I9) -> 0 | K9: ="Model-averaged post-minus-pre contrast (contrast-informed): Delta-z = "&IF(B9<0,"-","+")&F9&"."&RIGHT(REPT("0",3)&ROUND((E9-F9)*10^3,0),3)&" (95% CI "&IF(C9<0,"-","+")&H9&"."&RIGHT(REPT("0",3)&ROUND((G9-H9)*10^3,0),3)&" to "&IF(D9<0,"-","+")&J9&"."&RIGHT(REPT("0",3)&ROUND((I9-J9)*10^3,0),3)&")." -> Model-averaged post-minus-pre contrast (contrast-informed): Delta-z = +0.003 (95% CI -0.031 to +0.045).

Sheet Manuscript_Text_Blocks
A1: Manuscript text blocks — TB-52…TB-56 (continue from TH-a/TH-c TB-36…TB-51)
A2: Numbers HARDCODED with this provenance: TH_b_results.csv @ run 2026-07-27, verifier O0–O14 PASS — regenerate on any re-run.
A3: Framing-neutral until the gate-resolution step; formula-live layer = Manuscript_Inputs.
A5: ID | B5: Target section | C5: Status | D5: Text (EN) | E5: Source pointers | F5: Note
A6: TB-52 | B6: Methods · Meta-analytic procedures | C6: READY | D6: Robust Bayesian model-averaging (RoBMA 3.6.1; Bartoš et al., 2022) complements the frequentist battery. Pooled models average 36 specifications — presence and absence of the effect and of between-cluster heterogeneity crossed with nine publication-selection components (six selection weight functions, PET and PEESE, and none) — and moderation models extend the space to 72 by adding the Paris-period term. Estimation uses the one-effect-per-cluster aggregates (k = 114; period cells 82 + 31 with the single both-period cluster disclosed) on the Fisher-z scale with an expected-negative orientation, three effect-prior sets (package defaults; a companion-informed prior N(−0.041, 0.021) derived from our cost-of-equity meta-analysis; a doubled-width variant), and a period-contrast prior N(0, 0.025) anchored in the secondary SESOI band, again with package-default and doubled-width variants. | E6: [DEC-031b; DEC-045; DEC-046]; [R/07]; [xlsx Tab 2]
A7: TB-53 | B7: Results · Bayesian model averaging (level) | C7: READY | D7: Model averaging leaves the pooled-effect component with limited support: BF01 = 7.03 under package defaults and 2.38 and 1.69 under the companion-informed and wide priors, with model-averaged estimates between −0.009 and +0.008 whose 95% intervals carry an exact-zero bound from the point-null spike. Heterogeneity support is saturated (BF01 = 0 at double precision in all sets), and the publication-selection block is strongly included throughout (BF10 = 94.7, 11.1, and 16.8). | E7: [xlsx Tab 6; Results_Long]; [TH_b_run_meta.txt BFPAIR]
A8: TB-54 | B8: Results · Bayesian model averaging (moderation) | C8: READY | D8: For the Paris-period moderator, the pre-specified contrast prior yields BF01 = 1.03 with a model-averaged post-minus-pre contrast of +0.003 (95% CI −0.031 to +0.045), and the doubled-width prior yields BF01 = 1.17; the package-default factor prior yields BF01 = 8.49, which we report with disclosed convergence caveats concentrated in that fit. | E8: [xlsx Tab 7; Results_Long] | F8: coherent with E2 (+0.010; p_TOST = .022)
A9: TB-55 | B9: Discussion · wording tier (gate) | C9: READY | D9: For the Paris-moderation claim we adopt the equivalence register: there is no detectable Paris-Agreement moderation, and the post-minus-pre contrast is statistically equivalent to zero within the secondary SESOI band (±0.05 on Fisher-z) — carried by the equivalence test (diff_z = +0.010, p = .582; p_TOST = .022; 90% CI [−0.022; +0.042]) and coherent with the model-averaged contrast (+0.003, 95% CI [−0.031; +0.045]). Under the pre-specified priors the Bayes factors remain anecdotal (BF01 = 1.03 / 1.17), with no support for moderation in any set (BF10 < 1 throughout); the diffuse package default yields BF01 = 8.49 and is shown as a sensitivity bracket with disclosed caveats. | E9: [DEC-044]; [xlsx Tab 7] | F9: Register per DEC-047; single-home: voiced once in Discussion, one Results cross-reference.
A10: TB-56 | B10: Limitations · prior sensitivity | C10: DRAFT | D10: Bayes-factor magnitudes for both components scale with prior width in the expected direction, which is why the pre-specified informed priors anchor the reported range and the package-default values are shown as sensitivity brackets. | E10: [xlsx Tabs 6–7] | F10: wording near-interpretive → DRAFT
