Workbook

Sheet data
A1: study | B1: outcome | C1: ES (corr_coeff) | D1: sample_size no_firms_rounded | E1: sample_size no_firm-years_rounded | F1: sample_size no_firms_source | G1: sample_size no_firm-years_source | H1: ES_measure | I1: ES_source | J1: sample_start | K1: sample_end | L1: sample_mid | M1: sample_median | N1: sample_post share_2016 | O1: sample_post share_2017 | P1: sample_post share_2018 | Q1: sample_post share_2019 | R1: pp_share_lag0 | S1: pp_mid_lag0 | T1: pp_median_lag0 | U1: pp_end_lag0 | V1: pp_start_lag0 | W1: pp_window_class | X1: pp_share_lag1 | Y1: pp_share_lag2 | Z1: pp_share_lag3 | AA1: pp_end_lag1 | AB1: pp_end_lag2 | AC1: pp_end_lag3 | AD1: pp_median split | AE1: pp_tertial split | AF1: COD_instrument | AG1: CER_measure | AH1: industry | AI1: regulation_sample_start | AJ1: regulation_sample_end | AK1: country_region | AL1: country_econ | AM1: country_culture | AN1: country_legal | AO1: q_status | AP1: q_VHB | AQ1: field | AR1: country | AS1: source | AT1: x_direction | AU1: outcome_direction | AV1: b | AW1: SE | AX1: t | AY1: p | AZ1: r_bivariate | BA1: n_obs | BB1: x_lag | BC1: estimation_method | BD1: se_clustering | BE1: subsample_dimension | BF1: subsample_value | BG1: subsample_start | BH1: subsample_end | BI1: table_no | BJ1: panel_model | BK1: page | BL1: cell_quote | BM1: construct_label_verbatim | BN1: outcome_label_verbatim | BO1: corpus_segment | BP1: cluster_id | BQ1: es_method | BR1: construct_variant | BS1: unit | BT1: duplicate | BU1: staging_file | BV1: v10_ID | BW1: d_sample_start | BX1: d_sample_end | BY1: d_country | BZ1: d_midyear | CA1: d_post_share | CB1: d_pp_mid | CC1: d_pp_any | CD1: d_fisher_z | CE1: d_es_usable | CF1: row_skey
A2: Al-Fakir Al Rabab'a et al (2023) | B2: 1307 | C2: -0.3 | D2: 3666 | E2: =IF(ISNUMBER($BA2),$BA2,IF(AND(ISNUMBER($D2),ISNUMBER($BW2),ISNUMBER($BX2)),$D2*($BX2-$BW2+1),"")) -> 58656 | H2: bivariate | I2: Correlation coefficient available | J2: =IF($BW2<>"",$BW2,"") -> 2003 | K2: =IF($BX2<>"",$BX2,"") -> 2018 | L2: =IF(AND(ISNUMBER($BW2),ISNUMBER($BX2)),($BW2+$BX2)/2,"") -> 2010.5 | M2: =IF($L2<>"",$L2,"") -> 2010.5 | N2: =IF(AND(ISNUMBER($BW2),ISNUMBER($BX2)),MIN(1,MAX(0,($BX2-2016+1)/($BX2-$BW2+1))),"") -> 0.1875 | O2: =IF(AND(ISNUMBER($BW2),ISNUMBER($BX2)),MIN(1,MAX(0,($BX2-2017+1)/($BX2-$BW2+1))),"") -> 0.125 | P2: =IF(AND(ISNUMBER($BW2),ISNUMBER($BX2)),MIN(1,MAX(0,($BX2-2018+1)/($BX2-$BW2+1))),"") -> 0.0625 | Q2: =IF(AND(ISNUMBER($BW2),ISNUMBER($BX2)),MIN(1,MAX(0,($BX2-2019+1)/($BX2-$BW2+1))),"") -> 0 | R2: =IF(AND(ISNUMBER($BW2),ISNUMBER($BX2)),MIN(1,MAX(0,($BX2-2016+1)/($BX2-$BW2+1))),"") -> 0.1875 | S2: =IF($L2<>"",IF($L2>=2015.5,1,0),"") -> 0 | T2: =IF($L2<>"",IF($L2>=2016,1,0),"") -> 0 | U2: =IF(ISNUMBER($BX2),IF($BX2>=2016,1,0),"") -> 1 | V2: =IF(ISNUMBER($BW2),IF($BW2>=2016,1,0),"") -> 0 | W2: =IF(AND(ISNUMBER($BW2),ISNUMBER($BX2)),IF($BW2>=2016,"post-only",IF($BX2<2016,"pre-only","mixed")),"") -> mixed | X2: =IF(AND(ISNUMBER($BW2),ISNUMBER($BX2)),MIN(1,MAX(0,($BX2-2017+1)/($BX2-$BW2+1))),"") -> 0.125 | Y2: =IF(AND(ISNUMBER($BW2),ISNUMBER($BX2)),MIN(1,MAX(0,($BX2-2018+1)/($BX2-$BW2+1))),"") -> 0.0625 | Z2: =IF(AND(ISNUMBER($BW2),ISNUMBER($BX2)),MIN(1,MAX(0,($BX2-2019+1)/($BX2-$BW2+1))),"") -> 0 | AA2: =IF(ISNUMBER($BX2),IF($BX2>=2017,1,0),"") -> 1 | AB2: =IF(ISNUMBER($BX2),IF($BX2>=2018,1,0),"") -> 1 | AC2: =IF(ISNUMBER($BX2),IF($BX2>=2019,1,0),"") -> 0 | AD2: =IF($L2<>"",IF($L2>2013,1,0),"") -> 0 | AE2: =IF($L2<>"",1+IF($L2>2011,1,0)+IF($L2>2014,1,0),"") -> 1 | AF2: loan (interest rate) | AG2: performance | AH2: non-sensitive | AI2: 99_NCE | AJ2: 99_NCE | AK2: =IF(AND($CF2<>"",IFERROR(INDEX(subsample_country_map!$B:$B,MATCH($CF2,subsample_country_map!$A:$A,0)),"")<>""),INDEX(subsample_country_map!$B:$B,MATCH($CF2,subsample_country_map!$A:$A,0)),INDEX(lookup!$AA:$AA,MATCH($A2,lookup!$A:$A,0))) -> 3_AsiaPac | AL2: =IF(AND($CF2<>"",IFERROR(INDEX(subsample_country_map!$C:$C,MATCH($CF2,subsample_country_map!$A:$A,0)),"")<>""),INDEX(subsample_country_map!$C:$C,MATCH($CF2,subsample_country_map!$A:$A,0)),INDEX(lookup!$AB:$AB,MATCH($A2,lookup!$A:$A,0))) -> 99_NCE | AM2: =IF(AND($CF2<>"",IFERROR(INDEX(subsample_country_map!$D:$D,MATCH($CF2,subsample_country_map!$A:$A,0)),"")<>""),INDEX(subsample_country_map!$D:$D,MATCH($CF2,subsample_country_map!$A:$A,0)),INDEX(lookup!$AC:$AC,MATCH($A2,lookup!$A:$A,0))) -> 99_NCE | AN2: =IF(AND($CF2<>"",IFERROR(INDEX(subsample_country_map!$E:$E,MATCH($CF2,subsample_country_map!$A:$A,0)),"")<>""),INDEX(subsample_country_map!$E:$E,MATCH($CF2,subsample_country_map!$A:$A,0)),INDEX(lookup!$AD:$AD,MATCH($A2,lookup!$A:$A,0))) -> 99_NCE | AO2: =INDEX(lookup!$Y:$Y,MATCH($A2,lookup!$A:$A,0)) -> 0_published | AP2: =INDEX(lookup!$Z:$Z,MATCH($A2,lookup!$A:$A,0)) -> 1_VHB high | AQ2: =INDEX(lookup!$W:$W,MATCH($A2,lookup!$A:$A,0)) -> 1_fin/acc/econ | AS2: staging | AT2: author-inverted-to-good | AU2: cost | AZ2: -0.30 | BA2: FLAG | BB2: 0 | BC2: n/a (structural) | BD2: n/a (structural) | BE2: none | BI2: Table 4 | BJ2: Correlation matrix col (1) | BK2: 8 | BL2: (2) CCP1 -0.30 [bold] | BM2: CCP1 | BN2: COD | BO2: update | BP2: Al-Fakir Al Rabab'a et al (2023) | BQ2: bivariate | BT2: 0 | BU2: staging_Al-Fakir_Al_Rababa_et_al_2023.csv | BW2: 2003 | BX2: 2018 | BY2: multi: 14 Asia-Pacific countries (Australia, China, Hong Kong, India, Indonesia, Japan, Malaysia, New Zealand, Philippines, Singapore, South Korea, Sri Lanka, Taiwan, Thailand) | BZ2: 2010.5 | CA2: 0.1875 | CB2: 0 | CC2: 1 | CD2: -0.3095196 | CE2: 1
A3: Al-Fakir Al Rabab'a et al (2023) | B3: 1308 | C3: -0.08 | D3: 3666 | E3: =IF(ISNUMBER($BA3),$BA3,IF(AND(ISNUMBER($D3),ISNUMBER($BW3),ISNUMBER($BX3)),$D3*($BX3-$BW3+1),"")) -> 58656 | H3: bivariate | I3: Correlation coefficient available | J3: =IF($BW3<>"",$BW3,"") -> 2003 | K3: =IF($BX3<>"",$BX3,"") -> 2018 | L3: =IF(AND(ISNUMBER($BW3),ISNUMBER($BX3)),($BW3+$BX3)/2,"") -> 2010.5 | M3: =IF($L3<>"",$L3,"") -> 2010.5 | N3: =IF(AND(ISNUMBER($BW3),ISNUMBER($BX3)),MIN(1,MAX(0,($BX3-2016+1)/($BX3-$BW3+1))),"") -> 0.1875 | O3: =IF(AND(ISNUMBER($BW3),ISNUMBER($BX3)),MIN(1,MAX(0,($BX3-2017+1)/($BX3-$BW3+1))),"") -> 0.125 | P3: =IF(AND(ISNUMBER($BW3),ISNUMBER($BX3)),MIN(1,MAX(0,($BX3-2018+1)/($BX3-$BW3+1))),"") -> 0.0625 | Q3: =IF(AND(ISNUMBER($BW3),ISNUMBER($BX3)),MIN(1,MAX(0,($BX3-2019+1)/($BX3-$BW3+1))),"") -> 0 | R3: =IF(AND(ISNUMBER($BW3),ISNUMBER($BX3)),MIN(1,MAX(0,($BX3-2016+1)/($BX3-$BW3+1))),"") -> 0.1875 | S3: =IF($L3<>"",IF($L3>=2015.5,1,0),"") -> 0 | T3: =IF($L3<>"",IF($L3>=2016,1,0),"") -> 0 | U3: =IF(ISNUMBER($BX3),IF($BX3>=2016,1,0),"") -> 1 | V3: =IF(ISNUMBER($BW3),IF($BW3>=2016,1,0),"") -> 0 | W3: =IF(AND(ISNUMBER($BW3),ISNUMBER($BX3)),IF($BW3>=2016,"post-only",IF($BX3<2016,"pre-only","mixed")),"") -> mixed | X3: =IF(AND(ISNUMBER($BW3),ISNUMBER($BX3)),MIN(1,MAX(0,($BX3-2017+1)/($BX3-$BW3+1))),"") -> 0.125 | Y3: =IF(AND(ISNUMBER($BW3),ISNUMBER($BX3)),MIN(1,MAX(0,($BX3-2018+1)/($BX3-$BW3+1))),"") -> 0.0625 | Z3: =IF(AND(ISNUMBER($BW3),ISNUMBER($BX3)),MIN(1,MAX(0,($BX3-2019+1)/($BX3-$BW3+1))),"") -> 0 | AA3: =IF(ISNUMBER($BX3),IF($BX3>=2017,1,0),"") -> 1 | AB3: =IF(ISNUMBER($BX3),IF($BX3>=2018,1,0),"") -> 1 | AC3: =IF(ISNUMBER($BX3),IF($BX3>=2019,1,0),"") -> 0 | AD3: =IF($L3<>"",IF($L3>2013,1,0),"") -> 0 | AE3: =IF($L3<>"",1+IF($L3>2011,1,0)+IF($L3>2014,1,0),"") -> 1 | AF3: loan (interest rate) | AG3: performance | AH3: non-sensitive | AI3: 99_NCE | AJ3: 99_NCE | AK3: =IF(AND($CF3<>"",IFERROR(INDEX(subsample_country_map!$B:$B,MATCH($CF3,subsample_country_map!$A:$A,0)),"")<>""),INDEX(subsample_country_map!$B:$B,MATCH($CF3,subsample_country_map!$A:$A,0)),INDEX(lookup!$AA:$AA,MATCH($A3,lookup!$A:$A,0))) -> 3_AsiaPac | AL3: =IF(AND($CF3<>"",IFERROR(INDEX(subsample_country_map!$C:$C,MATCH($CF3,subsample_country_map!$A:$A,0)),"")<>""),INDEX(subsample_country_map!$C:$C,MATCH($CF3,subsample_country_map!$A:$A,0)),INDEX(lookup!$AB:$AB,MATCH($A3,lookup!$A:$A,0))) -> 99_NCE | AM3: =IF(AND($CF3<>"",IFERROR(INDEX(subsample_country_map!$D:$D,MATCH($CF3,subsample_country_map!$A:$A,0)),"")<>""),INDEX(subsample_country_map!$D:$D,MATCH($CF3,subsample_country_map!$A:$A,0)),INDEX(lookup!$AC:$AC,MATCH($A3,lookup!$A:$A,0))) -> 99_NCE | AN3: =IF(AND($CF3<>"",IFERROR(INDEX(subsample_country_map!$E:$E,MATCH($CF3,subsample_country_map!$A:$A,0)),"")<>""),INDEX(subsample_country_map!$E:$E,MATCH($CF3,subsample_country_map!$A:$A,0)),INDEX(lookup!$AD:$AD,MATCH($A3,lookup!$A:$A,0))) -> 99_NCE | AO3: =INDEX(lookup!$Y:$Y,MATCH($A3,lookup!$A:$A,0)) -> 0_published | AP3: =INDEX(lookup!$Z:$Z,MATCH($A3,lookup!$A:$A,0)) -> 1_VHB high | AQ3: =INDEX(lookup!$W:$W,MATCH($A3,lookup!$A:$A,0)) -> 1_fin/acc/econ | AS3: staging | AT3: author-inverted-to-good | AU3: cost | AZ3: -0.08 | BA3: FLAG | BB3: 0 | BC3: n/a (structural) | BD3: n/a (structural) | BE3: none | BI3: Table 4 | BJ3: Correlation matrix col (1) | BK3: 8 | BL3: (3) CCP2 -0.08 [bold] | BM3: CCP2 | BN3: COD | BO3: update | BP3: Al-Fakir Al Rabab'a et al (2023) | BQ3: bivariate | BT3: 0 | BU3: staging_Al-Fakir_Al_Rababa_et_al_2023.csv | BW3: 2003 | BX3: 2018 | BY3: multi: 14 Asia-Pacific countries (Australia, China, Hong Kong, India, Indonesia, Japan, Malaysia, New Zealand, Philippines, Singapore, South Korea, Sri Lanka, Taiwan, Thailand) | BZ3: 2010.5 | CA3: 0.1875 | CB3: 0 | CC3: 1 | CD3: -0.080171325 | CE3: 1
A4: Al-Fakir Al Rabab'a et al (2023) | B4: 1309 | C4: -0.12 | D4: 3666 | E4: =IF(ISNUMBER($BA4),$BA4,IF(AND(ISNUMBER($D4),ISNUMBER($BW4),ISNUMBER($BX4)),$D4*($BX4-$BW4+1),"")) -> 58656 | H4: bivariate | I4: Correlation coefficient available | J4: =IF($BW4<>"",$BW4,"") -> 2003 | K4: =IF($BX4<>"",$BX4,"") -> 2018 | L4: =IF(AND(ISNUMBER($BW4),ISNUMBER($BX4)),($BW4+$BX4)/2,"") -> 2010.5 | M4: =IF($L4<>"",$L4,"") -> 2010.5 | N4: =IF(AND(ISNUMBER($BW4),ISNUMBER($BX4)),MIN(1,MAX(0,($BX4-2016+1)/($BX4-$BW4+1))),"") -> 0.1875 | O4: =IF(AND(ISNUMBER($BW4),ISNUMBER($BX4)),MIN(1,MAX(0,($BX4-2017+1)/($BX4-$BW4+1))),"") -> 0.125 | P4: =IF(AND(ISNUMBER($BW4),ISNUMBER($BX4)),MIN(1,MAX(0,($BX4-2018+1)/($BX4-$BW4+1))),"") -> 0.0625 | Q4: =IF(AND(ISNUMBER($BW4),ISNUMBER($BX4)),MIN(1,MAX(0,($BX4-2019+1)/($BX4-$BW4+1))),"") -> 0 | R4: =IF(AND(ISNUMBER($BW4),ISNUMBER($BX4)),MIN(1,MAX(0,($BX4-2016+1)/($BX4-$BW4+1))),"") -> 0.1875 | S4: =IF($L4<>"",IF($L4>=2015.5,1,0),"") -> 0 | T4: =IF($L4<>"",IF($L4>=2016,1,0),"") -> 0 | U4: =IF(ISNUMBER($BX4),IF($BX4>=2016,1,0),"") -> 1 | V4: =IF(ISNUMBER($BW4),IF($BW4>=2016,1,0),"") -> 0 | W4: =IF(AND(ISNUMBER($BW4),ISNUMBER($BX4)),IF($BW4>=2016,"post-only",IF($BX4<2016,"pre-only","mixed")),"") -> mixed | X4: =IF(AND(ISNUMBER($BW4),ISNUMBER($BX4)),MIN(1,MAX(0,($BX4-2017+1)/($BX4-$BW4+1))),"") -> 0.125 | Y4: =IF(AND(ISNUMBER($BW4),ISNUMBER($BX4)),MIN(1,MAX(0,($BX4-2018+1)/($BX4-$BW4+1))),"") -> 0.0625 | Z4: =IF(AND(ISNUMBER($BW4),ISNUMBER($BX4)),MIN(1,MAX(0,($BX4-2019+1)/($BX4-$BW4+1))),"") -> 0 | AA4: =IF(ISNUMBER($BX4),IF($BX4>=2017,1,0),"") -> 1 | AB4: =IF(ISNUMBER($BX4),IF($BX4>=2018,1,0),"") -> 1 | AC4: =IF(ISNUMBER($BX4),IF($BX4>=2019,1,0),"") -> 0 | AD4: =IF($L4<>"",IF($L4>2013,1,0),"") -> 0 | AE4: =IF($L4<>"",1+IF($L4>2011,1,0)+IF($L4>2014,1,0),"") -> 1 | AF4: loan (interest rate) | AG4: performance | AH4: non-sensitive | AI4: 99_NCE | AJ4: 99_NCE | AK4: =IF(AND($CF4<>"",IFERROR(INDEX(subsample_country_map!$B:$B,MATCH($CF4,subsample_country_map!$A:$A,0)),"")<>""),INDEX(subsample_country_map!$B:$B,MATCH($CF4,subsample_country_map!$A:$A,0)),INDEX(lookup!$AA:$AA,MATCH($A4,lookup!$A:$A,0))) -> 3_AsiaPac | AL4: =IF(AND($CF4<>"",IFERROR(INDEX(subsample_country_map!$C:$C,MATCH($CF4,subsample_country_map!$A:$A,0)),"")<>""),INDEX(subsample_country_map!$C:$C,MATCH($CF4,subsample_country_map!$A:$A,0)),INDEX(lookup!$AB:$AB,MATCH($A4,lookup!$A:$A,0))) -> 99_NCE | AM4: =IF(AND($CF4<>"",IFERROR(INDEX(subsample_country_map!$D:$D,MATCH($CF4,subsample_country_map!$A:$A,0)),"")<>""),INDEX(subsample_country_map!$D:$D,MATCH($CF4,subsample_country_map!$A:$A,0)),INDEX(lookup!$AC:$AC,MATCH($A4,lookup!$A:$A,0))) -> 99_NCE | AN4: =IF(AND($CF4<>"",IFERROR(INDEX(subsample_country_map!$E:$E,MATCH($CF4,subsample_country_map!$A:$A,0)),"")<>""),INDEX(subsample_country_map!$E:$E,MATCH($CF4,subsample_country_map!$A:$A,0)),INDEX(lookup!$AD:$AD,MATCH($A4,lookup!$A:$A,0))) -> 99_NCE | AO4: =INDEX(lookup!$Y:$Y,MATCH($A4,lookup!$A:$A,0)) -> 0_published | AP4: =INDEX(lookup!$Z:$Z,MATCH($A4,lookup!$A:$A,0)) -> 1_VHB high | AQ4: =INDEX(lookup!$W:$W,MATCH($A4,lookup!$A:$A,0)) -> 1_fin/acc/econ | AS4: staging | AT4: good-CER | AU4: cost | AZ4: -0.12 | BA4: FLAG | BB4: 0 | BC4: n/a (structural) | BD4: n/a (structural) | BE4: none | BI4: Table 4 | BJ4: Correlation matrix col (1) | BK4: 8 | BL4: (4) CCP3 -0.12 [bold] | BM4: CCP3 | BN4: COD | BO4: update | BP4: Al-Fakir Al Rabab'a et al (2023) | BQ4: bivariate | BT4: 0 | BU4: staging_Al-Fakir_Al_Rababa_et_al_2023.csv | BW4: 2003 | BX4: 2018 | BY4: multi: 14 Asia-Pacific countries (Australia, China, Hong Kong, India, Indonesia, Japan, Malaysia, New Zealand, Philippines, Singapore, South Korea, Sri Lanka, Taiwan, Thailand) | BZ4: 2010.5 | CA4: 0.1875 | CB4: 0 | CC4: 1 | CD4: -0.12058103 | CE4: 1
A5: Al-Fakir Al Rabab'a et al (2023) | B5: 1310 | C5: -0.15 | D5: 3666 | E5: =IF(ISNUMBER($BA5),$BA5,IF(AND(ISNUMBER($D5),ISNUMBER($BW5),ISNUMBER($BX5)),$D5*($BX5-$BW5+1),"")) -> 58656 | H5: bivariate | I5: Correlation coefficient available | J5: =IF($BW5<>"",$BW5,"") -> 2003 | K5: =IF($BX5<>"",$BX5,"") -> 2018 | L5: =IF(AND(ISNUMBER($BW5),ISNUMBER($BX5)),($BW5+$BX5)/2,"") -> 2010.5 | M5: =IF($L5<>"",$L5,"") -> 2010.5 | N5: =IF(AND(ISNUMBER($BW5),ISNUMBER($BX5)),MIN(1,MAX(0,($BX5-2016+1)/($BX5-$BW5+1))),"") -> 0.1875 | O5: =IF(AND(ISNUMBER($BW5),ISNUMBER($BX5)),MIN(1,MAX(0,($BX5-2017+1)/($BX5-$BW5+1))),"") -> 0.125 | P5: =IF(AND(ISNUMBER($BW5),ISNUMBER($BX5)),MIN(1,MAX(0,($BX5-2018+1)/($BX5-$BW5+1))),"") -> 0.0625 | Q5: =IF(AND(ISNUMBER($BW5),ISNUMBER($BX5)),MIN(1,MAX(0,($BX5-2019+1)/($BX5-$BW5+1))),"") -> 0 | R5: =IF(AND(ISNUMBER($BW5),ISNUMBER($BX5)),MIN(1,MAX(0,($BX5-2016+1)/($BX5-$BW5+1))),"") -> 0.1875 | S5: =IF($L5<>"",IF($L5>=2015.5,1,0),"") -> 0 | T5: =IF($L5<>"",IF($L5>=2016,1,0),"") -> 0 | U5: =IF(ISNUMBER($BX5),IF($BX5>=2016,1,0),"") -> 1 | V5: =IF(ISNUMBER($BW5),IF($BW5>=2016,1,0),"") -> 0 | W5: =IF(AND(ISNUMBER($BW5),ISNUMBER($BX5)),IF($BW5>=2016,"post-only",IF($BX5<2016,"pre-only","mixed")),"") -> mixed | X5: =IF(AND(ISNUMBER($BW5),ISNUMBER($BX5)),MIN(1,MAX(0,($BX5-2017+1)/($BX5-$BW5+1))),"") -> 0.125 | Y5: =IF(AND(ISNUMBER($BW5),ISNUMBER($BX5)),MIN(1,MAX(0,($BX5-2018+1)/($BX5-$BW5+1))),"") -> 0.0625 | Z5: =IF(AND(ISNUMBER($BW5),ISNUMBER($BX5)),MIN(1,MAX(0,($BX5-2019+1)/($BX5-$BW5+1))),"") -> 0 | AA5: =IF(ISNUMBER($BX5),IF($BX5>=2017,1,0),"") -> 1 | AB5: =IF(ISNUMBER($BX5),IF($BX5>=2018,1,0),"") -> 1 | AC5: =IF(ISNUMBER($BX5),IF($BX5>=2019,1,0),"") -> 0 | AD5: =IF($L5<>"",IF($L5>2013,1,0),"") -> 0 | AE5: =IF($L5<>"",1+IF($L5>2011,1,0)+IF($L5>2014,1,0),"") -> 1 | AF5: loan (interest rate) | AG5: performance | AH5: non-sensitive | AI5: 99_NCE | AJ5: 99_NCE | AK5: =IF(AND($CF5<>"",IFERROR(INDEX(subsample_country_map!$B:$B,MATCH($CF5,subsample_country_map!$A:$A,0)),"")<>""),INDEX(subsample_country_map!$B:$B,MATCH($CF5,subsample_country_map!$A:$A,0)),INDEX(lookup!$AA:$AA,MATCH($A5,lookup!$A:$A,0))) -> 3_AsiaPac | AL5: =IF(AND($CF5<>"",IFERROR(INDEX(subsample_country_map!$C:$C,MATCH($CF5,subsample_country_map!$A:$A,0)),"")<>""),INDEX(subsample_country_map!$C:$C,MATCH($CF5,subsample_country_map!$A:$A,0)),INDEX(lookup!$AB:$AB,MATCH($A5,lookup!$A:$A,0))) -> 99_NCE | AM5: =IF(AND($CF5<>"",IFERROR(INDEX(subsample_country_map!$D:$D,MATCH($CF5,subsample_country_map!$A:$A,0)),"")<>""),INDEX(subsample_country_map!$D:$D,MATCH($CF5,subsample_country_map!$A:$A,0)),INDEX(lookup!$AC:$AC,MATCH($A5,lookup!$A:$A,0))) -> 99_NCE | AN5: =IF(AND($CF5<>"",IFERROR(INDEX(subsample_country_map!$E:$E,MATCH($CF5,subsample_country_map!$A:$A,0)),"")<>""),INDEX(subsample_country_map!$E:$E,MATCH($CF5,subsample_country_map!$A:$A,0)),INDEX(lookup!$AD:$AD,MATCH($A5,lookup!$A:$A,0))) -> 99_NCE | AO5: =INDEX(lookup!$Y:$Y,MATCH($A5,lookup!$A:$A,0)) -> 0_published | AP5: =INDEX(lookup!$Z:$Z,MATCH($A5,lookup!$A:$A,0)) -> 1_VHB high | AQ5: =INDEX(lookup!$W:$W,MATCH($A5,lookup!$A:$A,0)) -> 1_fin/acc/econ | AS5: staging | AT5: good-CER | AU5: cost | AZ5: -0.15 | BA5: FLAG | BB5: 0 | BC5: n/a (structural) | BD5: n/a (structural) | BE5: none | BI5: Table 4 | BJ5: Correlation matrix col (1) | BK5: 8 | BL5: (5) CCP4 -0.15 [bold] | BM5: CCP4 | BN5: COD | BO5: update | BP5: Al-Fakir Al Rabab'a et al (2023) | BQ5: bivariate | BT5: 0 | BU5: staging_Al-Fakir_Al_Rababa_et_al_2023.csv | BW5: 2003 | BX5: 2018 | BY5: multi: 14 Asia-Pacific countries (Australia, China, Hong Kong, India, Indonesia, Japan, Malaysia, New Zealand, Philippines, Singapore, South Korea, Sri Lanka, Taiwan, Thailand) | BZ5: 2010.5 | CA5: 0.1875 | CB5: 0 | CC5: 1 | CD5: -0.15114044 | CE5: 1
A6: Al-Fakir Al Rabab'a et al (2023) | B6: 1311 | C6: -0.039936732 | D6: 3666 | E6: =IF(ISNUMBER($BA6),$BA6,IF(AND(ISNUMBER($D6),ISNUMBER($BW6),ISNUMBER($BX6)),$D6*($BX6-$BW6+1),"")) -> 3666 | H6: partial | I6: T-Statistic available | J6: =IF($BW6<>"",$BW6,"") -> 2003 | K6: =IF($BX6<>"",$BX6,"") -> 2018 | L6: =IF(AND(ISNUMBER($BW6),ISNUMBER($BX6)),($BW6+$BX6)/2,"") -> 2010.5 | M6: =IF($L6<>"",$L6,"") -> 2010.5 | N6: =IF(AND(ISNUMBER($BW6),ISNUMBER($BX6)),MIN(1,MAX(0,($BX6-2016+1)/($BX6-$BW6+1))),"") -> 0.1875 | O6: =IF(AND(ISNUMBER($BW6),ISNUMBER($BX6)),MIN(1,MAX(0,($BX6-2017+1)/($BX6-$BW6+1))),"") -> 0.125 | P6: =IF(AND(ISNUMBER($BW6),ISNUMBER($BX6)),MIN(1,MAX(0,($BX6-2018+1)/($BX6-$BW6+1))),"") -> 0.0625 | Q6: =IF(AND(ISNUMBER($BW6),ISNUMBER($BX6)),MIN(1,MAX(0,($BX6-2019+1)/($BX6-$BW6+1))),"") -> 0 | R6: =IF(AND(ISNUMBER($BW6),ISNUMBER($BX6)),MIN(1,MAX(0,($BX6-2016+1)/($BX6-$BW6+1))),"") -> 0.1875 | S6: =IF($L6<>"",IF($L6>=2015.5,1,0),"") -> 0 | T6: =IF($L6<>"",IF($L6>=2016,1,0),"") -> 0 | U6: =IF(ISNUMBER($BX6),IF($BX6>=2016,1,0),"") -> 1 | V6: =IF(ISNUMBER($BW6),IF($BW6>=2016,1,0),"") -> 0 | W6: =IF(AND(ISNUMBER($BW6),ISNUMBER($BX6)),IF($BW6>=2016,"post-only",IF($BX6<2016,"pre-only","mixed")),"") -> mixed | X6: =IF(AND(ISNUMBER($BW6),ISNUMBER($BX6)),MIN(1,MAX(0,($BX6-2017+1)/($BX6-$BW6+1))),"") -> 0.125 | Y6: =IF(AND(ISNUMBER($BW6),ISNUMBER($BX6)),MIN(1,MAX(0,($BX6-2018+1)/($BX6-$BW6+1))),"") -> 0.0625 | Z6: =IF(AND(ISNUMBER($BW6),ISNUMBER($BX6)),MIN(1,MAX(0,($BX6-2019+1)/($BX6-$BW6+1))),"") -> 0 | AA6: =IF(ISNUMBER($BX6),IF($BX6>=2017,1,0),"") -> 1 | AB6: =IF(ISNUMBER($BX6),IF($BX6>=2018,1,0),"") -> 1 | AC6: =IF(ISNUMBER($BX6),IF($BX6>=2019,1,0),"") -> 0 | AD6: =IF($L6<>"",IF($L6>2013,1,0),"") -> 0 | AE6: =IF($L6<>"",1+IF($L6>2011,1,0)+IF($L6>2014,1,0),"") -> 1 | AF6: loan (interest rate) | AG6: performance | AH6: non-sensitive | AI6: 99_NCE | AJ6: 99_NCE | AK6: =IF(AND($CF6<>"",IFERROR(INDEX(subsample_country_map!$B:$B,MATCH($CF6,subsample_country_map!$A:$A,0)),"")<>""),INDEX(subsample_country_map!$B:$B,MATCH($CF6,subsample_country_map!$A:$A,0)),INDEX(lookup!$AA:$AA,MATCH($A6,lookup!$A:$A,0))) -> 3_AsiaPac | AL6: =IF(AND($CF6<>"",IFERROR(INDEX(subsample_country_map!$C:$C,MATCH($CF6,subsample_country_map!$A:$A,0)),"")<>""),INDEX(subsample_country_map!$C:$C,MATCH($CF6,subsample_country_map!$A:$A,0)),INDEX(lookup!$AB:$AB,MATCH($A6,lookup!$A:$A,0))) -> 99_NCE | AM6: =IF(AND($CF6<>"",IFERROR(INDEX(subsample_country_map!$D:$D,MATCH($CF6,subsample_country_map!$A:$A,0)),"")<>""),INDEX(subsample_country_map!$D:$D,MATCH($CF6,subsample_country_map!$A:$A,0)),INDEX(lookup!$AC:$AC,MATCH($A6,lookup!$A:$A,0))) -> 99_NCE | AN6: =IF(AND($CF6<>"",IFERROR(INDEX(subsample_country_map!$E:$E,MATCH($CF6,subsample_country_map!$A:$A,0)),"")<>""),INDEX(subsample_country_map!$E:$E,MATCH($CF6,subsample_country_map!$A:$A,0)),INDEX(lookup!$AD:$AD,MATCH($A6,lookup!$A:$A,0))) -> 99_NCE | AO6: =INDEX(lookup!$Y:$Y,MATCH($A6,lookup!$A:$A,0)) -> 0_published | AP6: =INDEX(lookup!$Z:$Z,MATCH($A6,lookup!$A:$A,0)) -> 1_VHB high | AQ6: =INDEX(lookup!$W:$W,MATCH($A6,lookup!$A:$A,0)) -> 1_fin/acc/econ | AS6: staging | AT6: author-inverted-to-good | AU6: cost | AV6: -0.240 | AX6: -2.42 | BA6: 3666 | BB6: 0 | BC6: OLS | BD6: firm | BE6: none | BI6: Table 5 | BJ6: Panel A col 1 | BK6: 8 | BL6: CCP1 -0.240** (-2.42) | BM6: CCP1 | BN6: COD | BO6: update | BP6: Al-Fakir Al Rabab'a et al (2023) | BQ6: computed | BT6: 0 | BU6: staging_Al-Fakir_Al_Rababa_et_al_2023.csv | BW6: 2003 | BX6: 2018 | BY6: multi: 14 Asia-Pacific countries (Australia, China, Hong Kong, India, Indonesia, Japan, Malaysia, New Zealand, Philippines, Singapore, South Korea, Sri Lanka, Taiwan, Thailand) | BZ6: 2010.5 | CA6: 0.1875 | CB6: 0 | CC6: 1 | CD6: -0.039957984 | CE6: 1
A7: Al-Fakir Al Rabab'a et al (2023) | B7: 1312 | C7: -0.039442423 | D7: 3666 | E7: =IF(ISNUMBER($BA7),$BA7,IF(AND(ISNUMBER($D7),ISNUMBER($BW7),ISNUMBER($BX7)),$D7*($BX7-$BW7+1),"")) -> 3666 | H7: partial | I7: T-Statistic available | J7: =IF($BW7<>"",$BW7,"") -> 2003 | K7: =IF($BX7<>"",$BX7,"") -> 2018 | L7: =IF(AND(ISNUMBER($BW7),ISNUMBER($BX7)),($BW7+$BX7)/2,"") -> 2010.5 | M7: =IF($L7<>"",$L7,"") -> 2010.5 | N7: =IF(AND(ISNUMBER($BW7),ISNUMBER($BX7)),MIN(1,MAX(0,($BX7-2016+1)/($BX7-$BW7+1))),"") -> 0.1875 | O7: =IF(AND(ISNUMBER($BW7),ISNUMBER($BX7)),MIN(1,MAX(0,($BX7-2017+1)/($BX7-$BW7+1))),"") -> 0.125 | P7: =IF(AND(ISNUMBER($BW7),ISNUMBER($BX7)),MIN(1,MAX(0,($BX7-2018+1)/($BX7-$BW7+1))),"") -> 0.0625 | Q7: =IF(AND(ISNUMBER($BW7),ISNUMBER($BX7)),MIN(1,MAX(0,($BX7-2019+1)/($BX7-$BW7+1))),"") -> 0 | R7: =IF(AND(ISNUMBER($BW7),ISNUMBER($BX7)),MIN(1,MAX(0,($BX7-2016+1)/($BX7-$BW7+1))),"") -> 0.1875 | S7: =IF($L7<>"",IF($L7>=2015.5,1,0),"") -> 0 | T7: =IF($L7<>"",IF($L7>=2016,1,0),"") -> 0 | U7: =IF(ISNUMBER($BX7),IF($BX7>=2016,1,0),"") -> 1 | V7: =IF(ISNUMBER($BW7),IF($BW7>=2016,1,0),"") -> 0 | W7: =IF(AND(ISNUMBER($BW7),ISNUMBER($BX7)),IF($BW7>=2016,"post-only",IF($BX7<2016,"pre-only","mixed")),"") -> mixed | X7: =IF(AND(ISNUMBER($BW7),ISNUMBER($BX7)),MIN(1,MAX(0,($BX7-2017+1)/($BX7-$BW7+1))),"") -> 0.125 | Y7: =IF(AND(ISNUMBER($BW7),ISNUMBER($BX7)),MIN(1,MAX(0,($BX7-2018+1)/($BX7-$BW7+1))),"") -> 0.0625 | Z7: =IF(AND(ISNUMBER($BW7),ISNUMBER($BX7)),MIN(1,MAX(0,($BX7-2019+1)/($BX7-$BW7+1))),"") -> 0 | AA7: =IF(ISNUMBER($BX7),IF($BX7>=2017,1,0),"") -> 1 | AB7: =IF(ISNUMBER($BX7),IF($BX7>=2018,1,0),"") -> 1 | AC7: =IF(ISNUMBER($BX7),IF($BX7>=2019,1,0),"") -> 0 | AD7: =IF($L7<>"",IF($L7>2013,1,0),"") -> 0 | AE7: =IF($L7<>"",1+IF($L7>2011,1,0)+IF($L7>2014,1,0),"") -> 1 | AF7: loan (interest rate) | AG7: performance | AH7: non-sensitive | AI7: 99_NCE | AJ7: 99_NCE | AK7: =IF(AND($CF7<>"",IFERROR(INDEX(subsample_country_map!$B:$B,MATCH($CF7,subsample_country_map!$A:$A,0)),"")<>""),INDEX(subsample_country_map!$B:$B,MATCH($CF7,subsample_country_map!$A:$A,0)),INDEX(lookup!$AA:$AA,MATCH($A7,lookup!$A:$A,0))) -> 3_AsiaPac | AL7: =IF(AND($CF7<>"",IFERROR(INDEX(subsample_country_map!$C:$C,MATCH($CF7,subsample_country_map!$A:$A,0)),"")<>""),INDEX(subsample_country_map!$C:$C,MATCH($CF7,subsample_country_map!$A:$A,0)),INDEX(lookup!$AB:$AB,MATCH($A7,lookup!$A:$A,0))) -> 99_NCE | AM7: =IF(AND($CF7<>"",IFERROR(INDEX(subsample_country_map!$D:$D,MATCH($CF7,subsample_country_map!$A:$A,0)),"")<>""),INDEX(subsample_country_map!$D:$D,MATCH($CF7,subsample_country_map!$A:$A,0)),INDEX(lookup!$AC:$AC,MATCH($A7,lookup!$A:$A,0))) -> 99_NCE | AN7: =IF(AND($CF7<>"",IFERROR(INDEX(subsample_country_map!$E:$E,MATCH($CF7,subsample_country_map!$A:$A,0)),"")<>""),INDEX(subsample_country_map!$E:$E,MATCH($CF7,subsample_country_map!$A:$A,0)),INDEX(lookup!$AD:$AD,MATCH($A7,lookup!$A:$A,0))) -> 99_NCE | AO7: =INDEX(lookup!$Y:$Y,MATCH($A7,lookup!$A:$A,0)) -> 0_published | AP7: =INDEX(lookup!$Z:$Z,MATCH($A7,lookup!$A:$A,0)) -> 1_VHB high | AQ7: =INDEX(lookup!$W:$W,MATCH($A7,lookup!$A:$A,0)) -> 1_fin/acc/econ | AS7: staging | AT7: author-inverted-to-good | AU7: cost | AV7: -0.238 | AX7: -2.39 | BA7: 3666 | BB7: 0 | BC7: OLS | BD7: firm | BE7: none | BI7: Table 5 | BJ7: Panel A col 2 | BK7: 8 | BL7: CCP2 -0.238** (-2.39) | BM7: CCP2 | BN7: COD | BO7: update | BP7: Al-Fakir Al Rabab'a et al (2023) | BQ7: computed | BT7: 0 | BU7: staging_Al-Fakir_Al_Rababa_et_al_2023.csv | BW7: 2003 | BX7: 2018 | BY7: multi: 14 Asia-Pacific countries (Australia, China, Hong Kong, India, Indonesia, Japan, Malaysia, New Zealand, Philippines, Singapore, South Korea, Sri Lanka, Taiwan, Thailand) | BZ7: 2010.5 | CA7: 0.1875 | CB7: 0 | CC7: 1 | CD7: -0.039462896 | CE7: 1
A8: Al-Fakir Al Rabab'a et al (2023) | B8: 1313 | C8: -0.040431011 | D8: 3666 | E8: =IF(ISNUMBER($BA8),$BA8,IF(AND(ISNUMBER($D8),ISNUMBER($BW8),ISNUMBER($BX8)),$D8*($BX8-$BW8+1),"")) -> 3666 | H8: partial | I8: T-Statistic available | J8: =IF($BW8<>"",$BW8,"") -> 2003 | K8: =IF($BX8<>"",$BX8,"") -> 2018 | L8: =IF(AND(ISNUMBER($BW8),ISNUMBER($BX8)),($BW8+$BX8)/2,"") -> 2010.5 | M8: =IF($L8<>"",$L8,"") -> 2010.5 | N8: =IF(AND(ISNUMBER($BW8),ISNUMBER($BX8)),MIN(1,MAX(0,($BX8-2016+1)/($BX8-$BW8+1))),"") -> 0.1875 | O8: =IF(AND(ISNUMBER($BW8),ISNUMBER($BX8)),MIN(1,MAX(0,($BX8-2017+1)/($BX8-$BW8+1))),"") -> 0.125 | P8: =IF(AND(ISNUMBER($BW8),ISNUMBER($BX8)),MIN(1,MAX(0,($BX8-2018+1)/($BX8-$BW8+1))),"") -> 0.0625 | Q8: =IF(AND(ISNUMBER($BW8),ISNUMBER($BX8)),MIN(1,MAX(0,($BX8-2019+1)/($BX8-$BW8+1))),"") -> 0 | R8: =IF(AND(ISNUMBER($BW8),ISNUMBER($BX8)),MIN(1,MAX(0,($BX8-2016+1)/($BX8-$BW8+1))),"") -> 0.1875 | S8: =IF($L8<>"",IF($L8>=2015.5,1,0),"") -> 0 | T8: =IF($L8<>"",IF($L8>=2016,1,0),"") -> 0 | U8: =IF(ISNUMBER($BX8),IF($BX8>=2016,1,0),"") -> 1 | V8: =IF(ISNUMBER($BW8),IF($BW8>=2016,1,0),"") -> 0 | W8: =IF(AND(ISNUMBER($BW8),ISNUMBER($BX8)),IF($BW8>=2016,"post-only",IF($BX8<2016,"pre-only","mixed")),"") -> mixed | X8: =IF(AND(ISNUMBER($BW8),ISNUMBER($BX8)),MIN(1,MAX(0,($BX8-2017+1)/($BX8-$BW8+1))),"") -> 0.125 | Y8: =IF(AND(ISNUMBER($BW8),ISNUMBER($BX8)),MIN(1,MAX(0,($BX8-2018+1)/($BX8-$BW8+1))),"") -> 0.0625 | Z8: =IF(AND(ISNUMBER($BW8),ISNUMBER($BX8)),MIN(1,MAX(0,($BX8-2019+1)/($BX8-$BW8+1))),"") -> 0 | AA8: =IF(ISNUMBER($BX8),IF($BX8>=2017,1,0),"") -> 1 | AB8: =IF(ISNUMBER($BX8),IF($BX8>=2018,1,0),"") -> 1 | AC8: =IF(ISNUMBER($BX8),IF($BX8>=2019,1,0),"") -> 0 | AD8: =IF($L8<>"",IF($L8>2013,1,0),"") -> 0 | AE8: =IF($L8<>"",1+IF($L8>2011,1,0)+IF($L8>2014,1,0),"") -> 1 | AF8: loan (interest rate) | AG8: performance | AH8: non-sensitive | AI8: 99_NCE | AJ8: 99_NCE | AK8: =IF(AND($CF8<>"",IFERROR(INDEX(subsample_country_map!$B:$B,MATCH($CF8,subsample_country_map!$A:$A,0)),"")<>""),INDEX(subsample_country_map!$B:$B,MATCH($CF8,subsample_country_map!$A:$A,0)),INDEX(lookup!$AA:$AA,MATCH($A8,lookup!$A:$A,0))) -> 3_AsiaPac | AL8: =IF(AND($CF8<>"",IFERROR(INDEX(subsample_country_map!$C:$C,MATCH($CF8,subsample_country_map!$A:$A,0)),"")<>""),INDEX(subsample_country_map!$C:$C,MATCH($CF8,subsample_country_map!$A:$A,0)),INDEX(lookup!$AB:$AB,MATCH($A8,lookup!$A:$A,0))) -> 99_NCE | AM8: =IF(AND($CF8<>"",IFERROR(INDEX(subsample_country_map!$D:$D,MATCH($CF8,subsample_country_map!$A:$A,0)),"")<>""),INDEX(subsample_country_map!$D:$D,MATCH($CF8,subsample_country_map!$A:$A,0)),INDEX(lookup!$AC:$AC,MATCH($A8,lookup!$A:$A,0))) -> 99_NCE | AN8: =IF(AND($CF8<>"",IFERROR(INDEX(subsample_country_map!$E:$E,MATCH($CF8,subsample_country_map!$A:$A,0)),"")<>""),INDEX(subsample_country_map!$E:$E,MATCH($CF8,subsample_country_map!$A:$A,0)),INDEX(lookup!$AD:$AD,MATCH($A8,lookup!$A:$A,0))) -> 99_NCE | AO8: =INDEX(lookup!$Y:$Y,MATCH($A8,lookup!$A:$A,0)) -> 0_published | AP8: =INDEX(lookup!$Z:$Z,MATCH($A8,lookup!$A:$A,0)) -> 1_VHB high | AQ8: =INDEX(lookup!$W:$W,MATCH($A8,lookup!$A:$A,0)) -> 1_fin/acc/econ | AS8: staging | AT8: good-CER | AU8: cost | AV8: -0.022 | AX8: -2.45 | BA8: 3666 | BB8: 0 | BC8: OLS | BD8: firm | BE8: none | BI8: Table 5 | BJ8: Panel A col 3 | BK8: 8 | BL8: CCP3 -0.022** (-2.45) | BM8: CCP3 | BN8: COD | BO8: update | BP8: Al-Fakir Al Rabab'a et al (2023) | BQ8: computed | BT8: 0 | BU8: staging_Al-Fakir_Al_Rababa_et_al_2023.csv | BW8: 2003 | BX8: 2018 | BY8: multi: 14 Asia-Pacific countries (Australia, China, Hong Kong, India, Indonesia, Japan, Malaysia, New Zealand, Philippines, Singapore, South Korea, Sri Lanka, Taiwan, Thailand) | BZ8: 2010.5 | CA8: 0.1875 | CB8: 0 | CC8: 1 | CD8: -0.040453063 | CE8: 1
A9: Al-Fakir Al Rabab'a et al (2023) | B9: 1314 | C9: -0.03037534 | D9: 3666 | E9: =IF(ISNUMBER($BA9),$BA9,IF(AND(ISNUMBER($D9),ISNUMBER($BW9),ISNUMBER($BX9)),$D9*($BX9-$BW9+1),"")) -> 3666 | H9: partial | I9: T-Statistic available | J9: =IF($BW9<>"",$BW9,"") -> 2003 | K9: =IF($BX9<>"",$BX9,"") -> 2018 | L9: =IF(AND(ISNUMBER($BW9),ISNUMBER($BX9)),($BW9+$BX9)/2,"") -> 2010.5 | M9: =IF($L9<>"",$L9,"") -> 2010.5 | N9: =IF(AND(ISNUMBER($BW9),ISNUMBER($BX9)),MIN(1,MAX(0,($BX9-2016+1)/($BX9-$BW9+1))),"") -> 0.1875 | O9: =IF(AND(ISNUMBER($BW9),ISNUMBER($BX9)),MIN(1,MAX(0,($BX9-2017+1)/($BX9-$BW9+1))),"") -> 0.125 | P9: =IF(AND(ISNUMBER($BW9),ISNUMBER($BX9)),MIN(1,MAX(0,($BX9-2018+1)/($BX9-$BW9+1))),"") -> 0.0625 | Q9: =IF(AND(ISNUMBER($BW9),ISNUMBER($BX9)),MIN(1,MAX(0,($BX9-2019+1)/($BX9-$BW9+1))),"") -> 0 | R9: =IF(AND(ISNUMBER($BW9),ISNUMBER($BX9)),MIN(1,MAX(0,($BX9-2016+1)/($BX9-$BW9+1))),"") -> 0.1875 | S9: =IF($L9<>"",IF($L9>=2015.5,1,0),"") -> 0 | T9: =IF($L9<>"",IF($L9>=2016,1,0),"") -> 0 | U9: =IF(ISNUMBER($BX9),IF($BX9>=2016,1,0),"") -> 1 | V9: =IF(ISNUMBER($BW9),IF($BW9>=2016,1,0),"") -> 0 | W9: =IF(AND(ISNUMBER($BW9),ISNUMBER($BX9)),IF($BW9>=2016,"post-only",IF($BX9<2016,"pre-only","mixed")),"") -> mixed | X9: =IF(AND(ISNUMBER($BW9),ISNUMBER($BX9)),MIN(1,MAX(0,($BX9-2017+1)/($BX9-$BW9+1))),"") -> 0.125 | Y9: =IF(AND(ISNUMBER($BW9),ISNUMBER($BX9)),MIN(1,MAX(0,($BX9-2018+1)/($BX9-$BW9+1))),"") -> 0.0625 | Z9: =IF(AND(ISNUMBER($BW9),ISNUMBER($BX9)),MIN(1,MAX(0,($BX9-2019+1)/($BX9-$BW9+1))),"") -> 0 | AA9: =IF(ISNUMBER($BX9),IF($BX9>=2017,1,0),"") -> 1 | AB9: =IF(ISNUMBER($BX9),IF($BX9>=2018,1,0),"") -> 1 | AC9: =IF(ISNUMBER($BX9),IF($BX9>=2019,1,0),"") -> 0 | AD9: =IF($L9<>"",IF($L9>2013,1,0),"") -> 0 | AE9: =IF($L9<>"",1+IF($L9>2011,1,0)+IF($L9>2014,1,0),"") -> 1 | AF9: loan (interest rate) | AG9: performance | AH9: non-sensitive | AI9: 99_NCE | AJ9: 99_NCE | AK9: =IF(AND($CF9<>"",IFERROR(INDEX(subsample_country_map!$B:$B,MATCH($CF9,subsample_country_map!$A:$A,0)),"")<>""),INDEX(subsample_country_map!$B:$B,MATCH($CF9,subsample_country_map!$A:$A,0)),INDEX(lookup!$AA:$AA,MATCH($A9,lookup!$A:$A,0))) -> 3_AsiaPac | AL9: =IF(AND($CF9<>"",IFERROR(INDEX(subsample_country_map!$C:$C,MATCH($CF9,subsample_country_map!$A:$A,0)),"")<>""),INDEX(subsample_country_map!$C:$C,MATCH($CF9,subsample_country_map!$A:$A,0)),INDEX(lookup!$AB:$AB,MATCH($A9,lookup!$A:$A,0))) -> 99_NCE | AM9: =IF(AND($CF9<>"",IFERROR(INDEX(subsample_country_map!$D:$D,MATCH($CF9,subsample_country_map!$A:$A,0)),"")<>""),INDEX(subsample_country_map!$D:$D,MATCH($CF9,subsample_country_map!$A:$A,0)),INDEX(lookup!$AC:$AC,MATCH($A9,lookup!$A:$A,0))) -> 99_NCE | AN9: =IF(AND($CF9<>"",IFERROR(INDEX(subsample_country_map!$E:$E,MATCH($CF9,subsample_country_map!$A:$A,0)),"")<>""),INDEX(subsample_country_map!$E:$E,MATCH($CF9,subsample_country_map!$A:$A,0)),INDEX(lookup!$AD:$AD,MATCH($A9,lookup!$A:$A,0))) -> 99_NCE | AO9: =INDEX(lookup!$Y:$Y,MATCH($A9,lookup!$A:$A,0)) -> 0_published | AP9: =INDEX(lookup!$Z:$Z,MATCH($A9,lookup!$A:$A,0)) -> 1_VHB high | AQ9: =INDEX(lookup!$W:$W,MATCH($A9,lookup!$A:$A,0)) -> 1_fin/acc/econ | AS9: staging | AT9: good-CER | AU9: cost | AV9: -0.024 | AX9: -1.84 | BA9: 3666 | BB9: 0 | BC9: OLS | BD9: firm | BE9: none | BI9: Table 5 | BJ9: Panel A col 4 | BK9: 8 | BL9: CCP4 -0.024* (-1.84) | BM9: CCP4 | BN9: COD | BO9: update | BP9: Al-Fakir Al Rabab'a et al (2023) | BQ9: computed | BT9: 0 | BU9: staging_Al-Fakir_Al_Rababa_et_al_2023.csv | BW9: 2003 | BX9: 2018 | BY9: multi: 14 Asia-Pacific countries (Australia, China, Hong Kong, India, Indonesia, Japan, Malaysia, New Zealand, Philippines, Singapore, South Korea, Sri Lanka, Taiwan, Thailand) | BZ9: 2010.5 | CA9: 0.1875 | CB9: 0 | CC9: 1 | CD9: -0.030384687 | CE9: 1
A10: Al-Fakir Al Rabab'a et al (2023) | B10: 1315 | C10: -0.050638939 | D10: 3666 | E10: =IF(ISNUMBER($BA10),$BA10,IF(AND(ISNUMBER($D10),ISNUMBER($BW10),ISNUMBER($BX10)),$D10*($BX10-$BW10+1),"")) -> 3666 | H10: partial | I10: T-Statistic available | J10: =IF($BW10<>"",$BW10,"") -> 2003 | K10: =IF($BX10<>"",$BX10,"") -> 2018 | L10: =IF(AND(ISNUMBER($BW10),ISNUMBER($BX10)),($BW10+$BX10)/2,"") -> 2010.5 | M10: =IF($L10<>"",$L10,"") -> 2010.5 | N10: =IF(AND(ISNUMBER($BW10),ISNUMBER($BX10)),MIN(1,MAX(0,($BX10-2016+1)/($BX10-$BW10+1))),"") -> 0.1875 | O10: =IF(AND(ISNUMBER($BW10),ISNUMBER($BX10)),MIN(1,MAX(0,($BX10-2017+1)/($BX10-$BW10+1))),"") -> 0.125 | P10: =IF(AND(ISNUMBER($BW10),ISNUMBER($BX10)),MIN(1,MAX(0,($BX10-2018+1)/($BX10-$BW10+1))),"") -> 0.0625 | Q10: =IF(AND(ISNUMBER($BW10),ISNUMBER($BX10)),MIN(1,MAX(0,($BX10-2019+1)/($BX10-$BW10+1))),"") -> 0 | R10: =IF(AND(ISNUMBER($BW10),ISNUMBER($BX10)),MIN(1,MAX(0,($BX10-2016+1)/($BX10-$BW10+1))),"") -> 0.1875 | S10: =IF($L10<>"",IF($L10>=2015.5,1,0),"") -> 0 | T10: =IF($L10<>"",IF($L10>=2016,1,0),"") -> 0 | U10: =IF(ISNUMBER($BX10),IF($BX10>=2016,1,0),"") -> 1 | V10: =IF(ISNUMBER($BW10),IF($BW10>=2016,1,0),"") -> 0 | W10: =IF(AND(ISNUMBER($BW10),ISNUMBER($BX10)),IF($BW10>=2016,"post-only",IF($BX10<2016,"pre-only","mixed")),"") -> mixed | X10: =IF(AND(ISNUMBER($BW10),ISNUMBER($BX10)),MIN(1,MAX(0,($BX10-2017+1)/($BX10-$BW10+1))),"") -> 0.125 | Y10: =IF(AND(ISNUMBER($BW10),ISNUMBER($BX10)),MIN(1,MAX(0,($BX10-2018+1)/($BX10-$BW10+1))),"") -> 0.0625 | Z10: =IF(AND(ISNUMBER($BW10),ISNUMBER($BX10)),MIN(1,MAX(0,($BX10-2019+1)/($BX10-$BW10+1))),"") -> 0 | AA10: =IF(ISNUMBER($BX10),IF($BX10>=2017,1,0),"") -> 1 | AB10: =IF(ISNUMBER($BX10),IF($BX10>=2018,1,0),"") -> 1 | AC10: =IF(ISNUMBER($BX10),IF($BX10>=2019,1,0),"") -> 0 | AD10: =IF($L10<>"",IF($L10>2013,1,0),"") -> 0 | AE10: =IF($L10<>"",1+IF($L10>2011,1,0)+IF($L10>2014,1,0),"") -> 1 | AF10: loan (interest rate) | AG10: performance | AH10: non-sensitive | AI10: 99_NCE | AJ10: 99_NCE | AK10: =IF(AND($CF10<>"",IFERROR(INDEX(subsample_country_map!$B:$B,MATCH($CF10,subsample_country_map!$A:$A,0)),"")<>""),INDEX(subsample_country_map!$B:$B,MATCH($CF10,subsample_country_map!$A:$A,0)),INDEX(lookup!$AA:$AA,MATCH($A10,lookup!$A:$A,0))) -> 3_AsiaPac | AL10: =IF(AND($CF10<>"",IFERROR(INDEX(subsample_country_map!$C:$C,MATCH($CF10,subsample_country_map!$A:$A,0)),"")<>""),INDEX(subsample_country_map!$C:$C,MATCH($CF10,subsample_country_map!$A:$A,0)),INDEX(lookup!$AB:$AB,MATCH($A10,lookup!$A:$A,0))) -> 99_NCE | AM10: =IF(AND($CF10<>"",IFERROR(INDEX(subsample_country_map!$D:$D,MATCH($CF10,subsample_country_map!$A:$A,0)),"")<>""),INDEX(subsample_country_map!$D:$D,MATCH($CF10,subsample_country_map!$A:$A,0)),INDEX(lookup!$AC:$AC,MATCH($A10,lookup!$A:$A,0))) -> 99_NCE | AN10: =IF(AND($CF10<>"",IFERROR(INDEX(subsample_country_map!$E:$E,MATCH($CF10,subsample_country_map!$A:$A,0)),"")<>""),INDEX(subsample_country_map!$E:$E,MATCH($CF10,subsample_country_map!$A:$A,0)),INDEX(lookup!$AD:$AD,MATCH($A10,lookup!$A:$A,0))) -> 99_NCE | AO10: =INDEX(lookup!$Y:$Y,MATCH($A10,lookup!$A:$A,0)) -> 0_published | AP10: =INDEX(lookup!$Z:$Z,MATCH($A10,lookup!$A:$A,0)) -> 1_VHB high | AQ10: =INDEX(lookup!$W:$W,MATCH($A10,lookup!$A:$A,0)) -> 1_fin/acc/econ | AS10: staging | AT10: author-inverted-to-good | AU10: cost | AV10: -0.456 | AX10: -3.07 | BA10: 3666 | BB10: 0 | BC10: OLS | BD10: not stated | BE10: none | BI10: Table 6 | BJ10: Panel A col 1 | BK10: 9 | BL10: CCP1 -0.456*** (-3.07) | BM10: CCP1 | BN10: COD | BO10: update | BP10: Al-Fakir Al Rabab'a et al (2023) | BQ10: computed | BT10: 0 | BU10: staging_Al-Fakir_Al_Rababa_et_al_2023.csv | BW10: 2003 | BX10: 2018 | BY10: multi: 14 Asia-Pacific countries (Australia, China, Hong Kong, India, Indonesia, Japan, Malaysia, New Zealand, Philippines, Singapore, South Korea, Sri Lanka, Taiwan, Thailand) | BZ10: 2010.5 | CA10: 0.1875 | CB10: 0 | CC10: 1 | CD10: -0.05068229 | CE10: 1
A11: Al-Fakir Al Rabab'a et al (2023) | B11: 1316 | C11: -0.051461511 | D11: 3666 | E11: =IF(ISNUMBER($BA11),$BA11,IF(AND(ISNUMBER($D11),ISNUMBER($BW11),ISNUMBER($BX11)),$D11*($BX11-$BW11+1),"")) -> 3666 | H11: partial | I11: T-Statistic available | J11: =IF($BW11<>"",$BW11,"") -> 2003 | K11: =IF($BX11<>"",$BX11,"") -> 2018 | L11: =IF(AND(ISNUMBER($BW11),ISNUMBER($BX11)),($BW11+$BX11)/2,"") -> 2010.5 | M11: =IF($L11<>"",$L11,"") -> 2010.5 | N11: =IF(AND(ISNUMBER($BW11),ISNUMBER($BX11)),MIN(1,MAX(0,($BX11-2016+1)/($BX11-$BW11+1))),"") -> 0.1875 | O11: =IF(AND(ISNUMBER($BW11),ISNUMBER($BX11)),MIN(1,MAX(0,($BX11-2017+1)/($BX11-$BW11+1))),"") -> 0.125 | P11: =IF(AND(ISNUMBER($BW11),ISNUMBER($BX11)),MIN(1,MAX(0,($BX11-2018+1)/($BX11-$BW11+1))),"") -> 0.0625 | Q11: =IF(AND(ISNUMBER($BW11),ISNUMBER($BX11)),MIN(1,MAX(0,($BX11-2019+1)/($BX11-$BW11+1))),"") -> 0 | R11: =IF(AND(ISNUMBER($BW11),ISNUMBER($BX11)),MIN(1,MAX(0,($BX11-2016+1)/($BX11-$BW11+1))),"") -> 0.1875 | S11: =IF($L11<>"",IF($L11>=2015.5,1,0),"") -> 0 | T11: =IF($L11<>"",IF($L11>=2016,1,0),"") -> 0 | U11: =IF(ISNUMBER($BX11),IF($BX11>=2016,1,0),"") -> 1 | V11: =IF(ISNUMBER($BW11),IF($BW11>=2016,1,0),"") -> 0 | W11: =IF(AND(ISNUMBER($BW11),ISNUMBER($BX11)),IF($BW11>=2016,"post-only",IF($BX11<2016,"pre-only","mixed")),"") -> mixed | X11: =IF(AND(ISNUMBER($BW11),ISNUMBER($BX11)),MIN(1,MAX(0,($BX11-2017+1)/($BX11-$BW11+1))),"") -> 0.125 | Y11: =IF(AND(ISNUMBER($BW11),ISNUMBER($BX11)),MIN(1,MAX(0,($BX11-2018+1)/($BX11-$BW11+1))),"") -> 0.0625 | Z11: =IF(AND(ISNUMBER($BW11),ISNUMBER($BX11)),MIN(1,MAX(0,($BX11-2019+1)/($BX11-$BW11+1))),"") -> 0 | AA11: =IF(ISNUMBER($BX11),IF($BX11>=2017,1,0),"") -> 1 | AB11: =IF(ISNUMBER($BX11),IF($BX11>=2018,1,0),"") -> 1 | AC11: =IF(ISNUMBER($BX11),IF($BX11>=2019,1,0),"") -> 0 | AD11: =IF($L11<>"",IF($L11>2013,1,0),"") -> 0 | AE11: =IF($L11<>"",1+IF($L11>2011,1,0)+IF($L11>2014,1,0),"") -> 1 | AF11: loan (interest rate) | AG11: performance | AH11: non-sensitive | AI11: 99_NCE | AJ11: 99_NCE | AK11: =IF(AND($CF11<>"",IFERROR(INDEX(subsample_country_map!$B:$B,MATCH($CF11,subsample_country_map!$A:$A,0)),"")<>""),INDEX(subsample_country_map!$B:$B,MATCH($CF11,subsample_country_map!$A:$A,0)),INDEX(lookup!$AA:$AA,MATCH($A11,lookup!$A:$A,0))) -> 3_AsiaPac | AL11: =IF(AND($CF11<>"",IFERROR(INDEX(subsample_country_map!$C:$C,MATCH($CF11,subsample_country_map!$A:$A,0)),"")<>""),INDEX(subsample_country_map!$C:$C,MATCH($CF11,subsample_country_map!$A:$A,0)),INDEX(lookup!$AB:$AB,MATCH($A11,lookup!$A:$A,0))) -> 99_NCE | AM11: =IF(AND($CF11<>"",IFERROR(INDEX(subsample_country_map!$D:$D,MATCH($CF11,subsample_country_map!$A:$A,0)),"")<>""),INDEX(subsample_country_map!$D:$D,MATCH($CF11,subsample_country_map!$A:$A,0)),INDEX(lookup!$AC:$AC,MATCH($A11,lookup!$A:$A,0))) -> 99_NCE | AN11: =IF(AND($CF11<>"",IFERROR(INDEX(subsample_country_map!$E:$E,MATCH($CF11,subsample_country_map!$A:$A,0)),"")<>""),INDEX(subsample_country_map!$E:$E,MATCH($CF11,subsample_country_map!$A:$A,0)),INDEX(lookup!$AD:$AD,MATCH($A11,lookup!$A:$A,0))) -> 99_NCE | AO11: =INDEX(lookup!$Y:$Y,MATCH($A11,lookup!$A:$A,0)) -> 0_published | AP11: =INDEX(lookup!$Z:$Z,MATCH($A11,lookup!$A:$A,0)) -> 1_VHB high | AQ11: =INDEX(lookup!$W:$W,MATCH($A11,lookup!$A:$A,0)) -> 1_fin/acc/econ | AS11: staging | AT11: author-inverted-to-good | AU11: cost | AV11: -0.688 | AX11: -3.12 | BA11: 3666 | BB11: 0 | BC11: OLS | BD11: not stated | BE11: none | BI11: Table 6 | BJ11: Panel A col 2 | BK11: 9 | BL11: CCP2 -0.688*** (-3.12) | BM11: CCP2 | BN11: COD | BO11: update | BP11: Al-Fakir Al Rabab'a et al (2023) | BQ11: computed | BT11: 0 | BU11: staging_Al-Fakir_Al_Rababa_et_al_2023.csv | BW11: 2003 | BX11: 2018 | BY11: multi: 14 Asia-Pacific countries (Australia, China, Hong Kong, India, Indonesia, Japan, Malaysia, New Zealand, Philippines, Singapore, South Korea, Sri Lanka, Taiwan, Thailand) | BZ11: 2010.5 | CA11: 0.1875 | CB11: 0 | CC11: 1 | CD11: -0.051507011 | CE11: 1
A12: Al-Fakir Al Rabab'a et al (2023) | B12: 1317 | C12: -0.049322611 | D12: 3666 | E12: =IF(ISNUMBER($BA12),$BA12,IF(AND(ISNUMBER($D12),ISNUMBER($BW12),ISNUMBER($BX12)),$D12*($BX12-$BW12+1),"")) -> 3666 | H12: partial | I12: T-Statistic available | J12: =IF($BW12<>"",$BW12,"") -> 2003 | K12: =IF($BX12<>"",$BX12,"") -> 2018 | L12: =IF(AND(ISNUMBER($BW12),ISNUMBER($BX12)),($BW12+$BX12)/2,"") -> 2010.5 | M12: =IF($L12<>"",$L12,"") -> 2010.5 | N12: =IF(AND(ISNUMBER($BW12),ISNUMBER($BX12)),MIN(1,MAX(0,($BX12-2016+1)/($BX12-$BW12+1))),"") -> 0.1875 | O12: =IF(AND(ISNUMBER($BW12),ISNUMBER($BX12)),MIN(1,MAX(0,($BX12-2017+1)/($BX12-$BW12+1))),"") -> 0.125 | P12: =IF(AND(ISNUMBER($BW12),ISNUMBER($BX12)),MIN(1,MAX(0,($BX12-2018+1)/($BX12-$BW12+1))),"") -> 0.0625 | Q12: =IF(AND(ISNUMBER($BW12),ISNUMBER($BX12)),MIN(1,MAX(0,($BX12-2019+1)/($BX12-$BW12+1))),"") -> 0 | R12: =IF(AND(ISNUMBER($BW12),ISNUMBER($BX12)),MIN(1,MAX(0,($BX12-2016+1)/($BX12-$BW12+1))),"") -> 0.1875 | S12: =IF($L12<>"",IF($L12>=2015.5,1,0),"") -> 0 | T12: =IF($L12<>"",IF($L12>=2016,1,0),"") -> 0 | U12: =IF(ISNUMBER($BX12),IF($BX12>=2016,1,0),"") -> 1 | V12: =IF(ISNUMBER($BW12),IF($BW12>=2016,1,0),"") -> 0 | W12: =IF(AND(ISNUMBER($BW12),ISNUMBER($BX12)),IF($BW12>=2016,"post-only",IF($BX12<2016,"pre-only","mixed")),"") -> mixed | X12: =IF(AND(ISNUMBER($BW12),ISNUMBER($BX12)),MIN(1,MAX(0,($BX12-2017+1)/($BX12-$BW12+1))),"") -> 0.125 | Y12: =IF(AND(ISNUMBER($BW12),ISNUMBER($BX12)),MIN(1,MAX(0,($BX12-2018+1)/($BX12-$BW12+1))),"") -> 0.0625 | Z12: =IF(AND(ISNUMBER($BW12),ISNUMBER($BX12)),MIN(1,MAX(0,($BX12-2019+1)/($BX12-$BW12+1))),"") -> 0 | AA12: =IF(ISNUMBER($BX12),IF($BX12>=2017,1,0),"") -> 1 | AB12: =IF(ISNUMBER($BX12),IF($BX12>=2018,1,0),"") -> 1 | AC12: =IF(ISNUMBER($BX12),IF($BX12>=2019,1,0),"") -> 0 | AD12: =IF($L12<>"",IF($L12>2013,1,0),"") -> 0 | AE12: =IF($L12<>"",1+IF($L12>2011,1,0)+IF($L12>2014,1,0),"") -> 1 | AF12: loan (interest rate) | AG12: performance | AH12: non-sensitive | AI12: 99_NCE | AJ12: 99_NCE | AK12: =IF(AND($CF12<>"",IFERROR(INDEX(subsample_country_map!$B:$B,MATCH($CF12,subsample_country_map!$A:$A,0)),"")<>""),INDEX(subsample_country_map!$B:$B,MATCH($CF12,subsample_country_map!$A:$A,0)),INDEX(lookup!$AA:$AA,MATCH($A12,lookup!$A:$A,0))) -> 3_AsiaPac | AL12: =IF(AND($CF12<>"",IFERROR(INDEX(subsample_country_map!$C:$C,MATCH($CF12,subsample_country_map!$A:$A,0)),"")<>""),INDEX(subsample_country_map!$C:$C,MATCH($CF12,subsample_country_map!$A:$A,0)),INDEX(lookup!$AB:$AB,MATCH($A12,lookup!$A:$A,0))) -> 99_NCE | AM12: =IF(AND($CF12<>"",IFERROR(INDEX(subsample_country_map!$D:$D,MATCH($CF12,subsample_country_map!$A:$A,0)),"")<>""),INDEX(subsample_country_map!$D:$D,MATCH($CF12,subsample_country_map!$A:$A,0)),INDEX(lookup!$AC:$AC,MATCH($A12,lookup!$A:$A,0))) -> 99_NCE | AN12: =IF(AND($CF12<>"",IFERROR(INDEX(subsample_country_map!$E:$E,MATCH($CF12,subsample_country_map!$A:$A,0)),"")<>""),INDEX(subsample_country_map!$E:$E,MATCH($CF12,subsample_country_map!$A:$A,0)),INDEX(lookup!$AD:$AD,MATCH($A12,lookup!$A:$A,0))) -> 99_NCE | AO12: =INDEX(lookup!$Y:$Y,MATCH($A12,lookup!$A:$A,0)) -> 0_published | AP12: =INDEX(lookup!$Z:$Z,MATCH($A12,lookup!$A:$A,0)) -> 1_VHB high | AQ12: =INDEX(lookup!$W:$W,MATCH($A12,lookup!$A:$A,0)) -> 1_fin/acc/econ | AS12: staging | AT12: good-CER | AU12: cost | AV12: -0.195 | AX12: -2.99 | BA12: 3666 | BB12: 0 | BC12: OLS | BD12: not stated | BE12: none | BI12: Table 6 | BJ12: Panel A col 3 | BK12: 9 | BL12: CCP3 -0.195*** (-2.99) | BM12: CCP3 | BN12: COD | BO12: update | BP12: Al-Fakir Al Rabab'a et al (2023) | BQ12: computed | BT12: 0 | BU12: staging_Al-Fakir_Al_Rababa_et_al_2023.csv | BW12: 2003 | BX12: 2018 | BY12: multi: 14 Asia-Pacific countries (Australia, China, Hong Kong, India, Indonesia, Japan, Malaysia, New Zealand, Philippines, Singapore, South Korea, Sri Lanka, Taiwan, Thailand) | BZ12: 2010.5 | CA12: 0.1875 | CB12: 0 | CC12: 1 | CD12: -0.049362665 | CE12: 1
A13: Al-Fakir Al Rabab'a et al (2023) | B13: 1318 | C13: -0.041913669 | D13: 3666 | E13: =IF(ISNUMBER($BA13),$BA13,IF(AND(ISNUMBER($D13),ISNUMBER($BW13),ISNUMBER($BX13)),$D13*($BX13-$BW13+1),"")) -> 3666 | H13: partial | I13: T-Statistic available | J13: =IF($BW13<>"",$BW13,"") -> 2003 | K13: =IF($BX13<>"",$BX13,"") -> 2018 | L13: =IF(AND(ISNUMBER($BW13),ISNUMBER($BX13)),($BW13+$BX13)/2,"") -> 2010.5 | M13: =IF($L13<>"",$L13,"") -> 2010.5 | N13: =IF(AND(ISNUMBER($BW13),ISNUMBER($BX13)),MIN(1,MAX(0,($BX13-2016+1)/($BX13-$BW13+1))),"") -> 0.1875 | O13: =IF(AND(ISNUMBER($BW13),ISNUMBER($BX13)),MIN(1,MAX(0,($BX13-2017+1)/($BX13-$BW13+1))),"") -> 0.125 | P13: =IF(AND(ISNUMBER($BW13),ISNUMBER($BX13)),MIN(1,MAX(0,($BX13-2018+1)/($BX13-$BW13+1))),"") -> 0.0625 | Q13: =IF(AND(ISNUMBER($BW13),ISNUMBER($BX13)),MIN(1,MAX(0,($BX13-2019+1)/($BX13-$BW13+1))),"") -> 0 | R13: =IF(AND(ISNUMBER($BW13),ISNUMBER($BX13)),MIN(1,MAX(0,($BX13-2016+1)/($BX13-$BW13+1))),"") -> 0.1875 | S13: =IF($L13<>"",IF($L13>=2015.5,1,0),"") -> 0 | T13: =IF($L13<>"",IF($L13>=2016,1,0),"") -> 0 | U13: =IF(ISNUMBER($BX13),IF($BX13>=2016,1,0),"") -> 1 | V13: =IF(ISNUMBER($BW13),IF($BW13>=2016,1,0),"") -> 0 | W13: =IF(AND(ISNUMBER($BW13),ISNUMBER($BX13)),IF($BW13>=2016,"post-only",IF($BX13<2016,"pre-only","mixed")),"") -> mixed | X13: =IF(AND(ISNUMBER($BW13),ISNUMBER($BX13)),MIN(1,MAX(0,($BX13-2017+1)/($BX13-$BW13+1))),"") -> 0.125 | Y13: =IF(AND(ISNUMBER($BW13),ISNUMBER($BX13)),MIN(1,MAX(0,($BX13-2018+1)/($BX13-$BW13+1))),"") -> 0.0625 | Z13: =IF(AND(ISNUMBER($BW13),ISNUMBER($BX13)),MIN(1,MAX(0,($BX13-2019+1)/($BX13-$BW13+1))),"") -> 0 | AA13: =IF(ISNUMBER($BX13),IF($BX13>=2017,1,0),"") -> 1 | AB13: =IF(ISNUMBER($BX13),IF($BX13>=2018,1,0),"") -> 1 | AC13: =IF(ISNUMBER($BX13),IF($BX13>=2019,1,0),"") -> 0 | AD13: =IF($L13<>"",IF($L13>2013,1,0),"") -> 0 | AE13: =IF($L13<>"",1+IF($L13>2011,1,0)+IF($L13>2014,1,0),"") -> 1 | AF13: loan (interest rate) | AG13: performance | AH13: non-sensitive | AI13: 99_NCE | AJ13: 99_NCE | AK13: =IF(AND($CF13<>"",IFERROR(INDEX(subsample_country_map!$B:$B,MATCH($CF13,subsample_country_map!$A:$A,0)),"")<>""),INDEX(subsample_country_map!$B:$B,MATCH($CF13,subsample_country_map!$A:$A,0)),INDEX(lookup!$AA:$AA,MATCH($A13,lookup!$A:$A,0))) -> 3_AsiaPac | AL13: =IF(AND($CF13<>"",IFERROR(INDEX(subsample_country_map!$C:$C,MATCH($CF13,subsample_country_map!$A:$A,0)),"")<>""),INDEX(subsample_country_map!$C:$C,MATCH($CF13,subsample_country_map!$A:$A,0)),INDEX(lookup!$AB:$AB,MATCH($A13,lookup!$A:$A,0))) -> 99_NCE | AM13: =IF(AND($CF13<>"",IFERROR(INDEX(subsample_country_map!$D:$D,MATCH($CF13,subsample_country_map!$A:$A,0)),"")<>""),INDEX(subsample_country_map!$D:$D,MATCH($CF13,subsample_country_map!$A:$A,0)),INDEX(lookup!$AC:$AC,MATCH($A13,lookup!$A:$A,0))) -> 99_NCE | AN13: =IF(AND($CF13<>"",IFERROR(INDEX(subsample_country_map!$E:$E,MATCH($CF13,subsample_country_map!$A:$A,0)),"")<>""),INDEX(subsample_country_map!$E:$E,MATCH($CF13,subsample_country_map!$A:$A,0)),INDEX(lookup!$AD:$AD,MATCH($A13,lookup!$A:$A,0))) -> 99_NCE | AO13: =INDEX(lookup!$Y:$Y,MATCH($A13,lookup!$A:$A,0)) -> 0_published | AP13: =INDEX(lookup!$Z:$Z,MATCH($A13,lookup!$A:$A,0)) -> 1_VHB high | AQ13: =INDEX(lookup!$W:$W,MATCH($A13,lookup!$A:$A,0)) -> 1_fin/acc/econ | AS13: staging | AT13: good-CER | AU13: cost | AV13: -0.274 | AX13: -2.54 | BA13: 3666 | BB13: 0 | BC13: OLS | BD13: not stated | BE13: none | BI13: Table 6 | BJ13: Panel A col 4 | BK13: 9 | BL13: CCP4 -0.274** (-2.54) | BM13: CCP4 | BN13: COD | BO13: update | BP13: Al-Fakir Al Rabab'a et al (2023) | BQ13: computed | BT13: 0 | BU13: staging_Al-Fakir_Al_Rababa_et_al_2023.csv | BW13: 2003 | BX13: 2018 | BY13: multi: 14 Asia-Pacific countries (Australia, China, Hong Kong, India, Indonesia, Japan, Malaysia, New Zealand, Philippines, Singapore, South Korea, Sri Lanka, Taiwan, Thailand) | BZ13: 2010.5 | CA13: 0.1875 | CB13: 0 | CC13: 1 | CD13: -0.041938239 | CE13: 1
A14: Al-Fakir Al Rabab'a et al (2023) | B14: 1319 | C14: -0.039607196 | D14: 3666 | E14: =IF(ISNUMBER($BA14),$BA14,IF(AND(ISNUMBER($D14),ISNUMBER($BW14),ISNUMBER($BX14)),$D14*($BX14-$BW14+1),"")) -> 3666 | H14: partial | I14: T-Statistic available | J14: =IF($BW14<>"",$BW14,"") -> 2003 | K14: =IF($BX14<>"",$BX14,"") -> 2018 | L14: =IF(AND(ISNUMBER($BW14),ISNUMBER($BX14)),($BW14+$BX14)/2,"") -> 2010.5 | M14: =IF($L14<>"",$L14,"") -> 2010.5 | N14: =IF(AND(ISNUMBER($BW14),ISNUMBER($BX14)),MIN(1,MAX(0,($BX14-2016+1)/($BX14-$BW14+1))),"") -> 0.1875 | O14: =IF(AND(ISNUMBER($BW14),ISNUMBER($BX14)),MIN(1,MAX(0,($BX14-2017+1)/($BX14-$BW14+1))),"") -> 0.125 | P14: =IF(AND(ISNUMBER($BW14),ISNUMBER($BX14)),MIN(1,MAX(0,($BX14-2018+1)/($BX14-$BW14+1))),"") -> 0.0625 | Q14: =IF(AND(ISNUMBER($BW14),ISNUMBER($BX14)),MIN(1,MAX(0,($BX14-2019+1)/($BX14-$BW14+1))),"") -> 0 | R14: =IF(AND(ISNUMBER($BW14),ISNUMBER($BX14)),MIN(1,MAX(0,($BX14-2016+1)/($BX14-$BW14+1))),"") -> 0.1875 | S14: =IF($L14<>"",IF($L14>=2015.5,1,0),"") -> 0 | T14: =IF($L14<>"",IF($L14>=2016,1,0),"") -> 0 | U14: =IF(ISNUMBER($BX14),IF($BX14>=2016,1,0),"") -> 1 | V14: =IF(ISNUMBER($BW14),IF($BW14>=2016,1,0),"") -> 0 | W14: =IF(AND(ISNUMBER($BW14),ISNUMBER($BX14)),IF($BW14>=2016,"post-only",IF($BX14<2016,"pre-only","mixed")),"") -> mixed | X14: =IF(AND(ISNUMBER($BW14),ISNUMBER($BX14)),MIN(1,MAX(0,($BX14-2017+1)/($BX14-$BW14+1))),"") -> 0.125 | Y14: =IF(AND(ISNUMBER($BW14),ISNUMBER($BX14)),MIN(1,MAX(0,($BX14-2018+1)/($BX14-$BW14+1))),"") -> 0.0625 | Z14: =IF(AND(ISNUMBER($BW14),ISNUMBER($BX14)),MIN(1,MAX(0,($BX14-2019+1)/($BX14-$BW14+1))),"") -> 0 | AA14: =IF(ISNUMBER($BX14),IF($BX14>=2017,1,0),"") -> 1 | AB14: =IF(ISNUMBER($BX14),IF($BX14>=2018,1,0),"") -> 1 | AC14: =IF(ISNUMBER($BX14),IF($BX14>=2019,1,0),"") -> 0 | AD14: =IF($L14<>"",IF($L14>2013,1,0),"") -> 0 | AE14: =IF($L14<>"",1+IF($L14>2011,1,0)+IF($L14>2014,1,0),"") -> 1 | AF14: loan (interest rate) | AG14: performance | AH14: non-sensitive | AI14: 99_NCE | AJ14: 99_NCE | AK14: =IF(AND($CF14<>"",IFERROR(INDEX(subsample_country_map!$B:$B,MATCH($CF14,subsample_country_map!$A:$A,0)),"")<>""),INDEX(subsample_country_map!$B:$B,MATCH($CF14,subsample_country_map!$A:$A,0)),INDEX(lookup!$AA:$AA,MATCH($A14,lookup!$A:$A,0))) -> 3_AsiaPac | AL14: =IF(AND($CF14<>"",IFERROR(INDEX(subsample_country_map!$C:$C,MATCH($CF14,subsample_country_map!$A:$A,0)),"")<>""),INDEX(subsample_country_map!$C:$C,MATCH($CF14,subsample_country_map!$A:$A,0)),INDEX(lookup!$AB:$AB,MATCH($A14,lookup!$A:$A,0))) -> 99_NCE | AM14: =IF(AND($CF14<>"",IFERROR(INDEX(subsample_country_map!$D:$D,MATCH($CF14,subsample_country_map!$A:$A,0)),"")<>""),INDEX(subsample_country_map!$D:$D,MATCH($CF14,subsample_country_map!$A:$A,0)),INDEX(lookup!$AC:$AC,MATCH($A14,lookup!$A:$A,0))) -> 99_NCE | AN14: =IF(AND($CF14<>"",IFERROR(INDEX(subsample_country_map!$E:$E,MATCH($CF14,subsample_country_map!$A:$A,0)),"")<>""),INDEX(subsample_country_map!$E:$E,MATCH($CF14,subsample_country_map!$A:$A,0)),INDEX(lookup!$AD:$AD,MATCH($A14,lookup!$A:$A,0))) -> 99_NCE | AO14: =INDEX(lookup!$Y:$Y,MATCH($A14,lookup!$A:$A,0)) -> 0_published | AP14: =INDEX(lookup!$Z:$Z,MATCH($A14,lookup!$A:$A,0)) -> 1_VHB high | AQ14: =INDEX(lookup!$W:$W,MATCH($A14,lookup!$A:$A,0)) -> 1_fin/acc/econ | AS14: staging | AT14: author-inverted-to-good | AU14: cost | AV14: -0.397 | AX14: -2.40 | BA14: 3666 | BB14: 0 | BC14: OLS | BD14: not stated | BE14: none | BI14: Table 6 | BJ14: Panel B col 1 | BK14: 9 | BL14: CCP1 -0.397** (-2.40) | BM14: CCP1 | BN14: COD | BO14: update | BP14: Al-Fakir Al Rabab'a et al (2023) | BQ14: computed | BT14: 0 | BU14: staging_Al-Fakir_Al_Rababa_et_al_2023.csv | BW14: 2003 | BX14: 2018 | BY14: multi: 14 Asia-Pacific countries (Australia, China, Hong Kong, India, Indonesia, Japan, Malaysia, New Zealand, Philippines, Singapore, South Korea, Sri Lanka, Taiwan, Thailand) | BZ14: 2010.5 | CA14: 0.1875 | CB14: 0 | CC14: 1 | CD14: -0.039627927 | CE14: 1
A15: Al-Fakir Al Rabab'a et al (2023) | B15: 1320 | C15: -0.031694708 | D15: 3666 | E15: =IF(ISNUMBER($BA15),$BA15,IF(AND(ISNUMBER($D15),ISNUMBER($BW15),ISNUMBER($BX15)),$D15*($BX15-$BW15+1),"")) -> 3666 | H15: partial | I15: T-Statistic available | J15: =IF($BW15<>"",$BW15,"") -> 2003 | K15: =IF($BX15<>"",$BX15,"") -> 2018 | L15: =IF(AND(ISNUMBER($BW15),ISNUMBER($BX15)),($BW15+$BX15)/2,"") -> 2010.5 | M15: =IF($L15<>"",$L15,"") -> 2010.5 | N15: =IF(AND(ISNUMBER($BW15),ISNUMBER($BX15)),MIN(1,MAX(0,($BX15-2016+1)/($BX15-$BW15+1))),"") -> 0.1875 | O15: =IF(AND(ISNUMBER($BW15),ISNUMBER($BX15)),MIN(1,MAX(0,($BX15-2017+1)/($BX15-$BW15+1))),"") -> 0.125 | P15: =IF(AND(ISNUMBER($BW15),ISNUMBER($BX15)),MIN(1,MAX(0,($BX15-2018+1)/($BX15-$BW15+1))),"") -> 0.0625 | Q15: =IF(AND(ISNUMBER($BW15),ISNUMBER($BX15)),MIN(1,MAX(0,($BX15-2019+1)/($BX15-$BW15+1))),"") -> 0 | R15: =IF(AND(ISNUMBER($BW15),ISNUMBER($BX15)),MIN(1,MAX(0,($BX15-2016+1)/($BX15-$BW15+1))),"") -> 0.1875 | S15: =IF($L15<>"",IF($L15>=2015.5,1,0),"") -> 0 | T15: =IF($L15<>"",IF($L15>=2016,1,0),"") -> 0 | U15: =IF(ISNUMBER($BX15),IF($BX15>=2016,1,0),"") -> 1 | V15: =IF(ISNUMBER($BW15),IF($BW15>=2016,1,0),"") -> 0 | W15: =IF(AND(ISNUMBER($BW15),ISNUMBER($BX15)),IF($BW15>=2016,"post-only",IF($BX15<2016,"pre-only","mixed")),"") -> mixed | X15: =IF(AND(ISNUMBER($BW15),ISNUMBER($BX15)),MIN(1,MAX(0,($BX15-2017+1)/($BX15-$BW15+1))),"") -> 0.125 | Y15: =IF(AND(ISNUMBER($BW15),ISNUMBER($BX15)),MIN(1,MAX(0,($BX15-2018+1)/($BX15-$BW15+1))),"") -> 0.0625 | Z15: =IF(AND(ISNUMBER($BW15),ISNUMBER($BX15)),MIN(1,MAX(0,($BX15-2019+1)/($BX15-$BW15+1))),"") -> 0 | AA15: =IF(ISNUMBER($BX15),IF($BX15>=2017,1,0),"") -> 1 | AB15: =IF(ISNUMBER($BX15),IF($BX15>=2018,1,0),"") -> 1 | AC15: =IF(ISNUMBER($BX15),IF($BX15>=2019,1,0),"") -> 0 | AD15: =IF($L15<>"",IF($L15>2013,1,0),"") -> 0 | AE15: =IF($L15<>"",1+IF($L15>2011,1,0)+IF($L15>2014,1,0),"") -> 1 | AF15: loan (interest rate) | AG15: performance | AH15: non-sensitive | AI15: 99_NCE | AJ15: 99_NCE | AK15: =IF(AND($CF15<>"",IFERROR(INDEX(subsample_country_map!$B:$B,MATCH($CF15,subsample_country_map!$A:$A,0)),"")<>""),INDEX(subsample_country_map!$B:$B,MATCH($CF15,subsample_country_map!$A:$A,0)),INDEX(lookup!$AA:$AA,MATCH($A15,lookup!$A:$A,0))) -> 3_AsiaPac | AL15: =IF(AND($CF15<>"",IFERROR(INDEX(subsample_country_map!$C:$C,MATCH($CF15,subsample_country_map!$A:$A,0)),"")<>""),INDEX(subsample_country_map!$C:$C,MATCH($CF15,subsample_country_map!$A:$A,0)),INDEX(lookup!$AB:$AB,MATCH($A15,lookup!$A:$A,0))) -> 99_NCE | AM15: =IF(AND($CF15<>"",IFERROR(INDEX(subsample_country_map!$D:$D,MATCH($CF15,subsample_country_map!$A:$A,0)),"")<>""),INDEX(subsample_country_map!$D:$D,MATCH($CF15,subsample_country_map!$A:$A,0)),INDEX(lookup!$AC:$AC,MATCH($A15,lookup!$A:$A,0))) -> 99_NCE | AN15: =IF(AND($CF15<>"",IFERROR(INDEX(subsample_country_map!$E:$E,MATCH($CF15,subsample_country_map!$A:$A,0)),"")<>""),INDEX(subsample_country_map!$E:$E,MATCH($CF15,subsample_country_map!$A:$A,0)),INDEX(lookup!$AD:$AD,MATCH($A15,lookup!$A:$A,0))) -> 99_NCE | AO15: =INDEX(lookup!$Y:$Y,MATCH($A15,lookup!$A:$A,0)) -> 0_published | AP15: =INDEX(lookup!$Z:$Z,MATCH($A15,lookup!$A:$A,0)) -> 1_VHB high | AQ15: =INDEX(lookup!$W:$W,MATCH($A15,lookup!$A:$A,0)) -> 1_fin/acc/econ | AS15: staging | AT15: author-inverted-to-good | AU15: cost | AV15: -0.509 | AX15: -1.92 | BA15: 3666 | BB15: 0 | BC15: OLS | BD15: not stated | BE15: none | BI15: Table 6 | BJ15: Panel B col 2 | BK15: 9 | BL15: CCP2 -0.509* (-1.92) | BM15: CCP2 | BN15: COD | BO15: update | BP15: Al-Fakir Al Rabab'a et al (2023) | BQ15: computed | BT15: 0 | BU15: staging_Al-Fakir_Al_Rababa_et_al_2023.csv | BW15: 2003 | BX15: 2018 | BY15: multi: 14 Asia-Pacific countries (Australia, China, Hong Kong, India, Indonesia, Japan, Malaysia, New Zealand, Philippines, Singapore, South Korea, Sri Lanka, Taiwan, Thailand) | BZ15: 2010.5 | CA15: 0.1875 | CB15: 0 | CC15: 1 | CD15: -0.031705327 | CE15: 1
A16: Al-Fakir Al Rabab'a et al (2023) | B16: 1321 | C16: -0.048499774 | D16: 3666 | E16: =IF(ISNUMBER($BA16),$BA16,IF(AND(ISNUMBER($D16),ISNUMBER($BW16),ISNUMBER($BX16)),$D16*($BX16-$BW16+1),"")) -> 3666 | H16: partial | I16: T-Statistic available | J16: =IF($BW16<>"",$BW16,"") -> 2003 | K16: =IF($BX16<>"",$BX16,"") -> 2018 | L16: =IF(AND(ISNUMBER($BW16),ISNUMBER($BX16)),($BW16+$BX16)/2,"") -> 2010.5 | M16: =IF($L16<>"",$L16,"") -> 2010.5 | N16: =IF(AND(ISNUMBER($BW16),ISNUMBER($BX16)),MIN(1,MAX(0,($BX16-2016+1)/($BX16-$BW16+1))),"") -> 0.1875 | O16: =IF(AND(ISNUMBER($BW16),ISNUMBER($BX16)),MIN(1,MAX(0,($BX16-2017+1)/($BX16-$BW16+1))),"") -> 0.125 | P16: =IF(AND(ISNUMBER($BW16),ISNUMBER($BX16)),MIN(1,MAX(0,($BX16-2018+1)/($BX16-$BW16+1))),"") -> 0.0625 | Q16: =IF(AND(ISNUMBER($BW16),ISNUMBER($BX16)),MIN(1,MAX(0,($BX16-2019+1)/($BX16-$BW16+1))),"") -> 0 | R16: =IF(AND(ISNUMBER($BW16),ISNUMBER($BX16)),MIN(1,MAX(0,($BX16-2016+1)/($BX16-$BW16+1))),"") -> 0.1875 | S16: =IF($L16<>"",IF($L16>=2015.5,1,0),"") -> 0 | T16: =IF($L16<>"",IF($L16>=2016,1,0),"") -> 0 | U16: =IF(ISNUMBER($BX16),IF($BX16>=2016,1,0),"") -> 1 | V16: =IF(ISNUMBER($BW16),IF($BW16>=2016,1,0),"") -> 0 | W16: =IF(AND(ISNUMBER($BW16),ISNUMBER($BX16)),IF($BW16>=2016,"post-only",IF($BX16<2016,"pre-only","mixed")),"") -> mixed | X16: =IF(AND(ISNUMBER($BW16),ISNUMBER($BX16)),MIN(1,MAX(0,($BX16-2017+1)/($BX16-$BW16+1))),"") -> 0.125 | Y16: =IF(AND(ISNUMBER($BW16),ISNUMBER($BX16)),MIN(1,MAX(0,($BX16-2018+1)/($BX16-$BW16+1))),"") -> 0.0625 | Z16: =IF(AND(ISNUMBER($BW16),ISNUMBER($BX16)),MIN(1,MAX(0,($BX16-2019+1)/($BX16-$BW16+1))),"") -> 0 | AA16: =IF(ISNUMBER($BX16),IF($BX16>=2017,1,0),"") -> 1 | AB16: =IF(ISNUMBER($BX16),IF($BX16>=2018,1,0),"") -> 1 | AC16: =IF(ISNUMBER($BX16),IF($BX16>=2019,1,0),"") -> 0 | AD16: =IF($L16<>"",IF($L16>2013,1,0),"") -> 0 | AE16: =IF($L16<>"",1+IF($L16>2011,1,0)+IF($L16>2014,1,0),"") -> 1 | AF16: loan (interest rate) | AG16: performance | AH16: non-sensitive | AI16: 99_NCE | AJ16: 99_NCE | AK16: =IF(AND($CF16<>"",IFERROR(INDEX(subsample_country_map!$B:$B,MATCH($CF16,subsample_country_map!$A:$A,0)),"")<>""),INDEX(subsample_country_map!$B:$B,MATCH($CF16,subsample_country_map!$A:$A,0)),INDEX(lookup!$AA:$AA,MATCH($A16,lookup!$A:$A,0))) -> 3_AsiaPac | AL16: =IF(AND($CF16<>"",IFERROR(INDEX(subsample_country_map!$C:$C,MATCH($CF16,subsample_country_map!$A:$A,0)),"")<>""),INDEX(subsample_country_map!$C:$C,MATCH($CF16,subsample_country_map!$A:$A,0)),INDEX(lookup!$AB:$AB,MATCH($A16,lookup!$A:$A,0))) -> 99_NCE | AM16: =IF(AND($CF16<>"",IFERROR(INDEX(subsample_country_map!$D:$D,MATCH($CF16,subsample_country_map!$A:$A,0)),"")<>""),INDEX(subsample_country_map!$D:$D,MATCH($CF16,subsample_country_map!$A:$A,0)),INDEX(lookup!$AC:$AC,MATCH($A16,lookup!$A:$A,0))) -> 99_NCE | AN16: =IF(AND($CF16<>"",IFERROR(INDEX(subsample_country_map!$E:$E,MATCH($CF16,subsample_country_map!$A:$A,0)),"")<>""),INDEX(subsample_country_map!$E:$E,MATCH($CF16,subsample_country_map!$A:$A,0)),INDEX(lookup!$AD:$AD,MATCH($A16,lookup!$A:$A,0))) -> 99_NCE | AO16: =INDEX(lookup!$Y:$Y,MATCH($A16,lookup!$A:$A,0)) -> 0_published | AP16: =INDEX(lookup!$Z:$Z,MATCH($A16,lookup!$A:$A,0)) -> 1_VHB high | AQ16: =INDEX(lookup!$W:$W,MATCH($A16,lookup!$A:$A,0)) -> 1_fin/acc/econ | AS16: staging | AT16: good-CER | AU16: cost | AV16: -0.157 | AX16: -2.94 | BA16: 3666 | BB16: 0 | BC16: OLS | BD16: not stated | BE16: none | BI16: Table 6 | BJ16: Panel B col 3 | BK16: 9 | BL16: CCP3 -0.157*** (-2.94) | BM16: CCP3 | BN16: COD | BO16: update | BP16: Al-Fakir Al Rabab'a et al (2023) | BQ16: computed | BT16: 0 | BU16: staging_Al-Fakir_Al_Rababa_et_al_2023.csv | BW16: 2003 | BX16: 2018 | BY16: multi: 14 Asia-Pacific countries (Australia, China, Hong Kong, India, Indonesia, Japan, Malaysia, New Zealand, Philippines, Singapore, South Korea, Sri Lanka, Taiwan, Thailand) | BZ16: 2010.5 | CA16: 0.1875 | CB16: 0 | CC16: 1 | CD16: -0.048537856 | CE16: 1
A17: Al-Fakir Al Rabab'a et al (2023) | B17: 1322 | C17: -0.046195313 | D17: 3666 | E17: =IF(ISNUMBER($BA17),$BA17,IF(AND(ISNUMBER($D17),ISNUMBER($BW17),ISNUMBER($BX17)),$D17*($BX17-$BW17+1),"")) -> 3666 | H17: partial | I17: T-Statistic available | J17: =IF($BW17<>"",$BW17,"") -> 2003 | K17: =IF($BX17<>"",$BX17,"") -> 2018 | L17: =IF(AND(ISNUMBER($BW17),ISNUMBER($BX17)),($BW17+$BX17)/2,"") -> 2010.5 | M17: =IF($L17<>"",$L17,"") -> 2010.5 | N17: =IF(AND(ISNUMBER($BW17),ISNUMBER($BX17)),MIN(1,MAX(0,($BX17-2016+1)/($BX17-$BW17+1))),"") -> 0.1875 | O17: =IF(AND(ISNUMBER($BW17),ISNUMBER($BX17)),MIN(1,MAX(0,($BX17-2017+1)/($BX17-$BW17+1))),"") -> 0.125 | P17: =IF(AND(ISNUMBER($BW17),ISNUMBER($BX17)),MIN(1,MAX(0,($BX17-2018+1)/($BX17-$BW17+1))),"") -> 0.0625 | Q17: =IF(AND(ISNUMBER($BW17),ISNUMBER($BX17)),MIN(1,MAX(0,($BX17-2019+1)/($BX17-$BW17+1))),"") -> 0 | R17: =IF(AND(ISNUMBER($BW17),ISNUMBER($BX17)),MIN(1,MAX(0,($BX17-2016+1)/($BX17-$BW17+1))),"") -> 0.1875 | S17: =IF($L17<>"",IF($L17>=2015.5,1,0),"") -> 0 | T17: =IF($L17<>"",IF($L17>=2016,1,0),"") -> 0 | U17: =IF(ISNUMBER($BX17),IF($BX17>=2016,1,0),"") -> 1 | V17: =IF(ISNUMBER($BW17),IF($BW17>=2016,1,0),"") -> 0 | W17: =IF(AND(ISNUMBER($BW17),ISNUMBER($BX17)),IF($BW17>=2016,"post-only",IF($BX17<2016,"pre-only","mixed")),"") -> mixed | X17: =IF(AND(ISNUMBER($BW17),ISNUMBER($BX17)),MIN(1,MAX(0,($BX17-2017+1)/($BX17-$BW17+1))),"") -> 0.125 | Y17: =IF(AND(ISNUMBER($BW17),ISNUMBER($BX17)),MIN(1,MAX(0,($BX17-2018+1)/($BX17-$BW17+1))),"") -> 0.0625 | Z17: =IF(AND(ISNUMBER($BW17),ISNUMBER($BX17)),MIN(1,MAX(0,($BX17-2019+1)/($BX17-$BW17+1))),"") -> 0 | AA17: =IF(ISNUMBER($BX17),IF($BX17>=2017,1,0),"") -> 1 | AB17: =IF(ISNUMBER($BX17),IF($BX17>=2018,1,0),"") -> 1 | AC17: =IF(ISNUMBER($BX17),IF($BX17>=2019,1,0),"") -> 0 | AD17: =IF($L17<>"",IF($L17>2013,1,0),"") -> 0 | AE17: =IF($L17<>"",1+IF($L17>2011,1,0)+IF($L17>2014,1,0),"") -> 1 | AF17: loan (interest rate) | AG17: performance | AH17: non-sensitive | AI17: 99_NCE | AJ17: 99_NCE | AK17: =IF(AND($CF17<>"",IFERROR(INDEX(subsample_country_map!$B:$B,MATCH($CF17,subsample_country_map!$A:$A,0)),"")<>""),INDEX(subsample_country_map!$B:$B,MATCH($CF17,subsample_country_map!$A:$A,0)),INDEX(lookup!$AA:$AA,MATCH($A17,lookup!$A:$A,0))) -> 3_AsiaPac | AL17: =IF(AND($CF17<>"",IFERROR(INDEX(subsample_country_map!$C:$C,MATCH($CF17,subsample_country_map!$A:$A,0)),"")<>""),INDEX(subsample_country_map!$C:$C,MATCH($CF17,subsample_country_map!$A:$A,0)),INDEX(lookup!$AB:$AB,MATCH($A17,lookup!$A:$A,0))) -> 99_NCE | AM17: =IF(AND($CF17<>"",IFERROR(INDEX(subsample_country_map!$D:$D,MATCH($CF17,subsample_country_map!$A:$A,0)),"")<>""),INDEX(subsample_country_map!$D:$D,MATCH($CF17,subsample_country_map!$A:$A,0)),INDEX(lookup!$AC:$AC,MATCH($A17,lookup!$A:$A,0))) -> 99_NCE | AN17: =IF(AND($CF17<>"",IFERROR(INDEX(subsample_country_map!$E:$E,MATCH($CF17,subsample_country_map!$A:$A,0)),"")<>""),INDEX(subsample_country_map!$E:$E,MATCH($CF17,subsample_country_map!$A:$A,0)),INDEX(lookup!$AD:$AD,MATCH($A17,lookup!$A:$A,0))) -> 99_NCE | AO17: =INDEX(lookup!$Y:$Y,MATCH($A17,lookup!$A:$A,0)) -> 0_published | AP17: =INDEX(lookup!$Z:$Z,MATCH($A17,lookup!$A:$A,0)) -> 1_VHB high | AQ17: =INDEX(lookup!$W:$W,MATCH($A17,lookup!$A:$A,0)) -> 1_fin/acc/econ | AS17: staging | AT17: good-CER | AU17: cost | AV17: -0.241 | AX17: -2.80 | BA17: 3666 | BB17: 0 | BC17: OLS | BD17: not stated | BE17: none | BI17: Table 6 | BJ17: Panel B col 4 | BK17: 9 | BL17: CCP4 -0.241*** (-2.80) | BM17: CCP4 | BN17: COD | BO17: update | BP17: Al-Fakir Al Rabab'a et al (2023) | BQ17: computed | BT17: 0 | BU17: staging_Al-Fakir_Al_Rababa_et_al_2023.csv | BW17: 2003 | BX17: 2018 | BY17: multi: 14 Asia-Pacific countries (Australia, China, Hong Kong, India, Indonesia, Japan, Malaysia, New Zealand, Philippines, Singapore, South Korea, Sri Lanka, Taiwan, Thailand) | BZ17: 2010.5 | CA17: 0.1875 | CB17: 0 | CC17: 1 | CD17: -0.046228215 | CE17: 1
... A25: Al-Fakir Al Rabab'a et al (2023) | B25: 1330 | C25: -0.040760514 | D25: 3666 | E25: =IF(ISNUMBER($BA25),$BA25,IF(AND(ISNUMBER($D25),ISNUMBER($BW25),ISNUMBER($BX25)),$D25*($BX25-$BW25+1),"")) -> 3666 | H25: partial | I25: T-Statistic available | J25: =IF($BW25<>"",$BW25,"") -> 2003 | K25: =IF($BX25<>"",$BX25,"") -> 2018 | L25: =IF(AND(ISNUMBER($BW25),ISNUMBER($BX25)),($BW25+$BX25)/2,"") -> 2010.5 | M25: =IF($L25<>"",$L25,"") -> 2010.5 | N25: =IF(AND(ISNUMBER($BW25),ISNUMBER($BX25)),MIN(1,MAX(0,($BX25-2016+1)/($BX25-$BW25+1))),"") -> 0.1875 | O25: =IF(AND(ISNUMBER($BW25),ISNUMBER($BX25)),MIN(1,MAX(0,($BX25-2017+1)/($BX25-$BW25+1))),"") -> 0.125 | P25: =IF(AND(ISNUMBER($BW25),ISNUMBER($BX25)),MIN(1,MAX(0,($BX25-2018+1)/($BX25-$BW25+1))),"") -> 0.0625 | Q25: =IF(AND(ISNUMBER($BW25),ISNUMBER($BX25)),MIN(1,MAX(0,($BX25-2019+1)/($BX25-$BW25+1))),"") -> 0 | R25: =IF(AND(ISNUMBER($BW25),ISNUMBER($BX25)),MIN(1,MAX(0,($BX25-2016+1)/($BX25-$BW25+1))),"") -> 0.1875 | S25: =IF($L25<>"",IF($L25>=2015.5,1,0),"") -> 0 | T25: =IF($L25<>"",IF($L25>=2016,1,0),"") -> 0 | U25: =IF(ISNUMBER($BX25),IF($BX25>=2016,1,0),"") -> 1 | V25: =IF(ISNUMBER($BW25),IF($BW25>=2016,1,0),"") -> 0 | W25: =IF(AND(ISNUMBER($BW25),ISNUMBER($BX25)),IF($BW25>=2016,"post-only",IF($BX25<2016,"pre-only","mixed")),"") -> mixed | X25: =IF(AND(ISNUMBER($BW25),ISNUMBER($BX25)),MIN(1,MAX(0,($BX25-2017+1)/($BX25-$BW25+1))),"") -> 0.125 | Y25: =IF(AND(ISNUMBER($BW25),ISNUMBER($BX25)),MIN(1,MAX(0,($BX25-2018+1)/($BX25-$BW25+1))),"") -> 0.0625 | Z25: =IF(AND(ISNUMBER($BW25),ISNUMBER($BX25)),MIN(1,MAX(0,($BX25-2019+1)/($BX25-$BW25+1))),"") -> 0 | AA25: =IF(ISNUMBER($BX25),IF($BX25>=2017,1,0),"") -> 1 | AB25: =IF(ISNUMBER($BX25),IF($BX25>=2018,1,0),"") -> 1 | AC25: =IF(ISNUMBER($BX25),IF($BX25>=2019,1,0),"") -> 0 | AD25: =IF($L25<>"",IF($L25>2013,1,0),"") -> 0 | AE25: =IF($L25<>"",1+IF($L25>2011,1,0)+IF($L25>2014,1,0),"") -> 1 | AF25: loan (interest rate) | AG25: performance | AH25: non-sensitive | AI25: 99_NCE | AJ25: 99_NCE | AK25: =IF(AND($CF25<>"",IFERROR(INDEX(subsample_country_map!$B:$B,MATCH($CF25,subsample_country_map!$A:$A,0)),"")<>""),INDEX(subsample_country_map!$B:$B,MATCH($CF25,subsample_country_map!$A:$A,0)),INDEX(lookup!$AA:$AA,MATCH($A25,lookup!$A:$A,0))) -> 3_AsiaPac | AL25: =IF(AND($CF25<>"",IFERROR(INDEX(subsample_country_map!$C:$C,MATCH($CF25,subsample_country_map!$A:$A,0)),"")<>""),INDEX(subsample_country_map!$C:$C,MATCH($CF25,subsample_country_map!$A:$A,0)),INDEX(lookup!$AB:$AB,MATCH($A25,lookup!$A:$A,0))) -> 99_NCE | AM25: =IF(AND($CF25<>"",IFERROR(INDEX(subsample_country_map!$D:$D,MATCH($CF25,subsample_country_map!$A:$A,0)),"")<>""),INDEX(subsample_country_map!$D:$D,MATCH($CF25,subsample_country_map!$A:$A,0)),INDEX(lookup!$AC:$AC,MATCH($A25,lookup!$A:$A,0))) -> 99_NCE | AN25: =IF(AND($CF25<>"",IFERROR(INDEX(subsample_country_map!$E:$E,MATCH($CF25,subsample_country_map!$A:$A,0)),"")<>""),INDEX(subsample_country_map!$E:$E,MATCH($CF25,subsample_country_map!$A:$A,0)),INDEX(lookup!$AD:$AD,MATCH($A25,lookup!$A:$A,0))) -> 99_NCE | AO25: =INDEX(lookup!$Y:$Y,MATCH($A25,lookup!$A:$A,0)) -> 0_published | AP25: =INDEX(lookup!$Z:$Z,MATCH($A25,lookup!$A:$A,0)) -> 1_VHB high | AQ25: =INDEX(lookup!$W:$W,MATCH($A25,lookup!$A:$A,0)) -> 1_fin/acc/econ | AS25: staging | AT25: good-CER | AU25: cost | AV25: -0.018 | AX25: -2.47 | BA25: 3666 | BB25: 0 | BC25: other:Heckman's (1979) two-stage model (second stage) | BD25: firm | BE25: none | BI25: Table 7 | BJ25: Second stage col 5 | BK25: 11 | BL25: CCP4 -0.018** (-2.47) | BM25: CCP4 | BN25: COD | BO25: update | BP25: Al-Fakir Al Rabab'a et al (2023) | BQ25: computed | BT25: 0 | BU25: staging_Al-Fakir_Al_Rababa_et_al_2023.csv | BW25: 2003 | BX25: 2018 | BY25: multi: 14 Asia-Pacific countries (Australia, China, Hong Kong, India, Indonesia, Japan, Malaysia, New Zealand, Philippines, Singapore, South Korea, Sri Lanka, Taiwan, Thailand) | BZ25: 2010.5 | CA25: 0.1875 | CB25: 0 | CC25: 1 | CD25: -0.04078311 | CE25: 1
A26: Al-Fakir Al Rabab'a et al (2023) | B26: 1331 | C26: -0.040139362 | D26: 2237 | E26: =IF(ISNUMBER($BA26),$BA26,IF(AND(ISNUMBER($D26),ISNUMBER($BW26),ISNUMBER($BX26)),$D26*($BX26-$BW26+1),"")) -> 2237 | H26: partial | I26: T-Statistic available | J26: =IF($BW26<>"",$BW26,"") -> 2003 | K26: =IF($BX26<>"",$BX26,"") -> 2018 | L26: =IF(AND(ISNUMBER($BW26),ISNUMBER($BX26)),($BW26+$BX26)/2,"") -> 2010.5 | M26: =IF($L26<>"",$L26,"") -> 2010.5 | N26: =IF(AND(ISNUMBER($BW26),ISNUMBER($BX26)),MIN(1,MAX(0,($BX26-2016+1)/($BX26-$BW26+1))),"") -> 0.1875 | O26: =IF(AND(ISNUMBER($BW26),ISNUMBER($BX26)),MIN(1,MAX(0,($BX26-2017+1)/($BX26-$BW26+1))),"") -> 0.125 | P26: =IF(AND(ISNUMBER($BW26),ISNUMBER($BX26)),MIN(1,MAX(0,($BX26-2018+1)/($BX26-$BW26+1))),"") -> 0.0625 | Q26: =IF(AND(ISNUMBER($BW26),ISNUMBER($BX26)),MIN(1,MAX(0,($BX26-2019+1)/($BX26-$BW26+1))),"") -> 0 | R26: =IF(AND(ISNUMBER($BW26),ISNUMBER($BX26)),MIN(1,MAX(0,($BX26-2016+1)/($BX26-$BW26+1))),"") -> 0.1875 | S26: =IF($L26<>"",IF($L26>=2015.5,1,0),"") -> 0 | T26: =IF($L26<>"",IF($L26>=2016,1,0),"") -> 0 | U26: =IF(ISNUMBER($BX26),IF($BX26>=2016,1,0),"") -> 1 | V26: =IF(ISNUMBER($BW26),IF($BW26>=2016,1,0),"") -> 0 | W26: =IF(AND(ISNUMBER($BW26),ISNUMBER($BX26)),IF($BW26>=2016,"post-only",IF($BX26<2016,"pre-only","mixed")),"") -> mixed | X26: =IF(AND(ISNUMBER($BW26),ISNUMBER($BX26)),MIN(1,MAX(0,($BX26-2017+1)/($BX26-$BW26+1))),"") -> 0.125 | Y26: =IF(AND(ISNUMBER($BW26),ISNUMBER($BX26)),MIN(1,MAX(0,($BX26-2018+1)/($BX26-$BW26+1))),"") -> 0.0625 | Z26: =IF(AND(ISNUMBER($BW26),ISNUMBER($BX26)),MIN(1,MAX(0,($BX26-2019+1)/($BX26-$BW26+1))),"") -> 0 | AA26: =IF(ISNUMBER($BX26),IF($BX26>=2017,1,0),"") -> 1 | AB26: =IF(ISNUMBER($BX26),IF($BX26>=2018,1,0),"") -> 1 | AC26: =IF(ISNUMBER($BX26),IF($BX26>=2019,1,0),"") -> 0 | AD26: =IF($L26<>"",IF($L26>2013,1,0),"") -> 0 | AE26: =IF($L26<>"",1+IF($L26>2011,1,0)+IF($L26>2014,1,0),"") -> 1 | AF26: loan (interest rate) | AG26: performance | AH26: non-sensitive | AI26: 99_NCE | AJ26: 99_NCE | AK26: =IF(AND($CF26<>"",IFERROR(INDEX(subsample_country_map!$B:$B,MATCH($CF26,subsample_country_map!$A:$A,0)),"")<>""),INDEX(subsample_country_map!$B:$B,MATCH($CF26,subsample_country_map!$A:$A,0)),INDEX(lookup!$AA:$AA,MATCH($A26,lookup!$A:$A,0))) -> 3_AsiaPac | AL26: =IF(AND($CF26<>"",IFERROR(INDEX(subsample_country_map!$C:$C,MATCH($CF26,subsample_country_map!$A:$A,0)),"")<>""),INDEX(subsample_country_map!$C:$C,MATCH($CF26,subsample_country_map!$A:$A,0)),INDEX(lookup!$AB:$AB,MATCH($A26,lookup!$A:$A,0))) -> 1_developed | AM26: =IF(AND($CF26<>"",IFERROR(INDEX(subsample_country_map!$D:$D,MATCH($CF26,subsample_country_map!$A:$A,0)),"")<>""),INDEX(subsample_country_map!$D:$D,MATCH($CF26,subsample_country_map!$A:$A,0)),INDEX(lookup!$AC:$AC,MATCH($A26,lookup!$A:$A,0))) -> 2_non_western | AN26: =IF(AND($CF26<>"",IFERROR(INDEX(subsample_country_map!$E:$E,MATCH($CF26,subsample_country_map!$A:$A,0)),"")<>""),INDEX(subsample_country_map!$E:$E,MATCH($CF26,subsample_country_map!$A:$A,0)),INDEX(lookup!$AD:$AD,MATCH($A26,lookup!$A:$A,0))) -> 2_civil law | AO26: =INDEX(lookup!$Y:$Y,MATCH($A26,lookup!$A:$A,0)) -> 0_published | AP26: =INDEX(lookup!$Z:$Z,MATCH($A26,lookup!$A:$A,0)) -> 1_VHB high | AQ26: =INDEX(lookup!$W:$W,MATCH($A26,lookup!$A:$A,0)) -> 1_fin/acc/econ | AS26: staging | AT26: author-inverted-to-good | AU26: cost | AV26: -0.012 | AX26: -1.90 | BA26: 2237 | BB26: 0 | BC26: OLS | BD26: not stated | BE26: region | BF26: Japan | BI26: Table 8 | BJ26: Panel A col 1 | BK26: 12 | BL26: CCP1 -0.012* (-1.90) | BM26: CCP1 | BN26: COD | BO26: update | BP26: Al-Fakir Al Rabab'a et al (2023) | BQ26: computed | BT26: 0 | BU26: staging_Al-Fakir_Al_Rababa_et_al_2023.csv | BW26: 2003 | BX26: 2018 | BY26: multi: 14 Asia-Pacific countries (Australia, China, Hong Kong, India, Indonesia, Japan, Malaysia, New Zealand, Philippines, Singapore, South Korea, Sri Lanka, Taiwan, Thailand) | BZ26: 2010.5 | CA26: 0.1875 | CB26: 0 | CC26: 1 | CD26: -0.04016094 | CE26: 1 | CF26: Japan
A27: Al-Fakir Al Rabab'a et al (2023) | B27: 1332 | C27: -0.045410598 | D27: 2237 | E27: =IF(ISNUMBER($BA27),$BA27,IF(AND(ISNUMBER($D27),ISNUMBER($BW27),ISNUMBER($BX27)),$D27*($BX27-$BW27+1),"")) -> 2237 | H27: partial | I27: T-Statistic available | J27: =IF($BW27<>"",$BW27,"") -> 2003 | K27: =IF($BX27<>"",$BX27,"") -> 2018 | L27: =IF(AND(ISNUMBER($BW27),ISNUMBER($BX27)),($BW27+$BX27)/2,"") -> 2010.5 | M27: =IF($L27<>"",$L27,"") -> 2010.5 | N27: =IF(AND(ISNUMBER($BW27),ISNUMBER($BX27)),MIN(1,MAX(0,($BX27-2016+1)/($BX27-$BW27+1))),"") -> 0.1875 | O27: =IF(AND(ISNUMBER($BW27),ISNUMBER($BX27)),MIN(1,MAX(0,($BX27-2017+1)/($BX27-$BW27+1))),"") -> 0.125 | P27: =IF(AND(ISNUMBER($BW27),ISNUMBER($BX27)),MIN(1,MAX(0,($BX27-2018+1)/($BX27-$BW27+1))),"") -> 0.0625 | Q27: =IF(AND(ISNUMBER($BW27),ISNUMBER($BX27)),MIN(1,MAX(0,($BX27-2019+1)/($BX27-$BW27+1))),"") -> 0 | R27: =IF(AND(ISNUMBER($BW27),ISNUMBER($BX27)),MIN(1,MAX(0,($BX27-2016+1)/($BX27-$BW27+1))),"") -> 0.1875 | S27: =IF($L27<>"",IF($L27>=2015.5,1,0),"") -> 0 | T27: =IF($L27<>"",IF($L27>=2016,1,0),"") -> 0 | U27: =IF(ISNUMBER($BX27),IF($BX27>=2016,1,0),"") -> 1 | V27: =IF(ISNUMBER($BW27),IF($BW27>=2016,1,0),"") -> 0 | W27: =IF(AND(ISNUMBER($BW27),ISNUMBER($BX27)),IF($BW27>=2016,"post-only",IF($BX27<2016,"pre-only","mixed")),"") -> mixed | X27: =IF(AND(ISNUMBER($BW27),ISNUMBER($BX27)),MIN(1,MAX(0,($BX27-2017+1)/($BX27-$BW27+1))),"") -> 0.125 | Y27: =IF(AND(ISNUMBER($BW27),ISNUMBER($BX27)),MIN(1,MAX(0,($BX27-2018+1)/($BX27-$BW27+1))),"") -> 0.0625 | Z27: =IF(AND(ISNUMBER($BW27),ISNUMBER($BX27)),MIN(1,MAX(0,($BX27-2019+1)/($BX27-$BW27+1))),"") -> 0 | AA27: =IF(ISNUMBER($BX27),IF($BX27>=2017,1,0),"") -> 1 | AB27: =IF(ISNUMBER($BX27),IF($BX27>=2018,1,0),"") -> 1 | AC27: =IF(ISNUMBER($BX27),IF($BX27>=2019,1,0),"") -> 0 | AD27: =IF($L27<>"",IF($L27>2013,1,0),"") -> 0 | AE27: =IF($L27<>"",1+IF($L27>2011,1,0)+IF($L27>2014,1,0),"") -> 1 | AF27: loan (interest rate) | AG27: performance | AH27: non-sensitive | AI27: 99_NCE | AJ27: 99_NCE | AK27: =IF(AND($CF27<>"",IFERROR(INDEX(subsample_country_map!$B:$B,MATCH($CF27,subsample_country_map!$A:$A,0)),"")<>""),INDEX(subsample_country_map!$B:$B,MATCH($CF27,subsample_country_map!$A:$A,0)),INDEX(lookup!$AA:$AA,MATCH($A27,lookup!$A:$A,0))) -> 3_AsiaPac | AL27: =IF(AND($CF27<>"",IFERROR(INDEX(subsample_country_map!$C:$C,MATCH($CF27,subsample_country_map!$A:$A,0)),"")<>""),INDEX(subsample_country_map!$C:$C,MATCH($CF27,subsample_country_map!$A:$A,0)),INDEX(lookup!$AB:$AB,MATCH($A27,lookup!$A:$A,0))) -> 1_developed | AM27: =IF(AND($CF27<>"",IFERROR(INDEX(subsample_country_map!$D:$D,MATCH($CF27,subsample_country_map!$A:$A,0)),"")<>""),INDEX(subsample_country_map!$D:$D,MATCH($CF27,subsample_country_map!$A:$A,0)),INDEX(lookup!$AC:$AC,MATCH($A27,lookup!$A:$A,0))) -> 2_non_western | AN27: =IF(AND($CF27<>"",IFERROR(INDEX(subsample_country_map!$E:$E,MATCH($CF27,subsample_country_map!$A:$A,0)),"")<>""),INDEX(subsample_country_map!$E:$E,MATCH($CF27,subsample_country_map!$A:$A,0)),INDEX(lookup!$AD:$AD,MATCH($A27,lookup!$A:$A,0))) -> 2_civil law | AO27: =INDEX(lookup!$Y:$Y,MATCH($A27,lookup!$A:$A,0)) -> 0_published | AP27: =INDEX(lookup!$Z:$Z,MATCH($A27,lookup!$A:$A,0)) -> 1_VHB high | AQ27: =INDEX(lookup!$W:$W,MATCH($A27,lookup!$A:$A,0)) -> 1_fin/acc/econ | AS27: staging | AT27: author-inverted-to-good | AU27: cost | AV27: -0.015 | AX27: -2.15 | BA27: 2237 | BB27: 0 | BC27: OLS | BD27: not stated | BE27: region | BF27: Japan | BI27: Table 8 | BJ27: Panel A col 2 | BK27: 12 | BL27: CCP2 -0.015** (-2.15) | BM27: CCP2 | BN27: COD | BO27: update | BP27: Al-Fakir Al Rabab'a et al (2023) | BQ27: computed | BT27: 0 | BU27: staging_Al-Fakir_Al_Rababa_et_al_2023.csv | BW27: 2003 | BX27: 2018 | BY27: multi: 14 Asia-Pacific countries (Australia, China, Hong Kong, India, Indonesia, Japan, Malaysia, New Zealand, Philippines, Singapore, South Korea, Sri Lanka, Taiwan, Thailand) | BZ27: 2010.5 | CA27: 0.1875 | CB27: 0 | CC27: 1 | CD27: -0.045441851 | CE27: 1 | CF27: Japan
A28: Al-Fakir Al Rabab'a et al (2023) | B28: 1333 | C28: 0.029164955 | D28: 2237 | E28: =IF(ISNUMBER($BA28),$BA28,IF(AND(ISNUMBER($D28),ISNUMBER($BW28),ISNUMBER($BX28)),$D28*($BX28-$BW28+1),"")) -> 2237 | H28: partial | I28: T-Statistic available | J28: =IF($BW28<>"",$BW28,"") -> 2003 | K28: =IF($BX28<>"",$BX28,"") -> 2018 | L28: =IF(AND(ISNUMBER($BW28),ISNUMBER($BX28)),($BW28+$BX28)/2,"") -> 2010.5 | M28: =IF($L28<>"",$L28,"") -> 2010.5 | N28: =IF(AND(ISNUMBER($BW28),ISNUMBER($BX28)),MIN(1,MAX(0,($BX28-2016+1)/($BX28-$BW28+1))),"") -> 0.1875 | O28: =IF(AND(ISNUMBER($BW28),ISNUMBER($BX28)),MIN(1,MAX(0,($BX28-2017+1)/($BX28-$BW28+1))),"") -> 0.125 | P28: =IF(AND(ISNUMBER($BW28),ISNUMBER($BX28)),MIN(1,MAX(0,($BX28-2018+1)/($BX28-$BW28+1))),"") -> 0.0625 | Q28: =IF(AND(ISNUMBER($BW28),ISNUMBER($BX28)),MIN(1,MAX(0,($BX28-2019+1)/($BX28-$BW28+1))),"") -> 0 | R28: =IF(AND(ISNUMBER($BW28),ISNUMBER($BX28)),MIN(1,MAX(0,($BX28-2016+1)/($BX28-$BW28+1))),"") -> 0.1875 | S28: =IF($L28<>"",IF($L28>=2015.5,1,0),"") -> 0 | T28: =IF($L28<>"",IF($L28>=2016,1,0),"") -> 0 | U28: =IF(ISNUMBER($BX28),IF($BX28>=2016,1,0),"") -> 1 | V28: =IF(ISNUMBER($BW28),IF($BW28>=2016,1,0),"") -> 0 | W28: =IF(AND(ISNUMBER($BW28),ISNUMBER($BX28)),IF($BW28>=2016,"post-only",IF($BX28<2016,"pre-only","mixed")),"") -> mixed | X28: =IF(AND(ISNUMBER($BW28),ISNUMBER($BX28)),MIN(1,MAX(0,($BX28-2017+1)/($BX28-$BW28+1))),"") -> 0.125 | Y28: =IF(AND(ISNUMBER($BW28),ISNUMBER($BX28)),MIN(1,MAX(0,($BX28-2018+1)/($BX28-$BW28+1))),"") -> 0.0625 | Z28: =IF(AND(ISNUMBER($BW28),ISNUMBER($BX28)),MIN(1,MAX(0,($BX28-2019+1)/($BX28-$BW28+1))),"") -> 0 | AA28: =IF(ISNUMBER($BX28),IF($BX28>=2017,1,0),"") -> 1 | AB28: =IF(ISNUMBER($BX28),IF($BX28>=2018,1,0),"") -> 1 | AC28: =IF(ISNUMBER($BX28),IF($BX28>=2019,1,0),"") -> 0 | AD28: =IF($L28<>"",IF($L28>2013,1,0),"") -> 0 | AE28: =IF($L28<>"",1+IF($L28>2011,1,0)+IF($L28>2014,1,0),"") -> 1 | AF28: loan (interest rate) | AG28: performance | AH28: non-sensitive | AI28: 99_NCE | AJ28: 99_NCE | AK28: =IF(AND($CF28<>"",IFERROR(INDEX(subsample_country_map!$B:$B,MATCH($CF28,subsample_country_map!$A:$A,0)),"")<>""),INDEX(subsample_country_map!$B:$B,MATCH($CF28,subsample_country_map!$A:$A,0)),INDEX(lookup!$AA:$AA,MATCH($A28,lookup!$A:$A,0))) -> 3_AsiaPac | AL28: =IF(AND($CF28<>"",IFERROR(INDEX(subsample_country_map!$C:$C,MATCH($CF28,subsample_country_map!$A:$A,0)),"")<>""),INDEX(subsample_country_map!$C:$C,MATCH($CF28,subsample_country_map!$A:$A,0)),INDEX(lookup!$AB:$AB,MATCH($A28,lookup!$A:$A,0))) -> 1_developed | AM28: =IF(AND($CF28<>"",IFERROR(INDEX(subsample_country_map!$D:$D,MATCH($CF28,subsample_country_map!$A:$A,0)),"")<>""),INDEX(subsample_country_map!$D:$D,MATCH($CF28,subsample_country_map!$A:$A,0)),INDEX(lookup!$AC:$AC,MATCH($A28,lookup!$A:$A,0))) -> 2_non_western | AN28: =IF(AND($CF28<>"",IFERROR(INDEX(subsample_country_map!$E:$E,MATCH($CF28,subsample_country_map!$A:$A,0)),"")<>""),INDEX(subsample_country_map!$E:$E,MATCH($CF28,subsample_country_map!$A:$A,0)),INDEX(lookup!$AD:$AD,MATCH($A28,lookup!$A:$A,0))) -> 2_civil law | AO28: =INDEX(lookup!$Y:$Y,MATCH($A28,lookup!$A:$A,0)) -> 0_published | AP28: =INDEX(lookup!$Z:$Z,MATCH($A28,lookup!$A:$A,0)) -> 1_VHB high | AQ28: =INDEX(lookup!$W:$W,MATCH($A28,lookup!$A:$A,0)) -> 1_fin/acc/econ | AS28: staging | AT28: good-CER | AU28: cost | AV28: 0.003 | AX28: 1.38 | BA28: 2237 | BB28: 0 | BC28: OLS | BD28: not stated | BE28: region | BF28: Japan | BI28: Table 8 | BJ28: Panel A col 3 | BK28: 12 | BL28: CCP3 0.003 (1.38) | BM28: CCP3 | BN28: COD | BO28: update | BP28: Al-Fakir Al Rabab'a et al (2023) | BQ28: computed | BT28: 0 | BU28: staging_Al-Fakir_Al_Rababa_et_al_2023.csv | BW28: 2003 | BX28: 2018 | BY28: multi: 14 Asia-Pacific countries (Australia, China, Hong Kong, India, Indonesia, Japan, Malaysia, New Zealand, Philippines, Singapore, South Korea, Sri Lanka, Taiwan, Thailand) | BZ28: 2010.5 | CA28: 0.1875 | CB28: 0 | CC28: 1 | CD28: 0.029173228 | CE28: 1 | CF28: Japan
A29: Al-Fakir Al Rabab'a et al (2023) | B29: 1334 | C29: 0.023673545 | D29: 2237 | E29: =IF(ISNUMBER($BA29),$BA29,IF(AND(ISNUMBER($D29),ISNUMBER($BW29),ISNUMBER($BX29)),$D29*($BX29-$BW29+1),"")) -> 2237 | H29: partial | I29: T-Statistic available | J29: =IF($BW29<>"",$BW29,"") -> 2003 | K29: =IF($BX29<>"",$BX29,"") -> 2018 | L29: =IF(AND(ISNUMBER($BW29),ISNUMBER($BX29)),($BW29+$BX29)/2,"") -> 2010.5 | M29: =IF($L29<>"",$L29,"") -> 2010.5 | N29: =IF(AND(ISNUMBER($BW29),ISNUMBER($BX29)),MIN(1,MAX(0,($BX29-2016+1)/($BX29-$BW29+1))),"") -> 0.1875 | O29: =IF(AND(ISNUMBER($BW29),ISNUMBER($BX29)),MIN(1,MAX(0,($BX29-2017+1)/($BX29-$BW29+1))),"") -> 0.125 | P29: =IF(AND(ISNUMBER($BW29),ISNUMBER($BX29)),MIN(1,MAX(0,($BX29-2018+1)/($BX29-$BW29+1))),"") -> 0.0625 | Q29: =IF(AND(ISNUMBER($BW29),ISNUMBER($BX29)),MIN(1,MAX(0,($BX29-2019+1)/($BX29-$BW29+1))),"") -> 0 | R29: =IF(AND(ISNUMBER($BW29),ISNUMBER($BX29)),MIN(1,MAX(0,($BX29-2016+1)/($BX29-$BW29+1))),"") -> 0.1875 | S29: =IF($L29<>"",IF($L29>=2015.5,1,0),"") -> 0 | T29: =IF($L29<>"",IF($L29>=2016,1,0),"") -> 0 | U29: =IF(ISNUMBER($BX29),IF($BX29>=2016,1,0),"") -> 1 | V29: =IF(ISNUMBER($BW29),IF($BW29>=2016,1,0),"") -> 0 | W29: =IF(AND(ISNUMBER($BW29),ISNUMBER($BX29)),IF($BW29>=2016,"post-only",IF($BX29<2016,"pre-only","mixed")),"") -> mixed | X29: =IF(AND(ISNUMBER($BW29),ISNUMBER($BX29)),MIN(1,MAX(0,($BX29-2017+1)/($BX29-$BW29+1))),"") -> 0.125 | Y29: =IF(AND(ISNUMBER($BW29),ISNUMBER($BX29)),MIN(1,MAX(0,($BX29-2018+1)/($BX29-$BW29+1))),"") -> 0.0625 | Z29: =IF(AND(ISNUMBER($BW29),ISNUMBER($BX29)),MIN(1,MAX(0,($BX29-2019+1)/($BX29-$BW29+1))),"") -> 0 | AA29: =IF(ISNUMBER($BX29),IF($BX29>=2017,1,0),"") -> 1 | AB29: =IF(ISNUMBER($BX29),IF($BX29>=2018,1,0),"") -> 1 | AC29: =IF(ISNUMBER($BX29),IF($BX29>=2019,1,0),"") -> 0 | AD29: =IF($L29<>"",IF($L29>2013,1,0),"") -> 0 | AE29: =IF($L29<>"",1+IF($L29>2011,1,0)+IF($L29>2014,1,0),"") -> 1 | AF29: loan (interest rate) | AG29: performance | AH29: non-sensitive | AI29: 99_NCE | AJ29: 99_NCE | AK29: =IF(AND($CF29<>"",IFERROR(INDEX(subsample_country_map!$B:$B,MATCH($CF29,subsample_country_map!$A:$A,0)),"")<>""),INDEX(subsample_country_map!$B:$B,MATCH($CF29,subsample_country_map!$A:$A,0)),INDEX(lookup!$AA:$AA,MATCH($A29,lookup!$A:$A,0))) -> 3_AsiaPac | AL29: =IF(AND($CF29<>"",IFERROR(INDEX(subsample_country_map!$C:$C,MATCH($CF29,subsample_country_map!$A:$A,0)),"")<>""),INDEX(subsample_country_map!$C:$C,MATCH($CF29,subsample_country_map!$A:$A,0)),INDEX(lookup!$AB:$AB,MATCH($A29,lookup!$A:$A,0))) -> 1_developed | AM29: =IF(AND($CF29<>"",IFERROR(INDEX(subsample_country_map!$D:$D,MATCH($CF29,subsample_country_map!$A:$A,0)),"")<>""),INDEX(subsample_country_map!$D:$D,MATCH($CF29,subsample_country_map!$A:$A,0)),INDEX(lookup!$AC:$AC,MATCH($A29,lookup!$A:$A,0))) -> 2_non_western | AN29: =IF(AND($CF29<>"",IFERROR(INDEX(subsample_country_map!$E:$E,MATCH($CF29,subsample_country_map!$A:$A,0)),"")<>""),INDEX(subsample_country_map!$E:$E,MATCH($CF29,subsample_country_map!$A:$A,0)),INDEX(lookup!$AD:$AD,MATCH($A29,lookup!$A:$A,0))) -> 2_civil law | AO29: =INDEX(lookup!$Y:$Y,MATCH($A29,lookup!$A:$A,0)) -> 0_published | AP29: =INDEX(lookup!$Z:$Z,MATCH($A29,lookup!$A:$A,0)) -> 1_VHB high | AQ29: =INDEX(lookup!$W:$W,MATCH($A29,lookup!$A:$A,0)) -> 1_fin/acc/econ | AS29: staging | AT29: good-CER | AU29: cost | AV29: 0.003 | AX29: 1.12 | BA29: 2237 | BB29: 0 | BC29: OLS | BD29: not stated | BE29: region | BF29: Japan | BI29: Table 8 | BJ29: Panel A col 4 | BK29: 12 | BL29: CCP4 0.003 (1.12) | BM29: CCP4 | BN29: COD | BO29: update | BP29: Al-Fakir Al Rabab'a et al (2023) | BQ29: computed | BT29: 0 | BU29: staging_Al-Fakir_Al_Rababa_et_al_2023.csv | BW29: 2003 | BX29: 2018 | BY29: multi: 14 Asia-Pacific countries (Australia, China, Hong Kong, India, Indonesia, Japan, Malaysia, New Zealand, Philippines, Singapore, South Korea, Sri Lanka, Taiwan, Thailand) | BZ29: 2010.5 | CA29: 0.1875 | CB29: 0 | CC29: 1 | CD29: 0.023677969 | CE29: 1 | CF29: Japan
A30: Al-Fakir Al Rabab'a et al (2023) | B30: 1335 | C30: 0.11517851 | D30: 360 | E30: =IF(ISNUMBER($BA30),$BA30,IF(AND(ISNUMBER($D30),ISNUMBER($BW30),ISNUMBER($BX30)),$D30*($BX30-$BW30+1),"")) -> 360 | H30: partial | I30: T-Statistic available | J30: =IF($BW30<>"",$BW30,"") -> 2003 | K30: =IF($BX30<>"",$BX30,"") -> 2018 | L30: =IF(AND(ISNUMBER($BW30),ISNUMBER($BX30)),($BW30+$BX30)/2,"") -> 2010.5 | M30: =IF($L30<>"",$L30,"") -> 2010.5 | N30: =IF(AND(ISNUMBER($BW30),ISNUMBER($BX30)),MIN(1,MAX(0,($BX30-2016+1)/($BX30-$BW30+1))),"") -> 0.1875 | O30: =IF(AND(ISNUMBER($BW30),ISNUMBER($BX30)),MIN(1,MAX(0,($BX30-2017+1)/($BX30-$BW30+1))),"") -> 0.125 | P30: =IF(AND(ISNUMBER($BW30),ISNUMBER($BX30)),MIN(1,MAX(0,($BX30-2018+1)/($BX30-$BW30+1))),"") -> 0.0625 | Q30: =IF(AND(ISNUMBER($BW30),ISNUMBER($BX30)),MIN(1,MAX(0,($BX30-2019+1)/($BX30-$BW30+1))),"") -> 0 | R30: =IF(AND(ISNUMBER($BW30),ISNUMBER($BX30)),MIN(1,MAX(0,($BX30-2016+1)/($BX30-$BW30+1))),"") -> 0.1875 | S30: =IF($L30<>"",IF($L30>=2015.5,1,0),"") -> 0 | T30: =IF($L30<>"",IF($L30>=2016,1,0),"") -> 0 | U30: =IF(ISNUMBER($BX30),IF($BX30>=2016,1,0),"") -> 1 | V30: =IF(ISNUMBER($BW30),IF($BW30>=2016,1,0),"") -> 0 | W30: =IF(AND(ISNUMBER($BW30),ISNUMBER($BX30)),IF($BW30>=2016,"post-only",IF($BX30<2016,"pre-only","mixed")),"") -> mixed | X30: =IF(AND(ISNUMBER($BW30),ISNUMBER($BX30)),MIN(1,MAX(0,($BX30-2017+1)/($BX30-$BW30+1))),"") -> 0.125 | Y30: =IF(AND(ISNUMBER($BW30),ISNUMBER($BX30)),MIN(1,MAX(0,($BX30-2018+1)/($BX30-$BW30+1))),"") -> 0.0625 | Z30: =IF(AND(ISNUMBER($BW30),ISNUMBER($BX30)),MIN(1,MAX(0,($BX30-2019+1)/($BX30-$BW30+1))),"") -> 0 | AA30: =IF(ISNUMBER($BX30),IF($BX30>=2017,1,0),"") -> 1 | AB30: =IF(ISNUMBER($BX30),IF($BX30>=2018,1,0),"") -> 1 | AC30: =IF(ISNUMBER($BX30),IF($BX30>=2019,1,0),"") -> 0 | AD30: =IF($L30<>"",IF($L30>2013,1,0),"") -> 0 | AE30: =IF($L30<>"",1+IF($L30>2011,1,0)+IF($L30>2014,1,0),"") -> 1 | AF30: loan (interest rate) | AG30: performance | AH30: non-sensitive | AI30: 99_NCE | AJ30: 99_NCE | AK30: =IF(AND($CF30<>"",IFERROR(INDEX(subsample_country_map!$B:$B,MATCH($CF30,subsample_country_map!$A:$A,0)),"")<>""),INDEX(subsample_country_map!$B:$B,MATCH($CF30,subsample_country_map!$A:$A,0)),INDEX(lookup!$AA:$AA,MATCH($A30,lookup!$A:$A,0))) -> 3_AsiaPac | AL30: =IF(AND($CF30<>"",IFERROR(INDEX(subsample_country_map!$C:$C,MATCH($CF30,subsample_country_map!$A:$A,0)),"")<>""),INDEX(subsample_country_map!$C:$C,MATCH($CF30,subsample_country_map!$A:$A,0)),INDEX(lookup!$AB:$AB,MATCH($A30,lookup!$A:$A,0))) -> 1_developed | AM30: =IF(AND($CF30<>"",IFERROR(INDEX(subsample_country_map!$D:$D,MATCH($CF30,subsample_country_map!$A:$A,0)),"")<>""),INDEX(subsample_country_map!$D:$D,MATCH($CF30,subsample_country_map!$A:$A,0)),INDEX(lookup!$AC:$AC,MATCH($A30,lookup!$A:$A,0))) -> 1_western | AN30: =IF(AND($CF30<>"",IFERROR(INDEX(subsample_country_map!$E:$E,MATCH($CF30,subsample_country_map!$A:$A,0)),"")<>""),INDEX(subsample_country_map!$E:$E,MATCH($CF30,subsample_country_map!$A:$A,0)),INDEX(lookup!$AD:$AD,MATCH($A30,lookup!$A:$A,0))) -> 1_common law | AO30: =INDEX(lookup!$Y:$Y,MATCH($A30,lookup!$A:$A,0)) -> 0_published | AP30: =INDEX(lookup!$Z:$Z,MATCH($A30,lookup!$A:$A,0)) -> 1_VHB high | AQ30: =INDEX(lookup!$W:$W,MATCH($A30,lookup!$A:$A,0)) -> 1_fin/acc/econ | AS30: staging | AT30: author-inverted-to-good | AU30: cost | AV30: -0.125 | AX30: 2.20 | BA30: 360 | BB30: 0 | BC30: OLS | BD30: not stated | BE30: region | BF30: Australia | BI30: Table 8 | BJ30: Panel B col 1 | BK30: 12 | BL30: CCP1 -0.125** (2.20) | BM30: CCP1 | BN30: COD | BO30: update | BP30: Al-Fakir Al Rabab'a et al (2023) | BQ30: computed | BT30: 0 | BU30: staging_Al-Fakir_Al_Rababa_et_al_2023.csv | BW30: 2003 | BX30: 2018 | BY30: multi: 14 Asia-Pacific countries (Australia, China, Hong Kong, India, Indonesia, Japan, Malaysia, New Zealand, Philippines, Singapore, South Korea, Sri Lanka, Taiwan, Thailand) | BZ30: 2010.5 | CA30: 0.1875 | CB30: 0 | CC30: 1 | CD30: 0.11569193 | CE30: 1 | CF30: Australia
A31: Al-Fakir Al Rabab'a et al (2023) | B31: 1336 | C31: 0.25243851 | D31: 360 | E31: =IF(ISNUMBER($BA31),$BA31,IF(AND(ISNUMBER($D31),ISNUMBER($BW31),ISNUMBER($BX31)),$D31*($BX31-$BW31+1),"")) -> 360 | H31: partial | I31: T-Statistic available | J31: =IF($BW31<>"",$BW31,"") -> 2003 | K31: =IF($BX31<>"",$BX31,"") -> 2018 | L31: =IF(AND(ISNUMBER($BW31),ISNUMBER($BX31)),($BW31+$BX31)/2,"") -> 2010.5 | M31: =IF($L31<>"",$L31,"") -> 2010.5 | N31: =IF(AND(ISNUMBER($BW31),ISNUMBER($BX31)),MIN(1,MAX(0,($BX31-2016+1)/($BX31-$BW31+1))),"") -> 0.1875 | O31: =IF(AND(ISNUMBER($BW31),ISNUMBER($BX31)),MIN(1,MAX(0,($BX31-2017+1)/($BX31-$BW31+1))),"") -> 0.125 | P31: =IF(AND(ISNUMBER($BW31),ISNUMBER($BX31)),MIN(1,MAX(0,($BX31-2018+1)/($BX31-$BW31+1))),"") -> 0.0625 | Q31: =IF(AND(ISNUMBER($BW31),ISNUMBER($BX31)),MIN(1,MAX(0,($BX31-2019+1)/($BX31-$BW31+1))),"") -> 0 | R31: =IF(AND(ISNUMBER($BW31),ISNUMBER($BX31)),MIN(1,MAX(0,($BX31-2016+1)/($BX31-$BW31+1))),"") -> 0.1875 | S31: =IF($L31<>"",IF($L31>=2015.5,1,0),"") -> 0 | T31: =IF($L31<>"",IF($L31>=2016,1,0),"") -> 0 | U31: =IF(ISNUMBER($BX31),IF($BX31>=2016,1,0),"") -> 1 | V31: =IF(ISNUMBER($BW31),IF($BW31>=2016,1,0),"") -> 0 | W31: =IF(AND(ISNUMBER($BW31),ISNUMBER($BX31)),IF($BW31>=2016,"post-only",IF($BX31<2016,"pre-only","mixed")),"") -> mixed | X31: =IF(AND(ISNUMBER($BW31),ISNUMBER($BX31)),MIN(1,MAX(0,($BX31-2017+1)/($BX31-$BW31+1))),"") -> 0.125 | Y31: =IF(AND(ISNUMBER($BW31),ISNUMBER($BX31)),MIN(1,MAX(0,($BX31-2018+1)/($BX31-$BW31+1))),"") -> 0.0625 | Z31: =IF(AND(ISNUMBER($BW31),ISNUMBER($BX31)),MIN(1,MAX(0,($BX31-2019+1)/($BX31-$BW31+1))),"") -> 0 | AA31: =IF(ISNUMBER($BX31),IF($BX31>=2017,1,0),"") -> 1 | AB31: =IF(ISNUMBER($BX31),IF($BX31>=2018,1,0),"") -> 1 | AC31: =IF(ISNUMBER($BX31),IF($BX31>=2019,1,0),"") -> 0 | AD31: =IF($L31<>"",IF($L31>2013,1,0),"") -> 0 | AE31: =IF($L31<>"",1+IF($L31>2011,1,0)+IF($L31>2014,1,0),"") -> 1 | AF31: loan (interest rate) | AG31: performance | AH31: non-sensitive | AI31: 99_NCE | AJ31: 99_NCE | AK31: =IF(AND($CF31<>"",IFERROR(INDEX(subsample_country_map!$B:$B,MATCH($CF31,subsample_country_map!$A:$A,0)),"")<>""),INDEX(subsample_country_map!$B:$B,MATCH($CF31,subsample_country_map!$A:$A,0)),INDEX(lookup!$AA:$AA,MATCH($A31,lookup!$A:$A,0))) -> 3_AsiaPac | AL31: =IF(AND($CF31<>"",IFERROR(INDEX(subsample_country_map!$C:$C,MATCH($CF31,subsample_country_map!$A:$A,0)),"")<>""),INDEX(subsample_country_map!$C:$C,MATCH($CF31,subsample_country_map!$A:$A,0)),INDEX(lookup!$AB:$AB,MATCH($A31,lookup!$A:$A,0))) -> 1_developed | AM31: =IF(AND($CF31<>"",IFERROR(INDEX(subsample_country_map!$D:$D,MATCH($CF31,subsample_country_map!$A:$A,0)),"")<>""),INDEX(subsample_country_map!$D:$D,MATCH($CF31,subsample_country_map!$A:$A,0)),INDEX(lookup!$AC:$AC,MATCH($A31,lookup!$A:$A,0))) -> 1_western | AN31: =IF(AND($CF31<>"",IFERROR(INDEX(subsample_country_map!$E:$E,MATCH($CF31,subsample_country_map!$A:$A,0)),"")<>""),INDEX(subsample_country_map!$E:$E,MATCH($CF31,subsample_country_map!$A:$A,0)),INDEX(lookup!$AD:$AD,MATCH($A31,lookup!$A:$A,0))) -> 1_common law | AO31: =INDEX(lookup!$Y:$Y,MATCH($A31,lookup!$A:$A,0)) -> 0_published | AP31: =INDEX(lookup!$Z:$Z,MATCH($A31,lookup!$A:$A,0)) -> 1_VHB high | AQ31: =INDEX(lookup!$W:$W,MATCH($A31,lookup!$A:$A,0)) -> 1_fin/acc/econ | AS31: staging | AT31: author-inverted-to-good | AU31: cost | AV31: -0.350 | AX31: 4.95 | BA31: 360 | BB31: 0 | BC31: OLS | BD31: not stated | BE31: region | BF31: Australia | BI31: Table 8 | BJ31: Panel B col 2 | BK31: 12 | BL31: CCP2 -0.350*** (4.95) | BM31: CCP2 | BN31: COD | BO31: update | BP31: Al-Fakir Al Rabab'a et al (2023) | BQ31: computed | BT31: 0 | BU31: staging_Al-Fakir_Al_Rababa_et_al_2023.csv | BW31: 2003 | BX31: 2018 | BY31: multi: 14 Asia-Pacific countries (Australia, China, Hong Kong, India, Indonesia, Japan, Malaysia, New Zealand, Philippines, Singapore, South Korea, Sri Lanka, Taiwan, Thailand) | BZ31: 2010.5 | CA31: 0.1875 | CB31: 0 | CC31: 1 | CD31: 0.25801559 | CE31: 1 | CF31: Australia
A32: Al-Fakir Al Rabab'a et al (2023) | B32: 1337 | C32: -0.061547508 | D32: 360 | E32: =IF(ISNUMBER($BA32),$BA32,IF(AND(ISNUMBER($D32),ISNUMBER($BW32),ISNUMBER($BX32)),$D32*($BX32-$BW32+1),"")) -> 360 | H32: partial | I32: T-Statistic available | J32: =IF($BW32<>"",$BW32,"") -> 2003 | K32: =IF($BX32<>"",$BX32,"") -> 2018 | L32: =IF(AND(ISNUMBER($BW32),ISNUMBER($BX32)),($BW32+$BX32)/2,"") -> 2010.5 | M32: =IF($L32<>"",$L32,"") -> 2010.5 | N32: =IF(AND(ISNUMBER($BW32),ISNUMBER($BX32)),MIN(1,MAX(0,($BX32-2016+1)/($BX32-$BW32+1))),"") -> 0.1875 | O32: =IF(AND(ISNUMBER($BW32),ISNUMBER($BX32)),MIN(1,MAX(0,($BX32-2017+1)/($BX32-$BW32+1))),"") -> 0.125 | P32: =IF(AND(ISNUMBER($BW32),ISNUMBER($BX32)),MIN(1,MAX(0,($BX32-2018+1)/($BX32-$BW32+1))),"") -> 0.0625 | Q32: =IF(AND(ISNUMBER($BW32),ISNUMBER($BX32)),MIN(1,MAX(0,($BX32-2019+1)/($BX32-$BW32+1))),"") -> 0 | R32: =IF(AND(ISNUMBER($BW32),ISNUMBER($BX32)),MIN(1,MAX(0,($BX32-2016+1)/($BX32-$BW32+1))),"") -> 0.1875 | S32: =IF($L32<>"",IF($L32>=2015.5,1,0),"") -> 0 | T32: =IF($L32<>"",IF($L32>=2016,1,0),"") -> 0 | U32: =IF(ISNUMBER($BX32),IF($BX32>=2016,1,0),"") -> 1 | V32: =IF(ISNUMBER($BW32),IF($BW32>=2016,1,0),"") -> 0 | W32: =IF(AND(ISNUMBER($BW32),ISNUMBER($BX32)),IF($BW32>=2016,"post-only",IF($BX32<2016,"pre-only","mixed")),"") -> mixed | X32: =IF(AND(ISNUMBER($BW32),ISNUMBER($BX32)),MIN(1,MAX(0,($BX32-2017+1)/($BX32-$BW32+1))),"") -> 0.125 | Y32: =IF(AND(ISNUMBER($BW32),ISNUMBER($BX32)),MIN(1,MAX(0,($BX32-2018+1)/($BX32-$BW32+1))),"") -> 0.0625 | Z32: =IF(AND(ISNUMBER($BW32),ISNUMBER($BX32)),MIN(1,MAX(0,($BX32-2019+1)/($BX32-$BW32+1))),"") -> 0 | AA32: =IF(ISNUMBER($BX32),IF($BX32>=2017,1,0),"") -> 1 | AB32: =IF(ISNUMBER($BX32),IF($BX32>=2018,1,0),"") -> 1 | AC32: =IF(ISNUMBER($BX32),IF($BX32>=2019,1,0),"") -> 0 | AD32: =IF($L32<>"",IF($L32>2013,1,0),"") -> 0 | AE32: =IF($L32<>"",1+IF($L32>2011,1,0)+IF($L32>2014,1,0),"") -> 1 | AF32: loan (interest rate) | AG32: performance | AH32: non-sensitive | AI32: 99_NCE | AJ32: 99_NCE | AK32: =IF(AND($CF32<>"",IFERROR(INDEX(subsample_country_map!$B:$B,MATCH($CF32,subsample_country_map!$A:$A,0)),"")<>""),INDEX(subsample_country_map!$B:$B,MATCH($CF32,subsample_country_map!$A:$A,0)),INDEX(lookup!$AA:$AA,MATCH($A32,lookup!$A:$A,0))) -> 3_AsiaPac | AL32: =IF(AND($CF32<>"",IFERROR(INDEX(subsample_country_map!$C:$C,MATCH($CF32,subsample_country_map!$A:$A,0)),"")<>""),INDEX(subsample_country_map!$C:$C,MATCH($CF32,subsample_country_map!$A:$A,0)),INDEX(lookup!$AB:$AB,MATCH($A32,lookup!$A:$A,0))) -> 1_developed | AM32: =IF(AND($CF32<>"",IFERROR(INDEX(subsample_country_map!$D:$D,MATCH($CF32,subsample_country_map!$A:$A,0)),"")<>""),INDEX(subsample_country_map!$D:$D,MATCH($CF32,subsample_country_map!$A:$A,0)),INDEX(lookup!$AC:$AC,MATCH($A32,lookup!$A:$A,0))) -> 1_western | AN32: =IF(AND($CF32<>"",IFERROR(INDEX(subsample_country_map!$E:$E,MATCH($CF32,subsample_country_map!$A:$A,0)),"")<>""),INDEX(subsample_country_map!$E:$E,MATCH($CF32,subsample_country_map!$A:$A,0)),INDEX(lookup!$AD:$AD,MATCH($A32,lookup!$A:$A,0))) -> 1_common law | AO32: =INDEX(lookup!$Y:$Y,MATCH($A32,lookup!$A:$A,0)) -> 0_published | AP32: =INDEX(lookup!$Z:$Z,MATCH($A32,lookup!$A:$A,0)) -> 1_VHB high | AQ32: =INDEX(lookup!$W:$W,MATCH($A32,lookup!$A:$A,0)) -> 1_fin/acc/econ | AS32: staging | AT32: good-CER | AU32: cost | AV32: -0.025 | AX32: -1.17 | BA32: 360 | BB32: 0 | BC32: OLS | BD32: not stated | BE32: region | BF32: Australia | BI32: Table 8 | BJ32: Panel B col 3 | BK32: 12 | BL32: CCP3 -0.025 (-1.17) | BM32: CCP3 | BN32: COD | BO32: update | BP32: Al-Fakir Al Rabab'a et al (2023) | BQ32: computed | BT32: 0 | BU32: staging_Al-Fakir_Al_Rababa_et_al_2023.csv | BW32: 2003 | BX32: 2018 | BY32: multi: 14 Asia-Pacific countries (Australia, China, Hong Kong, India, Indonesia, Japan, Malaysia, New Zealand, Philippines, Singapore, South Korea, Sri Lanka, Taiwan, Thailand) | BZ32: 2010.5 | CA32: 0.1875 | CB32: 0 | CC32: 1 | CD32: -0.061625401 | CE32: 1 | CF32: Australia
A33: Al-Fakir Al Rabab'a et al (2023) | B33: 1338 | C33: 0.012121174 | D33: 360 | E33: =IF(ISNUMBER($BA33),$BA33,IF(AND(ISNUMBER($D33),ISNUMBER($BW33),ISNUMBER($BX33)),$D33*($BX33-$BW33+1),"")) -> 360 | H33: partial | I33: T-Statistic available | J33: =IF($BW33<>"",$BW33,"") -> 2003 | K33: =IF($BX33<>"",$BX33,"") -> 2018 | L33: =IF(AND(ISNUMBER($BW33),ISNUMBER($BX33)),($BW33+$BX33)/2,"") -> 2010.5 | M33: =IF($L33<>"",$L33,"") -> 2010.5 | N33: =IF(AND(ISNUMBER($BW33),ISNUMBER($BX33)),MIN(1,MAX(0,($BX33-2016+1)/($BX33-$BW33+1))),"") -> 0.1875 | O33: =IF(AND(ISNUMBER($BW33),ISNUMBER($BX33)),MIN(1,MAX(0,($BX33-2017+1)/($BX33-$BW33+1))),"") -> 0.125 | P33: =IF(AND(ISNUMBER($BW33),ISNUMBER($BX33)),MIN(1,MAX(0,($BX33-2018+1)/($BX33-$BW33+1))),"") -> 0.0625 | Q33: =IF(AND(ISNUMBER($BW33),ISNUMBER($BX33)),MIN(1,MAX(0,($BX33-2019+1)/($BX33-$BW33+1))),"") -> 0 | R33: =IF(AND(ISNUMBER($BW33),ISNUMBER($BX33)),MIN(1,MAX(0,($BX33-2016+1)/($BX33-$BW33+1))),"") -> 0.1875 | S33: =IF($L33<>"",IF($L33>=2015.5,1,0),"") -> 0 | T33: =IF($L33<>"",IF($L33>=2016,1,0),"") -> 0 | U33: =IF(ISNUMBER($BX33),IF($BX33>=2016,1,0),"") -> 1 | V33: =IF(ISNUMBER($BW33),IF($BW33>=2016,1,0),"") -> 0 | W33: =IF(AND(ISNUMBER($BW33),ISNUMBER($BX33)),IF($BW33>=2016,"post-only",IF($BX33<2016,"pre-only","mixed")),"") -> mixed | X33: =IF(AND(ISNUMBER($BW33),ISNUMBER($BX33)),MIN(1,MAX(0,($BX33-2017+1)/($BX33-$BW33+1))),"") -> 0.125 | Y33: =IF(AND(ISNUMBER($BW33),ISNUMBER($BX33)),MIN(1,MAX(0,($BX33-2018+1)/($BX33-$BW33+1))),"") -> 0.0625 | Z33: =IF(AND(ISNUMBER($BW33),ISNUMBER($BX33)),MIN(1,MAX(0,($BX33-2019+1)/($BX33-$BW33+1))),"") -> 0 | AA33: =IF(ISNUMBER($BX33),IF($BX33>=2017,1,0),"") -> 1 | AB33: =IF(ISNUMBER($BX33),IF($BX33>=2018,1,0),"") -> 1 | AC33: =IF(ISNUMBER($BX33),IF($BX33>=2019,1,0),"") -> 0 | AD33: =IF($L33<>"",IF($L33>2013,1,0),"") -> 0 | AE33: =IF($L33<>"",1+IF($L33>2011,1,0)+IF($L33>2014,1,0),"") -> 1 | AF33: loan (interest rate) | AG33: performance | AH33: non-sensitive | AI33: 99_NCE | AJ33: 99_NCE | AK33: =IF(AND($CF33<>"",IFERROR(INDEX(subsample_country_map!$B:$B,MATCH($CF33,subsample_country_map!$A:$A,0)),"")<>""),INDEX(subsample_country_map!$B:$B,MATCH($CF33,subsample_country_map!$A:$A,0)),INDEX(lookup!$AA:$AA,MATCH($A33,lookup!$A:$A,0))) -> 3_AsiaPac | AL33: =IF(AND($CF33<>"",IFERROR(INDEX(subsample_country_map!$C:$C,MATCH($CF33,subsample_country_map!$A:$A,0)),"")<>""),INDEX(subsample_country_map!$C:$C,MATCH($CF33,subsample_country_map!$A:$A,0)),INDEX(lookup!$AB:$AB,MATCH($A33,lookup!$A:$A,0))) -> 1_developed | AM33: =IF(AND($CF33<>"",IFERROR(INDEX(subsample_country_map!$D:$D,MATCH($CF33,subsample_country_map!$A:$A,0)),"")<>""),INDEX(subsample_country_map!$D:$D,MATCH($CF33,subsample_country_map!$A:$A,0)),INDEX(lookup!$AC:$AC,MATCH($A33,lookup!$A:$A,0))) -> 1_western | AN33: =IF(AND($CF33<>"",IFERROR(INDEX(subsample_country_map!$E:$E,MATCH($CF33,subsample_country_map!$A:$A,0)),"")<>""),INDEX(subsample_country_map!$E:$E,MATCH($CF33,subsample_country_map!$A:$A,0)),INDEX(lookup!$AD:$AD,MATCH($A33,lookup!$A:$A,0))) -> 1_common law | AO33: =INDEX(lookup!$Y:$Y,MATCH($A33,lookup!$A:$A,0)) -> 0_published | AP33: =INDEX(lookup!$Z:$Z,MATCH($A33,lookup!$A:$A,0)) -> 1_VHB high | AQ33: =INDEX(lookup!$W:$W,MATCH($A33,lookup!$A:$A,0)) -> 1_fin/acc/econ | AS33: staging | AT33: good-CER | AU33: cost | AV33: 0.007 | AX33: 0.23 | BA33: 360 | BB33: 0 | BC33: OLS | BD33: not stated | BE33: region | BF33: Australia | BI33: Table 8 | BJ33: Panel B col 4 | BK33: 12 | BL33: CCP4 0.007 (0.23) | BM33: CCP4 | BN33: COD | BO33: update | BP33: Al-Fakir Al Rabab'a et al (2023) | BQ33: computed | BT33: 0 | BU33: staging_Al-Fakir_Al_Rababa_et_al_2023.csv | BW33: 2003 | BX33: 2018 | BY33: multi: 14 Asia-Pacific countries (Australia, China, Hong Kong, India, Indonesia, Japan, Malaysia, New Zealand, Philippines, Singapore, South Korea, Sri Lanka, Taiwan, Thailand) | BZ33: 2010.5 | CA33: 0.1875 | CB33: 0 | CC33: 1 | CD33: 0.012121768 | CE33: 1 | CF33: Australia
A34: Al-Fakir Al Rabab'a et al (2023) | B34: 1339 | C34: -0.1351568 | D34: 344 | E34: =IF(ISNUMBER($BA34),$BA34,IF(AND(ISNUMBER($D34),ISNUMBER($BW34),ISNUMBER($BX34)),$D34*($BX34-$BW34+1),"")) -> 344 | H34: partial | I34: T-Statistic available | J34: =IF($BW34<>"",$BW34,"") -> 2003 | K34: =IF($BX34<>"",$BX34,"") -> 2018 | L34: =IF(AND(ISNUMBER($BW34),ISNUMBER($BX34)),($BW34+$BX34)/2,"") -> 2010.5 | M34: =IF($L34<>"",$L34,"") -> 2010.5 | N34: =IF(AND(ISNUMBER($BW34),ISNUMBER($BX34)),MIN(1,MAX(0,($BX34-2016+1)/($BX34-$BW34+1))),"") -> 0.1875 | O34: =IF(AND(ISNUMBER($BW34),ISNUMBER($BX34)),MIN(1,MAX(0,($BX34-2017+1)/($BX34-$BW34+1))),"") -> 0.125 | P34: =IF(AND(ISNUMBER($BW34),ISNUMBER($BX34)),MIN(1,MAX(0,($BX34-2018+1)/($BX34-$BW34+1))),"") -> 0.0625 | Q34: =IF(AND(ISNUMBER($BW34),ISNUMBER($BX34)),MIN(1,MAX(0,($BX34-2019+1)/($BX34-$BW34+1))),"") -> 0 | R34: =IF(AND(ISNUMBER($BW34),ISNUMBER($BX34)),MIN(1,MAX(0,($BX34-2016+1)/($BX34-$BW34+1))),"") -> 0.1875 | S34: =IF($L34<>"",IF($L34>=2015.5,1,0),"") -> 0 | T34: =IF($L34<>"",IF($L34>=2016,1,0),"") -> 0 | U34: =IF(ISNUMBER($BX34),IF($BX34>=2016,1,0),"") -> 1 | V34: =IF(ISNUMBER($BW34),IF($BW34>=2016,1,0),"") -> 0 | W34: =IF(AND(ISNUMBER($BW34),ISNUMBER($BX34)),IF($BW34>=2016,"post-only",IF($BX34<2016,"pre-only","mixed")),"") -> mixed | X34: =IF(AND(ISNUMBER($BW34),ISNUMBER($BX34)),MIN(1,MAX(0,($BX34-2017+1)/($BX34-$BW34+1))),"") -> 0.125 | Y34: =IF(AND(ISNUMBER($BW34),ISNUMBER($BX34)),MIN(1,MAX(0,($BX34-2018+1)/($BX34-$BW34+1))),"") -> 0.0625 | Z34: =IF(AND(ISNUMBER($BW34),ISNUMBER($BX34)),MIN(1,MAX(0,($BX34-2019+1)/($BX34-$BW34+1))),"") -> 0 | AA34: =IF(ISNUMBER($BX34),IF($BX34>=2017,1,0),"") -> 1 | AB34: =IF(ISNUMBER($BX34),IF($BX34>=2018,1,0),"") -> 1 | AC34: =IF(ISNUMBER($BX34),IF($BX34>=2019,1,0),"") -> 0 | AD34: =IF($L34<>"",IF($L34>2013,1,0),"") -> 0 | AE34: =IF($L34<>"",1+IF($L34>2011,1,0)+IF($L34>2014,1,0),"") -> 1 | AF34: loan (interest rate) | AG34: performance | AH34: non-sensitive | AI34: 99_NCE | AJ34: 99_NCE | AK34: =IF(AND($CF34<>"",IFERROR(INDEX(subsample_country_map!$B:$B,MATCH($CF34,subsample_country_map!$A:$A,0)),"")<>""),INDEX(subsample_country_map!$B:$B,MATCH($CF34,subsample_country_map!$A:$A,0)),INDEX(lookup!$AA:$AA,MATCH($A34,lookup!$A:$A,0))) -> 3_AsiaPac | AL34: =IF(AND($CF34<>"",IFERROR(INDEX(subsample_country_map!$C:$C,MATCH($CF34,subsample_country_map!$A:$A,0)),"")<>""),INDEX(subsample_country_map!$C:$C,MATCH($CF34,subsample_country_map!$A:$A,0)),INDEX(lookup!$AB:$AB,MATCH($A34,lookup!$A:$A,0))) -> 1_developed | AM34: =IF(AND($CF34<>"",IFERROR(INDEX(subsample_country_map!$D:$D,MATCH($CF34,subsample_country_map!$A:$A,0)),"")<>""),INDEX(subsample_country_map!$D:$D,MATCH($CF34,subsample_country_map!$A:$A,0)),INDEX(lookup!$AC:$AC,MATCH($A34,lookup!$A:$A,0))) -> 2_non_western | AN34: =IF(AND($CF34<>"",IFERROR(INDEX(subsample_country_map!$E:$E,MATCH($CF34,subsample_country_map!$A:$A,0)),"")<>""),INDEX(subsample_country_map!$E:$E,MATCH($CF34,subsample_country_map!$A:$A,0)),INDEX(lookup!$AD:$AD,MATCH($A34,lookup!$A:$A,0))) -> 2_civil law | AO34: =INDEX(lookup!$Y:$Y,MATCH($A34,lookup!$A:$A,0)) -> 0_published | AP34: =INDEX(lookup!$Z:$Z,MATCH($A34,lookup!$A:$A,0)) -> 1_VHB high | AQ34: =INDEX(lookup!$W:$W,MATCH($A34,lookup!$A:$A,0)) -> 1_fin/acc/econ | AS34: staging | AT34: author-inverted-to-good | AU34: cost | AV34: -0.062 | AX34: -2.53 | BA34: 344 | BB34: 0 | BC34: OLS | BD34: not stated | BE34: region | BF34: Taiwan | BI34: Table 8 | BJ34: Panel C col 1 | BK34: 12 | BL34: CCP1 -0.062** (-2.53) | BM34: CCP1 | BN34: COD | BO34: update | BP34: Al-Fakir Al Rabab'a et al (2023) | BQ34: computed | BT34: 0 | BU34: staging_Al-Fakir_Al_Rababa_et_al_2023.csv | BW34: 2003 | BX34: 2018 | BY34: multi: 14 Asia-Pacific countries (Australia, China, Hong Kong, India, Indonesia, Japan, Malaysia, New Zealand, Philippines, Singapore, South Korea, Sri Lanka, Taiwan, Thailand) | BZ34: 2010.5 | CA34: 0.1875 | CB34: 0 | CC34: 1 | CD34: -0.13598893 | CE34: 1 | CF34: Taiwan
A35: Al-Fakir Al Rabab'a et al (2023) | B35: 1340 | C35: 0.072060134 | D35: 344 | E35: =IF(ISNUMBER($BA35),$BA35,IF(AND(ISNUMBER($D35),ISNUMBER($BW35),ISNUMBER($BX35)),$D35*($BX35-$BW35+1),"")) -> 344 | H35: partial | I35: T-Statistic available | J35: =IF($BW35<>"",$BW35,"") -> 2003 | K35: =IF($BX35<>"",$BX35,"") -> 2018 | L35: =IF(AND(ISNUMBER($BW35),ISNUMBER($BX35)),($BW35+$BX35)/2,"") -> 2010.5 | M35: =IF($L35<>"",$L35,"") -> 2010.5 | N35: =IF(AND(ISNUMBER($BW35),ISNUMBER($BX35)),MIN(1,MAX(0,($BX35-2016+1)/($BX35-$BW35+1))),"") -> 0.1875 | O35: =IF(AND(ISNUMBER($BW35),ISNUMBER($BX35)),MIN(1,MAX(0,($BX35-2017+1)/($BX35-$BW35+1))),"") -> 0.125 | P35: =IF(AND(ISNUMBER($BW35),ISNUMBER($BX35)),MIN(1,MAX(0,($BX35-2018+1)/($BX35-$BW35+1))),"") -> 0.0625 | Q35: =IF(AND(ISNUMBER($BW35),ISNUMBER($BX35)),MIN(1,MAX(0,($BX35-2019+1)/($BX35-$BW35+1))),"") -> 0 | R35: =IF(AND(ISNUMBER($BW35),ISNUMBER($BX35)),MIN(1,MAX(0,($BX35-2016+1)/($BX35-$BW35+1))),"") -> 0.1875 | S35: =IF($L35<>"",IF($L35>=2015.5,1,0),"") -> 0 | T35: =IF($L35<>"",IF($L35>=2016,1,0),"") -> 0 | U35: =IF(ISNUMBER($BX35),IF($BX35>=2016,1,0),"") -> 1 | V35: =IF(ISNUMBER($BW35),IF($BW35>=2016,1,0),"") -> 0 | W35: =IF(AND(ISNUMBER($BW35),ISNUMBER($BX35)),IF($BW35>=2016,"post-only",IF($BX35<2016,"pre-only","mixed")),"") -> mixed | X35: =IF(AND(ISNUMBER($BW35),ISNUMBER($BX35)),MIN(1,MAX(0,($BX35-2017+1)/($BX35-$BW35+1))),"") -> 0.125 | Y35: =IF(AND(ISNUMBER($BW35),ISNUMBER($BX35)),MIN(1,MAX(0,($BX35-2018+1)/($BX35-$BW35+1))),"") -> 0.0625 | Z35: =IF(AND(ISNUMBER($BW35),ISNUMBER($BX35)),MIN(1,MAX(0,($BX35-2019+1)/($BX35-$BW35+1))),"") -> 0 | AA35: =IF(ISNUMBER($BX35),IF($BX35>=2017,1,0),"") -> 1 | AB35: =IF(ISNUMBER($BX35),IF($BX35>=2018,1,0),"") -> 1 | AC35: =IF(ISNUMBER($BX35),IF($BX35>=2019,1,0),"") -> 0 | AD35: =IF($L35<>"",IF($L35>2013,1,0),"") -> 0 | AE35: =IF($L35<>"",1+IF($L35>2011,1,0)+IF($L35>2014,1,0),"") -> 1 | AF35: loan (interest rate) | AG35: performance | AH35: non-sensitive | AI35: 99_NCE | AJ35: 99_NCE | AK35: =IF(AND($CF35<>"",IFERROR(INDEX(subsample_country_map!$B:$B,MATCH($CF35,subsample_country_map!$A:$A,0)),"")<>""),INDEX(subsample_country_map!$B:$B,MATCH($CF35,subsample_country_map!$A:$A,0)),INDEX(lookup!$AA:$AA,MATCH($A35,lookup!$A:$A,0))) -> 3_AsiaPac | AL35: =IF(AND($CF35<>"",IFERROR(INDEX(subsample_country_map!$C:$C,MATCH($CF35,subsample_country_map!$A:$A,0)),"")<>""),INDEX(subsample_country_map!$C:$C,MATCH($CF35,subsample_country_map!$A:$A,0)),INDEX(lookup!$AB:$AB,MATCH($A35,lookup!$A:$A,0))) -> 1_developed | AM35: =IF(AND($CF35<>"",IFERROR(INDEX(subsample_country_map!$D:$D,MATCH($CF35,subsample_country_map!$A:$A,0)),"")<>""),INDEX(subsample_country_map!$D:$D,MATCH($CF35,subsample_country_map!$A:$A,0)),INDEX(lookup!$AC:$AC,MATCH($A35,lookup!$A:$A,0))) -> 2_non_western | AN35: =IF(AND($CF35<>"",IFERROR(INDEX(subsample_country_map!$E:$E,MATCH($CF35,subsample_country_map!$A:$A,0)),"")<>""),INDEX(subsample_country_map!$E:$E,MATCH($CF35,subsample_country_map!$A:$A,0)),INDEX(lookup!$AD:$AD,MATCH($A35,lookup!$A:$A,0))) -> 2_civil law | AO35: =INDEX(lookup!$Y:$Y,MATCH($A35,lookup!$A:$A,0)) -> 0_published | AP35: =INDEX(lookup!$Z:$Z,MATCH($A35,lookup!$A:$A,0)) -> 1_VHB high | AQ35: =INDEX(lookup!$W:$W,MATCH($A35,lookup!$A:$A,0)) -> 1_fin/acc/econ | AS35: staging | AT35: author-inverted-to-good | AU35: cost | AV35: 0.037 | AX35: 1.34 | BA35: 344 | BB35: 0 | BC35: OLS | BD35: not stated | BE35: region | BF35: Taiwan | BI35: Table 8 | BJ35: Panel C col 2 | BK35: 12 | BL35: CCP2 0.037 (1.34) | BM35: CCP2 | BN35: COD | BO35: update | BP35: Al-Fakir Al Rabab'a et al (2023) | BQ35: computed | BT35: 0 | BU35: staging_Al-Fakir_Al_Rababa_et_al_2023.csv | BW35: 2003 | BX35: 2018 | BY35: multi: 14 Asia-Pacific countries (Australia, China, Hong Kong, India, Indonesia, Japan, Malaysia, New Zealand, Philippines, Singapore, South Korea, Sri Lanka, Taiwan, Thailand) | BZ35: 2010.5 | CA35: 0.1875 | CB35: 0 | CC35: 1 | CD35: 0.072185252 | CE35: 1 | CF35: Taiwan
A36: Al-Fakir Al Rabab'a et al (2023) | B36: 1341 | C36: 0.10827086 | D36: 344 | E36: =IF(ISNUMBER($BA36),$BA36,IF(AND(ISNUMBER($D36),ISNUMBER($BW36),ISNUMBER($BX36)),$D36*($BX36-$BW36+1),"")) -> 344 | H36: partial | I36: T-Statistic available | J36: =IF($BW36<>"",$BW36,"") -> 2003 | K36: =IF($BX36<>"",$BX36,"") -> 2018 | L36: =IF(AND(ISNUMBER($BW36),ISNUMBER($BX36)),($BW36+$BX36)/2,"") -> 2010.5 | M36: =IF($L36<>"",$L36,"") -> 2010.5 | N36: =IF(AND(ISNUMBER($BW36),ISNUMBER($BX36)),MIN(1,MAX(0,($BX36-2016+1)/($BX36-$BW36+1))),"") -> 0.1875 | O36: =IF(AND(ISNUMBER($BW36),ISNUMBER($BX36)),MIN(1,MAX(0,($BX36-2017+1)/($BX36-$BW36+1))),"") -> 0.125 | P36: =IF(AND(ISNUMBER($BW36),ISNUMBER($BX36)),MIN(1,MAX(0,($BX36-2018+1)/($BX36-$BW36+1))),"") -> 0.0625 | Q36: =IF(AND(ISNUMBER($BW36),ISNUMBER($BX36)),MIN(1,MAX(0,($BX36-2019+1)/($BX36-$BW36+1))),"") -> 0 | R36: =IF(AND(ISNUMBER($BW36),ISNUMBER($BX36)),MIN(1,MAX(0,($BX36-2016+1)/($BX36-$BW36+1))),"") -> 0.1875 | S36: =IF($L36<>"",IF($L36>=2015.5,1,0),"") -> 0 | T36: =IF($L36<>"",IF($L36>=2016,1,0),"") -> 0 | U36: =IF(ISNUMBER($BX36),IF($BX36>=2016,1,0),"") -> 1 | V36: =IF(ISNUMBER($BW36),IF($BW36>=2016,1,0),"") -> 0 | W36: =IF(AND(ISNUMBER($BW36),ISNUMBER($BX36)),IF($BW36>=2016,"post-only",IF($BX36<2016,"pre-only","mixed")),"") -> mixed | X36: =IF(AND(ISNUMBER($BW36),ISNUMBER($BX36)),MIN(1,MAX(0,($BX36-2017+1)/($BX36-$BW36+1))),"") -> 0.125 | Y36: =IF(AND(ISNUMBER($BW36),ISNUMBER($BX36)),MIN(1,MAX(0,($BX36-2018+1)/($BX36-$BW36+1))),"") -> 0.0625 | Z36: =IF(AND(ISNUMBER($BW36),ISNUMBER($BX36)),MIN(1,MAX(0,($BX36-2019+1)/($BX36-$BW36+1))),"") -> 0 | AA36: =IF(ISNUMBER($BX36),IF($BX36>=2017,1,0),"") -> 1 | AB36: =IF(ISNUMBER($BX36),IF($BX36>=2018,1,0),"") -> 1 | AC36: =IF(ISNUMBER($BX36),IF($BX36>=2019,1,0),"") -> 0 | AD36: =IF($L36<>"",IF($L36>2013,1,0),"") -> 0 | AE36: =IF($L36<>"",1+IF($L36>2011,1,0)+IF($L36>2014,1,0),"") -> 1 | AF36: loan (interest rate) | AG36: performance | AH36: non-sensitive | AI36: 99_NCE | AJ36: 99_NCE | AK36: =IF(AND($CF36<>"",IFERROR(INDEX(subsample_country_map!$B:$B,MATCH($CF36,subsample_country_map!$A:$A,0)),"")<>""),INDEX(subsample_country_map!$B:$B,MATCH($CF36,subsample_country_map!$A:$A,0)),INDEX(lookup!$AA:$AA,MATCH($A36,lookup!$A:$A,0))) -> 3_AsiaPac | AL36: =IF(AND($CF36<>"",IFERROR(INDEX(subsample_country_map!$C:$C,MATCH($CF36,subsample_country_map!$A:$A,0)),"")<>""),INDEX(subsample_country_map!$C:$C,MATCH($CF36,subsample_country_map!$A:$A,0)),INDEX(lookup!$AB:$AB,MATCH($A36,lookup!$A:$A,0))) -> 1_developed | AM36: =IF(AND($CF36<>"",IFERROR(INDEX(subsample_country_map!$D:$D,MATCH($CF36,subsample_country_map!$A:$A,0)),"")<>""),INDEX(subsample_country_map!$D:$D,MATCH($CF36,subsample_country_map!$A:$A,0)),INDEX(lookup!$AC:$AC,MATCH($A36,lookup!$A:$A,0))) -> 2_non_western | AN36: =IF(AND($CF36<>"",IFERROR(INDEX(subsample_country_map!$E:$E,MATCH($CF36,subsample_country_map!$A:$A,0)),"")<>""),INDEX(subsample_country_map!$E:$E,MATCH($CF36,subsample_country_map!$A:$A,0)),INDEX(lookup!$AD:$AD,MATCH($A36,lookup!$A:$A,0))) -> 2_civil law | AO36: =INDEX(lookup!$Y:$Y,MATCH($A36,lookup!$A:$A,0)) -> 0_published | AP36: =INDEX(lookup!$Z:$Z,MATCH($A36,lookup!$A:$A,0)) -> 1_VHB high | AQ36: =INDEX(lookup!$W:$W,MATCH($A36,lookup!$A:$A,0)) -> 1_fin/acc/econ | AS36: staging | AT36: good-CER | AU36: cost | AV36: 0.015 | AX36: 2.02 | BA36: 344 | BB36: 0 | BC36: OLS | BD36: not stated | BE36: region | BF36: Taiwan | BI36: Table 8 | BJ36: Panel C col 3 | BK36: 12 | BL36: CCP3 0.015** (2.02) | BM36: CCP3 | BN36: COD | BO36: update | BP36: Al-Fakir Al Rabab'a et al (2023) | BQ36: computed | BT36: 0 | BU36: staging_Al-Fakir_Al_Rababa_et_al_2023.csv | BW36: 2003 | BX36: 2018 | BY36: multi: 14 Asia-Pacific countries (Australia, China, Hong Kong, India, Indonesia, Japan, Malaysia, New Zealand, Philippines, Singapore, South Korea, Sri Lanka, Taiwan, Thailand) | BZ36: 2010.5 | CA36: 0.1875 | CB36: 0 | CC36: 1 | CD36: 0.10869693 | CE36: 1 | CF36: Taiwan
A37: Al-Fakir Al Rabab'a et al (2023) | B37: 1342 | C37: 0.13463229 | D37: 344 | E37: =IF(ISNUMBER($BA37),$BA37,IF(AND(ISNUMBER($D37),ISNUMBER($BW37),ISNUMBER($BX37)),$D37*($BX37-$BW37+1),"")) -> 344 | H37: partial | I37: T-Statistic available | J37: =IF($BW37<>"",$BW37,"") -> 2003 | K37: =IF($BX37<>"",$BX37,"") -> 2018 | L37: =IF(AND(ISNUMBER($BW37),ISNUMBER($BX37)),($BW37+$BX37)/2,"") -> 2010.5 | M37: =IF($L37<>"",$L37,"") -> 2010.5 | N37: =IF(AND(ISNUMBER($BW37),ISNUMBER($BX37)),MIN(1,MAX(0,($BX37-2016+1)/($BX37-$BW37+1))),"") -> 0.1875 | O37: =IF(AND(ISNUMBER($BW37),ISNUMBER($BX37)),MIN(1,MAX(0,($BX37-2017+1)/($BX37-$BW37+1))),"") -> 0.125 | P37: =IF(AND(ISNUMBER($BW37),ISNUMBER($BX37)),MIN(1,MAX(0,($BX37-2018+1)/($BX37-$BW37+1))),"") -> 0.0625 | Q37: =IF(AND(ISNUMBER($BW37),ISNUMBER($BX37)),MIN(1,MAX(0,($BX37-2019+1)/($BX37-$BW37+1))),"") -> 0 | R37: =IF(AND(ISNUMBER($BW37),ISNUMBER($BX37)),MIN(1,MAX(0,($BX37-2016+1)/($BX37-$BW37+1))),"") -> 0.1875 | S37: =IF($L37<>"",IF($L37>=2015.5,1,0),"") -> 0 | T37: =IF($L37<>"",IF($L37>=2016,1,0),"") -> 0 | U37: =IF(ISNUMBER($BX37),IF($BX37>=2016,1,0),"") -> 1 | V37: =IF(ISNUMBER($BW37),IF($BW37>=2016,1,0),"") -> 0 | W37: =IF(AND(ISNUMBER($BW37),ISNUMBER($BX37)),IF($BW37>=2016,"post-only",IF($BX37<2016,"pre-only","mixed")),"") -> mixed | X37: =IF(AND(ISNUMBER($BW37),ISNUMBER($BX37)),MIN(1,MAX(0,($BX37-2017+1)/($BX37-$BW37+1))),"") -> 0.125 | Y37: =IF(AND(ISNUMBER($BW37),ISNUMBER($BX37)),MIN(1,MAX(0,($BX37-2018+1)/($BX37-$BW37+1))),"") -> 0.0625 | Z37: =IF(AND(ISNUMBER($BW37),ISNUMBER($BX37)),MIN(1,MAX(0,($BX37-2019+1)/($BX37-$BW37+1))),"") -> 0 | AA37: =IF(ISNUMBER($BX37),IF($BX37>=2017,1,0),"") -> 1 | AB37: =IF(ISNUMBER($BX37),IF($BX37>=2018,1,0),"") -> 1 | AC37: =IF(ISNUMBER($BX37),IF($BX37>=2019,1,0),"") -> 0 | AD37: =IF($L37<>"",IF($L37>2013,1,0),"") -> 0 | AE37: =IF($L37<>"",1+IF($L37>2011,1,0)+IF($L37>2014,1,0),"") -> 1 | AF37: loan (interest rate) | AG37: performance | AH37: non-sensitive | AI37: 99_NCE | AJ37: 99_NCE | AK37: =IF(AND($CF37<>"",IFERROR(INDEX(subsample_country_map!$B:$B,MATCH($CF37,subsample_country_map!$A:$A,0)),"")<>""),INDEX(subsample_country_map!$B:$B,MATCH($CF37,subsample_country_map!$A:$A,0)),INDEX(lookup!$AA:$AA,MATCH($A37,lookup!$A:$A,0))) -> 3_AsiaPac | AL37: =IF(AND($CF37<>"",IFERROR(INDEX(subsample_country_map!$C:$C,MATCH($CF37,subsample_country_map!$A:$A,0)),"")<>""),INDEX(subsample_country_map!$C:$C,MATCH($CF37,subsample_country_map!$A:$A,0)),INDEX(lookup!$AB:$AB,MATCH($A37,lookup!$A:$A,0))) -> 1_developed | AM37: =IF(AND($CF37<>"",IFERROR(INDEX(subsample_country_map!$D:$D,MATCH($CF37,subsample_country_map!$A:$A,0)),"")<>""),INDEX(subsample_country_map!$D:$D,MATCH($CF37,subsample_country_map!$A:$A,0)),INDEX(lookup!$AC:$AC,MATCH($A37,lookup!$A:$A,0))) -> 2_non_western | AN37: =IF(AND($CF37<>"",IFERROR(INDEX(subsample_country_map!$E:$E,MATCH($CF37,subsample_country_map!$A:$A,0)),"")<>""),INDEX(subsample_country_map!$E:$E,MATCH($CF37,subsample_country_map!$A:$A,0)),INDEX(lookup!$AD:$AD,MATCH($A37,lookup!$A:$A,0))) -> 2_civil law | AO37: =INDEX(lookup!$Y:$Y,MATCH($A37,lookup!$A:$A,0)) -> 0_published | AP37: =INDEX(lookup!$Z:$Z,MATCH($A37,lookup!$A:$A,0)) -> 1_VHB high | AQ37: =INDEX(lookup!$W:$W,MATCH($A37,lookup!$A:$A,0)) -> 1_fin/acc/econ | AS37: staging | AT37: good-CER | AU37: cost | AV37: 0.023 | AX37: 2.52 | BA37: 344 | BB37: 0 | BC37: OLS | BD37: not stated | BE37: region | BF37: Taiwan | BI37: Table 8 | BJ37: Panel C col 4 | BK37: 12 | BL37: CCP4 0.023** (2.52) | BM37: CCP4 | BN37: COD | BO37: update | BP37: Al-Fakir Al Rabab'a et al (2023) | BQ37: computed | BT37: 0 | BU37: staging_Al-Fakir_Al_Rababa_et_al_2023.csv | BW37: 2003 | BX37: 2018 | BY37: multi: 14 Asia-Pacific countries (Australia, China, Hong Kong, India, Indonesia, Japan, Malaysia, New Zealand, Philippines, Singapore, South Korea, Sri Lanka, Taiwan, Thailand) | BZ37: 2010.5 | CA37: 0.1875 | CB37: 0 | CC37: 1 | CD37: 0.13545469 | CE37: 1 | CF37: Taiwan
... A41: Al-Fakir Al Rabab'a et al (2023) | B41: 1346 | C41: -0.14894696 | D41: 358 | E41: =IF(ISNUMBER($BA41),$BA41,IF(AND(ISNUMBER($D41),ISNUMBER($BW41),ISNUMBER($BX41)),$D41*($BX41-$BW41+1),"")) -> 358 | H41: partial | I41: T-Statistic available | J41: =IF($BW41<>"",$BW41,"") -> 2003 | K41: =IF($BX41<>"",$BX41,"") -> 2018 | L41: =IF(AND(ISNUMBER($BW41),ISNUMBER($BX41)),($BW41+$BX41)/2,"") -> 2010.5 | M41: =IF($L41<>"",$L41,"") -> 2010.5 | N41: =IF(AND(ISNUMBER($BW41),ISNUMBER($BX41)),MIN(1,MAX(0,($BX41-2016+1)/($BX41-$BW41+1))),"") -> 0.1875 | O41: =IF(AND(ISNUMBER($BW41),ISNUMBER($BX41)),MIN(1,MAX(0,($BX41-2017+1)/($BX41-$BW41+1))),"") -> 0.125 | P41: =IF(AND(ISNUMBER($BW41),ISNUMBER($BX41)),MIN(1,MAX(0,($BX41-2018+1)/($BX41-$BW41+1))),"") -> 0.0625 | Q41: =IF(AND(ISNUMBER($BW41),ISNUMBER($BX41)),MIN(1,MAX(0,($BX41-2019+1)/($BX41-$BW41+1))),"") -> 0 | R41: =IF(AND(ISNUMBER($BW41),ISNUMBER($BX41)),MIN(1,MAX(0,($BX41-2016+1)/($BX41-$BW41+1))),"") -> 0.1875 | S41: =IF($L41<>"",IF($L41>=2015.5,1,0),"") -> 0 | T41: =IF($L41<>"",IF($L41>=2016,1,0),"") -> 0 | U41: =IF(ISNUMBER($BX41),IF($BX41>=2016,1,0),"") -> 1 | V41: =IF(ISNUMBER($BW41),IF($BW41>=2016,1,0),"") -> 0 | W41: =IF(AND(ISNUMBER($BW41),ISNUMBER($BX41)),IF($BW41>=2016,"post-only",IF($BX41<2016,"pre-only","mixed")),"") -> mixed | X41: =IF(AND(ISNUMBER($BW41),ISNUMBER($BX41)),MIN(1,MAX(0,($BX41-2017+1)/($BX41-$BW41+1))),"") -> 0.125 | Y41: =IF(AND(ISNUMBER($BW41),ISNUMBER($BX41)),MIN(1,MAX(0,($BX41-2018+1)/($BX41-$BW41+1))),"") -> 0.0625 | Z41: =IF(AND(ISNUMBER($BW41),ISNUMBER($BX41)),MIN(1,MAX(0,($BX41-2019+1)/($BX41-$BW41+1))),"") -> 0 | AA41: =IF(ISNUMBER($BX41),IF($BX41>=2017,1,0),"") -> 1 | AB41: =IF(ISNUMBER($BX41),IF($BX41>=2018,1,0),"") -> 1 | AC41: =IF(ISNUMBER($BX41),IF($BX41>=2019,1,0),"") -> 0 | AD41: =IF($L41<>"",IF($L41>2013,1,0),"") -> 0 | AE41: =IF($L41<>"",1+IF($L41>2011,1,0)+IF($L41>2014,1,0),"") -> 1 | AF41: loan (interest rate) | AG41: performance | AH41: non-sensitive | AI41: 99_NCE | AJ41: 99_NCE | AK41: =IF(AND($CF41<>"",IFERROR(INDEX(subsample_country_map!$B:$B,MATCH($CF41,subsample_country_map!$A:$A,0)),"")<>""),INDEX(subsample_country_map!$B:$B,MATCH($CF41,subsample_country_map!$A:$A,0)),INDEX(lookup!$AA:$AA,MATCH($A41,lookup!$A:$A,0))) -> 3_AsiaPac | AL41: =IF(AND($CF41<>"",IFERROR(INDEX(subsample_country_map!$C:$C,MATCH($CF41,subsample_country_map!$A:$A,0)),"")<>""),INDEX(subsample_country_map!$C:$C,MATCH($CF41,subsample_country_map!$A:$A,0)),INDEX(lookup!$AB:$AB,MATCH($A41,lookup!$A:$A,0))) -> 1_developed | AM41: =IF(AND($CF41<>"",IFERROR(INDEX(subsample_country_map!$D:$D,MATCH($CF41,subsample_country_map!$A:$A,0)),"")<>""),INDEX(subsample_country_map!$D:$D,MATCH($CF41,subsample_country_map!$A:$A,0)),INDEX(lookup!$AC:$AC,MATCH($A41,lookup!$A:$A,0))) -> 2_non_western | AN41: =IF(AND($CF41<>"",IFERROR(INDEX(subsample_country_map!$E:$E,MATCH($CF41,subsample_country_map!$A:$A,0)),"")<>""),INDEX(subsample_country_map!$E:$E,MATCH($CF41,subsample_country_map!$A:$A,0)),INDEX(lookup!$AD:$AD,MATCH($A41,lookup!$A:$A,0))) -> 2_civil law | AO41: =INDEX(lookup!$Y:$Y,MATCH($A41,lookup!$A:$A,0)) -> 0_published | AP41: =INDEX(lookup!$Z:$Z,MATCH($A41,lookup!$A:$A,0)) -> 1_VHB high | AQ41: =INDEX(lookup!$W:$W,MATCH($A41,lookup!$A:$A,0)) -> 1_fin/acc/econ | AS41: staging | AT41: good-CER | AU41: cost | AV41: -0.062 | AX41: -2.85 | BA41: 358 | BB41: 0 | BC41: OLS | BD41: not stated | BE41: region | BF41: South Korea | BI41: Table 8 | BJ41: Panel D col 4 | BK41: 12 | BL41: CCP4 -0.062*** (-2.85) | BM41: CCP4 | BN41: COD | BO41: update | BP41: Al-Fakir Al Rabab'a et al (2023) | BQ41: computed | BT41: 0 | BU41: staging_Al-Fakir_Al_Rababa_et_al_2023.csv | BW41: 2003 | BX41: 2018 | BY41: multi: 14 Asia-Pacific countries (Australia, China, Hong Kong, India, Indonesia, Japan, Malaysia, New Zealand, Philippines, Singapore, South Korea, Sri Lanka, Taiwan, Thailand) | BZ41: 2010.5 | CA41: 0.1875 | CB41: 0 | CC41: 1 | CD41: -0.15006333 | CE41: 1 | CF41: South Korea
A42: Al-Fakir Al Rabab'a et al (2023) | B42: 1347 | C42: 0.10366542 | D42: 1429 | E42: =IF(ISNUMBER($BA42),$BA42,IF(AND(ISNUMBER($D42),ISNUMBER($BW42),ISNUMBER($BX42)),$D42*($BX42-$BW42+1),"")) -> 1429 | H42: partial | I42: T-Statistic available | J42: =IF($BW42<>"",$BW42,"") -> 2003 | K42: =IF($BX42<>"",$BX42,"") -> 2018 | L42: =IF(AND(ISNUMBER($BW42),ISNUMBER($BX42)),($BW42+$BX42)/2,"") -> 2010.5 | M42: =IF($L42<>"",$L42,"") -> 2010.5 | N42: =IF(AND(ISNUMBER($BW42),ISNUMBER($BX42)),MIN(1,MAX(0,($BX42-2016+1)/($BX42-$BW42+1))),"") -> 0.1875 | O42: =IF(AND(ISNUMBER($BW42),ISNUMBER($BX42)),MIN(1,MAX(0,($BX42-2017+1)/($BX42-$BW42+1))),"") -> 0.125 | P42: =IF(AND(ISNUMBER($BW42),ISNUMBER($BX42)),MIN(1,MAX(0,($BX42-2018+1)/($BX42-$BW42+1))),"") -> 0.0625 | Q42: =IF(AND(ISNUMBER($BW42),ISNUMBER($BX42)),MIN(1,MAX(0,($BX42-2019+1)/($BX42-$BW42+1))),"") -> 0 | R42: =IF(AND(ISNUMBER($BW42),ISNUMBER($BX42)),MIN(1,MAX(0,($BX42-2016+1)/($BX42-$BW42+1))),"") -> 0.1875 | S42: =IF($L42<>"",IF($L42>=2015.5,1,0),"") -> 0 | T42: =IF($L42<>"",IF($L42>=2016,1,0),"") -> 0 | U42: =IF(ISNUMBER($BX42),IF($BX42>=2016,1,0),"") -> 1 | V42: =IF(ISNUMBER($BW42),IF($BW42>=2016,1,0),"") -> 0 | W42: =IF(AND(ISNUMBER($BW42),ISNUMBER($BX42)),IF($BW42>=2016,"post-only",IF($BX42<2016,"pre-only","mixed")),"") -> mixed | X42: =IF(AND(ISNUMBER($BW42),ISNUMBER($BX42)),MIN(1,MAX(0,($BX42-2017+1)/($BX42-$BW42+1))),"") -> 0.125 | Y42: =IF(AND(ISNUMBER($BW42),ISNUMBER($BX42)),MIN(1,MAX(0,($BX42-2018+1)/($BX42-$BW42+1))),"") -> 0.0625 | Z42: =IF(AND(ISNUMBER($BW42),ISNUMBER($BX42)),MIN(1,MAX(0,($BX42-2019+1)/($BX42-$BW42+1))),"") -> 0 | AA42: =IF(ISNUMBER($BX42),IF($BX42>=2017,1,0),"") -> 1 | AB42: =IF(ISNUMBER($BX42),IF($BX42>=2018,1,0),"") -> 1 | AC42: =IF(ISNUMBER($BX42),IF($BX42>=2019,1,0),"") -> 0 | AD42: =IF($L42<>"",IF($L42>2013,1,0),"") -> 0 | AE42: =IF($L42<>"",1+IF($L42>2011,1,0)+IF($L42>2014,1,0),"") -> 1 | AF42: loan (interest rate) | AG42: performance | AH42: non-sensitive | AI42: 99_NCE | AJ42: 99_NCE | AK42: =IF(AND($CF42<>"",IFERROR(INDEX(subsample_country_map!$B:$B,MATCH($CF42,subsample_country_map!$A:$A,0)),"")<>""),INDEX(subsample_country_map!$B:$B,MATCH($CF42,subsample_country_map!$A:$A,0)),INDEX(lookup!$AA:$AA,MATCH($A42,lookup!$A:$A,0))) -> 3_AsiaPac | AL42: =IF(AND($CF42<>"",IFERROR(INDEX(subsample_country_map!$C:$C,MATCH($CF42,subsample_country_map!$A:$A,0)),"")<>""),INDEX(subsample_country_map!$C:$C,MATCH($CF42,subsample_country_map!$A:$A,0)),INDEX(lookup!$AB:$AB,MATCH($A42,lookup!$A:$A,0))) -> 99_NCE | AM42: =IF(AND($CF42<>"",IFERROR(INDEX(subsample_country_map!$D:$D,MATCH($CF42,subsample_country_map!$A:$A,0)),"")<>""),INDEX(subsample_country_map!$D:$D,MATCH($CF42,subsample_country_map!$A:$A,0)),INDEX(lookup!$AC:$AC,MATCH($A42,lookup!$A:$A,0))) -> 99_NCE | AN42: =IF(AND($CF42<>"",IFERROR(INDEX(subsample_country_map!$E:$E,MATCH($CF42,subsample_country_map!$A:$A,0)),"")<>""),INDEX(subsample_country_map!$E:$E,MATCH($CF42,subsample_country_map!$A:$A,0)),INDEX(lookup!$AD:$AD,MATCH($A42,lookup!$A:$A,0))) -> 99_NCE | AO42: =INDEX(lookup!$Y:$Y,MATCH($A42,lookup!$A:$A,0)) -> 0_published | AP42: =INDEX(lookup!$Z:$Z,MATCH($A42,lookup!$A:$A,0)) -> 1_VHB high | AQ42: =INDEX(lookup!$W:$W,MATCH($A42,lookup!$A:$A,0)) -> 1_fin/acc/econ | AS42: staging | AT42: author-inverted-to-good | AU42: cost | AV42: -0.485 | AX42: 3.94 | BA42: 1429 | BB42: 0 | BC42: OLS | BD42: not stated | BE42: region | BF42: Excluding Japan | BI42: Table 8 | BJ42: Panel E col 1 | BK42: 12 | BL42: CCP1 -0.485*** (3.94) | BM42: CCP1 | BN42: COD | BO42: update | BP42: Al-Fakir Al Rabab'a et al (2023) | BQ42: computed | BT42: 0 | BU42: staging_Al-Fakir_Al_Rababa_et_al_2023.csv | BW42: 2003 | BX42: 2018 | BY42: multi: 14 Asia-Pacific countries (Australia, China, Hong Kong, India, Indonesia, Japan, Malaysia, New Zealand, Philippines, Singapore, South Korea, Sri Lanka, Taiwan, Thailand) | BZ42: 2010.5 | CA42: 0.1875 | CB42: 0 | CC42: 1 | CD42: 0.10403918 | CE42: 1
A43: Al-Fakir Al Rabab'a et al (2023) | B43: 1348 | C43: 0.073342795 | D43: 1429 | E43: =IF(ISNUMBER($BA43),$BA43,IF(AND(ISNUMBER($D43),ISNUMBER($BW43),ISNUMBER($BX43)),$D43*($BX43-$BW43+1),"")) -> 1429 | H43: partial | I43: T-Statistic available | J43: =IF($BW43<>"",$BW43,"") -> 2003 | K43: =IF($BX43<>"",$BX43,"") -> 2018 | L43: =IF(AND(ISNUMBER($BW43),ISNUMBER($BX43)),($BW43+$BX43)/2,"") -> 2010.5 | M43: =IF($L43<>"",$L43,"") -> 2010.5 | N43: =IF(AND(ISNUMBER($BW43),ISNUMBER($BX43)),MIN(1,MAX(0,($BX43-2016+1)/($BX43-$BW43+1))),"") -> 0.1875 | O43: =IF(AND(ISNUMBER($BW43),ISNUMBER($BX43)),MIN(1,MAX(0,($BX43-2017+1)/($BX43-$BW43+1))),"") -> 0.125 | P43: =IF(AND(ISNUMBER($BW43),ISNUMBER($BX43)),MIN(1,MAX(0,($BX43-2018+1)/($BX43-$BW43+1))),"") -> 0.0625 | Q43: =IF(AND(ISNUMBER($BW43),ISNUMBER($BX43)),MIN(1,MAX(0,($BX43-2019+1)/($BX43-$BW43+1))),"") -> 0 | R43: =IF(AND(ISNUMBER($BW43),ISNUMBER($BX43)),MIN(1,MAX(0,($BX43-2016+1)/($BX43-$BW43+1))),"") -> 0.1875 | S43: =IF($L43<>"",IF($L43>=2015.5,1,0),"") -> 0 | T43: =IF($L43<>"",IF($L43>=2016,1,0),"") -> 0 | U43: =IF(ISNUMBER($BX43),IF($BX43>=2016,1,0),"") -> 1 | V43: =IF(ISNUMBER($BW43),IF($BW43>=2016,1,0),"") -> 0 | W43: =IF(AND(ISNUMBER($BW43),ISNUMBER($BX43)),IF($BW43>=2016,"post-only",IF($BX43<2016,"pre-only","mixed")),"") -> mixed | X43: =IF(AND(ISNUMBER($BW43),ISNUMBER($BX43)),MIN(1,MAX(0,($BX43-2017+1)/($BX43-$BW43+1))),"") -> 0.125 | Y43: =IF(AND(ISNUMBER($BW43),ISNUMBER($BX43)),MIN(1,MAX(0,($BX43-2018+1)/($BX43-$BW43+1))),"") -> 0.0625 | Z43: =IF(AND(ISNUMBER($BW43),ISNUMBER($BX43)),MIN(1,MAX(0,($BX43-2019+1)/($BX43-$BW43+1))),"") -> 0 | AA43: =IF(ISNUMBER($BX43),IF($BX43>=2017,1,0),"") -> 1 | AB43: =IF(ISNUMBER($BX43),IF($BX43>=2018,1,0),"") -> 1 | AC43: =IF(ISNUMBER($BX43),IF($BX43>=2019,1,0),"") -> 0 | AD43: =IF($L43<>"",IF($L43>2013,1,0),"") -> 0 | AE43: =IF($L43<>"",1+IF($L43>2011,1,0)+IF($L43>2014,1,0),"") -> 1 | AF43: loan (interest rate) | AG43: performance | AH43: non-sensitive | AI43: 99_NCE | AJ43: 99_NCE | AK43: =IF(AND($CF43<>"",IFERROR(INDEX(subsample_country_map!$B:$B,MATCH($CF43,subsample_country_map!$A:$A,0)),"")<>""),INDEX(subsample_country_map!$B:$B,MATCH($CF43,subsample_country_map!$A:$A,0)),INDEX(lookup!$AA:$AA,MATCH($A43,lookup!$A:$A,0))) -> 3_AsiaPac | AL43: =IF(AND($CF43<>"",IFERROR(INDEX(subsample_country_map!$C:$C,MATCH($CF43,subsample_country_map!$A:$A,0)),"")<>""),INDEX(subsample_country_map!$C:$C,MATCH($CF43,subsample_country_map!$A:$A,0)),INDEX(lookup!$AB:$AB,MATCH($A43,lookup!$A:$A,0))) -> 99_NCE | AM43: =IF(AND($CF43<>"",IFERROR(INDEX(subsample_country_map!$D:$D,MATCH($CF43,subsample_country_map!$A:$A,0)),"")<>""),INDEX(subsample_country_map!$D:$D,MATCH($CF43,subsample_country_map!$A:$A,0)),INDEX(lookup!$AC:$AC,MATCH($A43,lookup!$A:$A,0))) -> 99_NCE | AN43: =IF(AND($CF43<>"",IFERROR(INDEX(subsample_country_map!$E:$E,MATCH($CF43,subsample_country_map!$A:$A,0)),"")<>""),INDEX(subsample_country_map!$E:$E,MATCH($CF43,subsample_country_map!$A:$A,0)),INDEX(lookup!$AD:$AD,MATCH($A43,lookup!$A:$A,0))) -> 99_NCE | AO43: =INDEX(lookup!$Y:$Y,MATCH($A43,lookup!$A:$A,0)) -> 0_published | AP43: =INDEX(lookup!$Z:$Z,MATCH($A43,lookup!$A:$A,0)) -> 1_VHB high | AQ43: =INDEX(lookup!$W:$W,MATCH($A43,lookup!$A:$A,0)) -> 1_fin/acc/econ | AS43: staging | AT43: author-inverted-to-good | AU43: cost | AV43: -0.419 | AX43: 2.78 | BA43: 1429 | BB43: 0 | BC43: OLS | BD43: not stated | BE43: region | BF43: Excluding Japan | BI43: Table 8 | BJ43: Panel E col 2 | BK43: 12 | BL43: CCP2 -0.419*** (2.78) | BM43: CCP2 | BN43: COD | BO43: update | BP43: Al-Fakir Al Rabab'a et al (2023) | BQ43: computed | BT43: 0 | BU43: staging_Al-Fakir_Al_Rababa_et_al_2023.csv | BW43: 2003 | BX43: 2018 | BY43: multi: 14 Asia-Pacific countries (Australia, China, Hong Kong, India, Indonesia, Japan, Malaysia, New Zealand, Philippines, Singapore, South Korea, Sri Lanka, Taiwan, Thailand) | BZ43: 2010.5 | CA43: 0.1875 | CB43: 0 | CC43: 1 | CD43: 0.073474729 | CE43: 1
A44: Al-Fakir Al Rabab'a et al (2023) | B44: 1349 | C44: -0.12260601 | D44: 1429 | E44: =IF(ISNUMBER($BA44),$BA44,IF(AND(ISNUMBER($D44),ISNUMBER($BW44),ISNUMBER($BX44)),$D44*($BX44-$BW44+1),"")) -> 1429 | H44: partial | I44: T-Statistic available | J44: =IF($BW44<>"",$BW44,"") -> 2003 | K44: =IF($BX44<>"",$BX44,"") -> 2018 | L44: =IF(AND(ISNUMBER($BW44),ISNUMBER($BX44)),($BW44+$BX44)/2,"") -> 2010.5 | M44: =IF($L44<>"",$L44,"") -> 2010.5 | N44: =IF(AND(ISNUMBER($BW44),ISNUMBER($BX44)),MIN(1,MAX(0,($BX44-2016+1)/($BX44-$BW44+1))),"") -> 0.1875 | O44: =IF(AND(ISNUMBER($BW44),ISNUMBER($BX44)),MIN(1,MAX(0,($BX44-2017+1)/($BX44-$BW44+1))),"") -> 0.125 | P44: =IF(AND(ISNUMBER($BW44),ISNUMBER($BX44)),MIN(1,MAX(0,($BX44-2018+1)/($BX44-$BW44+1))),"") -> 0.0625 | Q44: =IF(AND(ISNUMBER($BW44),ISNUMBER($BX44)),MIN(1,MAX(0,($BX44-2019+1)/($BX44-$BW44+1))),"") -> 0 | R44: =IF(AND(ISNUMBER($BW44),ISNUMBER($BX44)),MIN(1,MAX(0,($BX44-2016+1)/($BX44-$BW44+1))),"") -> 0.1875 | S44: =IF($L44<>"",IF($L44>=2015.5,1,0),"") -> 0 | T44: =IF($L44<>"",IF($L44>=2016,1,0),"") -> 0 | U44: =IF(ISNUMBER($BX44),IF($BX44>=2016,1,0),"") -> 1 | V44: =IF(ISNUMBER($BW44),IF($BW44>=2016,1,0),"") -> 0 | W44: =IF(AND(ISNUMBER($BW44),ISNUMBER($BX44)),IF($BW44>=2016,"post-only",IF($BX44<2016,"pre-only","mixed")),"") -> mixed | X44: =IF(AND(ISNUMBER($BW44),ISNUMBER($BX44)),MIN(1,MAX(0,($BX44-2017+1)/($BX44-$BW44+1))),"") -> 0.125 | Y44: =IF(AND(ISNUMBER($BW44),ISNUMBER($BX44)),MIN(1,MAX(0,($BX44-2018+1)/($BX44-$BW44+1))),"") -> 0.0625 | Z44: =IF(AND(ISNUMBER($BW44),ISNUMBER($BX44)),MIN(1,MAX(0,($BX44-2019+1)/($BX44-$BW44+1))),"") -> 0 | AA44: =IF(ISNUMBER($BX44),IF($BX44>=2017,1,0),"") -> 1 | AB44: =IF(ISNUMBER($BX44),IF($BX44>=2018,1,0),"") -> 1 | AC44: =IF(ISNUMBER($BX44),IF($BX44>=2019,1,0),"") -> 0 | AD44: =IF($L44<>"",IF($L44>2013,1,0),"") -> 0 | AE44: =IF($L44<>"",1+IF($L44>2011,1,0)+IF($L44>2014,1,0),"") -> 1 | AF44: loan (interest rate) | AG44: performance | AH44: non-sensitive | AI44: 99_NCE | AJ44: 99_NCE | AK44: =IF(AND($CF44<>"",IFERROR(INDEX(subsample_country_map!$B:$B,MATCH($CF44,subsample_country_map!$A:$A,0)),"")<>""),INDEX(subsample_country_map!$B:$B,MATCH($CF44,subsample_country_map!$A:$A,0)),INDEX(lookup!$AA:$AA,MATCH($A44,lookup!$A:$A,0))) -> 3_AsiaPac | AL44: =IF(AND($CF44<>"",IFERROR(INDEX(subsample_country_map!$C:$C,MATCH($CF44,subsample_country_map!$A:$A,0)),"")<>""),INDEX(subsample_country_map!$C:$C,MATCH($CF44,subsample_country_map!$A:$A,0)),INDEX(lookup!$AB:$AB,MATCH($A44,lookup!$A:$A,0))) -> 99_NCE | AM44: =IF(AND($CF44<>"",IFERROR(INDEX(subsample_country_map!$D:$D,MATCH($CF44,subsample_country_map!$A:$A,0)),"")<>""),INDEX(subsample_country_map!$D:$D,MATCH($CF44,subsample_country_map!$A:$A,0)),INDEX(lookup!$AC:$AC,MATCH($A44,lookup!$A:$A,0))) -> 99_NCE | AN44: =IF(AND($CF44<>"",IFERROR(INDEX(subsample_country_map!$E:$E,MATCH($CF44,subsample_country_map!$A:$A,0)),"")<>""),INDEX(subsample_country_map!$E:$E,MATCH($CF44,subsample_country_map!$A:$A,0)),INDEX(lookup!$AD:$AD,MATCH($A44,lookup!$A:$A,0))) -> 99_NCE | AO44: =INDEX(lookup!$Y:$Y,MATCH($A44,lookup!$A:$A,0)) -> 0_published | AP44: =INDEX(lookup!$Z:$Z,MATCH($A44,lookup!$A:$A,0)) -> 1_VHB high | AQ44: =INDEX(lookup!$W:$W,MATCH($A44,lookup!$A:$A,0)) -> 1_fin/acc/econ | AS44: staging | AT44: good-CER | AU44: cost | AV44: -0.102 | AX44: -4.67 | BA44: 1429 | BB44: 0 | BC44: OLS | BD44: not stated | BE44: region | BF44: Excluding Japan | BI44: Table 8 | BJ44: Panel E col 3 | BK44: 12 | BL44: CCP3 -0.102*** (-4.67) | BM44: CCP3 | BN44: COD | BO44: update | BP44: Al-Fakir Al Rabab'a et al (2023) | BQ44: computed | BT44: 0 | BU44: staging_Al-Fakir_Al_Rababa_et_al_2023.csv | BW44: 2003 | BX44: 2018 | BY44: multi: 14 Asia-Pacific countries (Australia, China, Hong Kong, India, Indonesia, Japan, Malaysia, New Zealand, Philippines, Singapore, South Korea, Sri Lanka, Taiwan, Thailand) | BZ44: 2010.5 | CA44: 0.1875 | CB44: 0 | CC44: 1 | CD44: -0.12322596 | CE44: 1
A45: Al-Fakir Al Rabab'a et al (2023) | B45: 1350 | C45: -0.1127619 | D45: 1429 | E45: =IF(ISNUMBER($BA45),$BA45,IF(AND(ISNUMBER($D45),ISNUMBER($BW45),ISNUMBER($BX45)),$D45*($BX45-$BW45+1),"")) -> 1429 | H45: partial | I45: T-Statistic available | J45: =IF($BW45<>"",$BW45,"") -> 2003 | K45: =IF($BX45<>"",$BX45,"") -> 2018 | L45: =IF(AND(ISNUMBER($BW45),ISNUMBER($BX45)),($BW45+$BX45)/2,"") -> 2010.5 | M45: =IF($L45<>"",$L45,"") -> 2010.5 | N45: =IF(AND(ISNUMBER($BW45),ISNUMBER($BX45)),MIN(1,MAX(0,($BX45-2016+1)/($BX45-$BW45+1))),"") -> 0.1875 | O45: =IF(AND(ISNUMBER($BW45),ISNUMBER($BX45)),MIN(1,MAX(0,($BX45-2017+1)/($BX45-$BW45+1))),"") -> 0.125 | P45: =IF(AND(ISNUMBER($BW45),ISNUMBER($BX45)),MIN(1,MAX(0,($BX45-2018+1)/($BX45-$BW45+1))),"") -> 0.0625 | Q45: =IF(AND(ISNUMBER($BW45),ISNUMBER($BX45)),MIN(1,MAX(0,($BX45-2019+1)/($BX45-$BW45+1))),"") -> 0 | R45: =IF(AND(ISNUMBER($BW45),ISNUMBER($BX45)),MIN(1,MAX(0,($BX45-2016+1)/($BX45-$BW45+1))),"") -> 0.1875 | S45: =IF($L45<>"",IF($L45>=2015.5,1,0),"") -> 0 | T45: =IF($L45<>"",IF($L45>=2016,1,0),"") -> 0 | U45: =IF(ISNUMBER($BX45),IF($BX45>=2016,1,0),"") -> 1 | V45: =IF(ISNUMBER($BW45),IF($BW45>=2016,1,0),"") -> 0 | W45: =IF(AND(ISNUMBER($BW45),ISNUMBER($BX45)),IF($BW45>=2016,"post-only",IF($BX45<2016,"pre-only","mixed")),"") -> mixed | X45: =IF(AND(ISNUMBER($BW45),ISNUMBER($BX45)),MIN(1,MAX(0,($BX45-2017+1)/($BX45-$BW45+1))),"") -> 0.125 | Y45: =IF(AND(ISNUMBER($BW45),ISNUMBER($BX45)),MIN(1,MAX(0,($BX45-2018+1)/($BX45-$BW45+1))),"") -> 0.0625 | Z45: =IF(AND(ISNUMBER($BW45),ISNUMBER($BX45)),MIN(1,MAX(0,($BX45-2019+1)/($BX45-$BW45+1))),"") -> 0 | AA45: =IF(ISNUMBER($BX45),IF($BX45>=2017,1,0),"") -> 1 | AB45: =IF(ISNUMBER($BX45),IF($BX45>=2018,1,0),"") -> 1 | AC45: =IF(ISNUMBER($BX45),IF($BX45>=2019,1,0),"") -> 0 | AD45: =IF($L45<>"",IF($L45>2013,1,0),"") -> 0 | AE45: =IF($L45<>"",1+IF($L45>2011,1,0)+IF($L45>2014,1,0),"") -> 1 | AF45: loan (interest rate) | AG45: performance | AH45: non-sensitive | AI45: 99_NCE | AJ45: 99_NCE | AK45: =IF(AND($CF45<>"",IFERROR(INDEX(subsample_country_map!$B:$B,MATCH($CF45,subsample_country_map!$A:$A,0)),"")<>""),INDEX(subsample_country_map!$B:$B,MATCH($CF45,subsample_country_map!$A:$A,0)),INDEX(lookup!$AA:$AA,MATCH($A45,lookup!$A:$A,0))) -> 3_AsiaPac | AL45: =IF(AND($CF45<>"",IFERROR(INDEX(subsample_country_map!$C:$C,MATCH($CF45,subsample_country_map!$A:$A,0)),"")<>""),INDEX(subsample_country_map!$C:$C,MATCH($CF45,subsample_country_map!$A:$A,0)),INDEX(lookup!$AB:$AB,MATCH($A45,lookup!$A:$A,0))) -> 99_NCE | AM45: =IF(AND($CF45<>"",IFERROR(INDEX(subsample_country_map!$D:$D,MATCH($CF45,subsample_country_map!$A:$A,0)),"")<>""),INDEX(subsample_country_map!$D:$D,MATCH($CF45,subsample_country_map!$A:$A,0)),INDEX(lookup!$AC:$AC,MATCH($A45,lookup!$A:$A,0))) -> 99_NCE | AN45: =IF(AND($CF45<>"",IFERROR(INDEX(subsample_country_map!$E:$E,MATCH($CF45,subsample_country_map!$A:$A,0)),"")<>""),INDEX(subsample_country_map!$E:$E,MATCH($CF45,subsample_country_map!$A:$A,0)),INDEX(lookup!$AD:$AD,MATCH($A45,lookup!$A:$A,0))) -> 99_NCE | AO45: =INDEX(lookup!$Y:$Y,MATCH($A45,lookup!$A:$A,0)) -> 0_published | AP45: =INDEX(lookup!$Z:$Z,MATCH($A45,lookup!$A:$A,0)) -> 1_VHB high | AQ45: =INDEX(lookup!$W:$W,MATCH($A45,lookup!$A:$A,0)) -> 1_fin/acc/econ | AS45: staging | AT45: good-CER | AU45: cost | AV45: -0.140 | AX45: -4.29 | BA45: 1429 | BB45: 0 | BC45: OLS | BD45: not stated | BE45: region | BF45: Excluding Japan | BI45: Table 8 | BJ45: Panel E col 4 | BK45: 12 | BL45: CCP4 -0.140*** (-4.29) | BM45: CCP4 | BN45: COD | BO45: update | BP45: Al-Fakir Al Rabab'a et al (2023) | BQ45: computed | BT45: 0 | BU45: staging_Al-Fakir_Al_Rababa_et_al_2023.csv | BW45: 2003 | BX45: 2018 | BY45: multi: 14 Asia-Pacific countries (Australia, China, Hong Kong, India, Indonesia, Japan, Malaysia, New Zealand, Philippines, Singapore, South Korea, Sri Lanka, Taiwan, Thailand) | BZ45: 2010.5 | CA45: 0.1875 | CB45: 0 | CC45: 1 | CD45: -0.11324351 | CE45: 1
A46: Al-Fakir Al Rabab'a et al (2023) | B46: 1351 | C46: 0.12926444 | D46: 725 | E46: =IF(ISNUMBER($BA46),$BA46,IF(AND(ISNUMBER($D46),ISNUMBER($BW46),ISNUMBER($BX46)),$D46*($BX46-$BW46+1),"")) -> 725 | H46: partial | I46: T-Statistic available | J46: =IF($BW46<>"",$BW46,"") -> 2003 | K46: =IF($BX46<>"",$BX46,"") -> 2018 | L46: =IF(AND(ISNUMBER($BW46),ISNUMBER($BX46)),($BW46+$BX46)/2,"") -> 2010.5 | M46: =IF($L46<>"",$L46,"") -> 2010.5 | N46: =IF(AND(ISNUMBER($BW46),ISNUMBER($BX46)),MIN(1,MAX(0,($BX46-2016+1)/($BX46-$BW46+1))),"") -> 0.1875 | O46: =IF(AND(ISNUMBER($BW46),ISNUMBER($BX46)),MIN(1,MAX(0,($BX46-2017+1)/($BX46-$BW46+1))),"") -> 0.125 | P46: =IF(AND(ISNUMBER($BW46),ISNUMBER($BX46)),MIN(1,MAX(0,($BX46-2018+1)/($BX46-$BW46+1))),"") -> 0.0625 | Q46: =IF(AND(ISNUMBER($BW46),ISNUMBER($BX46)),MIN(1,MAX(0,($BX46-2019+1)/($BX46-$BW46+1))),"") -> 0 | R46: =IF(AND(ISNUMBER($BW46),ISNUMBER($BX46)),MIN(1,MAX(0,($BX46-2016+1)/($BX46-$BW46+1))),"") -> 0.1875 | S46: =IF($L46<>"",IF($L46>=2015.5,1,0),"") -> 0 | T46: =IF($L46<>"",IF($L46>=2016,1,0),"") -> 0 | U46: =IF(ISNUMBER($BX46),IF($BX46>=2016,1,0),"") -> 1 | V46: =IF(ISNUMBER($BW46),IF($BW46>=2016,1,0),"") -> 0 | W46: =IF(AND(ISNUMBER($BW46),ISNUMBER($BX46)),IF($BW46>=2016,"post-only",IF($BX46<2016,"pre-only","mixed")),"") -> mixed | X46: =IF(AND(ISNUMBER($BW46),ISNUMBER($BX46)),MIN(1,MAX(0,($BX46-2017+1)/($BX46-$BW46+1))),"") -> 0.125 | Y46: =IF(AND(ISNUMBER($BW46),ISNUMBER($BX46)),MIN(1,MAX(0,($BX46-2018+1)/($BX46-$BW46+1))),"") -> 0.0625 | Z46: =IF(AND(ISNUMBER($BW46),ISNUMBER($BX46)),MIN(1,MAX(0,($BX46-2019+1)/($BX46-$BW46+1))),"") -> 0 | AA46: =IF(ISNUMBER($BX46),IF($BX46>=2017,1,0),"") -> 1 | AB46: =IF(ISNUMBER($BX46),IF($BX46>=2018,1,0),"") -> 1 | AC46: =IF(ISNUMBER($BX46),IF($BX46>=2019,1,0),"") -> 0 | AD46: =IF($L46<>"",IF($L46>2013,1,0),"") -> 0 | AE46: =IF($L46<>"",1+IF($L46>2011,1,0)+IF($L46>2014,1,0),"") -> 1 | AF46: loan (interest rate) | AG46: performance | AH46: non-sensitive | AI46: 99_NCE | AJ46: 99_NCE | AK46: =IF(AND($CF46<>"",IFERROR(INDEX(subsample_country_map!$B:$B,MATCH($CF46,subsample_country_map!$A:$A,0)),"")<>""),INDEX(subsample_country_map!$B:$B,MATCH($CF46,subsample_country_map!$A:$A,0)),INDEX(lookup!$AA:$AA,MATCH($A46,lookup!$A:$A,0))) -> 3_AsiaPac | AL46: =IF(AND($CF46<>"",IFERROR(INDEX(subsample_country_map!$C:$C,MATCH($CF46,subsample_country_map!$A:$A,0)),"")<>""),INDEX(subsample_country_map!$C:$C,MATCH($CF46,subsample_country_map!$A:$A,0)),INDEX(lookup!$AB:$AB,MATCH($A46,lookup!$A:$A,0))) -> 99_NCE | AM46: =IF(AND($CF46<>"",IFERROR(INDEX(subsample_country_map!$D:$D,MATCH($CF46,subsample_country_map!$A:$A,0)),"")<>""),INDEX(subsample_country_map!$D:$D,MATCH($CF46,subsample_country_map!$A:$A,0)),INDEX(lookup!$AC:$AC,MATCH($A46,lookup!$A:$A,0))) -> 99_NCE | AN46: =IF(AND($CF46<>"",IFERROR(INDEX(subsample_country_map!$E:$E,MATCH($CF46,subsample_country_map!$A:$A,0)),"")<>""),INDEX(subsample_country_map!$E:$E,MATCH($CF46,subsample_country_map!$A:$A,0)),INDEX(lookup!$AD:$AD,MATCH($A46,lookup!$A:$A,0))) -> 99_NCE | AO46: =INDEX(lookup!$Y:$Y,MATCH($A46,lookup!$A:$A,0)) -> 0_published | AP46: =INDEX(lookup!$Z:$Z,MATCH($A46,lookup!$A:$A,0)) -> 1_VHB high | AQ46: =INDEX(lookup!$W:$W,MATCH($A46,lookup!$A:$A,0)) -> 1_fin/acc/econ | AS46: staging | AT46: author-inverted-to-good | AU46: cost | AV46: -0.387 | AX46: 3.51 | BA46: 725 | BB46: 0 | BC46: OLS | BD46: not stated | BE46: region | BF46: Excluding top three countries | BI46: Table 8 | BJ46: Panel F col 1 | BK46: 12 | BL46: CCP1 -0.387*** (3.51) | BM46: CCP1 | BN46: COD | BO46: update | BP46: Al-Fakir Al Rabab'a et al (2023) | BQ46: computed | BT46: 0 | BU46: staging_Al-Fakir_Al_Rababa_et_al_2023.csv | BW46: 2003 | BX46: 2018 | BY46: multi: 14 Asia-Pacific countries (Australia, China, Hong Kong, India, Indonesia, Japan, Malaysia, New Zealand, Philippines, Singapore, South Korea, Sri Lanka, Taiwan, Thailand) | BZ46: 2010.5 | CA46: 0.1875 | CB46: 0 | CC46: 1 | CD46: 0.12999172 | CE46: 1
A47: Al-Fakir Al Rabab'a et al (2023) | B47: 1352 | C47: 0.098677352 | D47: 725 | E47: =IF(ISNUMBER($BA47),$BA47,IF(AND(ISNUMBER($D47),ISNUMBER($BW47),ISNUMBER($BX47)),$D47*($BX47-$BW47+1),"")) -> 725 | H47: partial | I47: T-Statistic available | J47: =IF($BW47<>"",$BW47,"") -> 2003 | K47: =IF($BX47<>"",$BX47,"") -> 2018 | L47: =IF(AND(ISNUMBER($BW47),ISNUMBER($BX47)),($BW47+$BX47)/2,"") -> 2010.5 | M47: =IF($L47<>"",$L47,"") -> 2010.5 | N47: =IF(AND(ISNUMBER($BW47),ISNUMBER($BX47)),MIN(1,MAX(0,($BX47-2016+1)/($BX47-$BW47+1))),"") -> 0.1875 | O47: =IF(AND(ISNUMBER($BW47),ISNUMBER($BX47)),MIN(1,MAX(0,($BX47-2017+1)/($BX47-$BW47+1))),"") -> 0.125 | P47: =IF(AND(ISNUMBER($BW47),ISNUMBER($BX47)),MIN(1,MAX(0,($BX47-2018+1)/($BX47-$BW47+1))),"") -> 0.0625 | Q47: =IF(AND(ISNUMBER($BW47),ISNUMBER($BX47)),MIN(1,MAX(0,($BX47-2019+1)/($BX47-$BW47+1))),"") -> 0 | R47: =IF(AND(ISNUMBER($BW47),ISNUMBER($BX47)),MIN(1,MAX(0,($BX47-2016+1)/($BX47-$BW47+1))),"") -> 0.1875 | S47: =IF($L47<>"",IF($L47>=2015.5,1,0),"") -> 0 | T47: =IF($L47<>"",IF($L47>=2016,1,0),"") -> 0 | U47: =IF(ISNUMBER($BX47),IF($BX47>=2016,1,0),"") -> 1 | V47: =IF(ISNUMBER($BW47),IF($BW47>=2016,1,0),"") -> 0 | W47: =IF(AND(ISNUMBER($BW47),ISNUMBER($BX47)),IF($BW47>=2016,"post-only",IF($BX47<2016,"pre-only","mixed")),"") -> mixed | X47: =IF(AND(ISNUMBER($BW47),ISNUMBER($BX47)),MIN(1,MAX(0,($BX47-2017+1)/($BX47-$BW47+1))),"") -> 0.125 | Y47: =IF(AND(ISNUMBER($BW47),ISNUMBER($BX47)),MIN(1,MAX(0,($BX47-2018+1)/($BX47-$BW47+1))),"") -> 0.0625 | Z47: =IF(AND(ISNUMBER($BW47),ISNUMBER($BX47)),MIN(1,MAX(0,($BX47-2019+1)/($BX47-$BW47+1))),"") -> 0 | AA47: =IF(ISNUMBER($BX47),IF($BX47>=2017,1,0),"") -> 1 | AB47: =IF(ISNUMBER($BX47),IF($BX47>=2018,1,0),"") -> 1 | AC47: =IF(ISNUMBER($BX47),IF($BX47>=2019,1,0),"") -> 0 | AD47: =IF($L47<>"",IF($L47>2013,1,0),"") -> 0 | AE47: =IF($L47<>"",1+IF($L47>2011,1,0)+IF($L47>2014,1,0),"") -> 1 | AF47: loan (interest rate) | AG47: performance | AH47: non-sensitive | AI47: 99_NCE | AJ47: 99_NCE | AK47: =IF(AND($CF47<>"",IFERROR(INDEX(subsample_country_map!$B:$B,MATCH($CF47,subsample_country_map!$A:$A,0)),"")<>""),INDEX(subsample_country_map!$B:$B,MATCH($CF47,subsample_country_map!$A:$A,0)),INDEX(lookup!$AA:$AA,MATCH($A47,lookup!$A:$A,0))) -> 3_AsiaPac | AL47: =IF(AND($CF47<>"",IFERROR(INDEX(subsample_country_map!$C:$C,MATCH($CF47,subsample_country_map!$A:$A,0)),"")<>""),INDEX(subsample_country_map!$C:$C,MATCH($CF47,subsample_country_map!$A:$A,0)),INDEX(lookup!$AB:$AB,MATCH($A47,lookup!$A:$A,0))) -> 99_NCE | AM47: =IF(AND($CF47<>"",IFERROR(INDEX(subsample_country_map!$D:$D,MATCH($CF47,subsample_country_map!$A:$A,0)),"")<>""),INDEX(subsample_country_map!$D:$D,MATCH($CF47,subsample_country_map!$A:$A,0)),INDEX(lookup!$AC:$AC,MATCH($A47,lookup!$A:$A,0))) -> 99_NCE | AN47: =IF(AND($CF47<>"",IFERROR(INDEX(subsample_country_map!$E:$E,MATCH($CF47,subsample_country_map!$A:$A,0)),"")<>""),INDEX(subsample_country_map!$E:$E,MATCH($CF47,subsample_country_map!$A:$A,0)),INDEX(lookup!$AD:$AD,MATCH($A47,lookup!$A:$A,0))) -> 99_NCE | AO47: =INDEX(lookup!$Y:$Y,MATCH($A47,lookup!$A:$A,0)) -> 0_published | AP47: =INDEX(lookup!$Z:$Z,MATCH($A47,lookup!$A:$A,0)) -> 1_VHB high | AQ47: =INDEX(lookup!$W:$W,MATCH($A47,lookup!$A:$A,0)) -> 1_fin/acc/econ | AS47: staging | AT47: author-inverted-to-good | AU47: cost | AV47: -0.384 | AX47: 2.67 | BA47: 725 | BB47: 0 | BC47: OLS | BD47: not stated | BE47: region | BF47: Excluding top three countries | BI47: Table 8 | BJ47: Panel F col 2 | BK47: 12 | BL47: CCP2 -0.384*** (2.67) | BM47: CCP2 | BN47: COD | BO47: update | BP47: Al-Fakir Al Rabab'a et al (2023) | BQ47: computed | BT47: 0 | BU47: staging_Al-Fakir_Al_Rababa_et_al_2023.csv | BW47: 2003 | BX47: 2018 | BY47: multi: 14 Asia-Pacific countries (Australia, China, Hong Kong, India, Indonesia, Japan, Malaysia, New Zealand, Philippines, Singapore, South Korea, Sri Lanka, Taiwan, Thailand) | BZ47: 2010.5 | CA47: 0.1875 | CB47: 0 | CC47: 1 | CD47: 0.098999517 | CE47: 1
A48: Al-Fakir Al Rabab'a et al (2023) | B48: 1353 | C48: -0.10598874 | D48: 725 | E48: =IF(ISNUMBER($BA48),$BA48,IF(AND(ISNUMBER($D48),ISNUMBER($BW48),ISNUMBER($BX48)),$D48*($BX48-$BW48+1),"")) -> 725 | H48: partial | I48: T-Statistic available | J48: =IF($BW48<>"",$BW48,"") -> 2003 | K48: =IF($BX48<>"",$BX48,"") -> 2018 | L48: =IF(AND(ISNUMBER($BW48),ISNUMBER($BX48)),($BW48+$BX48)/2,"") -> 2010.5 | M48: =IF($L48<>"",$L48,"") -> 2010.5 | N48: =IF(AND(ISNUMBER($BW48),ISNUMBER($BX48)),MIN(1,MAX(0,($BX48-2016+1)/($BX48-$BW48+1))),"") -> 0.1875 | O48: =IF(AND(ISNUMBER($BW48),ISNUMBER($BX48)),MIN(1,MAX(0,($BX48-2017+1)/($BX48-$BW48+1))),"") -> 0.125 | P48: =IF(AND(ISNUMBER($BW48),ISNUMBER($BX48)),MIN(1,MAX(0,($BX48-2018+1)/($BX48-$BW48+1))),"") -> 0.0625 | Q48: =IF(AND(ISNUMBER($BW48),ISNUMBER($BX48)),MIN(1,MAX(0,($BX48-2019+1)/($BX48-$BW48+1))),"") -> 0 | R48: =IF(AND(ISNUMBER($BW48),ISNUMBER($BX48)),MIN(1,MAX(0,($BX48-2016+1)/($BX48-$BW48+1))),"") -> 0.1875 | S48: =IF($L48<>"",IF($L48>=2015.5,1,0),"") -> 0 | T48: =IF($L48<>"",IF($L48>=2016,1,0),"") -> 0 | U48: =IF(ISNUMBER($BX48),IF($BX48>=2016,1,0),"") -> 1 | V48: =IF(ISNUMBER($BW48),IF($BW48>=2016,1,0),"") -> 0 | W48: =IF(AND(ISNUMBER($BW48),ISNUMBER($BX48)),IF($BW48>=2016,"post-only",IF($BX48<2016,"pre-only","mixed")),"") -> mixed | X48: =IF(AND(ISNUMBER($BW48),ISNUMBER($BX48)),MIN(1,MAX(0,($BX48-2017+1)/($BX48-$BW48+1))),"") -> 0.125 | Y48: =IF(AND(ISNUMBER($BW48),ISNUMBER($BX48)),MIN(1,MAX(0,($BX48-2018+1)/($BX48-$BW48+1))),"") -> 0.0625 | Z48: =IF(AND(ISNUMBER($BW48),ISNUMBER($BX48)),MIN(1,MAX(0,($BX48-2019+1)/($BX48-$BW48+1))),"") -> 0 | AA48: =IF(ISNUMBER($BX48),IF($BX48>=2017,1,0),"") -> 1 | AB48: =IF(ISNUMBER($BX48),IF($BX48>=2018,1,0),"") -> 1 | AC48: =IF(ISNUMBER($BX48),IF($BX48>=2019,1,0),"") -> 0 | AD48: =IF($L48<>"",IF($L48>2013,1,0),"") -> 0 | AE48: =IF($L48<>"",1+IF($L48>2011,1,0)+IF($L48>2014,1,0),"") -> 1 | AF48: loan (interest rate) | AG48: performance | AH48: non-sensitive | AI48: 99_NCE | AJ48: 99_NCE | AK48: =IF(AND($CF48<>"",IFERROR(INDEX(subsample_country_map!$B:$B,MATCH($CF48,subsample_country_map!$A:$A,0)),"")<>""),INDEX(subsample_country_map!$B:$B,MATCH($CF48,subsample_country_map!$A:$A,0)),INDEX(lookup!$AA:$AA,MATCH($A48,lookup!$A:$A,0))) -> 3_AsiaPac | AL48: =IF(AND($CF48<>"",IFERROR(INDEX(subsample_country_map!$C:$C,MATCH($CF48,subsample_country_map!$A:$A,0)),"")<>""),INDEX(subsample_country_map!$C:$C,MATCH($CF48,subsample_country_map!$A:$A,0)),INDEX(lookup!$AB:$AB,MATCH($A48,lookup!$A:$A,0))) -> 99_NCE | AM48: =IF(AND($CF48<>"",IFERROR(INDEX(subsample_country_map!$D:$D,MATCH($CF48,subsample_country_map!$A:$A,0)),"")<>""),INDEX(subsample_country_map!$D:$D,MATCH($CF48,subsample_country_map!$A:$A,0)),INDEX(lookup!$AC:$AC,MATCH($A48,lookup!$A:$A,0))) -> 99_NCE | AN48: =IF(AND($CF48<>"",IFERROR(INDEX(subsample_country_map!$E:$E,MATCH($CF48,subsample_country_map!$A:$A,0)),"")<>""),INDEX(subsample_country_map!$E:$E,MATCH($CF48,subsample_country_map!$A:$A,0)),INDEX(lookup!$AD:$AD,MATCH($A48,lookup!$A:$A,0))) -> 99_NCE | AO48: =INDEX(lookup!$Y:$Y,MATCH($A48,lookup!$A:$A,0)) -> 0_published | AP48: =INDEX(lookup!$Z:$Z,MATCH($A48,lookup!$A:$A,0)) -> 1_VHB high | AQ48: =INDEX(lookup!$W:$W,MATCH($A48,lookup!$A:$A,0)) -> 1_fin/acc/econ | AS48: staging | AT48: good-CER | AU48: cost | AV48: -0.077 | AX48: -2.87 | BA48: 725 | BB48: 0 | BC48: OLS | BD48: not stated | BE48: region | BF48: Excluding top three countries | BI48: Table 8 | BJ48: Panel F col 3 | BK48: 12 | BL48: CCP3 -0.077*** (-2.87) | BM48: CCP3 | BN48: COD | BO48: update | BP48: Al-Fakir Al Rabab'a et al (2023) | BQ48: computed | BT48: 0 | BU48: staging_Al-Fakir_Al_Rababa_et_al_2023.csv | BW48: 2003 | BX48: 2018 | BY48: multi: 14 Asia-Pacific countries (Australia, China, Hong Kong, India, Indonesia, Japan, Malaysia, New Zealand, Philippines, Singapore, South Korea, Sri Lanka, Taiwan, Thailand) | BZ48: 2010.5 | CA48: 0.1875 | CB48: 0 | CC48: 1 | CD48: -0.10638832 | CE48: 1
A49: Al-Fakir Al Rabab'a et al (2023) | B49: 1354 | C49: -0.083272671 | D49: 725 | E49: =IF(ISNUMBER($BA49),$BA49,IF(AND(ISNUMBER($D49),ISNUMBER($BW49),ISNUMBER($BX49)),$D49*($BX49-$BW49+1),"")) -> 725 | H49: partial | I49: T-Statistic available | J49: =IF($BW49<>"",$BW49,"") -> 2003 | K49: =IF($BX49<>"",$BX49,"") -> 2018 | L49: =IF(AND(ISNUMBER($BW49),ISNUMBER($BX49)),($BW49+$BX49)/2,"") -> 2010.5 | M49: =IF($L49<>"",$L49,"") -> 2010.5 | N49: =IF(AND(ISNUMBER($BW49),ISNUMBER($BX49)),MIN(1,MAX(0,($BX49-2016+1)/($BX49-$BW49+1))),"") -> 0.1875 | O49: =IF(AND(ISNUMBER($BW49),ISNUMBER($BX49)),MIN(1,MAX(0,($BX49-2017+1)/($BX49-$BW49+1))),"") -> 0.125 | P49: =IF(AND(ISNUMBER($BW49),ISNUMBER($BX49)),MIN(1,MAX(0,($BX49-2018+1)/($BX49-$BW49+1))),"") -> 0.0625 | Q49: =IF(AND(ISNUMBER($BW49),ISNUMBER($BX49)),MIN(1,MAX(0,($BX49-2019+1)/($BX49-$BW49+1))),"") -> 0 | R49: =IF(AND(ISNUMBER($BW49),ISNUMBER($BX49)),MIN(1,MAX(0,($BX49-2016+1)/($BX49-$BW49+1))),"") -> 0.1875 | S49: =IF($L49<>"",IF($L49>=2015.5,1,0),"") -> 0 | T49: =IF($L49<>"",IF($L49>=2016,1,0),"") -> 0 | U49: =IF(ISNUMBER($BX49),IF($BX49>=2016,1,0),"") -> 1 | V49: =IF(ISNUMBER($BW49),IF($BW49>=2016,1,0),"") -> 0 | W49: =IF(AND(ISNUMBER($BW49),ISNUMBER($BX49)),IF($BW49>=2016,"post-only",IF($BX49<2016,"pre-only","mixed")),"") -> mixed | X49: =IF(AND(ISNUMBER($BW49),ISNUMBER($BX49)),MIN(1,MAX(0,($BX49-2017+1)/($BX49-$BW49+1))),"") -> 0.125 | Y49: =IF(AND(ISNUMBER($BW49),ISNUMBER($BX49)),MIN(1,MAX(0,($BX49-2018+1)/($BX49-$BW49+1))),"") -> 0.0625 | Z49: =IF(AND(ISNUMBER($BW49),ISNUMBER($BX49)),MIN(1,MAX(0,($BX49-2019+1)/($BX49-$BW49+1))),"") -> 0 | AA49: =IF(ISNUMBER($BX49),IF($BX49>=2017,1,0),"") -> 1 | AB49: =IF(ISNUMBER($BX49),IF($BX49>=2018,1,0),"") -> 1 | AC49: =IF(ISNUMBER($BX49),IF($BX49>=2019,1,0),"") -> 0 | AD49: =IF($L49<>"",IF($L49>2013,1,0),"") -> 0 | AE49: =IF($L49<>"",1+IF($L49>2011,1,0)+IF($L49>2014,1,0),"") -> 1 | AF49: loan (interest rate) | AG49: performance | AH49: non-sensitive | AI49: 99_NCE | AJ49: 99_NCE | AK49: =IF(AND($CF49<>"",IFERROR(INDEX(subsample_country_map!$B:$B,MATCH($CF49,subsample_country_map!$A:$A,0)),"")<>""),INDEX(subsample_country_map!$B:$B,MATCH($CF49,subsample_country_map!$A:$A,0)),INDEX(lookup!$AA:$AA,MATCH($A49,lookup!$A:$A,0))) -> 3_AsiaPac | AL49: =IF(AND($CF49<>"",IFERROR(INDEX(subsample_country_map!$C:$C,MATCH($CF49,subsample_country_map!$A:$A,0)),"")<>""),INDEX(subsample_country_map!$C:$C,MATCH($CF49,subsample_country_map!$A:$A,0)),INDEX(lookup!$AB:$AB,MATCH($A49,lookup!$A:$A,0))) -> 99_NCE | AM49: =IF(AND($CF49<>"",IFERROR(INDEX(subsample_country_map!$D:$D,MATCH($CF49,subsample_country_map!$A:$A,0)),"")<>""),INDEX(subsample_country_map!$D:$D,MATCH($CF49,subsample_country_map!$A:$A,0)),INDEX(lookup!$AC:$AC,MATCH($A49,lookup!$A:$A,0))) -> 99_NCE | AN49: =IF(AND($CF49<>"",IFERROR(INDEX(subsample_country_map!$E:$E,MATCH($CF49,subsample_country_map!$A:$A,0)),"")<>""),INDEX(subsample_country_map!$E:$E,MATCH($CF49,subsample_country_map!$A:$A,0)),INDEX(lookup!$AD:$AD,MATCH($A49,lookup!$A:$A,0))) -> 99_NCE | AO49: =INDEX(lookup!$Y:$Y,MATCH($A49,lookup!$A:$A,0)) -> 0_published | AP49: =INDEX(lookup!$Z:$Z,MATCH($A49,lookup!$A:$A,0)) -> 1_VHB high | AQ49: =INDEX(lookup!$W:$W,MATCH($A49,lookup!$A:$A,0)) -> 1_fin/acc/econ | AS49: staging | AT49: good-CER | AU49: cost | AV49: -0.098 | AX49: -2.25 | BA49: 725 | BB49: 0 | BC49: OLS | BD49: not stated | BE49: region | BF49: Excluding top three countries | BI49: Table 8 | BJ49: Panel F col 4 | BK49: 12 | BL49: CCP4 -0.098** (-2.25) | BM49: CCP4 | BN49: COD | BO49: update | BP49: Al-Fakir Al Rabab'a et al (2023) | BQ49: computed | BT49: 0 | BU49: staging_Al-Fakir_Al_Rababa_et_al_2023.csv | BW49: 2003 | BX49: 2018 | BY49: multi: 14 Asia-Pacific countries (Australia, China, Hong Kong, India, Indonesia, Japan, Malaysia, New Zealand, Philippines, Singapore, South Korea, Sri Lanka, Taiwan, Thailand) | BZ49: 2010.5 | CA49: 0.1875 | CB49: 0 | CC49: 1 | CD49: -0.083465957 | CE49: 1
A50: Al-Fakir Al Rabab'a et al (2023) | B50: 1355 | C50: -0.075791925 | D50: 3599 | E50: =IF(ISNUMBER($BA50),$BA50,IF(AND(ISNUMBER($D50),ISNUMBER($BW50),ISNUMBER($BX50)),$D50*($BX50-$BW50+1),"")) -> 3599 | H50: partial | I50: T-Statistic available | J50: =IF($BW50<>"",$BW50,"") -> 2003 | K50: =IF($BX50<>"",$BX50,"") -> 2018 | L50: =IF(AND(ISNUMBER($BW50),ISNUMBER($BX50)),($BW50+$BX50)/2,"") -> 2010.5 | M50: =IF($L50<>"",$L50,"") -> 2010.5 | N50: =IF(AND(ISNUMBER($BW50),ISNUMBER($BX50)),MIN(1,MAX(0,($BX50-2016+1)/($BX50-$BW50+1))),"") -> 0.1875 | O50: =IF(AND(ISNUMBER($BW50),ISNUMBER($BX50)),MIN(1,MAX(0,($BX50-2017+1)/($BX50-$BW50+1))),"") -> 0.125 | P50: =IF(AND(ISNUMBER($BW50),ISNUMBER($BX50)),MIN(1,MAX(0,($BX50-2018+1)/($BX50-$BW50+1))),"") -> 0.0625 | Q50: =IF(AND(ISNUMBER($BW50),ISNUMBER($BX50)),MIN(1,MAX(0,($BX50-2019+1)/($BX50-$BW50+1))),"") -> 0 | R50: =IF(AND(ISNUMBER($BW50),ISNUMBER($BX50)),MIN(1,MAX(0,($BX50-2016+1)/($BX50-$BW50+1))),"") -> 0.1875 | S50: =IF($L50<>"",IF($L50>=2015.5,1,0),"") -> 0 | T50: =IF($L50<>"",IF($L50>=2016,1,0),"") -> 0 | U50: =IF(ISNUMBER($BX50),IF($BX50>=2016,1,0),"") -> 1 | V50: =IF(ISNUMBER($BW50),IF($BW50>=2016,1,0),"") -> 0 | W50: =IF(AND(ISNUMBER($BW50),ISNUMBER($BX50)),IF($BW50>=2016,"post-only",IF($BX50<2016,"pre-only","mixed")),"") -> mixed | X50: =IF(AND(ISNUMBER($BW50),ISNUMBER($BX50)),MIN(1,MAX(0,($BX50-2017+1)/($BX50-$BW50+1))),"") -> 0.125 | Y50: =IF(AND(ISNUMBER($BW50),ISNUMBER($BX50)),MIN(1,MAX(0,($BX50-2018+1)/($BX50-$BW50+1))),"") -> 0.0625 | Z50: =IF(AND(ISNUMBER($BW50),ISNUMBER($BX50)),MIN(1,MAX(0,($BX50-2019+1)/($BX50-$BW50+1))),"") -> 0 | AA50: =IF(ISNUMBER($BX50),IF($BX50>=2017,1,0),"") -> 1 | AB50: =IF(ISNUMBER($BX50),IF($BX50>=2018,1,0),"") -> 1 | AC50: =IF(ISNUMBER($BX50),IF($BX50>=2019,1,0),"") -> 0 | AD50: =IF($L50<>"",IF($L50>2013,1,0),"") -> 0 | AE50: =IF($L50<>"",1+IF($L50>2011,1,0)+IF($L50>2014,1,0),"") -> 1 | AF50: loan (interest rate) | AG50: performance | AH50: non-sensitive | AI50: 99_NCE | AJ50: 99_NCE | AK50: =IF(AND($CF50<>"",IFERROR(INDEX(subsample_country_map!$B:$B,MATCH($CF50,subsample_country_map!$A:$A,0)),"")<>""),INDEX(subsample_country_map!$B:$B,MATCH($CF50,subsample_country_map!$A:$A,0)),INDEX(lookup!$AA:$AA,MATCH($A50,lookup!$A:$A,0))) -> 3_AsiaPac | AL50: =IF(AND($CF50<>"",IFERROR(INDEX(subsample_country_map!$C:$C,MATCH($CF50,subsample_country_map!$A:$A,0)),"")<>""),INDEX(subsample_country_map!$C:$C,MATCH($CF50,subsample_country_map!$A:$A,0)),INDEX(lookup!$AB:$AB,MATCH($A50,lookup!$A:$A,0))) -> 99_NCE | AM50: =IF(AND($CF50<>"",IFERROR(INDEX(subsample_country_map!$D:$D,MATCH($CF50,subsample_country_map!$A:$A,0)),"")<>""),INDEX(subsample_country_map!$D:$D,MATCH($CF50,subsample_country_map!$A:$A,0)),INDEX(lookup!$AC:$AC,MATCH($A50,lookup!$A:$A,0))) -> 99_NCE | AN50: =IF(AND($CF50<>"",IFERROR(INDEX(subsample_country_map!$E:$E,MATCH($CF50,subsample_country_map!$A:$A,0)),"")<>""),INDEX(subsample_country_map!$E:$E,MATCH($CF50,subsample_country_map!$A:$A,0)),INDEX(lookup!$AD:$AD,MATCH($A50,lookup!$A:$A,0))) -> 99_NCE | AO50: =INDEX(lookup!$Y:$Y,MATCH($A50,lookup!$A:$A,0)) -> 0_published | AP50: =INDEX(lookup!$Z:$Z,MATCH($A50,lookup!$A:$A,0)) -> 1_VHB high | AQ50: =INDEX(lookup!$W:$W,MATCH($A50,lookup!$A:$A,0)) -> 1_fin/acc/econ | AS50: staging | AT50: author-inverted-to-good | AU50: cost | AV50: -0.122 | AX50: -4.56 | BA50: 3599 | BB50: 0 | BC50: OLS | BD50: not stated | BE50: region | BF50: Excluding bottom five countries | BI50: Table 8 | BJ50: Panel G col 1 | BK50: 12 | BL50: CCP1 -0.122*** (-4.56) | BM50: CCP1 | BN50: COD | BO50: update | BP50: Al-Fakir Al Rabab'a et al (2023) | BQ50: computed | BT50: 0 | BU50: staging_Al-Fakir_Al_Rababa_et_al_2023.csv | BW50: 2003 | BX50: 2018 | BY50: multi: 14 Asia-Pacific countries (Australia, China, Hong Kong, India, Indonesia, Japan, Malaysia, New Zealand, Philippines, Singapore, South Korea, Sri Lanka, Taiwan, Thailand) | BZ50: 2010.5 | CA50: 0.1875 | CB50: 0 | CC50: 1 | CD50: -0.075937554 | CE50: 1
A51: Al-Fakir Al Rabab'a et al (2023) | B51: 1356 | C51: -0.065865829 | D51: 3599 | E51: =IF(ISNUMBER($BA51),$BA51,IF(AND(ISNUMBER($D51),ISNUMBER($BW51),ISNUMBER($BX51)),$D51*($BX51-$BW51+1),"")) -> 3599 | H51: partial | I51: T-Statistic available | J51: =IF($BW51<>"",$BW51,"") -> 2003 | K51: =IF($BX51<>"",$BX51,"") -> 2018 | L51: =IF(AND(ISNUMBER($BW51),ISNUMBER($BX51)),($BW51+$BX51)/2,"") -> 2010.5 | M51: =IF($L51<>"",$L51,"") -> 2010.5 | N51: =IF(AND(ISNUMBER($BW51),ISNUMBER($BX51)),MIN(1,MAX(0,($BX51-2016+1)/($BX51-$BW51+1))),"") -> 0.1875 | O51: =IF(AND(ISNUMBER($BW51),ISNUMBER($BX51)),MIN(1,MAX(0,($BX51-2017+1)/($BX51-$BW51+1))),"") -> 0.125 | P51: =IF(AND(ISNUMBER($BW51),ISNUMBER($BX51)),MIN(1,MAX(0,($BX51-2018+1)/($BX51-$BW51+1))),"") -> 0.0625 | Q51: =IF(AND(ISNUMBER($BW51),ISNUMBER($BX51)),MIN(1,MAX(0,($BX51-2019+1)/($BX51-$BW51+1))),"") -> 0 | R51: =IF(AND(ISNUMBER($BW51),ISNUMBER($BX51)),MIN(1,MAX(0,($BX51-2016+1)/($BX51-$BW51+1))),"") -> 0.1875 | S51: =IF($L51<>"",IF($L51>=2015.5,1,0),"") -> 0 | T51: =IF($L51<>"",IF($L51>=2016,1,0),"") -> 0 | U51: =IF(ISNUMBER($BX51),IF($BX51>=2016,1,0),"") -> 1 | V51: =IF(ISNUMBER($BW51),IF($BW51>=2016,1,0),"") -> 0 | W51: =IF(AND(ISNUMBER($BW51),ISNUMBER($BX51)),IF($BW51>=2016,"post-only",IF($BX51<2016,"pre-only","mixed")),"") -> mixed | X51: =IF(AND(ISNUMBER($BW51),ISNUMBER($BX51)),MIN(1,MAX(0,($BX51-2017+1)/($BX51-$BW51+1))),"") -> 0.125 | Y51: =IF(AND(ISNUMBER($BW51),ISNUMBER($BX51)),MIN(1,MAX(0,($BX51-2018+1)/($BX51-$BW51+1))),"") -> 0.0625 | Z51: =IF(AND(ISNUMBER($BW51),ISNUMBER($BX51)),MIN(1,MAX(0,($BX51-2019+1)/($BX51-$BW51+1))),"") -> 0 | AA51: =IF(ISNUMBER($BX51),IF($BX51>=2017,1,0),"") -> 1 | AB51: =IF(ISNUMBER($BX51),IF($BX51>=2018,1,0),"") -> 1 | AC51: =IF(ISNUMBER($BX51),IF($BX51>=2019,1,0),"") -> 0 | AD51: =IF($L51<>"",IF($L51>2013,1,0),"") -> 0 | AE51: =IF($L51<>"",1+IF($L51>2011,1,0)+IF($L51>2014,1,0),"") -> 1 | AF51: loan (interest rate) | AG51: performance | AH51: non-sensitive | AI51: 99_NCE | AJ51: 99_NCE | AK51: =IF(AND($CF51<>"",IFERROR(INDEX(subsample_country_map!$B:$B,MATCH($CF51,subsample_country_map!$A:$A,0)),"")<>""),INDEX(subsample_country_map!$B:$B,MATCH($CF51,subsample_country_map!$A:$A,0)),INDEX(lookup!$AA:$AA,MATCH($A51,lookup!$A:$A,0))) -> 3_AsiaPac | AL51: =IF(AND($CF51<>"",IFERROR(INDEX(subsample_country_map!$C:$C,MATCH($CF51,subsample_country_map!$A:$A,0)),"")<>""),INDEX(subsample_country_map!$C:$C,MATCH($CF51,subsample_country_map!$A:$A,0)),INDEX(lookup!$AB:$AB,MATCH($A51,lookup!$A:$A,0))) -> 99_NCE | AM51: =IF(AND($CF51<>"",IFERROR(INDEX(subsample_country_map!$D:$D,MATCH($CF51,subsample_country_map!$A:$A,0)),"")<>""),INDEX(subsample_country_map!$D:$D,MATCH($CF51,subsample_country_map!$A:$A,0)),INDEX(lookup!$AC:$AC,MATCH($A51,lookup!$A:$A,0))) -> 99_NCE | AN51: =IF(AND($CF51<>"",IFERROR(INDEX(subsample_country_map!$E:$E,MATCH($CF51,subsample_country_map!$A:$A,0)),"")<>""),INDEX(subsample_country_map!$E:$E,MATCH($CF51,subsample_country_map!$A:$A,0)),INDEX(lookup!$AD:$AD,MATCH($A51,lookup!$A:$A,0))) -> 99_NCE | AO51: =INDEX(lookup!$Y:$Y,MATCH($A51,lookup!$A:$A,0)) -> 0_published | AP51: =INDEX(lookup!$Z:$Z,MATCH($A51,lookup!$A:$A,0)) -> 1_VHB high | AQ51: =INDEX(lookup!$W:$W,MATCH($A51,lookup!$A:$A,0)) -> 1_fin/acc/econ | AS51: staging | AT51: author-inverted-to-good | AU51: cost | AV51: -0.085 | AX51: -3.96 | BA51: 3599 | BB51: 0 | BC51: OLS | BD51: not stated | BE51: region | BF51: Excluding bottom five countries | BI51: Table 8 | BJ51: Panel G col 2 | BK51: 12 | BL51: CCP2 -0.085*** (-3.96) | BM51: CCP2 | BN51: COD | BO51: update | BP51: Al-Fakir Al Rabab'a et al (2023) | BQ51: computed | BT51: 0 | BU51: staging_Al-Fakir_Al_Rababa_et_al_2023.csv | BW51: 2003 | BX51: 2018 | BY51: multi: 14 Asia-Pacific countries (Australia, China, Hong Kong, India, Indonesia, Japan, Malaysia, New Zealand, Philippines, Singapore, South Korea, Sri Lanka, Taiwan, Thailand) | BZ51: 2010.5 | CA51: 0.1875 | CB51: 0 | CC51: 1 | CD51: -0.065961326 | CE51: 1
A52: Al-Fakir Al Rabab'a et al (2023) | B52: 1357 | C52: -0.036813479 | D52: 3599 | E52: =IF(ISNUMBER($BA52),$BA52,IF(AND(ISNUMBER($D52),ISNUMBER($BW52),ISNUMBER($BX52)),$D52*($BX52-$BW52+1),"")) -> 3599 | H52: partial | I52: T-Statistic available | J52: =IF($BW52<>"",$BW52,"") -> 2003 | K52: =IF($BX52<>"",$BX52,"") -> 2018 | L52: =IF(AND(ISNUMBER($BW52),ISNUMBER($BX52)),($BW52+$BX52)/2,"") -> 2010.5 | M52: =IF($L52<>"",$L52,"") -> 2010.5 | N52: =IF(AND(ISNUMBER($BW52),ISNUMBER($BX52)),MIN(1,MAX(0,($BX52-2016+1)/($BX52-$BW52+1))),"") -> 0.1875 | O52: =IF(AND(ISNUMBER($BW52),ISNUMBER($BX52)),MIN(1,MAX(0,($BX52-2017+1)/($BX52-$BW52+1))),"") -> 0.125 | P52: =IF(AND(ISNUMBER($BW52),ISNUMBER($BX52)),MIN(1,MAX(0,($BX52-2018+1)/($BX52-$BW52+1))),"") -> 0.0625 | Q52: =IF(AND(ISNUMBER($BW52),ISNUMBER($BX52)),MIN(1,MAX(0,($BX52-2019+1)/($BX52-$BW52+1))),"") -> 0 | R52: =IF(AND(ISNUMBER($BW52),ISNUMBER($BX52)),MIN(1,MAX(0,($BX52-2016+1)/($BX52-$BW52+1))),"") -> 0.1875 | S52: =IF($L52<>"",IF($L52>=2015.5,1,0),"") -> 0 | T52: =IF($L52<>"",IF($L52>=2016,1,0),"") -> 0 | U52: =IF(ISNUMBER($BX52),IF($BX52>=2016,1,0),"") -> 1 | V52: =IF(ISNUMBER($BW52),IF($BW52>=2016,1,0),"") -> 0 | W52: =IF(AND(ISNUMBER($BW52),ISNUMBER($BX52)),IF($BW52>=2016,"post-only",IF($BX52<2016,"pre-only","mixed")),"") -> mixed | X52: =IF(AND(ISNUMBER($BW52),ISNUMBER($BX52)),MIN(1,MAX(0,($BX52-2017+1)/($BX52-$BW52+1))),"") -> 0.125 | Y52: =IF(AND(ISNUMBER($BW52),ISNUMBER($BX52)),MIN(1,MAX(0,($BX52-2018+1)/($BX52-$BW52+1))),"") -> 0.0625 | Z52: =IF(AND(ISNUMBER($BW52),ISNUMBER($BX52)),MIN(1,MAX(0,($BX52-2019+1)/($BX52-$BW52+1))),"") -> 0 | AA52: =IF(ISNUMBER($BX52),IF($BX52>=2017,1,0),"") -> 1 | AB52: =IF(ISNUMBER($BX52),IF($BX52>=2018,1,0),"") -> 1 | AC52: =IF(ISNUMBER($BX52),IF($BX52>=2019,1,0),"") -> 0 | AD52: =IF($L52<>"",IF($L52>2013,1,0),"") -> 0 | AE52: =IF($L52<>"",1+IF($L52>2011,1,0)+IF($L52>2014,1,0),"") -> 1 | AF52: loan (interest rate) | AG52: performance | AH52: non-sensitive | AI52: 99_NCE | AJ52: 99_NCE | AK52: =IF(AND($CF52<>"",IFERROR(INDEX(subsample_country_map!$B:$B,MATCH($CF52,subsample_country_map!$A:$A,0)),"")<>""),INDEX(subsample_country_map!$B:$B,MATCH($CF52,subsample_country_map!$A:$A,0)),INDEX(lookup!$AA:$AA,MATCH($A52,lookup!$A:$A,0))) -> 3_AsiaPac | AL52: =IF(AND($CF52<>"",IFERROR(INDEX(subsample_country_map!$C:$C,MATCH($CF52,subsample_country_map!$A:$A,0)),"")<>""),INDEX(subsample_country_map!$C:$C,MATCH($CF52,subsample_country_map!$A:$A,0)),INDEX(lookup!$AB:$AB,MATCH($A52,lookup!$A:$A,0))) -> 99_NCE | AM52: =IF(AND($CF52<>"",IFERROR(INDEX(subsample_country_map!$D:$D,MATCH($CF52,subsample_country_map!$A:$A,0)),"")<>""),INDEX(subsample_country_map!$D:$D,MATCH($CF52,subsample_country_map!$A:$A,0)),INDEX(lookup!$AC:$AC,MATCH($A52,lookup!$A:$A,0))) -> 99_NCE | AN52: =IF(AND($CF52<>"",IFERROR(INDEX(subsample_country_map!$E:$E,MATCH($CF52,subsample_country_map!$A:$A,0)),"")<>""),INDEX(subsample_country_map!$E:$E,MATCH($CF52,subsample_country_map!$A:$A,0)),INDEX(lookup!$AD:$AD,MATCH($A52,lookup!$A:$A,0))) -> 99_NCE | AO52: =INDEX(lookup!$Y:$Y,MATCH($A52,lookup!$A:$A,0)) -> 0_published | AP52: =INDEX(lookup!$Z:$Z,MATCH($A52,lookup!$A:$A,0)) -> 1_VHB high | AQ52: =INDEX(lookup!$W:$W,MATCH($A52,lookup!$A:$A,0)) -> 1_fin/acc/econ | AS52: staging | AT52: good-CER | AU52: cost | AV52: -0.022 | AX52: -2.21 | BA52: 3599 | BB52: 0 | BC52: OLS | BD52: not stated | BE52: region | BF52: Excluding bottom five countries | BI52: Table 8 | BJ52: Panel G col 3 | BK52: 12 | BL52: CCP3 -0.022** (-2.21) | BM52: CCP3 | BN52: COD | BO52: update | BP52: Al-Fakir Al Rabab'a et al (2023) | BQ52: computed | BT52: 0 | BU52: staging_Al-Fakir_Al_Rababa_et_al_2023.csv | BW52: 2003 | BX52: 2018 | BY52: multi: 14 Asia-Pacific countries (Australia, China, Hong Kong, India, Indonesia, Japan, Malaysia, New Zealand, Philippines, Singapore, South Korea, Sri Lanka, Taiwan, Thailand) | BZ52: 2010.5 | CA52: 0.1875 | CB52: 0 | CC52: 1 | CD52: -0.036830123 | CE52: 1
A53: Al-Fakir Al Rabab'a et al (2023) | B53: 1358 | C53: -0.044628362 | D53: 3599 | E53: =IF(ISNUMBER($BA53),$BA53,IF(AND(ISNUMBER($D53),ISNUMBER($BW53),ISNUMBER($BX53)),$D53*($BX53-$BW53+1),"")) -> 3599 | H53: partial | I53: T-Statistic available | J53: =IF($BW53<>"",$BW53,"") -> 2003 | K53: =IF($BX53<>"",$BX53,"") -> 2018 | L53: =IF(AND(ISNUMBER($BW53),ISNUMBER($BX53)),($BW53+$BX53)/2,"") -> 2010.5 | M53: =IF($L53<>"",$L53,"") -> 2010.5 | N53: =IF(AND(ISNUMBER($BW53),ISNUMBER($BX53)),MIN(1,MAX(0,($BX53-2016+1)/($BX53-$BW53+1))),"") -> 0.1875 | O53: =IF(AND(ISNUMBER($BW53),ISNUMBER($BX53)),MIN(1,MAX(0,($BX53-2017+1)/($BX53-$BW53+1))),"") -> 0.125 | P53: =IF(AND(ISNUMBER($BW53),ISNUMBER($BX53)),MIN(1,MAX(0,($BX53-2018+1)/($BX53-$BW53+1))),"") -> 0.0625 | Q53: =IF(AND(ISNUMBER($BW53),ISNUMBER($BX53)),MIN(1,MAX(0,($BX53-2019+1)/($BX53-$BW53+1))),"") -> 0 | R53: =IF(AND(ISNUMBER($BW53),ISNUMBER($BX53)),MIN(1,MAX(0,($BX53-2016+1)/($BX53-$BW53+1))),"") -> 0.1875 | S53: =IF($L53<>"",IF($L53>=2015.5,1,0),"") -> 0 | T53: =IF($L53<>"",IF($L53>=2016,1,0),"") -> 0 | U53: =IF(ISNUMBER($BX53),IF($BX53>=2016,1,0),"") -> 1 | V53: =IF(ISNUMBER($BW53),IF($BW53>=2016,1,0),"") -> 0 | W53: =IF(AND(ISNUMBER($BW53),ISNUMBER($BX53)),IF($BW53>=2016,"post-only",IF($BX53<2016,"pre-only","mixed")),"") -> mixed | X53: =IF(AND(ISNUMBER($BW53),ISNUMBER($BX53)),MIN(1,MAX(0,($BX53-2017+1)/($BX53-$BW53+1))),"") -> 0.125 | Y53: =IF(AND(ISNUMBER($BW53),ISNUMBER($BX53)),MIN(1,MAX(0,($BX53-2018+1)/($BX53-$BW53+1))),"") -> 0.0625 | Z53: =IF(AND(ISNUMBER($BW53),ISNUMBER($BX53)),MIN(1,MAX(0,($BX53-2019+1)/($BX53-$BW53+1))),"") -> 0 | AA53: =IF(ISNUMBER($BX53),IF($BX53>=2017,1,0),"") -> 1 | AB53: =IF(ISNUMBER($BX53),IF($BX53>=2018,1,0),"") -> 1 | AC53: =IF(ISNUMBER($BX53),IF($BX53>=2019,1,0),"") -> 0 | AD53: =IF($L53<>"",IF($L53>2013,1,0),"") -> 0 | AE53: =IF($L53<>"",1+IF($L53>2011,1,0)+IF($L53>2014,1,0),"") -> 1 | AF53: loan (interest rate) | AG53: performance | AH53: non-sensitive | AI53: 99_NCE | AJ53: 99_NCE | AK53: =IF(AND($CF53<>"",IFERROR(INDEX(subsample_country_map!$B:$B,MATCH($CF53,subsample_country_map!$A:$A,0)),"")<>""),INDEX(subsample_country_map!$B:$B,MATCH($CF53,subsample_country_map!$A:$A,0)),INDEX(lookup!$AA:$AA,MATCH($A53,lookup!$A:$A,0))) -> 3_AsiaPac | AL53: =IF(AND($CF53<>"",IFERROR(INDEX(subsample_country_map!$C:$C,MATCH($CF53,subsample_country_map!$A:$A,0)),"")<>""),INDEX(subsample_country_map!$C:$C,MATCH($CF53,subsample_country_map!$A:$A,0)),INDEX(lookup!$AB:$AB,MATCH($A53,lookup!$A:$A,0))) -> 99_NCE | AM53: =IF(AND($CF53<>"",IFERROR(INDEX(subsample_country_map!$D:$D,MATCH($CF53,subsample_country_map!$A:$A,0)),"")<>""),INDEX(subsample_country_map!$D:$D,MATCH($CF53,subsample_country_map!$A:$A,0)),INDEX(lookup!$AC:$AC,MATCH($A53,lookup!$A:$A,0))) -> 99_NCE | AN53: =IF(AND($CF53<>"",IFERROR(INDEX(subsample_country_map!$E:$E,MATCH($CF53,subsample_country_map!$A:$A,0)),"")<>""),INDEX(subsample_country_map!$E:$E,MATCH($CF53,subsample_country_map!$A:$A,0)),INDEX(lookup!$AD:$AD,MATCH($A53,lookup!$A:$A,0))) -> 99_NCE | AO53: =INDEX(lookup!$Y:$Y,MATCH($A53,lookup!$A:$A,0)) -> 0_published | AP53: =INDEX(lookup!$Z:$Z,MATCH($A53,lookup!$A:$A,0)) -> 1_VHB high | AQ53: =INDEX(lookup!$W:$W,MATCH($A53,lookup!$A:$A,0)) -> 1_fin/acc/econ | AS53: staging | AT53: good-CER | AU53: cost | AV53: -0.041 | AX53: -2.68 | BA53: 3599 | BB53: 0 | BC53: OLS | BD53: not stated | BE53: region | BF53: Excluding bottom five countries | BI53: Table 8 | BJ53: Panel G col 4 | BK53: 12 | BL53: CCP4 -0.041*** (-2.68) | BM53: CCP4 | BN53: COD | BO53: update | BP53: Al-Fakir Al Rabab'a et al (2023) | BQ53: computed | BT53: 0 | BU53: staging_Al-Fakir_Al_Rababa_et_al_2023.csv | BW53: 2003 | BX53: 2018 | BY53: multi: 14 Asia-Pacific countries (Australia, China, Hong Kong, India, Indonesia, Japan, Malaysia, New Zealand, Philippines, Singapore, South Korea, Sri Lanka, Taiwan, Thailand) | BZ53: 2010.5 | CA53: 0.1875 | CB53: 0 | CC53: 1 | CD53: -0.044658026 | CE53: 1
... A57: Al-Fakir Al Rabab'a et al (2023) | B57: 1362 | C57: -0.08344876 | D57: 870 | E57: =IF(ISNUMBER($BA57),$BA57,IF(AND(ISNUMBER($D57),ISNUMBER($BW57),ISNUMBER($BX57)),$D57*($BX57-$BW57+1),"")) -> 870 | H57: partial | I57: T-Statistic available | J57: =IF($BW57<>"",$BW57,"") -> 2003 | K57: =IF($BX57<>"",$BX57,"") -> 2018 | L57: =IF(AND(ISNUMBER($BW57),ISNUMBER($BX57)),($BW57+$BX57)/2,"") -> 2010.5 | M57: =IF($L57<>"",$L57,"") -> 2010.5 | N57: =IF(AND(ISNUMBER($BW57),ISNUMBER($BX57)),MIN(1,MAX(0,($BX57-2016+1)/($BX57-$BW57+1))),"") -> 0.1875 | O57: =IF(AND(ISNUMBER($BW57),ISNUMBER($BX57)),MIN(1,MAX(0,($BX57-2017+1)/($BX57-$BW57+1))),"") -> 0.125 | P57: =IF(AND(ISNUMBER($BW57),ISNUMBER($BX57)),MIN(1,MAX(0,($BX57-2018+1)/($BX57-$BW57+1))),"") -> 0.0625 | Q57: =IF(AND(ISNUMBER($BW57),ISNUMBER($BX57)),MIN(1,MAX(0,($BX57-2019+1)/($BX57-$BW57+1))),"") -> 0 | R57: =IF(AND(ISNUMBER($BW57),ISNUMBER($BX57)),MIN(1,MAX(0,($BX57-2016+1)/($BX57-$BW57+1))),"") -> 0.1875 | S57: =IF($L57<>"",IF($L57>=2015.5,1,0),"") -> 0 | T57: =IF($L57<>"",IF($L57>=2016,1,0),"") -> 0 | U57: =IF(ISNUMBER($BX57),IF($BX57>=2016,1,0),"") -> 1 | V57: =IF(ISNUMBER($BW57),IF($BW57>=2016,1,0),"") -> 0 | W57: =IF(AND(ISNUMBER($BW57),ISNUMBER($BX57)),IF($BW57>=2016,"post-only",IF($BX57<2016,"pre-only","mixed")),"") -> mixed | X57: =IF(AND(ISNUMBER($BW57),ISNUMBER($BX57)),MIN(1,MAX(0,($BX57-2017+1)/($BX57-$BW57+1))),"") -> 0.125 | Y57: =IF(AND(ISNUMBER($BW57),ISNUMBER($BX57)),MIN(1,MAX(0,($BX57-2018+1)/($BX57-$BW57+1))),"") -> 0.0625 | Z57: =IF(AND(ISNUMBER($BW57),ISNUMBER($BX57)),MIN(1,MAX(0,($BX57-2019+1)/($BX57-$BW57+1))),"") -> 0 | AA57: =IF(ISNUMBER($BX57),IF($BX57>=2017,1,0),"") -> 1 | AB57: =IF(ISNUMBER($BX57),IF($BX57>=2018,1,0),"") -> 1 | AC57: =IF(ISNUMBER($BX57),IF($BX57>=2019,1,0),"") -> 0 | AD57: =IF($L57<>"",IF($L57>2013,1,0),"") -> 0 | AE57: =IF($L57<>"",1+IF($L57>2011,1,0)+IF($L57>2014,1,0),"") -> 1 | AF57: rating | AG57: performance | AH57: non-sensitive | AI57: 99_NCE | AJ57: 99_NCE | AK57: =IF(AND($CF57<>"",IFERROR(INDEX(subsample_country_map!$B:$B,MATCH($CF57,subsample_country_map!$A:$A,0)),"")<>""),INDEX(subsample_country_map!$B:$B,MATCH($CF57,subsample_country_map!$A:$A,0)),INDEX(lookup!$AA:$AA,MATCH($A57,lookup!$A:$A,0))) -> 3_AsiaPac | AL57: =IF(AND($CF57<>"",IFERROR(INDEX(subsample_country_map!$C:$C,MATCH($CF57,subsample_country_map!$A:$A,0)),"")<>""),INDEX(subsample_country_map!$C:$C,MATCH($CF57,subsample_country_map!$A:$A,0)),INDEX(lookup!$AB:$AB,MATCH($A57,lookup!$A:$A,0))) -> 99_NCE | AM57: =IF(AND($CF57<>"",IFERROR(INDEX(subsample_country_map!$D:$D,MATCH($CF57,subsample_country_map!$A:$A,0)),"")<>""),INDEX(subsample_country_map!$D:$D,MATCH($CF57,subsample_country_map!$A:$A,0)),INDEX(lookup!$AC:$AC,MATCH($A57,lookup!$A:$A,0))) -> 99_NCE | AN57: =IF(AND($CF57<>"",IFERROR(INDEX(subsample_country_map!$E:$E,MATCH($CF57,subsample_country_map!$A:$A,0)),"")<>""),INDEX(subsample_country_map!$E:$E,MATCH($CF57,subsample_country_map!$A:$A,0)),INDEX(lookup!$AD:$AD,MATCH($A57,lookup!$A:$A,0))) -> 99_NCE | AO57: =INDEX(lookup!$Y:$Y,MATCH($A57,lookup!$A:$A,0)) -> 0_published | AP57: =INDEX(lookup!$Z:$Z,MATCH($A57,lookup!$A:$A,0)) -> 1_VHB high | AQ57: =INDEX(lookup!$W:$W,MATCH($A57,lookup!$A:$A,0)) -> 1_fin/acc/econ | AS57: staging | AT57: good-CER | AU57: creditworthiness | AV57: 0.220 | AX57: 2.47 | BA57: 870 | BB57: 0 | BC57: OLS | BD57: firm | BE57: other:firms with credit rating available | BF57: 12 countries where the CR variable is available | BI57: Table 9 | BJ57: col 4 | BK57: 13 | BL57: CCP4 0.220** (2.47) | BM57: CCP4 | BN57: CR | BO57: update | BP57: Al-Fakir Al Rabab'a et al (2023) | BQ57: computed | BT57: 0 | BU57: staging_Al-Fakir_Al_Rababa_et_al_2023.csv | BW57: 2003 | BX57: 2018 | BY57: multi: 14 Asia-Pacific countries (Australia, China, Hong Kong, India, Indonesia, Japan, Malaysia, New Zealand, Philippines, Singapore, South Korea, Sri Lanka, Taiwan, Thailand) | BZ57: 2010.5 | CA57: 0.1875 | CB57: 0 | CC57: 1 | CD57: -0.083643278 | CE57: 1
A58: Ali et al (2023) | B58: 1363 | C58: -0.21 | D58: 3066 | E58: =IF(ISNUMBER($BA58),$BA58,IF(AND(ISNUMBER($D58),ISNUMBER($BW58),ISNUMBER($BX58)),$D58*($BX58-$BW58+1),"")) -> 49056 | H58: bivariate | I58: Correlation coefficient available | J58: =IF($BW58<>"",$BW58,"") -> 2005 | K58: =IF($BX58<>"",$BX58,"") -> 2020 | L58: =IF(AND(ISNUMBER($BW58),ISNUMBER($BX58)),($BW58+$BX58)/2,"") -> 2012.5 | M58: =IF($L58<>"",$L58,"") -> 2012.5 | N58: =IF(AND(ISNUMBER($BW58),ISNUMBER($BX58)),MIN(1,MAX(0,($BX58-2016+1)/($BX58-$BW58+1))),"") -> 0.3125 | O58: =IF(AND(ISNUMBER($BW58),ISNUMBER($BX58)),MIN(1,MAX(0,($BX58-2017+1)/($BX58-$BW58+1))),"") -> 0.25 | P58: =IF(AND(ISNUMBER($BW58),ISNUMBER($BX58)),MIN(1,MAX(0,($BX58-2018+1)/($BX58-$BW58+1))),"") -> 0.1875 | Q58: =IF(AND(ISNUMBER($BW58),ISNUMBER($BX58)),MIN(1,MAX(0,($BX58-2019+1)/($BX58-$BW58+1))),"") -> 0.125 | R58: =IF(AND(ISNUMBER($BW58),ISNUMBER($BX58)),MIN(1,MAX(0,($BX58-2016+1)/($BX58-$BW58+1))),"") -> 0.3125 | S58: =IF($L58<>"",IF($L58>=2015.5,1,0),"") -> 0 | T58: =IF($L58<>"",IF($L58>=2016,1,0),"") -> 0 | U58: =IF(ISNUMBER($BX58),IF($BX58>=2016,1,0),"") -> 1 | V58: =IF(ISNUMBER($BW58),IF($BW58>=2016,1,0),"") -> 0 | W58: =IF(AND(ISNUMBER($BW58),ISNUMBER($BX58)),IF($BW58>=2016,"post-only",IF($BX58<2016,"pre-only","mixed")),"") -> mixed | X58: =IF(AND(ISNUMBER($BW58),ISNUMBER($BX58)),MIN(1,MAX(0,($BX58-2017+1)/($BX58-$BW58+1))),"") -> 0.25 | Y58: =IF(AND(ISNUMBER($BW58),ISNUMBER($BX58)),MIN(1,MAX(0,($BX58-2018+1)/($BX58-$BW58+1))),"") -> 0.1875 | Z58: =IF(AND(ISNUMBER($BW58),ISNUMBER($BX58)),MIN(1,MAX(0,($BX58-2019+1)/($BX58-$BW58+1))),"") -> 0.125 | AA58: =IF(ISNUMBER($BX58),IF($BX58>=2017,1,0),"") -> 1 | AB58: =IF(ISNUMBER($BX58),IF($BX58>=2018,1,0),"") -> 1 | AC58: =IF(ISNUMBER($BX58),IF($BX58>=2019,1,0),"") -> 1 | AD58: =IF($L58<>"",IF($L58>2013,1,0),"") -> 0 | AE58: =IF($L58<>"",1+IF($L58>2011,1,0)+IF($L58>2014,1,0),"") -> 2 | AF58: loan (interest rate) | AG58: performance | AH58: non-sensitive | AI58: without ETS/CT | AJ58: without ETS/CT | AK58: =IF(AND($CF58<>"",IFERROR(INDEX(subsample_country_map!$B:$B,MATCH($CF58,subsample_country_map!$A:$A,0)),"")<>""),INDEX(subsample_country_map!$B:$B,MATCH($CF58,subsample_country_map!$A:$A,0)),INDEX(lookup!$AA:$AA,MATCH($A58,lookup!$A:$A,0))) -> 1_US | AL58: =IF(AND($CF58<>"",IFERROR(INDEX(subsample_country_map!$C:$C,MATCH($CF58,subsample_country_map!$A:$A,0)),"")<>""),INDEX(subsample_country_map!$C:$C,MATCH($CF58,subsample_country_map!$A:$A,0)),INDEX(lookup!$AB:$AB,MATCH($A58,lookup!$A:$A,0))) -> 1_developed | AM58: =IF(AND($CF58<>"",IFERROR(INDEX(subsample_country_map!$D:$D,MATCH($CF58,subsample_country_map!$A:$A,0)),"")<>""),INDEX(subsample_country_map!$D:$D,MATCH($CF58,subsample_country_map!$A:$A,0)),INDEX(lookup!$AC:$AC,MATCH($A58,lookup!$A:$A,0))) -> 1_western | AN58: =IF(AND($CF58<>"",IFERROR(INDEX(subsample_country_map!$E:$E,MATCH($CF58,subsample_country_map!$A:$A,0)),"")<>""),INDEX(subsample_country_map!$E:$E,MATCH($CF58,subsample_country_map!$A:$A,0)),INDEX(lookup!$AD:$AD,MATCH($A58,lookup!$A:$A,0))) -> 1_common law | AO58: =INDEX(lookup!$Y:$Y,MATCH($A58,lookup!$A:$A,0)) -> 0_published | AP58: =INDEX(lookup!$Z:$Z,MATCH($A58,lookup!$A:$A,0)) -> 1_VHB high | AQ58: =INDEX(lookup!$W:$W,MATCH($A58,lookup!$A:$A,0)) -> 2_sust | AS58: staging | AT58: good-CER | AU58: cost | AZ58: -.21 | BA58: FLAG | BB58: FLAG | BC58: n/a (structural) | BD58: n/a (structural) | BE58: none | BI58: Table 3 | BJ58: Pearson correlation row 2 col 1 | BK58: 3424 | BL58: CC_ACTION 2 -.21*** | BM58: CC_ACTION | BN58: KD | BO58: update | BP58: Ali et al (2023) | BQ58: bivariate | BT58: 0 | BU58: staging_Ali_et_al_2023.csv | BW58: 2005 | BX58: 2020 | BY58: United States | BZ58: 2012.5 | CA58: 0.3125 | CB58: 0 | CC58: 1 | CD58: -0.21317135 | CE58: 1
A59: Ali et al (2023) | B59: 1364 | C59: -0.21105191 | D59: 3066 | E59: =IF(ISNUMBER($BA59),$BA59,IF(AND(ISNUMBER($D59),ISNUMBER($BW59),ISNUMBER($BX59)),$D59*($BX59-$BW59+1),"")) -> 3066 | H59: partial | I59: Regression Cofficient and Standard Error available | J59: =IF($BW59<>"",$BW59,"") -> 2005 | K59: =IF($BX59<>"",$BX59,"") -> 2020 | L59: =IF(AND(ISNUMBER($BW59),ISNUMBER($BX59)),($BW59+$BX59)/2,"") -> 2012.5 | M59: =IF($L59<>"",$L59,"") -> 2012.5 | N59: =IF(AND(ISNUMBER($BW59),ISNUMBER($BX59)),MIN(1,MAX(0,($BX59-2016+1)/($BX59-$BW59+1))),"") -> 0.3125 | O59: =IF(AND(ISNUMBER($BW59),ISNUMBER($BX59)),MIN(1,MAX(0,($BX59-2017+1)/($BX59-$BW59+1))),"") -> 0.25 | P59: =IF(AND(ISNUMBER($BW59),ISNUMBER($BX59)),MIN(1,MAX(0,($BX59-2018+1)/($BX59-$BW59+1))),"") -> 0.1875 | Q59: =IF(AND(ISNUMBER($BW59),ISNUMBER($BX59)),MIN(1,MAX(0,($BX59-2019+1)/($BX59-$BW59+1))),"") -> 0.125 | R59: =IF(AND(ISNUMBER($BW59),ISNUMBER($BX59)),MIN(1,MAX(0,($BX59-2016+1)/($BX59-$BW59+1))),"") -> 0.3125 | S59: =IF($L59<>"",IF($L59>=2015.5,1,0),"") -> 0 | T59: =IF($L59<>"",IF($L59>=2016,1,0),"") -> 0 | U59: =IF(ISNUMBER($BX59),IF($BX59>=2016,1,0),"") -> 1 | V59: =IF(ISNUMBER($BW59),IF($BW59>=2016,1,0),"") -> 0 | W59: =IF(AND(ISNUMBER($BW59),ISNUMBER($BX59)),IF($BW59>=2016,"post-only",IF($BX59<2016,"pre-only","mixed")),"") -> mixed | X59: =IF(AND(ISNUMBER($BW59),ISNUMBER($BX59)),MIN(1,MAX(0,($BX59-2017+1)/($BX59-$BW59+1))),"") -> 0.25 | Y59: =IF(AND(ISNUMBER($BW59),ISNUMBER($BX59)),MIN(1,MAX(0,($BX59-2018+1)/($BX59-$BW59+1))),"") -> 0.1875 | Z59: =IF(AND(ISNUMBER($BW59),ISNUMBER($BX59)),MIN(1,MAX(0,($BX59-2019+1)/($BX59-$BW59+1))),"") -> 0.125 | AA59: =IF(ISNUMBER($BX59),IF($BX59>=2017,1,0),"") -> 1 | AB59: =IF(ISNUMBER($BX59),IF($BX59>=2018,1,0),"") -> 1 | AC59: =IF(ISNUMBER($BX59),IF($BX59>=2019,1,0),"") -> 1 | AD59: =IF($L59<>"",IF($L59>2013,1,0),"") -> 0 | AE59: =IF($L59<>"",1+IF($L59>2011,1,0)+IF($L59>2014,1,0),"") -> 2 | AF59: loan (interest rate) | AG59: performance | AH59: non-sensitive | AI59: without ETS/CT | AJ59: without ETS/CT | AK59: =IF(AND($CF59<>"",IFERROR(INDEX(subsample_country_map!$B:$B,MATCH($CF59,subsample_country_map!$A:$A,0)),"")<>""),INDEX(subsample_country_map!$B:$B,MATCH($CF59,subsample_country_map!$A:$A,0)),INDEX(lookup!$AA:$AA,MATCH($A59,lookup!$A:$A,0))) -> 1_US | AL59: =IF(AND($CF59<>"",IFERROR(INDEX(subsample_country_map!$C:$C,MATCH($CF59,subsample_country_map!$A:$A,0)),"")<>""),INDEX(subsample_country_map!$C:$C,MATCH($CF59,subsample_country_map!$A:$A,0)),INDEX(lookup!$AB:$AB,MATCH($A59,lookup!$A:$A,0))) -> 1_developed | AM59: =IF(AND($CF59<>"",IFERROR(INDEX(subsample_country_map!$D:$D,MATCH($CF59,subsample_country_map!$A:$A,0)),"")<>""),INDEX(subsample_country_map!$D:$D,MATCH($CF59,subsample_country_map!$A:$A,0)),INDEX(lookup!$AC:$AC,MATCH($A59,lookup!$A:$A,0))) -> 1_western | AN59: =IF(AND($CF59<>"",IFERROR(INDEX(subsample_country_map!$E:$E,MATCH($CF59,subsample_country_map!$A:$A,0)),"")<>""),INDEX(subsample_country_map!$E:$E,MATCH($CF59,subsample_country_map!$A:$A,0)),INDEX(lookup!$AD:$AD,MATCH($A59,lookup!$A:$A,0))) -> 1_common law | AO59: =INDEX(lookup!$Y:$Y,MATCH($A59,lookup!$A:$A,0)) -> 0_published | AP59: =INDEX(lookup!$Z:$Z,MATCH($A59,lookup!$A:$A,0)) -> 1_VHB high | AQ59: =INDEX(lookup!$W:$W,MATCH($A59,lookup!$A:$A,0)) -> 2_sust | AS59: staging | AT59: good-CER | AU59: cost | AV59: -1.076 | AW59: .090 | BA59: 3066 | BB59: 1 | BC59: OLS | BD59: robust (unclustered) | BE59: none | BI59: Table 4 | BJ59: Model (1) OLS | BK59: 3425 | BL59: CC_ACTION -1.076***(.090) | BM59: CC_ACTION | BN59: KD | BO59: update | BP59: Ali et al (2023) | BQ59: computed | BT59: 0 | BU59: staging_Ali_et_al_2023.csv | BW59: 2005 | BX59: 2020 | BY59: United States | BZ59: 2012.5 | CA59: 0.3125 | CB59: 0 | CC59: 1 | CD59: -0.21427204 | CE59: 1
A60: Ali et al (2023) | B60: 1365 | C60: -0.049098929 | D60: 3065 | E60: =IF(ISNUMBER($BA60),$BA60,IF(AND(ISNUMBER($D60),ISNUMBER($BW60),ISNUMBER($BX60)),$D60*($BX60-$BW60+1),"")) -> 3065 | H60: partial | I60: Regression Cofficient and Standard Error available | J60: =IF($BW60<>"",$BW60,"") -> 2005 | K60: =IF($BX60<>"",$BX60,"") -> 2020 | L60: =IF(AND(ISNUMBER($BW60),ISNUMBER($BX60)),($BW60+$BX60)/2,"") -> 2012.5 | M60: =IF($L60<>"",$L60,"") -> 2012.5 | N60: =IF(AND(ISNUMBER($BW60),ISNUMBER($BX60)),MIN(1,MAX(0,($BX60-2016+1)/($BX60-$BW60+1))),"") -> 0.3125 | O60: =IF(AND(ISNUMBER($BW60),ISNUMBER($BX60)),MIN(1,MAX(0,($BX60-2017+1)/($BX60-$BW60+1))),"") -> 0.25 | P60: =IF(AND(ISNUMBER($BW60),ISNUMBER($BX60)),MIN(1,MAX(0,($BX60-2018+1)/($BX60-$BW60+1))),"") -> 0.1875 | Q60: =IF(AND(ISNUMBER($BW60),ISNUMBER($BX60)),MIN(1,MAX(0,($BX60-2019+1)/($BX60-$BW60+1))),"") -> 0.125 | R60: =IF(AND(ISNUMBER($BW60),ISNUMBER($BX60)),MIN(1,MAX(0,($BX60-2016+1)/($BX60-$BW60+1))),"") -> 0.3125 | S60: =IF($L60<>"",IF($L60>=2015.5,1,0),"") -> 0 | T60: =IF($L60<>"",IF($L60>=2016,1,0),"") -> 0 | U60: =IF(ISNUMBER($BX60),IF($BX60>=2016,1,0),"") -> 1 | V60: =IF(ISNUMBER($BW60),IF($BW60>=2016,1,0),"") -> 0 | W60: =IF(AND(ISNUMBER($BW60),ISNUMBER($BX60)),IF($BW60>=2016,"post-only",IF($BX60<2016,"pre-only","mixed")),"") -> mixed | X60: =IF(AND(ISNUMBER($BW60),ISNUMBER($BX60)),MIN(1,MAX(0,($BX60-2017+1)/($BX60-$BW60+1))),"") -> 0.25 | Y60: =IF(AND(ISNUMBER($BW60),ISNUMBER($BX60)),MIN(1,MAX(0,($BX60-2018+1)/($BX60-$BW60+1))),"") -> 0.1875 | Z60: =IF(AND(ISNUMBER($BW60),ISNUMBER($BX60)),MIN(1,MAX(0,($BX60-2019+1)/($BX60-$BW60+1))),"") -> 0.125 | AA60: =IF(ISNUMBER($BX60),IF($BX60>=2017,1,0),"") -> 1 | AB60: =IF(ISNUMBER($BX60),IF($BX60>=2018,1,0),"") -> 1 | AC60: =IF(ISNUMBER($BX60),IF($BX60>=2019,1,0),"") -> 1 | AD60: =IF($L60<>"",IF($L60>2013,1,0),"") -> 0 | AE60: =IF($L60<>"",1+IF($L60>2011,1,0)+IF($L60>2014,1,0),"") -> 2 | AF60: loan (interest rate) | AG60: performance | AH60: non-sensitive | AI60: without ETS/CT | AJ60: without ETS/CT | AK60: =IF(AND($CF60<>"",IFERROR(INDEX(subsample_country_map!$B:$B,MATCH($CF60,subsample_country_map!$A:$A,0)),"")<>""),INDEX(subsample_country_map!$B:$B,MATCH($CF60,subsample_country_map!$A:$A,0)),INDEX(lookup!$AA:$AA,MATCH($A60,lookup!$A:$A,0))) -> 1_US | AL60: =IF(AND($CF60<>"",IFERROR(INDEX(subsample_country_map!$C:$C,MATCH($CF60,subsample_country_map!$A:$A,0)),"")<>""),INDEX(subsample_country_map!$C:$C,MATCH($CF60,subsample_country_map!$A:$A,0)),INDEX(lookup!$AB:$AB,MATCH($A60,lookup!$A:$A,0))) -> 1_developed | AM60: =IF(AND($CF60<>"",IFERROR(INDEX(subsample_country_map!$D:$D,MATCH($CF60,subsample_country_map!$A:$A,0)),"")<>""),INDEX(subsample_country_map!$D:$D,MATCH($CF60,subsample_country_map!$A:$A,0)),INDEX(lookup!$AC:$AC,MATCH($A60,lookup!$A:$A,0))) -> 1_western | AN60: =IF(AND($CF60<>"",IFERROR(INDEX(subsample_country_map!$E:$E,MATCH($CF60,subsample_country_map!$A:$A,0)),"")<>""),INDEX(subsample_country_map!$E:$E,MATCH($CF60,subsample_country_map!$A:$A,0)),INDEX(lookup!$AD:$AD,MATCH($A60,lookup!$A:$A,0))) -> 1_common law | AO60: =INDEX(lookup!$Y:$Y,MATCH($A60,lookup!$A:$A,0)) -> 0_published | AP60: =INDEX(lookup!$Z:$Z,MATCH($A60,lookup!$A:$A,0)) -> 1_VHB high | AQ60: =INDEX(lookup!$W:$W,MATCH($A60,lookup!$A:$A,0)) -> 2_sust | AS60: staging | AT60: good-CER | AU60: cost | AV60: -.215 | AW60: .079 | BA60: 3065 | BB60: 1 | BC60: OLS | BD60: robust (unclustered) | BE60: none | BI60: Table 4 | BJ60: Model (2) OLS | BK60: 3425 | BL60: CC_ACTION -.215***(.079) | BM60: CC_ACTION | BN60: KD | BO60: update | BP60: Ali et al (2023) | BQ60: computed | BT60: 0 | BU60: staging_Ali_et_al_2023.csv | BW60: 2005 | BX60: 2020 | BY60: United States | BZ60: 2012.5 | CA60: 0.3125 | CB60: 0 | CC60: 1 | CD60: -0.049138441 | CE60: 1
A61: Ali et al (2023) | B61: 1366 | C61: -0.20288189 | D61: 3065 | E61: =IF(ISNUMBER($BA61),$BA61,IF(AND(ISNUMBER($D61),ISNUMBER($BW61),ISNUMBER($BX61)),$D61*($BX61-$BW61+1),"")) -> 3065 | H61: partial | I61: Regression Cofficient and Standard Error available | J61: =IF($BW61<>"",$BW61,"") -> 2005 | K61: =IF($BX61<>"",$BX61,"") -> 2020 | L61: =IF(AND(ISNUMBER($BW61),ISNUMBER($BX61)),($BW61+$BX61)/2,"") -> 2012.5 | M61: =IF($L61<>"",$L61,"") -> 2012.5 | N61: =IF(AND(ISNUMBER($BW61),ISNUMBER($BX61)),MIN(1,MAX(0,($BX61-2016+1)/($BX61-$BW61+1))),"") -> 0.3125 | O61: =IF(AND(ISNUMBER($BW61),ISNUMBER($BX61)),MIN(1,MAX(0,($BX61-2017+1)/($BX61-$BW61+1))),"") -> 0.25 | P61: =IF(AND(ISNUMBER($BW61),ISNUMBER($BX61)),MIN(1,MAX(0,($BX61-2018+1)/($BX61-$BW61+1))),"") -> 0.1875 | Q61: =IF(AND(ISNUMBER($BW61),ISNUMBER($BX61)),MIN(1,MAX(0,($BX61-2019+1)/($BX61-$BW61+1))),"") -> 0.125 | R61: =IF(AND(ISNUMBER($BW61),ISNUMBER($BX61)),MIN(1,MAX(0,($BX61-2016+1)/($BX61-$BW61+1))),"") -> 0.3125 | S61: =IF($L61<>"",IF($L61>=2015.5,1,0),"") -> 0 | T61: =IF($L61<>"",IF($L61>=2016,1,0),"") -> 0 | U61: =IF(ISNUMBER($BX61),IF($BX61>=2016,1,0),"") -> 1 | V61: =IF(ISNUMBER($BW61),IF($BW61>=2016,1,0),"") -> 0 | W61: =IF(AND(ISNUMBER($BW61),ISNUMBER($BX61)),IF($BW61>=2016,"post-only",IF($BX61<2016,"pre-only","mixed")),"") -> mixed | X61: =IF(AND(ISNUMBER($BW61),ISNUMBER($BX61)),MIN(1,MAX(0,($BX61-2017+1)/($BX61-$BW61+1))),"") -> 0.25 | Y61: =IF(AND(ISNUMBER($BW61),ISNUMBER($BX61)),MIN(1,MAX(0,($BX61-2018+1)/($BX61-$BW61+1))),"") -> 0.1875 | Z61: =IF(AND(ISNUMBER($BW61),ISNUMBER($BX61)),MIN(1,MAX(0,($BX61-2019+1)/($BX61-$BW61+1))),"") -> 0.125 | AA61: =IF(ISNUMBER($BX61),IF($BX61>=2017,1,0),"") -> 1 | AB61: =IF(ISNUMBER($BX61),IF($BX61>=2018,1,0),"") -> 1 | AC61: =IF(ISNUMBER($BX61),IF($BX61>=2019,1,0),"") -> 1 | AD61: =IF($L61<>"",IF($L61>2013,1,0),"") -> 0 | AE61: =IF($L61<>"",1+IF($L61>2011,1,0)+IF($L61>2014,1,0),"") -> 2 | AF61: loan (interest rate) | AG61: performance | AH61: non-sensitive | AI61: without ETS/CT | AJ61: without ETS/CT | AK61: =IF(AND($CF61<>"",IFERROR(INDEX(subsample_country_map!$B:$B,MATCH($CF61,subsample_country_map!$A:$A,0)),"")<>""),INDEX(subsample_country_map!$B:$B,MATCH($CF61,subsample_country_map!$A:$A,0)),INDEX(lookup!$AA:$AA,MATCH($A61,lookup!$A:$A,0))) -> 1_US | AL61: =IF(AND($CF61<>"",IFERROR(INDEX(subsample_country_map!$C:$C,MATCH($CF61,subsample_country_map!$A:$A,0)),"")<>""),INDEX(subsample_country_map!$C:$C,MATCH($CF61,subsample_country_map!$A:$A,0)),INDEX(lookup!$AB:$AB,MATCH($A61,lookup!$A:$A,0))) -> 1_developed | AM61: =IF(AND($CF61<>"",IFERROR(INDEX(subsample_country_map!$D:$D,MATCH($CF61,subsample_country_map!$A:$A,0)),"")<>""),INDEX(subsample_country_map!$D:$D,MATCH($CF61,subsample_country_map!$A:$A,0)),INDEX(lookup!$AC:$AC,MATCH($A61,lookup!$A:$A,0))) -> 1_western | AN61: =IF(AND($CF61<>"",IFERROR(INDEX(subsample_country_map!$E:$E,MATCH($CF61,subsample_country_map!$A:$A,0)),"")<>""),INDEX(subsample_country_map!$E:$E,MATCH($CF61,subsample_country_map!$A:$A,0)),INDEX(lookup!$AD:$AD,MATCH($A61,lookup!$A:$A,0))) -> 1_common law | AO61: =INDEX(lookup!$Y:$Y,MATCH($A61,lookup!$A:$A,0)) -> 0_published | AP61: =INDEX(lookup!$Z:$Z,MATCH($A61,lookup!$A:$A,0)) -> 1_VHB high | AQ61: =INDEX(lookup!$W:$W,MATCH($A61,lookup!$A:$A,0)) -> 2_sust | AS61: staging | AT61: good-CER | AU61: cost | AV61: -1.560 | AW61: .136 | BA61: 3065 | BB61: 1 | BC61: FE | BD61: robust (unclustered) | BE61: none | BI61: Table 4 | BJ61: Model (3) FE | BK61: 3425 | BL61: CC_ACTION -1.560***(.136) | BM61: CC_ACTION | BN61: KD | BO61: update | BP61: Ali et al (2023) | BQ61: computed | BT61: 0 | BU61: staging_Ali_et_al_2023.csv | BW61: 2005 | BX61: 2020 | BY61: United States | BZ61: 2012.5 | CA61: 0.3125 | CB61: 0 | CC61: 1 | CD61: -0.20573634 | CE61: 1
A62: Ali et al (2023) | B62: 1367 | C62: -0.12034701 | D62: 1037 | E62: =IF(ISNUMBER($BA62),$BA62,IF(AND(ISNUMBER($D62),ISNUMBER($BW62),ISNUMBER($BX62)),$D62*($BX62-$BW62+1),"")) -> 1037 | H62: partial | I62: Regression Cofficient and Standard Error available | J62: =IF($BW62<>"",$BW62,"") -> 2005 | K62: =IF($BX62<>"",$BX62,"") -> 2020 | L62: =IF(AND(ISNUMBER($BW62),ISNUMBER($BX62)),($BW62+$BX62)/2,"") -> 2012.5 | M62: =IF($L62<>"",$L62,"") -> 2012.5 | N62: =IF(AND(ISNUMBER($BW62),ISNUMBER($BX62)),MIN(1,MAX(0,($BX62-2016+1)/($BX62-$BW62+1))),"") -> 0.3125 | O62: =IF(AND(ISNUMBER($BW62),ISNUMBER($BX62)),MIN(1,MAX(0,($BX62-2017+1)/($BX62-$BW62+1))),"") -> 0.25 | P62: =IF(AND(ISNUMBER($BW62),ISNUMBER($BX62)),MIN(1,MAX(0,($BX62-2018+1)/($BX62-$BW62+1))),"") -> 0.1875 | Q62: =IF(AND(ISNUMBER($BW62),ISNUMBER($BX62)),MIN(1,MAX(0,($BX62-2019+1)/($BX62-$BW62+1))),"") -> 0.125 | R62: =IF(AND(ISNUMBER($BW62),ISNUMBER($BX62)),MIN(1,MAX(0,($BX62-2016+1)/($BX62-$BW62+1))),"") -> 0.3125 | S62: =IF($L62<>"",IF($L62>=2015.5,1,0),"") -> 0 | T62: =IF($L62<>"",IF($L62>=2016,1,0),"") -> 0 | U62: =IF(ISNUMBER($BX62),IF($BX62>=2016,1,0),"") -> 1 | V62: =IF(ISNUMBER($BW62),IF($BW62>=2016,1,0),"") -> 0 | W62: =IF(AND(ISNUMBER($BW62),ISNUMBER($BX62)),IF($BW62>=2016,"post-only",IF($BX62<2016,"pre-only","mixed")),"") -> mixed | X62: =IF(AND(ISNUMBER($BW62),ISNUMBER($BX62)),MIN(1,MAX(0,($BX62-2017+1)/($BX62-$BW62+1))),"") -> 0.25 | Y62: =IF(AND(ISNUMBER($BW62),ISNUMBER($BX62)),MIN(1,MAX(0,($BX62-2018+1)/($BX62-$BW62+1))),"") -> 0.1875 | Z62: =IF(AND(ISNUMBER($BW62),ISNUMBER($BX62)),MIN(1,MAX(0,($BX62-2019+1)/($BX62-$BW62+1))),"") -> 0.125 | AA62: =IF(ISNUMBER($BX62),IF($BX62>=2017,1,0),"") -> 1 | AB62: =IF(ISNUMBER($BX62),IF($BX62>=2018,1,0),"") -> 1 | AC62: =IF(ISNUMBER($BX62),IF($BX62>=2019,1,0),"") -> 1 | AD62: =IF($L62<>"",IF($L62>2013,1,0),"") -> 0 | AE62: =IF($L62<>"",1+IF($L62>2011,1,0)+IF($L62>2014,1,0),"") -> 2 | AF62: loan (interest rate) | AG62: performance | AH62: non-sensitive | AI62: without ETS/CT | AJ62: without ETS/CT | AK62: =IF(AND($CF62<>"",IFERROR(INDEX(subsample_country_map!$B:$B,MATCH($CF62,subsample_country_map!$A:$A,0)),"")<>""),INDEX(subsample_country_map!$B:$B,MATCH($CF62,subsample_country_map!$A:$A,0)),INDEX(lookup!$AA:$AA,MATCH($A62,lookup!$A:$A,0))) -> 1_US | AL62: =IF(AND($CF62<>"",IFERROR(INDEX(subsample_country_map!$C:$C,MATCH($CF62,subsample_country_map!$A:$A,0)),"")<>""),INDEX(subsample_country_map!$C:$C,MATCH($CF62,subsample_country_map!$A:$A,0)),INDEX(lookup!$AB:$AB,MATCH($A62,lookup!$A:$A,0))) -> 1_developed | AM62: =IF(AND($CF62<>"",IFERROR(INDEX(subsample_country_map!$D:$D,MATCH($CF62,subsample_country_map!$A:$A,0)),"")<>""),INDEX(subsample_country_map!$D:$D,MATCH($CF62,subsample_country_map!$A:$A,0)),INDEX(lookup!$AC:$AC,MATCH($A62,lookup!$A:$A,0))) -> 1_western | AN62: =IF(AND($CF62<>"",IFERROR(INDEX(subsample_country_map!$E:$E,MATCH($CF62,subsample_country_map!$A:$A,0)),"")<>""),INDEX(subsample_country_map!$E:$E,MATCH($CF62,subsample_country_map!$A:$A,0)),INDEX(lookup!$AD:$AD,MATCH($A62,lookup!$A:$A,0))) -> 1_common law | AO62: =INDEX(lookup!$Y:$Y,MATCH($A62,lookup!$A:$A,0)) -> 0_published | AP62: =INDEX(lookup!$Z:$Z,MATCH($A62,lookup!$A:$A,0)) -> 1_VHB high | AQ62: =INDEX(lookup!$W:$W,MATCH($A62,lookup!$A:$A,0)) -> 2_sust | AS62: staging | AT62: good-CER | AU62: cost | AV62: -.203 | AW62: .052 | BA62: 1037 | BB62: 1 | BC62: OLS | BD62: robust (unclustered) | BE62: none | BI62: Table 5 | BJ62: Model (1) | BK62: 3426 | BL62: W-RECYCLED -.203***(.052) | BM62: W-RECYCLED | BN62: interest-spread | BO62: update | BP62: Ali et al (2023) | BQ62: computed | BT62: 0 | BU62: staging_Ali_et_al_2023.csv | BW62: 2005 | BX62: 2020 | BY62: United States | BZ62: 2012.5 | CA62: 0.3125 | CB62: 0 | CC62: 1 | CD62: -0.12093312 | CE62: 1
A63: Ali et al (2023) | B63: 1368 | C63: -0.049098929 | D63: 3065 | E63: =IF(ISNUMBER($BA63),$BA63,IF(AND(ISNUMBER($D63),ISNUMBER($BW63),ISNUMBER($BX63)),$D63*($BX63-$BW63+1),"")) -> 3065 | H63: partial | I63: Regression Cofficient and Standard Error available | J63: =IF($BW63<>"",$BW63,"") -> 2005 | K63: =IF($BX63<>"",$BX63,"") -> 2020 | L63: =IF(AND(ISNUMBER($BW63),ISNUMBER($BX63)),($BW63+$BX63)/2,"") -> 2012.5 | M63: =IF($L63<>"",$L63,"") -> 2012.5 | N63: =IF(AND(ISNUMBER($BW63),ISNUMBER($BX63)),MIN(1,MAX(0,($BX63-2016+1)/($BX63-$BW63+1))),"") -> 0.3125 | O63: =IF(AND(ISNUMBER($BW63),ISNUMBER($BX63)),MIN(1,MAX(0,($BX63-2017+1)/($BX63-$BW63+1))),"") -> 0.25 | P63: =IF(AND(ISNUMBER($BW63),ISNUMBER($BX63)),MIN(1,MAX(0,($BX63-2018+1)/($BX63-$BW63+1))),"") -> 0.1875 | Q63: =IF(AND(ISNUMBER($BW63),ISNUMBER($BX63)),MIN(1,MAX(0,($BX63-2019+1)/($BX63-$BW63+1))),"") -> 0.125 | R63: =IF(AND(ISNUMBER($BW63),ISNUMBER($BX63)),MIN(1,MAX(0,($BX63-2016+1)/($BX63-$BW63+1))),"") -> 0.3125 | S63: =IF($L63<>"",IF($L63>=2015.5,1,0),"") -> 0 | T63: =IF($L63<>"",IF($L63>=2016,1,0),"") -> 0 | U63: =IF(ISNUMBER($BX63),IF($BX63>=2016,1,0),"") -> 1 | V63: =IF(ISNUMBER($BW63),IF($BW63>=2016,1,0),"") -> 0 | W63: =IF(AND(ISNUMBER($BW63),ISNUMBER($BX63)),IF($BW63>=2016,"post-only",IF($BX63<2016,"pre-only","mixed")),"") -> mixed | X63: =IF(AND(ISNUMBER($BW63),ISNUMBER($BX63)),MIN(1,MAX(0,($BX63-2017+1)/($BX63-$BW63+1))),"") -> 0.25 | Y63: =IF(AND(ISNUMBER($BW63),ISNUMBER($BX63)),MIN(1,MAX(0,($BX63-2018+1)/($BX63-$BW63+1))),"") -> 0.1875 | Z63: =IF(AND(ISNUMBER($BW63),ISNUMBER($BX63)),MIN(1,MAX(0,($BX63-2019+1)/($BX63-$BW63+1))),"") -> 0.125 | AA63: =IF(ISNUMBER($BX63),IF($BX63>=2017,1,0),"") -> 1 | AB63: =IF(ISNUMBER($BX63),IF($BX63>=2018,1,0),"") -> 1 | AC63: =IF(ISNUMBER($BX63),IF($BX63>=2019,1,0),"") -> 1 | AD63: =IF($L63<>"",IF($L63>2013,1,0),"") -> 0 | AE63: =IF($L63<>"",1+IF($L63>2011,1,0)+IF($L63>2014,1,0),"") -> 2 | AF63: loan (interest rate) | AG63: performance | AH63: non-sensitive | AI63: without ETS/CT | AJ63: without ETS/CT | AK63: =IF(AND($CF63<>"",IFERROR(INDEX(subsample_country_map!$B:$B,MATCH($CF63,subsample_country_map!$A:$A,0)),"")<>""),INDEX(subsample_country_map!$B:$B,MATCH($CF63,subsample_country_map!$A:$A,0)),INDEX(lookup!$AA:$AA,MATCH($A63,lookup!$A:$A,0))) -> 1_US | AL63: =IF(AND($CF63<>"",IFERROR(INDEX(subsample_country_map!$C:$C,MATCH($CF63,subsample_country_map!$A:$A,0)),"")<>""),INDEX(subsample_country_map!$C:$C,MATCH($CF63,subsample_country_map!$A:$A,0)),INDEX(lookup!$AB:$AB,MATCH($A63,lookup!$A:$A,0))) -> 1_developed | AM63: =IF(AND($CF63<>"",IFERROR(INDEX(subsample_country_map!$D:$D,MATCH($CF63,subsample_country_map!$A:$A,0)),"")<>""),INDEX(subsample_country_map!$D:$D,MATCH($CF63,subsample_country_map!$A:$A,0)),INDEX(lookup!$AC:$AC,MATCH($A63,lookup!$A:$A,0))) -> 1_western | AN63: =IF(AND($CF63<>"",IFERROR(INDEX(subsample_country_map!$E:$E,MATCH($CF63,subsample_country_map!$A:$A,0)),"")<>""),INDEX(subsample_country_map!$E:$E,MATCH($CF63,subsample_country_map!$A:$A,0)),INDEX(lookup!$AD:$AD,MATCH($A63,lookup!$A:$A,0))) -> 1_common law | AO63: =INDEX(lookup!$Y:$Y,MATCH($A63,lookup!$A:$A,0)) -> 0_published | AP63: =INDEX(lookup!$Z:$Z,MATCH($A63,lookup!$A:$A,0)) -> 1_VHB high | AQ63: =INDEX(lookup!$W:$W,MATCH($A63,lookup!$A:$A,0)) -> 2_sust | AS63: staging | AT63: good-CER | AU63: cost | AV63: -.215 | AW63: .079 | BA63: 3065 | BB63: 1 | BC63: OLS | BD63: robust (unclustered) | BE63: none | BI63: Table 5 | BJ63: Model (2) | BK63: 3426 | BL63: CC-ACTION -.215***(.079) | BM63: CC-ACTION | BN63: interest-spread | BO63: update | BP63: Ali et al (2023) | BQ63: computed | BT63: 0 | BU63: staging_Ali_et_al_2023.csv | BW63: 2005 | BX63: 2020 | BY63: United States | BZ63: 2012.5 | CA63: 0.3125 | CB63: 0 | CC63: 1 | CD63: -0.049138441 | CE63: 1
A64: Ali et al (2023) | B64: 1369 | C64: -0.10495945 | D64: 2000 | E64: =IF(ISNUMBER($BA64),$BA64,IF(AND(ISNUMBER($D64),ISNUMBER($BW64),ISNUMBER($BX64)),$D64*($BX64-$BW64+1),"")) -> 2000 | H64: partial | I64: Regression Cofficient and Standard Error available | J64: =IF($BW64<>"",$BW64,"") -> 2005 | K64: =IF($BX64<>"",$BX64,"") -> 2020 | L64: =IF(AND(ISNUMBER($BW64),ISNUMBER($BX64)),($BW64+$BX64)/2,"") -> 2012.5 | M64: =IF($L64<>"",$L64,"") -> 2012.5 | N64: =IF(AND(ISNUMBER($BW64),ISNUMBER($BX64)),MIN(1,MAX(0,($BX64-2016+1)/($BX64-$BW64+1))),"") -> 0.3125 | O64: =IF(AND(ISNUMBER($BW64),ISNUMBER($BX64)),MIN(1,MAX(0,($BX64-2017+1)/($BX64-$BW64+1))),"") -> 0.25 | P64: =IF(AND(ISNUMBER($BW64),ISNUMBER($BX64)),MIN(1,MAX(0,($BX64-2018+1)/($BX64-$BW64+1))),"") -> 0.1875 | Q64: =IF(AND(ISNUMBER($BW64),ISNUMBER($BX64)),MIN(1,MAX(0,($BX64-2019+1)/($BX64-$BW64+1))),"") -> 0.125 | R64: =IF(AND(ISNUMBER($BW64),ISNUMBER($BX64)),MIN(1,MAX(0,($BX64-2016+1)/($BX64-$BW64+1))),"") -> 0.3125 | S64: =IF($L64<>"",IF($L64>=2015.5,1,0),"") -> 0 | T64: =IF($L64<>"",IF($L64>=2016,1,0),"") -> 0 | U64: =IF(ISNUMBER($BX64),IF($BX64>=2016,1,0),"") -> 1 | V64: =IF(ISNUMBER($BW64),IF($BW64>=2016,1,0),"") -> 0 | W64: =IF(AND(ISNUMBER($BW64),ISNUMBER($BX64)),IF($BW64>=2016,"post-only",IF($BX64<2016,"pre-only","mixed")),"") -> mixed | X64: =IF(AND(ISNUMBER($BW64),ISNUMBER($BX64)),MIN(1,MAX(0,($BX64-2017+1)/($BX64-$BW64+1))),"") -> 0.25 | Y64: =IF(AND(ISNUMBER($BW64),ISNUMBER($BX64)),MIN(1,MAX(0,($BX64-2018+1)/($BX64-$BW64+1))),"") -> 0.1875 | Z64: =IF(AND(ISNUMBER($BW64),ISNUMBER($BX64)),MIN(1,MAX(0,($BX64-2019+1)/($BX64-$BW64+1))),"") -> 0.125 | AA64: =IF(ISNUMBER($BX64),IF($BX64>=2017,1,0),"") -> 1 | AB64: =IF(ISNUMBER($BX64),IF($BX64>=2018,1,0),"") -> 1 | AC64: =IF(ISNUMBER($BX64),IF($BX64>=2019,1,0),"") -> 1 | AD64: =IF($L64<>"",IF($L64>2013,1,0),"") -> 0 | AE64: =IF($L64<>"",1+IF($L64>2011,1,0)+IF($L64>2014,1,0),"") -> 2 | AF64: loan (interest rate) | AG64: performance | AH64: non-sensitive | AI64: without ETS/CT | AJ64: without ETS/CT | AK64: =IF(AND($CF64<>"",IFERROR(INDEX(subsample_country_map!$B:$B,MATCH($CF64,subsample_country_map!$A:$A,0)),"")<>""),INDEX(subsample_country_map!$B:$B,MATCH($CF64,subsample_country_map!$A:$A,0)),INDEX(lookup!$AA:$AA,MATCH($A64,lookup!$A:$A,0))) -> 1_US | AL64: =IF(AND($CF64<>"",IFERROR(INDEX(subsample_country_map!$C:$C,MATCH($CF64,subsample_country_map!$A:$A,0)),"")<>""),INDEX(subsample_country_map!$C:$C,MATCH($CF64,subsample_country_map!$A:$A,0)),INDEX(lookup!$AB:$AB,MATCH($A64,lookup!$A:$A,0))) -> 1_developed | AM64: =IF(AND($CF64<>"",IFERROR(INDEX(subsample_country_map!$D:$D,MATCH($CF64,subsample_country_map!$A:$A,0)),"")<>""),INDEX(subsample_country_map!$D:$D,MATCH($CF64,subsample_country_map!$A:$A,0)),INDEX(lookup!$AC:$AC,MATCH($A64,lookup!$A:$A,0))) -> 1_western | AN64: =IF(AND($CF64<>"",IFERROR(INDEX(subsample_country_map!$E:$E,MATCH($CF64,subsample_country_map!$A:$A,0)),"")<>""),INDEX(subsample_country_map!$E:$E,MATCH($CF64,subsample_country_map!$A:$A,0)),INDEX(lookup!$AD:$AD,MATCH($A64,lookup!$A:$A,0))) -> 1_common law | AO64: =INDEX(lookup!$Y:$Y,MATCH($A64,lookup!$A:$A,0)) -> 0_published | AP64: =INDEX(lookup!$Z:$Z,MATCH($A64,lookup!$A:$A,0)) -> 1_VHB high | AQ64: =INDEX(lookup!$W:$W,MATCH($A64,lookup!$A:$A,0)) -> 2_sust | AS64: staging | AT64: good-CER | AU64: cost | AV64: -.590 | AW64: .125 | BA64: 2000 | BB64: 1 | BC64: other:PSM (regression on propensity-score-matched sample) | BD64: robust (unclustered) | BE64: none | BI64: Table 6 | BJ64: Model (2) PSM | BK64: 3426 | BL64: CC_ACTION -.590***(.125) | BM64: CC_ACTION | BN64: KD | BO64: update | BP64: Ali et al (2023) | BQ64: computed | BT64: 0 | BU64: staging_Ali_et_al_2023.csv | BW64: 2005 | BX64: 2020 | BY64: United States | BZ64: 2012.5 | CA64: 0.3125 | CB64: 0 | CC64: 1 | CD64: -0.10534744 | CE64: 1
